{"content": "Mẫu 1B HỒ SƠ YÊU CẦU GÓI THẦU MUA SẮM HÀNG HÓA (Ban hành kèm theo Thông tư số 80/2025/TT-BTC ngày 08 tháng 8 năm 2025 của Bộ trưởng Bộ Tài chính) HỒ SƠ YÊU CẦU MUA SẮM HÀNG HÓA [BẢNG: Không tiêu đề] [BẢNG: Không tiêu đề] TỪ NGỮ VIẾT TẮT [BẢNG: Không tiêu đề] Phần 1. THỦ TỤC CHỈ ĐỊNH THẦU Chương I. CHỈ DẪN NHÀ THẦU Mục 1. Phạm vi gói thầu 1. Chủ đầu tư ___[Ghi tên, địa chỉ Chủ đầu tư] mời nhà thầu nhận HSYC gói thầu___ [Ghi tên gói thầu theo kế hoạch lựa chọn nhà thầu được duyệt] thuộc__ [Ghi tên dự án/dự toán mua sắm]. 2. Nguồn vốn để thực hiện gói thầu: [Ghi rõ nguồn vốn đã được xác định hoặc phê duyệt; trường hợp sử dụng vốn ODA, vốn vay ưu đãi nước ngoài thì phải ghi rõ tên nhà tài trợ và cơ cấu nguồn vốn, bao gồm vốn tài trợ, vốn đối ứng trong nước]. 3. Thời gian thực hiện gói thầu là: ___ [Ghi thời gian cụ thể theo kế hoạch lựa chọn nhà thầu được duyệt], được tính từ ngày hợp đồng có hiệu lực đến ngày nghiệm thu hàng hóa (bao gồm cả dịch vụ liên quan (nếu có)), không bao gồm thời gian hoàn thành nghĩa vụ bảo hành. Mục 2. Hành vi bị cấm trong đấu thầu Hành vi bị cấm trong đấu thầu là hành vi quy định tại Điều 16 của Luật Đấu thầu. Mục 3. Tư cách hợp lệ của nhà thầu 1. Nhà thầu là tổ chức có tư cách hợp lệ khi đáp ứng quy định tại các điểm a, b, c, d, e và g Khoản 1 Điều 5 của Luật Đấu thầu. 2. Nhà thầu là hộ kinh doanh có tư cách hợp lệ khi đáp ứng quy định tại các điểm a, b Khoản 2 và các điểm d, e Khoản 1 Điều 5 của Luật Đấu thầu. 3. Nhà thầu là cá nhân, nhóm cá nhân chào thầu sản phẩm đổi mới sáng tạo của mình có tư cách hợp lệ khi đáp ứng quy định tại Khoản 3 Điều 5 của Luật Đấu thầu. Trường hợp pháp luật có liên quan quy định nhà thầu dự thầu, thực hiện hợp đồng phải độc lập với các tổ chức, cá nhân khác thì phải tuân thủ quy định đó. Mục 4. Làm rõ, sửa đổi HSYC 1. Trường hợp nhà thầu cần làm rõ HSYC, nhà thầu gửi văn bản đến Chủ đầu tư trong thời hạn tối thiểu 03 ngày làm việc trước ngày có thời điểm đóng thầu để đánh giá, xử lý. 2. Trường hợp Chủ đầu tư sửa đổi HSYC, Chủ đầu tư có trách nhiệm gửi quyết định sửa đổi và các nội dung sửa đổi tới nhà thầu. Thời gian gửi văn bản sửa đổi HSYC đến nhà thầu là ___ [Ghi số ngày cụ thể, tối thiểu 03 ngày làm việc trước ngày có thời điểm đóng thầu và bảo đảm đủ thời gian để nhà thầu hoàn chỉnh HSĐX]; trường hợp không bảo đảm đủ thời gian như nêu trên thì phải gia hạn thời điểm đóng thầu. Mục 5. Chi phí, đồng tiền, ngôn ngữ khi dự thầu 1. Nhà thầu phải chịu mọi chi phí liên quan đến quá trình dự thầu. 2. Đồng tiền dự thầu và đồng tiền thanh toán là VND. 3. HSĐX cũng như tất cả văn bản và hồ sơ liên quan đến HSĐX được viết bằng tiếng Việt. Các hồ sơ bổ trợ trong HSĐX có thể được viết bằng ngôn ngữ khác, đồng thời kèm theo bản dịch sang tiếng Việt. Trường hợp thiếu bản dịch, Chủ đầu tư có thể yêu cầu nhà thầu gửi bổ sung (nếu cần thiết). Mục 6. Thành phần của HSĐX HSĐX do nhà thầu chuẩn bị phải bao gồm: 1. Đơn dự thầu theo Mẫu 01A hoặc Mẫu 01B Chương III; 2. Thỏa thuận liên danh nếu là nhà thầu liên danh theo Mẫu 03 Chương III; 3. hồ sơ chứng minh tư cách hợp lệ, năng lực và kinh nghiệm của nhà thầu, của người ký đơn dự thầu; 4. hồ sơ chứng minh sự phù hợp của hàng hóa và dịch vụ liên quan theo quy định tại Mục 8 Chương này; 5. Đề xuất về giá theo các bảng giá thầu quy định tại Mẫu 4. 1 (4. 1A hoặc 4. 1B hoặc 4. 1C) hoặc Mẫu 4. 2 (4. 2A hoặc 4. 2B hoặc 4. 2C) Chương III; 6. Các nội dung khác ___ [Nêu các nội dung khác tùy theo tính chất, yêu cầu của gói thầu]. Mục 7. giá thầu 1. giá thầu là giá do nhà thầu chào trong đơn dự thầu bao gồm toàn bộ các chi phí (chưa tính giảm giá) để thực hiện gói thầu theo yêu cầu của HSYC, kể cả các loại thuế, phí, lệ phí (nếu có) áp theo thuế suất, mức phí, lệ phí tại thời điểm 28 ngày trước ngày có thời điểm đóng thầu. 2. Nhà thầu chào giá: [Chủ đầu tư quy định theo Mẫu 4. 1A hoặc 4. 1B hoặc 4. 1C hoặc 4. 2A hoặc 4. 2B hoặc 4. 2C Chương III] 3. Nhà thầu phải nộp HSĐX cho toàn bộ công việc được mô tả tại Chương IV và chào giá cho tất cả các công việc nêu trong bảng giá tương ứng quy định tại Chương III. Mục 8. hồ sơ chứng minh sự phù hợp của hàng hóa, dịch vụ liên quan 1. Yêu cầu về hồ sơ để chứng minh năng lực thực hiện hợp đồng của nhà thầu: ___ [Chủ đầu tư ghi “Không yêu cầu giấy phép bán hàng, giấy ủy quyền bán hàng của nhà sản xuất hoặc của đại lý phân phối hoặc giấy chứng nhận quan hệ đối tác hoặc giấy cam kết hỗ trợ kỹ thuật, bảo hành của nhà sản xuất hoặc của đại lý phân phối hoặc hồ sơ khác có giá trị tương đương” hoặc “Có yêu cầu giấy phép bán hàng, giấy ủy quyền bán hàng của nhà sản xuất hoặc của đại lý phân phối hoặc giấy chứng nhận quan hệ đối tác hoặc giấy cam kết hỗ trợ kỹ thuật, bảo hành của nhà sản xuất hoặc của đại lý phân phối hoặc hồ sơ khác có giá trị tương đương (sau đây gọi là Giấy phép bán hàng)” căn cứ vào tính chất của hàng hóa như sau: Đối với hàng hóa thông thường, thông dụng, sẵn có trên thị trường, đã được tiêu chuẩn hóa và được bảo hành theo quy định của nhà sản xuất thì không yêu cầu nhà thầu phải nộp giấy phép bán hàng, giấy ủy quyền bán hàng của nhà sản xuất hoặc của đại lý phân phối hoặc giấy chứng nhận quan hệ đối tác hoặc giấy cam kết hỗ trợ kỹ thuật, bảo hành của nhà sản xuất hoặc của đại lý phân phối hoặc hồ sơ khác có giá trị tương đương. Đối với hàng hóa đặc thù, phức tạp cần sự khẳng định của nhà sản xuất, nhà cung cấp để đảm bảo tính khả thi trong việc cung cấp hàng hóa khi nhà thầu trúng thầu và cần gắn với trách nhiệm của nhà sản xuất trong việc cung cấp các dịch vụ sau bán hàng như lắp đặt, bảo trì, đào tạo và các dịch vụ liên quan khác, trong HSYC có thể yêu cầu nhà thầu dự thầu phải cung cấp giấy phép bán hàng, giấy ủy quyền bán hàng của nhà sản xuất hoặc của đại lý phân phối hoặc giấy chứng nhận quan hệ đối tác hoặc giấy cam kết hỗ trợ kỹ thuật, bảo hành của nhà sản xuất hoặc của đại lý phân phối hoặc hồ sơ khác có giá trị tương đương. Trường hợp có yêu cầu về giấy phép bán hàng, giấy ủy quyền bán hàng của nhà sản xuất hoặc của đại lý phân phối hoặc giấy chứng nhận quan hệ đối tác hoặc giấy cam kết hỗ trợ kỹ thuật, bảo hành của nhà sản xuất hoặc của đại lý phân phối hoặc hồ sơ khác có giá trị tương đương, Chủ đầu tư quy định nội dung sau: “Trường hợp nhà thầu không tự sản xuất hoặc chế tạo hàng hóa được chào trong HSĐX của mình thì nhà thầu phải nộp giấy phép bán hàng, giấy ủy quyền bán hàng của nhà sản xuất hoặc của đại lý phân phối hoặc giấy chứng nhận quan hệ đối tác hoặc giấy cam kết hỗ trợ kỹ thuật, bảo hành của nhà sản xuất hoặc của đại lý phân phối hoặc hồ sơ khác có giá trị tương đương nhằm chứng minh nhà thầu được ủy quyền hợp lệ của nhà sản xuất, đại lý phân phối để cung cấp hàng hóa đó ở Việt Nam. Nhà thầu có thể đính kèm hoặc không đính kèm hồ sơ này trong HSĐX, kể cả trường hợp HSYC có yêu cầu nhà thầu phải có hồ sơ này. Việc nhà thầu không đính kèm hồ sơ nêu trên không phải là lý do loại bỏ nhà thầu. Nhà thầu vẫn được tiếp tục đánh giá, đánh giá để được xét thầu trúng thầu. Trường hợp nhà thầu trúng thầu, nhà thầu phải xuất trình được hồ sơ nêu trên trước khi ký hợp đồng và chịu trách nhiệm về tính chính xác của những hồ sơ, thông tin do mình cung cấp. Trường hợp nhà thầu không xuất trình được giấy phép bán hàng, giấy ủy quyền bán hàng của nhà sản xuất hoặc của đại lý phân phối hoặc giấy chứng nhận quan hệ đối tác hoặc giấy cam kết hỗ trợ kỹ thuật, bảo hành của nhà sản xuất hoặc của đại lý phân phối hoặc hồ sơ khác có giá trị tương đương để ký hợp đồng thì nhà thầu đó không được đánh giá chỉ định thầu. Trường hợp nhà thầu đã được xét thầu trúng thầu nhưng nhà sản xuất, đại lý, nhà phân phối không cung cấp Giấy phép bán hàng mà không có lý do chính đáng và nếu nhà thầu vẫn chứng minh được khả năng bảo hành, bảo trì, duy tu, bảo dưỡng, sửa chữa, cung cấp phụ tùng thay thế hoặc cung cấp các dịch vụ sau bán hàng khác thì vẫn được ký hợp đồng mà không cần xuất trình Giấy phép bán hàng”]. 2. Tất cả vật tư, thiết bị và dịch vụ liên quan được cung cấp theo hợp đồng phải có xuất xứ rõ ràng, hợp pháp. Nhà thầu phải tuân thủ theo ký mã hiệu (nếu có), nhãn hiệu, xuất xứ và hãng sản xuất của vật tư, thiết bị nêu trong HSYC. Để chứng minh tính hợp lệ của hàng hóa, dịch vụ liên quan, Chủ đầu tư có thể yêu cầu nhà thầu cung cấp bằng chứng về xuất xứ của các vật tư, thiết bị bao gồm các hồ sơ sau ___ [nêu yêu cầu về hồ sơ chứng minh tính hợp lệ của hàng hoá]. 3. Để chứng minh sự phù hợp của hàng hóa và dịch vụ liên quan so với yêu cầu của HSYC, nhà thầu phải cung cấp các hồ sơ là một phần của HSĐX chứng minh rằng hàng hóa đáp ứng thông số và tiêu chuẩn kỹ thuật quy định tại Chương IV. 4. hồ sơ chứng minh sự phù hợp của hàng hóa và dịch vụ liên quan có thể là hồ sơ, giấy tờ, bản vẽ, số liệu được mô tả chi tiết theo từng khoản mục về đặc tính kỹ thuật và tính năng sử dụng cơ bản của hàng hóa và dịch vụ liên quan, qua đó chứng minh sự đáp ứng cơ bản của hàng hóa và dịch vụ đối với thông số kỹ thuật và một bảng kê những điểm sai khác và ngoại lệ (nếu có) so với quy định tại Chương IV. 5. Nhà thầu phải cung cấp đầy đủ danh mục, giá cả, nhà cung cấp vật tư, phụ tùng thay thế, dụng cụ chuyên dùng, vật tư tiêu hao. .. (sau đây gọi là vật tư, phụ tùng thay thế) cần thiết để bảo đảm sự vận hành đúng quy cách và liên tục của hàng hóa trong thời hạn ___ [ghi thời hạn hoạt động dự kiến của hàng hóa] sau khi hàng hóa bắt đầu được đưa vào sử dụng. Mục 9. Hiệu lực của HSĐX 1. Thời gian có hiệu lực của HSĐX phải bảo đảm theo yêu cầu là ___ [Ghi rõ số ngày tuỳ thuộc quy mô, tính chất của gói thầu, bảo đảm thời gian có hiệu lực đến ngày ký kết hợp đồng] kể từ ngày có thời điểm đóng thầu. 2. Trong trường hợp cần thiết, trước khi hết thời hạn hiệu lực của HSĐX, Chủ đầu tư có thể đề nghị nhà thầu gia hạn hiệu lực của HSĐX. Việc đề nghị gia hạn và chấp thuận gia hạn phải được thể hiện bằng văn bản. Mục 10. Quy cách của HSĐX và chữ ký trong HSĐX 1. Nhà thầu phải chuẩn bị một bản gốc và ___bản chụp HSĐX [Ghi số lượng yêu cầu nhưng không quá 03 bản], ghi rõ \"bản gốc\" và \"bản chụp\" tương ứng. Nhà thầu cần ghi rõ tên gói thầu, tên nhà thầu, tên Chủ đầu tư bên ngoài túi đựng HSĐX. Nhà thầu phải chịu trách nhiệm về tính chính xác và phù hợp giữa bản chụp và bản gốc. Trường hợp có sự sai khác giữa bản gốc và bản chụp thì căn cứ vào bản gốc để đánh giá. 2. Tất cả các thành phần của HSĐX nêu tại Mục 6 Chương I phải được ký bởi người đại diện hợp pháp của nhà thầu. Trường hợp là nhà thầu liên danh thì HSĐX phải có chữ ký của đại diện hợp pháp của tất cả thành viên liên danh hoặc thành viên đại diện nhà thầu liên danh theo phân công trong thỏa thuận liên danh. 3. Những chữ được ghi thêm, ghi chèn vào giữa các dòng, những chữ bị tẩy xóa hoặc viết đè lên sẽ chỉ được coi là hợp lệ nếu có chữ ký ở bên cạnh hoặc tại trang đó của người ký đơn dự thầu. Mục 11. Thời điểm đóng thầu và mở thầu 1. HSĐX do nhà thầu nộp trực tiếp hoặc gửi đến địa chỉ của Chủ đầu tư [Ghi địa chỉ] nhưng phải bảo đảm Chủ đầu tư nhận được trước thời điểm đóng thầu: ___ giờ, ngày ___ tháng ___ năm ____ [Ghi thời điểm đóng thầu]. 2. Mở thầu: Chủ đầu tư tiến hành mở thầu bao gồm các nội dung sau: a) Kiểm tra niêm phong; b) Mở hồ sơ và đọc rõ các thông tin về tên nhà thầu: - Tham dự độc lập hay liên danh; - Số lượng bản gốc, bản chụp; - giá thầu chào trong đơn dự thầu; - Giá trị giảm giá (nếu có); - Thời gian có hiệu lực của HSĐX; - Thời gian thực hiện gói thầu; - Các thông tin khác liên quan. Biên bản mở thầu bao gồm các thông tin quy định tại điểm a và điểm b khoản này. Biên bản mở thầu phải được ký xác nhận bởi đại diện của Chủ đầu tư và nhà thầu nộp HSĐX. Biên bản này phải được gửi cho nhà thầu nộp HSĐX. Đại diện của Chủ đầu tư phải ký xác nhận vào bản gốc đơn dự thầu, thư giảm giá (nếu có), giấy ủy quyền của người đại diện theo pháp luật của nhà thầu (nếu có), thỏa thuận liên danh (nếu có), các nội dung đề xuất về tài chính và các nội dung quan trọng khác của từng HSĐX. Mục 12. thầu phụ 1. thầu phụ là tổ chức, cá nhân ký hợp đồng với nhà thầu để thực hiện các dịch vụ liên quan. Trường hợp nhà thầu cần sử dụng thầu phụ thì phải kê khai danh sách thầu phụ theo Mẫu 11B Chương III. Việc sử dụng thầu phụ sẽ không làm thay đổi các trách nhiệm của nhà thầu. Nhà thầu phải chịu trách nhiệm về khối lượng, chất lượng, tiến độ và các trách nhiệm khác đối với phần công việc do thầu phụ thực hiện. Năng lực và kinh nghiệm của thầu phụ sẽ không được đánh giá khi đánh giá HSĐX của nhà thầu. Bản thân nhà thầu phải đáp ứng các tiêu chí năng lực và kinh nghiệm (không xét đến năng lực và kinh nghiệm của thầu phụ). 2. Nhà thầu được sử dụng thầu phụ thực hiện các dịch vụ liên quan. Việc kê khai sử dụng thầu phụ thực hiện theo Mẫu 11B Chương IV. Mục 13. Đánh giá HSĐX và thương thảo về các đề xuất của nhà thầu 1. Việc đánh giá HSĐX được thực hiện theo quy định tại Chương II. 2. Trong quá trình đánh giá, Chủ đầu tư mời nhà thầu thương thảo về giá bảo đảm đáp ứng tỷ lệ tiết kiệm theo quy định của HSYC, thương thảo, làm rõ hoặc sửa đổi, bổ sung nội dung HSĐX để chứng minh việc đáp ứng yêu cầu về năng lực, kinh nghiệm, tiến độ, khối lượng, chất lượng, giải pháp kỹ thuật, biện pháp tổ chức thực hiện gói thầu và tỷ lệ tiết kiệm. Mục 14. Điều kiện đối với nhà thầu được đề nghị chỉ định thầu Nhà thầu được đề nghị chỉ định thầu khi đáp ứng đầy đủ các điều kiện sau đây: 1. Có HSĐX hợp lệ; 2. Có năng lực, kinh nghiệm và đề xuất kỹ thuật đáp ứng yêu cầu của HSYC; 3. Có giá đề nghị trúng thầu không vượt giá gói thầu được duyệt và đáp ứng tỷ lệ tiết kiệm tối thiểu__% giá gói thầu. [Căn cứ quy mô, tính chất, điều kiện cụ thể của gói thầu, Chủ đầu tư quy định trong HSYC mức tỷ lệ tiết kiệm của giá đề nghị trúng thầu để làm cơ sở cho nhà thầu chuẩn bị HSĐX] Mục 15. Thông báo kết quả lựa chọn nhà thầu Trong thời hạn 05 ngày làm việc kể từ ngày kết quả lựa chọn nhà thầu được phê duyệt, Chủ đầu tư đăng tải thông tin về kết quả lựa chọn nhà thầu lên Hệ thống mạng đấu thầu quốc gia; gửi văn bản thông báo kết quả lựa chọn nhà thầu cho nhà thầu dự thầu. Nội dung thông báo kết quả lựa chọn nhà thầu như sau: a) Thông tin về gói thầu: - Tên gói thầu; - Giá gói thầu hoặc dự toán được duyệt (nếu có); - Tên Chủ đầu tư; - Hình thức lựa chọn nhà thầu; - Loại hợp đồng; - Thời gian thực hiện gói thầu b) Thông tin về nhà thầu trúng thầu: - Tên nhà thầu; - Mã số thuế (nếu có); - giá thầu; - Giá trúng thầu; - Thời gian thực hiện gói thầu; - Thời gian thực hiện hợp đồng. c) Kế hoạch hoàn thiện, ký kết hợp đồng với nhà thầu trúng thầu. Mục 16. Điều kiện ký kết hợp đồng 1. Tại thời điểm ký kết, HSĐX của nhà thầu trúng thầu còn hiệu lực. 2. Tại thời điểm ký kết hợp đồng, nhà thầu trúng thầu phải bảo đảm đáp ứng yêu cầu về năng lực kỹ thuật, tài chính để thực hiện gói thầu theo yêu cầu của HSYC. Trường hợp thực tế nhà thầu không còn đáp ứng cơ bản yêu cầu về năng lực kỹ thuật, tài chính theo quy định nêu trong HSYC thì Chủ đầu tư sẽ từ chối ký kết hợp đồng với nhà thầu và hủy quyết định phê duyệt kết quả lựa chọn nhà thầu. 3. Chủ đầu tư phải bảo đảm các điều kiện về vốn tạm ứng, vốn thanh toán, mặt bằng thực hiện và điều kiện cần thiết khác để triển khai thực hiện gói thầu theo đúng tiến độ. Mục 17. Bảo đảm thực hiện hợp đồng 1. Trước hoặc cùng thời điểm hợp đồng có hiệu lực, nhà thầu được chỉ định thầu phải cung cấp bảo đảm thực hiện hợp đồng theo quy định của HSYC. Trường hợp nhà thầu sử dụng thư bảo lãnh thực hiện hợp đồng thì phải sử dụng Mẫu thư bảo lãnh trong HSYC này hoặc Mẫu thư bảo lãnh khác được Chủ đầu tư chấp thuận. 2. Nhà thầu không được hoàn trả bảo đảm thực hiện hợp đồng trong trường hợp sau đây: a) Từ chối thực hiện hợp đồng khi hợp đồng đã có hiệu lực; b) Vi phạm thỏa thuận trong hợp đồng; c) Thực hiện hợp đồng chậm tiến độ do lỗi của nhà thầu nhưng từ chối gia hạn hiệu lực của bảo đảm thực hiện hợp đồng. Mục 18. Giải quyết kiến nghị 1. Đối với gói thầu thuộc phạm vi điều chỉnh của Luật Đấu thầu: a) Khi thấy quyền và lợi ích hợp pháp bị ảnh hưởng, nhà thầu được kiến nghị người có thẩm quyền, Chủ đầu tư, Hội đồng giải quyết kiến nghị đánh giá lại các vấn đề trong quá trình lựa chọn nhà thầu, kết quả lựa chọn nhà thầu theo quy định tại Điều 89 Luật Đấu thầu và các Điều 137, 138 và 139 của Nghị định số 214/2025/NĐ-CP. b) Địa chỉ nhận đơn kiến nghị: - Địa chỉ nhận đơn kiến nghị của Chủ đầu tư: ___ [ghi đầy đủ tên, địa chỉ, số điện thoại, email]; - Địa chỉ nhận đơn kiến nghị của người có thẩm quyền: ___ [ghi đầy đủ tên, địa chỉ, số điện thoại, email]; - Địa chỉ bộ phận thường trực giúp việc của Hội đồng giải quyết kiến nghị: ___ [ghi đầy đủ tên, địa chỉ, số điện thoại, email]. 2. Đối với hoạt động lựa chọn nhà thầu quy định tại điểm d Khoản 7 Điều 3 của Luật Đấu thầu hoặc hoạt động lựa chọn nhà thầu không thuộc phạm vi điều chỉnh của Luật Đấu thầu: Khi thấy quyền và lợi ích hợp pháp bị ảnh hưởng, nhà thầu, cơ quan, tổ chức được kiến nghị theo quy trình sau: ___ [ghi cụ thể quy trình, thủ tục của việc giải quyết kiến nghị của đơn vị, tổ chức đồng thời ghi rõ email, địa chỉ của cá nhân/tổ chức/đơn vị giải quyết kiến nghị]. Mục 19. Ưu đãi trong lựa chọn nhà thầu Ưu đãi: _____ [Chủ đầu tư ghi rõ đối tượng, điều kiện ưu đãi theo quy định tại Nghị quyết của Quốc hội hoặc văn bản quy phạm pháp luật (nếu có)]. Chương II. TIÊU CHUẨN ĐÁNH GIÁ HSĐX Mục 1. Đánh giá tính hợp lệ của HSĐX 1. 1. Kiểm tra HSĐX a) Kiểm tra số lượng bản gốc, bản chụp HSĐX; b) Kiểm tra các thành phần của HSĐX theo quy định tại Mục 6 Chương I; c) Kiểm tra sự thống nhất nội dung giữa bản gốc và bản chụp để phục vụ quá trình đánh giá chi tiết HSĐX. 1. 2. Đánh giá tính hợp lệ của HSĐX HSĐX của nhà thầu được đánh giá là hợp lệ khi đáp ứng đầy đủ các nội dung sau đây: a) Có bản gốc HSĐX; b) Có đơn dự thầu được đại diện hợp pháp của nhà thầu ký tên, đóng dấu (nếu có) theo yêu cầu của HSYC; thời gian ký đơn dự thầu phải sau thời điểm phát hành HSYC; không đề xuất các giá thầu khác nhau hoặc có kèm theo điều kiện gây bất lợi cho Chủ đầu tư. Đối với nhà thầu liên danh, đơn dự thầu phải do đại diện hợp pháp của từng thành viên liên danh ký tên, đóng dấu (nếu có) hoặc thành viên được phân công thay mặt liên danh ký đơn dự thầu theo phân công trách nhiệm trong thỏa thuận liên danh; c) Hiệu lực của HSĐX đáp ứng yêu cầu theo quy định tại Mục 9 Chương I; d) Có thỏa thuận liên danh (trong trường hợp liên danh) được đại diện hợp pháp của từng thành viên liên danh ký tên, đóng dấu (nếu có); thỏa thuận liên danh phải nêu rõ nội dung công việc cụ thể và ước tính giá trị tương ứng mà từng thành viên trong liên danh sẽ thực hiện. Việc phân chia công việc trong liên danh phải căn cứ các hạng mục nêu trong bảng giá thầu tại Mẫu 4. 1 (4. 1A hoặc 4. 1B hoặc 4. 1C) hoặc Mẫu 4. 2 (4. 2A hoặc 4. 2B hoặc 4. 2C) Chương III hoặc theo các công việc thuộc quá trình sản xuất hạng mục trong bảng giá thầu, không được phân chia các công việc không thuộc các hạng mục này hoặc không thuộc quá trình sản xuất các hạng mục này; đ) Nhà thầu bảo đảm tư cách hợp lệ theo quy định tại Mục 3 Chương I. e) Trong thời hạn 03 năm trước thời điểm đóng thầu, nhà thầu không có nhân sự (ký kết hợp đồng lao động với nhà thầu tại thời điểm nhân sự thực hiện hành vi vi phạm) bị Tòa án kết án có hành vi vi phạm quy định về đấu thầu gây hậu quả nghiêm trọng theo quy định của pháp luật về hình sự nhằm mục đích cho nhà thầu đó trúng thầu. Nhà thầu có HSĐX hợp lệ được đánh giá, đánh giá trong bước tiếp theo. Mục 2. Tiêu chuẩn đánh giá về năng lực, kinh nghiệm Nhà thầu được đánh giá là đạt về năng lực và kinh nghiệm khi đáp ứng tiêu chuẩn đánh giá quy định tại Mục 2. 1, 2. 2 và 2. 3. Năng lực và kinh nghiệm của thầu phụ sẽ không được đánh giá khi đánh giá HSĐX của nhà thầu. Bản thân nhà thầu phải đáp ứng các tiêu chí đánh giá về năng lực và kinh nghiệm. 2. 1. Tiêu chuẩn đánh giá về năng lực và kinh nghiệm Tiêu chuẩn đánh giá năng lực và kinh nghiệm thực hiện theo Bảng số 01 (đối với nhà thầu không phải là nhà sản xuất ra hàng hóa thuộc phạm vi của gói thầu) hoặc Bảng số 02 (đối với nhà thầu là nhà sản xuất ra hàng hóa thuộc phạm vi của gói thầu), nhà thầu được đánh giá là đạt về năng lực và kinh nghiệm khi đáp ứng tất cả các tiêu chuẩn đánh giá. Năng lực và kinh nghiệm của thầu phụ sẽ không được đánh giá khi đánh giá HSĐX của nhà thầu. Bản thân nhà thầu phải đáp ứng các tiêu chí đánh giá về năng lực và kinh nghiệm. Việc xác định mức độ yêu cầu cụ thể đối với từng tiêu chuẩn quy định tại Mục này căn cứ theo yêu cầu của từng gói thầu cụ thể. Nhà thầu được đánh giá đạt tất cả nội dung quy định tại Bảng số 01 (đối với nhà thầu không phải là nhà sản xuất ra hàng hóa thuộc phạm vi của gói thầu) hoặc Bảng số 02 (đối với nhà thầu là nhà sản xuất ra hàng hóa thuộc phạm vi của gói thầu) thì đáp ứng yêu cầu về năng lực và kinh nghiệm. Trường hợp đồng tiền nêu trong các hợp đồng tương tự hoặc xác nhận thanh toán của Chủ đầu tư đối với những hợp đồng cung cấp hàng hóa đã thực hiện hoặc tờ khai nộp thuế hoặc các hồ sơ liên quan chứng minh năng lực, kinh nghiệm của nhà thầu không phải VND thì khi lập HSĐX, nhà thầu phải quy đổi về VND để làm cơ sở đánh giá HSĐX. Việc quy đổi được áp dụng tỷ giá quy đổi của___[ghi căn cứ xác định tỷ giá quy đổi, thông thường áp dụng tỷ giá bán ra của một ngân hàng thương mại hoạt động tại Việt Nam] tại ngày ký hợp đồng tương tự đó. Trường hợp nhà thầu dự thầu là công ty mẹ (ví dụ như Tổng công ty) có huy động công ty con, công ty thành viên thực hiện một phần công việc của gói thầu thì nhà thầu phải kê khai cụ thể phần công việc dành cho các công ty con, công ty thành viên theo Mẫu 11A Chương III. Việc đánh giá kinh nghiệm thực hiện hợp đồng tương tự căn cứ vào giá trị, khối lượng công việc do công ty mẹ, công ty con, công ty thành viên đảm nhiệm trong gói thầu. Bảng số 01 BẢNG TIÊU CHUẨN ĐÁNH GIÁ VỀ NĂNG LỰC VÀ KINH NGHIỆM (Đối với nhà thầu không phải là nhà sản xuất(1) ra hàng hóa thuộc phạm vi của gói thầu) [BẢNG: Không tiêu đề] Ghi chú: (1) Nhà sản xuất được hiểu là doanh nghiệp/cơ sở sản xuất tự sản xuất ra hàng hóa hoặc tham gia vào quá trình sản xuất ra hàng hóa hoặc công ty con, công ty mẹ phụ trách việc phân phối, tiêu thụ sản phẩm do công ty mẹ, công ty con khác trong Tập đoàn, Tổng công ty sản xuất. (2) Ghi thời gian yêu cầu, thông thường là 03 năm trước năm có thời điểm đóng thầu. Ví dụ: từ ngày 01 tháng 01 năm 2022 đến thời điểm đóng thầu. (3) Hợp đồng cung cấp hàng hóa, EPC, EP, PC, chìa khóa trao tay không hoàn thành do lỗi của nhà thầu bao gồm: - Hợp đồng cung cấp hàng hóa, EPC, EP, PC, chìa khóa trao tay bị Chủ đầu tư kết luận nhà thầu không hoàn thành và nhà thầu không phản đối; - Hợp đồng cung cấp hàng hóa, EPC, EP, PC, chìa khóa trao tay bị Chủ đầu tư kết luận nhà thầu không hoàn thành, không được nhà thầu chấp thuận nhưng đã được trọng tài hoặc tòa án kết luận theo hướng bất lợi cho nhà thầu. Các hợp đồng cung cấp hàng hóa, EPC, EP, PC, chìa khóa trao tay không hoàn thành không bao gồm các hợp đồng mà quyết định của Chủ đầu tư đã bị bác bỏ bằng cơ chế giải quyết tranh chấp. Việc xác định hợp đồng không hoàn thành phải dựa trên tất cả những thông tin về tranh chấp hoặc kiện tụng được giải quyết theo quy định của cơ chế giải quyết tranh chấp của hợp đồng tương ứng và khi mà nhà thầu đã hết tất cả các cơ hội có thể khiếu nại. Đối với các hợp đồng chậm tiến độ do lỗi của nhà thầu nhưng vẫn hoàn thành hợp đồng thì không được coi là hợp đồng không hoàn thành. Đối với nhà thầu liên danh mà chỉ có một hoặc một số thành viên trong liên danh vi phạm và bị cấm tham gia hoạt động đấu thầu theo quy định tại Khoản 1 Điều 133 của Nghị định số 214/2025/NĐ-CP thì thành viên liên danh còn lại không bị coi là không hoàn thành hợp đồng do lỗi của nhà thầu. Trường hợp một hoặc một số thành viên liên danh vi phạm hợp đồng, không còn năng lực để tiếp tục thực hiện hợp đồng, làm ảnh hưởng nghiêm trọng đến tiến độ, chất lượng, hiệu quả của gói thầu thì chỉ một hoặc một số thành viên liên danh vi phạm hợp đồng bị coi là không hoàn thành hợp đồng, thành viên còn lại không bị coi là không hoàn thành hợp đồng do lỗi của nhà thầu. (4) Nhà thầu cung cấp hồ sơ chứng minh đã thực hiện nghĩa vụ kê khai thuế và nộp thuế thu nhập doanh nghiệp (thuế thu nhập cá nhân đối với nhà thầu là hộ kinh doanh) của năm tài chính gần nhất so với thời điểm đóng thầu. Nghĩa vụ kê khai thuế và nộp thuế phải được thực hiện trước thời điểm đóng thầu. Nghĩa vụ nộp thuế là nộp thuế với giá trị thuế tương ứng với thuế suất, thu nhập chịu thuế, doanh thu tính thuế nhà thầu kê khai trên Hệ thống thuế điện tử (số thuế đã nộp tương ứng với số thuế phải nộp); trường hợp được chậm nộp thuế, miễn thuế, giảm thuế theo chính sách của Nhà nước thì thực hiện theo quy định này. Nhà thầu nộp các hồ sơ như sau: - Tờ khai thuế (hoặc thông báo nộp tiền của cơ quan thuế đối với hộ kinh doanh) và Giấy nộp tiền có xác nhận của cơ quan thuế được in từ Hệ thống thuế điện tử hoặc - Tờ khai thuế (hoặc thông báo nộp tiền của cơ quan thuế đối với hộ kinh doanh) và xác nhận của cơ quan thuế về việc thực hiện nghĩa vụ thuế. Trường hợp thời điểm đóng thầu sau ngày kết thúc năm tài chính của nhà thầu (năm Y) và trước hoặc trong ngày cuối cùng của tháng thứ 3 tính từ ngày kết thúc năm Y, yêu cầu đã thực hiện nghĩa vụ kê khai thuế và nộp thuế áp dụng đối với năm tài chính trước năm Y (năm Y-1). (Ví dụ: Ngày có thời điểm đóng thầu là ngày 20/3/2024, năm tài chính của nhà thầu là 01/01 - 31/12 thì nhà thầu phải chứng minh đã thực hiện nghĩa vụ kê khai thuế và nộp thuế của năm 2022). (5) Việc xác định giá trị tài sản ròng được thực hiện trên cơ sở báo cáo tài chính của nhà thầu. Trường hợp thời điểm đóng thầu sau ngày kết thúc năm tài chính của nhà thầu (năm Y) và trước hoặc trong ngày cuối cùng của tháng thứ 3 tính từ ngày kết thúc năm Y, việc xác định giá trị tài sản ròng của nhà thầu được thực hiện trên cơ sở báo cáo tài chính năm trước của năm Y (năm Y-1). Ví dụ: Ngày có thời điểm đóng thầu là ngày 20/3/2024, năm tài chính của nhà thầu là 01/01 - 31/12 và HSYC yêu cầu nhà thầu nộp báo cáo tài chính của 03 năm gần nhất thì việc xác định giá trị tài sản ròng của nhà thầu được thực hiện trên cơ sở bảo cáo tài chính năm 2022. Đối với nhà thầu là hộ kinh doanh thì không đánh giá tiêu chí này. (6) Ghi thời gian yêu cầu, thông thường từ 03 năm đến 05 năm trước năm có thời điểm đóng thầu. Trường hợp nhà thầu có số năm thành lập ít hơn số năm theo yêu cầu của HSYC thì doanh thu bình quân hằng năm (không bao gồm thuế VAT) được tính trên số năm mà nhà thầu thành lập. Trường hợp doanh thu bình quân hằng năm (không bao gồm thuế VAT) của nhà thầu đáp ứng yêu cầu về giá trị của HSYC thì nhà thầu vẫn được đánh giá tiếp mà không bị loại. Đối với nhà thầu là hộ kinh doanh, không bắt buộc phải nộp báo cáo tài chính nhưng nhà thầu phải cung cấp hồ sơ chứng minh doanh thu tương ứng với nghĩa vụ thuế. Trường hợp thời điểm đóng thầu sau ngày kết thúc năm tài chính của nhà thầu (năm Y) và trước hoặc trong ngày cuối cùng của tháng thứ 3 tính từ ngày kết thúc năm Y, yêu cầu về nộp báo cáo tài chính áp dụng đối với các năm trước của năm Y (năm Y-1, Y-2. ..). Ví dụ 1: Ngày có thời điểm đóng thầu là ngày 20/3/2024, năm tài chính của nhà thầu là 01/01 - 31/12 và HSYC yêu cầu nhà thầu nộp báo cáo tài chính của 03 năm gần nhất thì nhà thầu phải nộp báo cáo tài chính của các năm 2020, 2021, 2022). Ví dụ 2: Doanh thu bình quân hằng năm (không bao gồm thuế VAT) của 3 năm tài chính gần nhất so với thời điểm đóng thầu. Trong trường hợp này, nếu thời điểm đóng thầu là ngày 15/11/2024 thì nhà thầu phải nộp báo cáo tài chính của các năm 2021, 2022, 2023. Nhà thầu được thành lập vào năm 2022 nhưng doanh thu trung bình của năm 2022 và năm 2023 đáp ứng yêu cầu thì nhà thầu được tiếp tục đánh giá. (7) Cách tính toán thông thường về mức yêu cầu doanh thu bình quân hằng năm (không bao gồm thuế VAT): a) Trường hợp thời gian thực hiện gói thầu từ 12 tháng trở lên thì cách tính doanh thu như sau: Yêu cầu tối thiểu về mức doanh thu bình quân hằng năm (không bao gồm thuế VAT) = [(Giá gói thầu - giá trị thuế VAT)/thời gian thực hiện gói thầu theo năm] x k. Thông thường yêu cầu hệ số “k” trong công thức này là từ 1, 5 đến 2. b) Trường hợp thời gian thực hiện gói thầu dưới 12 tháng thì cách tính doanh thu như sau: Yêu cầu tối thiểu về mức doanh thu bình quân hằng năm (không bao gồm thuế VAT) = (Giá gói thầu - giá trị thuế VAT) x k. Thông thường yêu cầu hệ số “k” trong công thức này là 1, 5. (8) Đối với các hợp đồng mà nhà thầu đã tham gia với tư cách là thành viên liên danh hoặc thầu phụ thì chỉ tính giá trị phần việc do nhà thầu thực hiện. (9) Ghi thời gian yêu cầu, thông thường là từ 03 năm đến 05 năm trước năm có thời điểm đóng thầu. Ví dụ: từ ngày 01 tháng 01 năm 2019 đến thời điểm đóng thầu. (10) Tương tự về tính chất: Chủ đầu tư lựa chọn một trong hai cách thức để quy định trong HSYC như sau: a) Cách 1: là hàng hóa thuộc cùng lĩnh vực tổng quát (Chủ đầu tư nêu lĩnh vực tổng quát, ví dụ thiết bị y tế, thiết bị điện, thiết bị văn phòng. ..) hoặc b) Cách 2: HSYC quy định theo 2 tiêu chí (i) Tiêu chí 1: là hàng hóa thuộc cùng lĩnh vực tổng quát (Chủ đầu tư nêu lĩnh vực tổng quát, ví dụ thiết bị y tế, thiết bị điện, thiết bị văn phòng. ..) (ii) Tiêu chí 2: là hàng hóa có cùng mã Chương, mã Nhóm (tương ứng với 4 số đầu tiên của bộ mã) trong Hệ thống hài hòa mô tả và mã hóa hàng hóa (HS - Harmonized Commodity Description and Coding System) theo Hệ thống phân loại hàng hóa do Tổ chức Hải quan thế giới WCO phát hành (gọi chung là mã HS). Mã HS căn cứ theo Thông tư số 31/2022/TT-BTC ngày 08 tháng 6 năm 2022 của Bộ Tài chính (được Tổng Cục Hải quan đăng tải trên trang thông tin điện tử: https: //www. customs. gov. vn). Nhà thầu cung cấp hàng hóa thuộc cùng lĩnh vực tổng quát do HSYC yêu cầu (Tiêu chí 1) hoặc cùng 4 số đầu tiên mã HS (Tiêu chí 2) đều được coi là có tính chất tương tự với hàng hóa thuộc gói thầu. Trường hợp một hạng mục hàng hóa có nhiều mã HS khác nhau, HSYC quy định các mã HS này, nhà thầu có hàng hóa đáp ứng một trong các mã HS này được coi là đáp ứng yêu cầu của HSYC. Ví dụ: hàng hóa thuộc gói thầu là máy tính xách tay có mã HS là 84. 71. 30. 20 thì các hàng hóa có mã HS là 84. 71. xx. xx được coi là có tính chất tương tự. Trường hợp hàng hóa thuộc gói thầu chưa được công bố mã HS, nhà thầu phải kê khai các hợp đồng cung cấp hàng hóa có cùng lĩnh vực tổng quát theo yêu cầu của HSYC (Tiêu chí 1). - Đối với gói thầu mua trang thiết bị y tế, mã HS được xác định theo Thông tư số 14/2018/TT-BYT ngày 15 tháng 5 năm 2018 của Bộ Y tế, hàng hóa tương tự theo mã HS (xác định theo tiêu chí 2) là trang thiết bị y tế cùng nhóm hàng hóa (tương ứng với 4 số đầu tiên của bộ mã) quy định tại Thông tư số 14/2018/TT-BYT. Trong quá trình thực hiện, trường hợp Thông tư số 31/2022/TT-BTC, Thông tư số 14/2018/TT-BYT được sửa đổi, bổ sung hoặc thay thế thì áp dụng theo văn bản quy phạm pháp luật sửa đổi, bổ sung hoặc thay thế Thông tư số 31/2022/TT-BTC, Thông tư số 14/2018/TT-BYT). - Trường hợp Chủ đầu tư, tổ chuyên gia khó khăn trong việc xác định mã HS của hàng hóa theo Tiêu chí 2, HSYC được đưa ra quy định tương tự về lĩnh vực tổng quát (theo Tiêu chí 1). Trong trường hợp này, nếu nhà thầu xác định được mã HS của hàng hóa theo yêu cầu của gói thầu và mã HS của hàng hóa trong hạng mục, hợp đồng đã thực hiện (nghiệm thu) cùng nhóm (tương ứng với 4 số đầu tiên của bộ mã) thì hạng mục, hợp đồng này được coi là tương tự để đánh giá, đánh giá (được coi như nhà thầu đáp ứng Tiêu chí 2). - Trường hợp gói thầu có nhiều hạng mục thì có thể chỉ quy định lĩnh vực tổng quát, mã HS cho các hạng mục chính của gói thầu. (11) Quy mô của hợp đồng tương tự: Trường hợp gói thầu có nhiều hạng mục hàng hóa thì phải ghi giá trị tương ứng của từng hạng mục hàng hóa để làm cơ sở đánh giá kinh nghiệm thực hiện hợp đồng cung cấp hàng hóa tương tự của nhà thầu. Trường hợp gói thầu bao gồm nhiều loại hàng hóa khác nhau thì tùy theo tính chất, quy mô gói thầu để Chủ đầu tư, tổ chuyên gia đưa ra yêu cầu về quy mô tương tự trên cơ sở các loại hàng hóa chính của gói thầu (phải nêu rõ các hàng hóa chính) hoặc yêu cầu về quy mô tương tự trên cơ sở tất cả các loại hàng hóa của gói thầu, trong đó ghi quy mô yêu cầu đối với mỗi hạng mục hàng hóa chính hoặc mỗi hạng mục hàng hóa. Trường hợp mua sắm hàng hóa có số lượng, khối lượng mời thầu lớn thì có thể điều chỉnh giảm yêu cầu về quy mô của hợp đồng tương tự (Y) xuống còn Y/1, 25. Trong đó, Y thông thường khoảng 50% giá trị của gói thầu đang xét; riêng đối với trường hợp gói thầu có một số hạng mục hàng hóa có cùng mã Chương, mã Nhóm thì việc xác định quy mô hợp đồng tương tự được xác định theo điểm (iii) và điểm (iv) ghi chú này. Đối với gói thầu mua sắm hàng hóa có khối lượng, số lượng công việc căn cứ nhu cầu theo các năm và thời gian thực hiện gói thầu dài hơn 1 năm thì HSYC yêu cầu về giá trị của hợp đồng tương tự trong 01 chu kỳ (01 năm) mà không xác định yêu cầu theo tổng số năm. Ví dụ: gói thầu cung cấp vật tư X cho nhu cầu của Chủ đầu tư trong 02 năm 2024-2025 (từ 01/01/2024 đến 31/12/2025), giá gói thầu là 100. 000. 000. 000 VNĐ (tính cho nhu cầu trong 02 năm). Yêu cầu giá trị của hợp đồng tương tự là: 50% x 100. 000. 000. 000/2 =25. 000. 000. 000 VNĐ. Việc đánh giá về quy mô của hợp đồng tương tự căn cứ vào giá trị hoàn thành, được nghiệm thu như sau: (i) Có ít nhất 01 hợp đồng hoàn thành cung cấp đầy đủ các loại hàng hóa tương tự có giá trị đáp ứng tối thiểu là Y (hoặc Y/1, 25 nếu thuộc trường hợp mua sắm hàng hóa có số lượng, khối lượng mời thầu lớn), trong đó từng hạng mục tương tự trong hợp đồng không cần có giá trị đáp ứng 50% (hoặc 40% nếu thuộc trường hợp mua hàng hóa có số lượng, khối lượng mời thầu lớn) giá trị tương ứng của hạng mục đó trong gói thầu hoặc (ii) Có các hạng mục hàng hóa tương tự đã thực hiện trong các hợp đồng khác nhau (hợp đồng có thể đã hoàn thành hoặc đang thực hiện, chưa nghiệm thu, thanh lý) hoặc trong một hợp đồng (hợp đồng chưa hoàn thành) nhưng bảo đảm giá trị của từng hạng mục hàng hóa tương tự đã thực hiện đáp ứng tối thiểu 50% giá trị của từng hạng mục hàng hóa trong gói thầu đang xét (hoặc 40% nếu thuộc trường hợp mua sắm hàng hóa có số lượng, khối lượng mời thầu lớn), trong đó không được cộng gộp giá trị của hạng mục hàng hóa tương tự trong nhiều hợp đồng khác nhau để hình thành một hạng mục hàng hóa tương tự có giá trị lớn hơn 50% (hoặc 40% nếu thuộc trường hợp mua sắm hàng hóa có số lượng, khối lượng mời thầu lớn) giá trị của hạng mục hàng hóa gói thầu đang xét. Trong đó: + Hạng mục hàng hóa đã thực hiện là một phần hoặc toàn bộ khối lượng hàng hóa trong hạng mục đã được nghiệm thu trong khoảng thời gian quy định mà không xét đến thời gian ký kết hợp đồng. Thời điểm xác nhận hạng mục hàng hóa đã thực hiện để xác định hạng mục hàng hóa tương tự là thời điểm nghiệm thu hàng hóa, không căn cứ vào thời điểm ký kết hợp đồng. + Hợp đồng hoàn thành là hợp đồng có toàn bộ hàng hóa đã được nghiệm thu hoặc hợp đồng đã được thanh lý. Thời điểm xác nhận hợp đồng hoàn thành để xác định hợp đồng tương tự là thời điểm nghiệm thu hàng hóa, không căn cứ vào thời điểm ký kết hợp đồng. - Trường hợp nhà thầu vừa là nhà sản xuất, vừa là nhà cung cấp (một số hàng hóa hoặc một phần khối lượng hàng hóa do nhà thầu chào trong HSYC là do nhà thầu sản xuất, một số hàng hóa khác hoặc một phần khối lượng hàng hóa do nhà thầu mua từ nhà sản xuất, cung cấp khác để cung cấp cho gói thầu), thì ngoài kê khai về kinh nghiệm thực hiện hợp đồng tương tự, nhà thầu còn phải kê khai về năng lực sản xuất theo nội dung quy định tại Mục 4 Bảng số 02 Chương này. Việc đánh giá kinh nghiệm của nhà thầu sẽ được thực hiện trên cơ sở hợp đồng cung cấp hàng hóa tương tự (tương ứng với phần hàng hóa mà nhà thầu mua từ nhà sản xuất, cung cấp khác) và năng lực sản xuất của nhà thầu (tương ứng với phần hàng hóa mà nhà thầu tự sản xuất để cung cấp cho gói thầu). Trường hợp một số hạng mục hàng hóa trong gói thầu có cùng mã Chương, mã Nhóm (mã A) thì việc đánh giá về quy mô của hợp đồng tương tự căn cứ vào giá trị hoàn thành, được nghiệm thu như sau: (iii) Có ít nhất 01 hợp đồng hoàn thành cung cấp đầy đủ các loại hàng hóa tương tự có giá trị đáp ứng tối thiểu là K (hoặc K/1, 25 nếu thuộc trường hợp mua sắm hàng hóa có số lượng, khối lượng mời thầu lớn), trong đó K bằng 50% tổng giá trị các hạng mục không có cùng mã Chương, mã Nhóm (không có mã A) và giá trị cao nhất của các hạng mục có cùng chung mã A (giá trị hạng mục theo giá gói thầu, dự toán được duyệt) hoặc (iv) Có các hạng mục hàng hóa tương tự đã thực hiện trong các hợp đồng khác nhau (hợp đồng có thể đã hoàn thành hoặc đang thực hiện, chưa nghiệm thu, thanh lý) hoặc trong một hợp đồng (hợp đồng chưa hoàn thành) nhưng bảo đảm giá trị của từng hạng mục hàng hóa tương tự không có mã A đã thực hiện đáp ứng tối thiểu 50% giá trị của từng hạng mục hàng hóa trong gói thầu đang xét (hoặc 40% nếu thuộc trường hợp mua sắm hàng hóa có số lượng, khối lượng mời thầu lớn), đối với hạng mục hàng hóa tương tự có cùng mã A thì chỉ cần giá trị của hạng mục hàng hóa tương tự đã thực hiện đáp ứng tối thiểu 50% giá trị cao nhất của hạng mục hàng hóa cùng mã A trong gói thầu đang xét (hoặc 40% nếu thuộc trường hợp mua sắm hàng hóa có số lượng, khối lượng mời thầu lớn). Không được cộng gộp giá trị của hạng mục hàng hóa tương tự trong nhiều hợp đồng khác nhau để hình thành một hạng mục hàng hóa tương tự có giá trị lớn hơn 50% (hoặc 40% nếu thuộc trường hợp mua sắm hàng hóa có số lượng, khối lượng mời thầu lớn) giá trị của hạng mục hàng hóa gói thầu đang xét. * Ví dụ cho ghi chú số (10), (11): - Ví dụ 1: Gói thầu đang xét là gói thầu cung cấp 500. 000 cái bơm tiêm dùng một lần có mã HS 9018. 31. 10 (Theo quy định của Thông tư số 14/2018/TT-BYT) giá trị 1. 000. 000. 000 VNĐ và 100 chiếc đèn mổ treo trần có mã HS 9405. 10. 20 (Theo quy định của Thông tư số 14/2018/TT-BYT) giá trị 2. 000. 000. 000 VNĐ. Nhà thầu X có hợp đồng A (chưa hoàn thành, chưa được thanh lý) cung cấp 2 máy thở có mã HS 9018. 90. 30, trong đó đã bàn giao 1 chiếc (đã được nghiệm thu) với giá trị 900. 000. 000 VNĐ (> 50% giá trị hạng mục bơm tiêm dùng một lần) và có hợp đồng B (chưa hoàn thành, chưa được thanh lý) cung cấp 200 chiếc đèn phẫu thuật có mã HS 9405. 40. 91, trong đó đã bàn giao 80 chiếc (đã được nghiệm thu) với giá trị 1. 450. 000. 000 VNĐ (> 50% giá trị hạng mục đèn mổ treo trần) thì nhà thầu X được đánh giá là đáp ứng yêu cầu về hợp đồng tương tự của gói thầu này. - Ví dụ 2: Phạm vi cung cấp gói thầu là mua xe Ben tự đổ kèm theo 20 cái lốp xe dự phòng; giá gói thầu được phê duyệt là 1, 8 tỷ đồng (trong đó giá trị của xe Ben là 1, 64 tỷ đồng và 20 lốp dự phòng có giá trị 0, 16 tỷ đồng). Như vậy, trong trường hợp này thì hàng hóa chính của gói thầu là xe Ben tự đổ và quy mô của hợp đồng tương tự được xác định bằng 50% x 1, 64 tỷ đồng. - Ví dụ 3: Phạm vi cung cấp của gói thầu đang xét gồm 50 máy điều hòa (mã HS 8415; giá dự toán 2 tỷ đồng); 20 máy tính xách tay (mã HS 8507; giá dự toán 400 triệu đồng); 20 máy in Laser (mã HS 8443; giá dự toán 100 triệu đồng), giao hàng trong thời gian 180 ngày kể từ ngày hợp đồng có hiệu lực. Nhà thầu dự thầu là nhà thầu Liên danh A - B trong đó thành viên A là nhà sản xuất máy điều hòa đảm nhận phần công việc cung cấp máy điều hòa (80% giá trị công việc gói thầu), thành viên B là nhà thương mại đảm nhận phần công việc cung cấp máy tính xách tay và máy in của gói thầu (20% giá trị công việc gói thầu). Trong trường hợp này, nhà thầu Liên danh A - B được coi là đáp ứng yêu cầu về năng lực sản xuất và kinh nghiệm thực hiện hợp đồng nếu: + Thành viên A cung cấp được hồ sơ chứng minh công suất thiết kế của nhà máy, dây chuyền thiết bị sản xuất máy điều hòa đạt tối thiểu 12, 5 máy điều hòa/tháng (1, 5 x 50 máy x 30 /180 ngày) hoặc sản lượng sản xuất máy điều hòa của 01 tháng cao nhất trong vòng 05 năm gần nhất tính đến thời điểm đóng thầu bằng hoặc lớn hơn 12, 5 máy/tháng; + Thành viên B đã thực hiện cung cấp các mã hàng hóa 8507, 8443 trong cùng 01 hợp đồng hoặc ở 02 hợp đồng khác nhau nhưng bảo đảm giá trị mã hàng hóa 8507 trong 01 hợp đồng bằng hoặc lớn hơn 50% giá trị của hạng mục máy tính xách tay (tức là ≥50% x 400 triệu đồng), giá trị mã hàng hóa 8443 trong 01 hợp đồng bằng hoặc lớn hơn 50% giá trị của hạng mục máy in laser (tức là ≥ 50% x 100 triệu đồng). - Ví dụ 4: Phạm vi cung cấp gói thầu mua sắm hàng hóa Q như sau: [BẢNG: Không tiêu đề] Trong trường hợp này, nhà thầu A tham dự gói thầu mua sắm hàng hóa Q nêu trên được coi là đáp ứng yêu cầu về kinh nghiệm thực hiện hợp đồng cung cấp hàng hóa tương tự nếu: + Cung cấp 01 hợp đồng có đầy đủ các mã hàng hóa 9025 và 9030 và tổng giá trị của mã hàng hóa 9025, 9030 trong hợp đồng đã hoàn thành với giá trị tối thiểu là 11 tỷ đồng (50% x (10 tỷ đồng + 12 tỷ đồng)) hoặc + Cung cấp 01 hợp đồng trong đó đã thực hiện việc cung cấp mã hàng hóa 9025 với giá trị tối thiểu 5 tỷ đồng (50% x 10 tỷ đồng) và 01 hợp đồng đã thực hiện việc cung cấp mã hàng hóa 9030 với giá trị tối thiểu 6 tỷ đồng [50% x 12 tỷ đồng)]. ”. Trường hợp nhà thầu A cung cấp 02 hợp đồng có đầy đủ các mã hàng hóa 9025 và 9030, trong đó hợp đồng số 01: giá trị của mã 9025 là 3 tỷ đồng, giá trị của mã 9030 là 5 tỷ đồng và hợp đồng số 02: giá trị của mã 9025 là 3 tỷ đồng, giá trị của mã 9030 là 4 tỷ đồng thì được coi là không đáp ứng yêu cầu về kinh nghiệm thực hiện hợp đồng cung cấp hàng hóa tương tự. (12) Trường hợp không yêu cầu dịch vụ sau bán hàng thì gạch bỏ tiêu chí đánh giá này. Trường hợp nhà thầu thiếu cam kết thì được bổ sung trong quá trình đánh giá HSĐX. Trường hợp nhà thầu không bổ sung cam kết trong khoảng thời gian hợp lý theo yêu cầu của Chủ đầu tư thì HSĐX của nhà thầu được coi là không đáp ứng yêu cầu về khả năng bảo hành, bảo trì, duy tu, bảo dưỡng, sửa chữa, cung cấp phụ tùng thay thế hoặc cung cấp các dịch vụ sau bán hàng khác và bị loại. Bảng số 02 BẢNG TIÊU CHUẨN ĐÁNH GIÁ VỀ NĂNG LỰC VÀ KINH NGHIỆM (Đối với nhà thầu là nhà sản xuất(1) ra hàng hóa thuộc phạm vi của gói thầu) [BẢNG: Không tiêu đề] Ghi chú: (1) Nhà sản xuất được hiểu là doanh nghiệp/cơ sở sản xuất tự sản xuất ra hàng hóa hoặc tham gia vào quá trình sản xuất ra hàng hóa hoặc công ty con, công ty mẹ phụ trách việc phân phối, tiêu thụ sản phẩm do công ty mẹ, công ty con khác trong Tập đoàn, Tổng công ty sản xuất. (2) Ghi thời gian yêu cầu, thông thường là 03 năm trước năm có thời điểm đóng thầu. Ví dụ: từ ngày 01 tháng 01 năm 2022 đến thời điểm đóng thầu. (3) Hợp đồng cung cấp hàng hóa, EPC, EP, PC, chìa khóa trao tay không hoàn thành do lỗi của nhà thầu bao gồm: - Hợp đồng cung cấp hàng hóa, EPC, EP, PC, chìa khóa trao tay bị Chủ đầu tư kết luận nhà thầu không hoàn thành và nhà thầu không phản đối; - Hợp đồng cung cấp hàng hóa, EPC, EP, PC, chìa khóa trao tay bị Chủ đầu tư kết luận nhà thầu không hoàn thành, không được nhà thầu chấp thuận nhưng đã được trọng tài hoặc tòa án kết luận theo hướng bất lợi cho nhà thầu. Các hợp đồng cung cấp hàng hóa, EPC, EP, PC, chìa khóa trao tay không hoàn thành không bao gồm các hợp đồng mà quyết định của Chủ đầu tư đã bị bác bỏ bằng cơ chế giải quyết tranh chấp. Việc xác định hợp đồng không hoàn thành phải dựa trên tất cả những thông tin về tranh chấp hoặc kiện tụng được giải quyết theo quy định của cơ chế giải quyết tranh chấp của hợp đồng tương ứng và khi mà nhà thầu đã hết tất cả các cơ hội có thể khiếu nại. Đối với các hợp đồng chậm tiến độ do lỗi của nhà thầu nhưng vẫn hoàn thành hợp đồng thì không được coi là hợp đồng không hoàn thành. Đối với nhà thầu liên danh mà chỉ có một hoặc một số thành viên trong liên danh vi phạm và bị cấm tham gia hoạt động đấu thầu theo quy định tại Khoản 1 Điều 133 của Nghị định số 214/2025/NĐ-CP thì thành viên liên danh còn lại không bị coi là không hoàn thành hợp đồng do lỗi của nhà thầu. Trường hợp một hoặc một số thành viên liên danh vi phạm hợp đồng, không còn năng lực để tiếp tục thực hiện hợp đồng, làm ảnh hưởng nghiêm trọng đến tiến độ, chất lượng, hiệu quả của gói thầu thì chỉ một hoặc một số thành viên liên danh vi phạm hợp đồng bị coi là không hoàn thành hợp đồng, thành viên còn lại không bị coi là không hoàn thành hợp đồng do lỗi của nhà thầu. (4) Nhà thầu cung cấp hồ sơ chứng minh đã thực hiện nghĩa vụ kê khai thuế và nộp thuế thu nhập doanh nghiệp (thuế thu nhập cá nhân đối với nhà thầu là hộ kinh doanh) của năm tài chính gần nhất so với thời điểm đóng thầu. Nghĩa vụ kê khai thuế và nộp thuế phải được thực hiện trước thời điểm đóng thầu. Nghĩa vụ nộp thuế là nộp thuế với giá trị thuế tương ứng với thuế suất, thu nhập chịu thuế, doanh thu tính thuế nhà thầu kê khai trên Hệ thống thuế điện tử (số thuế đã nộp tương ứng với số thuế phải nộp); trường hợp được chậm nộp thuế, miễn thuế, giảm thuế theo chính sách của Nhà nước thì thực hiện theo quy định này. Nhà thầu nộp các hồ sơ như sau: - Tờ khai thuế (hoặc thông báo nộp tiền của cơ quan thuế đối với hộ kinh doanh) và Giấy nộp tiền có xác nhận của cơ quan thuế được in từ Hệ thống thuế điện tử hoặc - Tờ khai thuế (hoặc thông báo nộp tiền của cơ quan thuế đối với hộ kinh doanh) và xác nhận của cơ quan thuế về việc thực hiện nghĩa vụ thuế. Trường hợp thời điểm đóng thầu sau ngày kết thúc năm tài chính của nhà thầu (năm Y) và trước hoặc trong ngày cuối cùng của tháng thứ 3 tính từ ngày kết thúc năm Y, yêu cầu đã thực hiện nghĩa vụ kê khai thuế và nộp thuế áp dụng đối với năm tài chính trước năm Y (năm Y-1). (Ví dụ: Thời điểm đóng thầu là ngày 20/3/2024, năm tài chính của nhà thầu là 01/01 - 31/12 thì nhà thầu phải chứng minh đã thực hiện nghĩa vụ kê khai thuế và nộp thuế của năm 2022). (5) Khi chào thầu sản phẩm đổi mới sáng tạo, cá nhân, nhóm cá nhân sản xuất sản phẩm đổi mới sáng tạo quy định tại Khoản 4 Điều 6 của Nghị định số 214/2025/NĐ-CP không phải đáp ứng yêu cầu về năng lực tài chính, số năm hoạt động trong cùng ngành nghề trong thời hạn 06 năm kể từ khi sản phẩm lần đầu được sản xuất và đủ điều kiện để đưa ra thị trường. (6) Việc xác định giá trị tài sản ròng được thực hiện trên cơ sở báo cáo tài chính của nhà thầu. Trường hợp thời điểm đóng thầu sau ngày kết thúc năm tài chính của nhà thầu (năm Y) và trước hoặc trong ngày cuối cùng của tháng thứ 3 tính từ ngày kết thúc năm Y, việc xác định giá trị tài sản ròng của nhà thầu được thực hiện trên cơ sở báo cáo tài chính năm trước của năm Y (năm Y-1). Ví dụ: Thời điểm đóng thầu là ngày 20/3/2024, năm tài chính của nhà thầu là 01/01 - 31/12 và HSYC yêu cầu nhà thầu nộp báo cáo tài chính của 03 năm gần nhất thì việc xác định giá trị tài sản ròng của nhà thầu được thực hiện trên cơ sở bảo cáo tài chính năm 2022. Đối với nhà thầu là hộ kinh doanh thì không đánh giá tiêu chí này. (7) Đối với doanh nghiệp khởi nghiệp sáng tạo trong nước khi chào thầu sản phẩm đổi mới sáng tạo của doanh nghiệp đó theo quy định tại Khoản 4 Điều 6 của Nghị định số 214/2025/NĐ-CP không phải đáp ứng tiêu chí này trong thời hạn 06 năm kể từ khi sản phẩm lần đầu được sản xuất và đủ điều kiện để đưa ra thị trường. Nhà thầu trong nước thuộc trường hợp quy định tại điểm g Khoản 1 Điều 10 của Luật Đấu thầu khi chào thầu sản phẩm do nhà thầu đó sản xuất không phải đáp ứng tiêu chí này trong thời hạn 05 năm kể từ khi được cơ quan có thẩm quyền công nhận. Trường hợp sau khi đánh giá mà nhà thầu không đáp ứng về đối tượng được hưởng ưu đãi thì Chủ đầu tư yêu cầu nhà thầu cung cấp hồ sơ chứng minh đáp ứng yêu cầu về doanh thu. Đối với nhà thầu trong nước được chuyển giao kỹ thuật để sản xuất hàng hóa có xuất xứ Việt Nam phù hợp với HSYC không phải đáp ứng tiêu chí này trong thời hạn 05 năm kể từ khi sản phẩm lần đầu được sản xuất và đủ điều kiện để đưa ra thị trường. Căn cứ xác định nhà thầu trong nước được chuyển giao kỹ thuật, nhà thầu trong nước được chuyển giao kỹ thuật khuyến khích chuyển giao để sản xuất hàng hóa có xuất xứ Việt Nam là Giấy chứng nhận đăng ký chuyển giao kỹ thuật, Giấy chứng nhận chuyển giao kỹ thuật khuyến khích chuyển giao theo quy định của pháp luật về kỹ thuật, pháp luật về đầu tư. Đối với nhà thầu trong nước sản xuất hàng hóa có xuất xứ Việt Nam phù hợp với HSYC, không phải đáp ứng yêu cầu về doanh thu khi nhà thầu chào thầu hàng hóa mà chủng loại hàng hóa này lần đầu được nhà thầu sản xuất và đủ điều kiện để đưa ra thị trường trong thời gian 05 năm trước thời điểm đóng thầu nhưng không quá 07 năm tính đến thời điểm đóng thầu. (8) Ghi thời gian yêu cầu, thông thường từ 03 năm đến 05 năm trước năm có thời điểm đóng thầu. Trường hợp nhà thầu có số năm thành lập ít hơn số năm theo yêu cầu của HSYC thì doanh thu bình quân hằng năm (không bao gồm thuế VAT) được tính trên số năm mà nhà thầu thành lập. Trong trường hợp này, nếu doanh thu bình quân hằng năm (không bao gồm thuế VAT) của nhà thầu đáp ứng yêu cầu về giá trị của HSYC thì nhà thầu vẫn được đánh giá tiếp mà không bị loại. Trường hợp thời điểm đóng thầu sau ngày kết thúc năm tài chính của nhà thầu (năm Y) và trước hoặc trong ngày cuối cùng của tháng thứ 3 tính từ ngày kết thúc năm Y, yêu cầu về nộp báo cáo tài chính áp dụng đối với các năm trước của năm Y (năm Y-1, Y-2. ..). Ví dụ 1: Thời điểm đóng thầu là ngày 20/3/2024, năm tài chính của nhà thầu là 01/01 - 31/12 và HSYC yêu cầu nhà thầu nộp báo cáo tài chính của 03 năm gần nhất thì nhà thầu phải nộp báo cáo tài chính của các năm 2020, 2021, 2022. Ví dụ 2: Doanh thu bình quân hằng năm (không bao gồm thuế VAT) của 3 năm tài chính gần nhất so với thời điểm đóng thầu. Trong trường hợp này, nếu thời điểm đóng thầu là ngày 15/11/2024 thì nhà thầu phải nộp báo cáo tài chính của các năm 2021, 2022, 2023. Nhà thầu được thành lập vào năm 2022 nhưng doanh thu trung bình của năm 2022 và năm 2023 đáp ứng yêu cầu thì nhà thầu được tiếp tục đánh giá. Đối với nhà thầu là hộ kinh doanh, không bắt buộc phải nộp báo cáo tài chính nhưng nhà thầu phải cung cấp hồ sơ chứng minh doanh thu tương ứng với nghĩa vụ thuế. (9) Cách tính toán thông thường về mức yêu cầu doanh thu bình quân hằng năm (không bao gồm thuế VAT): a) Trường hợp thời gian thực hiện gói thầu từ 12 tháng trở lên thì cách tính doanh thu như sau: Yêu cầu tối thiểu về mức doanh thu bình quân hằng năm (không bao gồm thuế VAT) = [(Giá gói thầu - giá trị thuế VAT)/thời gian thực hiện gói thầu theo năm] x k. Thông thường yêu cầu hệ số “k” trong công thức này là từ 1, 5 đến 2. b) Trường hợp thời gian thực hiện gói thầu dưới 12 tháng thì cách tính doanh thu như sau: Yêu cầu tối thiểu về mức doanh thu bình quân hằng năm từ hoạt động sản xuất, kinh doanh (không bao gồm thuế VAT) = (Giá gói thầu - giá trị thuế VAT) x k. Thông thường yêu cầu hệ số “k” trong công thức này là 1, 5. (10) Trường hợp gói thầu bao gồm nhiều loại hàng hoá khác nhau thì tùy theo tính chất, quy mô gói thầu để Chủ đầu tư, tổ chuyên gia đưa ra yêu cầu về công suất thiết kế của nhà máy, dây chuyền sản xuất hoặc sản lượng sản xuất cao nhất của 01 tháng trong 05 năm hoặc sản lượng sản xuất cao nhất của 01 năm trong 05 năm gần nhất tính đến thời điểm đóng thầu trên cơ sở các loại hàng hoá chính của gói thầu (phải nêu rõ các hàng hóa chính) hoặc trên cơ sở tất cả các loại hàng hoá của gói thầu, tương ứng với yêu cầu về hạng mục chính hoặc tất cả hàng hóa của gói thầu đối với nhà thầu là nhà thương mại. Công suất thiết kế của nhà máy, dây chuyền sản xuất hoặc sản lượng sản xuất cao nhất của 01 tháng trong 05 năm gần nhất tính đến thời điểm đóng thầu bằng: k x (Số lượng yêu cầu của gói thầu x 30/thời gian thực hiện gói thầu (tính theo ngày)). Thông thường k = 1, 5; trường hợp mua sắm hàng hóa có số lượng, khối lượng mời thầu lớn thì có thể quy định k = 1”, hoặc: Công suất thiết kế của nhà máy, dây chuyền sản xuất hoặc sản lượng sản xuất cao nhất của 01 năm trong 05 năm gần nhất tính đến thời điểm đóng thầu bằng: k x (Số lượng yêu cầu của gói thầu x 365/thời gian thực hiện gói thầu (tính theo ngày)). Thông thường k = 1, 5”. Ví dụ: Số lượng hàng hóa cần mua là 12. 000 hộp sữa, thời gian thực hiện gói thầu là 20 ngày, hệ số k = 1, 5 thì công suất thiết kế tối thiểu trong 01 tháng/sản lượng sản xuất sữa cao nhất của 01 tháng của nhà thầu là: 1, 5 x (12. 000 x 30/20) = 27. 000 hộp sữa hoặc công suất thiết kế tối thiểu trong 01 năm/sản lượng sản xuất sữa cao nhất của 01 năm của nhà thầu là: 1, 5 x (12. 000 x 365/20) = 328. 500 hộp sữa. Trường hợp hàng hóa là sản phẩm do nhà thầu Việt Nam sản xuất trong nước (có thể đã bán ra thị trường hoặc chưa bán ra thị trường), nhà thầu phải chứng minh công suất thiết kế hoặc sản lượng sản xuất đáp ứng yêu cầu. Trường hợp nhà thầu vừa là sản xuất, vừa là nhà cung cấp (một số hàng hóa hoặc một phần khối lượng hàng hóa do nhà thầu chào trong HSĐX là do nhà thầu sản xuất, một số hàng hóa khác hoặc một phần khối lượng hàng hóa do nhà thầu mua từ nhà sản xuất, cung cấp khác để cung cấp cho gói thầu) thì ngoài kê khai về năng lực sản xuất, nhà thầu còn phải kê khai về kinh nghiệm thực hiện hợp đồng tương tự theo nội dung quy định tại Mục 4 Bảng số 01 Chương này. Việc đánh giá kinh nghiệm của nhà thầu sẽ được thực hiện trên cơ sở hợp đồng cung cấp hàng hóa tương tự (tương ứng với phần hàng hóa mà nhà thầu mua từ nhà sản xuất, cung cấp khác) và năng lực sản xuất của nhà thầu (tương ứng với phần hàng hóa mà nhà thầu tự sản xuất để cung cấp cho gói thầu). Nhà thầu có thể sử dụng các hồ sơ như hóa đơn bán hàng, số lượng hàng tồn kho. .. để chứng minh sản lượng đã sản xuất trong 01 tháng hoặc 01 năm; sử dụng hồ sơ chứng minh công suất thiết kế của nhà máy, dây chuyền sản xuất để chứng minh năng lực sản xuất. Nhà thầu trong nước thuộc trường hợp quy định tại điểm g Khoản 1 Điều 10 của Luật Đấu thầu khi chào thầu sản phẩm do nhà thầu đó sản xuất không phải đáp ứng tiêu chí này trong thời hạn 05 năm kể từ khi được cơ quan có thẩm quyền công nhận. (11) Trường hợp nhà thầu thiếu cam kết thì được bổ sung trong quá trình đánh giá HSĐX. Trường hợp nhà thầu không bổ sung cam kết trong khoảng thời gian hợp lý theo yêu cầu của Chủ đầu tư thì HSĐX của nhà thầu được coi là không đáp ứng yêu cầu về khả năng bảo hành, cung cấp phụ tùng thay thế hoặc cung cấp các dịch vụ sau bán hàng khác và bị loại. Trường hợp không yêu cầu dịch vụ sau bán hàng thì gạch bỏ tiêu chí đánh giá này. Bảng Y BẢNG YÊU CẦU VỀ HỢP ĐỒNG TƯƠNG TỰ (Áp dụng đối với gói thầu có nhiều loại hàng hóa) [BẢNG: Không tiêu đề] Ghi chú: (1), (2) Nội dung tại cột này được Chủ đầu tư xác định theo nguyên tắc tại ghi chú số (10) Bảng số 01 Chương này. (3) Giá trị tại cột này được Chủ đầu tư xác định theo nguyên tắc nêu tại ghi chú số (11) Bảng số 01 Chương này. (4) Giá trị tại cột này được Chủ đầu tư xác định theo nguyên tắc nêu tại ghi chú số (10) Bảng số 02 Chương này. 2. 2. Tiêu chuẩn đánh giá về nhân sự chủ chốt Không được yêu cầu về huy động nhân sự chủ chốt đối với phần công việc cung cấp hàng hóa. Đối với hàng hóa thông dụng, sẵn có trên thị trường, không đòi hỏi nhân sự thực hiện dịch vụ liên quan (như: lắp đặt, đào tạo, chuyển giao kỹ thuật. ..) phải có trình độ cao thì không yêu cầu về nhân sự chủ chốt. Chỉ được yêu cầu về nhân sự chủ chốt đối với các dịch vụ liên quan có yếu tố đặc thù, phức tạp cần thiết phải có nhân sự có hiểu biết, nhiều kinh nghiệm đảm nhận. Trường hợp HSYC có yêu cầu về nhân sự chủ chốt thì nhà thầu phải chứng minh khả năng huy động các nhân sự chủ chốt đã đề xuất. Nhân sự chủ chốt có thể thuộc biên chế của nhà thầu hoặc do nhà thầu huy động. Trường hợp nhân sự chủ chốt mà nhà thầu đề xuất trong HSĐX không đáp ứng yêu cầu hoặc không chứng minh được khả năng huy động nhân sự (bao gồm cả trường hợp nhân sự đã huy động cho hợp đồng khác có thời gian làm việc trùng với thời gian thực hiện gói thầu này) thì Chủ đầu tư cho phép nhà thầu bổ sung, thay thế. Trường hợp nhà thầu không có nhân sự chủ chốt thay thế đáp ứng yêu cầu của HSYC thì nhà thầu bị loại. Trường hợp nhà thầu cố ý kê khai nhân sự chủ chốt không trung thực trong HSĐX nhằm làm sai lệch kết quả lựa chọn nhà thầu thì nhà thầu không được thay thế nhân sự khác, HSĐX của nhà thầu bị loại và nhà thầu sẽ bị coi là gian lận theo quy định tại điểm b Khoản 4 Điều 16 của Luật Đấu thầu và bị xử lý theo quy định tại Khoản 1 Điều 133 của Nghị định số 214/2025/NĐ-CP. Kinh nghiệm trong các công việc tương tự được thể hiện ở số năm tối thiểu nhân sự thực hiện các công việc tương tự hoặc số hợp đồng tối thiểu trong các công việc tương tự. Số năm kinh nghiệm của nhân sự chủ chốt được tính từ thời điểm nhân sự bắt đầu thực hiện công việc tương tự đó đến thời điểm đóng thầu. Nhà thầu phải cung cấp thông tin chi tiết về các nhân sự chủ chốt được đề xuất theo các Mẫu 08A, 08B và 08C Chương III để chứng minh rằng mình có đầy đủ nhân sự cho các vị trí chủ chốt đáp ứng những yêu cầu sau đây: Bảng số 03: Yêu cầu về nhân sự chủ chốt(1) [BẢNG: Không tiêu đề] Ghi chú: (1) Trường hợp gói thầu không có yêu cầu về nhân sự chủ chốt thì Chủ đầu tư không nhập Bảng này. (2) Chỉ quy định trong trường hợp dịch vụ liên quan có yêu cầu phải có chứng chỉ chuyên môn. Mục 3. Tiêu chuẩn đánh giá về kỹ thuật Sử dụng tiêu chí đạt/không đạt để xây dựng tiêu chuẩn đánh giá về kỹ thuật. Đối với các tiêu chí đánh giá tổng quát, chỉ sử dụng tiêu chí đạt, không đạt. Căn cứ quy mô, tính chất của gói thầu mà xác định mức độ yêu cầu đối với từng nội dung. Đối với các tiêu chí chi tiết cơ bản trong tiêu chí tổng quát, chỉ sử dụng tiêu chí đạt, không đạt; đối với các tiêu chí chi tiết không cơ bản trong tiêu chí tổng quát, ngoài tiêu chí đạt, không đạt, được áp dụng thêm tiêu chí chấp nhận được nhưng không được vượt quá 30% tổng số các tiêu chí chi tiết trong tiêu chí tổng quát đó. Tiêu chí tổng quát được đánh giá là đạt khi tất cả các tiêu chí chi tiết cơ bản được đánh giá là đạt và các tiêu chí chi tiết không cơ bản được đánh giá là đạt hoặc chấp nhận được. HSĐX được đánh giá là đáp ứng yêu cầu về kỹ thuật khi có tất cả các tiêu chí tổng quát đều được đánh giá là đạt. Việc xây dựng tiêu chuẩn đánh giá về kỹ thuật dựa trên các yếu tố về khả năng đáp ứng các yêu cầu về số lượng, chất lượng, thời hạn giao hàng, vận chuyển, lắp đặt, bảo hành, cung cấp các dịch vụ sau bán hàng (nếu có), thông tin về kết quả thực hiện hợp đồng của nhà thầu theo quy định tại Điều 19 và Điều 20 của Nghị định số 214/2025/NĐ-CP, chất lượng hàng hóa tương tự được công khai theo quy định tại Điều 20 của Nghị định số 214/2025/NĐ-CP (nếu có) và các yêu cầu khác nêu trong Chương IV. Căn cứ từng gói thầu cụ thể, khi lập HSYC phải cụ thể hóa các tiêu chí làm cơ sở để đánh giá về kỹ thuật bao gồm: - Đặc tính, thông số kỹ thuật của hàng hóa, tiêu chuẩn sản xuất, tiêu chuẩn chế tạo và kỹ thuật; - Tính hợp lý và hiệu quả tài chính của các giải pháp kỹ thuật, biện pháp tổ chức cung cấp, lắp đặt hàng hóa; - Mức độ đáp ứng các yêu cầu về bảo hành, bảo trì: nhà thầu phải trình bày được kế hoạch cung cấp dịch vụ bảo hành, bảo trì; - Mức độ đáp ứng các yêu cầu về cung cấp vật tư, thiết bị thay thế và các dịch vụ liên quan khác (nếu có) trong toàn bộ quá trình sử dụng của hàng hóa. - Khả năng thích ứng về mặt địa lý, môi trường; - Tác động đối với môi trường và biện pháp giải quyết; - Tiêu chí đấu thầu bền vững (nếu có); - Các yếu tố về điều kiện thương mại, thời gian giao hàng, đào tạo chuyển giao kỹ thuật, cung cấp các dịch vụ sau bán hàng; - Tiến độ cung cấp hàng hóa; - Yếu tố thân thiện môi trường; - Kết quả thực hiện hợp đồng của nhà thầu đối với gói thầu cung cấp hàng hóa, EPC, EP, PC, chìa khóa trao tay theo quy định tại Điều 19 và Điều 20 của Nghị định số 214/2025/NĐ-CP, chất lượng hàng hóa tương tự được công khai theo quy định tại Điều 20 của Nghị định số 214/2025/NĐ-CP (nếu có); - Các yếu tố cần thiết khác. Mục 4. Tiêu chuẩn đánh giá về tài chính Bước 1. Xác định giá thầu; Bước 2. Sửa lỗi, hiệu chỉnh sai lệch theo quy định tại Điều 31 của Nghị định số 214/2025/NĐ-CP (nếu có); Bước 3. Xác định giá thầu sau sửa lỗi, hiệu chỉnh sai lệch (nếu có), trừ đi giá trị giảm giá (nếu có) và đáp ứng tỷ lệ tiết kiệm theo quy định tại Mục 14 Chương I; Chương III. BIỂU MẪU Mẫu 01A ĐƠN DỰ THẦU (Áp dụng đối với nhà thầu là tổ chức) ________, ngày ____ tháng ____ năm ____ Kính gửi: _ [Ghi tên Chủ đầu tư] (sau đây gọi là Chủ đầu tư) Sau khi nghiên cứu hồ sơ yêu cầu và văn bản sửa đổi hồ sơ yêu cầu số ____ [Ghi số của văn bản sửa đổi, nếu có] mà chúng tôi đã nhận được, chúng tôi, _____ [Ghi tên nhà thầu], có địa chỉ tại ______[Ghi địa chỉ của nhà thầu] cam kết thực hiện gói thầu _______[Ghi tên gói thầu] theo đúng yêu cầu của hồ sơ yêu cầu với tổng số tiền là _____ [Ghi giá trị bằng số, bằng chữ và đồng tiền dự thầu] cùng với bảng giá thầu kèm theo. Thời gian thực hiện gói thầu là ____ [Ghi thời gian thực hiện tất cả các công việc theo yêu cầu của gói thầu]. Hồ sơ đề xuất này có hiệu lực trong thời gian ____ ngày, kể từ ngày ____ tháng ____ năm ____ [Ghi ngày có thời điểm đóng thầu]. Chúng tôi cam kết: 1. Không đang trong quá trình thực hiện thủ tục giải thể hoặc bị thu hồi giấy chứng nhận đăng ký doanh nghiệp, giấy chứng nhận đăng ký hợp tác xã, liên hiệp hợp tác xã, tổ hợp tác, không thuộc trường hợp mất khả năng thanh toán theo quy định của pháp luật về phá sản (không đang trong quá trình chấm dứt hoạt động hoặc bị thu hồi giấy chứng nhận đăng ký hộ kinh doanh đối với nhà thầu là hộ kinh doanh). 2. Đã thực hiện nghĩa vụ kê khai thuế và nộp thuế của năm tài chính gần nhất so với thời điểm đóng thầu; 3. Không đang trong thời gian bị cấm dự thầu theo quy định của pháp luật đấu thầu; 4. Không đang bị truy cứu trách nhiệm hình sự (chủ hộ không đang bị truy cứu trách nhiệm hình sự trong trường hợp nhà thầu là hộ kinh doanh); 5. Trong thời hạn 03 năm trước thời điểm đóng thầu, nhà thầu không có nhân sự (ký kết hợp đồng lao động với nhà thầu tại thời điểm nhân sự thực hiện hành vi vi phạm) bị tòa án kết án có hành vi vi phạm quy định về đấu thầu gây hậu quả nghiêm trọng theo quy định của pháp luật về hình sự nhằm mục đích cho nhà thầu trúng thầu(2). 6. Không thực hiện các hành vi tham nhũng, hối lộ, thông thầu, cản trở và các hành vi vi phạm quy định khác của pháp luật đấu thầu khi tham dự gói thầu này. 7. Những thông tin kê khai trong HSĐX là trung thực. 8. Trường hợp trúng thầu, HSĐX và các văn bản bổ sung, làm rõ HSĐX tạo thành thỏa thuận ràng buộc trách nhiệm giữa hai bên cho tới khi hợp đồng được ký kết. 9. Nếu HSĐX của chúng tôi được chấp nhận, chúng tôi sẽ thực hiện biện pháp bảo đảm thực hiện hợp đồng theo quy định của HSYC. [BẢNG: Không tiêu đề] Ghi chú: (1) Trường hợp đại diện theo pháp luật của nhà thầu ủy quyền cho cấp dưới ký đơn dự thầu thì phải gửi kèm theo Giấy ủy quyền theo Mẫu 02 Chương này. Trường hợp tại điều lệ công ty hoặc tại các hồ sơ khác liên quan có phân công trách nhiệm cho cấp dưới ký đơn dự thầu thì phải gửi kèm theo bản chụp các văn bản, hồ sơ này (không cần lập Giấy ủy quyền theo Mẫu 02 Chương này). (2) HSYC không được yêu cầu nhà thầu phải nộp lý lịch tư pháp của nhân sự để chứng minh cho nội dung đánh giá này. Nội dung này chỉ yêu cầu nhà thầu cam kết trong Đơn này. Mẫu 01B ĐƠN DỰ THẦU (Áp dụng đối với nhà thầu là cá nhân, nhóm cá nhân sản xuất sản phẩm đổi mới sáng tạo) ______, ngày ____ tháng ____ năm ____ Kính gửi: ____ [Ghi tên Chủ đầu tư] (sau đây gọi là Chủ đầu tư) Sau khi nghiên cứu hồ sơ yêu cầu (bao gồm văn bản sửa đổi hồ sơ yêu cầu, nếu có), chúng tôi, _____ [Ghi tên cá nhân và mã số thuế cá nhân; đối với nhà thầu là nhóm cá nhân thì ghi tên của các thành viên và mã số thuế theo Mẫu 01C], cam kết thực hiện gói thầu _____ [Ghi tên gói thầu] theo đúng yêu cầu của hồ sơ yêu cầu với tổng số tiền là _____ [Ghi giá trị bằng số, bằng chữ và đồng tiền dự thầu]. Thời gian thực hiện gói thầu là ____ [Ghi thời gian thực hiện tất cả các công việc theo yêu cầu của hồ sơ yêu cầu]. Hồ sơ đề xuất có hiệu lực là ___ngày [Ghi số ngày], kể từ ngày ___tháng ___ năm ___[Ghi ngày có thời điểm đóng thầu]. Chúng tôi cam kết: 1. Có năng lực hành vi dân sự đầy đủ; 2. Đã thực hiện nghĩa vụ kê khai thuế và nộp thuế của năm tài chính gần nhất so với thời điểm đóng thầu; 3. Không đang trong thời gian bị cấm dự thầu theo quy định của pháp luật đấu thầu; 4. Không đang bị truy cứu trách nhiệm hình sự; 5. Không thực hiện các hành vi tham nhũng, hối lộ, thông thầu, cản trở và các hành vi vi phạm quy định khác của pháp luật đấu thầu khi tham dự gói thầu này; 6. Trong thời hạn 03 năm trước thời điểm đóng thầu, các thành viên trong nhóm cá nhân không bị Tòa án kết án có hành vi vi phạm quy định về đấu thầu gây hậu quả nghiêm trọng theo quy định của pháp luật về hình sự nhằm mục đích cho cá nhân (hoặc nhóm cá nhân trong đó có nhân sự vi phạm) trúng thầu (2). 7. Những thông tin kê khai trong HSĐX là trung thực. 8. Trường hợp trúng thầu, HSĐX và các văn bản bổ sung, làm rõ HSĐX tạo thành thỏa thuận ràng buộc trách nhiệm giữa hai bên cho tới khi hợp đồng được ký kết. 9. Nếu HSĐX của chúng tôi được chấp nhận, chúng tôi sẽ thực hiện biện pháp bảo đảm thực hiện hợp đồng theo quy định của HSYC. 10. Có đủ năng lực sản xuất hàng hóa để thực hiện gói thầu. [BẢNG: Không tiêu đề] Ghi chú: (1) Cá nhân dự thầu phải ký đơn dự thầu. Đối với trường hợp nhóm cá nhân thì tất cả các thành viên trong nhóm hoặc thành viên được phân công theo Văn bản thỏa thuận ký đơn dự thầu. (2) HSYC không được yêu cầu nhà thầu phải nộp lý lịch tư pháp của nhân sự để chứng minh cho nội dung đánh giá này. Mẫu 01C VĂN BẢN THỎA THUẬN (Áp dụng đối với nhóm cá nhân sản xuất sản phẩm đổi mới sáng tạo) Ngày: ___ tháng___năm___ Căn cứ HCYC của gói thầu: ______ [ghi tên gói thầu] Chúng tôi gồm có: Thành viên thứ nhất: Họ và tên: Số CCCD/Hộ chiếu: Ngày cấp: Nơi cấp: Mã số thuế: Địa chỉ: Điện thoại: Thành viên thứ hai: Họ và tên: Số CCCD/Hộ chiếu: Ngày cấp: Nơi cấp: Mã số thuế: Địa chỉ: Điện thoại: .. . Thành viên thứ n: Họ và tên: Số CCCD/Hộ chiếu: Ngày cấp: Nơi cấp: Mã số thuế: Địa chỉ: Điện thoại: Các bên (sau đây gọi là thành viên) thống nhất ký kết văn bản thỏa thuận thành lập nhóm cá nhân với các nội dung sau: Điều 1. Nguyên tắc chung 1. Các thành viên tự nguyện thành lập nhóm cá nhân để dự thầu gói thầu____ [ghi tên gói thầu] thuộc ____ [ghi tên dự án/dự toán mua sắm] do____ [ghi tên Chủ đầu tư] tổ chức. 2. Các thành viên cam kết không thành viên nào được tham gia độc lập hoặc liên danh với cá nhân khác để tham gia gói thầu này. Trường hợp trúng thầu, các thành viên cùng ký hợp đồng và không thành viên nào có quyền từ chối thực hiện các trách nhiệm và nghĩa vụ đã quy định trong hợp đồng. Trường hợp thành viên của nhóm từ chối hoàn thành trách nhiệm và nghĩa vụ của mình thì thành viên đó bị xử lý như sau: - Bồi thường thiệt hại cho các bên trong nhóm; - Bồi thường thiệt hại cho Chủ đầu tư theo quy định nêu trong hợp đồng; - Hình thức xử lý khác ____ [ghi rõ hình thức xử lý khác]. Điều 2. Phân công trách nhiệm Các thành viên thống nhất phân công trách nhiệm để thực hiện gói thầu____ [ghi tên gói thầu] thuộc ____ [ghi tên dự án/dự toán mua sắm] như sau: Phân công ____ [ghi tên cá nhân] làm thành viên đứng đầu nhóm, đại diện cho nhóm trong những phần việc sau: [- Ký các văn bản, hồ sơ để giao dịch với Chủ đầu tư trong quá trình dự thầu, văn bản giải trình, làm rõ HSĐX hoặc văn bản đề nghị rút HSĐX; - Thực hiện bảo đảm dự thầu cho cả nhóm; - Tham gia quá trình hoàn thiện hợp đồng; - Ký đơn kiến nghị trong trường hợp nhà thầu có kiến nghị; - Các công việc khác trừ việc ký kết hợp đồng ____ [ghi rõ nội dung các công việc khác (nếu có)]. Điều 3. Hiệu lực của văn bản thỏa thuận 1. Văn bản thỏa thuận có hiệu lực kể từ ngày ký. 2. Văn bản thỏa thuận chấm dứt hiệu lực trong các trường hợp sau: - Các bên hoàn thành trách nhiệm, nghĩa vụ của mình và tiến hành thanh lý hợp đồng; - Các bên cùng thỏa thuận chấm dứt; - Nhóm cá nhân không trúng thầu; - Hủy thầu gói thầu ____ [ghi tên gói thầu] thuộc ____ [ghi tên dự án/dự toán mua sắm] theo thông báo của Chủ đầu tư. Văn bản thỏa thuận được lập trên sự chấp thuận của tất cả các thành viên. THÀNH VIÊN ĐỨNG ĐẦU NHÓM CÁ NHÂN [ký, ghi rõ họ tên] CÁC THÀNH VIÊN THUỘC NHÓM CÁ NHÂN [ký, ghi rõ họ tên] Mẫu 02 GIẤY ỦY QUYỀN(1) Hôm nay, ngày ____ tháng ____ năm ____, tại ____ Tôi là____ [Ghi tên, số CCCD hoặc số hộ chiếu, chức danh của người đại diện theo pháp luật của nhà thầu], là người đại diện theo pháp luật của ____ [Ghi tên nhà thầu] có địa chỉ tại____ [Ghi địa chỉ của nhà thầu] bằng văn bản này ủy quyền cho___ [Ghi tên, số CCCD hoặc số hộ chiếu, chức danh của người được ủy quyền] thực hiện các công việc sau đây trong quá trình dự thầu gói thầu__[Ghi tên gói thầu] thuộc ___ [Ghi tên dự án/dự toán mua sắm] do__ [Ghi tên Chủ đầu tư] tổ chức: [- Ký đơn dự thầu; - Ký thỏa thuận liên danh (nếu có); - Ký các văn bản, hồ sơ để giao dịch với Chủ đầu tư trong quá trình dự thầu, kể cả văn bản giải trình, làm rõ HSĐX; - Tham gia quá trình thương thảo (nếu có), hoàn thiện hợp đồng; - Ký kết hợp đồng với Chủ đầu tư nếu được chỉ định thầu.] (2) Người được ủy quyền nêu trên chỉ thực hiện các công việc trong phạm vi ủy quyền với tư cách là đại diện hợp pháp của ____ [Ghi tên nhà thầu]. ____ [Ghi tên nhà thầu] chịu trách nhiệm hoàn toàn về những công việc do ____ [Ghi tên người được ủy quyền] thực hiện trong phạm vi ủy quyền. Giấy ủy quyền có hiệu lực kể từ ngày ____ đến ngày ____(3). Giấy ủy quyền này được lập thành ____ bản có giá trị pháp lý như nhau, người ủy quyền giữ ____ bản, người được ủy quyền giữ ____ bản. [BẢNG: Không tiêu đề] Ghi chú: (1) Trường hợp ủy quyền thì bản gốc giấy ủy quyền phải được gửi cho Chủ đầu tư cùng với đơn dự thầu. Việc ủy quyền của người đại diện theo pháp luật của nhà thầu cho cấp phó, cấp dưới, giám đốc chi nhánh, người đứng đầu văn phòng đại diện của nhà thầu để thay mặt cho người đại diện theo pháp luật của nhà thầu thực hiện một hoặc các nội dung công việc nêu trên đây. Việc sử dụng con dấu trong trường hợp được ủy quyền có thể là dấu của nhà thầu hoặc dấu của đơn vị mà cá nhân liên quan được ủy quyền. Người được ủy quyền không được tiếp tục ủy quyền cho người khác. (2) Phạm vi ủy quyền bao gồm một hoặc nhiều công việc nêu trên. (3) Ghi ngày có hiệu lực và ngày hết hiệu lực của giấy ủy quyền phù hợp với quá trình dự thầu và phải bảo đảm có hiệu lực trước ngày thực hiện các công việc được ủy quyền. Mẫu 03 THỎA THUẬN LIÊN DANH (1), ngày tháng năm Gói thầu: [Ghi tên gói thầu] Thuộc: [Ghi tên dự án/dự toán mua sắm] - Căn cứ(2)_[Luật Đấu thầu]; - Căn cứ(2); - Căn cứ hồ sơ yêu cầu gói thầu __[Ghi tên gói thầu] ngày ___ tháng___ năm__[Ngày được ghi trên HSYC]; Chúng tôi, đại diện cho các bên ký thỏa thuận liên danh, gồm có: Tên thành viên liên danh [Ghi tên từng thành viên liên danh] Đại diện là ông/bà: Chức vụ: Địa chỉ: Điện thoại: E-mail: Tài khoản: Mã số thuế: Giấy ủy quyền số ngày ___tháng ____ năm ___ (trường hợp được ủy quyền). Các bên (sau đây gọi là thành viên) thống nhất ký kết thỏa thuận liên danh với các nội dung sau: Điều 1. Nguyên tắc chung 1. Các thành viên tự nguyện hình thành liên danh để dự thầu gói thầu___ [Ghi tên gói thầu] thuộc ___ [Ghi tên dự án/dự toán mua sắm]. 2. Các thành viên thống nhất tên gọi của liên danh cho mọi giao dịch liên quan đến gói thầu này là: [Ghi tên của liên danh theo thỏa thuận]. 3. Các thành viên cam kết không thành viên nào có quyền từ chối thực hiện các trách nhiệm và nghĩa vụ quy định trong hợp đồng. Trường hợp thành viên của liên danh từ chối hoàn thành trách nhiệm riêng của mình như đã thỏa thuận thì thành viên đó bị xử lý như sau: - Bồi thường thiệt hại cho các bên trong liên danh; - Bồi thường thiệt hại cho Chủ đầu tư theo quy định nêu trong hợp đồng; - Hình thức xử lý khác [Ghi rõ hình thức xử lý khác]. Điều 2. Phân công trách nhiệm Các thành viên thống nhất chịu trách nhiệm chung, trách nhiệm riêng để thực hiện gói thầu [Ghi tên gói thầu] thuộc ___ [Ghi tên dự án/dự toán mua sắm] đối với từng thành viên như sau: 1. Thành viên đứng đầu liên danh Các bên nhất trí ủy quyền cho [Ghi tên một bên] làm thành viên đứng đầu liên danh, đại diện cho liên danh trong những phần việc sau(3): [- Ký đơn dự thầu; - Ký các văn bản, hồ sơ để giao dịch với Chủ đầu tư trong quá trình dự thầu, kể cả văn bản đề nghị làm rõ HSYC và văn bản giải trình, làm rõ HSĐX; - Tham gia quá trình thương thảo (nếu có), hoàn thiện hợp đồng; - Ký đơn kiến nghị trong trường hợp nhà thầu có kiến nghị; - Các công việc khác trừ việc ký kết hợp đồng [Ghi rõ nội dung các công việc khác (nếu có)]. 2. Các thành viên trong liên danh thỏa thuận phân công trách nhiệm thực hiện công việc theo bảng dưới đây (4): [BẢNG: Không tiêu đề] Điều 3. Hiệu lực của thỏa thuận liên danh 1. Thỏa thuận liên danh có hiệu lực kể từ ngày ký. 2. Thỏa thuận liên danh chấm dứt hiệu lực trong các trường hợp sau: - Các bên hoàn thành trách nhiệm và nghĩa vụ của mình và tiến hành thanh lý hợp đồng; - Các bên cùng thỏa thuận chấm dứt; - Nhà thầu liên danh không được chỉ định thầu; - Hủy thầu gói thầu [Ghi tên gói thầu] thuộc [Ghi tên dự án/dự toán mua sắm] theo thông báo của Chủ đầu tư. Thỏa thuận liên danh được lập thành bản, mỗi bên giữ bản, các bản thỏa thuận có giá trị pháp lý như nhau. ĐẠI DIỆN HỢP PHÁP CỦA THÀNH VIÊN ĐỨNG ĐẦU LIÊN DANH(5) [Ghi tên, chức danh, ký tên và đóng dấu] ĐẠI DIỆN HỢP PHÁP CỦA THÀNH VIÊN LIÊN DANH [Ghi tên từng thành viên, chức danh, ký tên và đóng dấu] Ghi chú: (1) Căn cứ quy mô, tính chất của gói thầu, nội dung thỏa thuận liên danh theo mẫu này có thể được sửa đổi bổ sung cho phù hợp. (2) Cập nhật các văn bản quy phạm pháp luật theo quy định hiện hành. (3) Phạm vi ủy quyền bao gồm một hoặc nhiều công việc nêu trên. (4) Nhà thầu phải ghi rõ nội dung công việc cụ thể và ước tính giá trị tương ứng mà từng thành viên trong liên danh sẽ thực hiện, trách nhiệm chung, trách nhiệm của từng thành viên, kể cả thành viên đứng đầu liên danh. Việc phân chia công việc trong liên danh phải căn cứ các hạng mục nêu trong bảng giá thầu tại Mẫu 4. 1 (4. 1A hoặc 4. 1B hoặc 4. 1C) hoặc Mẫu 4. 2 (4. 2A hoặc 4. 2B hoặc 4. 2C) Chương này hoặc theo các công việc thuộc quá trình sản xuất hạng mục trong bảng giá thầu, không được phân chia các công việc không thuộc các hạng mục này hoặc không thuộc quá trình sản xuất các hạng mục này; không được phân chia các công việc không thuộc các hạng mục này hoặc không thuộc quá trình sản xuất các hạng mục này. (5) Đại diện hợp pháp của thành viên liên danh có thể là người đại diện theo pháp luật hoặc người được người đại diện theo pháp luật ủy quyền. Mẫu 4. 1A BẢNG giá thầu (Áp dụng với hợp đồng trọn gói) I. Hàng hóa dự thầu [BẢNG: Không tiêu đề] Ghi chú: - Chủ đầu tư điền nội dung tại các cột: (1), (2), (3), (4), (5), (6), (7), (8), (9), (10). Đối với cột (8), Chủ đầu tư dẫn chiếu đến nội dung tương ứng quy định tại Chương IV. - Nhà thầu điền từ cột (11), (12), (13): (11): Nhà thầu biết mã HS của hàng hóa thì nhà thầu liệt kê; (12), (13): Nhà thầu điền đơn giá, thành tiền bao gồm thuế, phí, lệ phí (nếu có). Khi dự thầu, nhà thầu phải chịu trách nhiệm tìm hiểu, tính toán và chào đầy đủ các loại thuế, phí, lệ phí (nếu có) theo thuế suất, mức phí, lệ phí tại thời điểm 28 ngày trước ngày có thời điểm đóng thầu theo quy định. II. Dịch vụ liên quan [BẢNG: Không tiêu đề] Ghi chú: - Cột (1) đến (6): Chủ đầu tư điền, trong đó dẫn chiếu đến yêu cầu tại Chương IV cho phù hợp. - Cột (7), (8): Nhà thầu chào (bao gồm tất cả các loại thuế, phí, lệ phí). [BẢNG: Không tiêu đề] III. Tổng hợp giá thầu Đại diện hợp pháp của nhà thầu [ghi tên, chức danh, ký tên và đóng dấu] Mẫu 4. 1B BẢNG giá thầu (Áp dụng với loại hợp đồng theo đơn giá) I. Hàng hóa dự thầu [BẢNG: Không tiêu đề] Ghi chú: - Chủ đầu tư điền nội dung tại các cột: (1), (2), (3), (4), (5), (6), (7), (8), (9), (10). Đối với cột (8), Chủ đầu tư dẫn chiếu đến nội dung tương ứng quy định tại Chương IV. - Nhà thầu điền từ cột (11), (12), (13): (11): Nhà thầu biết mã HS của hàng hóa thì nhà thầu liệt kê; (12), (13): Nhà thầu điền đơn giá, thành tiền bao gồm thuế, phí, lệ phí (nếu có). Khi dự thầu, nhà thầu phải chịu trách nhiệm tìm hiểu, tính toán và chào đầy đủ các loại thuế, phí, lệ phí (nếu có) theo thuế suất, mức phí, lệ phí tại thời điểm 28 ngày trước ngày có thời điểm đóng thầu theo quy định. II. Dịch vụ liên quan [BẢNG: Không tiêu đề] Ghi chú: - Cột (1) đến (6): Chủ đầu tư điền, trong đó dẫn chiếu đến yêu cầu tại Chương IV cho phù hợp. - Cột (7), (8): Nhà thầu chào (bao gồm tất cả các loại thuế, phí, lệ phí). [BẢNG: Không tiêu đề] III. Tổng hợp giá thầu Ghi chú: (*): a%: Chủ đầu tư quy định giá trị của a (%) để nhà thầu làm cơ sở chào chi phí dự phòng. Đại diện hợp pháp của nhà thầu [ghi tên, chức danh, ký tên và đóng dấu] Mẫu 4. 1C BẢNG giá thầu (Áp dụng với loại hợp đồng hỗn hợp) I. Hàng hóa dự thầu [BẢNG: Không tiêu đề] Ghi chú: - Chủ đầu tư điền nội dung tại các cột: (1), (2), (3), (4), (5), (6), (7), (8), (9), (10). Đối với cột (8), Chủ đầu tư dẫn chiếu đến nội dung tương ứng quy định tại Chương IV. - Nhà thầu điền từ cột (11), (12), (13): (11): Nhà thầu biết mã HS của hàng hóa thì nhà thầu liệt kê; (12), (13): Nhà thầu điền đơn giá, thành tiền bao gồm thuế, phí, lệ phí (nếu có). Khi dự thầu, nhà thầu phải chịu trách nhiệm tìm hiểu, tính toán và chào đầy đủ các loại thuế, phí, lệ phí (nếu có) theo thuế suất, mức phí, lệ phí tại thời điểm 28 ngày trước ngày có thời điểm đóng thầu theo quy định. II. Dịch vụ liên quan [BẢNG: Không tiêu đề] Ghi chú: - Cột (1) đến (6): Chủ đầu tư điền, trong đó dẫn chiếu đến yêu cầu tại Chương IV cho phù hợp. - Cột (7), (8): Nhà thầu chào (bao gồm tất cả các loại thuế, phí, lệ phí). [BẢNG: Không tiêu đề] III. Tổng hợp giá thầu Ghi chú: (*): a%: Chủ đầu tư quy định giá trị của a (%) để nhà thầu làm cơ sở chào chi phí dự phòng. Đại diện hợp pháp của nhà thầu [ghi tên, chức danh, ký tên và đóng dấu] Mẫu 4. 2A BẢNG giá thầu (Áp dụng loại hợp đồng trọn gói) I. Hàng hóa được sản xuất, gia công tại Việt Nam [BẢNG: Không tiêu đề] Ghi chú: - Chủ đầu tư điền các cột (1) (2) (3) (4) (5) (6) (7) (8) (9) (10) (8): Dẫn chiếu đến nội dung tương ứng quy định tại Chương IV. - Nhà thầu điền các cột sau: Cột (11): Nhà thầu biết mã HS của hàng hóa thì nhà thầu liệt kê; Cột (14): Chi phí vận chuyển, bảo hiểm và các dịch vụ khác (đã bao gồm thuế VAT) để vận chuyển hàng hóa đến địa điểm theo yêu cầu. Cột (16) Thuế tiêu thụ đặc biệt (nếu có), thuế VAT phải nộp trong trường hợp nhà thầu được trao hợp đồng. Cột (12) (13) (15) (17): Nhà thầu điền. II. Hàng hóa được sản xuất, gia công ngoài nước đã được nhập khẩu hoặc sẽ được nhập khẩu vào Việt Nam [BẢNG: Không tiêu đề] Ghi chú: - Chủ đầu tư điền các cột (1) (2) (3) (4) (5) (6) (7) (8) (9) (10) (8): Dẫn chiếu đến nội dung tương ứng quy định tại Chương IV. - Nhà thầu điền các cột sau: Cột (11): Nhà thầu biết mã HS của hàng hóa thì nhà thầu liệt kê; Cột (14): Chi phí vận chuyển, bảo hiểm và các dịch vụ khác (đã bao gồm thuế VAT) ở Việt Nam để vận chuyển hàng hóa đến địa điểm theo yêu cầu. Cột (12) (13) (15) (16) (17) (18) (19) (20): Nhà thầu điền. III. Dịch vụ liên quan [BẢNG: Không tiêu đề] Ghi chú: - Cột (1) đến (6): Chủ đầu tư điền, trong đó dẫn chiếu đến yêu cầu tại Chương IV cho phù hợp. - Cột (7) (8): Nhà thầu chào (bao gồm tất cả các loại thuế, phí, lệ phí). IV. Tổng hợp giá thầu [BẢNG: Không tiêu đề] Đại diện hợp pháp của nhà thầu [ghi tên, chức danh, ký tên và đóng dấu] Mẫu 4. 2B BẢNG giá thầu (Áp dụng loại hợp đồng theo đơn giá) I. Hàng hóa được sản xuất, gia công tại Việt Nam [BẢNG: Không tiêu đề] Ghi chú: - Chủ đầu tư điền các cột (1) (2) (3) (4) (5) (6) (7) (8) (9) (10) (8): Dẫn chiếu đến nội dung tương ứng quy định tại Chương IV. - Nhà thầu điền các cột sau: Cột (11): Nhà thầu biết mã HS của hàng hóa thì nhà thầu liệt kê; Cột (14): Chi phí vận chuyển, bảo hiểm và các dịch vụ khác (đã bao gồm thuế VAT) để vận chuyển hàng hóa đến địa điểm theo yêu cầu. Cột (16) Thuế tiêu thụ đặc biệt (nếu có), thuế VAT phải nộp trong trường hợp nhà thầu được trao hợp đồng. Cột (12) (13) (15) (17): Nhà thầu điền. II. Hàng hóa được sản xuất, gia công ngoài nước đã được nhập khẩu hoặc sẽ được nhập khẩu vào Việt Nam [BẢNG: Không tiêu đề] Ghi chú: - Chủ đầu tư điền các cột (1) (2) (3) (4) (5) (6) (7) (8) (9) (10) (8): Dẫn chiếu đến nội dung tương ứng quy định tại Chương IV. - Nhà thầu điền các cột sau: Cột (11): Nhà thầu biết mã HS của hàng hóa thì nhà thầu liệt kê; Cột (14): Chi phí vận chuyển, bảo hiểm và các dịch vụ khác (đã bao gồm thuế VAT) ở Việt Nam để vận chuyển hàng hóa đến địa điểm theo yêu cầu. Cột (12) (13) (15) (16) (17) (18) (19) (20): Nhà thầu điền. III. Dịch vụ liên quan [BẢNG: Không tiêu đề] Ghi chú: - Cột (1) đến (6): Chủ đầu tư điền, trong đó dẫn chiếu đến yêu cầu tại Chương IV cho phù hợp. - Cột (7) (8): Nhà thầu chào (bao gồm tất cả các loại thuế, phí, lệ phí). IV. Tổng hợp giá thầu [BẢNG: Không tiêu đề] Ghi chú: (*): a%: Chủ đầu tư quy định giá trị của a (%) để nhà thầu làm cơ sở chào chi phí dự phòng. Đại diện hợp pháp của nhà thầu [ghi tên, chức danh, ký tên và đóng dấu] Mẫu 4. 2C BẢNG giá thầu (Áp dụng loại hợp đồng hỗn hợp) I. Hàng hóa được sản xuất, gia công tại Việt Nam [BẢNG: Không tiêu đề] Ghi chú: - Chủ đầu tư điền các cột (1) (2) (3) (4) (5) (6) (7) (8) (9) (10) (8): Dẫn chiếu đến nội dung tương ứng quy định tại Chương IV. - Nhà thầu điền các cột sau: Cột (11): Nhà thầu biết mã HS của hàng hóa thì nhà thầu liệt kê; Cột (14): Chi phí vận chuyển, bảo hiểm và các dịch vụ khác (đã bao gồm thuế VAT) để vận chuyển hàng hóa đến địa điểm theo yêu cầu. Cột (16) Thuế tiêu thụ đặc biệt (nếu có), thuế VAT phải nộp trong trường hợp nhà thầu được trao hợp đồng. Cột (12) (13) (15) (17): Nhà thầu điền. II. Hàng hóa được sản xuất, gia công ngoài nước đã được nhập khẩu hoặc sẽ được nhập khẩu vào Việt Nam [BẢNG: Không tiêu đề] Ghi chú: - Chủ đầu tư điền các cột (1) (2) (3) (4) (5) (6) (7) (8) (9) (10) (8): Dẫn chiếu đến nội dung tương ứng quy định tại Chương IV. - Nhà thầu điền các cột sau: Cột (11): Nhà thầu biết mã HS của hàng hóa thì nhà thầu liệt kê; Cột (14): Chi phí vận chuyển, bảo hiểm và các dịch vụ khác (đã bao gồm thuế VAT) ở Việt Nam để vận chuyển hàng hóa đến địa điểm theo yêu cầu. Cột (12) (13) (15) (16) (17) (18) (19) (20): Nhà thầu điền. III. Dịch vụ liên quan [BẢNG: Không tiêu đề] Ghi chú: - Cột (1) đến (6): Chủ đầu tư điền, trong đó dẫn chiếu đến yêu cầu tại Chương IV cho phù hợp. - Cột (7) (8): Nhà thầu chào (bao gồm tất cả các loại thuế, phí, lệ phí). IV. Tổng hợp giá thầu [BẢNG: Không tiêu đề] Ghi chú: (*): a%: Chủ đầu tư quy định giá trị của a (%) để nhà thầu làm cơ sở chào chi phí dự phòng. Đại diện hợp pháp của nhà thầu [ghi tên, chức danh, ký tên và đóng dấu] Mẫu 05 BẢNG TIẾN ĐỘ CUNG CẤP(*) Nhà thầu đề xuất tiến độ cung cấp phù hợp với yêu cầu của Chủ đầu tư [BẢNG: Không tiêu đề] Đại diện hợp pháp của nhà thầu [ghi tên, chức danh, ký tên và đóng dấu] Ghi chú: Cột (1) (2) (3)(4) (5) (6) (7): Chủ đầu tư điền. Cột (8): Nhà thầu điền; (*) Hàng hóa phải được giao trong khoảng thời gian quy định trong HSYC. Nhà thầu đề xuất thời gian giao hàng sớm hơn ngày giao hàng sớm nhất thì không được tính ưu tiên và không bị loại. Nhà thầu đề xuất thời gian giao hàng muộn hơn khoảng thời gian này thì HSĐX của nhà thầu sẽ bị loại. Mẫu 06 BẢN KÊ KHAI THÔNG TIN VỀ NHÀ THẦU (1) Ngày: _________________ Tên gói thầu: _________________ [BẢNG: Không tiêu đề] Ghi chú: (1) Đối với nhà thầu liên danh thì từng thành viên phải kê khai theo Mẫu này. Mẫu 07A [BẢNG: Không tiêu đề] Thông tin về từng hợp đồng, mỗi hợp đồng cần bảo đảm các thông tin sau đây: [BẢNG: Không tiêu đề] Nhà thầu nghiên cứu kỹ HSYC và đề xuất các hợp đồng tương tự khác nhau để bảo đảm đáp ứng yêu cầu của HSYC. Nhà thầu phải gửi kèm theo bản chụp các văn bản, hồ sơ liên quan đến các hợp đồng đó (xác nhận của Chủ đầu tư về hợp đồng thực hiện theo các nội dung liên quan trong bảng trên). Ghi chú: (1) Trong trường hợp liên danh, từng thành viên trong liên danh kê khai theo Mẫu này. Trường hợp nhà thầu có nhiều hợp đồng tương tự thì kê khai từng hợp đồng theo Mẫu này. Trường hợp HSYC không yêu cầu về kinh nghiệm thực hiện hợp đồng cung cấp hàng hoá tương tự thì bỏ qua Bảng này. (2) Nhà thầu chỉ kê khai nội dung tương tự với yêu cầu của gói thầu. (3) Trường hợp giá trị hợp đồng không tính bằng VND thì quy đổi sang VND theo tỷ giá theo quy định tại Mục 2. 1 Chương II để làm cơ sở đánh giá. Mẫu 07B [BẢNG: Không tiêu đề] Số lượng nhà máy, cơ sở sản xuất (gọi chung là nhà máy): ____ [Điền số nhà máy] Đối với mỗi nhà máy, nhà thầu kê khai thông tin sau đây: [BẢNG: Không tiêu đề] Ghi chú: Trong trường hợp liên danh, từng thành viên trong liên danh kê khai theo Mẫu này. Trường hợp HSYC không yêu cầu về năng lực sản xuất hàng hóa thì bỏ qua Bảng này. Mẫu 08A BẢNG ĐỀ XUẤT NHÂN SỰ CHỦ CHỐT Nhà thầu phải kê khai những nhân sự chủ chốt theo quy định tại Mục 2. 2 Chương II và phải chứng minh khả năng sẵn sàng huy động các nhân sự này để tham gia thực hiện gói thầu. Nhân sự chủ chốt có thể thuộc biên chế của nhà thầu hoặc do nhà thầu huy động. Trường hợp nhân sự chủ chốt mà nhà thầu đề xuất trong HSĐX không đáp ứng yêu cầu hoặc không chứng minh được khả năng huy động nhân sự (bao gồm cả trường hợp nhân sự đã huy động cho hợp đồng khác có thời gian làm việc trùng với thời gian thực hiện gói thầu này) thì Chủ đầu tư cho phép nhà thầu bổ sung, thay thế. Trường hợp nhà thầu không có nhân sự thay thế đáp ứng yêu cầu của HSYC thì HSĐX bị loại. Trường hợp nhà thầu cố ý kê khai nhân sự chủ chốt không trung thực trong HSĐX nhằm làm sai lệch kết quả lựa chọn nhà thầu thì nhà thầu không được thay thế nhân sự khác, HSĐX của nhà thầu bị loại và nhà thầu sẽ bị coi là gian lận theo quy định tại điểm b Khoản 4 Điều 16 của Luật Đấu thầu và bị xử lý theo quy định tại Khoản 1 Điều 133 của Nghị định số 214/2025/NĐ-CP. [BẢNG: Không tiêu đề] Mẫu 08B [BẢNG: Không tiêu đề] Nhà thầu phải cung cấp tất cả các thông tin trong HSĐX theo yêu cầu tại Bảng trên. Mẫu 08C [BẢNG: BẢNG KINH NGHIỆM CHUYÊN MÔN] Liệt kê theo trình tự thời gian quá trình công tác của chuyên gia, không cần liệt kê các công việc đã làm không phù hợp hoặc không liên quan với công việc đang yêu cầu. Nhà thầu phải cung cấp tất cả các thông tin được yêu cầu. Mẫu 09 HỢP ĐỒNG CUNG CẤP HÀNG HÓA, EPC, EP, PC, CHÌA KHÓA TRAO TAY KHÔNG HOÀN THÀNH DO LỖI CỦA NHÀ THẦU TRONG QUÁ KHỨ(1) Tên nhà thầu: ________________ Ngày: ______________________ Tên thành viên của nhà thầu liên danh (nếu có): _________________________ [BẢNG: Không tiêu đề] Ghi chú: (1) Nhà thầu phải kê khai chính xác, trung thực các hợp đồng cung cấp hàng hóa, EPC, EP, PC, chìa khóa trao tay không hoàn thành do lỗi của nhà thầu trong quá khứ; trường hợp Chủ đầu tư, tổ chuyên gia phát hiện nhà thầu có hợp đồng cung cấp hàng hóa, EPC, EP, PC, chìa khóa trao tay không hoàn thành do lỗi của nhà thầu trong quá khứ mà không kê khai thì nhà thầu được coi là có hành vi gian lận và HSĐX của nhà thầu sẽ bị loại. Trường hợp nhà thầu liên danh thì từng thành viên liên danh phải kê khai theo Mẫu này. Mẫu 10 TÌNH HÌNH TÀI CHÍNH CỦA NHÀ THẦU(1) Tên nhà thầu: ________________ Ngày: ______________________ [BẢNG: Không tiêu đề] Ghi chú: (1) Trường hợp nhà thầu liên danh thì từng thành viên liên danh phải kê khai theo Mẫu này. (2) Để xác định doanh thu bình quân hằng năm (không bao gồm thuế VAT), nhà thầu chia tổng doanh thu của các năm (không bao gồm thuế VAT) cho số năm dựa trên thông tin đã được cung cấp. Doanh thu hằng năm được tính bằng tổng doanh thu trong báo cáo tài chính của năm đó (chưa bao gồm thuế VAT). Doanh thu bình quân hằng năm (không bao gồm thuế VAT) = tổng doanh thu từng năm (không bao gồm thuế VAT) theo yêu cầu của HSYC/số năm. Trường hợp nhà thầu mới thành lập không đủ số năm theo yêu cầu của HSYC thì Doanh thu bình quân hằng năm (không bao gồm thuế VAT) được tính trên cơ sở số năm mà nhà thầu có số liệu tài chính. Nhà thầu phải nộp các hồ sơ như sau: Bản sao các báo cáo tài chính (các bảng cân đối kế toán bao gồm tất cả thuyết minh có liên quan, và các báo cáo kết quả kinh doanh) cho các năm như đã nêu trên, tuân thủ các điều kiện sau: 1. Phản ánh tình hình tài chính của nhà thầu hoặc thành viên liên danh (nếu là nhà thầu liên danh) mà không phải tình hình tài chính của một chủ thể liên kết như công ty mẹ liên kết với công ty con hoặc công ty liên kết với nhà thầu hoặc thành viên liên danh. 2. Các báo cáo tài chính phải hoàn chỉnh, đầy đủ nội dung theo quy định. 3. Các báo cáo tài chính phải tương ứng với các kỳ kế toán đã hoàn thành kèm theo bản chụp được chứng thực một trong các hồ sơ sau đây: - Biên bản kiểm tra quyết toán thuế; - Tờ khai tự quyết toán thuế (thuế giá trị gia tăng và thuế thu nhập doanh nghiệp) có xác nhận của cơ quan thuế về thời điểm đã nộp tờ khai; - hồ sơ chứng minh việc nhà thầu đã kê khai quyết toán thuế điện tử; - Văn bản xác nhận của cơ quan quản lý thuế (xác nhận số nộp cả năm) về việc thực hiện nghĩa vụ nộp thuế; - Báo cáo kiểm toán (nếu có); - Các hồ sơ khác. Các hồ sơ trên đây phải phù hợp với số liệu nhà thầu đã kê khai trên Hệ thống Thuế điện tử tại thời điểm đóng thầu. Mẫu 11A DANH SÁCH CÁC CÔNG TY, CÔNG TY THÀNH VIÊN ĐẢM NHẬN PHẦN CÔNG VIỆC CỦA GÓI THẦU(1) [BẢNG: Không tiêu đề] Ghi chú: (1) Trường hợp nhà thầu dự thầu là công ty mẹ (ví dụ như Tổng công ty) huy động công ty con, công ty thành viên thực hiện một phần công việc gói thầu thì phải kê khai cụ thể tại bảng này. Việc đánh giá kinh nghiệm thực hiện hợp đồng tương tự căn cứ vào giá trị, khối lượng công việc do công ty mẹ, công ty con đảm nhiệm trong gói thầu. Trường hợp nhà thầu dự thầu không phải là công ty mẹ thì không áp dụng Mẫu này. (2) Ghi cụ thể tên công ty con, công ty thành viên. (3) Ghi cụ thể phần công việc đảm nhận của công ty con, công ty thành viên. (4) Ghi cụ thể giá trị % công việc của công ty con, công ty thành viên đảm nhận so với giá thầu. Mẫu 11B PHẠM VI CÔNG VIỆC SỬ DỤNG thầu phụ(1) (chỉ áp dụng đối với dịch vụ liên quan) [BẢNG: Không tiêu đề] Ghi chú: (1) Trường hợp sử dụng thầu phụ để thực hiện dịch vụ liên quan thì nhà thầu kê khai theo Mẫu này. Đối với gói thầu của dự án thuộc lĩnh vực khoa học, kỹ thuật, đổi mới sáng tạo và chuyển đổi số tổ chức đấu thầu trong nước, nhà thầu trong nước được sử dụng thầu phụ là nhà thầu nước ngoài đối với phần công việc đặc thù mà nhà thầu trong nước chưa thực hiện được hoặc cần chuyển giao kỹ thuật theo quy định tại Khoản 4 Điều 11 Luật Đấu thầu. (2) Nhà thầu ghi cụ thể tên thầu phụ. Trường hợp khi dự thầu chưa xác định được cụ thể danh tính của thầu phụ thì không phải kê khai vào cột này mà chỉ kê khai vào cột \"Phạm vi công việc”. Nếu nhà thầu trúng thầu thì khi huy động thầu phụ thực hiện công việc đã kê khai phải được sự chấp thuận của Chủ đầu tư. (3) Nhà thầu ghi cụ thể tên hạng mục công việc dành cho thầu phụ. (4) Nhà thầu ghi cụ thể khối lượng công việc dành cho thầu phụ. (5) Nhà thầu ghi giá trị % công việc ước tính mà từng thầu phụ đảm nhận so với giá thầu. (6) Nhà thầu ghi cụ thể số hợp đồng hoặc văn bản thỏa thuận sử dụng thầu phụ và phải nộp kèm theo bản gốc hoặc bản chụp được chứng thực các hồ sơ đó. Trường hợp chưa xác định được tên thầu phụ thì để trống cột này. Phần 2. YÊU VẦU VỀ KỸ THUẬT Chương IV. YÊU CẦU VỀ KỸ THUẬT CỦA HÀNG HÓA Mục 1. Yêu cầu về kỹ thuật Yêu cầu về kỹ thuật bao gồm yêu cầu kỹ thuật (mang tính kỹ thuật thuần túy) và các yêu cầu khác liên quan đến việc cung cấp hàng hóa (trừ giá). Yêu cầu về kỹ thuật phải được nêu đầy đủ, rõ ràng và cụ thể để làm cơ sở cho nhà thầu lập HSĐX. Yêu cầu về mặt kỹ thuật bao gồm các nội dung cơ bản như sau: 1. 1. Giới thiệu chung về dự án/dự toán mua sắm, gói thầu Khoản này nêu thông tin tóm tắt về dự án/dự toán mua sắm và gói thầu như địa điểm thực hiện dự án/dự toán mua sắm, quy mô của dự án/dự toán mua sắm, yêu cầu về cung cấp hàng hóa thuộc gói thầu, thời gian thực hiện gói thầu và những thông tin khác tùy theo tính chất và yêu cầu của gói thầu. 1. 2. Yêu cầu về kỹ thuật Yêu cầu về kỹ thuật bao gồm yêu cầu kỹ thuật chung và yêu cầu kỹ thuật chi tiết đối với hàng hóa thuộc phạm vi cung cấp của gói thầu, cụ thể: a) Yêu cầu kỹ thuật chung là các yêu cầu về chủng loại, tiêu chuẩn hàng hóa và các yêu cầu về kiểm tra, thử nghiệm, đóng gói, vận chuyển, điều kiện khí hậu tại nơi hàng hóa được sử dụng. Tùy thuộc vào sự phức tạp của hàng hóa, các yêu cầu kỹ thuật chung được nêu cho tất cả các hàng hóa hoặc cho từng loại hàng hóa riêng biệt. b) Yêu cầu kỹ thuật chi tiết như tính năng, thông số kỹ thuật, các bản vẽ, catalô, các thông số bảo hành. .. được nêu cho từng loại hàng hóa. Khi nêu yêu cầu, các thông số kỹ thuật có thể được mô tả dưới hình thức bảng biểu. Mục đích của phần Thông số kỹ thuật là xác định các đặc tính kỹ thuật của hàng hóa và dịch vụ liên quan theo yêu cầu của gói thầu. Chủ đầu tư phải soạn thảo chi tiết phần Thông số kỹ thuật trên cơ sở đánh giá đến những yếu tố sau: - Thông số kỹ thuật bao gồm các tiêu chuẩn làm căn cứ cho Chủ đầu tư, tổ chuyên gia xác minh tính đáp ứng về mặt kỹ thuật và đánh giá HSĐX. Do đó, nếu thông số kỹ thuật được xác định đầy đủ, rõ ràng thì sẽ giúp nhà thầu chuẩn bị tốt HSĐX và có tính đáp ứng cao, đồng thời giúp Chủ đầu tư, tổ chuyên gia nghiên cứu, đánh giá HSĐX. - Thông số kỹ thuật yêu cầu tất cả các hàng hóa và vật liệu, vật tư sử dụng cho hàng hóa phải mới, chưa qua sử dụng, sử dụng toàn bộ các cải tiến mới nhất về thiết kế và vật liệu, trừ trường hợp có quy định cụ thể khác trong hợp đồng. - Thông số kỹ thuật phải đủ khái quát để tránh gây hạn chế liên quan đến các yêu cầu tay nghề và vật tư thiết bị thường được sử dụng để sản xuất các hàng hóa thuộc loại tương tự. - Thông số kỹ thuật phải mô tả đầy đủ các yêu cầu liên quan và không giới hạn ở những điểm sau đây: + Các tiêu chuẩn về vật liệu, vật tư và tay nghề cần thiết để sản xuất chế tạo hàng hóa; + Các yêu cầu chi tiết về thử nghiệm (loại hình và số lần thử); + Các công việc bổ sung khác và/hoặc các dịch vụ liên quan cần thiết để giao hàng/hoàn thành đầy đủ; + Các hoạt động cụ thể mà nhà thầu sẽ phải thực hiện và sự tham gia của Chủ đầu tư; + Danh sách các yêu cầu bảo đảm chức năng vận hành cụ thể thuộc phạm vi bảo hành và quy định bồi thường thiệt hại nếu các yêu cầu bảo đảm nói trên không được thực hiện. - Thông số kỹ thuật phải nêu rõ tất cả các đặc tính và yêu cầu về công năng và kỹ thuật, bao gồm các giá trị tối đa và tối thiểu được bảo đảm hoặc được chấp nhận, tùy theo trường hợp. Chủ đầu tư được nêu cụ thể ký mã hiệu (nếu có), nhãn hiệu, hãng sản xuất, xuất xứ của hàng hóa. - Tiến độ giao hàng, ngày hoàn thành dịch vụ theo yêu cầu tại Mẫu 05 Chương III. Nếu Chủ đầu tư yêu cầu nhà thầu cung cấp trong HSĐX của mình một phần hoặc toàn bộ các thông số kỹ thuật, các bảng biểu kỹ thuật hoặc các thông tin kỹ thuật khác thì Chủ đầu tư phải quy định rõ tính chất và mức độ thông tin yêu cầu và cách trình bày các thông tin đó trong HSĐX. [Nếu yêu cầu cung cấp bản tóm tắt thông số kỹ thuật thì Chủ đầu tư phải ghi thông tin vào bảng dưới đây. Nhà thầu sẽ soạn một bảng tương tự để chứng minh hàng hóa do nhà thầu chào tuân thủ với các yêu cầu đó]. Tóm tắt thông số kỹ thuật của hàng hóa, dịch vụ liên quan. Hàng hóa, dịch vụ liên quan phải tuân thủ các thông số kỹ thuật và tiêu chuẩn sau đây: [BẢNG: Không tiêu đề] Thông số kỹ thuật chi tiết và các tiêu chuẩn chi tiết (khi cần thiết). [Mô tả chi tiết thông số kỹ thuật] _________________________ 1. 3. Các yêu cầu khác - Các yêu cầu khác về kỹ thuật bao gồm yêu cầu về phương thức thanh toán, yêu cầu về cung cấp tài chính (nếu có), yêu cầu về dịch vụ liên quan như lắp đặt, duy tu, bảo dưỡng, sửa chữa ban đầu, bảo hiểm lắp đặt, bảo hiểm sửa chữa hoặc cung cấp các dịch vụ sau bán hàng khác như đào tạo, chuyển giao kỹ thuật. .. (nếu có). Các yêu cầu này phải được nêu chi tiết để nhà thầu chuẩn bị HSĐX. - Đấu thầu bền vững: có thể đưa ra yêu cầu về hàng hóa thân thiện môi trường, xã hội, sản phẩm, dịch vụ được chứng nhận nhãn sinh thái, nhãn năng lượng và tương đương (nếu có) như: tiết kiệm năng lượng hoặc tiết kiệm nước khi sử dụng, khí thải ít độc hại, không có chất độc hại, phá hủy môi trường; hàng hóa sản xuất không vi phạm trách nhiệm xã hội hoặc từ nguồn nguyên liệu bền vững, hữu cơ, vật liệu tái chế; sử dụng vật liệu xanh để đóng gói hàng hóa; tiết kiệm nhiên liệu, giảm thiểu ô nhiễm tiếng ồn, sử dụng container có thể tái sử dụng để vận chuyển hàng hóa; mức độ xả thải, rác thải, ô nhiễm môi trường, giảm thiểu tác động môi trường và cộng đồng xung quanh; cam kết thu hồi hoặc tái chế khi hàng hóa hết sử dụng. .. - Tùy theo từng gói thầu có thể yêu cầu nhà thầu chào phương án thay thế ngoài phương án chính theo yêu cầu của HSYC, trong đó cần quy định rõ phương án thay thế của nhà thầu chỉ được đánh giá trong quá trình thương thảo hợp đồng (nếu có) khi nhà thầu được đề xuất trúng thầu theo phương án chính hoặc quy định trong trường hợp kết quả đánh giá HSĐX theo phương án chính không có nhà thầu nào đáp ứng yêu cầu của HSYC thì mới đánh giá phương án thay thế của nhà thầu. Mục 2. Bản vẽ HSYC này gồm có các bản vẽ trong danh mục sau đây [trường hợp không có bản vẽ kèm theo thì phải ghi rõ “Không có bản vẽ”]: [BẢNG: Không tiêu đề] Trường hợp có bản vẽ thì phải đính kèm theo bản vẽ. Mục 3. Kiểm tra và thử nghiệm Các kiểm tra và thử nghiệm cần tiến hành gồm có: ____ [ghi danh sách các kiểm tra và thử nghiệm]. Phần 3. ĐIỀU KIỆN HỢP ĐỒNG VÀ BIỂU MẪU HỢP ĐỒNG Căn cứ quy mô, tính chất, loại hợp đồng của gói thầu, Chủ đầu tư, tổ chuyên gia sử dụng các Chương VI, VII, VIII của Mẫu E-HSMT mua sắm hàng hóa một giai đoạn một túi hồ sơ ban hành kèm theo Thông tư số 79/2025/TT-BTC để xây dựng các Chương V. ĐIỀU KIỆN CHUNG, Chương VI. ĐIỀU KIỆN CỤ THỂ, Chương VII. BIỂU MẪU HỢP ĐỒNG cho phù hợp với quy định của Luật Đấu thầu, Nghị định số 214/2025/NĐ-CP. Trong quá trình thực hiện, trường hợp Thông tư số 79/2025/TT-BTC được sửa đổi, bổ sung hoặc thay thế thì áp dụng theo văn bản quy phạm pháp luật sửa đổi, bổ sung hoặc thay thế Thông tư số 79/2025/TT-BTC. Lưu ý: khi sử dụng cần thay đổi các thuật ngữ cho phù hợp như sau: - E-ĐKC thành ĐKC; - E-ĐKCT thành ĐKCT; - E-HSMT thành HSYC; - E-HSDT thành HSĐX.", "metadata": {"source_file": "01B. Mẫu HSYC hàng hóa.docx", "file_type": "bidding_document", "document_category": "goods", "extracted_at": "2025-10-30T19:54:40.566838", "file_size_bytes": 218998, "project_name": "/dự toán mua sắm]. 2. Nguồn vốn để thực hiện gói thầu: [Ghi rõ nguồn vốn đã được xác định hoặc phê duyệt; trường hợp sử dụng vốn ODA, vốn vay ưu đãi n", "package_name": "MUA SẮM HÀNG HÓA (Ban hành kèm theo Thông tư số 80/2025/TT-BTC ngày 08 tháng 8 năm 2025 của Bộ trưởng Bộ Tài chính) HỒ SƠ YÊU CẦU MUA SẮM HÀNG HÓA [BẢ", "bidding_method": "CHỈ ĐỊNH THẦU", "owner": "___[Ghi tên, địa chỉ Chủ đầu tư] mời nhà thầu nhận HSYC gói thầu___ [Ghi tên gói thầu theo kế hoạch lựa chọn nhà thầu được duyệt] thuộc__ [Ghi tên dự", "chunk_index": 0, "char_count": 97351, "word_count": 21637, "paragraph_count": 1, "doc_type": "bidding", "processed_at": "2025-10-30T19:54:40.658178", "total_chunks": 1, "document_type": "bidding_document", "file_path": "/home/sakana/Code/RAG-bidding/data/raw/Ho so moi thau/1. Mẫu HSYC/01B. Mẫu HSYC hàng hóa.docx", "bidding_type": "construction", "extraction_metadata": {"source_file": "01B. Mẫu HSYC hàng hóa.docx", "file_type": "bidding_document", "document_category": "goods", "extracted_at": "2025-10-30T19:54:40.566838", "file_size_bytes": 218998, "project_name": "/dự toán mua sắm].", "package_name": "MUA SẮM HÀNG HÓA", "bidding_method": "CHỈ ĐỊNH THẦU", "owner": "___[Ghi tên, địa chỉ Chủ đầu tư] mời nhà thầu nhận HSYC gói thầu___ [Ghi tên gói thầu theo kế hoạch lựa chọn nhà thầu được duyệt] thuộc__ [Ghi tên dự án/dự toán mua sắm]."}, "parsing_metadata": {"bidding_type": null, "detected_sections": {"general_info": [], "technical_requirements": [], "evaluation_criteria": [], "contract_conditions": [], "bidding_process": [], "forms": [], "drawings": [], "bill_of_quantities": []}, "document_info": {"project_name": "/dự toán mua sắm]. 2. nguồn vốn để thực hiện gói thầu: [ghi rõ nguồn vốn đã được xác định hoặc phê d", "package_name": "mua sắm hàng hóa (ban hành kèm theo thông tư số 80/2025/tt-btc ngày 08 tháng 8 năm 2025 của bộ trưởn", "owner": "___[ghi tên, địa chỉ chủ đầu tư] mời nhà thầu nhận hsyc gói thầu___ [ghi tên gói thầu theo kế hoạch"}, "statistics": {}}, "contract_value": "không tính bằng VND thì quy đổi sang VND theo tỷ g", "duration": "gói thầu là: ___ [Ghi thời gian cụ thể theo kế hoạ", "hierarchy": "HỒ SƠ MỜI THẦU > Phần 1 > Chương I > Mục 1 > Điều 16", "section_type": "scope_of_work", "has_tables": true, "table_count": 1, "table_types": ["bill_of_quantities"], "contains_forms": true, "contains_technical_specs": true, "contains_evaluation": true, "contains_monetary_values": true, "monetary_value_count": 26, "contains_time_references": true, "time_reference_count": 70, "entities": {"locations": ["các điểm a, b, c, d, e và g Khoản 1 Điều 5 của Luật", "các điểm a, b Khoản 2 và các điểm d, e Khoản 1 Điều", "Khoản 3 Điều 5 của Luật Đấu thầu. Trường hợp pháp l", "Mục 8 Chương này; 5. Đề xuất về giá theo các bảng g", "Mẫu 4. 1 (4. 1A hoặc 4. 1B hoặc 4. 1C) hoặc Mẫu 4.", "thời điểm 28 ngày trước ngày có thời điểm đóng thầu", "Chương IV và chào giá cho tất cả các công việc nêu", "Chương III. Mục 8. hồ sơ chứng minh sự phù hợp của", "Việt Nam. Nhà thầu có thể đính kèm hoặc không đính", "Chương IV. 4. hồ sơ chứng minh sự phù hợp của hàng", "Chương IV. 5. Nhà thầu phải cung cấp đầy đủ danh mụ", "Mục 6 Chương I phải được ký bởi người đại diện hợp", "bên cạnh hoặc tại trang đó của người ký đơn dự thầu", "thầu 1. HSĐX do nhà thầu nộp trực tiếp hoặc gửi đến", "thầu: Chủ đầu tư tiến hành mở thầu bao gồm các nội", "hồ sơ và đọc rõ các thông tin về tên nhà thầu: - Th", "thầu bao gồm các thông tin quy định tại điểm a và đ", "thầu phải được ký xác nhận bởi đại diện của Chủ đầu", "Chương II. 2. Trong quá trình đánh giá, Chủ đầu tư", "cho nhà thầu chuẩn bị HSĐX] Mục 15. Thông báo kết q", "thời điểm ký kết, HSĐX của nhà thầu trúng thầu còn", "thời điểm ký kết hợp đồng, nhà thầu trúng thầu phải", "Nghị quyết của Quốc hội hoặc văn bản quy phạm pháp", "Mục 6 Chương I; c) Kiểm tra sự thống nhất nội dung", "Mục 9 Chương I; d) Có thỏa thuận liên danh (trong t", "Mẫu 4. 1 (4. 1A hoặc 4. 1B hoặc 4. 1C) hoặc Mẫu 4.", "Mục 3 Chương I. e) Trong thời hạn 03 năm trước thời", "thời điểm nhân sự thực hiện hành vi vi phạm) bị Tòa", "Mục 2. 1, 2. 2 và 2. 3. Năng lực và kinh nghiệm của", "Mục này căn cứ theo yêu cầu của từng gói thầu cụ th", "Bảng số 01 (đối với nhà thầu không phải là nhà sản", "Việt Nam] tại ngày ký hợp đồng tương tự đó. Trường", "sản xuất tự sản xuất ra hàng hóa hoặc tham gia vào", "Khoản 1 Điều 133 của Nghị định số 214/2025/NĐ-CP th", "báo cáo tài chính của nhà thầu. Trường hợp thời điể", "báo cáo tài chính năm trước của năm Y (năm Y-1). Ví", "bảo cáo tài chính năm 2022. Đối với nhà thầu là hộ", "lên thì cách tính doanh thu như sau: Yêu cầu tối th", "Thông tư số 14/2018/TT-BYT. Trong quá trình thực hi", "các loại hàng hóa chính của gói thầu (phải nêu rõ c", "tất cả các loại hàng hóa của gói thầu, trong đó ghi", "Mục 4 Bảng số 02 Chương này. Việc đánh giá kinh ngh", "hợp đồng cung cấp hàng hóa tương tự (tương ứng với", "có mã HS 9018. 90. 30, trong đó đã bàn giao 1 chiếc", "sản xuất tự sản xuất ra hàng hóa hoặc tham gia vào", "Khoản 1 Điều 133 của Nghị định số 214/2025/NĐ-CP th", "Khoản 4 Điều 6 của Nghị định số 214/2025/NĐ-CP khôn", "báo cáo tài chính của nhà thầu. Trường hợp thời điể", "báo cáo tài chính năm trước của năm Y (năm Y-1). Ví", "bảo cáo tài chính năm 2022. Đối với nhà thầu là hộ", "Khoản 4 Điều 6 của Nghị định số 214/2025/NĐ-CP khôn", "lên thì cách tính doanh thu như sau: Yêu cầu tối th", "các loại hàng hoá chính của gói thầu (phải nêu rõ c", "tất cả các loại hàng hoá của gói thầu, tương ứng vớ", "Mục 4 Bảng số 01 Chương này. Việc đánh giá kinh ngh", "hợp đồng cung cấp hàng hóa tương tự (tương ứng với", "cột này được Chủ đầu tư xác định theo nguyên tắc tạ", "cột này được Chủ đầu tư xác định theo nguyên tắc nê", "ghi chú số (11) Bảng số 01 Chương này. (4) Giá trị", "cột này được Chủ đầu tư xác định theo nguyên tắc nê", "ghi chú số (10) Bảng số 02 Chương này. 2. 2. Tiêu c", "Khoản 1 Điều 133 của Nghị định số 214/2025/NĐ-CP. K", "số năm tối thiểu nhân sự thực hiện các công việc tư", "Mục 14 Chương I; Chương III. BIỂU MẪU Mẫu 01A ĐƠN D", "thời điểm nhân sự thực hiện hành vi vi phạm) bị tòa", "và các hành vi vi phạm quy định khác của pháp luật", "các hồ sơ khác liên quan có phân công trách nhiệm c", "và các hành vi vi phạm quy định khác của pháp luật", "Mẫu 4. 1 (4. 1A hoặc 4. 1B hoặc 4. 1C) hoặc Mẫu 4.", "các cột: (1), (2), (3), (4), (5), (6), (7), (8), (9", "Chương IV. - Nhà thầu điền từ cột (11), (12), (13):", "thời điểm 28 ngày trước ngày có thời điểm đóng thầu", "Chương IV cho phù hợp. - Cột (7), (8): Nhà thầu chà", "các cột: (1), (2), (3), (4), (5), (6), (7), (8), (9", "Chương IV. - Nhà thầu điền từ cột (11), (12), (13):", "thời điểm 28 ngày trước ngày có thời điểm đóng thầu", "Chương IV cho phù hợp. - Cột (7), (8): Nhà thầu chà", "chào chi phí dự phòng. Đại diện hợp pháp của nhà th", "các cột: (1), (2), (3), (4), (5), (6), (7), (8), (9", "Chương IV. - Nhà thầu điền từ cột (11), (12), (13):", "thời điểm 28 ngày trước ngày có thời điểm đóng thầu", "Chương IV cho phù hợp. - Cột (7), (8): Nhà thầu chà", "chào chi phí dự phòng. Đại diện hợp pháp của nhà th", "Việt Nam [BẢNG: Không tiêu đề] Ghi chú: - Chủ đầu t", "Chương IV. - Nhà thầu điền các cột sau: Cột (11): N", "phải nộp trong trường hợp nhà thầu được trao hợp đồ", "Chương IV. - Nhà thầu điền các cột sau: Cột (11): N", "Việt Nam để vận chuyển hàng hóa đến địa điểm theo y", "Chương IV cho phù hợp. - Cột (7) (8): Nhà thầu chào", "Việt Nam [BẢNG: Không tiêu đề] Ghi chú: - Chủ đầu t", "Chương IV. - Nhà thầu điền các cột sau: Cột (11): N", "phải nộp trong trường hợp nhà thầu được trao hợp đồ", "Chương IV. - Nhà thầu điền các cột sau: Cột (11): N", "Việt Nam để vận chuyển hàng hóa đến địa điểm theo y", "Chương IV cho phù hợp. - Cột (7) (8): Nhà thầu chào", "chào chi phí dự phòng. Đại diện hợp pháp của nhà th", "Việt Nam [BẢNG: Không tiêu đề] Ghi chú: - Chủ đầu t", "Chương IV. - Nhà thầu điền các cột sau: Cột (11): N", "phải nộp trong trường hợp nhà thầu được trao hợp đồ", "Chương IV. - Nhà thầu điền các cột sau: Cột (11): N", "Việt Nam để vận chuyển hàng hóa đến địa điểm theo y", "Chương IV cho phù hợp. - Cột (7) (8): Nhà thầu chào", "chào chi phí dự phòng. Đại diện hợp pháp của nhà th", "Mục 2. 1 Chương II để làm cơ sở đánh giá. Mẫu 07B [", "sản xuất (gọi chung là nhà máy): ____ [Điền số nhà", "Mục 2. 2 Chương II và phải chứng minh khả năng sẵn", "Khoản 1 Điều 133 của Nghị định số 214/2025/NĐ-CP. [", "Bảng trên. Mẫu 08C [BẢNG: BẢNG KINH NGHIỆM CHUYÊN M", "số năm mà nhà thầu có số liệu tài chính. Nhà thầu p", "thời điểm đóng thầu. Mẫu 11A DANH SÁCH CÁC CÔNG TY,", "bảng này. Việc đánh giá kinh nghiệm thực hiện hợp đ", "Khoản 4 Điều 11 Luật Đấu thầu. (2) Nhà thầu ghi cụ", "cho nhà thầu lập HSĐX. Yêu cầu về mặt kỹ thuật bao", "nơi hàng hóa được sử dụng. Tùy thuộc vào sự phức tạ", "những điểm sau đây: + Các tiêu chuẩn về vật liệu, v", "Mẫu 05 Chương III. Nếu Chủ đầu tư yêu cầu nhà thầu"]}, "content_stats": {"char_count": 97351, "word_count": 21637, "line_count": 1, "paragraph_count": 1, "sentence_count": 705}}, "chunk_id": "chunk_000", "char_count": 97351, "level": "paragraph", "hierarchy": [], "parent_id": null, "parsed_sections": [], "tables": [{"start_line": 0, "end_line": 1, "content": "Mẫu 1B HỒ SƠ YÊU CẦU GÓI THẦU MUA SẮM HÀNG HÓA (Ban hành kèm theo Thông tư số 80/2025/TT-BTC ngày 08 tháng 8 năm 2025 của Bộ trưởng Bộ Tài chính) HỒ SƠ YÊU CẦU MUA SẮM HÀNG HÓA [BẢNG: Không tiêu đề] [BẢNG: Không tiêu đề] TỪ NGỮ VIẾT TẮT [BẢNG: Không tiêu đề] Phần 1. THỦ TỤC CHỈ ĐỊNH THẦU Chương I. CHỈ DẪN NHÀ THẦU Mục 1. Phạm vi gói thầu 1. Chủ đầu tư ___[Ghi tên, địa chỉ Chủ đầu tư] mời nhà thầu nhận HSYC gói thầu___ [Ghi tên gói thầu theo kế hoạch lựa chọn nhà thầu được duyệt] thuộc__ [Ghi tên dự án/dự toán mua sắm]. 2. Nguồn vốn để thực hiện gói thầu: [Ghi rõ nguồn vốn đã được xác định hoặc phê duyệt; trường hợp sử dụng vốn ODA, vốn vay ưu đãi nước ngoài thì phải ghi rõ tên nhà tài trợ và cơ cấu nguồn vốn, bao gồm vốn tài trợ, vốn đối ứng trong nước]. 3. Thời gian thực hiện gói thầu là: ___ [Ghi thời gian cụ thể theo kế hoạch lựa chọn nhà thầu được duyệt], được tính từ ngày hợp đồng có hiệu lực đến ngày nghiệm thu hàng hóa (bao gồm cả dịch vụ liên quan (nếu có)), không bao gồm thời gian hoàn thành nghĩa vụ bảo hành. Mục 2. Hành vi bị cấm trong đấu thầu Hành vi bị cấm trong đấu thầu là hành vi quy định tại Điều 16 của Luật Đấu thầu. Mục 3. Tư cách hợp lệ của nhà thầu 1. Nhà thầu là tổ chức có tư cách hợp lệ khi đáp ứng quy định tại các điểm a, b, c, d, e và g Khoản 1 Điều 5 của Luật Đấu thầu. 2. Nhà thầu là hộ kinh doanh có tư cách hợp lệ khi đáp ứng quy định tại các điểm a, b Khoản 2 và các điểm d, e Khoản 1 Điều 5 của Luật Đấu thầu. 3. Nhà thầu là cá nhân, nhóm cá nhân chào thầu sản phẩm đổi mới sáng tạo của mình có tư cách hợp lệ khi đáp ứng quy định tại Khoản 3 Điều 5 của Luật Đấu thầu. Trường hợp pháp luật có liên quan quy định nhà thầu dự thầu, thực hiện hợp đồng phải độc lập với các tổ chức, cá nhân khác thì phải tuân thủ quy định đó. Mục 4. Làm rõ, sửa đổi HSYC 1. Trường hợp nhà thầu cần làm rõ HSYC, nhà thầu gửi văn bản đến Chủ đầu tư trong thời hạn tối thiểu 03 ngày làm việc trước ngày có thời điểm đóng thầu để đánh giá, xử lý. 2. Trường hợp Chủ đầu tư sửa đổi HSYC, Chủ đầu tư có trách nhiệm gửi quyết định sửa đổi và các nội dung sửa đổi tới nhà thầu. Thời gian gửi văn bản sửa đổi HSYC đến nhà thầu là ___ [Ghi số ngày cụ thể, tối thiểu 03 ngày làm việc trước ngày có thời điểm đóng thầu và bảo đảm đủ thời gian để nhà thầu hoàn chỉnh HSĐX]; trường hợp không bảo đảm đủ thời gian như nêu trên thì phải gia hạn thời điểm đóng thầu. Mục 5. Chi phí, đồng tiền, ngôn ngữ khi dự thầu 1. Nhà thầu phải chịu mọi chi phí liên quan đến quá trình dự thầu. 2. Đồng tiền dự thầu và đồng tiền thanh toán là VND. 3. HSĐX cũng như tất cả văn bản và hồ sơ liên quan đến HSĐX được viết bằng tiếng Việt. Các hồ sơ bổ trợ trong HSĐX có thể được viết bằng ngôn ngữ khác, đồng thời kèm theo bản dịch sang tiếng Việt. Trường hợp thiếu bản dịch, Chủ đầu tư có thể yêu cầu nhà thầu gửi bổ sung (nếu cần thiết). Mục 6. Thành phần của HSĐX HSĐX do nhà thầu chuẩn bị phải bao gồm: 1. Đơn dự thầu theo Mẫu 01A hoặc Mẫu 01B Chương III; 2. Thỏa thuận liên danh nếu là nhà thầu liên danh theo Mẫu 03 Chương III; 3. hồ sơ chứng minh tư cách hợp lệ, năng lực và kinh nghiệm của nhà thầu, của người ký đơn dự thầu; 4. hồ sơ chứng minh sự phù hợp của hàng hóa và dịch vụ liên quan theo quy định tại Mục 8 Chương này; 5. Đề xuất về giá theo các bảng giá thầu quy định tại Mẫu 4. 1 (4. 1A hoặc 4. 1B hoặc 4. 1C) hoặc Mẫu 4. 2 (4. 2A hoặc 4. 2B hoặc 4. 2C) Chương III; 6. Các nội dung khác ___ [Nêu các nội dung khác tùy theo tính chất, yêu cầu của gói thầu]. Mục 7. giá thầu 1. giá thầu là giá do nhà thầu chào trong đơn dự thầu bao gồm toàn bộ các chi phí (chưa tính giảm giá) để thực hiện gói thầu theo yêu cầu của HSYC, kể cả các loại thuế, phí, lệ phí (nếu có) áp theo thuế suất, mức phí, lệ phí tại thời điểm 28 ngày trước ngày có thời điểm đóng thầu. 2. Nhà thầu chào giá: [Chủ đầu tư quy định theo Mẫu 4. 1A hoặc 4. 1B hoặc 4. 1C hoặc 4. 2A hoặc 4. 2B hoặc 4. 2C Chương III] 3. Nhà thầu phải nộp HSĐX cho toàn bộ công việc được mô tả tại Chương IV và chào giá cho tất cả các công việc nêu trong bảng giá tương ứng quy định tại Chương III. Mục 8. hồ sơ chứng minh sự phù hợp của hàng hóa, dịch vụ liên quan 1. Yêu cầu về hồ sơ để chứng minh năng lực thực hiện hợp đồng của nhà thầu: ___ [Chủ đầu tư ghi “Không yêu cầu giấy phép bán hàng, giấy ủy quyền bán hàng của nhà sản xuất hoặc của đại lý phân phối hoặc giấy chứng nhận quan hệ đối tác hoặc giấy cam kết hỗ trợ kỹ thuật, bảo hành của nhà sản xuất hoặc của đại lý phân phối hoặc hồ sơ khác có giá trị tương đương” hoặc “Có yêu cầu giấy phép bán hàng, giấy ủy quyền bán hàng của nhà sản xuất hoặc của đại lý phân phối hoặc giấy chứng nhận quan hệ đối tác hoặc giấy cam kết hỗ trợ kỹ thuật, bảo hành của nhà sản xuất hoặc của đại lý phân phối hoặc hồ sơ khác có giá trị tương đương (sau đây gọi là Giấy phép bán hàng)” căn cứ vào tính chất của hàng hóa như sau: Đối với hàng hóa thông thường, thông dụng, sẵn có trên thị trường, đã được tiêu chuẩn hóa và được bảo hành theo quy định của nhà sản xuất thì không yêu cầu nhà thầu phải nộp giấy phép bán hàng, giấy ủy quyền bán hàng của nhà sản xuất hoặc của đại lý phân phối hoặc giấy chứng nhận quan hệ đối tác hoặc giấy cam kết hỗ trợ kỹ thuật, bảo hành của nhà sản xuất hoặc của đại lý phân phối hoặc hồ sơ khác có giá trị tương đương. Đối với hàng hóa đặc thù, phức tạp cần sự khẳng định của nhà sản xuất, nhà cung cấp để đảm bảo tính khả thi trong việc cung cấp hàng hóa khi nhà thầu trúng thầu và cần gắn với trách nhiệm của nhà sản xuất trong việc cung cấp các dịch vụ sau bán hàng như lắp đặt, bảo trì, đào tạo và các dịch vụ liên quan khác, trong HSYC có thể yêu cầu nhà thầu dự thầu phải cung cấp giấy phép bán hàng, giấy ủy quyền bán hàng của nhà sản xuất hoặc của đại lý phân phối hoặc giấy chứng nhận quan hệ đối tác hoặc giấy cam kết hỗ trợ kỹ thuật, bảo hành của nhà sản xuất hoặc của đại lý phân phối hoặc hồ sơ khác có giá trị tương đương. Trường hợp có yêu cầu về giấy phép bán hàng, giấy ủy quyền bán hàng của nhà sản xuất hoặc của đại lý phân phối hoặc giấy chứng nhận quan hệ đối tác hoặc giấy cam kết hỗ trợ kỹ thuật, bảo hành của nhà sản xuất hoặc của đại lý phân phối hoặc hồ sơ khác có giá trị tương đương, Chủ đầu tư quy định nội dung sau: “Trường hợp nhà thầu không tự sản xuất hoặc chế tạo hàng hóa được chào trong HSĐX của mình thì nhà thầu phải nộp giấy phép bán hàng, giấy ủy quyền bán hàng của nhà sản xuất hoặc của đại lý phân phối hoặc giấy chứng nhận quan hệ đối tác hoặc giấy cam kết hỗ trợ kỹ thuật, bảo hành của nhà sản xuất hoặc của đại lý phân phối hoặc hồ sơ khác có giá trị tương đương nhằm chứng minh nhà thầu được ủy quyền hợp lệ của nhà sản xuất, đại lý phân phối để cung cấp hàng hóa đó ở Việt Nam. Nhà thầu có thể đính kèm hoặc không đính kèm hồ sơ này trong HSĐX, kể cả trường hợp HSYC có yêu cầu nhà thầu phải có hồ sơ này. Việc nhà thầu không đính kèm hồ sơ nêu trên không phải là lý do loại bỏ nhà thầu. Nhà thầu vẫn được tiếp tục đánh giá, đánh giá để được xét thầu trúng thầu. Trường hợp nhà thầu trúng thầu, nhà thầu phải xuất trình được hồ sơ nêu trên trước khi ký hợp đồng và chịu trách nhiệm về tính chính xác của những hồ sơ, thông tin do mình cung cấp. Trường hợp nhà thầu không xuất trình được giấy phép bán hàng, giấy ủy quyền bán hàng của nhà sản xuất hoặc của đại lý phân phối hoặc giấy chứng nhận quan hệ đối tác hoặc giấy cam kết hỗ trợ kỹ thuật, bảo hành của nhà sản xuất hoặc của đại lý phân phối hoặc hồ sơ khác có giá trị tương đương để ký hợp đồng thì nhà thầu đó không được đánh giá chỉ định thầu. Trường hợp nhà thầu đã được xét thầu trúng thầu nhưng nhà sản xuất, đại lý, nhà phân phối không cung cấp Giấy phép bán hàng mà không có lý do chính đáng và nếu nhà thầu vẫn chứng minh được khả năng bảo hành, bảo trì, duy tu, bảo dưỡng, sửa chữa, cung cấp phụ tùng thay thế hoặc cung cấp các dịch vụ sau bán hàng khác thì vẫn được ký hợp đồng mà không cần xuất trình Giấy phép bán hàng”]. 2. Tất cả vật tư, thiết bị và dịch vụ liên quan được cung cấp theo hợp đồng phải có xuất xứ rõ ràng, hợp pháp. Nhà thầu phải tuân thủ theo ký mã hiệu (nếu có), nhãn hiệu, xuất xứ và hãng sản xuất của vật tư, thiết bị nêu trong HSYC. Để chứng minh tính hợp lệ của hàng hóa, dịch vụ liên quan, Chủ đầu tư có thể yêu cầu nhà thầu cung cấp bằng chứng về xuất xứ của các vật tư, thiết bị bao gồm các hồ sơ sau ___ [nêu yêu cầu về hồ sơ chứng minh tính hợp lệ của hàng hoá]. 3. Để chứng minh sự phù hợp của hàng hóa và dịch vụ liên quan so với yêu cầu của HSYC, nhà thầu phải cung cấp các hồ sơ là một phần của HSĐX chứng minh rằng hàng hóa đáp ứng thông số và tiêu chuẩn kỹ thuật quy định tại Chương IV. 4. hồ sơ chứng minh sự phù hợp của hàng hóa và dịch vụ liên quan có thể là hồ sơ, giấy tờ, bản vẽ, số liệu được mô tả chi tiết theo từng khoản mục về đặc tính kỹ thuật và tính năng sử dụng cơ bản của hàng hóa và dịch vụ liên quan, qua đó chứng minh sự đáp ứng cơ bản của hàng hóa và dịch vụ đối với thông số kỹ thuật và một bảng kê những điểm sai khác và ngoại lệ (nếu có) so với quy định tại Chương IV. 5. Nhà thầu phải cung cấp đầy đủ danh mục, giá cả, nhà cung cấp vật tư, phụ tùng thay thế, dụng cụ chuyên dùng, vật tư tiêu hao. .. (sau đây gọi là vật tư, phụ tùng thay thế) cần thiết để bảo đảm sự vận hành đúng quy cách và liên tục của hàng hóa trong thời hạn ___ [ghi thời hạn hoạt động dự kiến của hàng hóa] sau khi hàng hóa bắt đầu được đưa vào sử dụng. Mục 9. Hiệu lực của HSĐX 1. Thời gian có hiệu lực của HSĐX phải bảo đảm theo yêu cầu là ___ [Ghi rõ số ngày tuỳ thuộc quy mô, tính chất của gói thầu, bảo đảm thời gian có hiệu lực đến ngày ký kết hợp đồng] kể từ ngày có thời điểm đóng thầu. 2. Trong trường hợp cần thiết, trước khi hết thời hạn hiệu lực của HSĐX, Chủ đầu tư có thể đề nghị nhà thầu gia hạn hiệu lực của HSĐX. Việc đề nghị gia hạn và chấp thuận gia hạn phải được thể hiện bằng văn bản. Mục 10. Quy cách của HSĐX và chữ ký trong HSĐX 1. Nhà thầu phải chuẩn bị một bản gốc và ___bản chụp HSĐX [Ghi số lượng yêu cầu nhưng không quá 03 bản], ghi rõ \"bản gốc\" và \"bản chụp\" tương ứng. Nhà thầu cần ghi rõ tên gói thầu, tên nhà thầu, tên Chủ đầu tư bên ngoài túi đựng HSĐX. Nhà thầu phải chịu trách nhiệm về tính chính xác và phù hợp giữa bản chụp và bản gốc. Trường hợp có sự sai khác giữa bản gốc và bản chụp thì căn cứ vào bản gốc để đánh giá. 2. Tất cả các thành phần của HSĐX nêu tại Mục 6 Chương I phải được ký bởi người đại diện hợp pháp của nhà thầu. Trường hợp là nhà thầu liên danh thì HSĐX phải có chữ ký của đại diện hợp pháp của tất cả thành viên liên danh hoặc thành viên đại diện nhà thầu liên danh theo phân công trong thỏa thuận liên danh. 3. Những chữ được ghi thêm, ghi chèn vào giữa các dòng, những chữ bị tẩy xóa hoặc viết đè lên sẽ chỉ được coi là hợp lệ nếu có chữ ký ở bên cạnh hoặc tại trang đó của người ký đơn dự thầu. Mục 11. Thời điểm đóng thầu và mở thầu 1. HSĐX do nhà thầu nộp trực tiếp hoặc gửi đến địa chỉ của Chủ đầu tư [Ghi địa chỉ] nhưng phải bảo đảm Chủ đầu tư nhận được trước thời điểm đóng thầu: ___ giờ, ngày ___ tháng ___ năm ____ [Ghi thời điểm đóng thầu]. 2. Mở thầu: Chủ đầu tư tiến hành mở thầu bao gồm các nội dung sau: a) Kiểm tra niêm phong; b) Mở hồ sơ và đọc rõ các thông tin về tên nhà thầu: - Tham dự độc lập hay liên danh; - Số lượng bản gốc, bản chụp; - giá thầu chào trong đơn dự thầu; - Giá trị giảm giá (nếu có); - Thời gian có hiệu lực của HSĐX; - Thời gian thực hiện gói thầu; - Các thông tin khác liên quan. Biên bản mở thầu bao gồm các thông tin quy định tại điểm a và điểm b khoản này. Biên bản mở thầu phải được ký xác nhận bởi đại diện của Chủ đầu tư và nhà thầu nộp HSĐX. Biên bản này phải được gửi cho nhà thầu nộp HSĐX. Đại diện của Chủ đầu tư phải ký xác nhận vào bản gốc đơn dự thầu, thư giảm giá (nếu có), giấy ủy quyền của người đại diện theo pháp luật của nhà thầu (nếu có), thỏa thuận liên danh (nếu có), các nội dung đề xuất về tài chính và các nội dung quan trọng khác của từng HSĐX. Mục 12. thầu phụ 1. thầu phụ là tổ chức, cá nhân ký hợp đồng với nhà thầu để thực hiện các dịch vụ liên quan. Trường hợp nhà thầu cần sử dụng thầu phụ thì phải kê khai danh sách thầu phụ theo Mẫu 11B Chương III. Việc sử dụng thầu phụ sẽ không làm thay đổi các trách nhiệm của nhà thầu. Nhà thầu phải chịu trách nhiệm về khối lượng, chất lượng, tiến độ và các trách nhiệm khác đối với phần công việc do thầu phụ thực hiện. Năng lực và kinh nghiệm của thầu phụ sẽ không được đánh giá khi đánh giá HSĐX của nhà thầu. Bản thân nhà thầu phải đáp ứng các tiêu chí năng lực và kinh nghiệm (không xét đến năng lực và kinh nghiệm của thầu phụ). 2. Nhà thầu được sử dụng thầu phụ thực hiện các dịch vụ liên quan. Việc kê khai sử dụng thầu phụ thực hiện theo Mẫu 11B Chương IV. Mục 13. Đánh giá HSĐX và thương thảo về các đề xuất của nhà thầu 1. Việc đánh giá HSĐX được thực hiện theo quy định tại Chương II. 2. Trong quá trình đánh giá, Chủ đầu tư mời nhà thầu thương thảo về giá bảo đảm đáp ứng tỷ lệ tiết kiệm theo quy định của HSYC, thương thảo, làm rõ hoặc sửa đổi, bổ sung nội dung HSĐX để chứng minh việc đáp ứng yêu cầu về năng lực, kinh nghiệm, tiến độ, khối lượng, chất lượng, giải pháp kỹ thuật, biện pháp tổ chức thực hiện gói thầu và tỷ lệ tiết kiệm. Mục 14. Điều kiện đối với nhà thầu được đề nghị chỉ định thầu Nhà thầu được đề nghị chỉ định thầu khi đáp ứng đầy đủ các điều kiện sau đây: 1. Có HSĐX hợp lệ; 2. Có năng lực, kinh nghiệm và đề xuất kỹ thuật đáp ứng yêu cầu của HSYC; 3. Có giá đề nghị trúng thầu không vượt giá gói thầu được duyệt và đáp ứng tỷ lệ tiết kiệm tối thiểu__% giá gói thầu. [Căn cứ quy mô, tính chất, điều kiện cụ thể của gói thầu, Chủ đầu tư quy định trong HSYC mức tỷ lệ tiết kiệm của giá đề nghị trúng thầu để làm cơ sở cho nhà thầu chuẩn bị HSĐX] Mục 15. Thông báo kết quả lựa chọn nhà thầu Trong thời hạn 05 ngày làm việc kể từ ngày kết quả lựa chọn nhà thầu được phê duyệt, Chủ đầu tư đăng tải thông tin về kết quả lựa chọn nhà thầu lên Hệ thống mạng đấu thầu quốc gia; gửi văn bản thông báo kết quả lựa chọn nhà thầu cho nhà thầu dự thầu. Nội dung thông báo kết quả lựa chọn nhà thầu như sau: a) Thông tin về gói thầu: - Tên gói thầu; - Giá gói thầu hoặc dự toán được duyệt (nếu có); - Tên Chủ đầu tư; - Hình thức lựa chọn nhà thầu; - Loại hợp đồng; - Thời gian thực hiện gói thầu b) Thông tin về nhà thầu trúng thầu: - Tên nhà thầu; - Mã số thuế (nếu có); - giá thầu; - Giá trúng thầu; - Thời gian thực hiện gói thầu; - Thời gian thực hiện hợp đồng. c) Kế hoạch hoàn thiện, ký kết hợp đồng với nhà thầu trúng thầu. Mục 16. Điều kiện ký kết hợp đồng 1. Tại thời điểm ký kết, HSĐX của nhà thầu trúng thầu còn hiệu lực. 2. Tại thời điểm ký kết hợp đồng, nhà thầu trúng thầu phải bảo đảm đáp ứng yêu cầu về năng lực kỹ thuật, tài chính để thực hiện gói thầu theo yêu cầu của HSYC. Trường hợp thực tế nhà thầu không còn đáp ứng cơ bản yêu cầu về năng lực kỹ thuật, tài chính theo quy định nêu trong HSYC thì Chủ đầu tư sẽ từ chối ký kết hợp đồng với nhà thầu và hủy quyết định phê duyệt kết quả lựa chọn nhà thầu. 3. Chủ đầu tư phải bảo đảm các điều kiện về vốn tạm ứng, vốn thanh toán, mặt bằng thực hiện và điều kiện cần thiết khác để triển khai thực hiện gói thầu theo đúng tiến độ. Mục 17. Bảo đảm thực hiện hợp đồng 1. Trước hoặc cùng thời điểm hợp đồng có hiệu lực, nhà thầu được chỉ định thầu phải cung cấp bảo đảm thực hiện hợp đồng theo quy định của HSYC. Trường hợp nhà thầu sử dụng thư bảo lãnh thực hiện hợp đồng thì phải sử dụng Mẫu thư bảo lãnh trong HSYC này hoặc Mẫu thư bảo lãnh khác được Chủ đầu tư chấp thuận. 2. Nhà thầu không được hoàn trả bảo đảm thực hiện hợp đồng trong trường hợp sau đây: a) Từ chối thực hiện hợp đồng khi hợp đồng đã có hiệu lực; b) Vi phạm thỏa thuận trong hợp đồng; c) Thực hiện hợp đồng chậm tiến độ do lỗi của nhà thầu nhưng từ chối gia hạn hiệu lực của bảo đảm thực hiện hợp đồng. Mục 18. Giải quyết kiến nghị 1. Đối với gói thầu thuộc phạm vi điều chỉnh của Luật Đấu thầu: a) Khi thấy quyền và lợi ích hợp pháp bị ảnh hưởng, nhà thầu được kiến nghị người có thẩm quyền, Chủ đầu tư, Hội đồng giải quyết kiến nghị đánh giá lại các vấn đề trong quá trình lựa chọn nhà thầu, kết quả lựa chọn nhà thầu theo quy định tại Điều 89 Luật Đấu thầu và các Điều 137, 138 và 139 của Nghị định số 214/2025/NĐ-CP. b) Địa chỉ nhận đơn kiến nghị: - Địa chỉ nhận đơn kiến nghị của Chủ đầu tư: ___ [ghi đầy đủ tên, địa chỉ, số điện thoại, email]; - Địa chỉ nhận đơn kiến nghị của người có thẩm quyền: ___ [ghi đầy đủ tên, địa chỉ, số điện thoại, email]; - Địa chỉ bộ phận thường trực giúp việc của Hội đồng giải quyết kiến nghị: ___ [ghi đầy đủ tên, địa chỉ, số điện thoại, email]. 2. Đối với hoạt động lựa chọn nhà thầu quy định tại điểm d Khoản 7 Điều 3 của Luật Đấu thầu hoặc hoạt động lựa chọn nhà thầu không thuộc phạm vi điều chỉnh của Luật Đấu thầu: Khi thấy quyền và lợi ích hợp pháp bị ảnh hưởng, nhà thầu, cơ quan, tổ chức được kiến nghị theo quy trình sau: ___ [ghi cụ thể quy trình, thủ tục của việc giải quyết kiến nghị của đơn vị, tổ chức đồng thời ghi rõ email, địa chỉ của cá nhân/tổ chức/đơn vị giải quyết kiến nghị]. Mục 19. Ưu đãi trong lựa chọn nhà thầu Ưu đãi: _____ [Chủ đầu tư ghi rõ đối tượng, điều kiện ưu đãi theo quy định tại Nghị quyết của Quốc hội hoặc văn bản quy phạm pháp luật (nếu có)]. Chương II. TIÊU CHUẨN ĐÁNH GIÁ HSĐX Mục 1. Đánh giá tính hợp lệ của HSĐX 1. 1. Kiểm tra HSĐX a) Kiểm tra số lượng bản gốc, bản chụp HSĐX; b) Kiểm tra các thành phần của HSĐX theo quy định tại Mục 6 Chương I; c) Kiểm tra sự thống nhất nội dung giữa bản gốc và bản chụp để phục vụ quá trình đánh giá chi tiết HSĐX. 1. 2. Đánh giá tính hợp lệ của HSĐX HSĐX của nhà thầu được đánh giá là hợp lệ khi đáp ứng đầy đủ các nội dung sau đây: a) Có bản gốc HSĐX; b) Có đơn dự thầu được đại diện hợp pháp của nhà thầu ký tên, đóng dấu (nếu có) theo yêu cầu của HSYC; thời gian ký đơn dự thầu phải sau thời điểm phát hành HSYC; không đề xuất các giá thầu khác nhau hoặc có kèm theo điều kiện gây bất lợi cho Chủ đầu tư. Đối với nhà thầu liên danh, đơn dự thầu phải do đại diện hợp pháp của từng thành viên liên danh ký tên, đóng dấu (nếu có) hoặc thành viên được phân công thay mặt liên danh ký đơn dự thầu theo phân công trách nhiệm trong thỏa thuận liên danh; c) Hiệu lực của HSĐX đáp ứng yêu cầu theo quy định tại Mục 9 Chương I; d) Có thỏa thuận liên danh (trong trường hợp liên danh) được đại diện hợp pháp của từng thành viên liên danh ký tên, đóng dấu (nếu có); thỏa thuận liên danh phải nêu rõ nội dung công việc cụ thể và ước tính giá trị tương ứng mà từng thành viên trong liên danh sẽ thực hiện. Việc phân chia công việc trong liên danh phải căn cứ các hạng mục nêu trong bảng giá thầu tại Mẫu 4. 1 (4. 1A hoặc 4. 1B hoặc 4. 1C) hoặc Mẫu 4. 2 (4. 2A hoặc 4. 2B hoặc 4. 2C) Chương III hoặc theo các công việc thuộc quá trình sản xuất hạng mục trong bảng giá thầu, không được phân chia các công việc không thuộc các hạng mục này hoặc không thuộc quá trình sản xuất các hạng mục này; đ) Nhà thầu bảo đảm tư cách hợp lệ theo quy định tại Mục 3 Chương I. e) Trong thời hạn 03 năm trước thời điểm đóng thầu, nhà thầu không có nhân sự (ký kết hợp đồng lao động với nhà thầu tại thời điểm nhân sự thực hiện hành vi vi phạm) bị Tòa án kết án có hành vi vi phạm quy định về đấu thầu gây hậu quả nghiêm trọng theo quy định của pháp luật về hình sự nhằm mục đích cho nhà thầu đó trúng thầu. Nhà thầu có HSĐX hợp lệ được đánh giá, đánh giá trong bước tiếp theo. Mục 2. Tiêu chuẩn đánh giá về năng lực, kinh nghiệm Nhà thầu được đánh giá là đạt về năng lực và kinh nghiệm khi đáp ứng tiêu chuẩn đánh giá quy định tại Mục 2. 1, 2. 2 và 2. 3. Năng lực và kinh nghiệm của thầu phụ sẽ không được đánh giá khi đánh giá HSĐX của nhà thầu. Bản thân nhà thầu phải đáp ứng các tiêu chí đánh giá về năng lực và kinh nghiệm. 2. 1. Tiêu chuẩn đánh giá về năng lực và kinh nghiệm Tiêu chuẩn đánh giá năng lực và kinh nghiệm thực hiện theo Bảng số 01 (đối với nhà thầu không phải là nhà sản xuất ra hàng hóa thuộc phạm vi của gói thầu) hoặc Bảng số 02 (đối với nhà thầu là nhà sản xuất ra hàng hóa thuộc phạm vi của gói thầu), nhà thầu được đánh giá là đạt về năng lực và kinh nghiệm khi đáp ứng tất cả các tiêu chuẩn đánh giá. Năng lực và kinh nghiệm của thầu phụ sẽ không được đánh giá khi đánh giá HSĐX của nhà thầu. Bản thân nhà thầu phải đáp ứng các tiêu chí đánh giá về năng lực và kinh nghiệm. Việc xác định mức độ yêu cầu cụ thể đối với từng tiêu chuẩn quy định tại Mục này căn cứ theo yêu cầu của từng gói thầu cụ thể. Nhà thầu được đánh giá đạt tất cả nội dung quy định tại Bảng số 01 (đối với nhà thầu không phải là nhà sản xuất ra hàng hóa thuộc phạm vi của gói thầu) hoặc Bảng số 02 (đối với nhà thầu là nhà sản xuất ra hàng hóa thuộc phạm vi của gói thầu) thì đáp ứng yêu cầu về năng lực và kinh nghiệm. Trường hợp đồng tiền nêu trong các hợp đồng tương tự hoặc xác nhận thanh toán của Chủ đầu tư đối với những hợp đồng cung cấp hàng hóa đã thực hiện hoặc tờ khai nộp thuế hoặc các hồ sơ liên quan chứng minh năng lực, kinh nghiệm của nhà thầu không phải VND thì khi lập HSĐX, nhà thầu phải quy đổi về VND để làm cơ sở đánh giá HSĐX. Việc quy đổi được áp dụng tỷ giá quy đổi của___[ghi căn cứ xác định tỷ giá quy đổi, thông thường áp dụng tỷ giá bán ra của một ngân hàng thương mại hoạt động tại Việt Nam] tại ngày ký hợp đồng tương tự đó. Trường hợp nhà thầu dự thầu là công ty mẹ (ví dụ như Tổng công ty) có huy động công ty con, công ty thành viên thực hiện một phần công việc của gói thầu thì nhà thầu phải kê khai cụ thể phần công việc dành cho các công ty con, công ty thành viên theo Mẫu 11A Chương III. Việc đánh giá kinh nghiệm thực hiện hợp đồng tương tự căn cứ vào giá trị, khối lượng công việc do công ty mẹ, công ty con, công ty thành viên đảm nhiệm trong gói thầu. Bảng số 01 BẢNG TIÊU CHUẨN ĐÁNH GIÁ VỀ NĂNG LỰC VÀ KINH NGHIỆM (Đối với nhà thầu không phải là nhà sản xuất(1) ra hàng hóa thuộc phạm vi của gói thầu) [BẢNG: Không tiêu đề] Ghi chú: (1) Nhà sản xuất được hiểu là doanh nghiệp/cơ sở sản xuất tự sản xuất ra hàng hóa hoặc tham gia vào quá trình sản xuất ra hàng hóa hoặc công ty con, công ty mẹ phụ trách việc phân phối, tiêu thụ sản phẩm do công ty mẹ, công ty con khác trong Tập đoàn, Tổng công ty sản xuất. (2) Ghi thời gian yêu cầu, thông thường là 03 năm trước năm có thời điểm đóng thầu. Ví dụ: từ ngày 01 tháng 01 năm 2022 đến thời điểm đóng thầu. (3) Hợp đồng cung cấp hàng hóa, EPC, EP, PC, chìa khóa trao tay không hoàn thành do lỗi của nhà thầu bao gồm: - Hợp đồng cung cấp hàng hóa, EPC, EP, PC, chìa khóa trao tay bị Chủ đầu tư kết luận nhà thầu không hoàn thành và nhà thầu không phản đối; - Hợp đồng cung cấp hàng hóa, EPC, EP, PC, chìa khóa trao tay bị Chủ đầu tư kết luận nhà thầu không hoàn thành, không được nhà thầu chấp thuận nhưng đã được trọng tài hoặc tòa án kết luận theo hướng bất lợi cho nhà thầu. Các hợp đồng cung cấp hàng hóa, EPC, EP, PC, chìa khóa trao tay không hoàn thành không bao gồm các hợp đồng mà quyết định của Chủ đầu tư đã bị bác bỏ bằng cơ chế giải quyết tranh chấp. Việc xác định hợp đồng không hoàn thành phải dựa trên tất cả những thông tin về tranh chấp hoặc kiện tụng được giải quyết theo quy định của cơ chế giải quyết tranh chấp của hợp đồng tương ứng và khi mà nhà thầu đã hết tất cả các cơ hội có thể khiếu nại. Đối với các hợp đồng chậm tiến độ do lỗi của nhà thầu nhưng vẫn hoàn thành hợp đồng thì không được coi là hợp đồng không hoàn thành. Đối với nhà thầu liên danh mà chỉ có một hoặc một số thành viên trong liên danh vi phạm và bị cấm tham gia hoạt động đấu thầu theo quy định tại Khoản 1 Điều 133 của Nghị định số 214/2025/NĐ-CP thì thành viên liên danh còn lại không bị coi là không hoàn thành hợp đồng do lỗi của nhà thầu. Trường hợp một hoặc một số thành viên liên danh vi phạm hợp đồng, không còn năng lực để tiếp tục thực hiện hợp đồng, làm ảnh hưởng nghiêm trọng đến tiến độ, chất lượng, hiệu quả của gói thầu thì chỉ một hoặc một số thành viên liên danh vi phạm hợp đồng bị coi là không hoàn thành hợp đồng, thành viên còn lại không bị coi là không hoàn thành hợp đồng do lỗi của nhà thầu. (4) Nhà thầu cung cấp hồ sơ chứng minh đã thực hiện nghĩa vụ kê khai thuế và nộp thuế thu nhập doanh nghiệp (thuế thu nhập cá nhân đối với nhà thầu là hộ kinh doanh) của năm tài chính gần nhất so với thời điểm đóng thầu. Nghĩa vụ kê khai thuế và nộp thuế phải được thực hiện trước thời điểm đóng thầu. Nghĩa vụ nộp thuế là nộp thuế với giá trị thuế tương ứng với thuế suất, thu nhập chịu thuế, doanh thu tính thuế nhà thầu kê khai trên Hệ thống thuế điện tử (số thuế đã nộp tương ứng với số thuế phải nộp); trường hợp được chậm nộp thuế, miễn thuế, giảm thuế theo chính sách của Nhà nước thì thực hiện theo quy định này. Nhà thầu nộp các hồ sơ như sau: - Tờ khai thuế (hoặc thông báo nộp tiền của cơ quan thuế đối với hộ kinh doanh) và Giấy nộp tiền có xác nhận của cơ quan thuế được in từ Hệ thống thuế điện tử hoặc - Tờ khai thuế (hoặc thông báo nộp tiền của cơ quan thuế đối với hộ kinh doanh) và xác nhận của cơ quan thuế về việc thực hiện nghĩa vụ thuế. Trường hợp thời điểm đóng thầu sau ngày kết thúc năm tài chính của nhà thầu (năm Y) và trước hoặc trong ngày cuối cùng của tháng thứ 3 tính từ ngày kết thúc năm Y, yêu cầu đã thực hiện nghĩa vụ kê khai thuế và nộp thuế áp dụng đối với năm tài chính trước năm Y (năm Y-1). (Ví dụ: Ngày có thời điểm đóng thầu là ngày 20/3/2024, năm tài chính của nhà thầu là 01/01 - 31/12 thì nhà thầu phải chứng minh đã thực hiện nghĩa vụ kê khai thuế và nộp thuế của năm 2022). (5) Việc xác định giá trị tài sản ròng được thực hiện trên cơ sở báo cáo tài chính của nhà thầu. Trường hợp thời điểm đóng thầu sau ngày kết thúc năm tài chính của nhà thầu (năm Y) và trước hoặc trong ngày cuối cùng của tháng thứ 3 tính từ ngày kết thúc năm Y, việc xác định giá trị tài sản ròng của nhà thầu được thực hiện trên cơ sở báo cáo tài chính năm trước của năm Y (năm Y-1). Ví dụ: Ngày có thời điểm đóng thầu là ngày 20/3/2024, năm tài chính của nhà thầu là 01/01 - 31/12 và HSYC yêu cầu nhà thầu nộp báo cáo tài chính của 03 năm gần nhất thì việc xác định giá trị tài sản ròng của nhà thầu được thực hiện trên cơ sở bảo cáo tài chính năm 2022. Đối với nhà thầu là hộ kinh doanh thì không đánh giá tiêu chí này. (6) Ghi thời gian yêu cầu, thông thường từ 03 năm đến 05 năm trước năm có thời điểm đóng thầu. Trường hợp nhà thầu có số năm thành lập ít hơn số năm theo yêu cầu của HSYC thì doanh thu bình quân hằng năm (không bao gồm thuế VAT) được tính trên số năm mà nhà thầu thành lập. Trường hợp doanh thu bình quân hằng năm (không bao gồm thuế VAT) của nhà thầu đáp ứng yêu cầu về giá trị của HSYC thì nhà thầu vẫn được đánh giá tiếp mà không bị loại. Đối với nhà thầu là hộ kinh doanh, không bắt buộc phải nộp báo cáo tài chính nhưng nhà thầu phải cung cấp hồ sơ chứng minh doanh thu tương ứng với nghĩa vụ thuế. Trường hợp thời điểm đóng thầu sau ngày kết thúc năm tài chính của nhà thầu (năm Y) và trước hoặc trong ngày cuối cùng của tháng thứ 3 tính từ ngày kết thúc năm Y, yêu cầu về nộp báo cáo tài chính áp dụng đối với các năm trước của năm Y (năm Y-1, Y-2. ..). Ví dụ 1: Ngày có thời điểm đóng thầu là ngày 20/3/2024, năm tài chính của nhà thầu là 01/01 - 31/12 và HSYC yêu cầu nhà thầu nộp báo cáo tài chính của 03 năm gần nhất thì nhà thầu phải nộp báo cáo tài chính của các năm 2020, 2021, 2022). Ví dụ 2: Doanh thu bình quân hằng năm (không bao gồm thuế VAT) của 3 năm tài chính gần nhất so với thời điểm đóng thầu. Trong trường hợp này, nếu thời điểm đóng thầu là ngày 15/11/2024 thì nhà thầu phải nộp báo cáo tài chính của các năm 2021, 2022, 2023. Nhà thầu được thành lập vào năm 2022 nhưng doanh thu trung bình của năm 2022 và năm 2023 đáp ứng yêu cầu thì nhà thầu được tiếp tục đánh giá. (7) Cách tính toán thông thường về mức yêu cầu doanh thu bình quân hằng năm (không bao gồm thuế VAT): a) Trường hợp thời gian thực hiện gói thầu từ 12 tháng trở lên thì cách tính doanh thu như sau: Yêu cầu tối thiểu về mức doanh thu bình quân hằng năm (không bao gồm thuế VAT) = [(Giá gói thầu - giá trị thuế VAT)/thời gian thực hiện gói thầu theo năm] x k. Thông thường yêu cầu hệ số “k” trong công thức này là từ 1, 5 đến 2. b) Trường hợp thời gian thực hiện gói thầu dưới 12 tháng thì cách tính doanh thu như sau: Yêu cầu tối thiểu về mức doanh thu bình quân hằng năm (không bao gồm thuế VAT) = (Giá gói thầu - giá trị thuế VAT) x k. Thông thường yêu cầu hệ số “k” trong công thức này là 1, 5. (8) Đối với các hợp đồng mà nhà thầu đã tham gia với tư cách là thành viên liên danh hoặc thầu phụ thì chỉ tính giá trị phần việc do nhà thầu thực hiện. (9) Ghi thời gian yêu cầu, thông thường là từ 03 năm đến 05 năm trước năm có thời điểm đóng thầu. Ví dụ: từ ngày 01 tháng 01 năm 2019 đến thời điểm đóng thầu. (10) Tương tự về tính chất: Chủ đầu tư lựa chọn một trong hai cách thức để quy định trong HSYC như sau: a) Cách 1: là hàng hóa thuộc cùng lĩnh vực tổng quát (Chủ đầu tư nêu lĩnh vực tổng quát, ví dụ thiết bị y tế, thiết bị điện, thiết bị văn phòng. ..) hoặc b) Cách 2: HSYC quy định theo 2 tiêu chí (i) Tiêu chí 1: là hàng hóa thuộc cùng lĩnh vực tổng quát (Chủ đầu tư nêu lĩnh vực tổng quát, ví dụ thiết bị y tế, thiết bị điện, thiết bị văn phòng. ..) (ii) Tiêu chí 2: là hàng hóa có cùng mã Chương, mã Nhóm (tương ứng với 4 số đầu tiên của bộ mã) trong Hệ thống hài hòa mô tả và mã hóa hàng hóa (HS - Harmonized Commodity Description and Coding System) theo Hệ thống phân loại hàng hóa do Tổ chức Hải quan thế giới WCO phát hành (gọi chung là mã HS). Mã HS căn cứ theo Thông tư số 31/2022/TT-BTC ngày 08 tháng 6 năm 2022 của Bộ Tài chính (được Tổng Cục Hải quan đăng tải trên trang thông tin điện tử: https: //www. customs. gov. vn). Nhà thầu cung cấp hàng hóa thuộc cùng lĩnh vực tổng quát do HSYC yêu cầu (Tiêu chí 1) hoặc cùng 4 số đầu tiên mã HS (Tiêu chí 2) đều được coi là có tính chất tương tự với hàng hóa thuộc gói thầu. Trường hợp một hạng mục hàng hóa có nhiều mã HS khác nhau, HSYC quy định các mã HS này, nhà thầu có hàng hóa đáp ứng một trong các mã HS này được coi là đáp ứng yêu cầu của HSYC. Ví dụ: hàng hóa thuộc gói thầu là máy tính xách tay có mã HS là 84. 71. 30. 20 thì các hàng hóa có mã HS là 84. 71. xx. xx được coi là có tính chất tương tự. Trường hợp hàng hóa thuộc gói thầu chưa được công bố mã HS, nhà thầu phải kê khai các hợp đồng cung cấp hàng hóa có cùng lĩnh vực tổng quát theo yêu cầu của HSYC (Tiêu chí 1). - Đối với gói thầu mua trang thiết bị y tế, mã HS được xác định theo Thông tư số 14/2018/TT-BYT ngày 15 tháng 5 năm 2018 của Bộ Y tế, hàng hóa tương tự theo mã HS (xác định theo tiêu chí 2) là trang thiết bị y tế cùng nhóm hàng hóa (tương ứng với 4 số đầu tiên của bộ mã) quy định tại Thông tư số 14/2018/TT-BYT. Trong quá trình thực hiện, trường hợp Thông tư số 31/2022/TT-BTC, Thông tư số 14/2018/TT-BYT được sửa đổi, bổ sung hoặc thay thế thì áp dụng theo văn bản quy phạm pháp luật sửa đổi, bổ sung hoặc thay thế Thông tư số 31/2022/TT-BTC, Thông tư số 14/2018/TT-BYT). - Trường hợp Chủ đầu tư, tổ chuyên gia khó khăn trong việc xác định mã HS của hàng hóa theo Tiêu chí 2, HSYC được đưa ra quy định tương tự về lĩnh vực tổng quát (theo Tiêu chí 1). Trong trường hợp này, nếu nhà thầu xác định được mã HS của hàng hóa theo yêu cầu của gói thầu và mã HS của hàng hóa trong hạng mục, hợp đồng đã thực hiện (nghiệm thu) cùng nhóm (tương ứng với 4 số đầu tiên của bộ mã) thì hạng mục, hợp đồng này được coi là tương tự để đánh giá, đánh giá (được coi như nhà thầu đáp ứng Tiêu chí 2). - Trường hợp gói thầu có nhiều hạng mục thì có thể chỉ quy định lĩnh vực tổng quát, mã HS cho các hạng mục chính của gói thầu. (11) Quy mô của hợp đồng tương tự: Trường hợp gói thầu có nhiều hạng mục hàng hóa thì phải ghi giá trị tương ứng của từng hạng mục hàng hóa để làm cơ sở đánh giá kinh nghiệm thực hiện hợp đồng cung cấp hàng hóa tương tự của nhà thầu. Trường hợp gói thầu bao gồm nhiều loại hàng hóa khác nhau thì tùy theo tính chất, quy mô gói thầu để Chủ đầu tư, tổ chuyên gia đưa ra yêu cầu về quy mô tương tự trên cơ sở các loại hàng hóa chính của gói thầu (phải nêu rõ các hàng hóa chính) hoặc yêu cầu về quy mô tương tự trên cơ sở tất cả các loại hàng hóa của gói thầu, trong đó ghi quy mô yêu cầu đối với mỗi hạng mục hàng hóa chính hoặc mỗi hạng mục hàng hóa. Trường hợp mua sắm hàng hóa có số lượng, khối lượng mời thầu lớn thì có thể điều chỉnh giảm yêu cầu về quy mô của hợp đồng tương tự (Y) xuống còn Y/1, 25. Trong đó, Y thông thường khoảng 50% giá trị của gói thầu đang xét; riêng đối với trường hợp gói thầu có một số hạng mục hàng hóa có cùng mã Chương, mã Nhóm thì việc xác định quy mô hợp đồng tương tự được xác định theo điểm (iii) và điểm (iv) ghi chú này. Đối với gói thầu mua sắm hàng hóa có khối lượng, số lượng công việc căn cứ nhu cầu theo các năm và thời gian thực hiện gói thầu dài hơn 1 năm thì HSYC yêu cầu về giá trị của hợp đồng tương tự trong 01 chu kỳ (01 năm) mà không xác định yêu cầu theo tổng số năm. Ví dụ: gói thầu cung cấp vật tư X cho nhu cầu của Chủ đầu tư trong 02 năm 2024-2025 (từ 01/01/2024 đến 31/12/2025), giá gói thầu là 100. 000. 000. 000 VNĐ (tính cho nhu cầu trong 02 năm). Yêu cầu giá trị của hợp đồng tương tự là: 50% x 100. 000. 000. 000/2 =25. 000. 000. 000 VNĐ. Việc đánh giá về quy mô của hợp đồng tương tự căn cứ vào giá trị hoàn thành, được nghiệm thu như sau: (i) Có ít nhất 01 hợp đồng hoàn thành cung cấp đầy đủ các loại hàng hóa tương tự có giá trị đáp ứng tối thiểu là Y (hoặc Y/1, 25 nếu thuộc trường hợp mua sắm hàng hóa có số lượng, khối lượng mời thầu lớn), trong đó từng hạng mục tương tự trong hợp đồng không cần có giá trị đáp ứng 50% (hoặc 40% nếu thuộc trường hợp mua hàng hóa có số lượng, khối lượng mời thầu lớn) giá trị tương ứng của hạng mục đó trong gói thầu hoặc (ii) Có các hạng mục hàng hóa tương tự đã thực hiện trong các hợp đồng khác nhau (hợp đồng có thể đã hoàn thành hoặc đang thực hiện, chưa nghiệm thu, thanh lý) hoặc trong một hợp đồng (hợp đồng chưa hoàn thành) nhưng bảo đảm giá trị của từng hạng mục hàng hóa tương tự đã thực hiện đáp ứng tối thiểu 50% giá trị của từng hạng mục hàng hóa trong gói thầu đang xét (hoặc 40% nếu thuộc trường hợp mua sắm hàng hóa có số lượng, khối lượng mời thầu lớn), trong đó không được cộng gộp giá trị của hạng mục hàng hóa tương tự trong nhiều hợp đồng khác nhau để hình thành một hạng mục hàng hóa tương tự có giá trị lớn hơn 50% (hoặc 40% nếu thuộc trường hợp mua sắm hàng hóa có số lượng, khối lượng mời thầu lớn) giá trị của hạng mục hàng hóa gói thầu đang xét. Trong đó: + Hạng mục hàng hóa đã thực hiện là một phần hoặc toàn bộ khối lượng hàng hóa trong hạng mục đã được nghiệm thu trong khoảng thời gian quy định mà không xét đến thời gian ký kết hợp đồng. Thời điểm xác nhận hạng mục hàng hóa đã thực hiện để xác định hạng mục hàng hóa tương tự là thời điểm nghiệm thu hàng hóa, không căn cứ vào thời điểm ký kết hợp đồng. + Hợp đồng hoàn thành là hợp đồng có toàn bộ hàng hóa đã được nghiệm thu hoặc hợp đồng đã được thanh lý. Thời điểm xác nhận hợp đồng hoàn thành để xác định hợp đồng tương tự là thời điểm nghiệm thu hàng hóa, không căn cứ vào thời điểm ký kết hợp đồng. - Trường hợp nhà thầu vừa là nhà sản xuất, vừa là nhà cung cấp (một số hàng hóa hoặc một phần khối lượng hàng hóa do nhà thầu chào trong HSYC là do nhà thầu sản xuất, một số hàng hóa khác hoặc một phần khối lượng hàng hóa do nhà thầu mua từ nhà sản xuất, cung cấp khác để cung cấp cho gói thầu), thì ngoài kê khai về kinh nghiệm thực hiện hợp đồng tương tự, nhà thầu còn phải kê khai về năng lực sản xuất theo nội dung quy định tại Mục 4 Bảng số 02 Chương này. Việc đánh giá kinh nghiệm của nhà thầu sẽ được thực hiện trên cơ sở hợp đồng cung cấp hàng hóa tương tự (tương ứng với phần hàng hóa mà nhà thầu mua từ nhà sản xuất, cung cấp khác) và năng lực sản xuất của nhà thầu (tương ứng với phần hàng hóa mà nhà thầu tự sản xuất để cung cấp cho gói thầu). Trường hợp một số hạng mục hàng hóa trong gói thầu có cùng mã Chương, mã Nhóm (mã A) thì việc đánh giá về quy mô của hợp đồng tương tự căn cứ vào giá trị hoàn thành, được nghiệm thu như sau: (iii) Có ít nhất 01 hợp đồng hoàn thành cung cấp đầy đủ các loại hàng hóa tương tự có giá trị đáp ứng tối thiểu là K (hoặc K/1, 25 nếu thuộc trường hợp mua sắm hàng hóa có số lượng, khối lượng mời thầu lớn), trong đó K bằng 50% tổng giá trị các hạng mục không có cùng mã Chương, mã Nhóm (không có mã A) và giá trị cao nhất của các hạng mục có cùng chung mã A (giá trị hạng mục theo giá gói thầu, dự toán được duyệt) hoặc (iv) Có các hạng mục hàng hóa tương tự đã thực hiện trong các hợp đồng khác nhau (hợp đồng có thể đã hoàn thành hoặc đang thực hiện, chưa nghiệm thu, thanh lý) hoặc trong một hợp đồng (hợp đồng chưa hoàn thành) nhưng bảo đảm giá trị của từng hạng mục hàng hóa tương tự không có mã A đã thực hiện đáp ứng tối thiểu 50% giá trị của từng hạng mục hàng hóa trong gói thầu đang xét (hoặc 40% nếu thuộc trường hợp mua sắm hàng hóa có số lượng, khối lượng mời thầu lớn), đối với hạng mục hàng hóa tương tự có cùng mã A thì chỉ cần giá trị của hạng mục hàng hóa tương tự đã thực hiện đáp ứng tối thiểu 50% giá trị cao nhất của hạng mục hàng hóa cùng mã A trong gói thầu đang xét (hoặc 40% nếu thuộc trường hợp mua sắm hàng hóa có số lượng, khối lượng mời thầu lớn). Không được cộng gộp giá trị của hạng mục hàng hóa tương tự trong nhiều hợp đồng khác nhau để hình thành một hạng mục hàng hóa tương tự có giá trị lớn hơn 50% (hoặc 40% nếu thuộc trường hợp mua sắm hàng hóa có số lượng, khối lượng mời thầu lớn) giá trị của hạng mục hàng hóa gói thầu đang xét. * Ví dụ cho ghi chú số (10), (11): - Ví dụ 1: Gói thầu đang xét là gói thầu cung cấp 500. 000 cái bơm tiêm dùng một lần có mã HS 9018. 31. 10 (Theo quy định của Thông tư số 14/2018/TT-BYT) giá trị 1. 000. 000. 000 VNĐ và 100 chiếc đèn mổ treo trần có mã HS 9405. 10. 20 (Theo quy định của Thông tư số 14/2018/TT-BYT) giá trị 2. 000. 000. 000 VNĐ. Nhà thầu X có hợp đồng A (chưa hoàn thành, chưa được thanh lý) cung cấp 2 máy thở có mã HS 9018. 90. 30, trong đó đã bàn giao 1 chiếc (đã được nghiệm thu) với giá trị 900. 000. 000 VNĐ (> 50% giá trị hạng mục bơm tiêm dùng một lần) và có hợp đồng B (chưa hoàn thành, chưa được thanh lý) cung cấp 200 chiếc đèn phẫu thuật có mã HS 9405. 40. 91, trong đó đã bàn giao 80 chiếc (đã được nghiệm thu) với giá trị 1. 450. 000. 000 VNĐ (> 50% giá trị hạng mục đèn mổ treo trần) thì nhà thầu X được đánh giá là đáp ứng yêu cầu về hợp đồng tương tự của gói thầu này. - Ví dụ 2: Phạm vi cung cấp gói thầu là mua xe Ben tự đổ kèm theo 20 cái lốp xe dự phòng; giá gói thầu được phê duyệt là 1, 8 tỷ đồng (trong đó giá trị của xe Ben là 1, 64 tỷ đồng và 20 lốp dự phòng có giá trị 0, 16 tỷ đồng). Như vậy, trong trường hợp này thì hàng hóa chính của gói thầu là xe Ben tự đổ và quy mô của hợp đồng tương tự được xác định bằng 50% x 1, 64 tỷ đồng. - Ví dụ 3: Phạm vi cung cấp của gói thầu đang xét gồm 50 máy điều hòa (mã HS 8415; giá dự toán 2 tỷ đồng); 20 máy tính xách tay (mã HS 8507; giá dự toán 400 triệu đồng); 20 máy in Laser (mã HS 8443; giá dự toán 100 triệu đồng), giao hàng trong thời gian 180 ngày kể từ ngày hợp đồng có hiệu lực. Nhà thầu dự thầu là nhà thầu Liên danh A - B trong đó thành viên A là nhà sản xuất máy điều hòa đảm nhận phần công việc cung cấp máy điều hòa (80% giá trị công việc gói thầu), thành viên B là nhà thương mại đảm nhận phần công việc cung cấp máy tính xách tay và máy in của gói thầu (20% giá trị công việc gói thầu). Trong trường hợp này, nhà thầu Liên danh A - B được coi là đáp ứng yêu cầu về năng lực sản xuất và kinh nghiệm thực hiện hợp đồng nếu: + Thành viên A cung cấp được hồ sơ chứng minh công suất thiết kế của nhà máy, dây chuyền thiết bị sản xuất máy điều hòa đạt tối thiểu 12, 5 máy điều hòa/tháng (1, 5 x 50 máy x 30 /180 ngày) hoặc sản lượng sản xuất máy điều hòa của 01 tháng cao nhất trong vòng 05 năm gần nhất tính đến thời điểm đóng thầu bằng hoặc lớn hơn 12, 5 máy/tháng; + Thành viên B đã thực hiện cung cấp các mã hàng hóa 8507, 8443 trong cùng 01 hợp đồng hoặc ở 02 hợp đồng khác nhau nhưng bảo đảm giá trị mã hàng hóa 8507 trong 01 hợp đồng bằng hoặc lớn hơn 50% giá trị của hạng mục máy tính xách tay (tức là ≥50% x 400 triệu đồng), giá trị mã hàng hóa 8443 trong 01 hợp đồng bằng hoặc lớn hơn 50% giá trị của hạng mục máy in laser (tức là ≥ 50% x 100 triệu đồng). - Ví dụ 4: Phạm vi cung cấp gói thầu mua sắm hàng hóa Q như sau: [BẢNG: Không tiêu đề] Trong trường hợp này, nhà thầu A tham dự gói thầu mua sắm hàng hóa Q nêu trên được coi là đáp ứng yêu cầu về kinh nghiệm thực hiện hợp đồng cung cấp hàng hóa tương tự nếu: + Cung cấp 01 hợp đồng có đầy đủ các mã hàng hóa 9025 và 9030 và tổng giá trị của mã hàng hóa 9025, 9030 trong hợp đồng đã hoàn thành với giá trị tối thiểu là 11 tỷ đồng (50% x (10 tỷ đồng + 12 tỷ đồng)) hoặc + Cung cấp 01 hợp đồng trong đó đã thực hiện việc cung cấp mã hàng hóa 9025 với giá trị tối thiểu 5 tỷ đồng (50% x 10 tỷ đồng) và 01 hợp đồng đã thực hiện việc cung cấp mã hàng hóa 9030 với giá trị tối thiểu 6 tỷ đồng [50% x 12 tỷ đồng)]. ”. Trường hợp nhà thầu A cung cấp 02 hợp đồng có đầy đủ các mã hàng hóa 9025 và 9030, trong đó hợp đồng số 01: giá trị của mã 9025 là 3 tỷ đồng, giá trị của mã 9030 là 5 tỷ đồng và hợp đồng số 02: giá trị của mã 9025 là 3 tỷ đồng, giá trị của mã 9030 là 4 tỷ đồng thì được coi là không đáp ứng yêu cầu về kinh nghiệm thực hiện hợp đồng cung cấp hàng hóa tương tự. (12) Trường hợp không yêu cầu dịch vụ sau bán hàng thì gạch bỏ tiêu chí đánh giá này. Trường hợp nhà thầu thiếu cam kết thì được bổ sung trong quá trình đánh giá HSĐX. Trường hợp nhà thầu không bổ sung cam kết trong khoảng thời gian hợp lý theo yêu cầu của Chủ đầu tư thì HSĐX của nhà thầu được coi là không đáp ứng yêu cầu về khả năng bảo hành, bảo trì, duy tu, bảo dưỡng, sửa chữa, cung cấp phụ tùng thay thế hoặc cung cấp các dịch vụ sau bán hàng khác và bị loại. Bảng số 02 BẢNG TIÊU CHUẨN ĐÁNH GIÁ VỀ NĂNG LỰC VÀ KINH NGHIỆM (Đối với nhà thầu là nhà sản xuất(1) ra hàng hóa thuộc phạm vi của gói thầu) [BẢNG: Không tiêu đề] Ghi chú: (1) Nhà sản xuất được hiểu là doanh nghiệp/cơ sở sản xuất tự sản xuất ra hàng hóa hoặc tham gia vào quá trình sản xuất ra hàng hóa hoặc công ty con, công ty mẹ phụ trách việc phân phối, tiêu thụ sản phẩm do công ty mẹ, công ty con khác trong Tập đoàn, Tổng công ty sản xuất. (2) Ghi thời gian yêu cầu, thông thường là 03 năm trước năm có thời điểm đóng thầu. Ví dụ: từ ngày 01 tháng 01 năm 2022 đến thời điểm đóng thầu. (3) Hợp đồng cung cấp hàng hóa, EPC, EP, PC, chìa khóa trao tay không hoàn thành do lỗi của nhà thầu bao gồm: - Hợp đồng cung cấp hàng hóa, EPC, EP, PC, chìa khóa trao tay bị Chủ đầu tư kết luận nhà thầu không hoàn thành và nhà thầu không phản đối; - Hợp đồng cung cấp hàng hóa, EPC, EP, PC, chìa khóa trao tay bị Chủ đầu tư kết luận nhà thầu không hoàn thành, không được nhà thầu chấp thuận nhưng đã được trọng tài hoặc tòa án kết luận theo hướng bất lợi cho nhà thầu. Các hợp đồng cung cấp hàng hóa, EPC, EP, PC, chìa khóa trao tay không hoàn thành không bao gồm các hợp đồng mà quyết định của Chủ đầu tư đã bị bác bỏ bằng cơ chế giải quyết tranh chấp. Việc xác định hợp đồng không hoàn thành phải dựa trên tất cả những thông tin về tranh chấp hoặc kiện tụng được giải quyết theo quy định của cơ chế giải quyết tranh chấp của hợp đồng tương ứng và khi mà nhà thầu đã hết tất cả các cơ hội có thể khiếu nại. Đối với các hợp đồng chậm tiến độ do lỗi của nhà thầu nhưng vẫn hoàn thành hợp đồng thì không được coi là hợp đồng không hoàn thành. Đối với nhà thầu liên danh mà chỉ có một hoặc một số thành viên trong liên danh vi phạm và bị cấm tham gia hoạt động đấu thầu theo quy định tại Khoản 1 Điều 133 của Nghị định số 214/2025/NĐ-CP thì thành viên liên danh còn lại không bị coi là không hoàn thành hợp đồng do lỗi của nhà thầu. Trường hợp một hoặc một số thành viên liên danh vi phạm hợp đồng, không còn năng lực để tiếp tục thực hiện hợp đồng, làm ảnh hưởng nghiêm trọng đến tiến độ, chất lượng, hiệu quả của gói thầu thì chỉ một hoặc một số thành viên liên danh vi phạm hợp đồng bị coi là không hoàn thành hợp đồng, thành viên còn lại không bị coi là không hoàn thành hợp đồng do lỗi của nhà thầu. (4) Nhà thầu cung cấp hồ sơ chứng minh đã thực hiện nghĩa vụ kê khai thuế và nộp thuế thu nhập doanh nghiệp (thuế thu nhập cá nhân đối với nhà thầu là hộ kinh doanh) của năm tài chính gần nhất so với thời điểm đóng thầu. Nghĩa vụ kê khai thuế và nộp thuế phải được thực hiện trước thời điểm đóng thầu. Nghĩa vụ nộp thuế là nộp thuế với giá trị thuế tương ứng với thuế suất, thu nhập chịu thuế, doanh thu tính thuế nhà thầu kê khai trên Hệ thống thuế điện tử (số thuế đã nộp tương ứng với số thuế phải nộp); trường hợp được chậm nộp thuế, miễn thuế, giảm thuế theo chính sách của Nhà nước thì thực hiện theo quy định này. Nhà thầu nộp các hồ sơ như sau: - Tờ khai thuế (hoặc thông báo nộp tiền của cơ quan thuế đối với hộ kinh doanh) và Giấy nộp tiền có xác nhận của cơ quan thuế được in từ Hệ thống thuế điện tử hoặc - Tờ khai thuế (hoặc thông báo nộp tiền của cơ quan thuế đối với hộ kinh doanh) và xác nhận của cơ quan thuế về việc thực hiện nghĩa vụ thuế. Trường hợp thời điểm đóng thầu sau ngày kết thúc năm tài chính của nhà thầu (năm Y) và trước hoặc trong ngày cuối cùng của tháng thứ 3 tính từ ngày kết thúc năm Y, yêu cầu đã thực hiện nghĩa vụ kê khai thuế và nộp thuế áp dụng đối với năm tài chính trước năm Y (năm Y-1). (Ví dụ: Thời điểm đóng thầu là ngày 20/3/2024, năm tài chính của nhà thầu là 01/01 - 31/12 thì nhà thầu phải chứng minh đã thực hiện nghĩa vụ kê khai thuế và nộp thuế của năm 2022). (5) Khi chào thầu sản phẩm đổi mới sáng tạo, cá nhân, nhóm cá nhân sản xuất sản phẩm đổi mới sáng tạo quy định tại Khoản 4 Điều 6 của Nghị định số 214/2025/NĐ-CP không phải đáp ứng yêu cầu về năng lực tài chính, số năm hoạt động trong cùng ngành nghề trong thời hạn 06 năm kể từ khi sản phẩm lần đầu được sản xuất và đủ điều kiện để đưa ra thị trường. (6) Việc xác định giá trị tài sản ròng được thực hiện trên cơ sở báo cáo tài chính của nhà thầu. Trường hợp thời điểm đóng thầu sau ngày kết thúc năm tài chính của nhà thầu (năm Y) và trước hoặc trong ngày cuối cùng của tháng thứ 3 tính từ ngày kết thúc năm Y, việc xác định giá trị tài sản ròng của nhà thầu được thực hiện trên cơ sở báo cáo tài chính năm trước của năm Y (năm Y-1). Ví dụ: Thời điểm đóng thầu là ngày 20/3/2024, năm tài chính của nhà thầu là 01/01 - 31/12 và HSYC yêu cầu nhà thầu nộp báo cáo tài chính của 03 năm gần nhất thì việc xác định giá trị tài sản ròng của nhà thầu được thực hiện trên cơ sở bảo cáo tài chính năm 2022. Đối với nhà thầu là hộ kinh doanh thì không đánh giá tiêu chí này. (7) Đối với doanh nghiệp khởi nghiệp sáng tạo trong nước khi chào thầu sản phẩm đổi mới sáng tạo của doanh nghiệp đó theo quy định tại Khoản 4 Điều 6 của Nghị định số 214/2025/NĐ-CP không phải đáp ứng tiêu chí này trong thời hạn 06 năm kể từ khi sản phẩm lần đầu được sản xuất và đủ điều kiện để đưa ra thị trường. Nhà thầu trong nước thuộc trường hợp quy định tại điểm g Khoản 1 Điều 10 của Luật Đấu thầu khi chào thầu sản phẩm do nhà thầu đó sản xuất không phải đáp ứng tiêu chí này trong thời hạn 05 năm kể từ khi được cơ quan có thẩm quyền công nhận. Trường hợp sau khi đánh giá mà nhà thầu không đáp ứng về đối tượng được hưởng ưu đãi thì Chủ đầu tư yêu cầu nhà thầu cung cấp hồ sơ chứng minh đáp ứng yêu cầu về doanh thu. Đối với nhà thầu trong nước được chuyển giao kỹ thuật để sản xuất hàng hóa có xuất xứ Việt Nam phù hợp với HSYC không phải đáp ứng tiêu chí này trong thời hạn 05 năm kể từ khi sản phẩm lần đầu được sản xuất và đủ điều kiện để đưa ra thị trường. Căn cứ xác định nhà thầu trong nước được chuyển giao kỹ thuật, nhà thầu trong nước được chuyển giao kỹ thuật khuyến khích chuyển giao để sản xuất hàng hóa có xuất xứ Việt Nam là Giấy chứng nhận đăng ký chuyển giao kỹ thuật, Giấy chứng nhận chuyển giao kỹ thuật khuyến khích chuyển giao theo quy định của pháp luật về kỹ thuật, pháp luật về đầu tư. Đối với nhà thầu trong nước sản xuất hàng hóa có xuất xứ Việt Nam phù hợp với HSYC, không phải đáp ứng yêu cầu về doanh thu khi nhà thầu chào thầu hàng hóa mà chủng loại hàng hóa này lần đầu được nhà thầu sản xuất và đủ điều kiện để đưa ra thị trường trong thời gian 05 năm trước thời điểm đóng thầu nhưng không quá 07 năm tính đến thời điểm đóng thầu. (8) Ghi thời gian yêu cầu, thông thường từ 03 năm đến 05 năm trước năm có thời điểm đóng thầu. Trường hợp nhà thầu có số năm thành lập ít hơn số năm theo yêu cầu của HSYC thì doanh thu bình quân hằng năm (không bao gồm thuế VAT) được tính trên số năm mà nhà thầu thành lập. Trong trường hợp này, nếu doanh thu bình quân hằng năm (không bao gồm thuế VAT) của nhà thầu đáp ứng yêu cầu về giá trị của HSYC thì nhà thầu vẫn được đánh giá tiếp mà không bị loại. Trường hợp thời điểm đóng thầu sau ngày kết thúc năm tài chính của nhà thầu (năm Y) và trước hoặc trong ngày cuối cùng của tháng thứ 3 tính từ ngày kết thúc năm Y, yêu cầu về nộp báo cáo tài chính áp dụng đối với các năm trước của năm Y (năm Y-1, Y-2. ..). Ví dụ 1: Thời điểm đóng thầu là ngày 20/3/2024, năm tài chính của nhà thầu là 01/01 - 31/12 và HSYC yêu cầu nhà thầu nộp báo cáo tài chính của 03 năm gần nhất thì nhà thầu phải nộp báo cáo tài chính của các năm 2020, 2021, 2022. Ví dụ 2: Doanh thu bình quân hằng năm (không bao gồm thuế VAT) của 3 năm tài chính gần nhất so với thời điểm đóng thầu. Trong trường hợp này, nếu thời điểm đóng thầu là ngày 15/11/2024 thì nhà thầu phải nộp báo cáo tài chính của các năm 2021, 2022, 2023. Nhà thầu được thành lập vào năm 2022 nhưng doanh thu trung bình của năm 2022 và năm 2023 đáp ứng yêu cầu thì nhà thầu được tiếp tục đánh giá. Đối với nhà thầu là hộ kinh doanh, không bắt buộc phải nộp báo cáo tài chính nhưng nhà thầu phải cung cấp hồ sơ chứng minh doanh thu tương ứng với nghĩa vụ thuế. (9) Cách tính toán thông thường về mức yêu cầu doanh thu bình quân hằng năm (không bao gồm thuế VAT): a) Trường hợp thời gian thực hiện gói thầu từ 12 tháng trở lên thì cách tính doanh thu như sau: Yêu cầu tối thiểu về mức doanh thu bình quân hằng năm (không bao gồm thuế VAT) = [(Giá gói thầu - giá trị thuế VAT)/thời gian thực hiện gói thầu theo năm] x k. Thông thường yêu cầu hệ số “k” trong công thức này là từ 1, 5 đến 2. b) Trường hợp thời gian thực hiện gói thầu dưới 12 tháng thì cách tính doanh thu như sau: Yêu cầu tối thiểu về mức doanh thu bình quân hằng năm từ hoạt động sản xuất, kinh doanh (không bao gồm thuế VAT) = (Giá gói thầu - giá trị thuế VAT) x k. Thông thường yêu cầu hệ số “k” trong công thức này là 1, 5. (10) Trường hợp gói thầu bao gồm nhiều loại hàng hoá khác nhau thì tùy theo tính chất, quy mô gói thầu để Chủ đầu tư, tổ chuyên gia đưa ra yêu cầu về công suất thiết kế của nhà máy, dây chuyền sản xuất hoặc sản lượng sản xuất cao nhất của 01 tháng trong 05 năm hoặc sản lượng sản xuất cao nhất của 01 năm trong 05 năm gần nhất tính đến thời điểm đóng thầu trên cơ sở các loại hàng hoá chính của gói thầu (phải nêu rõ các hàng hóa chính) hoặc trên cơ sở tất cả các loại hàng hoá của gói thầu, tương ứng với yêu cầu về hạng mục chính hoặc tất cả hàng hóa của gói thầu đối với nhà thầu là nhà thương mại. Công suất thiết kế của nhà máy, dây chuyền sản xuất hoặc sản lượng sản xuất cao nhất của 01 tháng trong 05 năm gần nhất tính đến thời điểm đóng thầu bằng: k x (Số lượng yêu cầu của gói thầu x 30/thời gian thực hiện gói thầu (tính theo ngày)). Thông thường k = 1, 5; trường hợp mua sắm hàng hóa có số lượng, khối lượng mời thầu lớn thì có thể quy định k = 1”, hoặc: Công suất thiết kế của nhà máy, dây chuyền sản xuất hoặc sản lượng sản xuất cao nhất của 01 năm trong 05 năm gần nhất tính đến thời điểm đóng thầu bằng: k x (Số lượng yêu cầu của gói thầu x 365/thời gian thực hiện gói thầu (tính theo ngày)). Thông thường k = 1, 5”. Ví dụ: Số lượng hàng hóa cần mua là 12. 000 hộp sữa, thời gian thực hiện gói thầu là 20 ngày, hệ số k = 1, 5 thì công suất thiết kế tối thiểu trong 01 tháng/sản lượng sản xuất sữa cao nhất của 01 tháng của nhà thầu là: 1, 5 x (12. 000 x 30/20) = 27. 000 hộp sữa hoặc công suất thiết kế tối thiểu trong 01 năm/sản lượng sản xuất sữa cao nhất của 01 năm của nhà thầu là: 1, 5 x (12. 000 x 365/20) = 328. 500 hộp sữa. Trường hợp hàng hóa là sản phẩm do nhà thầu Việt Nam sản xuất trong nước (có thể đã bán ra thị trường hoặc chưa bán ra thị trường), nhà thầu phải chứng minh công suất thiết kế hoặc sản lượng sản xuất đáp ứng yêu cầu. Trường hợp nhà thầu vừa là sản xuất, vừa là nhà cung cấp (một số hàng hóa hoặc một phần khối lượng hàng hóa do nhà thầu chào trong HSĐX là do nhà thầu sản xuất, một số hàng hóa khác hoặc một phần khối lượng hàng hóa do nhà thầu mua từ nhà sản xuất, cung cấp khác để cung cấp cho gói thầu) thì ngoài kê khai về năng lực sản xuất, nhà thầu còn phải kê khai về kinh nghiệm thực hiện hợp đồng tương tự theo nội dung quy định tại Mục 4 Bảng số 01 Chương này. Việc đánh giá kinh nghiệm của nhà thầu sẽ được thực hiện trên cơ sở hợp đồng cung cấp hàng hóa tương tự (tương ứng với phần hàng hóa mà nhà thầu mua từ nhà sản xuất, cung cấp khác) và năng lực sản xuất của nhà thầu (tương ứng với phần hàng hóa mà nhà thầu tự sản xuất để cung cấp cho gói thầu). Nhà thầu có thể sử dụng các hồ sơ như hóa đơn bán hàng, số lượng hàng tồn kho. .. để chứng minh sản lượng đã sản xuất trong 01 tháng hoặc 01 năm; sử dụng hồ sơ chứng minh công suất thiết kế của nhà máy, dây chuyền sản xuất để chứng minh năng lực sản xuất. Nhà thầu trong nước thuộc trường hợp quy định tại điểm g Khoản 1 Điều 10 của Luật Đấu thầu khi chào thầu sản phẩm do nhà thầu đó sản xuất không phải đáp ứng tiêu chí này trong thời hạn 05 năm kể từ khi được cơ quan có thẩm quyền công nhận. (11) Trường hợp nhà thầu thiếu cam kết thì được bổ sung trong quá trình đánh giá HSĐX. Trường hợp nhà thầu không bổ sung cam kết trong khoảng thời gian hợp lý theo yêu cầu của Chủ đầu tư thì HSĐX của nhà thầu được coi là không đáp ứng yêu cầu về khả năng bảo hành, cung cấp phụ tùng thay thế hoặc cung cấp các dịch vụ sau bán hàng khác và bị loại. Trường hợp không yêu cầu dịch vụ sau bán hàng thì gạch bỏ tiêu chí đánh giá này. Bảng Y BẢNG YÊU CẦU VỀ HỢP ĐỒNG TƯƠNG TỰ (Áp dụng đối với gói thầu có nhiều loại hàng hóa) [BẢNG: Không tiêu đề] Ghi chú: (1), (2) Nội dung tại cột này được Chủ đầu tư xác định theo nguyên tắc tại ghi chú số (10) Bảng số 01 Chương này. (3) Giá trị tại cột này được Chủ đầu tư xác định theo nguyên tắc nêu tại ghi chú số (11) Bảng số 01 Chương này. (4) Giá trị tại cột này được Chủ đầu tư xác định theo nguyên tắc nêu tại ghi chú số (10) Bảng số 02 Chương này. 2. 2. Tiêu chuẩn đánh giá về nhân sự chủ chốt Không được yêu cầu về huy động nhân sự chủ chốt đối với phần công việc cung cấp hàng hóa. Đối với hàng hóa thông dụng, sẵn có trên thị trường, không đòi hỏi nhân sự thực hiện dịch vụ liên quan (như: lắp đặt, đào tạo, chuyển giao kỹ thuật. ..) phải có trình độ cao thì không yêu cầu về nhân sự chủ chốt. Chỉ được yêu cầu về nhân sự chủ chốt đối với các dịch vụ liên quan có yếu tố đặc thù, phức tạp cần thiết phải có nhân sự có hiểu biết, nhiều kinh nghiệm đảm nhận. Trường hợp HSYC có yêu cầu về nhân sự chủ chốt thì nhà thầu phải chứng minh khả năng huy động các nhân sự chủ chốt đã đề xuất. Nhân sự chủ chốt có thể thuộc biên chế của nhà thầu hoặc do nhà thầu huy động. Trường hợp nhân sự chủ chốt mà nhà thầu đề xuất trong HSĐX không đáp ứng yêu cầu hoặc không chứng minh được khả năng huy động nhân sự (bao gồm cả trường hợp nhân sự đã huy động cho hợp đồng khác có thời gian làm việc trùng với thời gian thực hiện gói thầu này) thì Chủ đầu tư cho phép nhà thầu bổ sung, thay thế. Trường hợp nhà thầu không có nhân sự chủ chốt thay thế đáp ứng yêu cầu của HSYC thì nhà thầu bị loại. Trường hợp nhà thầu cố ý kê khai nhân sự chủ chốt không trung thực trong HSĐX nhằm làm sai lệch kết quả lựa chọn nhà thầu thì nhà thầu không được thay thế nhân sự khác, HSĐX của nhà thầu bị loại và nhà thầu sẽ bị coi là gian lận theo quy định tại điểm b Khoản 4 Điều 16 của Luật Đấu thầu và bị xử lý theo quy định tại Khoản 1 Điều 133 của Nghị định số 214/2025/NĐ-CP. Kinh nghiệm trong các công việc tương tự được thể hiện ở số năm tối thiểu nhân sự thực hiện các công việc tương tự hoặc số hợp đồng tối thiểu trong các công việc tương tự. Số năm kinh nghiệm của nhân sự chủ chốt được tính từ thời điểm nhân sự bắt đầu thực hiện công việc tương tự đó đến thời điểm đóng thầu. Nhà thầu phải cung cấp thông tin chi tiết về các nhân sự chủ chốt được đề xuất theo các Mẫu 08A, 08B và 08C Chương III để chứng minh rằng mình có đầy đủ nhân sự cho các vị trí chủ chốt đáp ứng những yêu cầu sau đây: Bảng số 03: Yêu cầu về nhân sự chủ chốt(1) [BẢNG: Không tiêu đề] Ghi chú: (1) Trường hợp gói thầu không có yêu cầu về nhân sự chủ chốt thì Chủ đầu tư không nhập Bảng này. (2) Chỉ quy định trong trường hợp dịch vụ liên quan có yêu cầu phải có chứng chỉ chuyên môn. Mục 3. Tiêu chuẩn đánh giá về kỹ thuật Sử dụng tiêu chí đạt/không đạt để xây dựng tiêu chuẩn đánh giá về kỹ thuật. Đối với các tiêu chí đánh giá tổng quát, chỉ sử dụng tiêu chí đạt, không đạt. Căn cứ quy mô, tính chất của gói thầu mà xác định mức độ yêu cầu đối với từng nội dung. Đối với các tiêu chí chi tiết cơ bản trong tiêu chí tổng quát, chỉ sử dụng tiêu chí đạt, không đạt; đối với các tiêu chí chi tiết không cơ bản trong tiêu chí tổng quát, ngoài tiêu chí đạt, không đạt, được áp dụng thêm tiêu chí chấp nhận được nhưng không được vượt quá 30% tổng số các tiêu chí chi tiết trong tiêu chí tổng quát đó. Tiêu chí tổng quát được đánh giá là đạt khi tất cả các tiêu chí chi tiết cơ bản được đánh giá là đạt và các tiêu chí chi tiết không cơ bản được đánh giá là đạt hoặc chấp nhận được. HSĐX được đánh giá là đáp ứng yêu cầu về kỹ thuật khi có tất cả các tiêu chí tổng quát đều được đánh giá là đạt. Việc xây dựng tiêu chuẩn đánh giá về kỹ thuật dựa trên các yếu tố về khả năng đáp ứng các yêu cầu về số lượng, chất lượng, thời hạn giao hàng, vận chuyển, lắp đặt, bảo hành, cung cấp các dịch vụ sau bán hàng (nếu có), thông tin về kết quả thực hiện hợp đồng của nhà thầu theo quy định tại Điều 19 và Điều 20 của Nghị định số 214/2025/NĐ-CP, chất lượng hàng hóa tương tự được công khai theo quy định tại Điều 20 của Nghị định số 214/2025/NĐ-CP (nếu có) và các yêu cầu khác nêu trong Chương IV. Căn cứ từng gói thầu cụ thể, khi lập HSYC phải cụ thể hóa các tiêu chí làm cơ sở để đánh giá về kỹ thuật bao gồm: - Đặc tính, thông số kỹ thuật của hàng hóa, tiêu chuẩn sản xuất, tiêu chuẩn chế tạo và kỹ thuật; - Tính hợp lý và hiệu quả tài chính của các giải pháp kỹ thuật, biện pháp tổ chức cung cấp, lắp đặt hàng hóa; - Mức độ đáp ứng các yêu cầu về bảo hành, bảo trì: nhà thầu phải trình bày được kế hoạch cung cấp dịch vụ bảo hành, bảo trì; - Mức độ đáp ứng các yêu cầu về cung cấp vật tư, thiết bị thay thế và các dịch vụ liên quan khác (nếu có) trong toàn bộ quá trình sử dụng của hàng hóa. - Khả năng thích ứng về mặt địa lý, môi trường; - Tác động đối với môi trường và biện pháp giải quyết; - Tiêu chí đấu thầu bền vững (nếu có); - Các yếu tố về điều kiện thương mại, thời gian giao hàng, đào tạo chuyển giao kỹ thuật, cung cấp các dịch vụ sau bán hàng; - Tiến độ cung cấp hàng hóa; - Yếu tố thân thiện môi trường; - Kết quả thực hiện hợp đồng của nhà thầu đối với gói thầu cung cấp hàng hóa, EPC, EP, PC, chìa khóa trao tay theo quy định tại Điều 19 và Điều 20 của Nghị định số 214/2025/NĐ-CP, chất lượng hàng hóa tương tự được công khai theo quy định tại Điều 20 của Nghị định số 214/2025/NĐ-CP (nếu có); - Các yếu tố cần thiết khác. Mục 4. Tiêu chuẩn đánh giá về tài chính Bước 1. Xác định giá thầu; Bước 2. Sửa lỗi, hiệu chỉnh sai lệch theo quy định tại Điều 31 của Nghị định số 214/2025/NĐ-CP (nếu có); Bước 3. Xác định giá thầu sau sửa lỗi, hiệu chỉnh sai lệch (nếu có), trừ đi giá trị giảm giá (nếu có) và đáp ứng tỷ lệ tiết kiệm theo quy định tại Mục 14 Chương I; Chương III. BIỂU MẪU Mẫu 01A ĐƠN DỰ THẦU (Áp dụng đối với nhà thầu là tổ chức) ________, ngày ____ tháng ____ năm ____ Kính gửi: _ [Ghi tên Chủ đầu tư] (sau đây gọi là Chủ đầu tư) Sau khi nghiên cứu hồ sơ yêu cầu và văn bản sửa đổi hồ sơ yêu cầu số ____ [Ghi số của văn bản sửa đổi, nếu có] mà chúng tôi đã nhận được, chúng tôi, _____ [Ghi tên nhà thầu], có địa chỉ tại ______[Ghi địa chỉ của nhà thầu] cam kết thực hiện gói thầu _______[Ghi tên gói thầu] theo đúng yêu cầu của hồ sơ yêu cầu với tổng số tiền là _____ [Ghi giá trị bằng số, bằng chữ và đồng tiền dự thầu] cùng với bảng giá thầu kèm theo. Thời gian thực hiện gói thầu là ____ [Ghi thời gian thực hiện tất cả các công việc theo yêu cầu của gói thầu]. Hồ sơ đề xuất này có hiệu lực trong thời gian ____ ngày, kể từ ngày ____ tháng ____ năm ____ [Ghi ngày có thời điểm đóng thầu]. Chúng tôi cam kết: 1. Không đang trong quá trình thực hiện thủ tục giải thể hoặc bị thu hồi giấy chứng nhận đăng ký doanh nghiệp, giấy chứng nhận đăng ký hợp tác xã, liên hiệp hợp tác xã, tổ hợp tác, không thuộc trường hợp mất khả năng thanh toán theo quy định của pháp luật về phá sản (không đang trong quá trình chấm dứt hoạt động hoặc bị thu hồi giấy chứng nhận đăng ký hộ kinh doanh đối với nhà thầu là hộ kinh doanh). 2. Đã thực hiện nghĩa vụ kê khai thuế và nộp thuế của năm tài chính gần nhất so với thời điểm đóng thầu; 3. Không đang trong thời gian bị cấm dự thầu theo quy định của pháp luật đấu thầu; 4. Không đang bị truy cứu trách nhiệm hình sự (chủ hộ không đang bị truy cứu trách nhiệm hình sự trong trường hợp nhà thầu là hộ kinh doanh); 5. Trong thời hạn 03 năm trước thời điểm đóng thầu, nhà thầu không có nhân sự (ký kết hợp đồng lao động với nhà thầu tại thời điểm nhân sự thực hiện hành vi vi phạm) bị tòa án kết án có hành vi vi phạm quy định về đấu thầu gây hậu quả nghiêm trọng theo quy định của pháp luật về hình sự nhằm mục đích cho nhà thầu trúng thầu(2). 6. Không thực hiện các hành vi tham nhũng, hối lộ, thông thầu, cản trở và các hành vi vi phạm quy định khác của pháp luật đấu thầu khi tham dự gói thầu này. 7. Những thông tin kê khai trong HSĐX là trung thực. 8. Trường hợp trúng thầu, HSĐX và các văn bản bổ sung, làm rõ HSĐX tạo thành thỏa thuận ràng buộc trách nhiệm giữa hai bên cho tới khi hợp đồng được ký kết. 9. Nếu HSĐX của chúng tôi được chấp nhận, chúng tôi sẽ thực hiện biện pháp bảo đảm thực hiện hợp đồng theo quy định của HSYC. [BẢNG: Không tiêu đề] Ghi chú: (1) Trường hợp đại diện theo pháp luật của nhà thầu ủy quyền cho cấp dưới ký đơn dự thầu thì phải gửi kèm theo Giấy ủy quyền theo Mẫu 02 Chương này. Trường hợp tại điều lệ công ty hoặc tại các hồ sơ khác liên quan có phân công trách nhiệm cho cấp dưới ký đơn dự thầu thì phải gửi kèm theo bản chụp các văn bản, hồ sơ này (không cần lập Giấy ủy quyền theo Mẫu 02 Chương này). (2) HSYC không được yêu cầu nhà thầu phải nộp lý lịch tư pháp của nhân sự để chứng minh cho nội dung đánh giá này. Nội dung này chỉ yêu cầu nhà thầu cam kết trong Đơn này. Mẫu 01B ĐƠN DỰ THẦU (Áp dụng đối với nhà thầu là cá nhân, nhóm cá nhân sản xuất sản phẩm đổi mới sáng tạo) ______, ngày ____ tháng ____ năm ____ Kính gửi: ____ [Ghi tên Chủ đầu tư] (sau đây gọi là Chủ đầu tư) Sau khi nghiên cứu hồ sơ yêu cầu (bao gồm văn bản sửa đổi hồ sơ yêu cầu, nếu có), chúng tôi, _____ [Ghi tên cá nhân và mã số thuế cá nhân; đối với nhà thầu là nhóm cá nhân thì ghi tên của các thành viên và mã số thuế theo Mẫu 01C], cam kết thực hiện gói thầu _____ [Ghi tên gói thầu] theo đúng yêu cầu của hồ sơ yêu cầu với tổng số tiền là _____ [Ghi giá trị bằng số, bằng chữ và đồng tiền dự thầu]. Thời gian thực hiện gói thầu là ____ [Ghi thời gian thực hiện tất cả các công việc theo yêu cầu của hồ sơ yêu cầu]. Hồ sơ đề xuất có hiệu lực là ___ngày [Ghi số ngày], kể từ ngày ___tháng ___ năm ___[Ghi ngày có thời điểm đóng thầu]. Chúng tôi cam kết: 1. Có năng lực hành vi dân sự đầy đủ; 2. Đã thực hiện nghĩa vụ kê khai thuế và nộp thuế của năm tài chính gần nhất so với thời điểm đóng thầu; 3. Không đang trong thời gian bị cấm dự thầu theo quy định của pháp luật đấu thầu; 4. Không đang bị truy cứu trách nhiệm hình sự; 5. Không thực hiện các hành vi tham nhũng, hối lộ, thông thầu, cản trở và các hành vi vi phạm quy định khác của pháp luật đấu thầu khi tham dự gói thầu này; 6. Trong thời hạn 03 năm trước thời điểm đóng thầu, các thành viên trong nhóm cá nhân không bị Tòa án kết án có hành vi vi phạm quy định về đấu thầu gây hậu quả nghiêm trọng theo quy định của pháp luật về hình sự nhằm mục đích cho cá nhân (hoặc nhóm cá nhân trong đó có nhân sự vi phạm) trúng thầu (2). 7. Những thông tin kê khai trong HSĐX là trung thực. 8. Trường hợp trúng thầu, HSĐX và các văn bản bổ sung, làm rõ HSĐX tạo thành thỏa thuận ràng buộc trách nhiệm giữa hai bên cho tới khi hợp đồng được ký kết. 9. Nếu HSĐX của chúng tôi được chấp nhận, chúng tôi sẽ thực hiện biện pháp bảo đảm thực hiện hợp đồng theo quy định của HSYC. 10. Có đủ năng lực sản xuất hàng hóa để thực hiện gói thầu. [BẢNG: Không tiêu đề] Ghi chú: (1) Cá nhân dự thầu phải ký đơn dự thầu. Đối với trường hợp nhóm cá nhân thì tất cả các thành viên trong nhóm hoặc thành viên được phân công theo Văn bản thỏa thuận ký đơn dự thầu. (2) HSYC không được yêu cầu nhà thầu phải nộp lý lịch tư pháp của nhân sự để chứng minh cho nội dung đánh giá này. Mẫu 01C VĂN BẢN THỎA THUẬN (Áp dụng đối với nhóm cá nhân sản xuất sản phẩm đổi mới sáng tạo) Ngày: ___ tháng___năm___ Căn cứ HCYC của gói thầu: ______ [ghi tên gói thầu] Chúng tôi gồm có: Thành viên thứ nhất: Họ và tên: Số CCCD/Hộ chiếu: Ngày cấp: Nơi cấp: Mã số thuế: Địa chỉ: Điện thoại: Thành viên thứ hai: Họ và tên: Số CCCD/Hộ chiếu: Ngày cấp: Nơi cấp: Mã số thuế: Địa chỉ: Điện thoại: .. . Thành viên thứ n: Họ và tên: Số CCCD/Hộ chiếu: Ngày cấp: Nơi cấp: Mã số thuế: Địa chỉ: Điện thoại: Các bên (sau đây gọi là thành viên) thống nhất ký kết văn bản thỏa thuận thành lập nhóm cá nhân với các nội dung sau: Điều 1. Nguyên tắc chung 1. Các thành viên tự nguyện thành lập nhóm cá nhân để dự thầu gói thầu____ [ghi tên gói thầu] thuộc ____ [ghi tên dự án/dự toán mua sắm] do____ [ghi tên Chủ đầu tư] tổ chức. 2. Các thành viên cam kết không thành viên nào được tham gia độc lập hoặc liên danh với cá nhân khác để tham gia gói thầu này. Trường hợp trúng thầu, các thành viên cùng ký hợp đồng và không thành viên nào có quyền từ chối thực hiện các trách nhiệm và nghĩa vụ đã quy định trong hợp đồng. Trường hợp thành viên của nhóm từ chối hoàn thành trách nhiệm và nghĩa vụ của mình thì thành viên đó bị xử lý như sau: - Bồi thường thiệt hại cho các bên trong nhóm; - Bồi thường thiệt hại cho Chủ đầu tư theo quy định nêu trong hợp đồng; - Hình thức xử lý khác ____ [ghi rõ hình thức xử lý khác]. Điều 2. Phân công trách nhiệm Các thành viên thống nhất phân công trách nhiệm để thực hiện gói thầu____ [ghi tên gói thầu] thuộc ____ [ghi tên dự án/dự toán mua sắm] như sau: Phân công ____ [ghi tên cá nhân] làm thành viên đứng đầu nhóm, đại diện cho nhóm trong những phần việc sau: [- Ký các văn bản, hồ sơ để giao dịch với Chủ đầu tư trong quá trình dự thầu, văn bản giải trình, làm rõ HSĐX hoặc văn bản đề nghị rút HSĐX; - Thực hiện bảo đảm dự thầu cho cả nhóm; - Tham gia quá trình hoàn thiện hợp đồng; - Ký đơn kiến nghị trong trường hợp nhà thầu có kiến nghị; - Các công việc khác trừ việc ký kết hợp đồng ____ [ghi rõ nội dung các công việc khác (nếu có)]. Điều 3. Hiệu lực của văn bản thỏa thuận 1. Văn bản thỏa thuận có hiệu lực kể từ ngày ký. 2. Văn bản thỏa thuận chấm dứt hiệu lực trong các trường hợp sau: - Các bên hoàn thành trách nhiệm, nghĩa vụ của mình và tiến hành thanh lý hợp đồng; - Các bên cùng thỏa thuận chấm dứt; - Nhóm cá nhân không trúng thầu; - Hủy thầu gói thầu ____ [ghi tên gói thầu] thuộc ____ [ghi tên dự án/dự toán mua sắm] theo thông báo của Chủ đầu tư. Văn bản thỏa thuận được lập trên sự chấp thuận của tất cả các thành viên. THÀNH VIÊN ĐỨNG ĐẦU NHÓM CÁ NHÂN [ký, ghi rõ họ tên] CÁC THÀNH VIÊN THUỘC NHÓM CÁ NHÂN [ký, ghi rõ họ tên] Mẫu 02 GIẤY ỦY QUYỀN(1) Hôm nay, ngày ____ tháng ____ năm ____, tại ____ Tôi là____ [Ghi tên, số CCCD hoặc số hộ chiếu, chức danh của người đại diện theo pháp luật của nhà thầu], là người đại diện theo pháp luật của ____ [Ghi tên nhà thầu] có địa chỉ tại____ [Ghi địa chỉ của nhà thầu] bằng văn bản này ủy quyền cho___ [Ghi tên, số CCCD hoặc số hộ chiếu, chức danh của người được ủy quyền] thực hiện các công việc sau đây trong quá trình dự thầu gói thầu__[Ghi tên gói thầu] thuộc ___ [Ghi tên dự án/dự toán mua sắm] do__ [Ghi tên Chủ đầu tư] tổ chức: [- Ký đơn dự thầu; - Ký thỏa thuận liên danh (nếu có); - Ký các văn bản, hồ sơ để giao dịch với Chủ đầu tư trong quá trình dự thầu, kể cả văn bản giải trình, làm rõ HSĐX; - Tham gia quá trình thương thảo (nếu có), hoàn thiện hợp đồng; - Ký kết hợp đồng với Chủ đầu tư nếu được chỉ định thầu.] (2) Người được ủy quyền nêu trên chỉ thực hiện các công việc trong phạm vi ủy quyền với tư cách là đại diện hợp pháp của ____ [Ghi tên nhà thầu]. ____ [Ghi tên nhà thầu] chịu trách nhiệm hoàn toàn về những công việc do ____ [Ghi tên người được ủy quyền] thực hiện trong phạm vi ủy quyền. Giấy ủy quyền có hiệu lực kể từ ngày ____ đến ngày ____(3). Giấy ủy quyền này được lập thành ____ bản có giá trị pháp lý như nhau, người ủy quyền giữ ____ bản, người được ủy quyền giữ ____ bản. [BẢNG: Không tiêu đề] Ghi chú: (1) Trường hợp ủy quyền thì bản gốc giấy ủy quyền phải được gửi cho Chủ đầu tư cùng với đơn dự thầu. Việc ủy quyền của người đại diện theo pháp luật của nhà thầu cho cấp phó, cấp dưới, giám đốc chi nhánh, người đứng đầu văn phòng đại diện của nhà thầu để thay mặt cho người đại diện theo pháp luật của nhà thầu thực hiện một hoặc các nội dung công việc nêu trên đây. Việc sử dụng con dấu trong trường hợp được ủy quyền có thể là dấu của nhà thầu hoặc dấu của đơn vị mà cá nhân liên quan được ủy quyền. Người được ủy quyền không được tiếp tục ủy quyền cho người khác. (2) Phạm vi ủy quyền bao gồm một hoặc nhiều công việc nêu trên. (3) Ghi ngày có hiệu lực và ngày hết hiệu lực của giấy ủy quyền phù hợp với quá trình dự thầu và phải bảo đảm có hiệu lực trước ngày thực hiện các công việc được ủy quyền. Mẫu 03 THỎA THUẬN LIÊN DANH (1), ngày tháng năm Gói thầu: [Ghi tên gói thầu] Thuộc: [Ghi tên dự án/dự toán mua sắm] - Căn cứ(2)_[Luật Đấu thầu]; - Căn cứ(2); - Căn cứ hồ sơ yêu cầu gói thầu __[Ghi tên gói thầu] ngày ___ tháng___ năm__[Ngày được ghi trên HSYC]; Chúng tôi, đại diện cho các bên ký thỏa thuận liên danh, gồm có: Tên thành viên liên danh [Ghi tên từng thành viên liên danh] Đại diện là ông/bà: Chức vụ: Địa chỉ: Điện thoại: E-mail: Tài khoản: Mã số thuế: Giấy ủy quyền số ngày ___tháng ____ năm ___ (trường hợp được ủy quyền). Các bên (sau đây gọi là thành viên) thống nhất ký kết thỏa thuận liên danh với các nội dung sau: Điều 1. Nguyên tắc chung 1. Các thành viên tự nguyện hình thành liên danh để dự thầu gói thầu___ [Ghi tên gói thầu] thuộc ___ [Ghi tên dự án/dự toán mua sắm]. 2. Các thành viên thống nhất tên gọi của liên danh cho mọi giao dịch liên quan đến gói thầu này là: [Ghi tên của liên danh theo thỏa thuận]. 3. Các thành viên cam kết không thành viên nào có quyền từ chối thực hiện các trách nhiệm và nghĩa vụ quy định trong hợp đồng. Trường hợp thành viên của liên danh từ chối hoàn thành trách nhiệm riêng của mình như đã thỏa thuận thì thành viên đó bị xử lý như sau: - Bồi thường thiệt hại cho các bên trong liên danh; - Bồi thường thiệt hại cho Chủ đầu tư theo quy định nêu trong hợp đồng; - Hình thức xử lý khác [Ghi rõ hình thức xử lý khác]. Điều 2. Phân công trách nhiệm Các thành viên thống nhất chịu trách nhiệm chung, trách nhiệm riêng để thực hiện gói thầu [Ghi tên gói thầu] thuộc ___ [Ghi tên dự án/dự toán mua sắm] đối với từng thành viên như sau: 1. Thành viên đứng đầu liên danh Các bên nhất trí ủy quyền cho [Ghi tên một bên] làm thành viên đứng đầu liên danh, đại diện cho liên danh trong những phần việc sau(3): [- Ký đơn dự thầu; - Ký các văn bản, hồ sơ để giao dịch với Chủ đầu tư trong quá trình dự thầu, kể cả văn bản đề nghị làm rõ HSYC và văn bản giải trình, làm rõ HSĐX; - Tham gia quá trình thương thảo (nếu có), hoàn thiện hợp đồng; - Ký đơn kiến nghị trong trường hợp nhà thầu có kiến nghị; - Các công việc khác trừ việc ký kết hợp đồng [Ghi rõ nội dung các công việc khác (nếu có)]. 2. Các thành viên trong liên danh thỏa thuận phân công trách nhiệm thực hiện công việc theo bảng dưới đây (4): [BẢNG: Không tiêu đề] Điều 3. Hiệu lực của thỏa thuận liên danh 1. Thỏa thuận liên danh có hiệu lực kể từ ngày ký. 2. Thỏa thuận liên danh chấm dứt hiệu lực trong các trường hợp sau: - Các bên hoàn thành trách nhiệm và nghĩa vụ của mình và tiến hành thanh lý hợp đồng; - Các bên cùng thỏa thuận chấm dứt; - Nhà thầu liên danh không được chỉ định thầu; - Hủy thầu gói thầu [Ghi tên gói thầu] thuộc [Ghi tên dự án/dự toán mua sắm] theo thông báo của Chủ đầu tư. Thỏa thuận liên danh được lập thành bản, mỗi bên giữ bản, các bản thỏa thuận có giá trị pháp lý như nhau. ĐẠI DIỆN HỢP PHÁP CỦA THÀNH VIÊN ĐỨNG ĐẦU LIÊN DANH(5) [Ghi tên, chức danh, ký tên và đóng dấu] ĐẠI DIỆN HỢP PHÁP CỦA THÀNH VIÊN LIÊN DANH [Ghi tên từng thành viên, chức danh, ký tên và đóng dấu] Ghi chú: (1) Căn cứ quy mô, tính chất của gói thầu, nội dung thỏa thuận liên danh theo mẫu này có thể được sửa đổi bổ sung cho phù hợp. (2) Cập nhật các văn bản quy phạm pháp luật theo quy định hiện hành. (3) Phạm vi ủy quyền bao gồm một hoặc nhiều công việc nêu trên. (4) Nhà thầu phải ghi rõ nội dung công việc cụ thể và ước tính giá trị tương ứng mà từng thành viên trong liên danh sẽ thực hiện, trách nhiệm chung, trách nhiệm của từng thành viên, kể cả thành viên đứng đầu liên danh. Việc phân chia công việc trong liên danh phải căn cứ các hạng mục nêu trong bảng giá thầu tại Mẫu 4. 1 (4. 1A hoặc 4. 1B hoặc 4. 1C) hoặc Mẫu 4. 2 (4. 2A hoặc 4. 2B hoặc 4. 2C) Chương này hoặc theo các công việc thuộc quá trình sản xuất hạng mục trong bảng giá thầu, không được phân chia các công việc không thuộc các hạng mục này hoặc không thuộc quá trình sản xuất các hạng mục này; không được phân chia các công việc không thuộc các hạng mục này hoặc không thuộc quá trình sản xuất các hạng mục này. (5) Đại diện hợp pháp của thành viên liên danh có thể là người đại diện theo pháp luật hoặc người được người đại diện theo pháp luật ủy quyền. Mẫu 4. 1A BẢNG giá thầu (Áp dụng với hợp đồng trọn gói) I. Hàng hóa dự thầu [BẢNG: Không tiêu đề] Ghi chú: - Chủ đầu tư điền nội dung tại các cột: (1), (2), (3), (4), (5), (6), (7), (8), (9), (10). Đối với cột (8), Chủ đầu tư dẫn chiếu đến nội dung tương ứng quy định tại Chương IV. - Nhà thầu điền từ cột (11), (12), (13): (11): Nhà thầu biết mã HS của hàng hóa thì nhà thầu liệt kê; (12), (13): Nhà thầu điền đơn giá, thành tiền bao gồm thuế, phí, lệ phí (nếu có). Khi dự thầu, nhà thầu phải chịu trách nhiệm tìm hiểu, tính toán và chào đầy đủ các loại thuế, phí, lệ phí (nếu có) theo thuế suất, mức phí, lệ phí tại thời điểm 28 ngày trước ngày có thời điểm đóng thầu theo quy định. II. Dịch vụ liên quan [BẢNG: Không tiêu đề] Ghi chú: - Cột (1) đến (6): Chủ đầu tư điền, trong đó dẫn chiếu đến yêu cầu tại Chương IV cho phù hợp. - Cột (7), (8): Nhà thầu chào (bao gồm tất cả các loại thuế, phí, lệ phí). [BẢNG: Không tiêu đề] III. Tổng hợp giá thầu Đại diện hợp pháp của nhà thầu [ghi tên, chức danh, ký tên và đóng dấu] Mẫu 4. 1B BẢNG giá thầu (Áp dụng với loại hợp đồng theo đơn giá) I. Hàng hóa dự thầu [BẢNG: Không tiêu đề] Ghi chú: - Chủ đầu tư điền nội dung tại các cột: (1), (2), (3), (4), (5), (6), (7), (8), (9), (10). Đối với cột (8), Chủ đầu tư dẫn chiếu đến nội dung tương ứng quy định tại Chương IV. - Nhà thầu điền từ cột (11), (12), (13): (11): Nhà thầu biết mã HS của hàng hóa thì nhà thầu liệt kê; (12), (13): Nhà thầu điền đơn giá, thành tiền bao gồm thuế, phí, lệ phí (nếu có). Khi dự thầu, nhà thầu phải chịu trách nhiệm tìm hiểu, tính toán và chào đầy đủ các loại thuế, phí, lệ phí (nếu có) theo thuế suất, mức phí, lệ phí tại thời điểm 28 ngày trước ngày có thời điểm đóng thầu theo quy định. II. Dịch vụ liên quan [BẢNG: Không tiêu đề] Ghi chú: - Cột (1) đến (6): Chủ đầu tư điền, trong đó dẫn chiếu đến yêu cầu tại Chương IV cho phù hợp. - Cột (7), (8): Nhà thầu chào (bao gồm tất cả các loại thuế, phí, lệ phí). [BẢNG: Không tiêu đề] III. Tổng hợp giá thầu Ghi chú: (*): a%: Chủ đầu tư quy định giá trị của a (%) để nhà thầu làm cơ sở chào chi phí dự phòng. Đại diện hợp pháp của nhà thầu [ghi tên, chức danh, ký tên và đóng dấu] Mẫu 4. 1C BẢNG giá thầu (Áp dụng với loại hợp đồng hỗn hợp) I. Hàng hóa dự thầu [BẢNG: Không tiêu đề] Ghi chú: - Chủ đầu tư điền nội dung tại các cột: (1), (2), (3), (4), (5), (6), (7), (8), (9), (10). Đối với cột (8), Chủ đầu tư dẫn chiếu đến nội dung tương ứng quy định tại Chương IV. - Nhà thầu điền từ cột (11), (12), (13): (11): Nhà thầu biết mã HS của hàng hóa thì nhà thầu liệt kê; (12), (13): Nhà thầu điền đơn giá, thành tiền bao gồm thuế, phí, lệ phí (nếu có). Khi dự thầu, nhà thầu phải chịu trách nhiệm tìm hiểu, tính toán và chào đầy đủ các loại thuế, phí, lệ phí (nếu có) theo thuế suất, mức phí, lệ phí tại thời điểm 28 ngày trước ngày có thời điểm đóng thầu theo quy định. II. Dịch vụ liên quan [BẢNG: Không tiêu đề] Ghi chú: - Cột (1) đến (6): Chủ đầu tư điền, trong đó dẫn chiếu đến yêu cầu tại Chương IV cho phù hợp. - Cột (7), (8): Nhà thầu chào (bao gồm tất cả các loại thuế, phí, lệ phí). [BẢNG: Không tiêu đề] III. Tổng hợp giá thầu Ghi chú: (*): a%: Chủ đầu tư quy định giá trị của a (%) để nhà thầu làm cơ sở chào chi phí dự phòng. Đại diện hợp pháp của nhà thầu [ghi tên, chức danh, ký tên và đóng dấu] Mẫu 4. 2A BẢNG giá thầu (Áp dụng loại hợp đồng trọn gói) I. Hàng hóa được sản xuất, gia công tại Việt Nam [BẢNG: Không tiêu đề] Ghi chú: - Chủ đầu tư điền các cột (1) (2) (3) (4) (5) (6) (7) (8) (9) (10) (8): Dẫn chiếu đến nội dung tương ứng quy định tại Chương IV. - Nhà thầu điền các cột sau: Cột (11): Nhà thầu biết mã HS của hàng hóa thì nhà thầu liệt kê; Cột (14): Chi phí vận chuyển, bảo hiểm và các dịch vụ khác (đã bao gồm thuế VAT) để vận chuyển hàng hóa đến địa điểm theo yêu cầu. Cột (16) Thuế tiêu thụ đặc biệt (nếu có), thuế VAT phải nộp trong trường hợp nhà thầu được trao hợp đồng. Cột (12) (13) (15) (17): Nhà thầu điền. II. Hàng hóa được sản xuất, gia công ngoài nước đã được nhập khẩu hoặc sẽ được nhập khẩu vào Việt Nam [BẢNG: Không tiêu đề] Ghi chú: - Chủ đầu tư điền các cột (1) (2) (3) (4) (5) (6) (7) (8) (9) (10) (8): Dẫn chiếu đến nội dung tương ứng quy định tại Chương IV. - Nhà thầu điền các cột sau: Cột (11): Nhà thầu biết mã HS của hàng hóa thì nhà thầu liệt kê; Cột (14): Chi phí vận chuyển, bảo hiểm và các dịch vụ khác (đã bao gồm thuế VAT) ở Việt Nam để vận chuyển hàng hóa đến địa điểm theo yêu cầu. Cột (12) (13) (15) (16) (17) (18) (19) (20): Nhà thầu điền. III. Dịch vụ liên quan [BẢNG: Không tiêu đề] Ghi chú: - Cột (1) đến (6): Chủ đầu tư điền, trong đó dẫn chiếu đến yêu cầu tại Chương IV cho phù hợp. - Cột (7) (8): Nhà thầu chào (bao gồm tất cả các loại thuế, phí, lệ phí). IV. Tổng hợp giá thầu [BẢNG: Không tiêu đề] Đại diện hợp pháp của nhà thầu [ghi tên, chức danh, ký tên và đóng dấu] Mẫu 4. 2B BẢNG giá thầu (Áp dụng loại hợp đồng theo đơn giá) I. Hàng hóa được sản xuất, gia công tại Việt Nam [BẢNG: Không tiêu đề] Ghi chú: - Chủ đầu tư điền các cột (1) (2) (3) (4) (5) (6) (7) (8) (9) (10) (8): Dẫn chiếu đến nội dung tương ứng quy định tại Chương IV. - Nhà thầu điền các cột sau: Cột (11): Nhà thầu biết mã HS của hàng hóa thì nhà thầu liệt kê; Cột (14): Chi phí vận chuyển, bảo hiểm và các dịch vụ khác (đã bao gồm thuế VAT) để vận chuyển hàng hóa đến địa điểm theo yêu cầu. Cột (16) Thuế tiêu thụ đặc biệt (nếu có), thuế VAT phải nộp trong trường hợp nhà thầu được trao hợp đồng. Cột (12) (13) (15) (17): Nhà thầu điền. II. Hàng hóa được sản xuất, gia công ngoài nước đã được nhập khẩu hoặc sẽ được nhập khẩu vào Việt Nam [BẢNG: Không tiêu đề] Ghi chú: - Chủ đầu tư điền các cột (1) (2) (3) (4) (5) (6) (7) (8) (9) (10) (8): Dẫn chiếu đến nội dung tương ứng quy định tại Chương IV. - Nhà thầu điền các cột sau: Cột (11): Nhà thầu biết mã HS của hàng hóa thì nhà thầu liệt kê; Cột (14): Chi phí vận chuyển, bảo hiểm và các dịch vụ khác (đã bao gồm thuế VAT) ở Việt Nam để vận chuyển hàng hóa đến địa điểm theo yêu cầu. Cột (12) (13) (15) (16) (17) (18) (19) (20): Nhà thầu điền. III. Dịch vụ liên quan [BẢNG: Không tiêu đề] Ghi chú: - Cột (1) đến (6): Chủ đầu tư điền, trong đó dẫn chiếu đến yêu cầu tại Chương IV cho phù hợp. - Cột (7) (8): Nhà thầu chào (bao gồm tất cả các loại thuế, phí, lệ phí). IV. Tổng hợp giá thầu [BẢNG: Không tiêu đề] Ghi chú: (*): a%: Chủ đầu tư quy định giá trị của a (%) để nhà thầu làm cơ sở chào chi phí dự phòng. Đại diện hợp pháp của nhà thầu [ghi tên, chức danh, ký tên và đóng dấu] Mẫu 4. 2C BẢNG giá thầu (Áp dụng loại hợp đồng hỗn hợp) I. Hàng hóa được sản xuất, gia công tại Việt Nam [BẢNG: Không tiêu đề] Ghi chú: - Chủ đầu tư điền các cột (1) (2) (3) (4) (5) (6) (7) (8) (9) (10) (8): Dẫn chiếu đến nội dung tương ứng quy định tại Chương IV. - Nhà thầu điền các cột sau: Cột (11): Nhà thầu biết mã HS của hàng hóa thì nhà thầu liệt kê; Cột (14): Chi phí vận chuyển, bảo hiểm và các dịch vụ khác (đã bao gồm thuế VAT) để vận chuyển hàng hóa đến địa điểm theo yêu cầu. Cột (16) Thuế tiêu thụ đặc biệt (nếu có), thuế VAT phải nộp trong trường hợp nhà thầu được trao hợp đồng. Cột (12) (13) (15) (17): Nhà thầu điền. II. Hàng hóa được sản xuất, gia công ngoài nước đã được nhập khẩu hoặc sẽ được nhập khẩu vào Việt Nam [BẢNG: Không tiêu đề] Ghi chú: - Chủ đầu tư điền các cột (1) (2) (3) (4) (5) (6) (7) (8) (9) (10) (8): Dẫn chiếu đến nội dung tương ứng quy định tại Chương IV. - Nhà thầu điền các cột sau: Cột (11): Nhà thầu biết mã HS của hàng hóa thì nhà thầu liệt kê; Cột (14): Chi phí vận chuyển, bảo hiểm và các dịch vụ khác (đã bao gồm thuế VAT) ở Việt Nam để vận chuyển hàng hóa đến địa điểm theo yêu cầu. Cột (12) (13) (15) (16) (17) (18) (19) (20): Nhà thầu điền. III. Dịch vụ liên quan [BẢNG: Không tiêu đề] Ghi chú: - Cột (1) đến (6): Chủ đầu tư điền, trong đó dẫn chiếu đến yêu cầu tại Chương IV cho phù hợp. - Cột (7) (8): Nhà thầu chào (bao gồm tất cả các loại thuế, phí, lệ phí). IV. Tổng hợp giá thầu [BẢNG: Không tiêu đề] Ghi chú: (*): a%: Chủ đầu tư quy định giá trị của a (%) để nhà thầu làm cơ sở chào chi phí dự phòng. Đại diện hợp pháp của nhà thầu [ghi tên, chức danh, ký tên và đóng dấu] Mẫu 05 BẢNG TIẾN ĐỘ CUNG CẤP(*) Nhà thầu đề xuất tiến độ cung cấp phù hợp với yêu cầu của Chủ đầu tư [BẢNG: Không tiêu đề] Đại diện hợp pháp của nhà thầu [ghi tên, chức danh, ký tên và đóng dấu] Ghi chú: Cột (1) (2) (3)(4) (5) (6) (7): Chủ đầu tư điền. Cột (8): Nhà thầu điền; (*) Hàng hóa phải được giao trong khoảng thời gian quy định trong HSYC. Nhà thầu đề xuất thời gian giao hàng sớm hơn ngày giao hàng sớm nhất thì không được tính ưu tiên và không bị loại. Nhà thầu đề xuất thời gian giao hàng muộn hơn khoảng thời gian này thì HSĐX của nhà thầu sẽ bị loại. Mẫu 06 BẢN KÊ KHAI THÔNG TIN VỀ NHÀ THẦU (1) Ngày: _________________ Tên gói thầu: _________________ [BẢNG: Không tiêu đề] Ghi chú: (1) Đối với nhà thầu liên danh thì từng thành viên phải kê khai theo Mẫu này. Mẫu 07A [BẢNG: Không tiêu đề] Thông tin về từng hợp đồng, mỗi hợp đồng cần bảo đảm các thông tin sau đây: [BẢNG: Không tiêu đề] Nhà thầu nghiên cứu kỹ HSYC và đề xuất các hợp đồng tương tự khác nhau để bảo đảm đáp ứng yêu cầu của HSYC. Nhà thầu phải gửi kèm theo bản chụp các văn bản, hồ sơ liên quan đến các hợp đồng đó (xác nhận của Chủ đầu tư về hợp đồng thực hiện theo các nội dung liên quan trong bảng trên). Ghi chú: (1) Trong trường hợp liên danh, từng thành viên trong liên danh kê khai theo Mẫu này. Trường hợp nhà thầu có nhiều hợp đồng tương tự thì kê khai từng hợp đồng theo Mẫu này. Trường hợp HSYC không yêu cầu về kinh nghiệm thực hiện hợp đồng cung cấp hàng hoá tương tự thì bỏ qua Bảng này. (2) Nhà thầu chỉ kê khai nội dung tương tự với yêu cầu của gói thầu. (3) Trường hợp giá trị hợp đồng không tính bằng VND thì quy đổi sang VND theo tỷ giá theo quy định tại Mục 2. 1 Chương II để làm cơ sở đánh giá. Mẫu 07B [BẢNG: Không tiêu đề] Số lượng nhà máy, cơ sở sản xuất (gọi chung là nhà máy): ____ [Điền số nhà máy] Đối với mỗi nhà máy, nhà thầu kê khai thông tin sau đây: [BẢNG: Không tiêu đề] Ghi chú: Trong trường hợp liên danh, từng thành viên trong liên danh kê khai theo Mẫu này. Trường hợp HSYC không yêu cầu về năng lực sản xuất hàng hóa thì bỏ qua Bảng này. Mẫu 08A BẢNG ĐỀ XUẤT NHÂN SỰ CHỦ CHỐT Nhà thầu phải kê khai những nhân sự chủ chốt theo quy định tại Mục 2. 2 Chương II và phải chứng minh khả năng sẵn sàng huy động các nhân sự này để tham gia thực hiện gói thầu. Nhân sự chủ chốt có thể thuộc biên chế của nhà thầu hoặc do nhà thầu huy động. Trường hợp nhân sự chủ chốt mà nhà thầu đề xuất trong HSĐX không đáp ứng yêu cầu hoặc không chứng minh được khả năng huy động nhân sự (bao gồm cả trường hợp nhân sự đã huy động cho hợp đồng khác có thời gian làm việc trùng với thời gian thực hiện gói thầu này) thì Chủ đầu tư cho phép nhà thầu bổ sung, thay thế. Trường hợp nhà thầu không có nhân sự thay thế đáp ứng yêu cầu của HSYC thì HSĐX bị loại. Trường hợp nhà thầu cố ý kê khai nhân sự chủ chốt không trung thực trong HSĐX nhằm làm sai lệch kết quả lựa chọn nhà thầu thì nhà thầu không được thay thế nhân sự khác, HSĐX của nhà thầu bị loại và nhà thầu sẽ bị coi là gian lận theo quy định tại điểm b Khoản 4 Điều 16 của Luật Đấu thầu và bị xử lý theo quy định tại Khoản 1 Điều 133 của Nghị định số 214/2025/NĐ-CP. [BẢNG: Không tiêu đề] Mẫu 08B [BẢNG: Không tiêu đề] Nhà thầu phải cung cấp tất cả các thông tin trong HSĐX theo yêu cầu tại Bảng trên. Mẫu 08C [BẢNG: BẢNG KINH NGHIỆM CHUYÊN MÔN] Liệt kê theo trình tự thời gian quá trình công tác của chuyên gia, không cần liệt kê các công việc đã làm không phù hợp hoặc không liên quan với công việc đang yêu cầu. Nhà thầu phải cung cấp tất cả các thông tin được yêu cầu. Mẫu 09 HỢP ĐỒNG CUNG CẤP HÀNG HÓA, EPC, EP, PC, CHÌA KHÓA TRAO TAY KHÔNG HOÀN THÀNH DO LỖI CỦA NHÀ THẦU TRONG QUÁ KHỨ(1) Tên nhà thầu: ________________ Ngày: ______________________ Tên thành viên của nhà thầu liên danh (nếu có): _________________________ [BẢNG: Không tiêu đề] Ghi chú: (1) Nhà thầu phải kê khai chính xác, trung thực các hợp đồng cung cấp hàng hóa, EPC, EP, PC, chìa khóa trao tay không hoàn thành do lỗi của nhà thầu trong quá khứ; trường hợp Chủ đầu tư, tổ chuyên gia phát hiện nhà thầu có hợp đồng cung cấp hàng hóa, EPC, EP, PC, chìa khóa trao tay không hoàn thành do lỗi của nhà thầu trong quá khứ mà không kê khai thì nhà thầu được coi là có hành vi gian lận và HSĐX của nhà thầu sẽ bị loại. Trường hợp nhà thầu liên danh thì từng thành viên liên danh phải kê khai theo Mẫu này. Mẫu 10 TÌNH HÌNH TÀI CHÍNH CỦA NHÀ THẦU(1) Tên nhà thầu: ________________ Ngày: ______________________ [BẢNG: Không tiêu đề] Ghi chú: (1) Trường hợp nhà thầu liên danh thì từng thành viên liên danh phải kê khai theo Mẫu này. (2) Để xác định doanh thu bình quân hằng năm (không bao gồm thuế VAT), nhà thầu chia tổng doanh thu của các năm (không bao gồm thuế VAT) cho số năm dựa trên thông tin đã được cung cấp. Doanh thu hằng năm được tính bằng tổng doanh thu trong báo cáo tài chính của năm đó (chưa bao gồm thuế VAT). Doanh thu bình quân hằng năm (không bao gồm thuế VAT) = tổng doanh thu từng năm (không bao gồm thuế VAT) theo yêu cầu của HSYC/số năm. Trường hợp nhà thầu mới thành lập không đủ số năm theo yêu cầu của HSYC thì Doanh thu bình quân hằng năm (không bao gồm thuế VAT) được tính trên cơ sở số năm mà nhà thầu có số liệu tài chính. Nhà thầu phải nộp các hồ sơ như sau: Bản sao các báo cáo tài chính (các bảng cân đối kế toán bao gồm tất cả thuyết minh có liên quan, và các báo cáo kết quả kinh doanh) cho các năm như đã nêu trên, tuân thủ các điều kiện sau: 1. Phản ánh tình hình tài chính của nhà thầu hoặc thành viên liên danh (nếu là nhà thầu liên danh) mà không phải tình hình tài chính của một chủ thể liên kết như công ty mẹ liên kết với công ty con hoặc công ty liên kết với nhà thầu hoặc thành viên liên danh. 2. Các báo cáo tài chính phải hoàn chỉnh, đầy đủ nội dung theo quy định. 3. Các báo cáo tài chính phải tương ứng với các kỳ kế toán đã hoàn thành kèm theo bản chụp được chứng thực một trong các hồ sơ sau đây: - Biên bản kiểm tra quyết toán thuế; - Tờ khai tự quyết toán thuế (thuế giá trị gia tăng và thuế thu nhập doanh nghiệp) có xác nhận của cơ quan thuế về thời điểm đã nộp tờ khai; - hồ sơ chứng minh việc nhà thầu đã kê khai quyết toán thuế điện tử; - Văn bản xác nhận của cơ quan quản lý thuế (xác nhận số nộp cả năm) về việc thực hiện nghĩa vụ nộp thuế; - Báo cáo kiểm toán (nếu có); - Các hồ sơ khác. Các hồ sơ trên đây phải phù hợp với số liệu nhà thầu đã kê khai trên Hệ thống Thuế điện tử tại thời điểm đóng thầu. Mẫu 11A DANH SÁCH CÁC CÔNG TY, CÔNG TY THÀNH VIÊN ĐẢM NHẬN PHẦN CÔNG VIỆC CỦA GÓI THẦU(1) [BẢNG: Không tiêu đề] Ghi chú: (1) Trường hợp nhà thầu dự thầu là công ty mẹ (ví dụ như Tổng công ty) huy động công ty con, công ty thành viên thực hiện một phần công việc gói thầu thì phải kê khai cụ thể tại bảng này. Việc đánh giá kinh nghiệm thực hiện hợp đồng tương tự căn cứ vào giá trị, khối lượng công việc do công ty mẹ, công ty con đảm nhiệm trong gói thầu. Trường hợp nhà thầu dự thầu không phải là công ty mẹ thì không áp dụng Mẫu này. (2) Ghi cụ thể tên công ty con, công ty thành viên. (3) Ghi cụ thể phần công việc đảm nhận của công ty con, công ty thành viên. (4) Ghi cụ thể giá trị % công việc của công ty con, công ty thành viên đảm nhận so với giá thầu. Mẫu 11B PHẠM VI CÔNG VIỆC SỬ DỤNG thầu phụ(1) (chỉ áp dụng đối với dịch vụ liên quan) [BẢNG: Không tiêu đề] Ghi chú: (1) Trường hợp sử dụng thầu phụ để thực hiện dịch vụ liên quan thì nhà thầu kê khai theo Mẫu này. Đối với gói thầu của dự án thuộc lĩnh vực khoa học, kỹ thuật, đổi mới sáng tạo và chuyển đổi số tổ chức đấu thầu trong nước, nhà thầu trong nước được sử dụng thầu phụ là nhà thầu nước ngoài đối với phần công việc đặc thù mà nhà thầu trong nước chưa thực hiện được hoặc cần chuyển giao kỹ thuật theo quy định tại Khoản 4 Điều 11 Luật Đấu thầu. (2) Nhà thầu ghi cụ thể tên thầu phụ. Trường hợp khi dự thầu chưa xác định được cụ thể danh tính của thầu phụ thì không phải kê khai vào cột này mà chỉ kê khai vào cột \"Phạm vi công việc”. Nếu nhà thầu trúng thầu thì khi huy động thầu phụ thực hiện công việc đã kê khai phải được sự chấp thuận của Chủ đầu tư. (3) Nhà thầu ghi cụ thể tên hạng mục công việc dành cho thầu phụ. (4) Nhà thầu ghi cụ thể khối lượng công việc dành cho thầu phụ. (5) Nhà thầu ghi giá trị % công việc ước tính mà từng thầu phụ đảm nhận so với giá thầu. (6) Nhà thầu ghi cụ thể số hợp đồng hoặc văn bản thỏa thuận sử dụng thầu phụ và phải nộp kèm theo bản gốc hoặc bản chụp được chứng thực các hồ sơ đó. Trường hợp chưa xác định được tên thầu phụ thì để trống cột này. Phần 2. YÊU VẦU VỀ KỸ THUẬT Chương IV. YÊU CẦU VỀ KỸ THUẬT CỦA HÀNG HÓA Mục 1. Yêu cầu về kỹ thuật Yêu cầu về kỹ thuật bao gồm yêu cầu kỹ thuật (mang tính kỹ thuật thuần túy) và các yêu cầu khác liên quan đến việc cung cấp hàng hóa (trừ giá). Yêu cầu về kỹ thuật phải được nêu đầy đủ, rõ ràng và cụ thể để làm cơ sở cho nhà thầu lập HSĐX. Yêu cầu về mặt kỹ thuật bao gồm các nội dung cơ bản như sau: 1. 1. Giới thiệu chung về dự án/dự toán mua sắm, gói thầu Khoản này nêu thông tin tóm tắt về dự án/dự toán mua sắm và gói thầu như địa điểm thực hiện dự án/dự toán mua sắm, quy mô của dự án/dự toán mua sắm, yêu cầu về cung cấp hàng hóa thuộc gói thầu, thời gian thực hiện gói thầu và những thông tin khác tùy theo tính chất và yêu cầu của gói thầu. 1. 2. Yêu cầu về kỹ thuật Yêu cầu về kỹ thuật bao gồm yêu cầu kỹ thuật chung và yêu cầu kỹ thuật chi tiết đối với hàng hóa thuộc phạm vi cung cấp của gói thầu, cụ thể: a) Yêu cầu kỹ thuật chung là các yêu cầu về chủng loại, tiêu chuẩn hàng hóa và các yêu cầu về kiểm tra, thử nghiệm, đóng gói, vận chuyển, điều kiện khí hậu tại nơi hàng hóa được sử dụng. Tùy thuộc vào sự phức tạp của hàng hóa, các yêu cầu kỹ thuật chung được nêu cho tất cả các hàng hóa hoặc cho từng loại hàng hóa riêng biệt. b) Yêu cầu kỹ thuật chi tiết như tính năng, thông số kỹ thuật, các bản vẽ, catalô, các thông số bảo hành. .. được nêu cho từng loại hàng hóa. Khi nêu yêu cầu, các thông số kỹ thuật có thể được mô tả dưới hình thức bảng biểu. Mục đích của phần Thông số kỹ thuật là xác định các đặc tính kỹ thuật của hàng hóa và dịch vụ liên quan theo yêu cầu của gói thầu. Chủ đầu tư phải soạn thảo chi tiết phần Thông số kỹ thuật trên cơ sở đánh giá đến những yếu tố sau: - Thông số kỹ thuật bao gồm các tiêu chuẩn làm căn cứ cho Chủ đầu tư, tổ chuyên gia xác minh tính đáp ứng về mặt kỹ thuật và đánh giá HSĐX. Do đó, nếu thông số kỹ thuật được xác định đầy đủ, rõ ràng thì sẽ giúp nhà thầu chuẩn bị tốt HSĐX và có tính đáp ứng cao, đồng thời giúp Chủ đầu tư, tổ chuyên gia nghiên cứu, đánh giá HSĐX. - Thông số kỹ thuật yêu cầu tất cả các hàng hóa và vật liệu, vật tư sử dụng cho hàng hóa phải mới, chưa qua sử dụng, sử dụng toàn bộ các cải tiến mới nhất về thiết kế và vật liệu, trừ trường hợp có quy định cụ thể khác trong hợp đồng. - Thông số kỹ thuật phải đủ khái quát để tránh gây hạn chế liên quan đến các yêu cầu tay nghề và vật tư thiết bị thường được sử dụng để sản xuất các hàng hóa thuộc loại tương tự. - Thông số kỹ thuật phải mô tả đầy đủ các yêu cầu liên quan và không giới hạn ở những điểm sau đây: + Các tiêu chuẩn về vật liệu, vật tư và tay nghề cần thiết để sản xuất chế tạo hàng hóa; + Các yêu cầu chi tiết về thử nghiệm (loại hình và số lần thử); + Các công việc bổ sung khác và/hoặc các dịch vụ liên quan cần thiết để giao hàng/hoàn thành đầy đủ; + Các hoạt động cụ thể mà nhà thầu sẽ phải thực hiện và sự tham gia của Chủ đầu tư; + Danh sách các yêu cầu bảo đảm chức năng vận hành cụ thể thuộc phạm vi bảo hành và quy định bồi thường thiệt hại nếu các yêu cầu bảo đảm nói trên không được thực hiện. - Thông số kỹ thuật phải nêu rõ tất cả các đặc tính và yêu cầu về công năng và kỹ thuật, bao gồm các giá trị tối đa và tối thiểu được bảo đảm hoặc được chấp nhận, tùy theo trường hợp. Chủ đầu tư được nêu cụ thể ký mã hiệu (nếu có), nhãn hiệu, hãng sản xuất, xuất xứ của hàng hóa. - Tiến độ giao hàng, ngày hoàn thành dịch vụ theo yêu cầu tại Mẫu 05 Chương III. Nếu Chủ đầu tư yêu cầu nhà thầu cung cấp trong HSĐX của mình một phần hoặc toàn bộ các thông số kỹ thuật, các bảng biểu kỹ thuật hoặc các thông tin kỹ thuật khác thì Chủ đầu tư phải quy định rõ tính chất và mức độ thông tin yêu cầu và cách trình bày các thông tin đó trong HSĐX. [Nếu yêu cầu cung cấp bản tóm tắt thông số kỹ thuật thì Chủ đầu tư phải ghi thông tin vào bảng dưới đây. Nhà thầu sẽ soạn một bảng tương tự để chứng minh hàng hóa do nhà thầu chào tuân thủ với các yêu cầu đó]. Tóm tắt thông số kỹ thuật của hàng hóa, dịch vụ liên quan. Hàng hóa, dịch vụ liên quan phải tuân thủ các thông số kỹ thuật và tiêu chuẩn sau đây: [BẢNG: Không tiêu đề] Thông số kỹ thuật chi tiết và các tiêu chuẩn chi tiết (khi cần thiết). [Mô tả chi tiết thông số kỹ thuật] _________________________ 1. 3. Các yêu cầu khác - Các yêu cầu khác về kỹ thuật bao gồm yêu cầu về phương thức thanh toán, yêu cầu về cung cấp tài chính (nếu có), yêu cầu về dịch vụ liên quan như lắp đặt, duy tu, bảo dưỡng, sửa chữa ban đầu, bảo hiểm lắp đặt, bảo hiểm sửa chữa hoặc cung cấp các dịch vụ sau bán hàng khác như đào tạo, chuyển giao kỹ thuật. .. (nếu có). Các yêu cầu này phải được nêu chi tiết để nhà thầu chuẩn bị HSĐX. - Đấu thầu bền vững: có thể đưa ra yêu cầu về hàng hóa thân thiện môi trường, xã hội, sản phẩm, dịch vụ được chứng nhận nhãn sinh thái, nhãn năng lượng và tương đương (nếu có) như: tiết kiệm năng lượng hoặc tiết kiệm nước khi sử dụng, khí thải ít độc hại, không có chất độc hại, phá hủy môi trường; hàng hóa sản xuất không vi phạm trách nhiệm xã hội hoặc từ nguồn nguyên liệu bền vững, hữu cơ, vật liệu tái chế; sử dụng vật liệu xanh để đóng gói hàng hóa; tiết kiệm nhiên liệu, giảm thiểu ô nhiễm tiếng ồn, sử dụng container có thể tái sử dụng để vận chuyển hàng hóa; mức độ xả thải, rác thải, ô nhiễm môi trường, giảm thiểu tác động môi trường và cộng đồng xung quanh; cam kết thu hồi hoặc tái chế khi hàng hóa hết sử dụng. .. - Tùy theo từng gói thầu có thể yêu cầu nhà thầu chào phương án thay thế ngoài phương án chính theo yêu cầu của HSYC, trong đó cần quy định rõ phương án thay thế của nhà thầu chỉ được đánh giá trong quá trình thương thảo hợp đồng (nếu có) khi nhà thầu được đề xuất trúng thầu theo phương án chính hoặc quy định trong trường hợp kết quả đánh giá HSĐX theo phương án chính không có nhà thầu nào đáp ứng yêu cầu của HSYC thì mới đánh giá phương án thay thế của nhà thầu. Mục 2. Bản vẽ HSYC này gồm có các bản vẽ trong danh mục sau đây [trường hợp không có bản vẽ kèm theo thì phải ghi rõ “Không có bản vẽ”]: [BẢNG: Không tiêu đề] Trường hợp có bản vẽ thì phải đính kèm theo bản vẽ. Mục 3. Kiểm tra và thử nghiệm Các kiểm tra và thử nghiệm cần tiến hành gồm có: ____ [ghi danh sách các kiểm tra và thử nghiệm]. Phần 3. ĐIỀU KIỆN HỢP ĐỒNG VÀ BIỂU MẪU HỢP ĐỒNG Căn cứ quy mô, tính chất, loại hợp đồng của gói thầu, Chủ đầu tư, tổ chuyên gia sử dụng các Chương VI, VII, VIII của Mẫu E-HSMT mua sắm hàng hóa một giai đoạn một túi hồ sơ ban hành kèm theo Thông tư số 79/2025/TT-BTC để xây dựng các Chương V. ĐIỀU KIỆN CHUNG, Chương VI. ĐIỀU KIỆN CỤ THỂ, Chương VII. BIỂU MẪU HỢP ĐỒNG cho phù hợp với quy định của Luật Đấu thầu, Nghị định số 214/2025/NĐ-CP. Trong quá trình thực hiện, trường hợp Thông tư số 79/2025/TT-BTC được sửa đổi, bổ sung hoặc thay thế thì áp dụng theo văn bản quy phạm pháp luật sửa đổi, bổ sung hoặc thay thế Thông tư số 79/2025/TT-BTC. Lưu ý: khi sử dụng cần thay đổi các thuật ngữ cho phù hợp như sau: - E-ĐKC thành ĐKC; - E-ĐKCT thành ĐKCT; - E-HSMT thành HSYC; - E-HSDT thành HSĐX.", "type": "bill_of_quantities", "rows": []}], "parsing_metadata": {"bidding_type": null, "detected_sections": {"general_info": [], "technical_requirements": [], "evaluation_criteria": [], "contract_conditions": [], "bidding_process": [], "forms": [], "drawings": [], "bill_of_quantities": []}, "document_info": {"project_name": "/dự toán mua sắm]. 2. nguồn vốn để thực hiện gói thầu: [ghi rõ nguồn vốn đã được xác định hoặc phê d", "package_name": "mua sắm hàng hóa (ban hành kèm theo thông tư số 80/2025/tt-btc ngày 08 tháng 8 năm 2025 của bộ trưởn", "owner": "___[ghi tên, địa chỉ chủ đầu tư] mời nhà thầu nhận hsyc gói thầu___ [ghi tên gói thầu theo kế hoạch"}, "statistics": {}}, "extraction_metadata": {"source_file": "01B. Mẫu HSYC hàng hóa.docx", "file_type": "bidding_document", "document_category": "goods", "extracted_at": "2025-10-30T19:54:40.566838", "file_size_bytes": 218998, "project_name": "/dự toán mua sắm].", "package_name": "MUA SẮM HÀNG HÓA", "bidding_method": "CHỈ ĐỊNH THẦU", "owner": "___[Ghi tên, địa chỉ Chủ đầu tư] mời nhà thầu nhận HSYC gói thầu___ [Ghi tên gói thầu theo kế hoạch lựa chọn nhà thầu được duyệt] thuộc__ [Ghi tên dự án/dự toán mua sắm]."}}
