{"content": "Mẫu 1D MẪU HỒ SƠ YÊU CẦU GÓI THẦU DỊCH VỤ TƯ VẤN (Ban hành kèm theo Thông tư số 80/2025/TT-BTC ngày 08 tháng 8 năm 2025 của Bộ trưởng Bộ Tài chính) HỒ SƠ YÊU CẦU DỊCH VỤ TƯ VẤN [BẢNG: Không tiêu đề] [BẢNG: Không tiêu đề] TỪ NGỮ VIẾT TẮT [BẢNG: Không tiêu đề] Phần 1. THỦ TỤC CHỈ ĐỊNH THẦU Chương I. CHỈ DẪN NHÀ THẦU Mục 1. Nội dung gói thầu 1. Chủ đầu tư ___ [Ghi tên, địa chỉ chủ đầu tư] mời nhà thầu nhận HSYC gói thầu ___ [Ghi tên gói thầu theo kế hoạch lựa chọn nhà thầu được duyệt] thuộc___ [Ghi tên dự án/dự toán mua sắm]. 2. Nguồn vốn để thực hiện gói thầu: ______[Ghi rõ nguồn vốn đã được xác định hoặc phê duyệt; trường hợp sử dụng vốn ODA, vốn vay ưu đãi nước ngoài thì phải ghi rõ tên nhà tài trợ và cơ cấu nguồn vốn, bao gồm vốn tài trợ, vốn đối ứng trong nước]. 3. Thời gian thực hiện gói thầu là: ___ [Ghi thời gian cụ thể theo kế hoạch lựa chọn nhà thầu được duyệt], được tính từ ngày hợp đồng có hiệu lực đến ngày nghiệm thu hoàn thành DVTV, không bao gồm thời gian giám sát tác giả (nếu có). Mục 2. Hành vi bị cấm trong đấu thầu Hành vi bị cấm trong đấu thầu là hành vi quy định tại Điều 16 của Luật đấu thầu. Mục 3. Tư cách hợp lệ của nhà thầu 1. Nhà thầu là tổ chức có tư cách hợp lệ khi đáp ứng quy định tại các điểm a, b, c, d, e và g Khoản 1 Điều 5 của Luật Đấu thầu; 2. Nhà thầu là hộ kinh doanh có tư cách hợp lệ khi đáp ứng quy định tại các điểm a, b Khoản 2 và các điểm d, e Khoản 1 Điều 5 của Luật Đấu thầu; Trường hợp pháp luật có liên quan quy định nhà thầu dự thầu, thực hiện hợp đồng phải độc lập với các tổ chức, cá nhân khác thì phải tuân thủ quy định đó. Mục 4. Làm rõ, sửa đổi HSYC 1. Trường hợp nhà thầu cần làm rõ HSYC, nhà thầu gửi văn bản đến Chủ đầu tư trong thời hạn tối thiểu 03 ngày làm việc trước ngày có thời điểm đóng thầu để đánh giá, xử lý. 2. Trường hợp sửa đổi HSYC, Chủ đầu tư có trách nhiệm gửi quyết định sửa đổi và các nội dung sửa đổi tới nhà thầu. Thời gian gửi văn bản sửa đổi HSYC đến nhà thầu là ___ [Ghi số ngày cụ thể, tối thiểu 03 ngày làm việc trước ngày có thời điểm đóng thầu và bảo đảm đủ thời gian để nhà thầu hoàn chỉnh HSĐX]; trường hợp không bảo đảm đủ thời gian như nêu trên thì phải gia hạn thời điểm đóng thầu. Mục 5. Chi phí, đồng tiền, ngôn ngữ khi dự thầu 1. Nhà thầu phải chịu mọi chi phí liên quan đến quá trình dự thầu. 2. Đồng tiền dự thầu và đồng tiền thanh toán là VND. 3. HSĐX cũng như tất cả văn bản và hồ sơ liên quan đến HSĐX được viết bằng tiếng Việt. Các hồ sơ bổ trợ trong HSĐX có thể được viết bằng ngôn ngữ khác, đồng thời kèm theo bản dịch sang tiếng Việt. Trường hợp thiếu bản dịch, chủ đầu tư có thể yêu cầu nhà thầu gửi bổ sung (nếu cần thiết). Mục 6. Thành phần của HSĐX HSĐX do nhà thầu chuẩn bị phải bao gồm: 1. Đơn dự thầu theo quy định tại Mẫu 01 Chương III; 2. Thỏa thuận liên danh nếu là nhà thầu liên danh theo Mẫu 03 Chương III; 3. Đề xuất kỹ thuật theo quy định tại Mục 8 Chương này; 4. Đề xuất về giá theo Mẫu 12A, 12B, 13, 14 và 15 Chương III; 5. Các nội dung khác __ [Nêu các nội dung khác tùy theo tính chất, yêu cầu của gói thầu]. Mục 7. giá thầu 1. giá thầu do nhà thầu ghi trong đơn dự thầu bao gồm toàn bộ các chi phí (chưa tính giảm giá) để thực hiện gói thầu theo yêu cầu của HSYC, kể cả các loại thuế, phí, lệ phí (nếu có) áp theo thuế suất, mức phí, lệ phí tại thời điểm 28 ngày trước ngày có thời điểm đóng thầu. Nhà thầu ______ phân tích chi phí thù lao cho chuyên gia theo Mẫu 12B Chương III. [Trường hợp không yêu cầu nhà thầu phân tích chi phí thù lao cho chuyên gia thì ghi rõ “không”. Trường hợp yêu cầu nhà thầu phân tích chi phí thù lao cho chuyên gia thì ghi rõ “phải”]. 2. giá thầu phải bao gồm tất cả chi phí cho các yếu tố rủi ro và chi phí trượt giá có thể xảy ra trong quá trình thực hiện hợp đồng. Trường hợp gói thầu tư vấn đơn giản, thời gian thực hiện hợp đồng ngắn, không phát sinh rủi ro, trượt giá thì chi phí cho các yếu tố rủi ro và chi phí trượt giá được tính bằng 0 (đồng). Đối với gói thầu áp dụng loại hợp đồng theo thời gian, giá thầu không bao gồm chi phí cho các yếu tố rủi ro và chi phí trượt giá có thể xảy ra trong quá trình thực hiện hợp đồng. Mục 8. Thành phần đề xuất kỹ thuật Căn cứ phạm vi DVTV hoặc các nội dung yêu cầu khác, Nhà thầu phải nộp đề xuất kỹ thuật, trong đó mô tả cụ thể phương pháp thực hiện công việc, nhân sự, tiến độ thực hiện và các thông tin cần thiết khác theo quy định tại Chương III để chứng minh tính phù hợp của đề xuất đối với các yêu cầu công việc và thời hạn cần hoàn thành công việc. Mục 9. Hiệu lực của HSĐX 1. Thời gian có hiệu lực của HSĐX phải bảo đảm theo yêu cầu là ___ [Ghi rõ số ngày tuỳ thuộc quy mô, tính chất của gói thầu, bảo đảm thời gian có hiệu lực đến ngày ký kết hợp đồng] kể từ ngày có thời điểm đóng thầu. 2. Trong trường hợp cần thiết, trước khi hết thời hạn hiệu lực của HSĐX, Chủ đầu tư có thể đề nghị nhà thầu gia hạn hiệu lực của HSĐX. Việc đề nghị gia hạn và chấp thuận gia hạn phải được thể hiện bằng văn bản. Mục 10. Quy cách của HSĐX và chữ ký trong HSĐX 1. Nhà thầu phải chuẩn bị một bản gốc và _______bản chụp HSĐX [Ghi số lượng yêu cầu nhưng không quá 03 bản], ghi rõ \"bản gốc\" và \"bản chụp\" tương ứng. Nhà thầu cần ghi rõ tên gói thầu, tên nhà thầu, tên Chủ đầu tư bên ngoài túi đựng HSĐX. Nhà thầu phải chịu trách nhiệm về tính chính xác và phù hợp giữa bản chụp và bản gốc. Trường hợp có sự sai khác giữa bản gốc và bản chụp thì căn cứ vào bản gốc để đánh giá. 2. Tất cả các thành phần nêu tại Mục 6 Chương I phải được ký bởi người đại diện hợp pháp của nhà thầu. Trường hợp là nhà thầu liên danh thì HSĐX phải có chữ ký của đại diện hợp pháp của tất cả thành viên liên danh hoặc thành viên đại diện nhà thầu liên danh theo phân công trong thỏa thuận liên danh. 3. Những chữ được ghi thêm, ghi chèn vào giữa các dòng, những chữ bị tẩy xóa hoặc viết đè lên sẽ chỉ được coi là hợp lệ nếu có chữ ký ở bên cạnh hoặc tại trang đó của người ký đơn dự thầu. Mục 11. Thời điểm đóng thầu và mở thầu 1. HSĐX do nhà thầu nộp trực tiếp hoặc gửi đến địa chỉ của chủ đầu tư nhưng phải đảm bảo chủ đầu tư nhận được trước thời điểm đóng thầu: ___ giờ, ngày ___ tháng ___ năm ____ [Ghi thời điểm đóng thầu]. 2. Mở thầu: Chủ đầu tư tiến hành mở thầu bao gồm các nội dung sau: a) Kiểm tra niêm phong; b) Mở hồ sơ và đọc rõ các thông tin về tên nhà thầu: - Tham dự độc lập hay liên danh; - Số lượng bản gốc, bản chụp; - giá thầu chào trong đơn dự thầu; - Giá trị giảm giá (nếu có); - Thời gian có hiệu lực của HSĐX; - Thời gian thực hiện gói thầu; - Các thông tin khác liên quan. Biên bản mở thầu bao gồm các thông tin quy định tại điểm a và điểm b khoản này. Biên bản mở thầu phải được ký xác nhận bởi đại diện của Chủ đầu tư và nhà thầu nộp HSĐX. Biên bản này phải được gửi cho nhà thầu nộp HSĐX. Đại diện của Chủ đầu tư phải ký xác nhận vào bản gốc đơn dự thầu, thư giảm giá (nếu có), giấy ủy quyền của người đại diện theo pháp luật của nhà thầu (nếu có), thỏa thuận liên danh (nếu có), các nội dung đề xuất về tài chính và các nội dung quan trọng khác của HSĐX. Mục 12. thầu phụ 1. thầu phụ là tổ chức, cá nhân ký kết hợp đồng với nhà thầu để tham gia thực hiện một hoặc một số hạng mục công việc của gói thầu. Nhà thầu phải kê khai thầu phụ và các hạng mục công việc dành cho thầu phụ theo Mẫu 11 Chương III. Trường hợp tại thời điểm dự thầu, chưa xác định được thầu phụ thì phải kê khai các hạng mục công việc dự kiến dành cho thầu phụ. Việc sử dụng thầu phụ sẽ không làm thay đổi các trách nhiệm của nhà thầu. Nhà thầu phải chịu trách nhiệm về khối lượng, chất lượng, tiến độ và các trách nhiệm khác đối với phần công việc do thầu phụ thực hiện. Năng lực và kinh nghiệm của thầu phụ sẽ không được đánh giá khi đánh giá HSĐX của nhà thầu. Bản thân nhà thầu phải đáp ứng các tiêu chí năng lực và kinh nghiệm (không xét đến năng lực và kinh nghiệm của thầu phụ). Nhà thầu được ký kết hợp đồng với các thầu phụ trong danh sách các thầu phụ nêu trong HSĐX hoặc ký với thầu phụ được chủ đầu tư chấp thuận để tham gia thực hiện công việc gói thầu. 2. Nhà thầu chỉ được sử dụng thầu phụ thực hiện các công việc với tổng giá trị dành cho thầu phụ không vượt quá ___ [tùy theo quy mô, tính chất gói thầu, chủ đầu tư ghi tỷ lệ % tối đa dành cho thầu phụ] giá thầu của nhà thầu. Đối với trường hợp liên danh, từng thành viên liên danh chỉ được sử dụng thầu phụ không vượt quá tỷ lệ phần trăm quy định tại Mục này trên giá trị phần công việc mà thành viên liên danh đó đảm nhận trong thỏa thuận liên danh. Mục 13. Đánh giá HSĐX và thương thảo về các đề xuất của nhà thầu 1. Việc đánh giá HSĐX được thực hiện theo quy định tại Chương II. 2. Trong quá trình đánh giá, chủ đầu tư mời nhà thầu thương thảo về giá bảo đảm đáp ứng tỷ lệ tiết kiệm theo quy định của HSYC, thương thảo, làm rõ hoặc sửa đổi, bổ sung nội dung HSĐX để chứng minh việc đáp ứng yêu cầu về năng lực, kinh nghiệm, tiến độ, khối lượng, chất lượng, giải pháp kỹ thuật, biện pháp tổ chức thực hiện gói thầu và tỷ lệ tiết kiệm. Mục 14. Điều kiện đối với nhà thầu được đề nghị chỉ định thầu Nhà thầu được đề nghị chỉ định thầu khi đáp ứng đầy đủ các điều kiện sau đây: 1. Có HSĐX hợp lệ; 2. Có đề xuất về kỹ thuật đáp ứng yêu cầu của HSYC; 3. Có giá đề nghị trúng thầu không vượt giá gói thầu được duyệt và đáp ứng tỷ lệ tiết kiệm tối thiểu __% giá gói thầu [Căn cứ quy mô, tính chất, điều kiện cụ thể của gói thầu, chủ đầu tư quy định trong HSYC mức tỷ lệ tiết kiệm của giá đề nghị trúng thầu để làm cơ sở cho nhà thầu chuẩn bị HSĐX]. Mục 15. Thông báo kết quả lựa chọn nhà thầu Trong thời hạn 05 ngày làm việc kể từ ngày kết quả lựa chọn nhà thầu được phê duyệt, Chủ đầu tư đăng tải thông tin về kết quả lựa chọn nhà thầu lên Hệ thống mạng đấu thầu quốc gia; gửi văn bản thông báo kết quả lựa chọn nhà thầu cho nhà thầu dự thầu. Nội dung thông báo kết quả lựa chọn nhà thầu như sau: a) Thông tin về gói thầu: - Tên gói thầu; - Giá gói thầu hoặc dự toán được duyệt (nếu có); - Tên Chủ đầu tư; - Hình thức lựa chọn nhà thầu; - Loại hợp đồng; - Thời gian thực hiện gói thầu. b) Thông tin về nhà thầu trúng thầu: - Tên nhà thầu; - Mã số thuế (nếu có); - giá thầu; - Giá trúng thầu; - Thời gian thực hiện gói thầu; - Thời gian thực hiện hợp đồng. c) Kế hoạch hoàn thiện, ký kết hợp đồng với nhà thầu trúng thầu. Mục 16. Điều kiện ký kết hợp đồng 1. Tại thời điểm ký kết, HSĐX của nhà thầu trúng thầu còn hiệu lực. 2. Chủ đầu tư phải bảo đảm các điều kiện về vốn tạm ứng, vốn thanh toán, mặt bằng thực hiện (nếu có) và điều kiện cần thiết khác để triển khai thực hiện gói thầu theo đúng tiến độ. Mục 17. Giải quyết kiến nghị 1. Đối với gói thầu thuộc phạm vi điều chỉnh của Luật Đấu thầu: a) Khi thấy quyền và lợi ích hợp pháp bị ảnh hưởng, nhà thầu được kiến nghị người có thẩm quyền, Chủ đầu tư, Hội đồng giải quyết kiến nghị đánh giá lại các vấn đề trong quá trình lựa chọn nhà thầu, kết quả lựa chọn nhà thầu theo quy định tại Điều 89 của Luật Đấu thầu và các Điều 137, 138 và 139 của Nghị định số 214/2025/NĐ-CP. b) Địa chỉ nhận đơn kiến nghị: - Địa chỉ nhận đơn kiến nghị của Chủ đầu tư: ______ [ghi đầy đủ tên, địa chỉ, số điện thoại, email]. - Địa chỉ nhận đơn kiến nghị của người có thẩm quyền: ______ [ghi đầy đủ tên, địa chỉ, số điện thoại, email]. - Địa chỉ bộ phận thường trực giúp việc của Hội đồng giải quyết kiến nghị: ___ [ghi đầy đủ tên, địa chỉ, số điện thoại, email]. 2. Đối với hoạt động lựa chọn nhà thầu quy định tại điểm d Khoản 7 Điều 3 của Luật Đấu thầu hoặc hoạt động lựa chọn nhà thầu không thuộc phạm vi điều chỉnh của Luật Đấu thầu: Khi thấy quyền và lợi ích hợp pháp bị ảnh hưởng, nhà thầu, cơ quan, tổ chức được kiến nghị theo quy trình sau: ___ [ghi cụ thể quy trình, thủ tục của việc giải quyết kiến nghị của đơn vị, tổ chức đồng thời ghi rõ email, địa chỉ của cá nhân/tổ chức/đơn vị giải quyết kiến nghị]. Mục 18. Ưu đãi trong lựa chọn nhà thầu Ưu đãi: _____ [Chủ đầu tư ghi rõ đối tượng, điều kiện ưu đãi theo quy định tại Nghị quyết của Quốc hội hoặc văn bản quy phạm pháp luật (nếu có)]. Chương II. TIÊU CHUẨN ĐÁNH GIÁ HSĐX Mục 1. Kiểm tra và đánh giá tính hợp lệ của HSĐX 1. 1. Kiểm tra HSĐX a) Kiểm tra số lượng bản gốc, bản chụp HSĐX; b) Kiểm tra các thành phần của HSĐX theo quy định tại Mục 6 Chương I; c) Kiểm tra sự thống nhất nội dung giữa bản gốc và bản chụp để phục vụ quá trình đánh giá chi tiết HSĐX. 1. 2. Đánh giá tính hợp lệ của HSĐX HSĐX của nhà thầu được đánh giá là hợp lệ khi đáp ứng đầy đủ các nội dung sau đây: a) Có bản gốc HSĐX; b) Có đơn dự thầu được đại diện hợp pháp của nhà thầu ký tên, đóng dấu (nếu có) theo yêu cầu của HSYC; thời gian ký đơn dự thầu phải sau thời điểm phát hành HSYC; không kèm theo điều kiện gây bất lợi cho Chủ đầu tư. Đối với nhà thầu liên danh, đơn dự thầu phải do đại diện hợp pháp của từng thành viên liên danh ký tên, đóng dấu (nếu có) hoặc thành viên được phân công thay mặt liên danh ký đơn dự thầu theo phân công trách nhiệm trong thỏa thuận liên danh; c) Đã thực hiện nghĩa vụ kê khai thuế và nộp thuế: Trường hợp thời điểm đóng thầu sau ngày kết thúc năm tài chính của nhà thầu (năm Y) và trước hoặc trong ngày cuối cùng của tháng thứ 3 tính từ ngày kết thúc năm Y, yêu cầu đã thực hiện nghĩa vụ kê khai thuế và nộp thuế áp dụng đối với năm tài chính trước năm Y (năm Y-1) (Ví dụ: thời điểm đóng thầu là vào ngày 20/3/2024, năm tài chính của nhà thầu kết thúc vào ngày 31/12 thì nhà thầu phải chứng minh đã thực hiện nghĩa vụ kê khai thuế và nộp thuế của năm 2022); d) Hiệu lực của HSĐX đáp ứng yêu cầu theo quy định tại Mục 9 Chương I; đ) Có thỏa thuận liên danh (trong trường hợp liên danh) được đại diện hợp pháp của từng thành viên liên danh ký tên, đóng dấu (nếu có); trong thỏa thuận liên danh phải nêu rõ nội dung công việc cụ thể và ước tính giá trị tương ứng mà từng thành viên trong liên danh sẽ thực hiện. Việc phân chia công việc trong liên danh phải căn cứ các hạng mục công việc nêu trong điều khoản tham chiếu, đề xuất kỹ thuật, không được phân chia các công việc không thuộc các hạng mục này; e) Nhà thầu bảo đảm tư cách hợp lệ theo quy định tại Mục 3 Chương I; g) Trong thời hạn 03 năm trước thời điểm đóng thầu, nhà thầu không có nhân sự (ký kết hợp đồng lao động với nhà thầu tại thời điểm nhân sự thực hiện hành vi vi phạm) bị Tòa án kết án có hành vi vi phạm quy định về đấu thầu gây hậu quả nghiêm trọng theo quy định pháp luật về hình sự nhằm mục đích cho nhà thầu đó trúng thầu; h) Có đủ điều kiện năng lực hoạt động theo quy định của pháp luật quản lý ngành và lĩnh vực (nếu có). Nhà thầu có HSĐX hợp lệ được đánh giá, đánh giá trong các bước tiếp theo. Mục 2. Tiêu chuẩn đánh giá về kỹ thuật Việc đánh giá về kỹ thuật đối với từng HSĐX được thực hiện theo phương pháp chấm điểm, trong đó phải quy định mức điểm tối đa đối với các tiêu chuẩn tổng quát, tiêu chuẩn chi tiết; quy định mức điểm tối thiểu đối với tiêu chuẩn tổng quát và chi tiết (nếu cần thiết) của các nội dung giải pháp và phương pháp luận, nhân sự chủ chốt. Đối với tiêu chuẩn về kinh nghiệm và năng lực của nhà thầu, căn cứ tính chất gói thầu để xác định sự cần thiết quy định hoặc không quy định điểm tối thiểu đối với tiêu chuẩn tổng quát này. Việc đánh giá hợp đồng tương tự của nhà thầu liên danh căn cứ vào phạm vi công việc của từng thành viên trong liên danh đảm nhận. Tiêu chuẩn đánh giá về kỹ thuật gồm các nội dung tại Bảng số 01 sau đây: Bảng số 01 [BẢNG: Không tiêu đề] Ghi chú: (1) Thời điểm xác định hợp đồng hoàn thành để xác định hợp đồng tương tự là thời điểm nghiệm thu công việc hoàn thành. Đối với các hợp đồng mà Chủ đầu tư, tổ chuyên gia có bằng chứng cho thấy nhà thầu đã thực hiện với tư cách thầu phụ do được chuyển nhượng bất hợp pháp, vi phạm quy định tại Khoản 8 Điều 16 của Luật Đấu thầu thì hợp đồng này sẽ không được đánh giá, đánh giá. Hợp đồng tương tự được xác định trên cơ sở tương tự về tính chất, không căn cứ vào quy mô (giá trị hợp đồng). (2) Tùy theo tính chất của gói thầu mà quy định cho phù hợp. Ví dụ: đáp ứng về vật tư, máy móc, thiết bị (thuộc sở hữu của nhà thầu hoặc đi thuê) để phục vụ công việc thí nghiệm. .. . (3) Uy tín của nhà thầu thông qua việc dự thầu, kết quả thực hiện hợp đồng của nhà thầu thực hiện theo quy định tại Điều 19 và Điều 20 của Nghị định số 214/2025/NĐ-CP. Đối với nhà thầu là tư vấn lập hồ sơ mời thầu, uy tín của nhà thầu thông qua việc dự thầu, kết quả thực hiện hợp đồng của nhà thầu còn thể hiện qua số lượng hồ sơ mời thầu bị kết luận có nội dung vi phạm quy định tại Khoản 3 Điều 44 của Luật Đấu thầu. (4) Nhà thầu có thể đề xuất nhân sự chủ chốt thuộc biên chế của nhà thầu hoặc đi thuê. Nếu pháp luật quản lý ngành, lĩnh vực có quy định nhân sự phải có trình độ, bằng cấp chuyên môn cụ thể để được cấp giấy phép hành nghề/chứng chỉ chuyên môn thì trong HSYC ngoài yêu cầu về giấy phép hành nghề/chứng chỉ chuyên môn không được yêu cầu về trình độ, bằng cấp cụ thể của nhân sự chủ chốt. Trường hợp có quy định về số năm kinh nghiệm trong các công việc tương tự thì số năm kinh nghiệm này được tính từ thời điểm nhân sự bắt đầu thực hiện công việc tương tự đó đến thời điểm đóng thầu. Việc xây dựng tiêu chuẩn đánh giá về kỹ thuật cần đảm bảo các yêu cầu sau: - Tổng điểm cho các nội dung kinh nghiệm và năng lực, uy tín của nhà thầu thông qua việc dự thầu, kết quả thực hiện hợp đồng, giải pháp và phương pháp luận, nhân sự, yêu cầu về chuyển giao kỹ thuật (nếu có) là 100%. - Đối với tiêu chuẩn đánh giá về nhân sự chủ chốt: chỉ đưa các tiêu chuẩn đánh giá về trình độ chuyên môn, năng lực, kinh nghiệm trên cơ sở phù hợp với vị trí công việc của mỗi nhân sự chủ chốt nêu tại Khoản 4 của Bảng số 01 mà không đưa tiêu chuẩn đánh giá đối với nhân sự khác. - Mức điểm yêu cầu tối thiểu đối với tiêu chuẩn giải pháp và phương pháp luận, nhân sự, chuyển giao kỹ thuật (nếu có) không được quy định thấp hơn 60% điểm tối đa của tiêu chuẩn đó (không thấp hơn 70% đối với gói thầu tư vấn có yêu cầu kỹ thuật cao, đặc thù). HSĐX không đáp ứng mức điểm yêu cầu tối thiểu đối với một hoặc các tiêu chuẩn giải pháp và phương pháp luận, nhân sự, chuyển giao kỹ thuật (nếu có) được đánh giá là không đáp ứng yêu cầu về kỹ thuật. - Mức điểm yêu cầu tối thiểu về kỹ thuật không được quy định thấp hơn 70% tổng số điểm về kỹ thuật (80% đối với gói thầu tư vấn có yêu cầu kỹ thuật cao, đặc thù). HSĐX có điểm kỹ thuật không thấp hơn mức điểm yêu cầu tối thiểu được đánh giá là đáp ứng yêu cầu về kỹ thuật. Nhà thầu đáp ứng yêu cầu về kỹ thuật được đánh giá về tài chính. Mục 3. Tiêu chuẩn đánh giá về tài chính Bước 1. Xác định giá thầu; Bước 2. Sửa lỗi, hiệu chỉnh sai lệch theo quy định tại Điều 68 của Nghị định số 214/2025/NĐ-CP (nếu có); Bước 3. Xác định giá thầu sau sửa lỗi, hiệu chỉnh sai lệch (nếu có), trừ đi giá trị giảm giá (nếu có) và đáp ứng tỷ lệ tiết kiệm theo quy định tại Mục 14 Chương I. CHƯƠNG III. BIỂU MẪU Mẫu 01 ĐƠN DỰ THẦU ________, ngày ____ tháng ____ năm ____ Kính gửi: __________________ [Ghi tên chủ đầu tư] (sau đây gọi là Chủ đầu tư) Sau khi nghiên cứu hồ sơ yêu cầu (bao gồm văn bản sửa đổi hồ sơ yêu cầu, nếu có), chúng tôi, _____ [Ghi tên nhà thầu], có địa chỉ tại ______[Ghi địa chỉ của nhà thầu] cam kết thực hiện gói thầu _______[Ghi tên gói thầu] theo đúng yêu cầu của hồ sơ yêu cầu với tổng số tiền là _____ [Ghi giá trị bằng số, bằng chữ và đồng tiền dự thầu]. Thời gian thực hiện gói thầu là ____ [Ghi thời gian thực hiện tất cả các công việc theo yêu cầu của HSYC]. Hồ sơ đề xuất có hiệu lực là ___ngày [Ghi số ngày], kể từ ngày ___tháng ___ năm ___[Ghi ngày có thời điểm đóng thầu]. Chúng tôi cam kết: 1. Không đang trong quá trình thực hiện thủ tục giải thể hoặc bị thu hồi giấy chứng nhận đăng ký doanh nghiệp, giấy chứng nhận đăng ký hợp tác xã, liên hiệp hợp tác xã, tổ hợp tác, không thuộc trường hợp mất khả năng thanh toán theo quy định của pháp luật về phá sản (không đang trong quá trình chấm dứt hoạt động hoặc bị thu hồi giấy chứng nhận đăng ký hộ kinh doanh đối với nhà thầu là hộ kinh doanh). 2. Đã thực hiện nghĩa vụ kê khai thuế và nộp thuế của năm tài chính gần nhất so với thời điểm đóng thầu; 3. Không đang trong thời gian bị cấm dự thầu theo quy định của pháp luật đấu thầu; 4. Không đang bị truy cứu trách nhiệm hình sự (chủ hộ không đang bị truy cứu trách nhiệm hình sự trong trường hợp nhà thầu là hộ kinh doanh); 5. Không thực hiện các hành vi tham nhũng, hối lộ, thông thầu, cản trở và các hành vi vi phạm quy định khác của pháp luật đấu thầu khi tham dự gói thầu này. 6. Trong thời hạn 03 năm trước thời điểm đóng thầu, nhà thầu không có nhân sự (ký kết hợp đồng lao động với nhà thầu tại thời điểm nhân sự thực hiện hành vi vi phạm) bị tòa án kết án có hành vi vi phạm quy định về đấu thầu gây hậu quả nghiêm trọng theo quy định của pháp luật về hình sự nhằm mục đích cho nhà thầu trúng thầu. 7. Những thông tin kê khai trong HSĐX là trung thực. 8. Trường hợp trúng thầu, HSĐX và các văn bản bổ sung, làm rõ HSĐX tạo thành thỏa thuận ràng buộc trách nhiệm giữa hai bên cho tới khi hợp đồng được ký kết. [BẢNG: Không tiêu đề] Ghi chú: (1) Trường hợp đại diện theo pháp luật của nhà thầu ủy quyền cho cấp dưới ký đơn dự thầu thì phải gửi kèm theo Giấy ủy quyền theo Mẫu 02 Chương này. Trường hợp tại điều lệ công ty hoặc tại các hồ sơ khác liên quan có phân công trách nhiệm cho cấp dưới ký đơn dự thầu thì phải gửi kèm theo bản chụp các văn bản, hồ sơ này (không cần lập Giấy ủy quyền theo Mẫu 02 Chương này). (2) HSYC không được yêu cầu nhà thầu phải nộp lý lịch tư pháp của nhân sự để chứng minh cho nội dung đánh giá này. Nội dung này chỉ yêu cầu nhà thầu cam kết trong Đơn này. Mẫu 02 GIẤY ỦY QUYỀN(1) Hôm nay, ngày ____ tháng ____ năm ____, tại ____ Tôi là__[Ghi tên, số CCCD hoặc số hộ chiếu, chức danh của người đại diện theo pháp luật của nhà thầu], là người đại diện theo pháp luật của [Ghi tên nhà thầu] có địa chỉ tại [Ghi địa chỉ của nhà thầu] bằng văn bản này ủy quyền cho [Ghi tên, số CCCD hoặc số hộ chiếu, chức danh của người được ủy quyền] thực hiện các công việc sau đây trong quá trình dự thầu gói thầu__ [Ghi tên gói thầu] thuộc [Ghi tên dự án/dự toán mua sắm] do [Ghi tên chủ đầu tư] tổ chức: [- Ký đơn dự thầu; - Ký thỏa thuận liên danh (nếu có); - Ký các văn bản, hồ sơ để giao dịch với Chủ đầu tư trong quá trình dự thầu, kể cả văn bản giải trình, làm rõ HSĐX; - Tham gia quá trình thương thảo (nếu có), hoàn thiện hợp đồng; - Ký kết hợp đồng với chủ đầu tư nếu được chỉ định thầu.](2) Người được ủy quyền nêu trên chỉ thực hiện các công việc trong phạm vi ủy quyền với tư cách là đại diện hợp pháp của [Ghi tên nhà thầu]. [Ghi tên nhà thầu] chịu trách nhiệm hoàn toàn về những công việc do ____ [Ghi tên người được ủy quyền] thực hiện trong phạm vi ủy quyền. Giấy ủy quyền có hiệu lực kể từ ngày ____ đến ngày ____(3). Giấy ủy quyền này được lập thành bản có giá trị pháp lý như nhau, người ủy quyền giữ ____ bản, người được ủy quyền giữ ____ bản. [BẢNG: Không tiêu đề] Ghi chú: (1) Trường hợp ủy quyền thì bản gốc giấy ủy quyền phải được gửi cho chủ đầu tư cùng với đơn dự thầu. Việc ủy quyền của người đại diện theo pháp luật của nhà thầu cho cấp phó, cấp dưới, giám đốc chi nhánh, người đứng đầu văn phòng đại diện của nhà thầu để thay mặt cho người đại diện theo pháp luật của nhà thầu thực hiện một hoặc các nội dung công việc nêu trên đây. Việc sử dụng con dấu trong trường hợp được ủy quyền có thể là dấu của nhà thầu hoặc dấu của đơn vị mà cá nhân liên quan được ủy quyền. Người được ủy quyền không được tiếp tục ủy quyền cho người khác. (2) Phạm vi ủy quyền bao gồm một hoặc nhiều công việc nêu trên. (3) Ghi ngày có hiệu lực và ngày hết hiệu lực của giấy ủy quyền phù hợp với quá trình dự thầu và phải bảo đảm có hiệu lực trước ngày thực hiện các công việc được ủy quyền. Mẫu 03 THỎA THUẬN LIÊN DANH (1), ngày tháng năm Gói thầu: ___ [Ghi tên gói thầu] Thuộc: ___ [Ghi tên dự án/dự toán mua sắm] - Căn cứ ___ [Luật Đấu thầu](2); - Căn cứ ___ (2); - Căn cứ hồ sơ yêu cầu gói thầu _______ [Ghi tên gói thầu] ngày___tháng____ năm ____[Ngày được ghi trên HSYC]; Chúng tôi, đại diện cho các bên ký thỏa thuận liên danh, gồm có: Tên thành viên liên danh [Ghi tên từng thành viên liên danh] Đại diện là ông/bà: Chức vụ: Địa chỉ: Điện thoại: E-mail: Tài khoản: Mã số thuế: Giấy ủy quyền số __ ngày __tháng __ năm __ (trường hợp được ủy quyền). Các bên (sau đây gọi là thành viên) thống nhất ký kết thỏa thuận liên danh với các nội dung sau: Điều 1. Nguyên tắc chung 1. Các thành viên tự nguyện hình thành liên danh để dự thầu gói thầu [Ghi tên gói thầu] thuộc ___ [Ghi tên dự án/dự toán mua sắm]. 2. Các thành viên thống nhất tên gọi của liên danh cho mọi giao dịch liên quan đến gói thầu này là: [Ghi tên của liên danh]. 3. Các thành viên cam kết không thành viên nào có quyền từ chối thực hiện các trách nhiệm và nghĩa vụ quy định trong hợp đồng. Trường hợp thành viên của liên danh từ chối hoàn thành trách nhiệm riêng của mình như đã thỏa thuận thì thành viên đó bị xử lý như sau: - Bồi thường thiệt hại cho các bên trong liên danh - Bồi thường thiệt hại cho Chủ đầu tư theo quy định nêu trong hợp đồng - Hình thức xử lý khác [Ghi rõ hình thức xử lý khác]. Điều 2. Phân công trách nhiệm Các thành viên thống nhất chịu trách nhiệm chung, trách nhiệm riêng để thực hiện gói thầu [Ghi tên gói thầu] thuộc ___ [Ghi tên dự án/dự toán mua sắm] đối với từng thành viên như sau: 1. Thành viên đứng đầu liên danh Các bên nhất trí ủy quyền cho [Ghi tên một bên] làm thành viên đứng đầu liên danh, đại diện cho liên danh trong những phần việc sau(3): [- Ký đơn dự thầu; - Ký các văn bản, hồ sơ để giao dịch với chủ đầu tư trong quá trình dự thầu, kể cả văn bản đề nghị làm rõ HSYC và văn bản giải trình, làm rõ HSĐX; - Tham gia quá trình thương thảo, hoàn thiện hợp đồng; - Các công việc khác trừ việc ký kết hợp đồng [Ghi rõ nội dung các công việc khác (nếu có)]. 2. Các thành viên trong liên danh thỏa thuận phân công trách nhiệm thực hiện công việc theo bảng dưới đây(4): [BẢNG: Không tiêu đề] Điều 3. Hiệu lực của thỏa thuận liên danh 1. Thỏa thuận liên danh có hiệu lực kể từ ngày ký. 2. Thỏa thuận liên danh chấm dứt hiệu lực trong các trường hợp sau: - Các bên hoàn thành trách nhiệm và nghĩa vụ của mình và tiến hành thanh lý hợp đồng; - Các bên cùng thỏa thuận chấm dứt; - Nhà thầu liên danh không được chỉ định thầu; - Hủy thầu gói thầu [Ghi tên gói thầu] thuộc ___ [Ghi tên dự án/dự toán mua sắm] theo thông báo của chủ đầu tư. Thỏa thuận liên danh được lập thành bản, mỗi bên giữ bản, các bản thỏa thuận có giá trị pháp lý như nhau. ĐẠI DIỆN HỢP PHÁP CỦA THÀNH VIÊN ĐỨNG ĐẦU LIÊN DANH(5) [Ghi tên, chức danh, ký tên và đóng dấu] ĐẠI DIỆN HỢP PHÁP CỦA THÀNH VIÊN LIÊN DANH [Ghi tên từng thành viên, chức danh, ký tên và đóng dấu] Ghi chú: (1) Căn cứ quy mô, tính chất của gói thầu, nội dung thỏa thuận liên danh theo mẫu này có thể được sửa đổi bổ sung cho phù hợp. (2) Cập nhật các văn bản quy phạm pháp luật theo quy định hiện hành. (3) Phạm vi ủy quyền bao gồm một hoặc nhiều công việc nêu trên. (4) Nhà thầu phải ghi rõ nội dung công việc cụ thể và ước tính giá trị tương ứng mà từng thành viên trong liên danh sẽ thực hiện, trách nhiệm chung, trách nhiệm riêng của từng thành viên, kể cả thành viên đứng đầu liên danh. Việc phân chia công việc trong liên danh phải căn cứ các hạng mục công việc nêu trong điều khoản tham chiếu, đề xuất kỹ thuật, không được phân chia các công việc không thuộc các hạng mục này. (5) Đại diện hợp pháp của thành viên liên danh có thể là người đại diện theo pháp luật hoặc người được người đại diện theo pháp luật ủy quyền. Mẫu 04 HẠNG MỤC CÔNG VIỆC CỦA GÓI THẦU 1. Phần công việc dựa trên đơn giá và khối lượng, áp dụng loại hợp đồng trọn gói hoặc loại hợp đồng theo đơn giá(1) [BẢNG: Không tiêu đề] 2. Phần công việc dựa trên lương chuyên gia và chi phí khác ngoài lương, áp dụng loại hợp đồng trọn gói hoặc hợp đồng theo thời gian(2) [BẢNG: Không tiêu đề] Ghi chú: (1) Áp dụng khi gói thầu bao gồm phần công việc dựa theo đơn giá và khối lượng, áp dụng loại hợp đồng trọn gói hoặc loại hợp đồng theo đơn giá; (2) Áp dụng cho phần công việc dựa trên lương chuyên gia và chi phí khác ngoài lương, áp dụng loại hợp đồng trọn gói hoặc hợp đồng theo thời gian; Trường hợp gói thầu có nhiều hạng mục công việc khác nhau thì có thể áp dụng đồng thời các bảng trên tương ứng cho từng hạng mục công việc. Mẫu 05 CƠ CẤU TỔ CHỨC VÀ KINH NGHIỆM CỦA NHÀ THẦU TƯ VẤN A. Cơ cấu tổ chức của nhà thầu [Mô tả tóm tắt quá trình hình thành và tổ chức của nhà thầu (trường hợp liên danh thì mô tả tổ chức của mỗi thành viên trong liên danh). Mô tả số lượng chuyên gia tư vấn chuyên ngành mà nhà thầu ký hợp đồng lao động dài hạn hoặc không xác định thời hạn và nêu rõ số năm kinh nghiệm của từng chuyên gia]. B. Kinh nghiệm của nhà thầu Các gói thầu DVTV tương tự do nhà thầu thực hiện trong vòng [Ghi số năm] năm gần đây. Nhà thầu phải sử dụng bảng sau để kê khai cho mỗi DVTV tương tự như DVTV được yêu cầu trong gói thầu này mà nhà thầu đã thực hiện (với tư cách là nhà thầu độc lập hoặc liên danh với nhà thầu khác hoặc là thầu phụ). Đối với từng công việc tương tự, nhà thầu tư vấn phải cung cấp bản tóm tắt bao gồm tên của nhân sự chủ chốt và thầu phụ của nhà thầu đã tham gia, thời gian thực hiện công việc, giá hợp đồng (trường hợp nhà thầu dự thầu là thành viên liên danh hoặc là thầu phụ thì ghi rõ khối lượng công việc, giá trị đảm nhận với vai trò thành viên liên danh, thầu phụ). Kinh nghiệm thực hiện hợp đồng của các chuyên gia với vai trò tư vấn cá nhân hoặc làm chuyên gia cho các nhà thầu tư vấn khác chỉ được tính vào kinh nghiệm làm việc của bản thân chuyên gia, không tính vào kinh nghiệm thực hiện hợp đồng của nhà thầu nộp HSĐX. [BẢNG: Không tiêu đề] Nhà thầu phải gửi kèm theo bản chụp các văn bản, hồ sơ liên quan. Mẫu 06 NHỮNG GÓP Ý (NẾU CÓ) ĐỂ HOÀN THIỆN NỘI DUNG ĐIỀU KHOẢN THAM CHIẾU [Nhà thầu trình bày những nội dung sửa đổi để hoàn thiện điều khoản tham chiếu nhằm thực hiện hợp đồng] Đề xuất bổ sung, sửa đổi điều khoản tham chiếu: 1. 2. 3. 4. 5. Mẫu 07 GIẢI PHÁP VÀ PHƯƠNG PHÁP LUẬN TỔNG QUÁT DO NHÀ THẦU ĐỀ XUẤT ĐỂ THỰC HIỆN DỊCH VỤ TƯ VẤN Nhà thầu chuẩn bị đề xuất kỹ thuật (cả biểu đồ) gồm 3 phần: 1. Giải pháp và phương pháp luận 2. Kế hoạch công tác 3. Tổ chức và nhân sự Giải pháp và phương pháp luận [Mô tả hiểu biết về mục tiêu của công việc ghi trong Điều khoản tham chiếu, cách tiếp cận kỹ thuật và phương pháp luận sẽ áp dụng để thực hiện công việc nhằm đạt được kết quả dự kiến và mức độ chi tiết của kết quả đó. Đối với gói thầu tư vấn giám sát, giải pháp và phương pháp luận cần bao gồm cả khía cạnh môi trường, xã hội. Nhà thầu lưu ý không sao chép, nhắc lại Điều khoản tham chiếu trong phần này] Kế hoạch thực hiện [Đưa ra kế hoạch thực hiện các hoạt động/công việc chính, nội dung và thời gian hoạt động, phân kỳ hoạt động và tương quan giữa các kỳ, các mốc chính (bao gồm các bước phê duyệt tạm thời của chủ đầu tư) và ngày dự kiến giao nộp báo cáo. Kế hoạch thực hiện phải thống nhất với cách tiếp cận kỹ thuật và phương pháp luận, thể hiện sự hiểu biết về Điều khoản tham chiếu và khả năng chuyển Điều khoản tham chiếu thành kế hoạch thực hiện khả thi. Cần đính kèm danh sách các hồ sơ hoàn chỉnh (bao gồm báo cáo) sẽ phải giao nộp. Kế hoạch thực hiện phải thống nhất với Kế hoạch tiến độ] Tổ chức và Nhân sự [Mô tả cơ cấu và thành phần nhóm chuyên gia, bao gồm danh sách các nhân sự chủ chốt, nhân sự khác, nhân viên hỗ trợ kỹ thuật và hành chính liên quan] Mẫu 08 LÝ LỊCH CHUYÊN GIA TƯ VẤN Tên nhà thầu: [BẢNG: Không tiêu đề] Trình độ học vấn: [liệt kê trường cao đẳng/đại học hoặc khóa học chuyên ngành, nêu tên của cơ sở đào tạo, thời gian học, loại bằng cấp đã đạt được]_______ Quá trình công tác phù hợp với công việc: [liệt kê theo trình tự thời gian quá trình công tác của chuyên gia theo Bảng sau, không cần liệt kê các công việc đã làm không phù hợp với công việc đang yêu cầu] [BẢNG: Không tiêu đề] Thành viên của Hiệp hội chuyên ngành, tổ chức nghề nghiệp và tác phẩm đã xuất bản: ________________________________________________ Ngôn ngữ (Chỉ nêu những ngôn ngữ có thể dùng để làm việc): _______ Tôi xin cam đoan các thông tin nêu trên là đúng sự thật, nếu sai tôi xin chịu trách nhiệm trước pháp luật. [BẢNG: Không tiêu đề] Ghi chú: - Từng cá nhân chuyên gia tư vấn trong danh sách nêu tại Mẫu 10 phải kê khai Mẫu này. - Nhà thầu gửi kèm hợp đồng lao động; bản chụp bằng tốt nghiệp, chứng chỉ hành nghề chuyên môn của các chuyên gia tư vấn nêu trên đính kèm cùng HSĐX. Mẫu 09 TIẾN ĐỘ THỰC HIỆN CÔNG VIỆC [BẢNG: Không tiêu đề] Ghi chú: (1) Liệt kê tất cả hạng mục công việc, trong mỗi hạng mục công việc phải nêu tiến độ thực hiện các công việc cụ thể. (2) Thời gian cho mỗi công việc cụ thể thể hiện bằng biểu đồ, trường hợp cần thiết nhà thầu có ghi chú, giải thích biểu đồ. Mẫu 10 DANH SÁCH CHUYÊN GIA THAM GIA THỰC HIỆN DỊCH VỤ TƯ VẤN [BẢNG: Không tiêu đề] Ghi chú: 1. Trường hợp HSYC có quy định, nhà thầu chọn người/tháng hoặc người/ngày phù hợp với quy định tại Mục này, nhà thầu phải đề xuất tổng số công cho nhân sự chủ chốt không ngắn hơn quy định trong HSYC. 2. Vị trí, số lượng nhân sự chủ chốt phù hợp với yêu cầu nêu tại Bảng số 01 Mục 2 Chương II. Mẫu 11 PHẠM VI CÔNG VIỆC SỬ DỤNG thầu phụ (1) [BẢNG: Không tiêu đề] Ghi chú: (1) Trường hợp HSYC có quy định về việc sử dụng thầu phụ thì nhà thầu kê khai theo Mẫu này. Đối với gói thầu của dự án thuộc lĩnh vực khoa học, kỹ thuật, đổi mới sáng tạo và chuyển đổi số tổ chức đấu thầu trong nước, nhà thầu trong nước được sử dụng thầu phụ là nhà thầu nước ngoài đối với phần công việc đặc thù mà nhà thầu trong nước chưa thực hiện được hoặc cần chuyển giao kỹ thuật theo quy định tại Khoản 4 Điều 11 Luật Đấu thầu. (2) Nhà thầu ghi cụ thể tên thầu phụ. Trường hợp khi dự thầu chưa xác định được cụ thể danh tính của thầu phụ thì không phải kê khai vào cột này mà chỉ kê khai vào cột “Phạm vi công việc”. Nếu nhà thầu trúng thầu thì khi huy động thầu phụ thực hiện công việc đã kê khai phải được sự chấp thuận của chủ đầu tư. (3) Nhà thầu ghi cụ thể tên hạng mục công việc dành cho thầu phụ. (4) Nhà thầu ghi cụ thể khối lượng công việc dành cho thầu phụ. (5) Nhà thầu ghi cụ thể giá trị % công việc mà thầu phụ đảm nhận so với giá thầu nhưng không được vượt quá tỷ lệ phần trăm (%) quy định tại Mục 12. 2 Chương I. Trường hợp nhà thầu liên danh, thành viên liên danh được sử dụng thầu phụ đối với phần công việc đảm nhận theo tỷ lệ % quy định tại Mục 12. 2 Chương I. (6) Nhà thầu ghi cụ thể số hợp đồng hoặc văn bản thỏa thuận và đính kèm bản chụp được chứng thực các hồ sơ này trong HSĐX. Trường hợp khi dự thầu chưa xác định được thầu phụ thì để trống cột này. Mẫu 12A BẢNG THÙ LAO CHO CHUYÊN GIA (*) [BẢNG: Không tiêu đề] Đại diện hợp pháp của nhà thầu [ghi tên, chức danh, ký tên và đóng dấu] Ghi chú: - (*): Mẫu này áp dụng cho các công việc thuộc Mục 2 Mẫu 04 Chương này. - (4): Nhà thầu điền theo Mẫu 12A trong trường hợp HSYC không yêu cầu phân tích thù lao cho chuyên gia. Trường hợp HSYC yêu cầu phân tích thù lao chuyên gia thì nhà thầu hoàn thành cả Mẫu 12B Chương này. Mẫu 12B BẢNG PHÂN TÍCH CHI PHÍ THÙ LAO CHO CHUYÊN GIA [BẢNG: Không tiêu đề] Đại diện hợp pháp của nhà thầu [ghi tên, chức danh, ký tên và đóng dấu] Ghi chú: Trường hợp không yêu cầu nhà thầu phân tích chi tiết chi phí thù lao chuyên gia thì không sử dụng Mẫu này. Mẫu 13 [BẢNG: Không tiêu đề] Mẫu 14 CHI PHÍ HẠNG MỤC CÔNG VIỆC DỰA TRÊN ĐƠN GIÁ VÀ KHỐI LƯỢNG [BẢNG: Không tiêu đề] Đại diện hợp pháp của nhà thầu [ghi tên, chức danh, ký tên và đóng dấu] Ghi chú: (2), (3), (4): chủ đầu tư điền (5), (6) Nhà thầu điền đơn giá, thành tiền đã bao gồm các chi phí cần thiết để thực hiện dịch vụ, kể cả thuế, phí, lệ phí. Mẫu 15 BẢNG TỔNG HỢP CHI PHÍ [BẢNG: Không tiêu đề] Đại diện hợp pháp của nhà thầu [ghi tên, chức danh, ký tên và đóng dấu] PHẦN 2. ĐIỀU KHOẢN THAM CHIẾU CHƯƠNG IV. ĐIỀU KHOẢN THAM CHIẾU Điều khoản tham chiếu bao gồm những nội dung chủ yếu sau: I. Giới thiệu Mô tả khái quát về dự án/dự toán mua sắm và gói thầu. Mô tả mục đích lựa chọn nhà thầu. II. Phạm vi công việc 1. Mô tả chi tiết phạm vi công việc đối với nhà thầu, nguồn vốn, tên cơ quan thực hiện dự án/dự toán mua sắm, thời gian, tiến độ thực hiện, số tháng - người hoặc ngày - người cần thiết (nếu có). 2. Mô tả các nhiệm vụ cụ thể do nhà thầu phải tiến hành trong thời gian thực hiện gói thầu tư vấn. Trong đó phải nêu rõ loại công việc dựa trên đơn giá và khối lượng, loại công việc tính theo lương chuyên gia. 3. Dự kiến thời gian chuyên gia bắt đầu thực hiện DVTV III. Báo cáo và thời gian thực hiện Các báo cáo phải nộp và tiến độ nộp báo cáo. IV. Kinh nghiệm và nhân sự của nhà thầu Yêu cầu về nhân sự cần thiết cho gói thầu và cho từng vị trí. V. Trách nhiệm của chủ đầu tư Dự kiến khả năng cung cấp điều kiện làm việc, cán bộ hỗ trợ của chủ đầu tư và những hồ sơ có liên quan đến nhiệm vụ của tư vấn, kể cả các hồ sơ nghiên cứu liên quan hiện có nhằm tạo điều kiện thuận lợi cho nhà thầu thực hiện nhiệm vụ của mình. Phần 3. ĐIỀU KIỆN HỢP ĐỒNG VÀ BIỂU MẪU HỢP ĐỒNG Căn cứ quy mô, tính chất, loại hợp đồng của gói thầu, chủ đầu tư, tổ chuyên gia sử dụng các Chương VI, VII, VIII của Mẫu E-HSMT dịch vụ tư vấn ban hành kèm theo Thông tư số 79/2025/TT-BTC để xây dựng các Chương V. ĐIỀU KIỆN CHUNG, Chương VI. ĐIỀU KIỆN CỤ THỂ, Chương VII. BIỂU MẪU HỢP ĐỒNG cho phù hợp với quy định của Luật Đấu thầu, Nghị định số 214/2025/NĐ-CP. Trong quá trình thực hiện, trường hợp Thông tư số 79/2025/TT-BTC được sửa đổi, bổ sung hoặc thay thế thì áp dụng theo văn bản quy phạm pháp luật sửa đổi, bổ sung hoặc thay thế Thông tư số 79/2025/TT-BTC. Lưu ý: khi sử dụng cần thay đổi các thuật ngữ cho phù hợp như sau: - E-ĐKC thành ĐKC; - E-ĐKCT thành ĐKCT; - E-HSMT thành HSYC; - E-HSDT thành HSĐX.", "metadata": {"source_file": "01D. Mẫu HSYC Tư vấn.docx", "file_type": "bidding_document", "document_category": "consulting", "extracted_at": "2025-10-30T19:54:40.990688", "file_size_bytes": 120879, "project_name": "/dự toán mua sắm]. 2. Nguồn vốn để thực hiện gói thầu: ______[Ghi rõ nguồn vốn đã được xác định hoặc phê duyệt; trường hợp sử dụng vốn ODA, vốn vay ưu", "package_name": "DỊCH VỤ TƯ VẤN (Ban hành kèm theo Thông tư số 80/2025/TT-BTC ngày 08 tháng 8 năm 2025 của Bộ trưởng Bộ Tài chính) HỒ SƠ YÊU CẦU DỊCH VỤ TƯ VẤN [BẢNG:", "bidding_method": "CHỈ ĐỊNH THẦU", "owner": "___ [Ghi tên, địa chỉ chủ đầu tư] mời nhà thầu nhận HSYC gói thầu ___ [Ghi tên gói thầu theo kế hoạch lựa chọn nhà thầu được duyệt] thuộc___ [Ghi tên", "chunk_index": 0, "char_count": 37393, "word_count": 8229, "paragraph_count": 1, "doc_type": "bidding", "processed_at": "2025-10-30T19:54:41.023830", "total_chunks": 1, "document_type": "bidding_document", "file_path": "/home/sakana/Code/RAG-bidding/data/raw/Ho so moi thau/1. Mẫu HSYC/01D. Mẫu HSYC Tư vấn.docx", "bidding_type": "construction", "extraction_metadata": {"source_file": "01D. Mẫu HSYC Tư vấn.docx", "file_type": "bidding_document", "document_category": "consulting", "extracted_at": "2025-10-30T19:54:40.990688", "file_size_bytes": 120879, "project_name": "/dự toán mua sắm].", "package_name": "DỊCH VỤ TƯ VẤN", "bidding_method": "CHỈ ĐỊNH THẦU", "owner": "___ [Ghi tên, địa chỉ chủ đầu tư] mời nhà thầu nhận HSYC gói thầu ___ [Ghi tên gói thầu theo kế hoạch lựa chọn nhà thầu được duyệt] thuộc___ [Ghi tên dự án/dự toán mua sắm]."}, "parsing_metadata": {"bidding_type": null, "detected_sections": {"general_info": [], "technical_requirements": [], "evaluation_criteria": [], "contract_conditions": [], "bidding_process": [], "forms": [], "drawings": [], "bill_of_quantities": []}, "document_info": {"project_name": "/dự toán mua sắm]. 2. nguồn vốn để thực hiện gói thầu: ______[ghi rõ nguồn vốn đã được xác định hoặc", "package_name": "dịch vụ tư vấn (ban hành kèm theo thông tư số 80/2025/tt-btc ngày 08 tháng 8 năm 2025 của bộ trưởng", "owner": "___ [ghi tên, địa chỉ chủ đầu tư] mời nhà thầu nhận hsyc gói thầu ___ [ghi tên gói thầu theo kế hoạc"}, "statistics": {}}, "contract_value": "). (2) Tùy theo tính chất của gói thầu mà quy định", "duration": "gói thầu là: ___ [Ghi thời gian cụ thể theo kế hoạ", "hierarchy": "HỒ SƠ MỜI THẦU > Phần 1 > Chương I > Mục 1 > Điều 16", "section_type": "scope_of_work", "has_tables": true, "table_count": 1, "table_types": ["bill_of_quantities"], "contains_forms": true, "contains_technical_specs": true, "contains_time_references": true, "time_reference_count": 8, "entities": {"locations": ["các điểm a, b, c, d, e và g Khoản 1 Điều 5 của Luật", "các điểm a, b Khoản 2 và các điểm d, e Khoản 1 Điều", "Mẫu 01 Chương III; 2. Thỏa thuận liên danh nếu là n", "Mục 8 Chương này; 4. Đề xuất về giá theo Mẫu 12A, 1", "thời điểm 28 ngày trước ngày có thời điểm đóng thầu", "Chương III để chứng minh tính phù hợp của đề xuất đ", "Mục 6 Chương I phải được ký bởi người đại diện hợp", "bên cạnh hoặc tại trang đó của người ký đơn dự thầu", "thầu 1. HSĐX do nhà thầu nộp trực tiếp hoặc gửi đến", "thầu: Chủ đầu tư tiến hành mở thầu bao gồm các nội", "hồ sơ và đọc rõ các thông tin về tên nhà thầu: - Th", "thầu bao gồm các thông tin quy định tại điểm a và đ", "thầu phải được ký xác nhận bởi đại diện của Chủ đầu", "thời điểm dự thầu, chưa xác định được thầu phụ thì", "Mục này trên giá trị phần công việc mà thành viên l", "Chương II. 2. Trong quá trình đánh giá, chủ đầu tư", "cho nhà thầu chuẩn bị HSĐX]. Mục 15. Thông báo kết", "thời điểm ký kết, HSĐX của nhà thầu trúng thầu còn", "Nghị quyết của Quốc hội hoặc văn bản quy phạm pháp", "Mục 6 Chương I; c) Kiểm tra sự thống nhất nội dung", "Mục 9 Chương I; đ) Có thỏa thuận liên danh (trong t", "Mục 3 Chương I; g) Trong thời hạn 03 năm trước thời", "thời điểm nhân sự thực hiện hành vi vi phạm) bị Tòa", "Bảng số 01 sau đây: Bảng số 01 [BẢNG: Không tiêu đề", "Khoản 8 Điều 16 của Luật Đấu thầu thì hợp đồng này", "tương tự về tính chất, không căn cứ vào quy mô (giá", "hữu của nhà thầu hoặc đi thuê) để phục vụ công việc", "Khoản 3 Điều 44 của Luật Đấu thầu. (4) Nhà thầu có", "phù hợp với vị trí công việc của mỗi nhân sự chủ ch", "Khoản 4 của Bảng số 01 mà không đưa tiêu chuẩn đánh", "Mục 14 Chương I. CHƯƠNG III. BIỂU MẪU Mẫu 01 ĐƠN DỰ", "và các hành vi vi phạm quy định khác của pháp luật", "thời điểm nhân sự thực hiện hành vi vi phạm) bị tòa", "các hồ sơ khác liên quan có phân công trách nhiệm c", "Mẫu 10 phải kê khai Mẫu này. - Nhà thầu gửi kèm hợp", "Mục này, nhà thầu phải đề xuất tổng số công cho nhâ", "Bảng số 01 Mục 2 Chương II. Mẫu 11 PHẠM VI CÔNG VIỆ", "Khoản 4 Điều 11 Luật Đấu thầu. (2) Nhà thầu ghi cụ", "Mục 12. 2 Chương I. Trường hợp nhà thầu liên danh,", "Mục 12. 2 Chương I. (6) Nhà thầu ghi cụ thể số hợp"]}, "content_stats": {"char_count": 37393, "word_count": 8229, "line_count": 1, "paragraph_count": 1, "sentence_count": 292}}, "chunk_id": "chunk_000", "char_count": 37393, "level": "paragraph", "hierarchy": [], "parent_id": null, "parsed_sections": [], "tables": [{"start_line": 0, "end_line": 1, "content": "Mẫu 1D MẪU HỒ SƠ YÊU CẦU GÓI THẦU DỊCH VỤ TƯ VẤN (Ban hành kèm theo Thông tư số 80/2025/TT-BTC ngày 08 tháng 8 năm 2025 của Bộ trưởng Bộ Tài chính) HỒ SƠ YÊU CẦU DỊCH VỤ TƯ VẤN [BẢNG: Không tiêu đề] [BẢNG: Không tiêu đề] TỪ NGỮ VIẾT TẮT [BẢNG: Không tiêu đề] Phần 1. THỦ TỤC CHỈ ĐỊNH THẦU Chương I. CHỈ DẪN NHÀ THẦU Mục 1. Nội dung gói thầu 1. Chủ đầu tư ___ [Ghi tên, địa chỉ chủ đầu tư] mời nhà thầu nhận HSYC gói thầu ___ [Ghi tên gói thầu theo kế hoạch lựa chọn nhà thầu được duyệt] thuộc___ [Ghi tên dự án/dự toán mua sắm]. 2. Nguồn vốn để thực hiện gói thầu: ______[Ghi rõ nguồn vốn đã được xác định hoặc phê duyệt; trường hợp sử dụng vốn ODA, vốn vay ưu đãi nước ngoài thì phải ghi rõ tên nhà tài trợ và cơ cấu nguồn vốn, bao gồm vốn tài trợ, vốn đối ứng trong nước]. 3. Thời gian thực hiện gói thầu là: ___ [Ghi thời gian cụ thể theo kế hoạch lựa chọn nhà thầu được duyệt], được tính từ ngày hợp đồng có hiệu lực đến ngày nghiệm thu hoàn thành DVTV, không bao gồm thời gian giám sát tác giả (nếu có). Mục 2. Hành vi bị cấm trong đấu thầu Hành vi bị cấm trong đấu thầu là hành vi quy định tại Điều 16 của Luật đấu thầu. Mục 3. Tư cách hợp lệ của nhà thầu 1. Nhà thầu là tổ chức có tư cách hợp lệ khi đáp ứng quy định tại các điểm a, b, c, d, e và g Khoản 1 Điều 5 của Luật Đấu thầu; 2. Nhà thầu là hộ kinh doanh có tư cách hợp lệ khi đáp ứng quy định tại các điểm a, b Khoản 2 và các điểm d, e Khoản 1 Điều 5 của Luật Đấu thầu; Trường hợp pháp luật có liên quan quy định nhà thầu dự thầu, thực hiện hợp đồng phải độc lập với các tổ chức, cá nhân khác thì phải tuân thủ quy định đó. Mục 4. Làm rõ, sửa đổi HSYC 1. Trường hợp nhà thầu cần làm rõ HSYC, nhà thầu gửi văn bản đến Chủ đầu tư trong thời hạn tối thiểu 03 ngày làm việc trước ngày có thời điểm đóng thầu để đánh giá, xử lý. 2. Trường hợp sửa đổi HSYC, Chủ đầu tư có trách nhiệm gửi quyết định sửa đổi và các nội dung sửa đổi tới nhà thầu. Thời gian gửi văn bản sửa đổi HSYC đến nhà thầu là ___ [Ghi số ngày cụ thể, tối thiểu 03 ngày làm việc trước ngày có thời điểm đóng thầu và bảo đảm đủ thời gian để nhà thầu hoàn chỉnh HSĐX]; trường hợp không bảo đảm đủ thời gian như nêu trên thì phải gia hạn thời điểm đóng thầu. Mục 5. Chi phí, đồng tiền, ngôn ngữ khi dự thầu 1. Nhà thầu phải chịu mọi chi phí liên quan đến quá trình dự thầu. 2. Đồng tiền dự thầu và đồng tiền thanh toán là VND. 3. HSĐX cũng như tất cả văn bản và hồ sơ liên quan đến HSĐX được viết bằng tiếng Việt. Các hồ sơ bổ trợ trong HSĐX có thể được viết bằng ngôn ngữ khác, đồng thời kèm theo bản dịch sang tiếng Việt. Trường hợp thiếu bản dịch, chủ đầu tư có thể yêu cầu nhà thầu gửi bổ sung (nếu cần thiết). Mục 6. Thành phần của HSĐX HSĐX do nhà thầu chuẩn bị phải bao gồm: 1. Đơn dự thầu theo quy định tại Mẫu 01 Chương III; 2. Thỏa thuận liên danh nếu là nhà thầu liên danh theo Mẫu 03 Chương III; 3. Đề xuất kỹ thuật theo quy định tại Mục 8 Chương này; 4. Đề xuất về giá theo Mẫu 12A, 12B, 13, 14 và 15 Chương III; 5. Các nội dung khác __ [Nêu các nội dung khác tùy theo tính chất, yêu cầu của gói thầu]. Mục 7. giá thầu 1. giá thầu do nhà thầu ghi trong đơn dự thầu bao gồm toàn bộ các chi phí (chưa tính giảm giá) để thực hiện gói thầu theo yêu cầu của HSYC, kể cả các loại thuế, phí, lệ phí (nếu có) áp theo thuế suất, mức phí, lệ phí tại thời điểm 28 ngày trước ngày có thời điểm đóng thầu. Nhà thầu ______ phân tích chi phí thù lao cho chuyên gia theo Mẫu 12B Chương III. [Trường hợp không yêu cầu nhà thầu phân tích chi phí thù lao cho chuyên gia thì ghi rõ “không”. Trường hợp yêu cầu nhà thầu phân tích chi phí thù lao cho chuyên gia thì ghi rõ “phải”]. 2. giá thầu phải bao gồm tất cả chi phí cho các yếu tố rủi ro và chi phí trượt giá có thể xảy ra trong quá trình thực hiện hợp đồng. Trường hợp gói thầu tư vấn đơn giản, thời gian thực hiện hợp đồng ngắn, không phát sinh rủi ro, trượt giá thì chi phí cho các yếu tố rủi ro và chi phí trượt giá được tính bằng 0 (đồng). Đối với gói thầu áp dụng loại hợp đồng theo thời gian, giá thầu không bao gồm chi phí cho các yếu tố rủi ro và chi phí trượt giá có thể xảy ra trong quá trình thực hiện hợp đồng. Mục 8. Thành phần đề xuất kỹ thuật Căn cứ phạm vi DVTV hoặc các nội dung yêu cầu khác, Nhà thầu phải nộp đề xuất kỹ thuật, trong đó mô tả cụ thể phương pháp thực hiện công việc, nhân sự, tiến độ thực hiện và các thông tin cần thiết khác theo quy định tại Chương III để chứng minh tính phù hợp của đề xuất đối với các yêu cầu công việc và thời hạn cần hoàn thành công việc. Mục 9. Hiệu lực của HSĐX 1. Thời gian có hiệu lực của HSĐX phải bảo đảm theo yêu cầu là ___ [Ghi rõ số ngày tuỳ thuộc quy mô, tính chất của gói thầu, bảo đảm thời gian có hiệu lực đến ngày ký kết hợp đồng] kể từ ngày có thời điểm đóng thầu. 2. Trong trường hợp cần thiết, trước khi hết thời hạn hiệu lực của HSĐX, Chủ đầu tư có thể đề nghị nhà thầu gia hạn hiệu lực của HSĐX. Việc đề nghị gia hạn và chấp thuận gia hạn phải được thể hiện bằng văn bản. Mục 10. Quy cách của HSĐX và chữ ký trong HSĐX 1. Nhà thầu phải chuẩn bị một bản gốc và _______bản chụp HSĐX [Ghi số lượng yêu cầu nhưng không quá 03 bản], ghi rõ \"bản gốc\" và \"bản chụp\" tương ứng. Nhà thầu cần ghi rõ tên gói thầu, tên nhà thầu, tên Chủ đầu tư bên ngoài túi đựng HSĐX. Nhà thầu phải chịu trách nhiệm về tính chính xác và phù hợp giữa bản chụp và bản gốc. Trường hợp có sự sai khác giữa bản gốc và bản chụp thì căn cứ vào bản gốc để đánh giá. 2. Tất cả các thành phần nêu tại Mục 6 Chương I phải được ký bởi người đại diện hợp pháp của nhà thầu. Trường hợp là nhà thầu liên danh thì HSĐX phải có chữ ký của đại diện hợp pháp của tất cả thành viên liên danh hoặc thành viên đại diện nhà thầu liên danh theo phân công trong thỏa thuận liên danh. 3. Những chữ được ghi thêm, ghi chèn vào giữa các dòng, những chữ bị tẩy xóa hoặc viết đè lên sẽ chỉ được coi là hợp lệ nếu có chữ ký ở bên cạnh hoặc tại trang đó của người ký đơn dự thầu. Mục 11. Thời điểm đóng thầu và mở thầu 1. HSĐX do nhà thầu nộp trực tiếp hoặc gửi đến địa chỉ của chủ đầu tư nhưng phải đảm bảo chủ đầu tư nhận được trước thời điểm đóng thầu: ___ giờ, ngày ___ tháng ___ năm ____ [Ghi thời điểm đóng thầu]. 2. Mở thầu: Chủ đầu tư tiến hành mở thầu bao gồm các nội dung sau: a) Kiểm tra niêm phong; b) Mở hồ sơ và đọc rõ các thông tin về tên nhà thầu: - Tham dự độc lập hay liên danh; - Số lượng bản gốc, bản chụp; - giá thầu chào trong đơn dự thầu; - Giá trị giảm giá (nếu có); - Thời gian có hiệu lực của HSĐX; - Thời gian thực hiện gói thầu; - Các thông tin khác liên quan. Biên bản mở thầu bao gồm các thông tin quy định tại điểm a và điểm b khoản này. Biên bản mở thầu phải được ký xác nhận bởi đại diện của Chủ đầu tư và nhà thầu nộp HSĐX. Biên bản này phải được gửi cho nhà thầu nộp HSĐX. Đại diện của Chủ đầu tư phải ký xác nhận vào bản gốc đơn dự thầu, thư giảm giá (nếu có), giấy ủy quyền của người đại diện theo pháp luật của nhà thầu (nếu có), thỏa thuận liên danh (nếu có), các nội dung đề xuất về tài chính và các nội dung quan trọng khác của HSĐX. Mục 12. thầu phụ 1. thầu phụ là tổ chức, cá nhân ký kết hợp đồng với nhà thầu để tham gia thực hiện một hoặc một số hạng mục công việc của gói thầu. Nhà thầu phải kê khai thầu phụ và các hạng mục công việc dành cho thầu phụ theo Mẫu 11 Chương III. Trường hợp tại thời điểm dự thầu, chưa xác định được thầu phụ thì phải kê khai các hạng mục công việc dự kiến dành cho thầu phụ. Việc sử dụng thầu phụ sẽ không làm thay đổi các trách nhiệm của nhà thầu. Nhà thầu phải chịu trách nhiệm về khối lượng, chất lượng, tiến độ và các trách nhiệm khác đối với phần công việc do thầu phụ thực hiện. Năng lực và kinh nghiệm của thầu phụ sẽ không được đánh giá khi đánh giá HSĐX của nhà thầu. Bản thân nhà thầu phải đáp ứng các tiêu chí năng lực và kinh nghiệm (không xét đến năng lực và kinh nghiệm của thầu phụ). Nhà thầu được ký kết hợp đồng với các thầu phụ trong danh sách các thầu phụ nêu trong HSĐX hoặc ký với thầu phụ được chủ đầu tư chấp thuận để tham gia thực hiện công việc gói thầu. 2. Nhà thầu chỉ được sử dụng thầu phụ thực hiện các công việc với tổng giá trị dành cho thầu phụ không vượt quá ___ [tùy theo quy mô, tính chất gói thầu, chủ đầu tư ghi tỷ lệ % tối đa dành cho thầu phụ] giá thầu của nhà thầu. Đối với trường hợp liên danh, từng thành viên liên danh chỉ được sử dụng thầu phụ không vượt quá tỷ lệ phần trăm quy định tại Mục này trên giá trị phần công việc mà thành viên liên danh đó đảm nhận trong thỏa thuận liên danh. Mục 13. Đánh giá HSĐX và thương thảo về các đề xuất của nhà thầu 1. Việc đánh giá HSĐX được thực hiện theo quy định tại Chương II. 2. Trong quá trình đánh giá, chủ đầu tư mời nhà thầu thương thảo về giá bảo đảm đáp ứng tỷ lệ tiết kiệm theo quy định của HSYC, thương thảo, làm rõ hoặc sửa đổi, bổ sung nội dung HSĐX để chứng minh việc đáp ứng yêu cầu về năng lực, kinh nghiệm, tiến độ, khối lượng, chất lượng, giải pháp kỹ thuật, biện pháp tổ chức thực hiện gói thầu và tỷ lệ tiết kiệm. Mục 14. Điều kiện đối với nhà thầu được đề nghị chỉ định thầu Nhà thầu được đề nghị chỉ định thầu khi đáp ứng đầy đủ các điều kiện sau đây: 1. Có HSĐX hợp lệ; 2. Có đề xuất về kỹ thuật đáp ứng yêu cầu của HSYC; 3. Có giá đề nghị trúng thầu không vượt giá gói thầu được duyệt và đáp ứng tỷ lệ tiết kiệm tối thiểu __% giá gói thầu [Căn cứ quy mô, tính chất, điều kiện cụ thể của gói thầu, chủ đầu tư quy định trong HSYC mức tỷ lệ tiết kiệm của giá đề nghị trúng thầu để làm cơ sở cho nhà thầu chuẩn bị HSĐX]. Mục 15. Thông báo kết quả lựa chọn nhà thầu Trong thời hạn 05 ngày làm việc kể từ ngày kết quả lựa chọn nhà thầu được phê duyệt, Chủ đầu tư đăng tải thông tin về kết quả lựa chọn nhà thầu lên Hệ thống mạng đấu thầu quốc gia; gửi văn bản thông báo kết quả lựa chọn nhà thầu cho nhà thầu dự thầu. Nội dung thông báo kết quả lựa chọn nhà thầu như sau: a) Thông tin về gói thầu: - Tên gói thầu; - Giá gói thầu hoặc dự toán được duyệt (nếu có); - Tên Chủ đầu tư; - Hình thức lựa chọn nhà thầu; - Loại hợp đồng; - Thời gian thực hiện gói thầu. b) Thông tin về nhà thầu trúng thầu: - Tên nhà thầu; - Mã số thuế (nếu có); - giá thầu; - Giá trúng thầu; - Thời gian thực hiện gói thầu; - Thời gian thực hiện hợp đồng. c) Kế hoạch hoàn thiện, ký kết hợp đồng với nhà thầu trúng thầu. Mục 16. Điều kiện ký kết hợp đồng 1. Tại thời điểm ký kết, HSĐX của nhà thầu trúng thầu còn hiệu lực. 2. Chủ đầu tư phải bảo đảm các điều kiện về vốn tạm ứng, vốn thanh toán, mặt bằng thực hiện (nếu có) và điều kiện cần thiết khác để triển khai thực hiện gói thầu theo đúng tiến độ. Mục 17. Giải quyết kiến nghị 1. Đối với gói thầu thuộc phạm vi điều chỉnh của Luật Đấu thầu: a) Khi thấy quyền và lợi ích hợp pháp bị ảnh hưởng, nhà thầu được kiến nghị người có thẩm quyền, Chủ đầu tư, Hội đồng giải quyết kiến nghị đánh giá lại các vấn đề trong quá trình lựa chọn nhà thầu, kết quả lựa chọn nhà thầu theo quy định tại Điều 89 của Luật Đấu thầu và các Điều 137, 138 và 139 của Nghị định số 214/2025/NĐ-CP. b) Địa chỉ nhận đơn kiến nghị: - Địa chỉ nhận đơn kiến nghị của Chủ đầu tư: ______ [ghi đầy đủ tên, địa chỉ, số điện thoại, email]. - Địa chỉ nhận đơn kiến nghị của người có thẩm quyền: ______ [ghi đầy đủ tên, địa chỉ, số điện thoại, email]. - Địa chỉ bộ phận thường trực giúp việc của Hội đồng giải quyết kiến nghị: ___ [ghi đầy đủ tên, địa chỉ, số điện thoại, email]. 2. Đối với hoạt động lựa chọn nhà thầu quy định tại điểm d Khoản 7 Điều 3 của Luật Đấu thầu hoặc hoạt động lựa chọn nhà thầu không thuộc phạm vi điều chỉnh của Luật Đấu thầu: Khi thấy quyền và lợi ích hợp pháp bị ảnh hưởng, nhà thầu, cơ quan, tổ chức được kiến nghị theo quy trình sau: ___ [ghi cụ thể quy trình, thủ tục của việc giải quyết kiến nghị của đơn vị, tổ chức đồng thời ghi rõ email, địa chỉ của cá nhân/tổ chức/đơn vị giải quyết kiến nghị]. Mục 18. Ưu đãi trong lựa chọn nhà thầu Ưu đãi: _____ [Chủ đầu tư ghi rõ đối tượng, điều kiện ưu đãi theo quy định tại Nghị quyết của Quốc hội hoặc văn bản quy phạm pháp luật (nếu có)]. Chương II. TIÊU CHUẨN ĐÁNH GIÁ HSĐX Mục 1. Kiểm tra và đánh giá tính hợp lệ của HSĐX 1. 1. Kiểm tra HSĐX a) Kiểm tra số lượng bản gốc, bản chụp HSĐX; b) Kiểm tra các thành phần của HSĐX theo quy định tại Mục 6 Chương I; c) Kiểm tra sự thống nhất nội dung giữa bản gốc và bản chụp để phục vụ quá trình đánh giá chi tiết HSĐX. 1. 2. Đánh giá tính hợp lệ của HSĐX HSĐX của nhà thầu được đánh giá là hợp lệ khi đáp ứng đầy đủ các nội dung sau đây: a) Có bản gốc HSĐX; b) Có đơn dự thầu được đại diện hợp pháp của nhà thầu ký tên, đóng dấu (nếu có) theo yêu cầu của HSYC; thời gian ký đơn dự thầu phải sau thời điểm phát hành HSYC; không kèm theo điều kiện gây bất lợi cho Chủ đầu tư. Đối với nhà thầu liên danh, đơn dự thầu phải do đại diện hợp pháp của từng thành viên liên danh ký tên, đóng dấu (nếu có) hoặc thành viên được phân công thay mặt liên danh ký đơn dự thầu theo phân công trách nhiệm trong thỏa thuận liên danh; c) Đã thực hiện nghĩa vụ kê khai thuế và nộp thuế: Trường hợp thời điểm đóng thầu sau ngày kết thúc năm tài chính của nhà thầu (năm Y) và trước hoặc trong ngày cuối cùng của tháng thứ 3 tính từ ngày kết thúc năm Y, yêu cầu đã thực hiện nghĩa vụ kê khai thuế và nộp thuế áp dụng đối với năm tài chính trước năm Y (năm Y-1) (Ví dụ: thời điểm đóng thầu là vào ngày 20/3/2024, năm tài chính của nhà thầu kết thúc vào ngày 31/12 thì nhà thầu phải chứng minh đã thực hiện nghĩa vụ kê khai thuế và nộp thuế của năm 2022); d) Hiệu lực của HSĐX đáp ứng yêu cầu theo quy định tại Mục 9 Chương I; đ) Có thỏa thuận liên danh (trong trường hợp liên danh) được đại diện hợp pháp của từng thành viên liên danh ký tên, đóng dấu (nếu có); trong thỏa thuận liên danh phải nêu rõ nội dung công việc cụ thể và ước tính giá trị tương ứng mà từng thành viên trong liên danh sẽ thực hiện. Việc phân chia công việc trong liên danh phải căn cứ các hạng mục công việc nêu trong điều khoản tham chiếu, đề xuất kỹ thuật, không được phân chia các công việc không thuộc các hạng mục này; e) Nhà thầu bảo đảm tư cách hợp lệ theo quy định tại Mục 3 Chương I; g) Trong thời hạn 03 năm trước thời điểm đóng thầu, nhà thầu không có nhân sự (ký kết hợp đồng lao động với nhà thầu tại thời điểm nhân sự thực hiện hành vi vi phạm) bị Tòa án kết án có hành vi vi phạm quy định về đấu thầu gây hậu quả nghiêm trọng theo quy định pháp luật về hình sự nhằm mục đích cho nhà thầu đó trúng thầu; h) Có đủ điều kiện năng lực hoạt động theo quy định của pháp luật quản lý ngành và lĩnh vực (nếu có). Nhà thầu có HSĐX hợp lệ được đánh giá, đánh giá trong các bước tiếp theo. Mục 2. Tiêu chuẩn đánh giá về kỹ thuật Việc đánh giá về kỹ thuật đối với từng HSĐX được thực hiện theo phương pháp chấm điểm, trong đó phải quy định mức điểm tối đa đối với các tiêu chuẩn tổng quát, tiêu chuẩn chi tiết; quy định mức điểm tối thiểu đối với tiêu chuẩn tổng quát và chi tiết (nếu cần thiết) của các nội dung giải pháp và phương pháp luận, nhân sự chủ chốt. Đối với tiêu chuẩn về kinh nghiệm và năng lực của nhà thầu, căn cứ tính chất gói thầu để xác định sự cần thiết quy định hoặc không quy định điểm tối thiểu đối với tiêu chuẩn tổng quát này. Việc đánh giá hợp đồng tương tự của nhà thầu liên danh căn cứ vào phạm vi công việc của từng thành viên trong liên danh đảm nhận. Tiêu chuẩn đánh giá về kỹ thuật gồm các nội dung tại Bảng số 01 sau đây: Bảng số 01 [BẢNG: Không tiêu đề] Ghi chú: (1) Thời điểm xác định hợp đồng hoàn thành để xác định hợp đồng tương tự là thời điểm nghiệm thu công việc hoàn thành. Đối với các hợp đồng mà Chủ đầu tư, tổ chuyên gia có bằng chứng cho thấy nhà thầu đã thực hiện với tư cách thầu phụ do được chuyển nhượng bất hợp pháp, vi phạm quy định tại Khoản 8 Điều 16 của Luật Đấu thầu thì hợp đồng này sẽ không được đánh giá, đánh giá. Hợp đồng tương tự được xác định trên cơ sở tương tự về tính chất, không căn cứ vào quy mô (giá trị hợp đồng). (2) Tùy theo tính chất của gói thầu mà quy định cho phù hợp. Ví dụ: đáp ứng về vật tư, máy móc, thiết bị (thuộc sở hữu của nhà thầu hoặc đi thuê) để phục vụ công việc thí nghiệm. .. . (3) Uy tín của nhà thầu thông qua việc dự thầu, kết quả thực hiện hợp đồng của nhà thầu thực hiện theo quy định tại Điều 19 và Điều 20 của Nghị định số 214/2025/NĐ-CP. Đối với nhà thầu là tư vấn lập hồ sơ mời thầu, uy tín của nhà thầu thông qua việc dự thầu, kết quả thực hiện hợp đồng của nhà thầu còn thể hiện qua số lượng hồ sơ mời thầu bị kết luận có nội dung vi phạm quy định tại Khoản 3 Điều 44 của Luật Đấu thầu. (4) Nhà thầu có thể đề xuất nhân sự chủ chốt thuộc biên chế của nhà thầu hoặc đi thuê. Nếu pháp luật quản lý ngành, lĩnh vực có quy định nhân sự phải có trình độ, bằng cấp chuyên môn cụ thể để được cấp giấy phép hành nghề/chứng chỉ chuyên môn thì trong HSYC ngoài yêu cầu về giấy phép hành nghề/chứng chỉ chuyên môn không được yêu cầu về trình độ, bằng cấp cụ thể của nhân sự chủ chốt. Trường hợp có quy định về số năm kinh nghiệm trong các công việc tương tự thì số năm kinh nghiệm này được tính từ thời điểm nhân sự bắt đầu thực hiện công việc tương tự đó đến thời điểm đóng thầu. Việc xây dựng tiêu chuẩn đánh giá về kỹ thuật cần đảm bảo các yêu cầu sau: - Tổng điểm cho các nội dung kinh nghiệm và năng lực, uy tín của nhà thầu thông qua việc dự thầu, kết quả thực hiện hợp đồng, giải pháp và phương pháp luận, nhân sự, yêu cầu về chuyển giao kỹ thuật (nếu có) là 100%. - Đối với tiêu chuẩn đánh giá về nhân sự chủ chốt: chỉ đưa các tiêu chuẩn đánh giá về trình độ chuyên môn, năng lực, kinh nghiệm trên cơ sở phù hợp với vị trí công việc của mỗi nhân sự chủ chốt nêu tại Khoản 4 của Bảng số 01 mà không đưa tiêu chuẩn đánh giá đối với nhân sự khác. - Mức điểm yêu cầu tối thiểu đối với tiêu chuẩn giải pháp và phương pháp luận, nhân sự, chuyển giao kỹ thuật (nếu có) không được quy định thấp hơn 60% điểm tối đa của tiêu chuẩn đó (không thấp hơn 70% đối với gói thầu tư vấn có yêu cầu kỹ thuật cao, đặc thù). HSĐX không đáp ứng mức điểm yêu cầu tối thiểu đối với một hoặc các tiêu chuẩn giải pháp và phương pháp luận, nhân sự, chuyển giao kỹ thuật (nếu có) được đánh giá là không đáp ứng yêu cầu về kỹ thuật. - Mức điểm yêu cầu tối thiểu về kỹ thuật không được quy định thấp hơn 70% tổng số điểm về kỹ thuật (80% đối với gói thầu tư vấn có yêu cầu kỹ thuật cao, đặc thù). HSĐX có điểm kỹ thuật không thấp hơn mức điểm yêu cầu tối thiểu được đánh giá là đáp ứng yêu cầu về kỹ thuật. Nhà thầu đáp ứng yêu cầu về kỹ thuật được đánh giá về tài chính. Mục 3. Tiêu chuẩn đánh giá về tài chính Bước 1. Xác định giá thầu; Bước 2. Sửa lỗi, hiệu chỉnh sai lệch theo quy định tại Điều 68 của Nghị định số 214/2025/NĐ-CP (nếu có); Bước 3. Xác định giá thầu sau sửa lỗi, hiệu chỉnh sai lệch (nếu có), trừ đi giá trị giảm giá (nếu có) và đáp ứng tỷ lệ tiết kiệm theo quy định tại Mục 14 Chương I. CHƯƠNG III. BIỂU MẪU Mẫu 01 ĐƠN DỰ THẦU ________, ngày ____ tháng ____ năm ____ Kính gửi: __________________ [Ghi tên chủ đầu tư] (sau đây gọi là Chủ đầu tư) Sau khi nghiên cứu hồ sơ yêu cầu (bao gồm văn bản sửa đổi hồ sơ yêu cầu, nếu có), chúng tôi, _____ [Ghi tên nhà thầu], có địa chỉ tại ______[Ghi địa chỉ của nhà thầu] cam kết thực hiện gói thầu _______[Ghi tên gói thầu] theo đúng yêu cầu của hồ sơ yêu cầu với tổng số tiền là _____ [Ghi giá trị bằng số, bằng chữ và đồng tiền dự thầu]. Thời gian thực hiện gói thầu là ____ [Ghi thời gian thực hiện tất cả các công việc theo yêu cầu của HSYC]. Hồ sơ đề xuất có hiệu lực là ___ngày [Ghi số ngày], kể từ ngày ___tháng ___ năm ___[Ghi ngày có thời điểm đóng thầu]. Chúng tôi cam kết: 1. Không đang trong quá trình thực hiện thủ tục giải thể hoặc bị thu hồi giấy chứng nhận đăng ký doanh nghiệp, giấy chứng nhận đăng ký hợp tác xã, liên hiệp hợp tác xã, tổ hợp tác, không thuộc trường hợp mất khả năng thanh toán theo quy định của pháp luật về phá sản (không đang trong quá trình chấm dứt hoạt động hoặc bị thu hồi giấy chứng nhận đăng ký hộ kinh doanh đối với nhà thầu là hộ kinh doanh). 2. Đã thực hiện nghĩa vụ kê khai thuế và nộp thuế của năm tài chính gần nhất so với thời điểm đóng thầu; 3. Không đang trong thời gian bị cấm dự thầu theo quy định của pháp luật đấu thầu; 4. Không đang bị truy cứu trách nhiệm hình sự (chủ hộ không đang bị truy cứu trách nhiệm hình sự trong trường hợp nhà thầu là hộ kinh doanh); 5. Không thực hiện các hành vi tham nhũng, hối lộ, thông thầu, cản trở và các hành vi vi phạm quy định khác của pháp luật đấu thầu khi tham dự gói thầu này. 6. Trong thời hạn 03 năm trước thời điểm đóng thầu, nhà thầu không có nhân sự (ký kết hợp đồng lao động với nhà thầu tại thời điểm nhân sự thực hiện hành vi vi phạm) bị tòa án kết án có hành vi vi phạm quy định về đấu thầu gây hậu quả nghiêm trọng theo quy định của pháp luật về hình sự nhằm mục đích cho nhà thầu trúng thầu. 7. Những thông tin kê khai trong HSĐX là trung thực. 8. Trường hợp trúng thầu, HSĐX và các văn bản bổ sung, làm rõ HSĐX tạo thành thỏa thuận ràng buộc trách nhiệm giữa hai bên cho tới khi hợp đồng được ký kết. [BẢNG: Không tiêu đề] Ghi chú: (1) Trường hợp đại diện theo pháp luật của nhà thầu ủy quyền cho cấp dưới ký đơn dự thầu thì phải gửi kèm theo Giấy ủy quyền theo Mẫu 02 Chương này. Trường hợp tại điều lệ công ty hoặc tại các hồ sơ khác liên quan có phân công trách nhiệm cho cấp dưới ký đơn dự thầu thì phải gửi kèm theo bản chụp các văn bản, hồ sơ này (không cần lập Giấy ủy quyền theo Mẫu 02 Chương này). (2) HSYC không được yêu cầu nhà thầu phải nộp lý lịch tư pháp của nhân sự để chứng minh cho nội dung đánh giá này. Nội dung này chỉ yêu cầu nhà thầu cam kết trong Đơn này. Mẫu 02 GIẤY ỦY QUYỀN(1) Hôm nay, ngày ____ tháng ____ năm ____, tại ____ Tôi là__[Ghi tên, số CCCD hoặc số hộ chiếu, chức danh của người đại diện theo pháp luật của nhà thầu], là người đại diện theo pháp luật của [Ghi tên nhà thầu] có địa chỉ tại [Ghi địa chỉ của nhà thầu] bằng văn bản này ủy quyền cho [Ghi tên, số CCCD hoặc số hộ chiếu, chức danh của người được ủy quyền] thực hiện các công việc sau đây trong quá trình dự thầu gói thầu__ [Ghi tên gói thầu] thuộc [Ghi tên dự án/dự toán mua sắm] do [Ghi tên chủ đầu tư] tổ chức: [- Ký đơn dự thầu; - Ký thỏa thuận liên danh (nếu có); - Ký các văn bản, hồ sơ để giao dịch với Chủ đầu tư trong quá trình dự thầu, kể cả văn bản giải trình, làm rõ HSĐX; - Tham gia quá trình thương thảo (nếu có), hoàn thiện hợp đồng; - Ký kết hợp đồng với chủ đầu tư nếu được chỉ định thầu.](2) Người được ủy quyền nêu trên chỉ thực hiện các công việc trong phạm vi ủy quyền với tư cách là đại diện hợp pháp của [Ghi tên nhà thầu]. [Ghi tên nhà thầu] chịu trách nhiệm hoàn toàn về những công việc do ____ [Ghi tên người được ủy quyền] thực hiện trong phạm vi ủy quyền. Giấy ủy quyền có hiệu lực kể từ ngày ____ đến ngày ____(3). Giấy ủy quyền này được lập thành bản có giá trị pháp lý như nhau, người ủy quyền giữ ____ bản, người được ủy quyền giữ ____ bản. [BẢNG: Không tiêu đề] Ghi chú: (1) Trường hợp ủy quyền thì bản gốc giấy ủy quyền phải được gửi cho chủ đầu tư cùng với đơn dự thầu. Việc ủy quyền của người đại diện theo pháp luật của nhà thầu cho cấp phó, cấp dưới, giám đốc chi nhánh, người đứng đầu văn phòng đại diện của nhà thầu để thay mặt cho người đại diện theo pháp luật của nhà thầu thực hiện một hoặc các nội dung công việc nêu trên đây. Việc sử dụng con dấu trong trường hợp được ủy quyền có thể là dấu của nhà thầu hoặc dấu của đơn vị mà cá nhân liên quan được ủy quyền. Người được ủy quyền không được tiếp tục ủy quyền cho người khác. (2) Phạm vi ủy quyền bao gồm một hoặc nhiều công việc nêu trên. (3) Ghi ngày có hiệu lực và ngày hết hiệu lực của giấy ủy quyền phù hợp với quá trình dự thầu và phải bảo đảm có hiệu lực trước ngày thực hiện các công việc được ủy quyền. Mẫu 03 THỎA THUẬN LIÊN DANH (1), ngày tháng năm Gói thầu: ___ [Ghi tên gói thầu] Thuộc: ___ [Ghi tên dự án/dự toán mua sắm] - Căn cứ ___ [Luật Đấu thầu](2); - Căn cứ ___ (2); - Căn cứ hồ sơ yêu cầu gói thầu _______ [Ghi tên gói thầu] ngày___tháng____ năm ____[Ngày được ghi trên HSYC]; Chúng tôi, đại diện cho các bên ký thỏa thuận liên danh, gồm có: Tên thành viên liên danh [Ghi tên từng thành viên liên danh] Đại diện là ông/bà: Chức vụ: Địa chỉ: Điện thoại: E-mail: Tài khoản: Mã số thuế: Giấy ủy quyền số __ ngày __tháng __ năm __ (trường hợp được ủy quyền). Các bên (sau đây gọi là thành viên) thống nhất ký kết thỏa thuận liên danh với các nội dung sau: Điều 1. Nguyên tắc chung 1. Các thành viên tự nguyện hình thành liên danh để dự thầu gói thầu [Ghi tên gói thầu] thuộc ___ [Ghi tên dự án/dự toán mua sắm]. 2. Các thành viên thống nhất tên gọi của liên danh cho mọi giao dịch liên quan đến gói thầu này là: [Ghi tên của liên danh]. 3. Các thành viên cam kết không thành viên nào có quyền từ chối thực hiện các trách nhiệm và nghĩa vụ quy định trong hợp đồng. Trường hợp thành viên của liên danh từ chối hoàn thành trách nhiệm riêng của mình như đã thỏa thuận thì thành viên đó bị xử lý như sau: - Bồi thường thiệt hại cho các bên trong liên danh - Bồi thường thiệt hại cho Chủ đầu tư theo quy định nêu trong hợp đồng - Hình thức xử lý khác [Ghi rõ hình thức xử lý khác]. Điều 2. Phân công trách nhiệm Các thành viên thống nhất chịu trách nhiệm chung, trách nhiệm riêng để thực hiện gói thầu [Ghi tên gói thầu] thuộc ___ [Ghi tên dự án/dự toán mua sắm] đối với từng thành viên như sau: 1. Thành viên đứng đầu liên danh Các bên nhất trí ủy quyền cho [Ghi tên một bên] làm thành viên đứng đầu liên danh, đại diện cho liên danh trong những phần việc sau(3): [- Ký đơn dự thầu; - Ký các văn bản, hồ sơ để giao dịch với chủ đầu tư trong quá trình dự thầu, kể cả văn bản đề nghị làm rõ HSYC và văn bản giải trình, làm rõ HSĐX; - Tham gia quá trình thương thảo, hoàn thiện hợp đồng; - Các công việc khác trừ việc ký kết hợp đồng [Ghi rõ nội dung các công việc khác (nếu có)]. 2. Các thành viên trong liên danh thỏa thuận phân công trách nhiệm thực hiện công việc theo bảng dưới đây(4): [BẢNG: Không tiêu đề] Điều 3. Hiệu lực của thỏa thuận liên danh 1. Thỏa thuận liên danh có hiệu lực kể từ ngày ký. 2. Thỏa thuận liên danh chấm dứt hiệu lực trong các trường hợp sau: - Các bên hoàn thành trách nhiệm và nghĩa vụ của mình và tiến hành thanh lý hợp đồng; - Các bên cùng thỏa thuận chấm dứt; - Nhà thầu liên danh không được chỉ định thầu; - Hủy thầu gói thầu [Ghi tên gói thầu] thuộc ___ [Ghi tên dự án/dự toán mua sắm] theo thông báo của chủ đầu tư. Thỏa thuận liên danh được lập thành bản, mỗi bên giữ bản, các bản thỏa thuận có giá trị pháp lý như nhau. ĐẠI DIỆN HỢP PHÁP CỦA THÀNH VIÊN ĐỨNG ĐẦU LIÊN DANH(5) [Ghi tên, chức danh, ký tên và đóng dấu] ĐẠI DIỆN HỢP PHÁP CỦA THÀNH VIÊN LIÊN DANH [Ghi tên từng thành viên, chức danh, ký tên và đóng dấu] Ghi chú: (1) Căn cứ quy mô, tính chất của gói thầu, nội dung thỏa thuận liên danh theo mẫu này có thể được sửa đổi bổ sung cho phù hợp. (2) Cập nhật các văn bản quy phạm pháp luật theo quy định hiện hành. (3) Phạm vi ủy quyền bao gồm một hoặc nhiều công việc nêu trên. (4) Nhà thầu phải ghi rõ nội dung công việc cụ thể và ước tính giá trị tương ứng mà từng thành viên trong liên danh sẽ thực hiện, trách nhiệm chung, trách nhiệm riêng của từng thành viên, kể cả thành viên đứng đầu liên danh. Việc phân chia công việc trong liên danh phải căn cứ các hạng mục công việc nêu trong điều khoản tham chiếu, đề xuất kỹ thuật, không được phân chia các công việc không thuộc các hạng mục này. (5) Đại diện hợp pháp của thành viên liên danh có thể là người đại diện theo pháp luật hoặc người được người đại diện theo pháp luật ủy quyền. Mẫu 04 HẠNG MỤC CÔNG VIỆC CỦA GÓI THẦU 1. Phần công việc dựa trên đơn giá và khối lượng, áp dụng loại hợp đồng trọn gói hoặc loại hợp đồng theo đơn giá(1) [BẢNG: Không tiêu đề] 2. Phần công việc dựa trên lương chuyên gia và chi phí khác ngoài lương, áp dụng loại hợp đồng trọn gói hoặc hợp đồng theo thời gian(2) [BẢNG: Không tiêu đề] Ghi chú: (1) Áp dụng khi gói thầu bao gồm phần công việc dựa theo đơn giá và khối lượng, áp dụng loại hợp đồng trọn gói hoặc loại hợp đồng theo đơn giá; (2) Áp dụng cho phần công việc dựa trên lương chuyên gia và chi phí khác ngoài lương, áp dụng loại hợp đồng trọn gói hoặc hợp đồng theo thời gian; Trường hợp gói thầu có nhiều hạng mục công việc khác nhau thì có thể áp dụng đồng thời các bảng trên tương ứng cho từng hạng mục công việc. Mẫu 05 CƠ CẤU TỔ CHỨC VÀ KINH NGHIỆM CỦA NHÀ THẦU TƯ VẤN A. Cơ cấu tổ chức của nhà thầu [Mô tả tóm tắt quá trình hình thành và tổ chức của nhà thầu (trường hợp liên danh thì mô tả tổ chức của mỗi thành viên trong liên danh). Mô tả số lượng chuyên gia tư vấn chuyên ngành mà nhà thầu ký hợp đồng lao động dài hạn hoặc không xác định thời hạn và nêu rõ số năm kinh nghiệm của từng chuyên gia]. B. Kinh nghiệm của nhà thầu Các gói thầu DVTV tương tự do nhà thầu thực hiện trong vòng [Ghi số năm] năm gần đây. Nhà thầu phải sử dụng bảng sau để kê khai cho mỗi DVTV tương tự như DVTV được yêu cầu trong gói thầu này mà nhà thầu đã thực hiện (với tư cách là nhà thầu độc lập hoặc liên danh với nhà thầu khác hoặc là thầu phụ). Đối với từng công việc tương tự, nhà thầu tư vấn phải cung cấp bản tóm tắt bao gồm tên của nhân sự chủ chốt và thầu phụ của nhà thầu đã tham gia, thời gian thực hiện công việc, giá hợp đồng (trường hợp nhà thầu dự thầu là thành viên liên danh hoặc là thầu phụ thì ghi rõ khối lượng công việc, giá trị đảm nhận với vai trò thành viên liên danh, thầu phụ). Kinh nghiệm thực hiện hợp đồng của các chuyên gia với vai trò tư vấn cá nhân hoặc làm chuyên gia cho các nhà thầu tư vấn khác chỉ được tính vào kinh nghiệm làm việc của bản thân chuyên gia, không tính vào kinh nghiệm thực hiện hợp đồng của nhà thầu nộp HSĐX. [BẢNG: Không tiêu đề] Nhà thầu phải gửi kèm theo bản chụp các văn bản, hồ sơ liên quan. Mẫu 06 NHỮNG GÓP Ý (NẾU CÓ) ĐỂ HOÀN THIỆN NỘI DUNG ĐIỀU KHOẢN THAM CHIẾU [Nhà thầu trình bày những nội dung sửa đổi để hoàn thiện điều khoản tham chiếu nhằm thực hiện hợp đồng] Đề xuất bổ sung, sửa đổi điều khoản tham chiếu: 1. 2. 3. 4. 5. Mẫu 07 GIẢI PHÁP VÀ PHƯƠNG PHÁP LUẬN TỔNG QUÁT DO NHÀ THẦU ĐỀ XUẤT ĐỂ THỰC HIỆN DỊCH VỤ TƯ VẤN Nhà thầu chuẩn bị đề xuất kỹ thuật (cả biểu đồ) gồm 3 phần: 1. Giải pháp và phương pháp luận 2. Kế hoạch công tác 3. Tổ chức và nhân sự Giải pháp và phương pháp luận [Mô tả hiểu biết về mục tiêu của công việc ghi trong Điều khoản tham chiếu, cách tiếp cận kỹ thuật và phương pháp luận sẽ áp dụng để thực hiện công việc nhằm đạt được kết quả dự kiến và mức độ chi tiết của kết quả đó. Đối với gói thầu tư vấn giám sát, giải pháp và phương pháp luận cần bao gồm cả khía cạnh môi trường, xã hội. Nhà thầu lưu ý không sao chép, nhắc lại Điều khoản tham chiếu trong phần này] Kế hoạch thực hiện [Đưa ra kế hoạch thực hiện các hoạt động/công việc chính, nội dung và thời gian hoạt động, phân kỳ hoạt động và tương quan giữa các kỳ, các mốc chính (bao gồm các bước phê duyệt tạm thời của chủ đầu tư) và ngày dự kiến giao nộp báo cáo. Kế hoạch thực hiện phải thống nhất với cách tiếp cận kỹ thuật và phương pháp luận, thể hiện sự hiểu biết về Điều khoản tham chiếu và khả năng chuyển Điều khoản tham chiếu thành kế hoạch thực hiện khả thi. Cần đính kèm danh sách các hồ sơ hoàn chỉnh (bao gồm báo cáo) sẽ phải giao nộp. Kế hoạch thực hiện phải thống nhất với Kế hoạch tiến độ] Tổ chức và Nhân sự [Mô tả cơ cấu và thành phần nhóm chuyên gia, bao gồm danh sách các nhân sự chủ chốt, nhân sự khác, nhân viên hỗ trợ kỹ thuật và hành chính liên quan] Mẫu 08 LÝ LỊCH CHUYÊN GIA TƯ VẤN Tên nhà thầu: [BẢNG: Không tiêu đề] Trình độ học vấn: [liệt kê trường cao đẳng/đại học hoặc khóa học chuyên ngành, nêu tên của cơ sở đào tạo, thời gian học, loại bằng cấp đã đạt được]_______ Quá trình công tác phù hợp với công việc: [liệt kê theo trình tự thời gian quá trình công tác của chuyên gia theo Bảng sau, không cần liệt kê các công việc đã làm không phù hợp với công việc đang yêu cầu] [BẢNG: Không tiêu đề] Thành viên của Hiệp hội chuyên ngành, tổ chức nghề nghiệp và tác phẩm đã xuất bản: ________________________________________________ Ngôn ngữ (Chỉ nêu những ngôn ngữ có thể dùng để làm việc): _______ Tôi xin cam đoan các thông tin nêu trên là đúng sự thật, nếu sai tôi xin chịu trách nhiệm trước pháp luật. [BẢNG: Không tiêu đề] Ghi chú: - Từng cá nhân chuyên gia tư vấn trong danh sách nêu tại Mẫu 10 phải kê khai Mẫu này. - Nhà thầu gửi kèm hợp đồng lao động; bản chụp bằng tốt nghiệp, chứng chỉ hành nghề chuyên môn của các chuyên gia tư vấn nêu trên đính kèm cùng HSĐX. Mẫu 09 TIẾN ĐỘ THỰC HIỆN CÔNG VIỆC [BẢNG: Không tiêu đề] Ghi chú: (1) Liệt kê tất cả hạng mục công việc, trong mỗi hạng mục công việc phải nêu tiến độ thực hiện các công việc cụ thể. (2) Thời gian cho mỗi công việc cụ thể thể hiện bằng biểu đồ, trường hợp cần thiết nhà thầu có ghi chú, giải thích biểu đồ. Mẫu 10 DANH SÁCH CHUYÊN GIA THAM GIA THỰC HIỆN DỊCH VỤ TƯ VẤN [BẢNG: Không tiêu đề] Ghi chú: 1. Trường hợp HSYC có quy định, nhà thầu chọn người/tháng hoặc người/ngày phù hợp với quy định tại Mục này, nhà thầu phải đề xuất tổng số công cho nhân sự chủ chốt không ngắn hơn quy định trong HSYC. 2. Vị trí, số lượng nhân sự chủ chốt phù hợp với yêu cầu nêu tại Bảng số 01 Mục 2 Chương II. Mẫu 11 PHẠM VI CÔNG VIỆC SỬ DỤNG thầu phụ (1) [BẢNG: Không tiêu đề] Ghi chú: (1) Trường hợp HSYC có quy định về việc sử dụng thầu phụ thì nhà thầu kê khai theo Mẫu này. Đối với gói thầu của dự án thuộc lĩnh vực khoa học, kỹ thuật, đổi mới sáng tạo và chuyển đổi số tổ chức đấu thầu trong nước, nhà thầu trong nước được sử dụng thầu phụ là nhà thầu nước ngoài đối với phần công việc đặc thù mà nhà thầu trong nước chưa thực hiện được hoặc cần chuyển giao kỹ thuật theo quy định tại Khoản 4 Điều 11 Luật Đấu thầu. (2) Nhà thầu ghi cụ thể tên thầu phụ. Trường hợp khi dự thầu chưa xác định được cụ thể danh tính của thầu phụ thì không phải kê khai vào cột này mà chỉ kê khai vào cột “Phạm vi công việc”. Nếu nhà thầu trúng thầu thì khi huy động thầu phụ thực hiện công việc đã kê khai phải được sự chấp thuận của chủ đầu tư. (3) Nhà thầu ghi cụ thể tên hạng mục công việc dành cho thầu phụ. (4) Nhà thầu ghi cụ thể khối lượng công việc dành cho thầu phụ. (5) Nhà thầu ghi cụ thể giá trị % công việc mà thầu phụ đảm nhận so với giá thầu nhưng không được vượt quá tỷ lệ phần trăm (%) quy định tại Mục 12. 2 Chương I. Trường hợp nhà thầu liên danh, thành viên liên danh được sử dụng thầu phụ đối với phần công việc đảm nhận theo tỷ lệ % quy định tại Mục 12. 2 Chương I. (6) Nhà thầu ghi cụ thể số hợp đồng hoặc văn bản thỏa thuận và đính kèm bản chụp được chứng thực các hồ sơ này trong HSĐX. Trường hợp khi dự thầu chưa xác định được thầu phụ thì để trống cột này. Mẫu 12A BẢNG THÙ LAO CHO CHUYÊN GIA (*) [BẢNG: Không tiêu đề] Đại diện hợp pháp của nhà thầu [ghi tên, chức danh, ký tên và đóng dấu] Ghi chú: - (*): Mẫu này áp dụng cho các công việc thuộc Mục 2 Mẫu 04 Chương này. - (4): Nhà thầu điền theo Mẫu 12A trong trường hợp HSYC không yêu cầu phân tích thù lao cho chuyên gia. Trường hợp HSYC yêu cầu phân tích thù lao chuyên gia thì nhà thầu hoàn thành cả Mẫu 12B Chương này. Mẫu 12B BẢNG PHÂN TÍCH CHI PHÍ THÙ LAO CHO CHUYÊN GIA [BẢNG: Không tiêu đề] Đại diện hợp pháp của nhà thầu [ghi tên, chức danh, ký tên và đóng dấu] Ghi chú: Trường hợp không yêu cầu nhà thầu phân tích chi tiết chi phí thù lao chuyên gia thì không sử dụng Mẫu này. Mẫu 13 [BẢNG: Không tiêu đề] Mẫu 14 CHI PHÍ HẠNG MỤC CÔNG VIỆC DỰA TRÊN ĐƠN GIÁ VÀ KHỐI LƯỢNG [BẢNG: Không tiêu đề] Đại diện hợp pháp của nhà thầu [ghi tên, chức danh, ký tên và đóng dấu] Ghi chú: (2), (3), (4): chủ đầu tư điền (5), (6) Nhà thầu điền đơn giá, thành tiền đã bao gồm các chi phí cần thiết để thực hiện dịch vụ, kể cả thuế, phí, lệ phí. Mẫu 15 BẢNG TỔNG HỢP CHI PHÍ [BẢNG: Không tiêu đề] Đại diện hợp pháp của nhà thầu [ghi tên, chức danh, ký tên và đóng dấu] PHẦN 2. ĐIỀU KHOẢN THAM CHIẾU CHƯƠNG IV. ĐIỀU KHOẢN THAM CHIẾU Điều khoản tham chiếu bao gồm những nội dung chủ yếu sau: I. Giới thiệu Mô tả khái quát về dự án/dự toán mua sắm và gói thầu. Mô tả mục đích lựa chọn nhà thầu. II. Phạm vi công việc 1. Mô tả chi tiết phạm vi công việc đối với nhà thầu, nguồn vốn, tên cơ quan thực hiện dự án/dự toán mua sắm, thời gian, tiến độ thực hiện, số tháng - người hoặc ngày - người cần thiết (nếu có). 2. Mô tả các nhiệm vụ cụ thể do nhà thầu phải tiến hành trong thời gian thực hiện gói thầu tư vấn. Trong đó phải nêu rõ loại công việc dựa trên đơn giá và khối lượng, loại công việc tính theo lương chuyên gia. 3. Dự kiến thời gian chuyên gia bắt đầu thực hiện DVTV III. Báo cáo và thời gian thực hiện Các báo cáo phải nộp và tiến độ nộp báo cáo. IV. Kinh nghiệm và nhân sự của nhà thầu Yêu cầu về nhân sự cần thiết cho gói thầu và cho từng vị trí. V. Trách nhiệm của chủ đầu tư Dự kiến khả năng cung cấp điều kiện làm việc, cán bộ hỗ trợ của chủ đầu tư và những hồ sơ có liên quan đến nhiệm vụ của tư vấn, kể cả các hồ sơ nghiên cứu liên quan hiện có nhằm tạo điều kiện thuận lợi cho nhà thầu thực hiện nhiệm vụ của mình. Phần 3. ĐIỀU KIỆN HỢP ĐỒNG VÀ BIỂU MẪU HỢP ĐỒNG Căn cứ quy mô, tính chất, loại hợp đồng của gói thầu, chủ đầu tư, tổ chuyên gia sử dụng các Chương VI, VII, VIII của Mẫu E-HSMT dịch vụ tư vấn ban hành kèm theo Thông tư số 79/2025/TT-BTC để xây dựng các Chương V. ĐIỀU KIỆN CHUNG, Chương VI. ĐIỀU KIỆN CỤ THỂ, Chương VII. BIỂU MẪU HỢP ĐỒNG cho phù hợp với quy định của Luật Đấu thầu, Nghị định số 214/2025/NĐ-CP. Trong quá trình thực hiện, trường hợp Thông tư số 79/2025/TT-BTC được sửa đổi, bổ sung hoặc thay thế thì áp dụng theo văn bản quy phạm pháp luật sửa đổi, bổ sung hoặc thay thế Thông tư số 79/2025/TT-BTC. Lưu ý: khi sử dụng cần thay đổi các thuật ngữ cho phù hợp như sau: - E-ĐKC thành ĐKC; - E-ĐKCT thành ĐKCT; - E-HSMT thành HSYC; - E-HSDT thành HSĐX.", "type": "bill_of_quantities", "rows": []}], "parsing_metadata": {"bidding_type": null, "detected_sections": {"general_info": [], "technical_requirements": [], "evaluation_criteria": [], "contract_conditions": [], "bidding_process": [], "forms": [], "drawings": [], "bill_of_quantities": []}, "document_info": {"project_name": "/dự toán mua sắm]. 2. nguồn vốn để thực hiện gói thầu: ______[ghi rõ nguồn vốn đã được xác định hoặc", "package_name": "dịch vụ tư vấn (ban hành kèm theo thông tư số 80/2025/tt-btc ngày 08 tháng 8 năm 2025 của bộ trưởng", "owner": "___ [ghi tên, địa chỉ chủ đầu tư] mời nhà thầu nhận hsyc gói thầu ___ [ghi tên gói thầu theo kế hoạc"}, "statistics": {}}, "extraction_metadata": {"source_file": "01D. Mẫu HSYC Tư vấn.docx", "file_type": "bidding_document", "document_category": "consulting", "extracted_at": "2025-10-30T19:54:40.990688", "file_size_bytes": 120879, "project_name": "/dự toán mua sắm].", "package_name": "DỊCH VỤ TƯ VẤN", "bidding_method": "CHỈ ĐỊNH THẦU", "owner": "___ [Ghi tên, địa chỉ chủ đầu tư] mời nhà thầu nhận HSYC gói thầu ___ [Ghi tên gói thầu theo kế hoạch lựa chọn nhà thầu được duyệt] thuộc___ [Ghi tên dự án/dự toán mua sắm]."}}
