{"content": "Mẫu 1A HỒ SƠ YÊU CẦU GÓI THẦU XÂY LẮP (Ban hành kèm theo Thông tư số 80/2025/TT-BTC ngày 08 tháng 8 năm 2025 của Bộ trưởng Bộ Tài chính) HỒ SƠ YÊU CẦU XÂY LẮP [BẢNG: Không tiêu đề] [BẢNG: Không tiêu đề] TỪ NGỮ VIẾT TẮT [BẢNG: Không tiêu đề] Phần 1. THỦ TỤC CHỈ ĐỊNH THẦU Chương I. CHỈ DẪN NHÀ THẦU Mục 1. Phạm vi gói thầu 1. Chủ đầu tư ___ [Ghi tên, địa chỉ Chủ đầu tư] mời nhà thầu nhận HSYC gói thầu ___ [Ghi tên gói thầu theo kế hoạch lựa chọn nhà thầu được duyệt] thuộc ___ [Ghi tên dự án/dự toán mua sắm]. 2. Nguồn vốn để thực hiện gói thầu: ______ [Ghi rõ nguồn vốn đã được xác định hoặc phê duyệt; trường hợp sử dụng vốn ODA, vốn vay ưu đãi nước ngoài thì phải ghi rõ tên nhà tài trợ và cơ cấu nguồn vốn, bao gồm vốn tài trợ, vốn đối ứng trong nước]. 3. Thời gian thực hiện gói thầu là: ____[Ghi thời gian cụ thể theo kế hoạch lựa chọn nhà thầu được duyệt], được tính từ ngày hợp đồng có hiệu lực đến ngày nghiệm thu hoàn thành dự án, không bao gồm thời gian hoàn thành nghĩa vụ bảo hành. Mục 2. Hành vi bị cấm trong đấu thầu Hành vi bị cấm trong đấu thầu là hành vi quy định tại Điều 16 của Luật Đấu thầu. Mục 3. Tư cách hợp lệ của nhà thầu 1. Nhà thầu là tổ chức có tư cách hợp lệ khi đáp ứng quy định tại các điểm a, b, c, d, e, và g Khoản 1 Điều 5 của Luật Đấu thầu. 2. Nhà thầu là hộ kinh doanh có tư cách hợp lệ khi đáp ứng quy định tại các điểm a, b Khoản 2 và các điểm d, e Khoản 1 Điều 5 của Luật Đấu thầu. Trường hợp pháp luật có liên quan quy định nhà thầu dự thầu, thực hiện hợp đồng phải độc lập với các tổ chức, cá nhân khác thì phải tuân thủ quy định đó. 3. Đáp ứng điều kiện về cấp doanh nghiệp: ____ [đối với các gói thầu theo trường hợp gói thầu có giá không quá 05 tỷ đồng thì ghi: “Là doanh nghiệp cấp nhỏ hoặc siêu nhỏ theo quy định của pháp luật về doanh nghiệp”. Trường hợp gói thầu có giá trên 05 tỷ đồng hoặc không quá 05 tỷ đồng nhưng chủ đầu tư xác định không có doanh nghiệp nhỏ, siêu nhỏ đáp ứng được yêu cầu thì ghi: “Không áp dụng\"]. Mục 4. Làm rõ, sửa đổi HSYC, khảo sát hiện trường 1. Trường hợp nhà thầu cần làm rõ HSYC, nhà thầu gửi văn bản đến Chủ đầu tư trong thời hạn tối thiểu 03 ngày làm việc trước ngày có thời điểm đóng thầu để đánh giá, xử lý. 2. Trường hợp sửa đổi HSYC, Chủ đầu tư có trách nhiệm gửi quyết định sửa đổi và các nội dung sửa đổi tới nhà thầu. Thời gian gửi văn bản sửa đổi HSYC đến nhà thầu là ___ [Ghi số ngày cụ thể, tối thiểu 03 ngày làm việc trước ngày có thời điểm đóng thầu và bảo đảm đủ thời gian để nhà thầu hoàn chỉnh HSĐX]; trường hợp không bảo đảm đủ thời gian như nêu trên thì phải gia hạn thời điểm đóng thầu. 3. Nhà thầu nên đi khảo sát hiện trường dự án cũng như khu vực liên quan và tự chịu trách nhiệm tìm hiểu mọi thông tin cần thiết để lập HSĐX cũng như thực hiện hợp đồng thi công dự án nếu trúng thầu. Toàn bộ chi phí đi khảo sát hiện trường do nhà thầu tự chi trả. Mục 5. Chi phí, đồng tiền, ngôn ngữ khi dự thầu 1. Nhà thầu phải chịu mọi chi phí liên quan đến quá trình dự thầu. 2. Đồng tiền dự thầu và đồng tiền thanh toán là VND. 3. HSĐX cũng như tất cả văn bản và hồ sơ liên quan đến HSĐX được viết bằng tiếng Việt. Các hồ sơ bổ trợ trong HSĐX có thể được viết bằng ngôn ngữ khác, đồng thời kèm theo bản dịch sang tiếng Việt. Trường hợp thiếu bản dịch, Chủ đầu tư có thể yêu cầu nhà thầu gửi bổ sung (nếu cần thiết). Mục 6. Thành phần của HSĐX HSĐX do nhà thầu chuẩn bị phải bao gồm: 1. Đơn dự thầu theo Mẫu 01 Chương III; 2. Thỏa thuận liên danh nếu là nhà thầu liên danh theo Mẫu 03 Chương III; 3. hồ sơ chứng minh tư cách hợp lệ, năng lực và kinh nghiệm của nhà thầu, của người ký đơn dự thầu; 4. Đề xuất kỹ thuật theo quy định tại Mục 8 Chương này; 5. Đề xuất về giá theo Mẫu 04A hoặc Mẫu 04B hoặc Mẫu 04C hoặc Mẫu 04D hoặc Mẫu 04E Chương III; 6. Các nội dung khác __ [Nêu các nội dung khác tùy theo tính chất, yêu cầu của gói thầu]. Mục 7. giá thầu 1. giá thầu là giá do nhà thầu chào trong đơn dự thầu bao gồm toàn bộ các chi phí (chưa tính giảm giá) để thực hiện gói thầu theo yêu cầu của HSYC, kể cả các loại thuế, phí, lệ phí (nếu có) áp theo thuế suất, mức phí, lệ phí tại thời điểm 28 ngày trước ngày có thời điểm đóng thầu. 2. Nhà thầu phải nộp HSĐX cho toàn bộ công việc được mô tả tại Chương IV và chào giá cho tất cả các công việc nêu trong bảng giá tương ứng quy định tại Chương III. Mục 8. Thành phần đề xuất kỹ thuật Nhà thầu phải nộp đề xuất kỹ thuật, trong đó mô tả cụ thể phương pháp thực hiện công việc, thiết bị, nhân sự, lịch biểu thực hiện và các thông tin cần thiết khác theo quy định tại Chương IV để chứng minh tính phù hợp của đề xuất đối với các yêu cầu công việc và thời hạn cần hoàn thành công việc. Mục 9. Hiệu lực của HSĐX 1. Thời gian có hiệu lực của HSĐX phải bảo đảm theo yêu cầu là ___ [Ghi rõ số ngày tuỳ thuộc quy mô, tính chất của gói thầu, bảo đảm thời gian có hiệu lực đến ngày ký kết hợp đồng] kể từ ngày có thời điểm đóng thầu. 2. Trong trường hợp cần thiết, trước khi hết thời hạn hiệu lực của HSĐX, Chủ đầu tư có thể đề nghị nhà thầu gia hạn hiệu lực của HSĐX. Việc đề nghị gia hạn và chấp thuận gia hạn phải được thể hiện bằng văn bản. Mục 10. Quy cách của HSĐX và chữ ký trong HSĐX 1. Nhà thầu phải chuẩn bị một bản gốc và ____bản chụp HSĐX [Ghi số lượng yêu cầu nhưng không quá 03 bản], ghi rõ\"bản gốc\"và\"bản chụp\" tương ứng. Nhà thầu cần ghi rõ tên gói thầu, tên nhà thầu, tên Chủ đầu tư bên ngoài túi đựng HSĐX. Nhà thầu phải chịu trách nhiệm về tính chính xác và phù hợp giữa bản chụp và bản gốc. Trường hợp có sự sai khác giữa bản gốc và bản chụp thì căn cứ vào bản gốc để đánh giá. 2. Tất cả các thành phần của HSĐX nêu tại Mục 6 Chương I phải được ký bởi người đại diện hợp pháp của nhà thầu. Trường hợp là nhà thầu liên danh thì HSĐX phải có chữ ký của đại diện hợp pháp của tất cả thành viên liên danh hoặc thành viên đại diện nhà thầu liên danh theo phân công trong thỏa thuận liên danh. 3. Những chữ được ghi thêm, ghi chèn vào giữa các dòng, những chữ bị tẩy xóa hoặc viết đè lên sẽ chỉ được coi là hợp lệ nếu có chữ ký ở bên cạnh hoặc tại trang đó của người ký đơn dự thầu. Mục 11. Thời điểm đóng thầu và mở thầu 1. HSĐX do nhà thầu nộp trực tiếp hoặc gửi đến địa chỉ của Chủ đầu tư [Ghi địa chỉ] nhưng phải bảo đảm Chủ đầu tư nhận được trước thời điểm đóng thầu: ___ giờ, ngày ___ tháng ___ năm ____ [Ghi thời điểm đóng thầu]. 2. Mở thầu Chủ đầu tư tiến hành mở thầu bao gồm các nội dung sau: a) Kiểm tra niêm phong; b) Thông tin về tên nhà thầu: - Tham dự độc lập hay liên danh; - Số lượng bản gốc, bản chụp; - giá thầu chào trong đơn dự thầu; - Giá trị giảm giá (nếu có); - Thời gian có hiệu lực của HSĐX; - Thời gian thực hiện gói thầu; - Các thông tin khác liên quan. Biên bản mở thầu bao gồm các thông tin quy định tại điểm a và điểm b khoản này. Biên bản mở thầu phải được ký xác nhận bởi đại diện của Chủ đầu tư và nhà thầu nộp HSĐX. Biên bản này phải được gửi cho nhà thầu nộp HSĐX. Đại diện của Chủ đầu tư phải ký xác nhận vào bản gốc đơn dự thầu, thư giảm giá (nếu có), giấy ủy quyền của người đại diện theo pháp luật của nhà thầu (nếu có), thỏa thuận liên danh (nếu có), các nội dung đề xuất về tài chính và các nội dung quan trọng khác của HSĐX. Mục 12. thầu phụ 1. thầu phụ là tổ chức, cá nhân ký hợp đồng với nhà thầu để thực hiện một phần công việc trong bảng giá thầu; không bao gồm tổ chức, cá nhân cung cấp, nguyên liệu, nhiên liệu, vật liệu, vật tư, cấu kiện bán thành phẩm, thiết bị, cho thuê thiết bị thi công. Việc nhà thầu thuê nhân công để thực hiện gói thầu không phải là sử dụng thầu phụ. Trừ các phần công việc của gói thầu không được sử dụng thầu phụ bao gồm: ____ [Ghi “Không có” trong trường hợp không có quy định. Trường hợp có quy định thì ghi các phần công việc của gói thầu không cho phép sử dụng thầu phụ], nhà thầu được kê khai thầu phụ và các hạng mục công việc dành cho thầu phụ theo Mẫu 10A Chương III. Trường hợp tại thời điểm dự thầu, chưa xác định được thầu phụ thì phải kê khai các hạng mục công việc dự kiến dành cho thầu phụ. Việc sử dụng thầu phụ sẽ không làm thay đổi các trách nhiệm của nhà thầu. Nhà thầu phải chịu trách nhiệm về khối lượng, chất lượng, tiến độ và các trách nhiệm khác đối với phần công việc do thầu phụ thực hiện. Năng lực và kinh nghiệm của thầu phụ sẽ không được đánh giá khi đánh giá HSĐX của nhà thầu, trừ trường hợp quy định tại Mục 12. 3 Chương này. Bản thân nhà thầu phải đáp ứng các tiêu chí năng lực và kinh nghiệm (không xét đến năng lực và kinh nghiệm của thầu phụ). Nhà thầu được ký kết hợp đồng với các thầu phụ trong danh sách các thầu phụ nêu trong HSĐX hoặc ký với thầu phụ được Chủ đầu tư chấp thuận để tham gia thực hiện công việc xây lắp. 2. Nhà thầu chỉ được sử dụng thầu phụ thực hiện các công việc với tổng giá trị dành cho thầu phụ không vượt quá ___ tỷ lệ phần trăm (%) trên giá thầu của nhà thầu [tùy theo quy mô, tính chất gói thầu, Chủ đầu tư ghi tỷ lệ % tối đa dành cho thầu phụ]. Đối với trường hợp liên danh, từng thành viên liên danh chỉ được sử dụng thầu phụ không vượt quá tỷ lệ phần trăm quy định tại Mục này trên giá trị phần công việc mà thành viên liên danh đó đảm nhận trong thoả thuận liên danh. 3. thầu phụ đặc biệt ___ [Ghi được phép sử dụng hoặc không được phép sử dụng]. Trong trường hợp được phép sử dụng thầu phụ đặc biệt, nhà thầu phải kê khai danh sách thầu phụ đặc biệt theo Mẫu 10B Chương III và kê khai về năng lực, kinh nghiệm của thầu phụ đặc biệt. Tổ chuyên gia sẽ đánh giá năng lực, kinh nghiệm của thầu phụ đặc biệt theo tiêu chuẩn đánh giá quy định tại Mục 2. 3 Chương II. Trường hợp thầu phụ đặc biệt do nhà thầu đề xuất trong HSĐX không đáp ứng yêu cầu của HSYC (hoặc không đề xuất thầu phụ đặc biệt) và nhà thầu có năng lực, kinh nghiệm không đáp ứng yêu cầu thực hiện phần công việc đã dành cho thầu phụ đặc biệt thì nhà thầu được phép đề xuất thầu phụ đặc biệt hoặc thay thế thầu phụ đặc biệt khác đáp ứng yêu cầu. Khi sử dụng thầu phụ đặc biệt, nhà thầu không bắt buộc phải đáp ứng yêu cầu về năng lực, kinh nghiệm đối với phần công việc giao cho thầu phụ đặc biệt. Mục 13. Đánh giá HSĐX và thương thảo về các đề xuất của nhà thầu 1. Việc đánh giá HSĐX được thực hiện theo quy định tại Chương II. 2. Trong quá trình đánh giá, Chủ đầu tư mời nhà thầu thương thảo về giá bảo đảm đáp ứng tỷ lệ tiết kiệm theo quy định của HSYC, thương thảo, làm rõ hoặc sửa đổi, bổ sung nội dung HSĐX để chứng minh việc đáp ứng yêu cầu về năng lực, kinh nghiệm, tiến độ, khối lượng, chất lượng, giải pháp kỹ thuật, biện pháp tổ chức thực hiện gói thầu và tỷ lệ tiết kiệm. Mục 14. Điều kiện đối với nhà thầu được đề nghị chỉ định thầu Nhà thầu được đề nghị chỉ định thầu khi đáp ứng đầy đủ điều kiện sau đây: 1. Có HSĐX hợp lệ; 2. Có năng lực, kinh nghiệm và đề xuất kỹ thuật đáp ứng yêu cầu của HSYC; 3. Có giá đề nghị trúng thầu không vượt giá gói thầu được duyệt và đáp ứng tỷ lệ tiết kiệm tối thiểu ___ % giá gói thầu. [Căn cứ quy mô, tính chất, điều kiện cụ thể của gói thầu, Chủ đầu tư quy định trong HSYC mức tỷ lệ tiết kiệm của giá đề nghị trúng thầu để làm cơ sở cho nhà thầu chuẩn bị HSĐX]. Mục 15. Thông báo kết quả lựa chọn nhà thầu Trong thời hạn 05 ngày làm việc kể từ ngày kết quả lựa chọn nhà thầu được phê duyệt, Chủ đầu tư đăng tải thông tin về kết quả lựa chọn nhà thầu lên Hệ thống mạng đấu thầu quốc gia; gửi văn bản thông báo kết quả lựa chọn nhà thầu cho nhà thầu dự thầu. Nội dung thông báo kết quả lựa chọn nhà thầu như sau: a) Thông tin về gói thầu: - Tên gói thầu; - Giá gói thầu hoặc dự toán được duyệt (nếu có); - Tên Chủ đầu tư; - Hình thức lựa chọn nhà thầu; - Loại hợp đồng. - Thời gian thực hiện gói thầu. b) Thông tin về nhà thầu trúng thầu: - Tên nhà thầu; - Mã số thuế (nếu có); - giá thầu; - Giá trúng thầu; - Thời gian thực hiện gói thầu; - Thời gian thực hiện hợp đồng. c) Kế hoạch hoàn thiện, ký kết hợp đồng với nhà thầu trúng thầu. Mục 16. Điều kiện ký kết hợp đồng 1. Tại thời điểm ký kết, HSĐX của nhà thầu trúng thầu còn hiệu lực. 2. Tại thời điểm ký kết hợp đồng, nhà thầu trúng thầu phải bảo đảm đáp ứng yêu cầu về năng lực kỹ thuật, tài chính để thực hiện gói thầu theo yêu cầu của HSYC. Trường hợp thực tế nhà thầu không còn đáp ứng cơ bản yêu cầu về năng lực kỹ thuật, tài chính theo quy định nêu trong HSYC thì Chủ đầu tư sẽ từ chối ký kết hợp đồng với nhà thầu và hủy quyết định phê duyệt kết quả lựa chọn nhà thầu. 3. Chủ đầu tư phải bảo đảm các điều kiện về vốn tạm ứng, vốn thanh toán, mặt bằng thực hiện và điều kiện cần thiết khác để triển khai thực hiện gói thầu theo đúng tiến độ. Mục 17. Bảo đảm thực hiện hợp đồng 1. Trước hoặc cùng thời điểm hợp đồng có hiệu lực, nhà thầu được chỉ định thầu phải cung cấp bảo đảm thực hiện hợp đồng theo quy định của HSYC. Trường hợp nhà thầu sử dụng thư bảo lãnh thực hiện hợp đồng thì phải sử dụng Mẫu thư bảo lãnh trong HSYC này hoặc Mẫu thư bảo lãnh khác được Chủ đầu tư chấp thuận. 2. Nhà thầu không được hoàn trả bảo đảm thực hiện hợp đồng trong trường hợp sau đây: a) Từ chối thực hiện hợp đồng khi hợp đồng đã có hiệu lực; b) Vi phạm thỏa thuận trong hợp đồng; c) Thực hiện hợp đồng chậm tiến độ do lỗi của nhà thầu nhưng từ chối gia hạn hiệu lực của bảo đảm thực hiện hợp đồng. Mục 18. Giải quyết kiến nghị 1. Đối với gói thầu thuộc phạm vi điều chỉnh của Luật Đấu thầu: a) Khi thấy quyền và lợi ích hợp pháp bị ảnh hưởng, nhà thầu được kiến nghị người có thẩm quyền, Chủ đầu tư, Hội đồng giải quyết kiến nghị đánh giá lại các vấn đề trong quá trình lựa chọn nhà thầu, kết quả lựa chọn nhà thầu theo quy định tại Điều 89 Luật Đấu thầu và các Điều 137, 138 và 139 của Nghị định số 214/2025/NĐ-CP. b) Địa chỉ nhận đơn kiến nghị: - Địa chỉ nhận đơn kiến nghị của Chủ đầu tư: ___ [ghi đầy đủ tên, địa chỉ, số điện thoại, email]; - Địa chỉ nhận đơn kiến nghị của người có thẩm quyền: ___ [ghi đầy đủ tên, địa chỉ, số điện thoại, email]; - Địa chỉ bộ phận thường trực giúp việc của Hội đồng giải quyết kiến nghị: ___ [ghi đầy đủ tên, địa chỉ, số điện thoại, email]. 2. Đối với hoạt động lựa chọn nhà thầu quy định tại điểm d Khoản 7 Điều 3 của Luật Đấu thầu hoặc hoạt động lựa chọn nhà thầu không thuộc phạm vi điều chỉnh của Luật Đấu thầu: Khi thấy quyền và lợi ích hợp pháp bị ảnh hưởng, nhà thầu, cơ quan, tổ chức được kiến nghị theo quy trình sau: ___ [ghi cụ thể quy trình, thủ tục của việc giải quyết kiến nghị của đơn vị, tổ chức đồng thời ghi rõ email, địa chỉ của cá nhân/tổ chức/đơn vị giải quyết kiến nghị]. Mục 19. Ưu đãi trong lựa chọn nhà thầu Ưu đãi: _____ [Chủ đầu tư ghi rõ đối tượng, điều kiện ưu đãi theo quy định tại Nghị quyết của Quốc hội hoặc văn bản quy phạm pháp luật (nếu có)]. Chương II. TIÊU CHUẨN ĐÁNH GIÁ HSĐX Mục 1. Đánh giá tính hợp lệ của HSĐX 1. 1. Kiểm tra HSĐX a) Kiểm tra số lượng bản gốc, bản chụp HSĐX; b) Kiểm tra các thành phần của HSĐX theo quy định tại Mục 6 Chương I; c) Kiểm tra sự thống nhất nội dung giữa bản gốc và bản chụp để phục vụ quá trình đánh giá chi tiết HSĐX. 1. 2. Đánh giá tính hợp lệ của HSĐX HSĐX của nhà thầu được đánh giá là hợp lệ khi đáp ứng đầy đủ các nội dung sau đây: a) Có bản gốc HSĐX; b) Có đơn dự thầu được đại diện hợp pháp của nhà thầu ký tên, đóng dấu (nếu có) theo yêu cầu của HSYC; thời gian ký đơn dự thầu phải sau thời điểm phát hành HSYC; không đề xuất các giá thầu khác nhau hoặc có kèm theo điều kiện gây bất lợi cho Chủ đầu tư. Đối với nhà thầu liên danh, đơn dự thầu phải do đại diện hợp pháp của từng thành viên liên danh ký tên, đóng dấu (nếu có) hoặc thành viên được phân công thay mặt liên danh ký đơn dự thầu theo phân công trách nhiệm trong thỏa thuận liên danh; c) Hiệu lực của HSĐX đáp ứng yêu cầu theo quy định tại Mục 9 Chương I; d) Có thỏa thuận liên danh (trong trường hợp liên danh) được đại diện hợp pháp của từng thành viên liên danh ký tên, đóng dấu (nếu có); thỏa thuận liên danh phải nêu rõ nội dung công việc cụ thể và ước tính giá trị tương ứng mà từng thành viên trong liên danh sẽ thực hiện. Việc phân chia công việc trong liên danh phải căn cứ các hạng mục nêu trong bảng giá thầu quy định tại Mẫu 04 (04A hoặc 04B hoặc 04C hoặc 04D hoặc 04E) Chương III hoặc theo các công việc thuộc quá trình sản xuất hạng mục trong bảng giá thầu; không được phân chia các công việc không thuộc các hạng mục này hoặc không thuộc quá trình sản xuất các hạng mục này; đ) Nhà thầu bảo đảm tư cách hợp lệ theo quy định tại Mục 3 Chương I; e) Trong thời hạn 03 năm trước thời điểm đóng thầu, nhà thầu không có nhân sự (ký kết hợp đồng lao động với nhà thầu tại thời điểm nhân sự thực hiện hành vi vi phạm) bị Tòa án kết án có hành vi vi phạm quy định về đấu thầu gây hậu quả nghiêm trọng theo quy định của pháp luật về hình sự nhằm mục đích cho nhà thầu đó trúng thầu. Nhà thầu có HSĐX hợp lệ được đánh giá, đánh giá trong bước tiếp theo. Mục 2. Tiêu chuẩn đánh giá về năng lực và kinh nghiệm Nhà thầu được đánh giá là đạt về năng lực và kinh nghiệm khi đáp ứng tiêu chuẩn đánh giá quy định tại Mục 2. 1, 2. 2 và 2. 3. Năng lực và kinh nghiệm của thầu phụ (trừ thầu phụ đặc biệt) sẽ không được đánh giá khi đánh giá HSĐX của nhà thầu. Bản thân nhà thầu phải đáp ứng các tiêu chí đánh giá về năng lực và kinh nghiệm. 2. 1. Tiêu chuẩn đánh giá về năng lực và kinh nghiệm Tiêu chuẩn đánh giá năng lực và kinh nghiệm thực hiện theo Bảng số 01 Chương này, nhà thầu được đánh giá là đạt về năng lực và kinh nghiệm khi đáp ứng tất cả các tiêu chuẩn đánh giá. Trường hợp đồng tiền nêu trong các hợp đồng tương tự hoặc xác nhận thanh toán của Chủ đầu tư đối với những hợp đồng xây lắp đã thực hiện hoặc tờ khai nộp thuế hoặc các hồ sơ liên quan chứng minh năng lực, kinh nghiệm của nhà thầu không phải VND thì khi lập HSĐX, nhà thầu phải quy đổi về VND để làm cơ sở đánh giá HSĐX. Việc quy đổi được áp dụng tỷ giá quy đổi của ____ [ghi căn cứ xác định tỷ giá quy đổi, thông thường áp dụng tỷ giá bán ra của một ngân hàng thương mại hoạt động tại Việt Nam] tại ngày ký hợp đồng tương tự đó. Trường hợp nhà thầu dự thầu là công ty mẹ (ví dụ như Tổng công ty) có huy động công ty con, công ty thành viên thực hiện một phần công việc của gói thầu thì nhà thầu phải kê khai cụ thể phần công việc dành cho các công ty con, công ty thành viên theo Mẫu 10C Chương III. Việc đánh giá kinh nghiệm thực hiện hợp đồng tương tự căn cứ vào giá trị, khối lượng công việc do công ty mẹ, công ty con, công ty thành viên đảm nhiệm trong gói thầu. Bảng số 01 [BẢNG: BẢNG TIÊU CHUẨN ĐÁNH GIÁ VỀ NĂNG LỰC VÀ KINH NGHIỆM] Ghi chú: (1) Ghi thời gian yêu cầu, thông thường là 03 trước năm có thời điểm đóng thầu. Ví dụ: từ ngày 01 tháng 01 năm 2022 đến thời điểm đóng thầu. (2) Hợp đồng xây lắp, EPC, EC, PC, chìa khóa trao tay không hoàn thành do lỗi của nhà thầu bao gồm: - Hợp đồng bị Chủ đầu tư kết luận nhà thầu không hoàn thành và nhà thầu không phản đối; - Hợp đồng bị Chủ đầu tư kết luận nhà thầu không hoàn thành, không được nhà thầu chấp thuận nhưng đã được trọng tài hoặc tòa án kết luận theo hướng bất lợi cho nhà thầu. Các hợp đồng không hoàn thành không bao gồm các hợp đồng mà quyết định của Chủ đầu tư đã bị bác bỏ bằng cơ chế giải quyết tranh chấp. Việc xác định hợp đồng không hoàn thành phải dựa trên tất cả những thông tin về tranh chấp hoặc kiện tụng được giải quyết theo quy định của cơ chế giải quyết tranh chấp của hợp đồng tương ứng và khi mà nhà thầu đã hết tất cả các cơ hội có thể khiếu nại. Đối với các hợp đồng chậm tiến độ do lỗi của nhà thầu nhưng vẫn hoàn thành hợp đồng thì không được coi là hợp đồng không hoàn thành. Đối với nhà thầu liên danh mà chỉ có một hoặc một số thành viên trong liên danh vi phạm và bị cấm tham gia hoạt động đấu thầu theo quy định tại Khoản 1 Điều 133 của Nghị định số 214/2025/NĐ-CP thì thành viên liên danh còn lại không bị coi là không hoàn thành hợp đồng do lỗi của nhà thầu. Trường hợp một hoặc một số thành viên liên danh vi phạm hợp đồng, không còn năng lực để tiếp tục thực hiện hợp đồng, làm ảnh hưởng nghiêm trọng đến tiến độ, chất lượng, hiệu quả của gói thầu thì chỉ một hoặc một số thành viên liên danh vi phạm hợp đồng bị coi là không hoàn thành hợp đồng, thành viên còn lại không bị coi là không hoàn thành hợp đồng do lỗi của nhà thầu. (3) Nhà thầu cung cấp hồ sơ chứng minh đã thực hiện nghĩa vụ kê khai thuế và nộp thuế thu nhập doanh nghiệp (thuế thu nhập cá nhân đối với nhà thầu là hộ kinh doanh) của năm tài chính gần nhất so với thời điểm đóng thầu. Nghĩa vụ kê khai thuế và nộp thuế phải được thực hiện trước thời điểm đóng thầu. Nghĩa vụ nộp thuế là nộp thuế với giá trị thuế tương ứng với thuế suất, thu nhập chịu thuế, doanh thu tính thuế nhà thầu kê khai trên Hệ thống thuế điện tử (số thuế đã nộp tương ứng với số thuế phải nộp); trường hợp được chậm nộp thuế, miễn thuế, giảm thuế theo chính sách của Nhà nước thì thực hiện theo quy định này. Nhà thầu nộp các hồ sơ như sau: - Tờ khai thuế (hoặc thông báo nộp tiền của cơ quan thuế đối với hộ kinh doanh) và Giấy nộp tiền có xác nhận của cơ quan thuế được in từ Hệ thống thuế điện tử hoặc - Tờ khai thuế (hoặc thông báo nộp tiền của cơ quan thuế đối với hộ kinh doanh) và xác nhận của cơ quan thuế về việc thực hiện nghĩa vụ thuế. Trường hợp thời điểm đóng thầu sau ngày kết thúc năm tài chính của nhà thầu (năm Y) và trước hoặc trong ngày cuối cùng của tháng thứ 3 tính từ ngày kết thúc năm Y, yêu cầu đã thực hiện nghĩa vụ kê khai thuế và nộp thuế áp dụng đối với năm tài chính trước năm Y (năm Y-1). (Ví dụ: Thời điểm đóng thầu là ngày 20/3/2024, năm tài chính của nhà thầu là 01/01 - 31/12 thì nhà thầu phải chứng minh đã thực hiện nghĩa vụ kê khai thuế và nộp thuế của năm 2022). (4) Việc xác định giá trị tài sản ròng được thực hiện trên cơ sở báo cáo tài chính của nhà thầu. Trường hợp thời điểm đóng thầu sau ngày kết thúc năm tài chính của nhà thầu (năm Y) và trước hoặc trong ngày cuối cùng của tháng thứ 3 tính từ ngày kết thúc năm Y, việc xác định giá trị tài sản ròng của nhà thầu được thực hiện trên cơ sở báo cáo tài chính năm trước của năm Y (năm Y-1). Ví dụ: Ngày có thời điểm đóng thầu là ngày 20/3/2024, năm tài chính của nhà thầu là 01/01 - 31/12 và HSYC yêu cầu nhà thầu nộp báo cáo tài chính của 03 năm gần nhất thì việc xác định giá trị tài sản ròng của nhà thầu được thực hiện trên cơ sở bảo cáo tài chính năm 2022. Đối với nhà thầu là hộ kinh doanh thì không đánh giá tiêu chí này. (5) Ghi thời gian yêu cầu, thông thường từ 03 năm đến 05 năm trước năm có thời điểm đóng thầu. Trường hợp nhà thầu có số năm thành lập ít hơn số năm theo yêu cầu của HSYC thì doanh thu bình quân hằng năm (không bao gồm thuế VAT) được tính trên số năm mà nhà thầu thành lập. Trường hợp doanh thu bình quân hằng năm (không bao gồm thuế VAT) của nhà thầu đáp ứng yêu cầu về giá trị của HSYC thì nhà thầu vẫn được đánh giá tiếp mà không bị loại. Đối với nhà thầu là hộ kinh doanh, không bắt buộc phải nộp báo cáo tài chính nhưng nhà thầu phải cung cấp hồ sơ chứng minh doanh thu tương ứng với nghĩa vụ thuế. Trường hợp thời điểm đóng thầu sau ngày kết thúc năm tài chính của nhà thầu (năm Y) và trước hoặc trong ngày cuối cùng của tháng thứ 3 tính từ ngày kết thúc năm Y, yêu cầu về nộp báo cáo tài chính áp dụng đối với các năm trước của năm Y (năm Y-1, Y-2. ..). Ví dụ: - Ngày có thời điểm đóng thầu là ngày 20/3/2024, năm tài chính của nhà thầu là 01/01 - 31/12 và HSYC yêu cầu nhà thầu nộp báo cáo tài chính của 03 năm gần nhất thì nhà thầu phải nộp báo cáo tài chính của các năm 2020, 2021, 2022). - Doanh thu bình quân hằng năm (không bao gồm thuế VAT) của 03 năm tài chính gần nhất so với thời điểm đóng thầu. Trong trường hợp này, thời điểm đóng thầu là ngày 15/11/2024 thì nhà thầu phải nộp báo cáo tài chính của các năm 2021, 2022, 2023. Nhà thầu được thành lập vào năm 2022 nhưng doanh thu trung bình của năm 2022 và năm 2023 đáp ứng yêu cầu thì nhà thầu được tiếp tục đánh giá. (6) Cách tính toán thông thường về mức yêu cầu doanh thu bình quân hằng năm (không bao gồm thuế VAT): a) Trường hợp thời gian thực hiện gói thầu từ 12 tháng trở lên thì cách tính doanh thu như sau: Yêu cầu tối thiểu về mức doanh thu bình quân hằng năm (không bao gồm thuế VAT) = [(Giá gói thầu - giá trị thuế VAT)/thời gian thực hiện gói thầu theo năm] x k. Thông thường yêu cầu hệ số k trong công thức này là từ 1, 5 đến 2; b) Trường hợp thời gian thực hiện gói thầu dưới 12 tháng thì cách tính doanh thu như sau: Yêu cầu tối thiểu về mức doanh thu bình quân hằng năm (không bao gồm thuế VAT) = (Giá gói thầu - giá trị thuế VAT) x k. Thông thường yêu cầu hệ số “k” trong công thức này là 1, 5. (7) Tài sản có khả năng thanh khoản cao là tiền mặt và tương đương tiền mặt, các công cụ tài chính ngắn hạn, các chứng khoán sẵn sàng để bán, chứng khoán dễ bán, các khoản phải thu thương mại, các khoản phải thu tài chính ngắn hạn và các tài sản khác mà có thể chuyển đổi thành tiền mặt trong vòng một năm. Trường hợp HSYC có yêu cầu về cam kết cung cấp tín dụng và nhà thầu sử dụng cam kết này để chứng minh nguồn lực tài chính thì nhà thầu phải đính kèm cam kết cung cấp tín dụng trong HSĐX. (8) Yêu cầu về nguồn lực tài chính cho gói thầu: a) Đối với gói thầu có thời gian thực hiện gói thầu từ 12 tháng trở lên, yêu cầu về nguồn lực tài chính cho gói thầu được xác định theo công thức sau: Yêu cầu về nguồn lực tài chính cho gói thầu = t x (Giá gói thầu/thời gian thực hiện gói thầu (tính theo tháng)). Thông thường yêu cầu hệ số “t” trong công thức này là 3. b) Đối với gói thầu có thời gian thực hiện gói thầu dưới 12 tháng, yêu cầu về nguồn lực tài chính cho gói thầu được xác định theo công thức sau: Yêu cầu về nguồn lực tài chính cho gói thầu = 30% x Giá gói thầu. (9) Trường hợp gói thầu gồm dự án và hạng mục theo quy định của pháp luật về xây dựng thì chỉ nêu yêu cầu về hợp đồng tương tự đối với dự án. Đối với các hợp đồng tương tự mà nhà thầu đã tham gia với tư cách là thành viên liên danh hoặc thầu phụ thì chỉ tính giá trị phần việc do nhà thầu thực hiện. Đối với các hợp đồng mà Chủ đầu tư, tổ chuyên gia có bằng chứng cho thấy nhà thầu đã thực hiện với tư cách thầu phụ do được chuyển nhượng thầu bất hợp pháp, vi phạm quy định tại Khoản 8 Điều 16 của Luật Đấu thầu thì hợp đồng này sẽ không được đánh giá, đánh giá. (10) Ghi năm yêu cầu, thông thường từ 03 năm đến 05 năm trước năm có thời điểm đóng thầu. (11) Hoàn thành toàn bộ nghĩa là đã thực hiện xong toàn bộ công việc của dự án/hạng mục và được nghiệm thu; hoàn thành phần lớn nghĩa là đã hoàn thành và được nghiệm thu ít nhất 80% khối lượng công việc của dự án/hạng mục dự án. Thời điểm xác nhận dự án/hạng mục hoàn thành để xác định dự án/hạng mục tương tự là thời điểm nghiệm thu dự án/hạng mục, không căn cứ vào thời điểm ký kết hợp đồng. (12) Ghi loại kết cấu, cấp dự án của dự án thuộc gói thầu. Loại kết cấu, cấp dự án được xác định theo Phụ lục II Thông tư số 06/2021/TT-BXD ngày 30 tháng 6 năm 2021 của Bộ Xây dựng quy định về phân cấp dự án xây dựng và hướng dẫn áp dụng trong quản lý hoạt động đầu tư xây dựng. Trường hợp dự án/loại kết cấu dự án thuộc gói thầu không có trong Phụ lục II Thông tư số 06/2021/TT-BXD thì HSYC phải đưa ra quy định tính tương tự về bản chất của dự án; riêng đối với cấp dự án được xác định theo Phụ lục I Thông tư số 06/2021/TT-BXD. Trường hợp Thông tư số 06/2021/TT-BXD được sửa đổi, bổ sung, thay thế thì việc xác định loại, cấp dự án thực hiện theo quy định tại Thông tư sửa đổi, bổ sung, thay thế Thông tư số 06/2021/TT-BXD. Loại kết cấu, cấp dự án của nhà thầu thực hiện được xác định theo quy định của pháp luật xây dựng tại thời điểm phê duyệt dự án đầu tư xây dựng dự án. Chủ đầu tư, tổ chuyên gia không được đưa ra yêu cầu về hợp đồng tương tự đối với hạng mục trong trường hợp gói thầu chỉ gồm dự án hoặc cả dự án và hạng mục theo quy định của pháp luật về xây dựng (Ví dụ: yêu cầu hợp đồng tương tự đối với dự án giao thông cấp IV nhưng phải bao gồm hạng mục nền đắp đất, cấp phối đá dăm, mặt bê tông nhựa hoặc bê tông, rãnh thoát nước dọc, ngang, mái kè gia cố. ..). (13) Ghi giá trị của V, V1, V2, V3. Trong đó: - V có giá trị thông thường khoảng 50% giá trị công việc xây lắp của dự án thuộc gói thầu đang xét (dự án A). Đối với các công việc đặc thù hoặc ở các địa phương mà năng lực của nhà thầu trên địa bàn còn hạn chế, có thể yêu cầu giá trị V trong khoảng 40% - 50% giá trị công việc xây lắp của dự án A. - V1, V2, V3. .. có giá trị thông thường khoảng 50% giá trị của từng dự án/hạng mục tương ứng (A1, A2, A3. ..) thuộc gói thầu đang xét (bao gồm thuế, phí, lệ phí và chi phí dự phòng nếu có). Đối với các công việc đặc thù hoặc ở các địa phương mà năng lực của nhà thầu trên địa bàn còn hạn chế, có thể yêu cầu giá trị V1, V2, V3. .. trong khoảng 40% - 50% giá trị của dự án/hạng mục A1, A2, A3. .. - Việc đánh giá về giá trị của các dự án/hạng mục mà nhà thầu đã thực hiện, Tổ chuyên gia căn cứ vào giá trị hoàn thành, được nghiệm thu của dự án/hạng mục đó. Thời điểm xác nhận dự án/hạng mục hoàn thành để xác định dự án/hạng mục tương tự là thời điểm nghiệm thu dự án/hạng mục, không căn cứ vào thời điểm ký kết hợp đồng. Hai dự án có cấp thấp hơn liền kề với cấp của dự án đang xét, giá trị hoàn thành mỗi dự án cấp thấp hơn liền kề bằng hoặc lớn hơn 50% giá trị của dự án đang xét thì được đánh giá là một dự án xây lắp tương tự. Ví dụ: Trường hợp dự án đang xét là dự án xây dựng có loại kết cấu dạng nhà cấp II với giá trị dự án là 60 tỷ đồng, nếu nhà thầu có 02 dự án xây dựng có loại kết cấu dạng nhà cấp III với giá trị đã hoàn thành toàn bộ hoặc hoàn thành phần lớn lần lượt là 30 tỷ đồng, 50 tỷ đồng thì được đánh giá là đã hoàn thành hoặc hoàn thành phần lớn một dự án dân dụng cấp II với giá trị 30 tỷ đồng. - Các dự án/hạng mục tương tự mà nhà thầu đã hoàn thành có thể thuộc một hoặc nhiều hợp đồng (hợp đồng có thể đang thực hiện, chưa thanh lý). - Đối với gói thầu gồm tổ hợp nhiều dự án theo pháp luật về xây dựng, Chủ đầu tư có thể yêu cầu phải hoàn thành dự án/hạng mục tương tự cho tất cả các dự án/hạng mục trong gói thầu hoặc chỉ yêu cầu hoàn thành dự án/hạng mục tương tự đối với một số dự án/hạng mục chính, trường hợp có một số dự án có cùng loại kết cấu thì chỉ yêu cầu về dự án/hạng mục tương tự đối với cùng loại kết cấu mà có cấp dự án cao nhất (trường hợp có nhiều dự án cùng loại kết cấu và cấp dự án thì giá trị hợp đồng tương tự được tính theo dự án có giá trị cao nhất). dự án/hạng mục mà nhà thầu đã hoàn thành có cùng loại kết cấu và có cấp dự án cao hơn cấp dự án của gói thầu đang xét thì được coi là đáp ứng yêu cầu về loại kết cấu và cấp dự án. Loại kết cấu, cấp dự án của dự án tương tự được xác định theo quy định của pháp luật xây dựng tại thời điểm phê duyệt dự án đầu tư xây dựng dự án. Ví dụ: Đối với gói thầu xây dựng “Trường trung học phổ thông A”, bao gồm tổ hợp các dự án: + Nhà A1 (Nhà học): Cao 10 tầng, tổng diện tích sàn 8. 000 m2, có giá trị theo dự toán được duyệt là (2X) VND. Nhà A1 là dự án kết cấu dạng nhà cấp II theo quy định của Thông tư số 06/2021/TT-BXD. + Nhà A2 (Nhà học): Cao 10 tầng, tổng diện tích sàn 5. 000 m2, có giá trị theo dự toán được duyệt là (X) VND. Nhà A2 là dự án kết cấu dạng nhà cấp II theo quy định của Thông tư số 06/2021/TT-BXD. + Nhà A3 (Nhà học): Cao 6 tầng, tổng diện tích sàn 1. 000 m2, có giá trị theo dự toán được duyệt là (Y) VND. Nhà A3 là dự án kết cấu dạng nhà cấp III theo quy định của Thông tư số 06/2021/TT-BXD. + Hàng rào bảo vệ: Cao 3 m + Nhà bảo vệ: Cao 1 tầng, diện tích sàn 12 m2 Trong HSYC có thể quy định kinh nghiệm thi công dự án tương tự là: “nhà thầu đã hoàn thành dự án xây dựng nhà, kết cấu dạng nhà cấp II, có giá trị tối thiểu là 50% x (2X) VND” mà không phải quy định nhà thầu phải có kinh nghiệm thực hiện cả các dự án xây dựng nhà A2, A3, hàng rào bảo vệ, nhà bảo vệ. Căn cứ quy mô, tính chất của gói thầu mà có thể yêu cầu tương tự về điều kiện hiện trường. (14) Nhà thầu quản lý là nhà thầu không trực tiếp thực hiện một phần hoặc toàn bộ các công việc của gói thầu mà ký hợp đồng với các nhà thầu khác để thực hiện nhưng nhà thầu vẫn quản lý việc thực hiện của các nhà thầu mà mình đã ký hợp đồng, đồng thời vẫn chịu toàn bộ trách nhiệm cũng như rủi ro liên quan đến giá thành, tiến độ thực hiện, chất lượng và các nội dung khác của gói thầu. 2. 2. Tiêu chuẩn đánh giá về năng lực kỹ thuật Nhà thầu được đánh giá là đạt về năng lực kỹ thuật khi đáp ứng tất cả các tiêu chuẩn đánh giá về nhân sự chủ chốt và thiết bị thi công chủ yếu dự kiến huy động để thực hiện gói thầu. a) Nhân sự chủ chốt Căn cứ quy mô, tính chất của gói thầu và pháp luật về xây dựng mà Chủ đầu tư đưa ra yêu cầu về nhân sự chủ chốt trong HSYC cho phù hợp như chỉ huy trưởng công trường, cán bộ phụ trách kỹ thuật, an toàn lao động và các vị trí công việc quan trọng khác. HSYC không được yêu cầu về nhân sự chủ chốt đối với các vị trí công nhân kỹ thuật, lao động phổ thông. Trường hợp HSYC có yêu cầu về nhân sự chủ chốt thì nhà thầu phải chứng minh khả năng huy động các nhân sự chủ chốt đã đề xuất. Nhân sự chủ chốt có thể thuộc biên chế của nhà thầu hoặc do nhà thầu huy động. Trường hợp nhân sự chủ chốt mà nhà thầu đề xuất trong HSĐX không đáp ứng yêu cầu hoặc không chứng minh được khả năng huy động nhân sự (bao gồm cả trường hợp nhân sự đã huy động cho hợp đồng khác có thời gian làm việc trùng với thời gian thực hiện gói thầu này) thì Chủ đầu tư cho phép nhà thầu bổ sung, thay thế. Trường hợp nhà thầu không có nhân sự chủ chốt thay thế đáp ứng yêu cầu của HSYC thì nhà thầu bị loại. Trường hợp nhà thầu cố ý kê khai nhân sự chủ chốt không trung thực trong HSĐX nhằm làm sai lệch kết quả lựa chọn nhà thầu thì nhà thầu không được thay thế nhân sự khác, HSĐX của nhà thầu bị loại và nhà thầu sẽ bị coi là gian lận theo quy định tại điểm b Khoản 4 Điều 16 Luật Đấu thầu và bị xử lý theo quy định tại Khoản 1 Điều 133 Nghị định số 214/2025/NĐ-CP. Kinh nghiệm trong các công việc tương tự được thể hiện ở số năm tối thiểu nhân sự thực hiện các công việc tương tự hoặc số hợp đồng tối thiểu trong các công việc tương tự. Số năm kinh nghiệm của nhân sự chủ chốt được tính từ thời điểm nhân sự bắt đầu thực hiện công việc tương tự đó đến thời điểm đóng thầu. Nhà thầu phải cung cấp thông tin chi tiết về các nhân sự chủ chốt được đề xuất theo các Mẫu 07A, 07B và 07C Chương III để chứng minh rằng mình có đầy đủ nhân sự cho các vị trí chủ chốt đáp ứng những yêu cầu sau đây: Bảng số 02: Yêu cầu về nhân sự chủ chốt [BẢNG: Không tiêu đề] Ghi chú: (1) Trường hợp pháp luật quản lý ngành, lĩnh vực có yêu cầu về điều kiện hành nghề đối với vị trí công việc nêu tại Bảng này trong đó có nêu rõ yêu cầu về cấp dự án thì cấp dự án theo hợp đồng mà nhân sự chủ chốt đã tham gia được xác định theo quy định của pháp luật xây dựng tại thời điểm phê duyệt dự án đầu tư xây dựng dự án theo hợp đồng này. (2) Chỉ quy định trong trường hợp pháp luật chuyên ngành có yêu cầu về bằng cấp/chứng chỉ chuyên môn. b) Thiết bị thi công chủ yếu dự kiến huy động để thực hiện gói thầu Căn cứ quy mô, tính chất của gói thầu, Chủ đầu tư đưa ra các yêu cầu về thiết bị thi công chủ yếu dự kiến huy động và số lượng để thực hiện gói thầu cho phù hợp. Chỉ quy định về thiết bị thi công chủ yếu đối với các thiết bị quan trọng, đặc chủng, đặc thù bắt buộc phải có để triển khai thi công gói thầu. Thiết bị thi công chủ yếu có thể của nhà thầu hoặc do nhà thầu huy động. Trường hợp thiết bị thi công chủ yếu mà nhà thầu đề xuất trong HSĐX không đáp ứng yêu cầu thì Chủ đầu tư cho phép nhà thầu bổ sung, thay thế. Trường hợp nhà thầu không có thiết bị thay thế đáp ứng yêu cầu của HSYC thì nhà thầu bị loại. Trường hợp nhà thầu cố ý kê khai thiết bị thi công chủ yếu không trung thực trong HSĐX nhằm làm sai lệch kết quả lựa chọn nhà thầu thì nhà thầu không được thay thế thiết bị khác, HSĐX của nhà thầu bị loại và nhà thầu sẽ bị coi là gian lận theo quy định tại điểm b Khoản 4 Điều 16 của Luật Đấu thầu và bị xử lý theo quy định tại Khoản 1 Điều 133 của Nghị định số 214/2025/NĐ-CP. Nhà thầu phải cung cấp thông tin chi tiết về các Thiết bị thi công chủ yếu được đề xuất theo Mẫu 07D Chương III để chứng minh rằng mình có đầy đủ thiết bị đáp ứng những yêu cầu sau đây: Bảng số 03: Yêu cầu về thiết bị thi công chủ yếu [BẢNG: Không tiêu đề] Trường hợp nhà thầu trúng thầu và ký kết hợp đồng, nhà thầu có nghĩa vụ huy động nhân sự chủ chốt, thiết bị thi công chủ yếu như đã đề xuất ban đầu hoặc đề xuất thay đổi theo quy định tại Mục này. Trường hợp không huy động được nhân sự chủ chốt, thiết bị thi công chủ yếu, nhà thầu bị phạt hợp đồng, bị đánh giá về uy tín khi tham gia các gói thầu khác. 2. 3. thầu phụ đặc biệt (nếu có) Tổ chuyên gia chỉ đánh giá, đánh giá về năng lực kỹ thuật và kinh nghiệm của thầu phụ đặc biệt cho phần công việc chuyên ngành được phép sử dụng thầu phụ đặc biệt quy định tại Mục 12 Chương I. Kinh nghiệm cụ thể và nguồn lực tài chính của thầu phụ đặc biệt sẽ không được cộng vào kinh nghiệm và nguồn lực của nhà thầu khi đánh giá kinh nghiệm, năng lực của nhà thầu. thầu phụ đặc biệt được đề xuất phải có đầy đủ kinh nghiệm, năng lực kỹ thuật để thực hiện công việc và phải đáp ứng các tiêu chí sau đây: ____[ghi các tiêu chí, tiêu chuẩn đánh giá đối với thầu phụ đặc biệt]. Mục 3. Tiêu chuẩn đánh giá về kỹ thuật Sử dụng tiêu chí đạt/không đạt để xây dựng tiêu chuẩn đánh giá về kỹ thuật. Đối với các tiêu chí đánh giá tổng quát, chỉ sử dụng tiêu chí đạt, không đạt. Căn cứ quy mô, tính chất của gói thầu mà xác định mức độ yêu cầu đối với từng nội dung. Đối với các tiêu chí chi tiết cơ bản trong tiêu chí tổng quát, chỉ sử dụng tiêu chí đạt, không đạt; đối với các tiêu chí chi tiết không cơ bản trong tiêu chí tổng quát, ngoài tiêu chí đạt, không đạt, được áp dụng thêm tiêu chí chấp nhận được nhưng không được vượt quá 30% tổng số các tiêu chí chi tiết trong tiêu chí tổng quát đó. Tiêu chí tổng quát được đánh giá là đạt khi tất cả các tiêu chí chi tiết cơ bản được đánh giá là đạt và các tiêu chí chi tiết không cơ bản được đánh giá là đạt hoặc chấp nhận được. Việc xây dựng tiêu chuẩn đánh giá về kỹ thuật dựa trên các nội dung quy định tại Chương IV, thông tin về kết quả thực hiện hợp đồng của nhà thầu theo quy định tại Điều 19 và Điều 20 của Nghị định số 214/2025/NĐ-CP và các yêu cầu khác nêu trong HSYC. Căn cứ vào từng gói thầu cụ thể, khi lập HSYC phải cụ thể hóa các tiêu chí làm cơ sở để đánh giá về kỹ thuật bao gồm: - Tính hợp lý và khả thi của các giải pháp kỹ thuật, biện pháp tổ chức thi công phù hợp với đề xuất về tiến độ thi công; - Tiến độ thi công; - Cách thức quản lý dự án bao gồm: tổ chức quản lý dự án, tổ chức quản lý hiện trường; các biện pháp bảo đảm chất lượng; bảo đảm điều kiện vệ sinh môi trường và các điều kiện khác như phòng cháy, chữa cháy, an toàn lao động; - Mức độ đáp ứng các yêu cầu về bảo hành, bảo trì; - Các yếu tố thân thiện môi trường (nếu có) gồm việc sử dụng các vật tư, vật liệu, biện pháp tổ chức thi công, dây chuyền, kỹ thuật thi công và các yếu tố khác (nếu có); - Thông tin về kết quả thực hiện hợp đồng của nhà thầu theo quy định tại Điều 19 và Điều 20 của Nghị định số 214/2025/NĐ-CP; - Các yếu tố cần thiết khác; Chủ đầu tư được đưa ra yêu cầu về ký mã hiệu, nhãn hiệu, xuất xứ cho nguyên nhiên vật liệu, vật tư, máy móc, thiết bị và các yếu tố đầu vào khác. Nhà thầu được chào theo ký mã hiệu, nhãn hiệu, xuất xứ các nguyên nhiên vật liệu, vật tư, máy móc, thiết bị và các yếu tố đầu vào khác theo quy định trong hồ sơ yêu cầu hoặc ký mã hiệu, nhãn hiệu, xuất xứ khác có chất lượng hàng hóa (đặc tính kỹ thuật, tính năng sử dụng) tương đương hoặc tốt hơn. Trừ trường hợp do tính chất của gói thầu mà HSYC yêu cầu nhà thầu phải thực hiện theo đúng biện pháp thi công nêu trong HSYC, HSYC cần quy định nhà thầu được đề xuất biện pháp thi công khác với biện pháp thi công nêu trong HSYC. HSĐX được đánh giá là đáp ứng yêu cầu về kỹ thuật khi có tất cả các tiêu chí tổng quát đều được đánh giá là đạt. Mục 4. Tiêu chuẩn đánh giá về tài chính Bước 1. Xác định giá thầu; Bước 2. Sửa lỗi, hiệu chỉnh sai lệch theo quy định tại Điều 31 của Nghị định số 214/2025/NĐ-CP (nếu có); Bước 3. Xác định giá thầu sau sửa lỗi, hiệu chỉnh sai lệch (nếu có), trừ đi giá trị giảm giá (nếu có) và đáp ứng tỷ lệ tiết kiệm theo quy định tại Mục 14 Chương I; Chương III. BIỂU MẪU Mẫu 01 ĐƠN DỰ THẦU ________, ngày ____ tháng ____ năm ____ Kính gửi: __________________ [Ghi tên Chủ đầu tư] (sau đây gọi là Chủ đầu tư) Sau khi nghiên cứu hồ sơ yêu cầu và văn bản sửa đổi hồ sơ yêu cầu số ____ [Ghi số của văn bản sửa đổi, nếu có] mà chúng tôi đã nhận được, chúng tôi, __[Ghi tên nhà thầu], có địa chỉ tại ______[Ghi địa chỉ của nhà thầu] cam kết thực hiện gói thầu__[Ghi tên gói thầu] theo đúng yêu cầu của hồ sơ yêu cầu với tổng số tiền là__[Ghi giá trị bằng số, bằng chữ và đồng tiền dự thầu] cùng với bảng giá thầu kèm theo. Thời gian thực hiện gói thầu là ____ [Ghi thời gian thực hiện tất cả các công việc theo yêu cầu của gói thầu]. Hồ sơ đề xuất này có hiệu lực trong thời gian ____ ngày, kể từ ngày ____ tháng ____ năm ____ [Ghi ngày có thời điểm đóng thầu]. Chúng tôi cam kết: 1. Không đang trong quá trình thực hiện thủ tục giải thể hoặc bị thu hồi giấy chứng nhận đăng ký doanh nghiệp, giấy chứng nhận đăng ký hợp tác xã, liên hiệp hợp tác xã, tổ hợp tác, không thuộc trường hợp mất khả năng thanh toán theo quy định của pháp luật về phá sản (không đang trong quá trình chấm dứt hoạt động hoặc bị thu hồi giấy chứng nhận đăng ký hộ kinh doanh đối với nhà thầu là hộ kinh doanh). 2. Đã thực hiện nghĩa vụ kê khai thuế và nộp thuế của năm tài chính gần nhất so với thời điểm đóng thầu; 3. Không đang trong thời gian bị cấm dự thầu theo quy định của pháp luật đấu thầu; 4. Không đang bị truy cứu trách nhiệm hình sự (chủ hộ không đang bị truy cứu trách nhiệm hình sự trong trường hợp nhà thầu là hộ kinh doanh); 5. Trong thời hạn 03 năm trước thời điểm đóng thầu, nhà thầu không có nhân sự (ký kết hợp đồng lao động với nhà thầu tại thời điểm nhân sự thực hiện hành vi vi phạm) bị tòa án kết án có hành vi vi phạm quy định về đấu thầu gây hậu quả nghiêm trọng theo quy định của pháp luật về hình sự nhằm mục đích cho nhà thầu trúng thầu(2). 6. Không thực hiện các hành vi tham nhũng, hối lộ, thông thầu, cản trở và các hành vi vi phạm quy định khác của pháp luật đấu thầu khi tham dự gói thầu này. 7. Những thông tin kê khai trong HSĐX là trung thực. 8. Trường hợp trúng thầu, HSĐX và các văn bản bổ sung, làm rõ HSĐX tạo thành thỏa thuận ràng buộc trách nhiệm giữa hai bên cho tới khi hợp đồng được ký kết. 9. Nếu HSĐX của chúng tôi được chấp nhận, chúng tôi sẽ thực hiện biện pháp bảo đảm thực hiện hợp đồng theo quy định của HSYC. Đại diện hợp pháp của nhà thầu(1) [Ghi tên, chức danh, ký tên và đóng dấu] Ghi chú: (1) Trường hợp đại diện theo pháp luật của nhà thầu ủy quyền cho cấp dưới ký đơn dự thầu thì phải gửi kèm theo Giấy ủy quyền theo Mẫu 02 Chương này. Trường hợp tại điều lệ công ty hoặc tại các hồ sơ khác liên quan có phân công trách nhiệm cho cấp dưới ký đơn dự thầu thì phải gửi kèm theo bản chụp các văn bản, hồ sơ này (không cần lập Giấy ủy quyền theo Mẫu 02 Chương này). (2) HSYC không được yêu cầu nhà thầu phải nộp lý lịch tư pháp của nhân sự để chứng minh cho nội dung đánh giá này. Nội dung này chỉ yêu cầu nhà thầu cam kết trong Đơn này. Mẫu 02 GIẤY ỦY QUYỀN(1) Hôm nay, ngày ____ tháng ____ năm ____, tại ____ Tôi là__[Ghi tên, số CCCD hoặc số hộ chiếu, chức danh của người đại diện theo pháp luật của nhà thầu], là người đại diện theo pháp luật của __ [Ghi tên nhà thầu] có địa chỉ tại_ [Ghi địa chỉ của nhà thầu] bằng văn bản này ủy quyền cho___ [Ghi tên, số CCCD hoặc số hộ chiếu, chức danh của người được ủy quyền] thực hiện các công việc sau đây trong quá trình dự thầu gói thầu__ [Ghi tên gói thầu] thuộc ___ [Ghi tên dự án/dự toán mua sắm] do___ [Ghi tên Chủ đầu tư] tổ chức: [- Ký đơn dự thầu; - Ký thỏa thuận liên danh (nếu có); - Ký các văn bản, hồ sơ để giao dịch với Chủ đầu tư trong quá trình dự thầu, kể cả văn bản giải trình, làm rõ HSĐX; - Tham gia quá trình thương thảo (nếu có), hoàn thiện hợp đồng; - Ký kết hợp đồng với Chủ đầu tư nếu được chỉ định thầu.] (2) Người được ủy quyền nêu trên chỉ thực hiện các công việc trong phạm vi ủy quyền với tư cách là đại diện hợp pháp của____ [Ghi tên nhà thầu]. ____ [Ghi tên nhà thầu] chịu trách nhiệm hoàn toàn về những công việc do ____ [Ghi tên người được ủy quyền] thực hiện trong phạm vi ủy quyền. Giấy ủy quyền có hiệu lực kể từ ngày ____ đến ngày ____(3). Giấy ủy quyền này được lập thành ____ bản có giá trị pháp lý như nhau, người ủy quyền giữ ____ bản, người được ủy quyền giữ ____ bản. [BẢNG: Không tiêu đề] Ghi chú: (1) Trường hợp ủy quyền thì bản gốc giấy ủy quyền phải được gửi cho Chủ đầu tư cùng với đơn dự thầu. Việc ủy quyền của người đại diện theo pháp luật của nhà thầu cho cấp phó, cấp dưới, giám đốc chi nhánh, người đứng đầu văn phòng đại diện của nhà thầu để thay mặt cho người đại diện theo pháp luật của nhà thầu thực hiện một hoặc các nội dung công việc nêu trên đây. Việc sử dụng con dấu trong trường hợp được ủy quyền có thể là dấu của nhà thầu hoặc dấu của đơn vị mà cá nhân liên quan được ủy quyền. Người được ủy quyền không được tiếp tục ủy quyền cho người khác. (2) Phạm vi ủy quyền bao gồm một hoặc nhiều công việc nêu trên. (3) Ghi ngày có hiệu lực và ngày hết hiệu lực của giấy ủy quyền phù hợp với quá trình dự thầu và phải bảo đảm có hiệu lực trước ngày thực hiện các công việc được ủy quyền. Mẫu 03 THỎA THUẬN LIÊN DANH(1), ngày tháng năm Gói thầu: ___ [Ghi tên gói thầu] Thuộc: ___ [Ghi tên dự án/dự toán mua sắm] - Căn cứ ___ [Luật Đấu thầu](2); - Căn cứ ___ (2); - Căn cứ hồ sơ yêu cầu gói thầu _______ [Ghi tên gói thầu] ngày ___ tháng ____ năm ____[Ngày được ghi trên HSYC]; Chúng tôi, đại diện cho các bên ký thỏa thuận liên danh, gồm có: Tên thành viên liên danh [Ghi tên từng thành viên liên danh] Đại diện là ông/bà: Chức vụ: Địa chỉ: Điện thoại: E-mail: Tài khoản: Mã số thuế: Giấy ủy quyền số __ ngày __tháng __ năm __ (trường hợp được ủy quyền). Các bên (sau đây gọi là thành viên) thống nhất ký kết thỏa thuận liên danh với các nội dung sau: Điều 1. Nguyên tắc chung 1. Các thành viên tự nguyện hình thành liên danh để dự thầu gói thầu___[Ghi tên gói thầu] thuộc ___ [Ghi tên dự án/dự toán mua sắm]. 2. Các thành viên thống nhất tên gọi của liên danh cho mọi giao dịch liên quan đến gói thầu này là: [Ghi tên của liên danh]. 3. Các thành viên cam kết không thành viên nào có quyền từ chối thực hiện các trách nhiệm và nghĩa vụ quy định trong hợp đồng. Trường hợp thành viên của liên danh từ chối hoàn thành trách nhiệm riêng của mình như đã thỏa thuận thì thành viên đó bị xử lý như sau: - Bồi thường thiệt hại cho các bên trong liên danh - Bồi thường thiệt hại cho Chủ đầu tư theo quy định nêu trong hợp đồng - Hình thức xử lý khác [Ghi rõ hình thức xử lý khác]. Điều 2. Phân công trách nhiệm Các thành viên thống nhất chịu trách nhiệm chung, trách nhiệm riêng để thực hiện gói thầu [Ghi tên gói thầu] thuộc ___ [Ghi tên dự án/dự toán mua sắm] đối với từng thành viên như sau: 1. Thành viên đứng đầu liên danh Các bên nhất trí ủy quyền cho [Ghi tên một bên] làm thành viên đứng đầu liên danh, đại diện cho liên danh trong những phần việc sau(3): [- Ký đơn dự thầu; - Ký các văn bản, hồ sơ để giao dịch với Chủ đầu tư trong quá trình dự thầu, kể cả văn bản đề nghị làm rõ HSYC và văn bản giải trình, làm rõ HSĐX; - Tham gia quá trình thương thảo (nếu có), hoàn thiện hợp đồng; - Ký đơn kiến nghị trong trường hợp nhà thầu có kiến nghị; - Các công việc khác trừ việc ký kết hợp đồng [Ghi rõ nội dung các công việc khác (nếu có)]. 2. Các thành viên trong liên danh thỏa thuận phân công trách nhiệm thực hiện công việc theo bảng dưới đây(4): [BẢNG: Không tiêu đề] Điều 3. Hiệu lực của thỏa thuận liên danh 1. Thỏa thuận liên danh có hiệu lực kể từ ngày ký. 2. Thỏa thuận liên danh chấm dứt hiệu lực trong các trường hợp sau: - Các bên hoàn thành trách nhiệm và nghĩa vụ của mình và tiến hành thanh lý hợp đồng; - Các bên cùng thỏa thuận chấm dứt; - Nhà thầu liên danh không được chỉ định thầu; - Hủy thầu gói thầu [Ghi tên gói thầu] thuộc ___ [Ghi tên dự án/dự toán mua sắm] theo thông báo của Chủ đầu tư. Thỏa thuận liên danh được lập thành bản, mỗi bên giữ bản, các bản thỏa thuận có giá trị pháp lý như nhau. ĐẠI DIỆN HỢP PHÁP CỦA THÀNH VIÊN ĐỨNG ĐẦU LIÊN DANH(5) [Ghi tên, chức danh, ký tên và đóng dấu] ĐẠI DIỆN HỢP PHÁP CỦA THÀNH VIÊN LIÊN DANH [Ghi tên từng thành viên, chức danh, ký tên và đóng dấu] Ghi chú: (1) Căn cứ quy mô, tính chất của gói thầu, nội dung thỏa thuận liên danh theo mẫu này có thể được sửa đổi bổ sung cho phù hợp. (2) Cập nhật các văn bản quy phạm pháp luật theo quy định hiện hành. (3) Phạm vi ủy quyền bao gồm một hoặc nhiều công việc nêu trên. (4) Nhà thầu phải ghi rõ nội dung công việc cụ thể và ước tính giá trị tương ứng mà từng thành viên trong liên danh sẽ thực hiện, trách nhiệm chung, trách nhiệm của từng thành viên, kể cả thành viên đứng đầu liên danh. Việc phân chia công việc trong liên danh phải căn cứ các hạng mục nêu trong bảng giá thầu quy định tại Mẫu 04 (04A hoặc 04B hoặc 04C hoặc 04D hoặc 04E) Chương III; không được phân chia các công việc không thuộc các hạng mục này hoặc không thuộc quá trình sản xuất các hạng mục này. (5) Đại diện hợp pháp của thành viên liên danh có thể là người đại diện theo pháp luật hoặc người được người đại diện theo pháp luật ủy quyền. Mẫu 04A BẢNG giá thầu(1) (Đối với loại hợp đồng trọn gói) [BẢNG: Không tiêu đề] Đại diện hợp pháp của nhà thầu [ghi tên, chức danh, ký tên và đóng dấu] Ghi chú: (1) giá thầu của nhà thầu được coi là đã bao gồm toàn bộ các chi phí cần thiết để thực hiện gói thầu theo đúng thiết kế và yêu cầu kỹ thuật nêu trong HSYC, không tiến hành hiệu chỉnh sai lệch trong trường hợp hạng mục công việc mà nhà thầu đề xuất trong bảng giá thầu khác so với các hạng mục công việc nêu trong HSYC, trừ trường hợp công việc được đề xuất khác đó ngoài phạm vi yêu cầu trong HSYC (ngoài khối lượng để hoàn thành theo thiết kế). Trong trường hợp này, phần công việc ngoài phạm vi yêu cầu trong HSYC sẽ được coi là chào thừa và được hiệu chỉnh theo quy định. giá thầu là tổng giá trị của các hạng mục ghi trong cột “Mô tả công việc”. giá thầu của nhà thầu phải bao gồm chi phí cho các loại thuế, phí, lệ phí và chi phí dự phòng (nếu có). Nhà thầu phải tính toán các chi phí nêu trên và phân bổ vào trong giá thầu. Khi thực hiện hợp đồng, trường hợp nhà thầu hoàn thành toàn bộ gói thầu theo đúng hồ sơ thiết kế, yêu cầu kỹ thuật thì tổng số tiền mà nhà thầu được thanh toán cho đến khi hoàn thành các nghĩa vụ theo hợp đồng bằng đúng giá ghi trong hợp đồng. (2), (3) Các hạng mục công việc nêu trong HSYC và khối lượng chỉ có giá trị tham khảo, nhà thầu có trách nhiệm chuẩn xác hạng mục công việc phù hợp với thiết kế và yêu cầu kỹ thuật tại Chương IV. Nhà thầu có trách nhiệm rà soát lại các hạng mục công việc nêu trong HSYC. Nhà thầu phải tự bổ sung và chào giá cho các hạng mục công việc mà nhà thầu phát hiện chưa bao gồm trong các hạng mục công việc nêu trong HSYC nhưng cần thiết để hoàn thành công việc theo thiết kế. Trường hợp nhà thầu không bổ sung các hạng mục công việc thiếu so với thiết kế, nhà thầu được coi là đã phân bổ giá của các hạng mục công việc này vào các hạng mục công việc khác của gói thầu. Nhà thầu có trách nhiệm hoàn thành công việc theo thiết kế và đáp ứng yêu cầu về kỹ thuật với giá đã chào. Trường hợp phát hiện các hạng mục công việc nêu trong HSYC thừa so với thiết kế, nhà thầu loại hạng mục thừa ra khỏi bảng giá thầu. (4) Nhà thầu có trách nhiệm phân bổ chi phí dự phòng (nếu có) vào giá thầu. Nhà thầu không được chào riêng chi phí dự phòng. Trường hợp nhà thầu chào riêng chi phí dự phòng thì được coi là chào thừa và sẽ bị hiệu chỉnh sai lệch. Mẫu 04B BẢNG giá thầu (Đối với loại hợp đồng theo đơn giá cố định) [BẢNG: Không tiêu đề] Đại diện hợp pháp của nhà thầu [ghi tên, chức danh, ký tên và đóng dấu] Ghi chú: (2), (4), (5) Chủ đầu tư ghi các công việc cụ thể của từng hạng mục cùng với đơn vị tính và khối lượng mời thầu trên cơ sở phù hợp với mô tả công việc, bản vẽ và chi tiết kỹ thuật trong Chương IV làm cơ sở để nhà thầu chào giá thầu cho từng hạng mục. (3) Chủ đầu tư ghi dẫn chiếu cụ thể đến nội dung yêu cầu về kỹ thuật/chỉ dẫn kỹ thuật chính để thực hiện hạng mục công việc tương ứng trong Chương IV hoặc trong hồ sơ chỉ dẫn kỹ thuật (tên mục, số trang, số quyển. ..) để nhà thầu thuận tiện trong việc đánh giá, nghiên cứu các yêu cầu về kỹ thuật/chỉ dẫn kỹ thuật làm cơ sở chào giá thầu. (6) (7): Nhà thầu ghi đơn giá thầu, thành tiền của từng hạng mục. giá thầu của nhà thầu phải bao gồm chi phí cho các loại thuế, phí, lệ phí (nếu có) và chi phí dự phòng. (*): Trong HSYC phải ghi rõ tỷ lệ dự phòng cho khối lượng phát sinh (b1%) làm cơ sở để nhà thầu chào thầu. Khi dự thầu, nhà thầu phải chào chi phí dự phòng cho khối lượng phát sinh với giá trị bằng tỷ lệ phần trăm (%) quy định trong HSYC (b1%) nhân với Chi phí của các hạng mục do nhà thầu chào (A). Chi phí dự phòng chỉ được sử dụng khi có phát sinh khối lượng công việc trong thực tế. Mẫu 04C BẢNG giá thầu (Đối với loại hợp đồng theo đơn giá điều chỉnh) [BẢNG: Không tiêu đề] Đại diện hợp pháp của nhà thầu [ghi tên, chức danh, ký tên và đóng dấu] Ghi chú: (2), (4), (5) Chủ đầu tư ghi các công việc cụ thể của từng hạng mục cùng với đơn vị tính và khối lượng mời thầu trên cơ sở phù hợp với mô tả công việc, bản vẽ và chi tiết kỹ thuật trong Chương IV làm cơ sở để nhà thầu chào giá thầu cho từng hạng mục. (3) Chủ đầu tư ghi dẫn chiếu cụ thể đến nội dung yêu cầu về kỹ thuật/chỉ dẫn kỹ thuật chính để thực hiện hạng mục công việc tương ứng trong Chương IV hoặc trong hồ sơ chỉ dẫn kỹ thuật (tên mục, số trang, số quyển. ..) để nhà thầu thuận tiện trong việc đánh giá, nghiên cứu các yêu cầu về kỹ thuật/chỉ dẫn kỹ thuật làm cơ sở chào giá thầu. (6) (7) Nhà thầu ghi đơn giá thầu, thành tiền của từng hạng mục. giá thầu của nhà thầu phải bao gồm chi phí cho các loại thuế, phí, lệ phí (nếu có) và chi phí dự phòng. (*): Trong HSYC phải ghi rõ tỷ lệ dự phòng cho khối lượng phát sinh và dự phòng trượt giá (b2%) làm cơ sở để nhà thầu chào thầu. Khi dự thầu, nhà thầu phải chào chi phí dự phòng cho khối lượng phát sinh và chi phí dự phòng trượt giá với giá trị bằng tỷ lệ phần trăm (%) quy định trong HSYC (b2%) nhân với Chi phí của các hạng mục do nhà thầu chào (A). Chi phí dự phòng chỉ được sử dụng khi có phát sinh khối lượng công việc trong thực tế và có trượt giá. Mẫu 04D BẢNG giá thầu (Đối với loại hợp đồng theo kết quả đầu ra) [BẢNG: Không tiêu đề] Đại diện hợp pháp của nhà thầu [ghi tên, chức danh, ký tên và đóng dấu] Ghi chú: (2), (4), (5) Chủ đầu tư ghi các công việc cụ thể của từng hạng mục cùng với đơn vị tính và khối lượng mời thầu trên cơ sở phù hợp với mô tả công việc, bản vẽ và chi tiết kỹ thuật trong Chương IV làm cơ sở để nhà thầu chào giá thầu cho từng hạng mục. (3) Chủ đầu tư ghi dẫn chiếu cụ thể đến nội dung yêu cầu về kỹ thuật/chỉ dẫn kỹ thuật chính để thực hiện hạng mục công việc tương ứng trong Chương IV hoặc trong hồ sơ chỉ dẫn kỹ thuật (tên mục, số trang, số quyển. ..) để nhà thầu thuận tiện trong việc đánh giá, nghiên cứu các yêu cầu về kỹ thuật/chỉ dẫn kỹ thuật làm cơ sở chào giá thầu. (6), (7): Nhà thầu ghi đơn giá thầu, thành tiền của từng hạng mục. giá thầu của nhà thầu phải bao gồm chi phí cho các loại thuế, phí, lệ phí (nếu có). Mẫu 04E BẢNG giá thầu (Đối với loại hợp đồng hỗn hợp) I. Các hạng mục áp dụng loại hợp đồng trọn gói(1) [BẢNG: Không tiêu đề] Ghi chú: (1) giá thầu của các hạng mục này được coi là đã bao gồm toàn bộ các chi phí cần thiết để thực hiện theo đúng thiết kế và yêu cầu kỹ thuật nêu trong HSYC, không tiến hành hiệu chỉnh sai lệch trong trường hợp hạng mục công việc mà nhà thầu đề xuất trong các hạng mục này khác so với các hạng mục công việc áp dụng loại hợp đồng trọn gói nêu trong HSYC, trừ trường hợp công việc được đề xuất khác đó ngoài phạm vi yêu cầu trong HSYC (ngoài khối lượng để hoàn thành theo thiết kế). Trong trường hợp này, phần công việc ngoài phạm vi yêu cầu trong HSYC sẽ được coi là chào thừa và được hiệu chỉnh theo quy định. giá thầu cho các hạng mục này là tổng giá trị của các hạng mục ghi trong cột “Mô tả công việc”. giá thầu của nhà thầu phải bao gồm chi phí cho các loại thuế, phí, lệ phí và chi phí dự phòng (nếu có). Nhà thầu phải tính toán các chi phí nêu trên và phân bổ vào trong giá các hạng mục. Khi thực hiện hợp đồng, trường hợp nhà thầu hoàn thành toàn bộ các hạng mục áp dụng loại hợp đồng trọn gói theo đúng hồ sơ thiết kế, yêu cầu kỹ thuật thì tổng số tiền mà nhà thầu được thanh toán cho đến khi hoàn thành các nghĩa vụ theo hợp đồng bằng đúng giá của các hạng mục áp dụng loại hợp đồng trọn gói ghi trong hợp đồng. (2), (3) Các hạng mục công việc nêu trong HSYC và khối lượng chỉ có giá trị tham khảo, nhà thầu có trách nhiệm chuẩn xác hạng mục công việc phù hợp với thiết kế và yêu cầu kỹ thuật tại Chương IV. (4) Nhà thầu có trách nhiệm phân bổ chi phí dự phòng (nếu có) vào giá của các hạng mục. Nhà thầu không được chào riêng chi phí dự phòng. Trường hợp nhà thầu chào riêng chi phí dự phòng thì được coi là chào thừa và sẽ bị hiệu chỉnh sai lệch. II. Các hạng mục áp dụng loại hợp đồng theo đơn giá cố định [BẢNG: Không tiêu đề] Ghi chú: (2), (4), (5) Chủ đầu tư ghi các công việc cụ thể của từng hạng mục cùng với đơn vị tính và khối lượng mời thầu trên cơ sở phù hợp với mô tả công việc, bản vẽ và chi tiết kỹ thuật trong Chương IV làm cơ sở để nhà thầu chào giá thầu cho từng hạng mục. (3) Chủ đầu tư ghi dẫn chiếu cụ thể đến nội dung yêu cầu về kỹ thuật/chỉ dẫn kỹ thuật chính để thực hiện hạng mục công việc tương ứng trong Chương IV hoặc trong hồ sơ chỉ dẫn kỹ thuật (tên mục, số trang, số quyển. ..) để nhà thầu thuận tiện trong việc đánh giá, nghiên cứu các yêu cầu về kỹ thuật/chỉ dẫn kỹ thuật làm cơ sở chào giá thầu. (6) (7) Nhà thầu ghi đơn giá thầu, thành tiền của từng hạng mục. giá thầu của nhà thầu phải bao gồm chi phí cho các loại thuế, phí, lệ phí (nếu có) và chi phí dự phòng. (*): Trong HSYC phải ghi rõ tỷ lệ dự phòng cho khối lượng phát sinh (b1%) làm cơ sở để nhà thầu chào thầu. Khi dự thầu, nhà thầu phải chào chi phí dự phòng cho khối lượng phát sinh với giá trị bằng tỷ lệ phần trăm (%) quy định trong HSYC (b1%) nhân với Chi phí của các hạng mục do nhà thầu chào (A). Chi phí dự phòng chỉ được sử dụng khi có phát sinh khối lượng công việc trong thực tế. III. Các hạng mục áp dụng loại hợp đồng theo đơn giá điều chỉnh [BẢNG: Không tiêu đề] Ghi chú: (2), (4), (5) Chủ đầu tư ghi các công việc cụ thể của từng hạng mục cùng với đơn vị tính và khối lượng mời thầu trên cơ sở phù hợp với mô tả công việc, bản vẽ và chi tiết kỹ thuật trong Chương IV làm cơ sở để nhà thầu chào giá thầu cho từng hạng mục. (3) Chủ đầu tư ghi dẫn chiếu cụ thể đến nội dung yêu cầu về kỹ thuật/chỉ dẫn kỹ thuật chính để thực hiện hạng mục công việc tương ứng trong Chương IV hoặc trong hồ sơ chỉ dẫn kỹ thuật (tên mục, số trang, số quyển. ..) để nhà thầu thuận tiện trong việc đánh giá, nghiên cứu các yêu cầu về kỹ thuật/chỉ dẫn kỹ thuật làm cơ sở chào giá thầu. (6) (7) Nhà thầu ghi đơn giá thầu, thành tiền của từng hạng mục. giá thầu của nhà thầu phải bao gồm chi phí cho các loại thuế, phí, lệ phí (nếu có) và chi phí dự phòng. (*): Trong HSYC phải ghi rõ tỷ lệ dự phòng cho khối lượng phát sinh và dự phòng trượt giá (b2%) làm cơ sở để nhà thầu chào thầu. Khi dự thầu, nhà thầu phải chào chi phí dự phòng cho khối lượng phát sinh và chi phí dự phòng trượt giá với giá trị bằng tỷ lệ phần trăm (%) quy định trong HSYC (b2%) nhân với Chi phí của các hạng mục do nhà thầu chào (A). Chi phí dự phòng chỉ được sử dụng khi có phát sinh khối lượng công việc trong thực tế và có trượt giá. IV. Các hạng mục áp dụng loại hợp đồng theo kết quả đầu ra [BẢNG: Không tiêu đề] Ghi chú: (2), (4), (5) Chủ đầu tư ghi các công việc cụ thể của từng hạng mục cùng với đơn vị tính và khối lượng mời thầu trên cơ sở phù hợp với mô tả công việc, bản vẽ và chi tiết kỹ thuật trong Chương IV làm cơ sở để nhà thầu chào giá thầu cho từng hạng mục. (3) Chủ đầu tư ghi dẫn chiếu cụ thể đến nội dung yêu cầu về kỹ thuật/chỉ dẫn kỹ thuật chính để thực hiện hạng mục công việc tương ứng trong Chương IV hoặc trong hồ sơ chỉ dẫn kỹ thuật (tên mục, số trang, số quyển. ..) để nhà thầu thuận tiện trong việc đánh giá, nghiên cứu các yêu cầu về kỹ thuật/chỉ dẫn kỹ thuật làm cơ sở chào giá thầu. (6), (7): Nhà thầu ghi đơn giá thầu, thành tiền của từng hạng mục. giá thầu của nhà thầu phải bao gồm chi phí cho các loại thuế, phí, lệ phí (nếu có). V. Tổng hợp giá thầu [BẢNG: Không tiêu đề] Mẫu 04G BẢNG KÊ CÔNG NHẬT 1. Quy định chung a) Bảng kê Công nhật thông thường được áp dụng đối với các gói thầu có khả năng phát sinh công việc ngoài các công việc nêu trong Bảng giá thầu hoặc không thể đưa vào nội dung mô tả, khối lượng, số lượng ước tính trong Bảng giá thầu. Trường hợp cần đưa Bảng kê Công nhật vào HSYC thì phải ghi rõ khối lượng, số lượng danh nghĩa đối với các hạng mục có khả năng phải sử dụng công nhật để nhà thầu làm cơ sở chào giá. giá thầu cho phần công nhật được kết chuyển vào phần Chi phí cho các khoản tạm tính trong Bảng giá thầu. Phần Chi phí cho các khoản tạm tính, trong đó bao gồm Chi phí công nhật sẽ được tách riêng và không được đánh giá trong quá trình đánh giá HSĐX. b) Giá trúng thầu và giá hợp đồng sẽ bao gồm Chi phí cho các khoản tạm tính do nhà thầu chào trong HSĐX. Trường hợp trong quá trình thực hiện hợp đồng, nếu có phát sinh công nhật hoặc các công việc tạm tính khác thì Chủ đầu tư sẽ dùng khoản kinh phí cho các khoản tạm tính để thanh toán cho nhà thầu theo quy định trong hợp đồng. c) Các công việc sẽ không được thực hiện trên cơ sở công nhật trừ trường hợp có yêu cầu bằng văn bản của Chủ đầu tư. Nhà thầu phải điền đơn giá, thành tiền cho các hạng mục công nhật trong các Bảng nhân công, vật liệu, thiết bị. Đơn giá do nhà thầu chào sẽ được áp dụng đối với bất kỳ khối lượng công nhật nào được Chủ đầu tư yêu cầu thực hiện. Trừ khi hợp đồng có quy định khác, các khoản thanh toán cho công nhật sẽ phụ thuộc vào quy định về điều chỉnh giá trong Điều kiện hợp đồng. 2. Nhân công tính theo Công nhật a) Khi tính toán các khoản thanh toán cho nhà thầu theo công nhật, số giờ cho nhân công sẽ được tính từ thời điểm nhân công đến hiện trường để thực hiện hạng mục công nhật đến thời điểm nhân công quay trở về nơi xuất phát ban đầu, nhưng không bao gồm thời gian nghỉ ăn trưa và những khoảng thời gian nghỉ khác. Chỉ có thời gian của các nhân công trực tiếp làm công việc theo yêu cầu của Chủ đầu tư và công việc mà nhân công có khả năng thực hiện mới được tính chi phí. Thời gian đội trưởng tham gia xây lắp cùng tập thể lao động cũng sẽ được tính nhưng không tính thời gian của đốc công hoặc nhân sự giám sát khác. b) Nhà thầu được thanh toán đối với tổng số thời gian mà nhân công được thuê theo công nhật. Giá trị thanh toán được tính theo đơn giá mà nhà thầu chào trong Bảng đơn giá công nhật: 1. Nhân công. Đơn giá được coi là đã bao gồm (nhưng không giới hạn) tất cả các chi phí phải thanh toán cho nhà thầu như: - Số tiền lương trả cho người lao động; - Chi phí đi lại, làm thêm giờ, sinh hoạt phí; - Các chi phí về phúc lợi xã hội liên quan; - Lợi nhuận của nhà thầu, chi phí quản lý, giám sát, bảo hiểm; - Chi phí điện, nước, an ninh, văn phòng phẩm, thông tin liên lạc, hành chính, văn thư và các chi phí liên quan khác. 3. Vật liệu tính theo Công nhật Nhà thầu sẽ được thanh toán đối với vật liệu được sử dụng để thực hiện công việc theo công nhật với đơn giá mà nhà thầu chào trong Bảng đơn giá công nhật: 2. Vật liệu. Đơn giá phải được chào bằng VND và được coi là đã bao gồm chi phí quản lý, lợi nhuận như sau: a) Đơn giá vật liệu sẽ được tính trên cơ sở giá ghi trên hóa đơn cộng với các chi phí để giao vật liệu đến kho tại Công trường bao gồm chi phí vận chuyển, bảo hiểm, chi phí bốc dỡ, thiệt hại, tổn thất. .. ; b) Chi phí vận chuyển vật liệu để sử dụng vào công việc được yêu cầu thực hiện theo công nhật từ kho chứa tại Công trường đến địa điểm mà vật liệu được sử dụng sẽ được thanh toán theo các điều khoản về Nhân công và Thiết bị thi công trong Bảng này. 4. Thiết bị của nhà thầu tính theo Công nhật a) Nhà thầu được thanh toán đối với Thiết bị của nhà thầu đã có tại Công trường và được sử dụng vào công việc theo công nhật theo đơn giá mà nhà thầu chào trong Bảng đơn giá công nhật: 3. Thiết bị của nhà thầu. Đơn giá phải được chào bằng VND và được coi là đã bao gồm (nhưng không giới hạn) các khoản chi phí sau: Chi phí khấu hao thiết bị; Chi phí lãi suất, tiền bồi thường, tiền bảo hiểm, sửa chữa, bảo trì, vật tư, nhiên liệu, dầu nhờn và vật tư tiêu hao khác; Lợi nhuận và chi phí quản lý liên quan đến việc sử dụng các thiết bị. Chi phí cho nhân viên vận hành thiết bị và trợ lý sẽ được thanh toán riêng như mô tả tại phần Nhân công tính theo Công nhật. b) Chỉ có số giờ vận hành thực sự của thiết bị để thực hiện các công việc theo công nhật mới đủ điều kiện để thanh toán; trừ trường hợp Chủ đầu tư chấp nhận thanh toán đối với thời gian di chuyển thiết bị từ Công trường nơi thiết bị được đặt đến vị trí thi công các công việc theo công nhật và thời gian di chuyển thiết bị về vị trí ban đầu. Bảng đơn giá công nhật 1. Nhân công [BẢNG: Không tiêu đề] Đại diện hợp pháp của nhà thầu [ghi tên, chức danh, ký tên và đóng dấu] Ghi chú: (1), (2), (3) Chủ đầu tư căn cứ khả năng phát sinh công việc ngoài các công việc nêu trong Bảng giá thầu hoặc không thể đưa vào nội dung mô tả, khối lượng, số lượng ước tính trong Bảng giá thầu để dự tính và ghi cụ thể tên công việc, đơn vị tính và số lượng danh nghĩa cho các công việc có thể sử dụng công nhật để nhà thầu làm cơ sở chào thầu. (4), (5) Nhà thầu ghi đơn giá, thành tiền cho từng nội dung tương ứng trong cột “Mô tả”. Bảng Đơn giá Công nhật 2. Vật liệu [BẢNG: Không tiêu đề] Đại diện hợp pháp của nhà thầu [ghi tên, chức danh, ký tên và đóng dấu] Ghi chú: (1), (2), (3) Chủ đầu tư căn cứ khả năng phát sinh công việc ngoài các công việc nêu trong Bảng giá thầu hoặc không thể đưa vào nội dung mô tả, khối lượng, số lượng ước tính trong Bảng giá thầu để dự tính và ghi cụ thể tên công việc, đơn vị tính và số lượng danh nghĩa cho các công việc có thể sử dụng công nhật để nhà thầu làm cơ sở chào thầu. (4), (5) Nhà thầu ghi đơn giá, thành tiền cho từng nội dung tương ứng trong cột “Mô tả”. Bảng Đơn giá Công nhật 3. Thiết bị của Nhà thầu [BẢNG: Không tiêu đề] Đại diện hợp pháp của nhà thầu [ghi tên, chức danh, ký tên và đóng dấu] Ghi chú: (1), (2), (3) Chủ đầu tư căn cứ khả năng phát sinh công việc ngoài các công việc nêu trong Bảng giá thầu hoặc không thể đưa vào nội dung mô tả, khối lượng, số lượng ước tính trong Bảng giá thầu để dự tính và ghi cụ thể tên công việc, đơn vị tính và số lượng danh nghĩa cho các công việc có thể sử dụng công nhật để nhà thầu làm cơ sở chào thầu. (4), (5) Nhà thầu ghi đơn giá, thành tiền cho từng nội dung tương ứng trong cột “Mô tả”. Bảng Công nhật tổng hợp [BẢNG: Không tiêu đề] Đại diện hợp pháp của nhà thầu [ghi tên, chức danh, ký tên và đóng dấu] Mẫu 04H BẢNG KÊ CÁC KHOẢN TẠM TÍNH Phần chi phí cho các khoản tạm tính sẽ được tách riêng và không được đánh giá trong quá trình đánh giá HSĐX. Giá trúng thầu và giá hợp đồng sẽ bao gồm chi phí cho các khoản tạm tính do nhà thầu chào trong HSĐX. Trường hợp trong quá trình thực hiện hợp đồng, nếu có phát sinh các công việc theo mô tả thì Chủ đầu tư sẽ dùng khoản kinh phí cho các khoản tạm tính để thanh toán cho nhà thầu theo quy định trong hợp đồng. [BẢNG: Bảng số] Đại diện hợp pháp của nhà thầu [ghi tên, chức danh, ký tên và đóng dấu] Ghi chú: (1) Do Chủ đầu tư điền nội dung công việc để nhà thầu làm căn cứ chào trong HSĐX theo đúng nội dung công việc nêu trong HSYC. (2) Nhà thầu ghi thành tiền cho từng nội dung tương ứng trong cột “Mô tả”. Mẫu 04I BẢNG KÊ SỐ LIỆU ĐIỀU CHỈNH (áp dụng cho hợp đồng theo đơn điều chỉnh) [BẢNG: Không tiêu đề] Mẫu 05 BẢN KÊ KHAI THÔNG TIN VỀ NHÀ THẦU (1) Ngày: _________________ Tên gói thầu: _________________ [BẢNG: Không tiêu đề] Ghi chú: (1) Đối với nhà thầu liên danh thì từng thành viên phải kê khai theo Mẫu này. Mẫu 06 HỢP ĐỒNG TƯƠNG TỰ DO NHÀ THẦU THỰC HIỆN Tên nhà thầu: _____[ghi tên đầy đủ của nhà thầu]. Thông tin về từng hợp đồng, mỗi hợp đồng cần bảo đảm các thông tin sau đây: [BẢNG: Không tiêu đề] Ghi chú: Nhà thầu nghiên cứu kỹ HSYC và đề xuất các hợp đồng tương tự để bảo đảm đáp ứng yêu cầu của HSYC. (1) Trong trường hợp liên danh, từng thành viên trong liên danh kê khai theo Mẫu này. Trường hợp nhà thầu có nhiều hợp đồng tương tự thì kê khai từng hợp đồng theo Mẫu này. Trường hợp HSYC không yêu cầu về kinh nghiệm thực hiện hợp đồng xây lắp tương tự thì bỏ qua Bảng này. (2) Nhà thầu chỉ kê khai nội dung tương tự với yêu cầu của gói thầu. (3) Trường hợp giá trị hợp đồng không tính bằng VND thì quy đổi sang VND theo tỷ giá theo quy định tại Mục 2. 1 Chương II để làm cơ sở đánh giá. Mẫu 07A BẢNG ĐỀ XUẤT NHÂN SỰ CHỦ CHỐT Nhà thầu phải kê khai những nhân sự chủ chốt theo quy định tại điểm a Mục 2. 2 Chương II và phải chứng minh khả năng sẵn sàng huy động các nhân sự này để tham gia thực hiện gói thầu. Nhân sự chủ chốt có thể thuộc biên chế của nhà thầu hoặc do nhà thầu huy động. Trường hợp nhân sự chủ chốt mà nhà thầu đề xuất trong HSĐX không đáp ứng yêu cầu hoặc không chứng minh được khả năng huy động nhân sự (bao gồm cả trường hợp nhân sự đã huy động cho hợp đồng khác có thời gian làm việc trùng với thời gian thực hiện gói thầu này) thì Chủ đầu tư cho phép nhà thầu bổ sung, thay thế. Trường hợp nhà thầu không có nhân sự thay thế đáp ứng yêu cầu của HSYC thì HSĐX bị loại. Trường hợp nhà thầu cố ý kê khai kê khai nhân sự chủ chốt không trung thực trong HSĐX nhằm làm sai lệch kết quả lựa chọn nhà thầu thì nhà thầu không được thay thế nhân sự khác, HSĐX của nhà thầu bị loại và nhà thầu sẽ bị coi là gian lận theo quy định tại điểm b Khoản 4 Điều 16 của Luật Đấu thầu và bị xử lý theo quy định tại Khoản 1 Điều 133 của Nghị định số 214/2025/NĐ-CP. [BẢNG: Không tiêu đề] Mẫu 07B [BẢNG: Không tiêu đề] Nhà thầu phải cung cấp tất cả các thông tin trong HSĐX theo yêu cầu tại Bảng trên. Mẫu 07C [BẢNG: BẢNG KINH NGHIỆM CHUYÊN MÔN] Liệt kê theo trình tự thời gian quá trình công tác của chuyên gia, không cần liệt kê các công việc đã làm không phù hợp hoặc không liên quan với công việc đang yêu cầu. Nhà thầu phải cung cấp tất cả các thông tin được yêu cầu. Mẫu 07D BẢNG KÊ KHAI THIẾT BỊ THI CÔNG CHỦ YẾU Nhà thầu phải kê khai những thiết bị thi công chủ yếu theo quy định tại điểm b Mục 2. 2 Chương II và phải chứng minh khả năng sẵn sàng huy động các thiết bị này để tham gia thực hiện gói thầu. Thiết bị thi công chủ yếu có thể thuộc sở hữu của nhà thầu hoặc do nhà thầu huy động. Trường hợp thiết bị mà nhà thầu đề xuất trong HSĐX không đáp ứng yêu cầu thì Chủ đầu tư cho phép nhà thầu bổ sung, thay thế. Trường hợp nhà thầu không có thiết bị thay thế đáp ứng yêu cầu của HSYC thì nhà thầu bị loại. Trường hợp nhà thầu cố ý kê khai thiết bị thi công chủ yếu không trung thực trong HSĐX nhằm làm sai lệch kết quả lựa chọn nhà thầu thì nhà thầu không được thay thế thiết bị khác, HSĐX của nhà thầu bị loại và nhà thầu sẽ bị coi là gian lận theo quy định tại điểm b Khoản 4 Điều 16 của Luật Đấu thầu và bị xử lý theo quy định tại Khoản 1 Điều 133 của Nghị định số 214/2025/NĐ-CP. [BẢNG: Không tiêu đề] Đối với các thiết bị không thuộc sở hữu của mình thì nhà thầu phải kê khai thêm các thông tin dưới đây: [BẢNG: Không tiêu đề] Mẫu 08 HỢP ĐỒNG XÂY LẮP, EPC, EC, PC, CHÌA KHÓA TRAO TAY KHÔNG HOÀN THÀNH DO LỖI CỦA NHÀ THẦU TRONG QUÁ KHỨ(1) Tên nhà thầu: ________________ Ngày: ______________________ Tên thành viên của nhà thầu liên danh (nếu có): _________________________ [BẢNG: Không tiêu đề] Ghi chú: (1) Nhà thầu phải kê khai chính xác, trung thực các hợp đồng xây lắp, EPC, EC, PC, chìa khóa trao tay không hoàn thành do lỗi của nhà thầu trong quá khứ; trường hợp Chủ đầu tư, tổ chuyên gia phát hiện nhà thầu có hợp đồng xây lắp, EPC, EC, PC, chìa khóa trao tay không hoàn thành do lỗi của nhà thầu trong quá khứ mà không kê khai thì nhà thầu được coi là có hành vi gian lận và HSĐX của nhà thầu sẽ bị loại. Trường hợp nhà thầu liên danh thì từng thành viên liên danh phải kê khai theo Mẫu này. Mẫu 09A TÌNH HÌNH TÀI CHÍNH CỦA NHÀ THẦU(1) Tên nhà thầu: ________________ Ngày: ______________________ [BẢNG: Không tiêu đề] Ghi chú: (1) Trường hợp nhà thầu liên danh thì từng thành viên liên danh phải kê khai theo Mẫu này. (2) Để xác định doanh thu bình quân hằng năm (không bao gồm thuế VAT), nhà thầu chia tổng doanh thu của các năm (không bao gồm thuế VAT) cho số năm dựa trên thông tin đã được cung cấp. Doanh thu hằng năm được tính bằng tổng doanh thu trong báo cáo tài chính của năm đó (chưa bao gồm thuế VAT). Doanh thu bình quân hằng năm (không bao gồm thuế VAT) = tổng doanh thu từng năm (không bao gồm thuế VAT) theo yêu cầu của HSYC/số năm. Trường hợp nhà thầu mới thành lập không đủ số năm theo yêu cầu của HSYC thì Doanh thu bình quân hằng năm (không bao gồm thuế VAT) được tính trên cơ sở số năm mà nhà thầu có số liệu tài chính. Nhà thầu phải nộp các hồ sơ như sau: Bản sao các báo cáo tài chính (các bảng cân đối kế toán bao gồm tất cả thuyết minh có liên quan, và các báo cáo kết quả kinh doanh) cho các năm như đã nêu trên, tuân thủ các điều kiện sau: 1. Phản ánh tình hình tài chính của nhà thầu hoặc thành viên liên danh (nếu là nhà thầu liên danh) mà không phải tình hình tài chính của một chủ thể liên kết như công ty mẹ liên kết với công ty con hoặc công ty liên kết với nhà thầu hoặc thành viên liên danh. 2. Các báo cáo tài chính phải hoàn chỉnh, đầy đủ nội dung theo quy định. 3. Các báo cáo tài chính phải tương ứng với các kỳ kế toán đã hoàn thành kèm theo bản chụp được chứng thực một trong các hồ sơ sau đây: - Biên bản kiểm tra quyết toán thuế; - Tờ khai tự quyết toán thuế (thuế giá trị gia tăng và thuế thu nhập doanh nghiệp) có xác nhận của cơ quan thuế về thời điểm đã nộp tờ khai; - hồ sơ chứng minh việc nhà thầu đã kê khai quyết toán thuế điện tử; - Văn bản xác nhận của cơ quan quản lý thuế (xác nhận số nộp cả năm) về việc thực hiện nghĩa vụ nộp thuế; - Báo cáo kiểm toán (nếu có); - Các hồ sơ khác. Các hồ sơ trên đây phải phù hợp với số liệu nhà thầu đã kê khai trên Hệ thống Thuế điện tử tại thời điểm đóng thầu. Mẫu 09B NGUỒN LỰC TÀI CHÍNH (1) Nêu rõ các nguồn tài chính dự kiến, chẳng hạn như các tài sản có khả năng thanh khoản cao(2), hạn mức tín dụng khả dụng (hạn mức tín dụng còn được sử dụng) hoặc các nguồn tài chính khác (không bao gồm các khoản tạm ứng thanh toán theo hợp đồng) có sẵn để đáp ứng yêu cầu về nguồn lực tài chính được nêu trong Mẫu 09C Chương này. [BẢNG: Không tiêu đề] Ghi chú: (1) Từng nhà thầu hoặc thành viên liên danh phải cung cấp thông tin về nguồn lực tài chính của mình, kèm theo hồ sơ chứng minh. Nguồn lực tài chính mà nhà thầu dự kiến huy động để thực hiện gói thầu được tính theo công thức sau: NLTC = TNL - ĐTH Trong đó: - NLTC là nguồn lực tài chính mà nhà thầu dự kiến huy động để thực hiện gói thầu; - TNL là tổng nguồn lực tài chính của nhà thầu (nêu tại Mẫu này); - ĐTH là tổng yêu cầu về nguồn lực tài chính hàng tháng cho các hợp đồng đang thực hiện (nêu tại Mẫu 09C). Nhà thầu được đánh giá là đáp ứng yêu cầu về nguồn lực tài chính cho gói thầu nếu có nguồn lực tài chính dự kiến huy động để thực hiện gói thầu (NLTC) tối thiểu bằng giá trị yêu cầu tại tiêu chí đánh giá 3. 3 Bảng số 01: Tiêu chuẩn đánh giá về năng lực tài chính và kinh nghiệm Mục 2. 1 Chương II. Trường hợp HSYC có yêu cầu về cam kết cung cấp tín dụng và trong HSĐX của nhà thầu có nộp kèm theo bản cam kết cung cấp tín dụng của tổ chức tín dụng hoạt động hợp pháp tại Việt Nam, trong đó cam kết sẽ cung cấp tín dụng cho nhà thầu để thực hiện gói đang xét đáp ứng quy định tại tiêu chí đánh giá 3. 3 Bảng số 01: Tiêu chuẩn đánh giá về năng lực tài chính và kinh nghiệm Mục 2. 1 Chương II thì nhà thầu được đánh giá là đáp ứng yêu cầu về nguồn lực tài chính cho gói thầu. Bản cam kết cung cấp tín dụng bao gồm các điều kiện để được ngân hàng cấp tín dụng theo quy định của pháp luật về tín dụng vẫn được chấp nhận; bên cạnh việc sử dụng cam kết cung cấp tín dụng, nhà thầu vẫn phải kê khai thông tin theo Mẫu này và Mẫu 09C. (2) Tài sản có khả năng thanh khoản cao là tiền mặt và tương đương tiền mặt, các công cụ tài chính ngắn hạn, các chứng khoán sẵn sàng để bán, chứng khoán dễ bán, các khoản phải thu thương mại, các khoản phải thu tài chính ngắn hạn và các tài sản khác mà có thể chuyển đổi thành tiền mặt trong vòng một năm. Mẫu 09C NGUỒN LỰC TÀI CHÍNH HÀNG THÁNG CHO CÁC HỢP ĐỒNG ĐANG THỰC HIỆN (1) [BẢNG: Không tiêu đề] Ghi chú: (1) Từng nhà thầu hoặc thành viên liên danh phải cung cấp thông tin được nêu dưới đây để tính toán tổng các yêu cầu về nguồn lực tài chính, bằng tổng của: (i) các cam kết hiện tại của nhà thầu (hoặc từng thành viên trong liên danh) trong tất cả các hợp đồng mà nhà thầu (hoặc từng thành trong viên liên danh) đang thực hiện hoặc sẽ được thực hiện; (ii) yêu cầu về nguồn lực tài chính đối với hợp đồng đang xét. Ngoài ra, nhà thầu cũng phải cung cấp thông tin về bất kỳ nghĩa vụ tài chính nào khác có thể ảnh hưởng đáng kể đến việc thực hiện hợp đồng đang xét nếu nhà thầu được trao hợp đồng. (2) Thời hạn còn lại của hợp đồng tính tại thời điểm 28 ngày trước ngày có thời điểm đóng thầu. (3) Giá trị hợp đồng còn lại chưa được thanh toán tính tại thời điểm 28 ngày trước ngày có thời điểm đóng thầu. Mẫu 10A PHẠM VI CÔNG VIỆC SỬ DỤNG thầu phụ(1) [BẢNG: Không tiêu đề] Ghi chú: (1) Trường hợp HSYC có quy định về việc sử dụng thầu phụ thì nhà thầu kê khai theo Mẫu này. (2) Nhà thầu ghi cụ thể tên thầu phụ. Trường hợp khi dự thầu chưa xác định được cụ thể danh tính của thầu phụ thì không phải kê khai vào cột này mà chỉ kê khai vào cột “Phạm vi công việc”. Nếu nhà thầu trúng thầu thì khi huy động thầu phụ thực hiện công việc đã kê khai phải được sự chấp thuận của Chủ đầu tư. (3) Nhà thầu ghi cụ thể tên hạng mục công việc dành cho thầu phụ. (4) Nhà thầu ghi cụ thể khối lượng công việc dành cho thầu phụ. (5) Nhà thầu ghi cụ thể giá trị % công việc mà thầu phụ đảm nhận so với giá thầu nhưng không được vượt quá tỷ lệ phần trăm (%) quy định tại Mục 12. 2 Chương I. Trường hợp nhà thầu liên danh, thành viên liên danh được sử dụng thầu phụ đối với phần công việc đảm nhận theo tỷ lệ % quy định tại Mục 12. 2 Chương I. (6) Nhà thầu ghi cụ thể số hợp đồng hoặc văn bản thỏa thuận và đính kèm bản chụp được chứng thực các hồ sơ này trong HSĐX. Trường hợp khi dự thầu chưa xác định được thầu phụ thì để trống cột này. Mẫu 10B BẢNG KÊ KHAI thầu phụ ĐẶC BIỆT(1) Nhà thầu phải cung cấp hồ sơ chứng minh đáp ứng yêu cầu quy định tại Mục 2. 3 Chương II. [BẢNG: Không tiêu đề] Ghi chú: (1) Trường hợp sử dụng thầu phụ đặc biệt thì kê khai theo Mẫu này. (2) Nhà thầu ghi cụ thể tên thầu phụ đặc biệt. (3) Chủ đầu tư ghi cụ thể tên hạng mục công việc sẽ được sử dụng thầu phụ đặc biệt. (4) Nhà thầu ghi cụ thể khối lượng công việc dành cho thầu phụ đặc biệt. (5) Nhà thầu ghi cụ thể giá trị % công việc mà thầu phụ đặc biệt đảm nhận so với giá trị gói thầu. (6) Nhà thầu ghi cụ thể số hợp đồng hoặc văn bản thỏa thuận và đính kèm các hồ sơ này trong HSĐX. Mẫu 10C DANH SÁCH CÁC CÔNG TY CON, CÔNG TY THÀNH VIÊN ĐẢM NHẬN PHẦN CÔNG VIỆC CỦA GÓI THẦU(1) [BẢNG: Không tiêu đề] Ghi chú: (1) Trường hợp nhà thầu dự thầu là công ty mẹ (ví dụ như Tổng công ty) huy động công ty con, công ty thành viên thực hiện một phần công việc gói thầu thì phải kê khai cụ thể tại bảng này. Việc đánh giá kinh nghiệm thực hiện hợp đồng tương tự căn cứ vào giá trị, khối lượng công việc do công ty mẹ, công ty con đảm nhiệm trong gói thầu. Trường hợp nhà thầu dự thầu không phải là công ty mẹ thì không áp dụng Mẫu này. (2) Ghi cụ thể tên công ty con, công ty thành viên. (3) Ghi cụ thể phần công việc đảm nhận của công ty con, công ty thành viên. (4) Ghi cụ thể giá trị % công việc của công ty con, công ty thành viên đảm nhận so với giá thầu. Mẫu 11 BẢNG TIẾN ĐỘ THỰC HIỆN Nhà thầu đề xuất tiến độ thực hiện phù hợp với yêu cầu của Chủ đầu tư và phù hợp với đề xuất kỹ thuật của nhà thầu [BẢNG: Không tiêu đề] Ghi chú: (2), (3), (4), (5): Chủ đầu tư điền theo yêu cầu tại Chương IV. (6): Nhà thầu đề xuất. Phần 2. YÊU VẦU VỀ XÂY LẮP Chương IV. YÊU CẦU VỀ XÂY LẮP I. Giới thiệu về gói thầu 1. Phạm vi công việc của gói thầu. 2. Thời hạn hoàn thành. II. Yêu cầu về tiến độ thực hiện Nêu yêu cầu về thời gian từ khi khởi công đến khi hoàn thành hợp đồng theo ngày/tuần/tháng. Trường hợp ngoài yêu cầu thời hạn hoàn thành cho toàn bộ dự án còn có yêu cầu tiến độ hoàn thành cho từng hạng mục dự án thì lập bảng yêu cầu tiến độ hoàn thành. [BẢNG: Không tiêu đề] III. Yêu cầu về kỹ thuật/chỉ dẫn kỹ thuật 1. Quy định kỹ thuật chính xác và rõ ràng là một điều kiện tiên quyết để nhà thầu đáp ứng một cách thực tế và cạnh tranh các yêu cầu của Chủ đầu tư mà không đặt điều kiện cho HSĐX của nhà thầu. Quy định kỹ thuật phải được soạn thảo để không làm hạn chế cạnh tranh, đồng thời nêu rõ các yêu cầu về trình độ tay nghề, vật tư và hiệu suất sử dụng của các hàng hóa và dịch vụ được cung cấp. Quy định kỹ thuật cần yêu cầu rằng tất cả hàng hóa và vật tư được sử dụng trong dự án đều mới, chưa từng qua sử dụng, thuộc thế hệ mới nhất, đã đưa vào tất cả các cải tiến về thiết kế và vật liệu trừ khi được quy định khác đi trong hợp đồng. 2. Trong yêu cầu về mặt kỹ thuật không được đưa ra các điều kiện nhằm hạn chế sự tham gia của nhà thầu hoặc nhằm tạo lợi thế cho một hoặc một số nhà thầu gây ra sự cạnh tranh không bình đẳng, đồng thời cũng không đưa ra các yêu cầu quá cao dẫn đến làm tăng giá thầu. 3. Chủ đầu tư được đưa ra yêu cầu về ký mã hiệu, nhãn hiệu, xuất xứ cho nguyên nhiên vật liệu, vật tư, máy móc, thiết bị và các yếu tố đầu vào khác. Nhà thầu được chào theo ký mã hiệu, nhãn hiệu, xuất xứ các nguyên nhiên vật liệu, vật tư, máy móc, thiết bị và các yếu tố đầu vào khác theo quy định trong hồ sơ yêu cầu hoặc ký mã hiệu, nhãn hiệu, xuất xứ khác có chất lượng hàng hóa (đặc tính kỹ thuật, tính năng sử dụng) tương đương hoặc tốt hơn. 4. Yêu cầu về bảo hành, bảo trì, duy tu bảo dưỡng (nếu có); 5. Đấu thầu bền vững: Trường hợp có yêu cầu về đấu thầu bền vững thì Chủ đầu tư cần đưa ra quy định bảo đảm sự thân thiện với môi trường, xã hội (sử dụng vật tư, vật liệu xây dựng, thiết bị được chứng nhận nhãn năng lượng, nhãn sinh thái, vật liệu không nung, vật liệu bền vững, thân thiện môi trường, vật liệu có khả năng tái chế, tái sử dụng; biện pháp thi công nhằm hạn chế mức độ xả thải, rác thải, ô nhiễm môi trường, giảm thiểu tác động tiêu cực tới mặt bằng, khu vực thi công. ..) nhưng phải bảo đảm các quy định này là rõ ràng, không làm hạn chế sự tham gia của nhà thầu. 6. Đối với phạm vi công việc gói thầu áp dụng loại hợp đồng theo kết quả đầu ra, các yêu cầu về kỹ thuật do Chủ đầu tư đưa ra cần chú trọng vào sản phẩm đầu ra như tiêu chuẩn, quy cách, thông số kỹ thuật, chất lượng. .. của các công việc này. Chủ đầu tư cũng cần nêu các tiêu chuẩn thi công nhà thầu phải đáp ứng, nhà thầu có thể áp dụng các tiêu chuẩn khác nhưng phải chứng minh các tiêu chuẩn này tương đương hoặc cao hơn tiêu chuẩn do Chủ đầu tư yêu cầu. Về cơ bản, HSYC không cần nêu quy trình, phương pháp thực hiện dịch vụ cụ thể mà nhà thầu phải tuân theo. Nhà thầu được quyền đề xuất quy trình, phương pháp thực hiện mà nhà thầu thấy là thích hợp để thực hiện gói thầu. Yêu cầu về kỹ thuật cần thể hiện các mức độ đáp ứng yêu cầu về kết quả đầu ra tương ứng với số tiền bị giảm trừ giá trị thanh toán trong quá trình khai thác dự án; yêu cầu về chất lượng, độ bền dự án và các yêu cầu khác. IV. Các bản vẽ HSYC này gồm có các bản vẽ trong danh mục sau đây: [BẢNG: Không tiêu đề] Phần 3. ĐIỀU KIỆN HỢP ĐỒNG VÀ BIỂU MẪU HỢP ĐỒNG Căn cứ quy mô, tính chất, loại hợp đồng của gói thầu, Chủ đầu tư, tổ chuyên gia sử dụng các Chương VI, VII, VIII của Mẫu E-HSMT xây lắp một giai đoạn một túi hồ sơ ban hành kèm theo Thông tư số 79/2025/TT-BTC để xây dựng các Chương V. ĐIỀU KIỆN CHUNG, Chương VI. ĐIỀU KIỆN CỤ THỂ, Chương VII. BIỂU MẪU HỢP ĐỒNG cho phù hợp với quy định của Luật Đấu thầu, Nghị định số 214/2025/NĐ-CP. Trong quá trình thực hiện, trường hợp Thông tư số 79/2025/TT-BTC được sửa đổi, bổ sung hoặc thay thế thì áp dụng theo văn bản quy phạm pháp luật sửa đổi, bổ sung hoặc thay thế Thông tư số 79/2025/TT-BTC. Lưu ý: khi sử dụng cần thay đổi các thuật ngữ cho phù hợp như sau: - E-ĐKC thành ĐKC; - E-ĐKCT thành ĐKCT; - E-HSMT thành HSYC; - E-HSDT thành HSĐX.", "metadata": {"source_file": "01A. Mẫu HSYC Xây lắp.docx", "file_type": "bidding_document", "document_category": "construction", "extracted_at": "2025-10-30T19:54:40.828563", "file_size_bytes": 215777, "project_name": "/dự toán mua sắm]. 2. Nguồn vốn để thực hiện gói thầu: ______ [Ghi rõ nguồn vốn đã được xác định hoặc phê duyệt; trường hợp sử dụng vốn ODA, vốn vay ư", "package_name": "XÂY LẮP (Ban hành kèm theo Thông tư số 80/2025/TT-BTC ngày 08 tháng 8 năm 2025 của Bộ trưởng Bộ Tài chính) HỒ SƠ YÊU CẦU XÂY LẮP [BẢNG: Không tiêu đề]", "bidding_method": "CHỈ ĐỊNH THẦU", "owner": "___ [Ghi tên, địa chỉ Chủ đầu tư] mời nhà thầu nhận HSYC gói thầu ___ [Ghi tên gói thầu theo kế hoạch lựa chọn nhà thầu được duyệt] thuộc ___ [Ghi tên", "chunk_index": 0, "char_count": 83920, "word_count": 18617, "paragraph_count": 1, "doc_type": "bidding", "processed_at": "2025-10-30T19:54:40.904015", "total_chunks": 1, "document_type": "bidding_document", "file_path": "/home/sakana/Code/RAG-bidding/data/raw/Ho so moi thau/1. Mẫu HSYC/01A. Mẫu HSYC Xây lắp.docx", "bidding_type": "construction", "extraction_metadata": {"source_file": "01A. Mẫu HSYC Xây lắp.docx", "file_type": "bidding_document", "document_category": "construction", "extracted_at": "2025-10-30T19:54:40.828563", "file_size_bytes": 215777, "project_name": "/dự toán mua sắm].", "package_name": "XÂY LẮP", "bidding_method": "CHỈ ĐỊNH THẦU", "owner": "___ [Ghi tên, địa chỉ Chủ đầu tư] mời nhà thầu nhận HSYC gói thầu ___ [Ghi tên gói thầu theo kế hoạch lựa chọn nhà thầu được duyệt] thuộc ___ [Ghi tên dự án/dự toán mua sắm]."}, "parsing_metadata": {"bidding_type": null, "detected_sections": {"general_info": [], "technical_requirements": [], "evaluation_criteria": [], "contract_conditions": [], "bidding_process": [], "forms": [], "drawings": [], "bill_of_quantities": []}, "document_info": {"project_name": "/dự toán mua sắm]. 2. nguồn vốn để thực hiện gói thầu: ______ [ghi rõ nguồn vốn đã được xác định hoặ", "package_name": "xây lắp (ban hành kèm theo thông tư số 80/2025/tt-btc ngày 08 tháng 8 năm 2025 của bộ trưởng bộ tài", "owner": "___ [ghi tên, địa chỉ chủ đầu tư] mời nhà thầu nhận hsyc gói thầu ___ [ghi tên gói thầu theo kế hoạc"}, "statistics": {}}, "contract_value": "tương tự được tính theo dự án có giá trị cao nhất)", "duration": "gói thầu là: ____[Ghi thời gian cụ thể theo kế hoạ", "hierarchy": "HỒ SƠ MỜI THẦU > Phần 1 > Chương I > Mục 1 > Điều 16", "section_type": "scope_of_work", "has_tables": true, "table_count": 1, "table_types": ["bill_of_quantities"], "contains_forms": true, "contains_technical_specs": true, "contains_evaluation": true, "contains_monetary_values": true, "monetary_value_count": 7, "contains_time_references": true, "time_reference_count": 25, "entities": {"locations": ["các điểm a, b, c, d, e, và g Khoản 1 Điều 5 của Luậ", "các điểm a, b Khoản 2 và các điểm d, e Khoản 1 Điều", "Mục 8 Chương này; 5. Đề xuất về giá theo Mẫu 04A ho", "thời điểm 28 ngày trước ngày có thời điểm đóng thầu", "Chương IV và chào giá cho tất cả các công việc nêu", "Chương III. Mục 8. Thành phần đề xuất kỹ thuật Nhà", "Chương IV để chứng minh tính phù hợp của đề xuất đố", "Mục 6 Chương I phải được ký bởi người đại diện hợp", "bên cạnh hoặc tại trang đó của người ký đơn dự thầu", "thầu 1. HSĐX do nhà thầu nộp trực tiếp hoặc gửi đến", "thầu Chủ đầu tư tiến hành mở thầu bao gồm các nội d", "thầu bao gồm các thông tin quy định tại điểm a và đ", "thầu phải được ký xác nhận bởi đại diện của Chủ đầu", "thời điểm dự thầu, chưa xác định được thầu phụ thì", "Mục 12. 3 Chương này. Bản thân nhà thầu phải đáp ứn", "Mục này trên giá trị phần công việc mà thành viên l", "Mục 2. 3 Chương II. Trường hợp thầu phụ đặc biệt do", "Chương II. 2. Trong quá trình đánh giá, Chủ đầu tư", "cho nhà thầu chuẩn bị HSĐX]. Mục 15. Thông báo kết", "thời điểm ký kết, HSĐX của nhà thầu trúng thầu còn", "thời điểm ký kết hợp đồng, nhà thầu trúng thầu phải", "Nghị quyết của Quốc hội hoặc văn bản quy phạm pháp", "Mục 6 Chương I; c) Kiểm tra sự thống nhất nội dung", "Mục 9 Chương I; d) Có thỏa thuận liên danh (trong t", "Mẫu 04 (04A hoặc 04B hoặc 04C hoặc 04D hoặc 04E) Ch", "Mục 3 Chương I; e) Trong thời hạn 03 năm trước thời", "thời điểm nhân sự thực hiện hành vi vi phạm) bị Tòa", "Mục 2. 1, 2. 2 và 2. 3. Năng lực và kinh nghiệm của", "Việt Nam] tại ngày ký hợp đồng tương tự đó. Trường", "Khoản 1 Điều 133 của Nghị định số 214/2025/NĐ-CP th", "báo cáo tài chính của nhà thầu. Trường hợp thời điể", "báo cáo tài chính năm trước của năm Y (năm Y-1). Ví", "bảo cáo tài chính năm 2022. Đối với nhà thầu là hộ", "lên thì cách tính doanh thu như sau: Yêu cầu tối th", "lên, yêu cầu về nguồn lực tài chính cho gói thầu đư", "Khoản 8 Điều 16 của Luật Đấu thầu thì hợp đồng này", "Thông tư sửa đổi, bổ sung, thay thế Thông tư số 06/", "thời điểm phê duyệt dự án đầu tư xây dựng dự án. Ch", "các địa phương mà năng lực của nhà thầu trên địa bà", "các địa phương mà năng lực của nhà thầu trên địa bà", "thời điểm phê duyệt dự án đầu tư xây dựng dự án. Ví", "Khoản 1 Điều 133 Nghị định số 214/2025/NĐ-CP. Kinh", "số năm tối thiểu nhân sự thực hiện các công việc tư", "Bảng này trong đó có nêu rõ yêu cầu về cấp dự án th", "thời điểm phê duyệt dự án đầu tư xây dựng dự án the", "Khoản 1 Điều 133 của Nghị định số 214/2025/NĐ-CP. N", "Mục này. Trường hợp không huy động được nhân sự chủ", "Mục 12 Chương I. Kinh nghiệm cụ thể và nguồn lực tà", "Chương IV, thông tin về kết quả thực hiện hợp đồng", "Mục 14 Chương I; Chương III. BIỂU MẪU Mẫu 01 ĐƠN DỰ", "thời điểm nhân sự thực hiện hành vi vi phạm) bị tòa", "và các hành vi vi phạm quy định khác của pháp luật", "các hồ sơ khác liên quan có phân công trách nhiệm c", "Mẫu 04 (04A hoặc 04B hoặc 04C hoặc 04D hoặc 04E) Ch", "Chương IV. Nhà thầu có trách nhiệm rà soát lại các", "phù hợp với mô tả công việc, bản vẽ và chi tiết kỹ", "chào giá thầu. (6) (7): Nhà thầu ghi đơn giá thầu,", "phù hợp với mô tả công việc, bản vẽ và chi tiết kỹ", "chào giá thầu. (6) (7) Nhà thầu ghi đơn giá thầu, t", "phù hợp với mô tả công việc, bản vẽ và chi tiết kỹ", "chào giá thầu. (6), (7): Nhà thầu ghi đơn giá thầu,", "Chương IV. (4) Nhà thầu có trách nhiệm phân bổ chi", "phù hợp với mô tả công việc, bản vẽ và chi tiết kỹ", "chào giá thầu. (6) (7) Nhà thầu ghi đơn giá thầu, t", "phù hợp với mô tả công việc, bản vẽ và chi tiết kỹ", "chào giá thầu. (6) (7) Nhà thầu ghi đơn giá thầu, t", "phù hợp với mô tả công việc, bản vẽ và chi tiết kỹ", "chào giá thầu. (6), (7): Nhà thầu ghi đơn giá thầu,", "chào giá. giá thầu cho phần công nhật được kết chuy", "công nhật trừ trường hợp có yêu cầu bằng văn bản củ", "về nơi xuất phát ban đầu, nhưng không bao gồm thời", "giá ghi trên hóa đơn cộng với các chi phí để giao v", "Công trường bao gồm chi phí vận chuyển, bảo hiểm, c", "Công trường đến địa điểm mà vật liệu được sử dụng s", "Công trường và được sử dụng vào công việc theo công", "phần Nhân công tính theo Công nhật. b) Chỉ có số gi", "chào thầu. (4), (5) Nhà thầu ghi đơn giá, thành tiề", "chào thầu. (4), (5) Nhà thầu ghi đơn giá, thành tiề", "chào thầu. (4), (5) Nhà thầu ghi đơn giá, thành tiề", "Mục 2. 1 Chương II để làm cơ sở đánh giá. Mẫu 07A B", "Khoản 1 Điều 133 của Nghị định số 214/2025/NĐ-CP. [", "Bảng trên. Mẫu 07C [BẢNG: BẢNG KINH NGHIỆM CHUYÊN M", "hữu của nhà thầu hoặc do nhà thầu huy động. Trường", "Khoản 1 Điều 133 của Nghị định số 214/2025/NĐ-CP. [", "hữu của mình thì nhà thầu phải kê khai thêm các thô", "số năm mà nhà thầu có số liệu tài chính. Nhà thầu p", "thời điểm đóng thầu. Mẫu 09B NGUỒN LỰC TÀI CHÍNH (1", "Mẫu này); - ĐTH là tổng yêu cầu về nguồn lực tài ch", "Mẫu 09C). Nhà thầu được đánh giá là đáp ứng yêu cầu", "tiêu chí đánh giá 3. 3 Bảng số 01: Tiêu chuẩn đánh", "Việt Nam, trong đó cam kết sẽ cung cấp tín dụng cho", "tiêu chí đánh giá 3. 3 Bảng số 01: Tiêu chuẩn đánh", "của nhà thầu (hoặc từng thành viên trong liên danh)", "thời điểm 28 ngày trước ngày có thời điểm đóng thầu", "thời điểm 28 ngày trước ngày có thời điểm đóng thầu", "Mục 12. 2 Chương I. Trường hợp nhà thầu liên danh,", "Mục 12. 2 Chương I. (6) Nhà thầu ghi cụ thể số hợp", "Mục 2. 3 Chương II. [BẢNG: Không tiêu đề] Ghi chú:", "bảng này. Việc đánh giá kinh nghiệm thực hiện hợp đ", "Chương IV. (6): Nhà thầu đề xuất. Phần 2. YÊU VẦU V"]}, "content_stats": {"char_count": 83920, "word_count": 18617, "line_count": 1, "paragraph_count": 1, "sentence_count": 610}}, "chunk_id": "chunk_000", "char_count": 83920, "level": "paragraph", "hierarchy": [], "parent_id": null, "parsed_sections": [], "tables": [{"start_line": 0, "end_line": 1, "content": "Mẫu 1A HỒ SƠ YÊU CẦU GÓI THẦU XÂY LẮP (Ban hành kèm theo Thông tư số 80/2025/TT-BTC ngày 08 tháng 8 năm 2025 của Bộ trưởng Bộ Tài chính) HỒ SƠ YÊU CẦU XÂY LẮP [BẢNG: Không tiêu đề] [BẢNG: Không tiêu đề] TỪ NGỮ VIẾT TẮT [BẢNG: Không tiêu đề] Phần 1. THỦ TỤC CHỈ ĐỊNH THẦU Chương I. CHỈ DẪN NHÀ THẦU Mục 1. Phạm vi gói thầu 1. Chủ đầu tư ___ [Ghi tên, địa chỉ Chủ đầu tư] mời nhà thầu nhận HSYC gói thầu ___ [Ghi tên gói thầu theo kế hoạch lựa chọn nhà thầu được duyệt] thuộc ___ [Ghi tên dự án/dự toán mua sắm]. 2. Nguồn vốn để thực hiện gói thầu: ______ [Ghi rõ nguồn vốn đã được xác định hoặc phê duyệt; trường hợp sử dụng vốn ODA, vốn vay ưu đãi nước ngoài thì phải ghi rõ tên nhà tài trợ và cơ cấu nguồn vốn, bao gồm vốn tài trợ, vốn đối ứng trong nước]. 3. Thời gian thực hiện gói thầu là: ____[Ghi thời gian cụ thể theo kế hoạch lựa chọn nhà thầu được duyệt], được tính từ ngày hợp đồng có hiệu lực đến ngày nghiệm thu hoàn thành dự án, không bao gồm thời gian hoàn thành nghĩa vụ bảo hành. Mục 2. Hành vi bị cấm trong đấu thầu Hành vi bị cấm trong đấu thầu là hành vi quy định tại Điều 16 của Luật Đấu thầu. Mục 3. Tư cách hợp lệ của nhà thầu 1. Nhà thầu là tổ chức có tư cách hợp lệ khi đáp ứng quy định tại các điểm a, b, c, d, e, và g Khoản 1 Điều 5 của Luật Đấu thầu. 2. Nhà thầu là hộ kinh doanh có tư cách hợp lệ khi đáp ứng quy định tại các điểm a, b Khoản 2 và các điểm d, e Khoản 1 Điều 5 của Luật Đấu thầu. Trường hợp pháp luật có liên quan quy định nhà thầu dự thầu, thực hiện hợp đồng phải độc lập với các tổ chức, cá nhân khác thì phải tuân thủ quy định đó. 3. Đáp ứng điều kiện về cấp doanh nghiệp: ____ [đối với các gói thầu theo trường hợp gói thầu có giá không quá 05 tỷ đồng thì ghi: “Là doanh nghiệp cấp nhỏ hoặc siêu nhỏ theo quy định của pháp luật về doanh nghiệp”. Trường hợp gói thầu có giá trên 05 tỷ đồng hoặc không quá 05 tỷ đồng nhưng chủ đầu tư xác định không có doanh nghiệp nhỏ, siêu nhỏ đáp ứng được yêu cầu thì ghi: “Không áp dụng\"]. Mục 4. Làm rõ, sửa đổi HSYC, khảo sát hiện trường 1. Trường hợp nhà thầu cần làm rõ HSYC, nhà thầu gửi văn bản đến Chủ đầu tư trong thời hạn tối thiểu 03 ngày làm việc trước ngày có thời điểm đóng thầu để đánh giá, xử lý. 2. Trường hợp sửa đổi HSYC, Chủ đầu tư có trách nhiệm gửi quyết định sửa đổi và các nội dung sửa đổi tới nhà thầu. Thời gian gửi văn bản sửa đổi HSYC đến nhà thầu là ___ [Ghi số ngày cụ thể, tối thiểu 03 ngày làm việc trước ngày có thời điểm đóng thầu và bảo đảm đủ thời gian để nhà thầu hoàn chỉnh HSĐX]; trường hợp không bảo đảm đủ thời gian như nêu trên thì phải gia hạn thời điểm đóng thầu. 3. Nhà thầu nên đi khảo sát hiện trường dự án cũng như khu vực liên quan và tự chịu trách nhiệm tìm hiểu mọi thông tin cần thiết để lập HSĐX cũng như thực hiện hợp đồng thi công dự án nếu trúng thầu. Toàn bộ chi phí đi khảo sát hiện trường do nhà thầu tự chi trả. Mục 5. Chi phí, đồng tiền, ngôn ngữ khi dự thầu 1. Nhà thầu phải chịu mọi chi phí liên quan đến quá trình dự thầu. 2. Đồng tiền dự thầu và đồng tiền thanh toán là VND. 3. HSĐX cũng như tất cả văn bản và hồ sơ liên quan đến HSĐX được viết bằng tiếng Việt. Các hồ sơ bổ trợ trong HSĐX có thể được viết bằng ngôn ngữ khác, đồng thời kèm theo bản dịch sang tiếng Việt. Trường hợp thiếu bản dịch, Chủ đầu tư có thể yêu cầu nhà thầu gửi bổ sung (nếu cần thiết). Mục 6. Thành phần của HSĐX HSĐX do nhà thầu chuẩn bị phải bao gồm: 1. Đơn dự thầu theo Mẫu 01 Chương III; 2. Thỏa thuận liên danh nếu là nhà thầu liên danh theo Mẫu 03 Chương III; 3. hồ sơ chứng minh tư cách hợp lệ, năng lực và kinh nghiệm của nhà thầu, của người ký đơn dự thầu; 4. Đề xuất kỹ thuật theo quy định tại Mục 8 Chương này; 5. Đề xuất về giá theo Mẫu 04A hoặc Mẫu 04B hoặc Mẫu 04C hoặc Mẫu 04D hoặc Mẫu 04E Chương III; 6. Các nội dung khác __ [Nêu các nội dung khác tùy theo tính chất, yêu cầu của gói thầu]. Mục 7. giá thầu 1. giá thầu là giá do nhà thầu chào trong đơn dự thầu bao gồm toàn bộ các chi phí (chưa tính giảm giá) để thực hiện gói thầu theo yêu cầu của HSYC, kể cả các loại thuế, phí, lệ phí (nếu có) áp theo thuế suất, mức phí, lệ phí tại thời điểm 28 ngày trước ngày có thời điểm đóng thầu. 2. Nhà thầu phải nộp HSĐX cho toàn bộ công việc được mô tả tại Chương IV và chào giá cho tất cả các công việc nêu trong bảng giá tương ứng quy định tại Chương III. Mục 8. Thành phần đề xuất kỹ thuật Nhà thầu phải nộp đề xuất kỹ thuật, trong đó mô tả cụ thể phương pháp thực hiện công việc, thiết bị, nhân sự, lịch biểu thực hiện và các thông tin cần thiết khác theo quy định tại Chương IV để chứng minh tính phù hợp của đề xuất đối với các yêu cầu công việc và thời hạn cần hoàn thành công việc. Mục 9. Hiệu lực của HSĐX 1. Thời gian có hiệu lực của HSĐX phải bảo đảm theo yêu cầu là ___ [Ghi rõ số ngày tuỳ thuộc quy mô, tính chất của gói thầu, bảo đảm thời gian có hiệu lực đến ngày ký kết hợp đồng] kể từ ngày có thời điểm đóng thầu. 2. Trong trường hợp cần thiết, trước khi hết thời hạn hiệu lực của HSĐX, Chủ đầu tư có thể đề nghị nhà thầu gia hạn hiệu lực của HSĐX. Việc đề nghị gia hạn và chấp thuận gia hạn phải được thể hiện bằng văn bản. Mục 10. Quy cách của HSĐX và chữ ký trong HSĐX 1. Nhà thầu phải chuẩn bị một bản gốc và ____bản chụp HSĐX [Ghi số lượng yêu cầu nhưng không quá 03 bản], ghi rõ\"bản gốc\"và\"bản chụp\" tương ứng. Nhà thầu cần ghi rõ tên gói thầu, tên nhà thầu, tên Chủ đầu tư bên ngoài túi đựng HSĐX. Nhà thầu phải chịu trách nhiệm về tính chính xác và phù hợp giữa bản chụp và bản gốc. Trường hợp có sự sai khác giữa bản gốc và bản chụp thì căn cứ vào bản gốc để đánh giá. 2. Tất cả các thành phần của HSĐX nêu tại Mục 6 Chương I phải được ký bởi người đại diện hợp pháp của nhà thầu. Trường hợp là nhà thầu liên danh thì HSĐX phải có chữ ký của đại diện hợp pháp của tất cả thành viên liên danh hoặc thành viên đại diện nhà thầu liên danh theo phân công trong thỏa thuận liên danh. 3. Những chữ được ghi thêm, ghi chèn vào giữa các dòng, những chữ bị tẩy xóa hoặc viết đè lên sẽ chỉ được coi là hợp lệ nếu có chữ ký ở bên cạnh hoặc tại trang đó của người ký đơn dự thầu. Mục 11. Thời điểm đóng thầu và mở thầu 1. HSĐX do nhà thầu nộp trực tiếp hoặc gửi đến địa chỉ của Chủ đầu tư [Ghi địa chỉ] nhưng phải bảo đảm Chủ đầu tư nhận được trước thời điểm đóng thầu: ___ giờ, ngày ___ tháng ___ năm ____ [Ghi thời điểm đóng thầu]. 2. Mở thầu Chủ đầu tư tiến hành mở thầu bao gồm các nội dung sau: a) Kiểm tra niêm phong; b) Thông tin về tên nhà thầu: - Tham dự độc lập hay liên danh; - Số lượng bản gốc, bản chụp; - giá thầu chào trong đơn dự thầu; - Giá trị giảm giá (nếu có); - Thời gian có hiệu lực của HSĐX; - Thời gian thực hiện gói thầu; - Các thông tin khác liên quan. Biên bản mở thầu bao gồm các thông tin quy định tại điểm a và điểm b khoản này. Biên bản mở thầu phải được ký xác nhận bởi đại diện của Chủ đầu tư và nhà thầu nộp HSĐX. Biên bản này phải được gửi cho nhà thầu nộp HSĐX. Đại diện của Chủ đầu tư phải ký xác nhận vào bản gốc đơn dự thầu, thư giảm giá (nếu có), giấy ủy quyền của người đại diện theo pháp luật của nhà thầu (nếu có), thỏa thuận liên danh (nếu có), các nội dung đề xuất về tài chính và các nội dung quan trọng khác của HSĐX. Mục 12. thầu phụ 1. thầu phụ là tổ chức, cá nhân ký hợp đồng với nhà thầu để thực hiện một phần công việc trong bảng giá thầu; không bao gồm tổ chức, cá nhân cung cấp, nguyên liệu, nhiên liệu, vật liệu, vật tư, cấu kiện bán thành phẩm, thiết bị, cho thuê thiết bị thi công. Việc nhà thầu thuê nhân công để thực hiện gói thầu không phải là sử dụng thầu phụ. Trừ các phần công việc của gói thầu không được sử dụng thầu phụ bao gồm: ____ [Ghi “Không có” trong trường hợp không có quy định. Trường hợp có quy định thì ghi các phần công việc của gói thầu không cho phép sử dụng thầu phụ], nhà thầu được kê khai thầu phụ và các hạng mục công việc dành cho thầu phụ theo Mẫu 10A Chương III. Trường hợp tại thời điểm dự thầu, chưa xác định được thầu phụ thì phải kê khai các hạng mục công việc dự kiến dành cho thầu phụ. Việc sử dụng thầu phụ sẽ không làm thay đổi các trách nhiệm của nhà thầu. Nhà thầu phải chịu trách nhiệm về khối lượng, chất lượng, tiến độ và các trách nhiệm khác đối với phần công việc do thầu phụ thực hiện. Năng lực và kinh nghiệm của thầu phụ sẽ không được đánh giá khi đánh giá HSĐX của nhà thầu, trừ trường hợp quy định tại Mục 12. 3 Chương này. Bản thân nhà thầu phải đáp ứng các tiêu chí năng lực và kinh nghiệm (không xét đến năng lực và kinh nghiệm của thầu phụ). Nhà thầu được ký kết hợp đồng với các thầu phụ trong danh sách các thầu phụ nêu trong HSĐX hoặc ký với thầu phụ được Chủ đầu tư chấp thuận để tham gia thực hiện công việc xây lắp. 2. Nhà thầu chỉ được sử dụng thầu phụ thực hiện các công việc với tổng giá trị dành cho thầu phụ không vượt quá ___ tỷ lệ phần trăm (%) trên giá thầu của nhà thầu [tùy theo quy mô, tính chất gói thầu, Chủ đầu tư ghi tỷ lệ % tối đa dành cho thầu phụ]. Đối với trường hợp liên danh, từng thành viên liên danh chỉ được sử dụng thầu phụ không vượt quá tỷ lệ phần trăm quy định tại Mục này trên giá trị phần công việc mà thành viên liên danh đó đảm nhận trong thoả thuận liên danh. 3. thầu phụ đặc biệt ___ [Ghi được phép sử dụng hoặc không được phép sử dụng]. Trong trường hợp được phép sử dụng thầu phụ đặc biệt, nhà thầu phải kê khai danh sách thầu phụ đặc biệt theo Mẫu 10B Chương III và kê khai về năng lực, kinh nghiệm của thầu phụ đặc biệt. Tổ chuyên gia sẽ đánh giá năng lực, kinh nghiệm của thầu phụ đặc biệt theo tiêu chuẩn đánh giá quy định tại Mục 2. 3 Chương II. Trường hợp thầu phụ đặc biệt do nhà thầu đề xuất trong HSĐX không đáp ứng yêu cầu của HSYC (hoặc không đề xuất thầu phụ đặc biệt) và nhà thầu có năng lực, kinh nghiệm không đáp ứng yêu cầu thực hiện phần công việc đã dành cho thầu phụ đặc biệt thì nhà thầu được phép đề xuất thầu phụ đặc biệt hoặc thay thế thầu phụ đặc biệt khác đáp ứng yêu cầu. Khi sử dụng thầu phụ đặc biệt, nhà thầu không bắt buộc phải đáp ứng yêu cầu về năng lực, kinh nghiệm đối với phần công việc giao cho thầu phụ đặc biệt. Mục 13. Đánh giá HSĐX và thương thảo về các đề xuất của nhà thầu 1. Việc đánh giá HSĐX được thực hiện theo quy định tại Chương II. 2. Trong quá trình đánh giá, Chủ đầu tư mời nhà thầu thương thảo về giá bảo đảm đáp ứng tỷ lệ tiết kiệm theo quy định của HSYC, thương thảo, làm rõ hoặc sửa đổi, bổ sung nội dung HSĐX để chứng minh việc đáp ứng yêu cầu về năng lực, kinh nghiệm, tiến độ, khối lượng, chất lượng, giải pháp kỹ thuật, biện pháp tổ chức thực hiện gói thầu và tỷ lệ tiết kiệm. Mục 14. Điều kiện đối với nhà thầu được đề nghị chỉ định thầu Nhà thầu được đề nghị chỉ định thầu khi đáp ứng đầy đủ điều kiện sau đây: 1. Có HSĐX hợp lệ; 2. Có năng lực, kinh nghiệm và đề xuất kỹ thuật đáp ứng yêu cầu của HSYC; 3. Có giá đề nghị trúng thầu không vượt giá gói thầu được duyệt và đáp ứng tỷ lệ tiết kiệm tối thiểu ___ % giá gói thầu. [Căn cứ quy mô, tính chất, điều kiện cụ thể của gói thầu, Chủ đầu tư quy định trong HSYC mức tỷ lệ tiết kiệm của giá đề nghị trúng thầu để làm cơ sở cho nhà thầu chuẩn bị HSĐX]. Mục 15. Thông báo kết quả lựa chọn nhà thầu Trong thời hạn 05 ngày làm việc kể từ ngày kết quả lựa chọn nhà thầu được phê duyệt, Chủ đầu tư đăng tải thông tin về kết quả lựa chọn nhà thầu lên Hệ thống mạng đấu thầu quốc gia; gửi văn bản thông báo kết quả lựa chọn nhà thầu cho nhà thầu dự thầu. Nội dung thông báo kết quả lựa chọn nhà thầu như sau: a) Thông tin về gói thầu: - Tên gói thầu; - Giá gói thầu hoặc dự toán được duyệt (nếu có); - Tên Chủ đầu tư; - Hình thức lựa chọn nhà thầu; - Loại hợp đồng. - Thời gian thực hiện gói thầu. b) Thông tin về nhà thầu trúng thầu: - Tên nhà thầu; - Mã số thuế (nếu có); - giá thầu; - Giá trúng thầu; - Thời gian thực hiện gói thầu; - Thời gian thực hiện hợp đồng. c) Kế hoạch hoàn thiện, ký kết hợp đồng với nhà thầu trúng thầu. Mục 16. Điều kiện ký kết hợp đồng 1. Tại thời điểm ký kết, HSĐX của nhà thầu trúng thầu còn hiệu lực. 2. Tại thời điểm ký kết hợp đồng, nhà thầu trúng thầu phải bảo đảm đáp ứng yêu cầu về năng lực kỹ thuật, tài chính để thực hiện gói thầu theo yêu cầu của HSYC. Trường hợp thực tế nhà thầu không còn đáp ứng cơ bản yêu cầu về năng lực kỹ thuật, tài chính theo quy định nêu trong HSYC thì Chủ đầu tư sẽ từ chối ký kết hợp đồng với nhà thầu và hủy quyết định phê duyệt kết quả lựa chọn nhà thầu. 3. Chủ đầu tư phải bảo đảm các điều kiện về vốn tạm ứng, vốn thanh toán, mặt bằng thực hiện và điều kiện cần thiết khác để triển khai thực hiện gói thầu theo đúng tiến độ. Mục 17. Bảo đảm thực hiện hợp đồng 1. Trước hoặc cùng thời điểm hợp đồng có hiệu lực, nhà thầu được chỉ định thầu phải cung cấp bảo đảm thực hiện hợp đồng theo quy định của HSYC. Trường hợp nhà thầu sử dụng thư bảo lãnh thực hiện hợp đồng thì phải sử dụng Mẫu thư bảo lãnh trong HSYC này hoặc Mẫu thư bảo lãnh khác được Chủ đầu tư chấp thuận. 2. Nhà thầu không được hoàn trả bảo đảm thực hiện hợp đồng trong trường hợp sau đây: a) Từ chối thực hiện hợp đồng khi hợp đồng đã có hiệu lực; b) Vi phạm thỏa thuận trong hợp đồng; c) Thực hiện hợp đồng chậm tiến độ do lỗi của nhà thầu nhưng từ chối gia hạn hiệu lực của bảo đảm thực hiện hợp đồng. Mục 18. Giải quyết kiến nghị 1. Đối với gói thầu thuộc phạm vi điều chỉnh của Luật Đấu thầu: a) Khi thấy quyền và lợi ích hợp pháp bị ảnh hưởng, nhà thầu được kiến nghị người có thẩm quyền, Chủ đầu tư, Hội đồng giải quyết kiến nghị đánh giá lại các vấn đề trong quá trình lựa chọn nhà thầu, kết quả lựa chọn nhà thầu theo quy định tại Điều 89 Luật Đấu thầu và các Điều 137, 138 và 139 của Nghị định số 214/2025/NĐ-CP. b) Địa chỉ nhận đơn kiến nghị: - Địa chỉ nhận đơn kiến nghị của Chủ đầu tư: ___ [ghi đầy đủ tên, địa chỉ, số điện thoại, email]; - Địa chỉ nhận đơn kiến nghị của người có thẩm quyền: ___ [ghi đầy đủ tên, địa chỉ, số điện thoại, email]; - Địa chỉ bộ phận thường trực giúp việc của Hội đồng giải quyết kiến nghị: ___ [ghi đầy đủ tên, địa chỉ, số điện thoại, email]. 2. Đối với hoạt động lựa chọn nhà thầu quy định tại điểm d Khoản 7 Điều 3 của Luật Đấu thầu hoặc hoạt động lựa chọn nhà thầu không thuộc phạm vi điều chỉnh của Luật Đấu thầu: Khi thấy quyền và lợi ích hợp pháp bị ảnh hưởng, nhà thầu, cơ quan, tổ chức được kiến nghị theo quy trình sau: ___ [ghi cụ thể quy trình, thủ tục của việc giải quyết kiến nghị của đơn vị, tổ chức đồng thời ghi rõ email, địa chỉ của cá nhân/tổ chức/đơn vị giải quyết kiến nghị]. Mục 19. Ưu đãi trong lựa chọn nhà thầu Ưu đãi: _____ [Chủ đầu tư ghi rõ đối tượng, điều kiện ưu đãi theo quy định tại Nghị quyết của Quốc hội hoặc văn bản quy phạm pháp luật (nếu có)]. Chương II. TIÊU CHUẨN ĐÁNH GIÁ HSĐX Mục 1. Đánh giá tính hợp lệ của HSĐX 1. 1. Kiểm tra HSĐX a) Kiểm tra số lượng bản gốc, bản chụp HSĐX; b) Kiểm tra các thành phần của HSĐX theo quy định tại Mục 6 Chương I; c) Kiểm tra sự thống nhất nội dung giữa bản gốc và bản chụp để phục vụ quá trình đánh giá chi tiết HSĐX. 1. 2. Đánh giá tính hợp lệ của HSĐX HSĐX của nhà thầu được đánh giá là hợp lệ khi đáp ứng đầy đủ các nội dung sau đây: a) Có bản gốc HSĐX; b) Có đơn dự thầu được đại diện hợp pháp của nhà thầu ký tên, đóng dấu (nếu có) theo yêu cầu của HSYC; thời gian ký đơn dự thầu phải sau thời điểm phát hành HSYC; không đề xuất các giá thầu khác nhau hoặc có kèm theo điều kiện gây bất lợi cho Chủ đầu tư. Đối với nhà thầu liên danh, đơn dự thầu phải do đại diện hợp pháp của từng thành viên liên danh ký tên, đóng dấu (nếu có) hoặc thành viên được phân công thay mặt liên danh ký đơn dự thầu theo phân công trách nhiệm trong thỏa thuận liên danh; c) Hiệu lực của HSĐX đáp ứng yêu cầu theo quy định tại Mục 9 Chương I; d) Có thỏa thuận liên danh (trong trường hợp liên danh) được đại diện hợp pháp của từng thành viên liên danh ký tên, đóng dấu (nếu có); thỏa thuận liên danh phải nêu rõ nội dung công việc cụ thể và ước tính giá trị tương ứng mà từng thành viên trong liên danh sẽ thực hiện. Việc phân chia công việc trong liên danh phải căn cứ các hạng mục nêu trong bảng giá thầu quy định tại Mẫu 04 (04A hoặc 04B hoặc 04C hoặc 04D hoặc 04E) Chương III hoặc theo các công việc thuộc quá trình sản xuất hạng mục trong bảng giá thầu; không được phân chia các công việc không thuộc các hạng mục này hoặc không thuộc quá trình sản xuất các hạng mục này; đ) Nhà thầu bảo đảm tư cách hợp lệ theo quy định tại Mục 3 Chương I; e) Trong thời hạn 03 năm trước thời điểm đóng thầu, nhà thầu không có nhân sự (ký kết hợp đồng lao động với nhà thầu tại thời điểm nhân sự thực hiện hành vi vi phạm) bị Tòa án kết án có hành vi vi phạm quy định về đấu thầu gây hậu quả nghiêm trọng theo quy định của pháp luật về hình sự nhằm mục đích cho nhà thầu đó trúng thầu. Nhà thầu có HSĐX hợp lệ được đánh giá, đánh giá trong bước tiếp theo. Mục 2. Tiêu chuẩn đánh giá về năng lực và kinh nghiệm Nhà thầu được đánh giá là đạt về năng lực và kinh nghiệm khi đáp ứng tiêu chuẩn đánh giá quy định tại Mục 2. 1, 2. 2 và 2. 3. Năng lực và kinh nghiệm của thầu phụ (trừ thầu phụ đặc biệt) sẽ không được đánh giá khi đánh giá HSĐX của nhà thầu. Bản thân nhà thầu phải đáp ứng các tiêu chí đánh giá về năng lực và kinh nghiệm. 2. 1. Tiêu chuẩn đánh giá về năng lực và kinh nghiệm Tiêu chuẩn đánh giá năng lực và kinh nghiệm thực hiện theo Bảng số 01 Chương này, nhà thầu được đánh giá là đạt về năng lực và kinh nghiệm khi đáp ứng tất cả các tiêu chuẩn đánh giá. Trường hợp đồng tiền nêu trong các hợp đồng tương tự hoặc xác nhận thanh toán của Chủ đầu tư đối với những hợp đồng xây lắp đã thực hiện hoặc tờ khai nộp thuế hoặc các hồ sơ liên quan chứng minh năng lực, kinh nghiệm của nhà thầu không phải VND thì khi lập HSĐX, nhà thầu phải quy đổi về VND để làm cơ sở đánh giá HSĐX. Việc quy đổi được áp dụng tỷ giá quy đổi của ____ [ghi căn cứ xác định tỷ giá quy đổi, thông thường áp dụng tỷ giá bán ra của một ngân hàng thương mại hoạt động tại Việt Nam] tại ngày ký hợp đồng tương tự đó. Trường hợp nhà thầu dự thầu là công ty mẹ (ví dụ như Tổng công ty) có huy động công ty con, công ty thành viên thực hiện một phần công việc của gói thầu thì nhà thầu phải kê khai cụ thể phần công việc dành cho các công ty con, công ty thành viên theo Mẫu 10C Chương III. Việc đánh giá kinh nghiệm thực hiện hợp đồng tương tự căn cứ vào giá trị, khối lượng công việc do công ty mẹ, công ty con, công ty thành viên đảm nhiệm trong gói thầu. Bảng số 01 [BẢNG: BẢNG TIÊU CHUẨN ĐÁNH GIÁ VỀ NĂNG LỰC VÀ KINH NGHIỆM] Ghi chú: (1) Ghi thời gian yêu cầu, thông thường là 03 trước năm có thời điểm đóng thầu. Ví dụ: từ ngày 01 tháng 01 năm 2022 đến thời điểm đóng thầu. (2) Hợp đồng xây lắp, EPC, EC, PC, chìa khóa trao tay không hoàn thành do lỗi của nhà thầu bao gồm: - Hợp đồng bị Chủ đầu tư kết luận nhà thầu không hoàn thành và nhà thầu không phản đối; - Hợp đồng bị Chủ đầu tư kết luận nhà thầu không hoàn thành, không được nhà thầu chấp thuận nhưng đã được trọng tài hoặc tòa án kết luận theo hướng bất lợi cho nhà thầu. Các hợp đồng không hoàn thành không bao gồm các hợp đồng mà quyết định của Chủ đầu tư đã bị bác bỏ bằng cơ chế giải quyết tranh chấp. Việc xác định hợp đồng không hoàn thành phải dựa trên tất cả những thông tin về tranh chấp hoặc kiện tụng được giải quyết theo quy định của cơ chế giải quyết tranh chấp của hợp đồng tương ứng và khi mà nhà thầu đã hết tất cả các cơ hội có thể khiếu nại. Đối với các hợp đồng chậm tiến độ do lỗi của nhà thầu nhưng vẫn hoàn thành hợp đồng thì không được coi là hợp đồng không hoàn thành. Đối với nhà thầu liên danh mà chỉ có một hoặc một số thành viên trong liên danh vi phạm và bị cấm tham gia hoạt động đấu thầu theo quy định tại Khoản 1 Điều 133 của Nghị định số 214/2025/NĐ-CP thì thành viên liên danh còn lại không bị coi là không hoàn thành hợp đồng do lỗi của nhà thầu. Trường hợp một hoặc một số thành viên liên danh vi phạm hợp đồng, không còn năng lực để tiếp tục thực hiện hợp đồng, làm ảnh hưởng nghiêm trọng đến tiến độ, chất lượng, hiệu quả của gói thầu thì chỉ một hoặc một số thành viên liên danh vi phạm hợp đồng bị coi là không hoàn thành hợp đồng, thành viên còn lại không bị coi là không hoàn thành hợp đồng do lỗi của nhà thầu. (3) Nhà thầu cung cấp hồ sơ chứng minh đã thực hiện nghĩa vụ kê khai thuế và nộp thuế thu nhập doanh nghiệp (thuế thu nhập cá nhân đối với nhà thầu là hộ kinh doanh) của năm tài chính gần nhất so với thời điểm đóng thầu. Nghĩa vụ kê khai thuế và nộp thuế phải được thực hiện trước thời điểm đóng thầu. Nghĩa vụ nộp thuế là nộp thuế với giá trị thuế tương ứng với thuế suất, thu nhập chịu thuế, doanh thu tính thuế nhà thầu kê khai trên Hệ thống thuế điện tử (số thuế đã nộp tương ứng với số thuế phải nộp); trường hợp được chậm nộp thuế, miễn thuế, giảm thuế theo chính sách của Nhà nước thì thực hiện theo quy định này. Nhà thầu nộp các hồ sơ như sau: - Tờ khai thuế (hoặc thông báo nộp tiền của cơ quan thuế đối với hộ kinh doanh) và Giấy nộp tiền có xác nhận của cơ quan thuế được in từ Hệ thống thuế điện tử hoặc - Tờ khai thuế (hoặc thông báo nộp tiền của cơ quan thuế đối với hộ kinh doanh) và xác nhận của cơ quan thuế về việc thực hiện nghĩa vụ thuế. Trường hợp thời điểm đóng thầu sau ngày kết thúc năm tài chính của nhà thầu (năm Y) và trước hoặc trong ngày cuối cùng của tháng thứ 3 tính từ ngày kết thúc năm Y, yêu cầu đã thực hiện nghĩa vụ kê khai thuế và nộp thuế áp dụng đối với năm tài chính trước năm Y (năm Y-1). (Ví dụ: Thời điểm đóng thầu là ngày 20/3/2024, năm tài chính của nhà thầu là 01/01 - 31/12 thì nhà thầu phải chứng minh đã thực hiện nghĩa vụ kê khai thuế và nộp thuế của năm 2022). (4) Việc xác định giá trị tài sản ròng được thực hiện trên cơ sở báo cáo tài chính của nhà thầu. Trường hợp thời điểm đóng thầu sau ngày kết thúc năm tài chính của nhà thầu (năm Y) và trước hoặc trong ngày cuối cùng của tháng thứ 3 tính từ ngày kết thúc năm Y, việc xác định giá trị tài sản ròng của nhà thầu được thực hiện trên cơ sở báo cáo tài chính năm trước của năm Y (năm Y-1). Ví dụ: Ngày có thời điểm đóng thầu là ngày 20/3/2024, năm tài chính của nhà thầu là 01/01 - 31/12 và HSYC yêu cầu nhà thầu nộp báo cáo tài chính của 03 năm gần nhất thì việc xác định giá trị tài sản ròng của nhà thầu được thực hiện trên cơ sở bảo cáo tài chính năm 2022. Đối với nhà thầu là hộ kinh doanh thì không đánh giá tiêu chí này. (5) Ghi thời gian yêu cầu, thông thường từ 03 năm đến 05 năm trước năm có thời điểm đóng thầu. Trường hợp nhà thầu có số năm thành lập ít hơn số năm theo yêu cầu của HSYC thì doanh thu bình quân hằng năm (không bao gồm thuế VAT) được tính trên số năm mà nhà thầu thành lập. Trường hợp doanh thu bình quân hằng năm (không bao gồm thuế VAT) của nhà thầu đáp ứng yêu cầu về giá trị của HSYC thì nhà thầu vẫn được đánh giá tiếp mà không bị loại. Đối với nhà thầu là hộ kinh doanh, không bắt buộc phải nộp báo cáo tài chính nhưng nhà thầu phải cung cấp hồ sơ chứng minh doanh thu tương ứng với nghĩa vụ thuế. Trường hợp thời điểm đóng thầu sau ngày kết thúc năm tài chính của nhà thầu (năm Y) và trước hoặc trong ngày cuối cùng của tháng thứ 3 tính từ ngày kết thúc năm Y, yêu cầu về nộp báo cáo tài chính áp dụng đối với các năm trước của năm Y (năm Y-1, Y-2. ..). Ví dụ: - Ngày có thời điểm đóng thầu là ngày 20/3/2024, năm tài chính của nhà thầu là 01/01 - 31/12 và HSYC yêu cầu nhà thầu nộp báo cáo tài chính của 03 năm gần nhất thì nhà thầu phải nộp báo cáo tài chính của các năm 2020, 2021, 2022). - Doanh thu bình quân hằng năm (không bao gồm thuế VAT) của 03 năm tài chính gần nhất so với thời điểm đóng thầu. Trong trường hợp này, thời điểm đóng thầu là ngày 15/11/2024 thì nhà thầu phải nộp báo cáo tài chính của các năm 2021, 2022, 2023. Nhà thầu được thành lập vào năm 2022 nhưng doanh thu trung bình của năm 2022 và năm 2023 đáp ứng yêu cầu thì nhà thầu được tiếp tục đánh giá. (6) Cách tính toán thông thường về mức yêu cầu doanh thu bình quân hằng năm (không bao gồm thuế VAT): a) Trường hợp thời gian thực hiện gói thầu từ 12 tháng trở lên thì cách tính doanh thu như sau: Yêu cầu tối thiểu về mức doanh thu bình quân hằng năm (không bao gồm thuế VAT) = [(Giá gói thầu - giá trị thuế VAT)/thời gian thực hiện gói thầu theo năm] x k. Thông thường yêu cầu hệ số k trong công thức này là từ 1, 5 đến 2; b) Trường hợp thời gian thực hiện gói thầu dưới 12 tháng thì cách tính doanh thu như sau: Yêu cầu tối thiểu về mức doanh thu bình quân hằng năm (không bao gồm thuế VAT) = (Giá gói thầu - giá trị thuế VAT) x k. Thông thường yêu cầu hệ số “k” trong công thức này là 1, 5. (7) Tài sản có khả năng thanh khoản cao là tiền mặt và tương đương tiền mặt, các công cụ tài chính ngắn hạn, các chứng khoán sẵn sàng để bán, chứng khoán dễ bán, các khoản phải thu thương mại, các khoản phải thu tài chính ngắn hạn và các tài sản khác mà có thể chuyển đổi thành tiền mặt trong vòng một năm. Trường hợp HSYC có yêu cầu về cam kết cung cấp tín dụng và nhà thầu sử dụng cam kết này để chứng minh nguồn lực tài chính thì nhà thầu phải đính kèm cam kết cung cấp tín dụng trong HSĐX. (8) Yêu cầu về nguồn lực tài chính cho gói thầu: a) Đối với gói thầu có thời gian thực hiện gói thầu từ 12 tháng trở lên, yêu cầu về nguồn lực tài chính cho gói thầu được xác định theo công thức sau: Yêu cầu về nguồn lực tài chính cho gói thầu = t x (Giá gói thầu/thời gian thực hiện gói thầu (tính theo tháng)). Thông thường yêu cầu hệ số “t” trong công thức này là 3. b) Đối với gói thầu có thời gian thực hiện gói thầu dưới 12 tháng, yêu cầu về nguồn lực tài chính cho gói thầu được xác định theo công thức sau: Yêu cầu về nguồn lực tài chính cho gói thầu = 30% x Giá gói thầu. (9) Trường hợp gói thầu gồm dự án và hạng mục theo quy định của pháp luật về xây dựng thì chỉ nêu yêu cầu về hợp đồng tương tự đối với dự án. Đối với các hợp đồng tương tự mà nhà thầu đã tham gia với tư cách là thành viên liên danh hoặc thầu phụ thì chỉ tính giá trị phần việc do nhà thầu thực hiện. Đối với các hợp đồng mà Chủ đầu tư, tổ chuyên gia có bằng chứng cho thấy nhà thầu đã thực hiện với tư cách thầu phụ do được chuyển nhượng thầu bất hợp pháp, vi phạm quy định tại Khoản 8 Điều 16 của Luật Đấu thầu thì hợp đồng này sẽ không được đánh giá, đánh giá. (10) Ghi năm yêu cầu, thông thường từ 03 năm đến 05 năm trước năm có thời điểm đóng thầu. (11) Hoàn thành toàn bộ nghĩa là đã thực hiện xong toàn bộ công việc của dự án/hạng mục và được nghiệm thu; hoàn thành phần lớn nghĩa là đã hoàn thành và được nghiệm thu ít nhất 80% khối lượng công việc của dự án/hạng mục dự án. Thời điểm xác nhận dự án/hạng mục hoàn thành để xác định dự án/hạng mục tương tự là thời điểm nghiệm thu dự án/hạng mục, không căn cứ vào thời điểm ký kết hợp đồng. (12) Ghi loại kết cấu, cấp dự án của dự án thuộc gói thầu. Loại kết cấu, cấp dự án được xác định theo Phụ lục II Thông tư số 06/2021/TT-BXD ngày 30 tháng 6 năm 2021 của Bộ Xây dựng quy định về phân cấp dự án xây dựng và hướng dẫn áp dụng trong quản lý hoạt động đầu tư xây dựng. Trường hợp dự án/loại kết cấu dự án thuộc gói thầu không có trong Phụ lục II Thông tư số 06/2021/TT-BXD thì HSYC phải đưa ra quy định tính tương tự về bản chất của dự án; riêng đối với cấp dự án được xác định theo Phụ lục I Thông tư số 06/2021/TT-BXD. Trường hợp Thông tư số 06/2021/TT-BXD được sửa đổi, bổ sung, thay thế thì việc xác định loại, cấp dự án thực hiện theo quy định tại Thông tư sửa đổi, bổ sung, thay thế Thông tư số 06/2021/TT-BXD. Loại kết cấu, cấp dự án của nhà thầu thực hiện được xác định theo quy định của pháp luật xây dựng tại thời điểm phê duyệt dự án đầu tư xây dựng dự án. Chủ đầu tư, tổ chuyên gia không được đưa ra yêu cầu về hợp đồng tương tự đối với hạng mục trong trường hợp gói thầu chỉ gồm dự án hoặc cả dự án và hạng mục theo quy định của pháp luật về xây dựng (Ví dụ: yêu cầu hợp đồng tương tự đối với dự án giao thông cấp IV nhưng phải bao gồm hạng mục nền đắp đất, cấp phối đá dăm, mặt bê tông nhựa hoặc bê tông, rãnh thoát nước dọc, ngang, mái kè gia cố. ..). (13) Ghi giá trị của V, V1, V2, V3. Trong đó: - V có giá trị thông thường khoảng 50% giá trị công việc xây lắp của dự án thuộc gói thầu đang xét (dự án A). Đối với các công việc đặc thù hoặc ở các địa phương mà năng lực của nhà thầu trên địa bàn còn hạn chế, có thể yêu cầu giá trị V trong khoảng 40% - 50% giá trị công việc xây lắp của dự án A. - V1, V2, V3. .. có giá trị thông thường khoảng 50% giá trị của từng dự án/hạng mục tương ứng (A1, A2, A3. ..) thuộc gói thầu đang xét (bao gồm thuế, phí, lệ phí và chi phí dự phòng nếu có). Đối với các công việc đặc thù hoặc ở các địa phương mà năng lực của nhà thầu trên địa bàn còn hạn chế, có thể yêu cầu giá trị V1, V2, V3. .. trong khoảng 40% - 50% giá trị của dự án/hạng mục A1, A2, A3. .. - Việc đánh giá về giá trị của các dự án/hạng mục mà nhà thầu đã thực hiện, Tổ chuyên gia căn cứ vào giá trị hoàn thành, được nghiệm thu của dự án/hạng mục đó. Thời điểm xác nhận dự án/hạng mục hoàn thành để xác định dự án/hạng mục tương tự là thời điểm nghiệm thu dự án/hạng mục, không căn cứ vào thời điểm ký kết hợp đồng. Hai dự án có cấp thấp hơn liền kề với cấp của dự án đang xét, giá trị hoàn thành mỗi dự án cấp thấp hơn liền kề bằng hoặc lớn hơn 50% giá trị của dự án đang xét thì được đánh giá là một dự án xây lắp tương tự. Ví dụ: Trường hợp dự án đang xét là dự án xây dựng có loại kết cấu dạng nhà cấp II với giá trị dự án là 60 tỷ đồng, nếu nhà thầu có 02 dự án xây dựng có loại kết cấu dạng nhà cấp III với giá trị đã hoàn thành toàn bộ hoặc hoàn thành phần lớn lần lượt là 30 tỷ đồng, 50 tỷ đồng thì được đánh giá là đã hoàn thành hoặc hoàn thành phần lớn một dự án dân dụng cấp II với giá trị 30 tỷ đồng. - Các dự án/hạng mục tương tự mà nhà thầu đã hoàn thành có thể thuộc một hoặc nhiều hợp đồng (hợp đồng có thể đang thực hiện, chưa thanh lý). - Đối với gói thầu gồm tổ hợp nhiều dự án theo pháp luật về xây dựng, Chủ đầu tư có thể yêu cầu phải hoàn thành dự án/hạng mục tương tự cho tất cả các dự án/hạng mục trong gói thầu hoặc chỉ yêu cầu hoàn thành dự án/hạng mục tương tự đối với một số dự án/hạng mục chính, trường hợp có một số dự án có cùng loại kết cấu thì chỉ yêu cầu về dự án/hạng mục tương tự đối với cùng loại kết cấu mà có cấp dự án cao nhất (trường hợp có nhiều dự án cùng loại kết cấu và cấp dự án thì giá trị hợp đồng tương tự được tính theo dự án có giá trị cao nhất). dự án/hạng mục mà nhà thầu đã hoàn thành có cùng loại kết cấu và có cấp dự án cao hơn cấp dự án của gói thầu đang xét thì được coi là đáp ứng yêu cầu về loại kết cấu và cấp dự án. Loại kết cấu, cấp dự án của dự án tương tự được xác định theo quy định của pháp luật xây dựng tại thời điểm phê duyệt dự án đầu tư xây dựng dự án. Ví dụ: Đối với gói thầu xây dựng “Trường trung học phổ thông A”, bao gồm tổ hợp các dự án: + Nhà A1 (Nhà học): Cao 10 tầng, tổng diện tích sàn 8. 000 m2, có giá trị theo dự toán được duyệt là (2X) VND. Nhà A1 là dự án kết cấu dạng nhà cấp II theo quy định của Thông tư số 06/2021/TT-BXD. + Nhà A2 (Nhà học): Cao 10 tầng, tổng diện tích sàn 5. 000 m2, có giá trị theo dự toán được duyệt là (X) VND. Nhà A2 là dự án kết cấu dạng nhà cấp II theo quy định của Thông tư số 06/2021/TT-BXD. + Nhà A3 (Nhà học): Cao 6 tầng, tổng diện tích sàn 1. 000 m2, có giá trị theo dự toán được duyệt là (Y) VND. Nhà A3 là dự án kết cấu dạng nhà cấp III theo quy định của Thông tư số 06/2021/TT-BXD. + Hàng rào bảo vệ: Cao 3 m + Nhà bảo vệ: Cao 1 tầng, diện tích sàn 12 m2 Trong HSYC có thể quy định kinh nghiệm thi công dự án tương tự là: “nhà thầu đã hoàn thành dự án xây dựng nhà, kết cấu dạng nhà cấp II, có giá trị tối thiểu là 50% x (2X) VND” mà không phải quy định nhà thầu phải có kinh nghiệm thực hiện cả các dự án xây dựng nhà A2, A3, hàng rào bảo vệ, nhà bảo vệ. Căn cứ quy mô, tính chất của gói thầu mà có thể yêu cầu tương tự về điều kiện hiện trường. (14) Nhà thầu quản lý là nhà thầu không trực tiếp thực hiện một phần hoặc toàn bộ các công việc của gói thầu mà ký hợp đồng với các nhà thầu khác để thực hiện nhưng nhà thầu vẫn quản lý việc thực hiện của các nhà thầu mà mình đã ký hợp đồng, đồng thời vẫn chịu toàn bộ trách nhiệm cũng như rủi ro liên quan đến giá thành, tiến độ thực hiện, chất lượng và các nội dung khác của gói thầu. 2. 2. Tiêu chuẩn đánh giá về năng lực kỹ thuật Nhà thầu được đánh giá là đạt về năng lực kỹ thuật khi đáp ứng tất cả các tiêu chuẩn đánh giá về nhân sự chủ chốt và thiết bị thi công chủ yếu dự kiến huy động để thực hiện gói thầu. a) Nhân sự chủ chốt Căn cứ quy mô, tính chất của gói thầu và pháp luật về xây dựng mà Chủ đầu tư đưa ra yêu cầu về nhân sự chủ chốt trong HSYC cho phù hợp như chỉ huy trưởng công trường, cán bộ phụ trách kỹ thuật, an toàn lao động và các vị trí công việc quan trọng khác. HSYC không được yêu cầu về nhân sự chủ chốt đối với các vị trí công nhân kỹ thuật, lao động phổ thông. Trường hợp HSYC có yêu cầu về nhân sự chủ chốt thì nhà thầu phải chứng minh khả năng huy động các nhân sự chủ chốt đã đề xuất. Nhân sự chủ chốt có thể thuộc biên chế của nhà thầu hoặc do nhà thầu huy động. Trường hợp nhân sự chủ chốt mà nhà thầu đề xuất trong HSĐX không đáp ứng yêu cầu hoặc không chứng minh được khả năng huy động nhân sự (bao gồm cả trường hợp nhân sự đã huy động cho hợp đồng khác có thời gian làm việc trùng với thời gian thực hiện gói thầu này) thì Chủ đầu tư cho phép nhà thầu bổ sung, thay thế. Trường hợp nhà thầu không có nhân sự chủ chốt thay thế đáp ứng yêu cầu của HSYC thì nhà thầu bị loại. Trường hợp nhà thầu cố ý kê khai nhân sự chủ chốt không trung thực trong HSĐX nhằm làm sai lệch kết quả lựa chọn nhà thầu thì nhà thầu không được thay thế nhân sự khác, HSĐX của nhà thầu bị loại và nhà thầu sẽ bị coi là gian lận theo quy định tại điểm b Khoản 4 Điều 16 Luật Đấu thầu và bị xử lý theo quy định tại Khoản 1 Điều 133 Nghị định số 214/2025/NĐ-CP. Kinh nghiệm trong các công việc tương tự được thể hiện ở số năm tối thiểu nhân sự thực hiện các công việc tương tự hoặc số hợp đồng tối thiểu trong các công việc tương tự. Số năm kinh nghiệm của nhân sự chủ chốt được tính từ thời điểm nhân sự bắt đầu thực hiện công việc tương tự đó đến thời điểm đóng thầu. Nhà thầu phải cung cấp thông tin chi tiết về các nhân sự chủ chốt được đề xuất theo các Mẫu 07A, 07B và 07C Chương III để chứng minh rằng mình có đầy đủ nhân sự cho các vị trí chủ chốt đáp ứng những yêu cầu sau đây: Bảng số 02: Yêu cầu về nhân sự chủ chốt [BẢNG: Không tiêu đề] Ghi chú: (1) Trường hợp pháp luật quản lý ngành, lĩnh vực có yêu cầu về điều kiện hành nghề đối với vị trí công việc nêu tại Bảng này trong đó có nêu rõ yêu cầu về cấp dự án thì cấp dự án theo hợp đồng mà nhân sự chủ chốt đã tham gia được xác định theo quy định của pháp luật xây dựng tại thời điểm phê duyệt dự án đầu tư xây dựng dự án theo hợp đồng này. (2) Chỉ quy định trong trường hợp pháp luật chuyên ngành có yêu cầu về bằng cấp/chứng chỉ chuyên môn. b) Thiết bị thi công chủ yếu dự kiến huy động để thực hiện gói thầu Căn cứ quy mô, tính chất của gói thầu, Chủ đầu tư đưa ra các yêu cầu về thiết bị thi công chủ yếu dự kiến huy động và số lượng để thực hiện gói thầu cho phù hợp. Chỉ quy định về thiết bị thi công chủ yếu đối với các thiết bị quan trọng, đặc chủng, đặc thù bắt buộc phải có để triển khai thi công gói thầu. Thiết bị thi công chủ yếu có thể của nhà thầu hoặc do nhà thầu huy động. Trường hợp thiết bị thi công chủ yếu mà nhà thầu đề xuất trong HSĐX không đáp ứng yêu cầu thì Chủ đầu tư cho phép nhà thầu bổ sung, thay thế. Trường hợp nhà thầu không có thiết bị thay thế đáp ứng yêu cầu của HSYC thì nhà thầu bị loại. Trường hợp nhà thầu cố ý kê khai thiết bị thi công chủ yếu không trung thực trong HSĐX nhằm làm sai lệch kết quả lựa chọn nhà thầu thì nhà thầu không được thay thế thiết bị khác, HSĐX của nhà thầu bị loại và nhà thầu sẽ bị coi là gian lận theo quy định tại điểm b Khoản 4 Điều 16 của Luật Đấu thầu và bị xử lý theo quy định tại Khoản 1 Điều 133 của Nghị định số 214/2025/NĐ-CP. Nhà thầu phải cung cấp thông tin chi tiết về các Thiết bị thi công chủ yếu được đề xuất theo Mẫu 07D Chương III để chứng minh rằng mình có đầy đủ thiết bị đáp ứng những yêu cầu sau đây: Bảng số 03: Yêu cầu về thiết bị thi công chủ yếu [BẢNG: Không tiêu đề] Trường hợp nhà thầu trúng thầu và ký kết hợp đồng, nhà thầu có nghĩa vụ huy động nhân sự chủ chốt, thiết bị thi công chủ yếu như đã đề xuất ban đầu hoặc đề xuất thay đổi theo quy định tại Mục này. Trường hợp không huy động được nhân sự chủ chốt, thiết bị thi công chủ yếu, nhà thầu bị phạt hợp đồng, bị đánh giá về uy tín khi tham gia các gói thầu khác. 2. 3. thầu phụ đặc biệt (nếu có) Tổ chuyên gia chỉ đánh giá, đánh giá về năng lực kỹ thuật và kinh nghiệm của thầu phụ đặc biệt cho phần công việc chuyên ngành được phép sử dụng thầu phụ đặc biệt quy định tại Mục 12 Chương I. Kinh nghiệm cụ thể và nguồn lực tài chính của thầu phụ đặc biệt sẽ không được cộng vào kinh nghiệm và nguồn lực của nhà thầu khi đánh giá kinh nghiệm, năng lực của nhà thầu. thầu phụ đặc biệt được đề xuất phải có đầy đủ kinh nghiệm, năng lực kỹ thuật để thực hiện công việc và phải đáp ứng các tiêu chí sau đây: ____[ghi các tiêu chí, tiêu chuẩn đánh giá đối với thầu phụ đặc biệt]. Mục 3. Tiêu chuẩn đánh giá về kỹ thuật Sử dụng tiêu chí đạt/không đạt để xây dựng tiêu chuẩn đánh giá về kỹ thuật. Đối với các tiêu chí đánh giá tổng quát, chỉ sử dụng tiêu chí đạt, không đạt. Căn cứ quy mô, tính chất của gói thầu mà xác định mức độ yêu cầu đối với từng nội dung. Đối với các tiêu chí chi tiết cơ bản trong tiêu chí tổng quát, chỉ sử dụng tiêu chí đạt, không đạt; đối với các tiêu chí chi tiết không cơ bản trong tiêu chí tổng quát, ngoài tiêu chí đạt, không đạt, được áp dụng thêm tiêu chí chấp nhận được nhưng không được vượt quá 30% tổng số các tiêu chí chi tiết trong tiêu chí tổng quát đó. Tiêu chí tổng quát được đánh giá là đạt khi tất cả các tiêu chí chi tiết cơ bản được đánh giá là đạt và các tiêu chí chi tiết không cơ bản được đánh giá là đạt hoặc chấp nhận được. Việc xây dựng tiêu chuẩn đánh giá về kỹ thuật dựa trên các nội dung quy định tại Chương IV, thông tin về kết quả thực hiện hợp đồng của nhà thầu theo quy định tại Điều 19 và Điều 20 của Nghị định số 214/2025/NĐ-CP và các yêu cầu khác nêu trong HSYC. Căn cứ vào từng gói thầu cụ thể, khi lập HSYC phải cụ thể hóa các tiêu chí làm cơ sở để đánh giá về kỹ thuật bao gồm: - Tính hợp lý và khả thi của các giải pháp kỹ thuật, biện pháp tổ chức thi công phù hợp với đề xuất về tiến độ thi công; - Tiến độ thi công; - Cách thức quản lý dự án bao gồm: tổ chức quản lý dự án, tổ chức quản lý hiện trường; các biện pháp bảo đảm chất lượng; bảo đảm điều kiện vệ sinh môi trường và các điều kiện khác như phòng cháy, chữa cháy, an toàn lao động; - Mức độ đáp ứng các yêu cầu về bảo hành, bảo trì; - Các yếu tố thân thiện môi trường (nếu có) gồm việc sử dụng các vật tư, vật liệu, biện pháp tổ chức thi công, dây chuyền, kỹ thuật thi công và các yếu tố khác (nếu có); - Thông tin về kết quả thực hiện hợp đồng của nhà thầu theo quy định tại Điều 19 và Điều 20 của Nghị định số 214/2025/NĐ-CP; - Các yếu tố cần thiết khác; Chủ đầu tư được đưa ra yêu cầu về ký mã hiệu, nhãn hiệu, xuất xứ cho nguyên nhiên vật liệu, vật tư, máy móc, thiết bị và các yếu tố đầu vào khác. Nhà thầu được chào theo ký mã hiệu, nhãn hiệu, xuất xứ các nguyên nhiên vật liệu, vật tư, máy móc, thiết bị và các yếu tố đầu vào khác theo quy định trong hồ sơ yêu cầu hoặc ký mã hiệu, nhãn hiệu, xuất xứ khác có chất lượng hàng hóa (đặc tính kỹ thuật, tính năng sử dụng) tương đương hoặc tốt hơn. Trừ trường hợp do tính chất của gói thầu mà HSYC yêu cầu nhà thầu phải thực hiện theo đúng biện pháp thi công nêu trong HSYC, HSYC cần quy định nhà thầu được đề xuất biện pháp thi công khác với biện pháp thi công nêu trong HSYC. HSĐX được đánh giá là đáp ứng yêu cầu về kỹ thuật khi có tất cả các tiêu chí tổng quát đều được đánh giá là đạt. Mục 4. Tiêu chuẩn đánh giá về tài chính Bước 1. Xác định giá thầu; Bước 2. Sửa lỗi, hiệu chỉnh sai lệch theo quy định tại Điều 31 của Nghị định số 214/2025/NĐ-CP (nếu có); Bước 3. Xác định giá thầu sau sửa lỗi, hiệu chỉnh sai lệch (nếu có), trừ đi giá trị giảm giá (nếu có) và đáp ứng tỷ lệ tiết kiệm theo quy định tại Mục 14 Chương I; Chương III. BIỂU MẪU Mẫu 01 ĐƠN DỰ THẦU ________, ngày ____ tháng ____ năm ____ Kính gửi: __________________ [Ghi tên Chủ đầu tư] (sau đây gọi là Chủ đầu tư) Sau khi nghiên cứu hồ sơ yêu cầu và văn bản sửa đổi hồ sơ yêu cầu số ____ [Ghi số của văn bản sửa đổi, nếu có] mà chúng tôi đã nhận được, chúng tôi, __[Ghi tên nhà thầu], có địa chỉ tại ______[Ghi địa chỉ của nhà thầu] cam kết thực hiện gói thầu__[Ghi tên gói thầu] theo đúng yêu cầu của hồ sơ yêu cầu với tổng số tiền là__[Ghi giá trị bằng số, bằng chữ và đồng tiền dự thầu] cùng với bảng giá thầu kèm theo. Thời gian thực hiện gói thầu là ____ [Ghi thời gian thực hiện tất cả các công việc theo yêu cầu của gói thầu]. Hồ sơ đề xuất này có hiệu lực trong thời gian ____ ngày, kể từ ngày ____ tháng ____ năm ____ [Ghi ngày có thời điểm đóng thầu]. Chúng tôi cam kết: 1. Không đang trong quá trình thực hiện thủ tục giải thể hoặc bị thu hồi giấy chứng nhận đăng ký doanh nghiệp, giấy chứng nhận đăng ký hợp tác xã, liên hiệp hợp tác xã, tổ hợp tác, không thuộc trường hợp mất khả năng thanh toán theo quy định của pháp luật về phá sản (không đang trong quá trình chấm dứt hoạt động hoặc bị thu hồi giấy chứng nhận đăng ký hộ kinh doanh đối với nhà thầu là hộ kinh doanh). 2. Đã thực hiện nghĩa vụ kê khai thuế và nộp thuế của năm tài chính gần nhất so với thời điểm đóng thầu; 3. Không đang trong thời gian bị cấm dự thầu theo quy định của pháp luật đấu thầu; 4. Không đang bị truy cứu trách nhiệm hình sự (chủ hộ không đang bị truy cứu trách nhiệm hình sự trong trường hợp nhà thầu là hộ kinh doanh); 5. Trong thời hạn 03 năm trước thời điểm đóng thầu, nhà thầu không có nhân sự (ký kết hợp đồng lao động với nhà thầu tại thời điểm nhân sự thực hiện hành vi vi phạm) bị tòa án kết án có hành vi vi phạm quy định về đấu thầu gây hậu quả nghiêm trọng theo quy định của pháp luật về hình sự nhằm mục đích cho nhà thầu trúng thầu(2). 6. Không thực hiện các hành vi tham nhũng, hối lộ, thông thầu, cản trở và các hành vi vi phạm quy định khác của pháp luật đấu thầu khi tham dự gói thầu này. 7. Những thông tin kê khai trong HSĐX là trung thực. 8. Trường hợp trúng thầu, HSĐX và các văn bản bổ sung, làm rõ HSĐX tạo thành thỏa thuận ràng buộc trách nhiệm giữa hai bên cho tới khi hợp đồng được ký kết. 9. Nếu HSĐX của chúng tôi được chấp nhận, chúng tôi sẽ thực hiện biện pháp bảo đảm thực hiện hợp đồng theo quy định của HSYC. Đại diện hợp pháp của nhà thầu(1) [Ghi tên, chức danh, ký tên và đóng dấu] Ghi chú: (1) Trường hợp đại diện theo pháp luật của nhà thầu ủy quyền cho cấp dưới ký đơn dự thầu thì phải gửi kèm theo Giấy ủy quyền theo Mẫu 02 Chương này. Trường hợp tại điều lệ công ty hoặc tại các hồ sơ khác liên quan có phân công trách nhiệm cho cấp dưới ký đơn dự thầu thì phải gửi kèm theo bản chụp các văn bản, hồ sơ này (không cần lập Giấy ủy quyền theo Mẫu 02 Chương này). (2) HSYC không được yêu cầu nhà thầu phải nộp lý lịch tư pháp của nhân sự để chứng minh cho nội dung đánh giá này. Nội dung này chỉ yêu cầu nhà thầu cam kết trong Đơn này. Mẫu 02 GIẤY ỦY QUYỀN(1) Hôm nay, ngày ____ tháng ____ năm ____, tại ____ Tôi là__[Ghi tên, số CCCD hoặc số hộ chiếu, chức danh của người đại diện theo pháp luật của nhà thầu], là người đại diện theo pháp luật của __ [Ghi tên nhà thầu] có địa chỉ tại_ [Ghi địa chỉ của nhà thầu] bằng văn bản này ủy quyền cho___ [Ghi tên, số CCCD hoặc số hộ chiếu, chức danh của người được ủy quyền] thực hiện các công việc sau đây trong quá trình dự thầu gói thầu__ [Ghi tên gói thầu] thuộc ___ [Ghi tên dự án/dự toán mua sắm] do___ [Ghi tên Chủ đầu tư] tổ chức: [- Ký đơn dự thầu; - Ký thỏa thuận liên danh (nếu có); - Ký các văn bản, hồ sơ để giao dịch với Chủ đầu tư trong quá trình dự thầu, kể cả văn bản giải trình, làm rõ HSĐX; - Tham gia quá trình thương thảo (nếu có), hoàn thiện hợp đồng; - Ký kết hợp đồng với Chủ đầu tư nếu được chỉ định thầu.] (2) Người được ủy quyền nêu trên chỉ thực hiện các công việc trong phạm vi ủy quyền với tư cách là đại diện hợp pháp của____ [Ghi tên nhà thầu]. ____ [Ghi tên nhà thầu] chịu trách nhiệm hoàn toàn về những công việc do ____ [Ghi tên người được ủy quyền] thực hiện trong phạm vi ủy quyền. Giấy ủy quyền có hiệu lực kể từ ngày ____ đến ngày ____(3). Giấy ủy quyền này được lập thành ____ bản có giá trị pháp lý như nhau, người ủy quyền giữ ____ bản, người được ủy quyền giữ ____ bản. [BẢNG: Không tiêu đề] Ghi chú: (1) Trường hợp ủy quyền thì bản gốc giấy ủy quyền phải được gửi cho Chủ đầu tư cùng với đơn dự thầu. Việc ủy quyền của người đại diện theo pháp luật của nhà thầu cho cấp phó, cấp dưới, giám đốc chi nhánh, người đứng đầu văn phòng đại diện của nhà thầu để thay mặt cho người đại diện theo pháp luật của nhà thầu thực hiện một hoặc các nội dung công việc nêu trên đây. Việc sử dụng con dấu trong trường hợp được ủy quyền có thể là dấu của nhà thầu hoặc dấu của đơn vị mà cá nhân liên quan được ủy quyền. Người được ủy quyền không được tiếp tục ủy quyền cho người khác. (2) Phạm vi ủy quyền bao gồm một hoặc nhiều công việc nêu trên. (3) Ghi ngày có hiệu lực và ngày hết hiệu lực của giấy ủy quyền phù hợp với quá trình dự thầu và phải bảo đảm có hiệu lực trước ngày thực hiện các công việc được ủy quyền. Mẫu 03 THỎA THUẬN LIÊN DANH(1), ngày tháng năm Gói thầu: ___ [Ghi tên gói thầu] Thuộc: ___ [Ghi tên dự án/dự toán mua sắm] - Căn cứ ___ [Luật Đấu thầu](2); - Căn cứ ___ (2); - Căn cứ hồ sơ yêu cầu gói thầu _______ [Ghi tên gói thầu] ngày ___ tháng ____ năm ____[Ngày được ghi trên HSYC]; Chúng tôi, đại diện cho các bên ký thỏa thuận liên danh, gồm có: Tên thành viên liên danh [Ghi tên từng thành viên liên danh] Đại diện là ông/bà: Chức vụ: Địa chỉ: Điện thoại: E-mail: Tài khoản: Mã số thuế: Giấy ủy quyền số __ ngày __tháng __ năm __ (trường hợp được ủy quyền). Các bên (sau đây gọi là thành viên) thống nhất ký kết thỏa thuận liên danh với các nội dung sau: Điều 1. Nguyên tắc chung 1. Các thành viên tự nguyện hình thành liên danh để dự thầu gói thầu___[Ghi tên gói thầu] thuộc ___ [Ghi tên dự án/dự toán mua sắm]. 2. Các thành viên thống nhất tên gọi của liên danh cho mọi giao dịch liên quan đến gói thầu này là: [Ghi tên của liên danh]. 3. Các thành viên cam kết không thành viên nào có quyền từ chối thực hiện các trách nhiệm và nghĩa vụ quy định trong hợp đồng. Trường hợp thành viên của liên danh từ chối hoàn thành trách nhiệm riêng của mình như đã thỏa thuận thì thành viên đó bị xử lý như sau: - Bồi thường thiệt hại cho các bên trong liên danh - Bồi thường thiệt hại cho Chủ đầu tư theo quy định nêu trong hợp đồng - Hình thức xử lý khác [Ghi rõ hình thức xử lý khác]. Điều 2. Phân công trách nhiệm Các thành viên thống nhất chịu trách nhiệm chung, trách nhiệm riêng để thực hiện gói thầu [Ghi tên gói thầu] thuộc ___ [Ghi tên dự án/dự toán mua sắm] đối với từng thành viên như sau: 1. Thành viên đứng đầu liên danh Các bên nhất trí ủy quyền cho [Ghi tên một bên] làm thành viên đứng đầu liên danh, đại diện cho liên danh trong những phần việc sau(3): [- Ký đơn dự thầu; - Ký các văn bản, hồ sơ để giao dịch với Chủ đầu tư trong quá trình dự thầu, kể cả văn bản đề nghị làm rõ HSYC và văn bản giải trình, làm rõ HSĐX; - Tham gia quá trình thương thảo (nếu có), hoàn thiện hợp đồng; - Ký đơn kiến nghị trong trường hợp nhà thầu có kiến nghị; - Các công việc khác trừ việc ký kết hợp đồng [Ghi rõ nội dung các công việc khác (nếu có)]. 2. Các thành viên trong liên danh thỏa thuận phân công trách nhiệm thực hiện công việc theo bảng dưới đây(4): [BẢNG: Không tiêu đề] Điều 3. Hiệu lực của thỏa thuận liên danh 1. Thỏa thuận liên danh có hiệu lực kể từ ngày ký. 2. Thỏa thuận liên danh chấm dứt hiệu lực trong các trường hợp sau: - Các bên hoàn thành trách nhiệm và nghĩa vụ của mình và tiến hành thanh lý hợp đồng; - Các bên cùng thỏa thuận chấm dứt; - Nhà thầu liên danh không được chỉ định thầu; - Hủy thầu gói thầu [Ghi tên gói thầu] thuộc ___ [Ghi tên dự án/dự toán mua sắm] theo thông báo của Chủ đầu tư. Thỏa thuận liên danh được lập thành bản, mỗi bên giữ bản, các bản thỏa thuận có giá trị pháp lý như nhau. ĐẠI DIỆN HỢP PHÁP CỦA THÀNH VIÊN ĐỨNG ĐẦU LIÊN DANH(5) [Ghi tên, chức danh, ký tên và đóng dấu] ĐẠI DIỆN HỢP PHÁP CỦA THÀNH VIÊN LIÊN DANH [Ghi tên từng thành viên, chức danh, ký tên và đóng dấu] Ghi chú: (1) Căn cứ quy mô, tính chất của gói thầu, nội dung thỏa thuận liên danh theo mẫu này có thể được sửa đổi bổ sung cho phù hợp. (2) Cập nhật các văn bản quy phạm pháp luật theo quy định hiện hành. (3) Phạm vi ủy quyền bao gồm một hoặc nhiều công việc nêu trên. (4) Nhà thầu phải ghi rõ nội dung công việc cụ thể và ước tính giá trị tương ứng mà từng thành viên trong liên danh sẽ thực hiện, trách nhiệm chung, trách nhiệm của từng thành viên, kể cả thành viên đứng đầu liên danh. Việc phân chia công việc trong liên danh phải căn cứ các hạng mục nêu trong bảng giá thầu quy định tại Mẫu 04 (04A hoặc 04B hoặc 04C hoặc 04D hoặc 04E) Chương III; không được phân chia các công việc không thuộc các hạng mục này hoặc không thuộc quá trình sản xuất các hạng mục này. (5) Đại diện hợp pháp của thành viên liên danh có thể là người đại diện theo pháp luật hoặc người được người đại diện theo pháp luật ủy quyền. Mẫu 04A BẢNG giá thầu(1) (Đối với loại hợp đồng trọn gói) [BẢNG: Không tiêu đề] Đại diện hợp pháp của nhà thầu [ghi tên, chức danh, ký tên và đóng dấu] Ghi chú: (1) giá thầu của nhà thầu được coi là đã bao gồm toàn bộ các chi phí cần thiết để thực hiện gói thầu theo đúng thiết kế và yêu cầu kỹ thuật nêu trong HSYC, không tiến hành hiệu chỉnh sai lệch trong trường hợp hạng mục công việc mà nhà thầu đề xuất trong bảng giá thầu khác so với các hạng mục công việc nêu trong HSYC, trừ trường hợp công việc được đề xuất khác đó ngoài phạm vi yêu cầu trong HSYC (ngoài khối lượng để hoàn thành theo thiết kế). Trong trường hợp này, phần công việc ngoài phạm vi yêu cầu trong HSYC sẽ được coi là chào thừa và được hiệu chỉnh theo quy định. giá thầu là tổng giá trị của các hạng mục ghi trong cột “Mô tả công việc”. giá thầu của nhà thầu phải bao gồm chi phí cho các loại thuế, phí, lệ phí và chi phí dự phòng (nếu có). Nhà thầu phải tính toán các chi phí nêu trên và phân bổ vào trong giá thầu. Khi thực hiện hợp đồng, trường hợp nhà thầu hoàn thành toàn bộ gói thầu theo đúng hồ sơ thiết kế, yêu cầu kỹ thuật thì tổng số tiền mà nhà thầu được thanh toán cho đến khi hoàn thành các nghĩa vụ theo hợp đồng bằng đúng giá ghi trong hợp đồng. (2), (3) Các hạng mục công việc nêu trong HSYC và khối lượng chỉ có giá trị tham khảo, nhà thầu có trách nhiệm chuẩn xác hạng mục công việc phù hợp với thiết kế và yêu cầu kỹ thuật tại Chương IV. Nhà thầu có trách nhiệm rà soát lại các hạng mục công việc nêu trong HSYC. Nhà thầu phải tự bổ sung và chào giá cho các hạng mục công việc mà nhà thầu phát hiện chưa bao gồm trong các hạng mục công việc nêu trong HSYC nhưng cần thiết để hoàn thành công việc theo thiết kế. Trường hợp nhà thầu không bổ sung các hạng mục công việc thiếu so với thiết kế, nhà thầu được coi là đã phân bổ giá của các hạng mục công việc này vào các hạng mục công việc khác của gói thầu. Nhà thầu có trách nhiệm hoàn thành công việc theo thiết kế và đáp ứng yêu cầu về kỹ thuật với giá đã chào. Trường hợp phát hiện các hạng mục công việc nêu trong HSYC thừa so với thiết kế, nhà thầu loại hạng mục thừa ra khỏi bảng giá thầu. (4) Nhà thầu có trách nhiệm phân bổ chi phí dự phòng (nếu có) vào giá thầu. Nhà thầu không được chào riêng chi phí dự phòng. Trường hợp nhà thầu chào riêng chi phí dự phòng thì được coi là chào thừa và sẽ bị hiệu chỉnh sai lệch. Mẫu 04B BẢNG giá thầu (Đối với loại hợp đồng theo đơn giá cố định) [BẢNG: Không tiêu đề] Đại diện hợp pháp của nhà thầu [ghi tên, chức danh, ký tên và đóng dấu] Ghi chú: (2), (4), (5) Chủ đầu tư ghi các công việc cụ thể của từng hạng mục cùng với đơn vị tính và khối lượng mời thầu trên cơ sở phù hợp với mô tả công việc, bản vẽ và chi tiết kỹ thuật trong Chương IV làm cơ sở để nhà thầu chào giá thầu cho từng hạng mục. (3) Chủ đầu tư ghi dẫn chiếu cụ thể đến nội dung yêu cầu về kỹ thuật/chỉ dẫn kỹ thuật chính để thực hiện hạng mục công việc tương ứng trong Chương IV hoặc trong hồ sơ chỉ dẫn kỹ thuật (tên mục, số trang, số quyển. ..) để nhà thầu thuận tiện trong việc đánh giá, nghiên cứu các yêu cầu về kỹ thuật/chỉ dẫn kỹ thuật làm cơ sở chào giá thầu. (6) (7): Nhà thầu ghi đơn giá thầu, thành tiền của từng hạng mục. giá thầu của nhà thầu phải bao gồm chi phí cho các loại thuế, phí, lệ phí (nếu có) và chi phí dự phòng. (*): Trong HSYC phải ghi rõ tỷ lệ dự phòng cho khối lượng phát sinh (b1%) làm cơ sở để nhà thầu chào thầu. Khi dự thầu, nhà thầu phải chào chi phí dự phòng cho khối lượng phát sinh với giá trị bằng tỷ lệ phần trăm (%) quy định trong HSYC (b1%) nhân với Chi phí của các hạng mục do nhà thầu chào (A). Chi phí dự phòng chỉ được sử dụng khi có phát sinh khối lượng công việc trong thực tế. Mẫu 04C BẢNG giá thầu (Đối với loại hợp đồng theo đơn giá điều chỉnh) [BẢNG: Không tiêu đề] Đại diện hợp pháp của nhà thầu [ghi tên, chức danh, ký tên và đóng dấu] Ghi chú: (2), (4), (5) Chủ đầu tư ghi các công việc cụ thể của từng hạng mục cùng với đơn vị tính và khối lượng mời thầu trên cơ sở phù hợp với mô tả công việc, bản vẽ và chi tiết kỹ thuật trong Chương IV làm cơ sở để nhà thầu chào giá thầu cho từng hạng mục. (3) Chủ đầu tư ghi dẫn chiếu cụ thể đến nội dung yêu cầu về kỹ thuật/chỉ dẫn kỹ thuật chính để thực hiện hạng mục công việc tương ứng trong Chương IV hoặc trong hồ sơ chỉ dẫn kỹ thuật (tên mục, số trang, số quyển. ..) để nhà thầu thuận tiện trong việc đánh giá, nghiên cứu các yêu cầu về kỹ thuật/chỉ dẫn kỹ thuật làm cơ sở chào giá thầu. (6) (7) Nhà thầu ghi đơn giá thầu, thành tiền của từng hạng mục. giá thầu của nhà thầu phải bao gồm chi phí cho các loại thuế, phí, lệ phí (nếu có) và chi phí dự phòng. (*): Trong HSYC phải ghi rõ tỷ lệ dự phòng cho khối lượng phát sinh và dự phòng trượt giá (b2%) làm cơ sở để nhà thầu chào thầu. Khi dự thầu, nhà thầu phải chào chi phí dự phòng cho khối lượng phát sinh và chi phí dự phòng trượt giá với giá trị bằng tỷ lệ phần trăm (%) quy định trong HSYC (b2%) nhân với Chi phí của các hạng mục do nhà thầu chào (A). Chi phí dự phòng chỉ được sử dụng khi có phát sinh khối lượng công việc trong thực tế và có trượt giá. Mẫu 04D BẢNG giá thầu (Đối với loại hợp đồng theo kết quả đầu ra) [BẢNG: Không tiêu đề] Đại diện hợp pháp của nhà thầu [ghi tên, chức danh, ký tên và đóng dấu] Ghi chú: (2), (4), (5) Chủ đầu tư ghi các công việc cụ thể của từng hạng mục cùng với đơn vị tính và khối lượng mời thầu trên cơ sở phù hợp với mô tả công việc, bản vẽ và chi tiết kỹ thuật trong Chương IV làm cơ sở để nhà thầu chào giá thầu cho từng hạng mục. (3) Chủ đầu tư ghi dẫn chiếu cụ thể đến nội dung yêu cầu về kỹ thuật/chỉ dẫn kỹ thuật chính để thực hiện hạng mục công việc tương ứng trong Chương IV hoặc trong hồ sơ chỉ dẫn kỹ thuật (tên mục, số trang, số quyển. ..) để nhà thầu thuận tiện trong việc đánh giá, nghiên cứu các yêu cầu về kỹ thuật/chỉ dẫn kỹ thuật làm cơ sở chào giá thầu. (6), (7): Nhà thầu ghi đơn giá thầu, thành tiền của từng hạng mục. giá thầu của nhà thầu phải bao gồm chi phí cho các loại thuế, phí, lệ phí (nếu có). Mẫu 04E BẢNG giá thầu (Đối với loại hợp đồng hỗn hợp) I. Các hạng mục áp dụng loại hợp đồng trọn gói(1) [BẢNG: Không tiêu đề] Ghi chú: (1) giá thầu của các hạng mục này được coi là đã bao gồm toàn bộ các chi phí cần thiết để thực hiện theo đúng thiết kế và yêu cầu kỹ thuật nêu trong HSYC, không tiến hành hiệu chỉnh sai lệch trong trường hợp hạng mục công việc mà nhà thầu đề xuất trong các hạng mục này khác so với các hạng mục công việc áp dụng loại hợp đồng trọn gói nêu trong HSYC, trừ trường hợp công việc được đề xuất khác đó ngoài phạm vi yêu cầu trong HSYC (ngoài khối lượng để hoàn thành theo thiết kế). Trong trường hợp này, phần công việc ngoài phạm vi yêu cầu trong HSYC sẽ được coi là chào thừa và được hiệu chỉnh theo quy định. giá thầu cho các hạng mục này là tổng giá trị của các hạng mục ghi trong cột “Mô tả công việc”. giá thầu của nhà thầu phải bao gồm chi phí cho các loại thuế, phí, lệ phí và chi phí dự phòng (nếu có). Nhà thầu phải tính toán các chi phí nêu trên và phân bổ vào trong giá các hạng mục. Khi thực hiện hợp đồng, trường hợp nhà thầu hoàn thành toàn bộ các hạng mục áp dụng loại hợp đồng trọn gói theo đúng hồ sơ thiết kế, yêu cầu kỹ thuật thì tổng số tiền mà nhà thầu được thanh toán cho đến khi hoàn thành các nghĩa vụ theo hợp đồng bằng đúng giá của các hạng mục áp dụng loại hợp đồng trọn gói ghi trong hợp đồng. (2), (3) Các hạng mục công việc nêu trong HSYC và khối lượng chỉ có giá trị tham khảo, nhà thầu có trách nhiệm chuẩn xác hạng mục công việc phù hợp với thiết kế và yêu cầu kỹ thuật tại Chương IV. (4) Nhà thầu có trách nhiệm phân bổ chi phí dự phòng (nếu có) vào giá của các hạng mục. Nhà thầu không được chào riêng chi phí dự phòng. Trường hợp nhà thầu chào riêng chi phí dự phòng thì được coi là chào thừa và sẽ bị hiệu chỉnh sai lệch. II. Các hạng mục áp dụng loại hợp đồng theo đơn giá cố định [BẢNG: Không tiêu đề] Ghi chú: (2), (4), (5) Chủ đầu tư ghi các công việc cụ thể của từng hạng mục cùng với đơn vị tính và khối lượng mời thầu trên cơ sở phù hợp với mô tả công việc, bản vẽ và chi tiết kỹ thuật trong Chương IV làm cơ sở để nhà thầu chào giá thầu cho từng hạng mục. (3) Chủ đầu tư ghi dẫn chiếu cụ thể đến nội dung yêu cầu về kỹ thuật/chỉ dẫn kỹ thuật chính để thực hiện hạng mục công việc tương ứng trong Chương IV hoặc trong hồ sơ chỉ dẫn kỹ thuật (tên mục, số trang, số quyển. ..) để nhà thầu thuận tiện trong việc đánh giá, nghiên cứu các yêu cầu về kỹ thuật/chỉ dẫn kỹ thuật làm cơ sở chào giá thầu. (6) (7) Nhà thầu ghi đơn giá thầu, thành tiền của từng hạng mục. giá thầu của nhà thầu phải bao gồm chi phí cho các loại thuế, phí, lệ phí (nếu có) và chi phí dự phòng. (*): Trong HSYC phải ghi rõ tỷ lệ dự phòng cho khối lượng phát sinh (b1%) làm cơ sở để nhà thầu chào thầu. Khi dự thầu, nhà thầu phải chào chi phí dự phòng cho khối lượng phát sinh với giá trị bằng tỷ lệ phần trăm (%) quy định trong HSYC (b1%) nhân với Chi phí của các hạng mục do nhà thầu chào (A). Chi phí dự phòng chỉ được sử dụng khi có phát sinh khối lượng công việc trong thực tế. III. Các hạng mục áp dụng loại hợp đồng theo đơn giá điều chỉnh [BẢNG: Không tiêu đề] Ghi chú: (2), (4), (5) Chủ đầu tư ghi các công việc cụ thể của từng hạng mục cùng với đơn vị tính và khối lượng mời thầu trên cơ sở phù hợp với mô tả công việc, bản vẽ và chi tiết kỹ thuật trong Chương IV làm cơ sở để nhà thầu chào giá thầu cho từng hạng mục. (3) Chủ đầu tư ghi dẫn chiếu cụ thể đến nội dung yêu cầu về kỹ thuật/chỉ dẫn kỹ thuật chính để thực hiện hạng mục công việc tương ứng trong Chương IV hoặc trong hồ sơ chỉ dẫn kỹ thuật (tên mục, số trang, số quyển. ..) để nhà thầu thuận tiện trong việc đánh giá, nghiên cứu các yêu cầu về kỹ thuật/chỉ dẫn kỹ thuật làm cơ sở chào giá thầu. (6) (7) Nhà thầu ghi đơn giá thầu, thành tiền của từng hạng mục. giá thầu của nhà thầu phải bao gồm chi phí cho các loại thuế, phí, lệ phí (nếu có) và chi phí dự phòng. (*): Trong HSYC phải ghi rõ tỷ lệ dự phòng cho khối lượng phát sinh và dự phòng trượt giá (b2%) làm cơ sở để nhà thầu chào thầu. Khi dự thầu, nhà thầu phải chào chi phí dự phòng cho khối lượng phát sinh và chi phí dự phòng trượt giá với giá trị bằng tỷ lệ phần trăm (%) quy định trong HSYC (b2%) nhân với Chi phí của các hạng mục do nhà thầu chào (A). Chi phí dự phòng chỉ được sử dụng khi có phát sinh khối lượng công việc trong thực tế và có trượt giá. IV. Các hạng mục áp dụng loại hợp đồng theo kết quả đầu ra [BẢNG: Không tiêu đề] Ghi chú: (2), (4), (5) Chủ đầu tư ghi các công việc cụ thể của từng hạng mục cùng với đơn vị tính và khối lượng mời thầu trên cơ sở phù hợp với mô tả công việc, bản vẽ và chi tiết kỹ thuật trong Chương IV làm cơ sở để nhà thầu chào giá thầu cho từng hạng mục. (3) Chủ đầu tư ghi dẫn chiếu cụ thể đến nội dung yêu cầu về kỹ thuật/chỉ dẫn kỹ thuật chính để thực hiện hạng mục công việc tương ứng trong Chương IV hoặc trong hồ sơ chỉ dẫn kỹ thuật (tên mục, số trang, số quyển. ..) để nhà thầu thuận tiện trong việc đánh giá, nghiên cứu các yêu cầu về kỹ thuật/chỉ dẫn kỹ thuật làm cơ sở chào giá thầu. (6), (7): Nhà thầu ghi đơn giá thầu, thành tiền của từng hạng mục. giá thầu của nhà thầu phải bao gồm chi phí cho các loại thuế, phí, lệ phí (nếu có). V. Tổng hợp giá thầu [BẢNG: Không tiêu đề] Mẫu 04G BẢNG KÊ CÔNG NHẬT 1. Quy định chung a) Bảng kê Công nhật thông thường được áp dụng đối với các gói thầu có khả năng phát sinh công việc ngoài các công việc nêu trong Bảng giá thầu hoặc không thể đưa vào nội dung mô tả, khối lượng, số lượng ước tính trong Bảng giá thầu. Trường hợp cần đưa Bảng kê Công nhật vào HSYC thì phải ghi rõ khối lượng, số lượng danh nghĩa đối với các hạng mục có khả năng phải sử dụng công nhật để nhà thầu làm cơ sở chào giá. giá thầu cho phần công nhật được kết chuyển vào phần Chi phí cho các khoản tạm tính trong Bảng giá thầu. Phần Chi phí cho các khoản tạm tính, trong đó bao gồm Chi phí công nhật sẽ được tách riêng và không được đánh giá trong quá trình đánh giá HSĐX. b) Giá trúng thầu và giá hợp đồng sẽ bao gồm Chi phí cho các khoản tạm tính do nhà thầu chào trong HSĐX. Trường hợp trong quá trình thực hiện hợp đồng, nếu có phát sinh công nhật hoặc các công việc tạm tính khác thì Chủ đầu tư sẽ dùng khoản kinh phí cho các khoản tạm tính để thanh toán cho nhà thầu theo quy định trong hợp đồng. c) Các công việc sẽ không được thực hiện trên cơ sở công nhật trừ trường hợp có yêu cầu bằng văn bản của Chủ đầu tư. Nhà thầu phải điền đơn giá, thành tiền cho các hạng mục công nhật trong các Bảng nhân công, vật liệu, thiết bị. Đơn giá do nhà thầu chào sẽ được áp dụng đối với bất kỳ khối lượng công nhật nào được Chủ đầu tư yêu cầu thực hiện. Trừ khi hợp đồng có quy định khác, các khoản thanh toán cho công nhật sẽ phụ thuộc vào quy định về điều chỉnh giá trong Điều kiện hợp đồng. 2. Nhân công tính theo Công nhật a) Khi tính toán các khoản thanh toán cho nhà thầu theo công nhật, số giờ cho nhân công sẽ được tính từ thời điểm nhân công đến hiện trường để thực hiện hạng mục công nhật đến thời điểm nhân công quay trở về nơi xuất phát ban đầu, nhưng không bao gồm thời gian nghỉ ăn trưa và những khoảng thời gian nghỉ khác. Chỉ có thời gian của các nhân công trực tiếp làm công việc theo yêu cầu của Chủ đầu tư và công việc mà nhân công có khả năng thực hiện mới được tính chi phí. Thời gian đội trưởng tham gia xây lắp cùng tập thể lao động cũng sẽ được tính nhưng không tính thời gian của đốc công hoặc nhân sự giám sát khác. b) Nhà thầu được thanh toán đối với tổng số thời gian mà nhân công được thuê theo công nhật. Giá trị thanh toán được tính theo đơn giá mà nhà thầu chào trong Bảng đơn giá công nhật: 1. Nhân công. Đơn giá được coi là đã bao gồm (nhưng không giới hạn) tất cả các chi phí phải thanh toán cho nhà thầu như: - Số tiền lương trả cho người lao động; - Chi phí đi lại, làm thêm giờ, sinh hoạt phí; - Các chi phí về phúc lợi xã hội liên quan; - Lợi nhuận của nhà thầu, chi phí quản lý, giám sát, bảo hiểm; - Chi phí điện, nước, an ninh, văn phòng phẩm, thông tin liên lạc, hành chính, văn thư và các chi phí liên quan khác. 3. Vật liệu tính theo Công nhật Nhà thầu sẽ được thanh toán đối với vật liệu được sử dụng để thực hiện công việc theo công nhật với đơn giá mà nhà thầu chào trong Bảng đơn giá công nhật: 2. Vật liệu. Đơn giá phải được chào bằng VND và được coi là đã bao gồm chi phí quản lý, lợi nhuận như sau: a) Đơn giá vật liệu sẽ được tính trên cơ sở giá ghi trên hóa đơn cộng với các chi phí để giao vật liệu đến kho tại Công trường bao gồm chi phí vận chuyển, bảo hiểm, chi phí bốc dỡ, thiệt hại, tổn thất. .. ; b) Chi phí vận chuyển vật liệu để sử dụng vào công việc được yêu cầu thực hiện theo công nhật từ kho chứa tại Công trường đến địa điểm mà vật liệu được sử dụng sẽ được thanh toán theo các điều khoản về Nhân công và Thiết bị thi công trong Bảng này. 4. Thiết bị của nhà thầu tính theo Công nhật a) Nhà thầu được thanh toán đối với Thiết bị của nhà thầu đã có tại Công trường và được sử dụng vào công việc theo công nhật theo đơn giá mà nhà thầu chào trong Bảng đơn giá công nhật: 3. Thiết bị của nhà thầu. Đơn giá phải được chào bằng VND và được coi là đã bao gồm (nhưng không giới hạn) các khoản chi phí sau: Chi phí khấu hao thiết bị; Chi phí lãi suất, tiền bồi thường, tiền bảo hiểm, sửa chữa, bảo trì, vật tư, nhiên liệu, dầu nhờn và vật tư tiêu hao khác; Lợi nhuận và chi phí quản lý liên quan đến việc sử dụng các thiết bị. Chi phí cho nhân viên vận hành thiết bị và trợ lý sẽ được thanh toán riêng như mô tả tại phần Nhân công tính theo Công nhật. b) Chỉ có số giờ vận hành thực sự của thiết bị để thực hiện các công việc theo công nhật mới đủ điều kiện để thanh toán; trừ trường hợp Chủ đầu tư chấp nhận thanh toán đối với thời gian di chuyển thiết bị từ Công trường nơi thiết bị được đặt đến vị trí thi công các công việc theo công nhật và thời gian di chuyển thiết bị về vị trí ban đầu. Bảng đơn giá công nhật 1. Nhân công [BẢNG: Không tiêu đề] Đại diện hợp pháp của nhà thầu [ghi tên, chức danh, ký tên và đóng dấu] Ghi chú: (1), (2), (3) Chủ đầu tư căn cứ khả năng phát sinh công việc ngoài các công việc nêu trong Bảng giá thầu hoặc không thể đưa vào nội dung mô tả, khối lượng, số lượng ước tính trong Bảng giá thầu để dự tính và ghi cụ thể tên công việc, đơn vị tính và số lượng danh nghĩa cho các công việc có thể sử dụng công nhật để nhà thầu làm cơ sở chào thầu. (4), (5) Nhà thầu ghi đơn giá, thành tiền cho từng nội dung tương ứng trong cột “Mô tả”. Bảng Đơn giá Công nhật 2. Vật liệu [BẢNG: Không tiêu đề] Đại diện hợp pháp của nhà thầu [ghi tên, chức danh, ký tên và đóng dấu] Ghi chú: (1), (2), (3) Chủ đầu tư căn cứ khả năng phát sinh công việc ngoài các công việc nêu trong Bảng giá thầu hoặc không thể đưa vào nội dung mô tả, khối lượng, số lượng ước tính trong Bảng giá thầu để dự tính và ghi cụ thể tên công việc, đơn vị tính và số lượng danh nghĩa cho các công việc có thể sử dụng công nhật để nhà thầu làm cơ sở chào thầu. (4), (5) Nhà thầu ghi đơn giá, thành tiền cho từng nội dung tương ứng trong cột “Mô tả”. Bảng Đơn giá Công nhật 3. Thiết bị của Nhà thầu [BẢNG: Không tiêu đề] Đại diện hợp pháp của nhà thầu [ghi tên, chức danh, ký tên và đóng dấu] Ghi chú: (1), (2), (3) Chủ đầu tư căn cứ khả năng phát sinh công việc ngoài các công việc nêu trong Bảng giá thầu hoặc không thể đưa vào nội dung mô tả, khối lượng, số lượng ước tính trong Bảng giá thầu để dự tính và ghi cụ thể tên công việc, đơn vị tính và số lượng danh nghĩa cho các công việc có thể sử dụng công nhật để nhà thầu làm cơ sở chào thầu. (4), (5) Nhà thầu ghi đơn giá, thành tiền cho từng nội dung tương ứng trong cột “Mô tả”. Bảng Công nhật tổng hợp [BẢNG: Không tiêu đề] Đại diện hợp pháp của nhà thầu [ghi tên, chức danh, ký tên và đóng dấu] Mẫu 04H BẢNG KÊ CÁC KHOẢN TẠM TÍNH Phần chi phí cho các khoản tạm tính sẽ được tách riêng và không được đánh giá trong quá trình đánh giá HSĐX. Giá trúng thầu và giá hợp đồng sẽ bao gồm chi phí cho các khoản tạm tính do nhà thầu chào trong HSĐX. Trường hợp trong quá trình thực hiện hợp đồng, nếu có phát sinh các công việc theo mô tả thì Chủ đầu tư sẽ dùng khoản kinh phí cho các khoản tạm tính để thanh toán cho nhà thầu theo quy định trong hợp đồng. [BẢNG: Bảng số] Đại diện hợp pháp của nhà thầu [ghi tên, chức danh, ký tên và đóng dấu] Ghi chú: (1) Do Chủ đầu tư điền nội dung công việc để nhà thầu làm căn cứ chào trong HSĐX theo đúng nội dung công việc nêu trong HSYC. (2) Nhà thầu ghi thành tiền cho từng nội dung tương ứng trong cột “Mô tả”. Mẫu 04I BẢNG KÊ SỐ LIỆU ĐIỀU CHỈNH (áp dụng cho hợp đồng theo đơn điều chỉnh) [BẢNG: Không tiêu đề] Mẫu 05 BẢN KÊ KHAI THÔNG TIN VỀ NHÀ THẦU (1) Ngày: _________________ Tên gói thầu: _________________ [BẢNG: Không tiêu đề] Ghi chú: (1) Đối với nhà thầu liên danh thì từng thành viên phải kê khai theo Mẫu này. Mẫu 06 HỢP ĐỒNG TƯƠNG TỰ DO NHÀ THẦU THỰC HIỆN Tên nhà thầu: _____[ghi tên đầy đủ của nhà thầu]. Thông tin về từng hợp đồng, mỗi hợp đồng cần bảo đảm các thông tin sau đây: [BẢNG: Không tiêu đề] Ghi chú: Nhà thầu nghiên cứu kỹ HSYC và đề xuất các hợp đồng tương tự để bảo đảm đáp ứng yêu cầu của HSYC. (1) Trong trường hợp liên danh, từng thành viên trong liên danh kê khai theo Mẫu này. Trường hợp nhà thầu có nhiều hợp đồng tương tự thì kê khai từng hợp đồng theo Mẫu này. Trường hợp HSYC không yêu cầu về kinh nghiệm thực hiện hợp đồng xây lắp tương tự thì bỏ qua Bảng này. (2) Nhà thầu chỉ kê khai nội dung tương tự với yêu cầu của gói thầu. (3) Trường hợp giá trị hợp đồng không tính bằng VND thì quy đổi sang VND theo tỷ giá theo quy định tại Mục 2. 1 Chương II để làm cơ sở đánh giá. Mẫu 07A BẢNG ĐỀ XUẤT NHÂN SỰ CHỦ CHỐT Nhà thầu phải kê khai những nhân sự chủ chốt theo quy định tại điểm a Mục 2. 2 Chương II và phải chứng minh khả năng sẵn sàng huy động các nhân sự này để tham gia thực hiện gói thầu. Nhân sự chủ chốt có thể thuộc biên chế của nhà thầu hoặc do nhà thầu huy động. Trường hợp nhân sự chủ chốt mà nhà thầu đề xuất trong HSĐX không đáp ứng yêu cầu hoặc không chứng minh được khả năng huy động nhân sự (bao gồm cả trường hợp nhân sự đã huy động cho hợp đồng khác có thời gian làm việc trùng với thời gian thực hiện gói thầu này) thì Chủ đầu tư cho phép nhà thầu bổ sung, thay thế. Trường hợp nhà thầu không có nhân sự thay thế đáp ứng yêu cầu của HSYC thì HSĐX bị loại. Trường hợp nhà thầu cố ý kê khai kê khai nhân sự chủ chốt không trung thực trong HSĐX nhằm làm sai lệch kết quả lựa chọn nhà thầu thì nhà thầu không được thay thế nhân sự khác, HSĐX của nhà thầu bị loại và nhà thầu sẽ bị coi là gian lận theo quy định tại điểm b Khoản 4 Điều 16 của Luật Đấu thầu và bị xử lý theo quy định tại Khoản 1 Điều 133 của Nghị định số 214/2025/NĐ-CP. [BẢNG: Không tiêu đề] Mẫu 07B [BẢNG: Không tiêu đề] Nhà thầu phải cung cấp tất cả các thông tin trong HSĐX theo yêu cầu tại Bảng trên. Mẫu 07C [BẢNG: BẢNG KINH NGHIỆM CHUYÊN MÔN] Liệt kê theo trình tự thời gian quá trình công tác của chuyên gia, không cần liệt kê các công việc đã làm không phù hợp hoặc không liên quan với công việc đang yêu cầu. Nhà thầu phải cung cấp tất cả các thông tin được yêu cầu. Mẫu 07D BẢNG KÊ KHAI THIẾT BỊ THI CÔNG CHỦ YẾU Nhà thầu phải kê khai những thiết bị thi công chủ yếu theo quy định tại điểm b Mục 2. 2 Chương II và phải chứng minh khả năng sẵn sàng huy động các thiết bị này để tham gia thực hiện gói thầu. Thiết bị thi công chủ yếu có thể thuộc sở hữu của nhà thầu hoặc do nhà thầu huy động. Trường hợp thiết bị mà nhà thầu đề xuất trong HSĐX không đáp ứng yêu cầu thì Chủ đầu tư cho phép nhà thầu bổ sung, thay thế. Trường hợp nhà thầu không có thiết bị thay thế đáp ứng yêu cầu của HSYC thì nhà thầu bị loại. Trường hợp nhà thầu cố ý kê khai thiết bị thi công chủ yếu không trung thực trong HSĐX nhằm làm sai lệch kết quả lựa chọn nhà thầu thì nhà thầu không được thay thế thiết bị khác, HSĐX của nhà thầu bị loại và nhà thầu sẽ bị coi là gian lận theo quy định tại điểm b Khoản 4 Điều 16 của Luật Đấu thầu và bị xử lý theo quy định tại Khoản 1 Điều 133 của Nghị định số 214/2025/NĐ-CP. [BẢNG: Không tiêu đề] Đối với các thiết bị không thuộc sở hữu của mình thì nhà thầu phải kê khai thêm các thông tin dưới đây: [BẢNG: Không tiêu đề] Mẫu 08 HỢP ĐỒNG XÂY LẮP, EPC, EC, PC, CHÌA KHÓA TRAO TAY KHÔNG HOÀN THÀNH DO LỖI CỦA NHÀ THẦU TRONG QUÁ KHỨ(1) Tên nhà thầu: ________________ Ngày: ______________________ Tên thành viên của nhà thầu liên danh (nếu có): _________________________ [BẢNG: Không tiêu đề] Ghi chú: (1) Nhà thầu phải kê khai chính xác, trung thực các hợp đồng xây lắp, EPC, EC, PC, chìa khóa trao tay không hoàn thành do lỗi của nhà thầu trong quá khứ; trường hợp Chủ đầu tư, tổ chuyên gia phát hiện nhà thầu có hợp đồng xây lắp, EPC, EC, PC, chìa khóa trao tay không hoàn thành do lỗi của nhà thầu trong quá khứ mà không kê khai thì nhà thầu được coi là có hành vi gian lận và HSĐX của nhà thầu sẽ bị loại. Trường hợp nhà thầu liên danh thì từng thành viên liên danh phải kê khai theo Mẫu này. Mẫu 09A TÌNH HÌNH TÀI CHÍNH CỦA NHÀ THẦU(1) Tên nhà thầu: ________________ Ngày: ______________________ [BẢNG: Không tiêu đề] Ghi chú: (1) Trường hợp nhà thầu liên danh thì từng thành viên liên danh phải kê khai theo Mẫu này. (2) Để xác định doanh thu bình quân hằng năm (không bao gồm thuế VAT), nhà thầu chia tổng doanh thu của các năm (không bao gồm thuế VAT) cho số năm dựa trên thông tin đã được cung cấp. Doanh thu hằng năm được tính bằng tổng doanh thu trong báo cáo tài chính của năm đó (chưa bao gồm thuế VAT). Doanh thu bình quân hằng năm (không bao gồm thuế VAT) = tổng doanh thu từng năm (không bao gồm thuế VAT) theo yêu cầu của HSYC/số năm. Trường hợp nhà thầu mới thành lập không đủ số năm theo yêu cầu của HSYC thì Doanh thu bình quân hằng năm (không bao gồm thuế VAT) được tính trên cơ sở số năm mà nhà thầu có số liệu tài chính. Nhà thầu phải nộp các hồ sơ như sau: Bản sao các báo cáo tài chính (các bảng cân đối kế toán bao gồm tất cả thuyết minh có liên quan, và các báo cáo kết quả kinh doanh) cho các năm như đã nêu trên, tuân thủ các điều kiện sau: 1. Phản ánh tình hình tài chính của nhà thầu hoặc thành viên liên danh (nếu là nhà thầu liên danh) mà không phải tình hình tài chính của một chủ thể liên kết như công ty mẹ liên kết với công ty con hoặc công ty liên kết với nhà thầu hoặc thành viên liên danh. 2. Các báo cáo tài chính phải hoàn chỉnh, đầy đủ nội dung theo quy định. 3. Các báo cáo tài chính phải tương ứng với các kỳ kế toán đã hoàn thành kèm theo bản chụp được chứng thực một trong các hồ sơ sau đây: - Biên bản kiểm tra quyết toán thuế; - Tờ khai tự quyết toán thuế (thuế giá trị gia tăng và thuế thu nhập doanh nghiệp) có xác nhận của cơ quan thuế về thời điểm đã nộp tờ khai; - hồ sơ chứng minh việc nhà thầu đã kê khai quyết toán thuế điện tử; - Văn bản xác nhận của cơ quan quản lý thuế (xác nhận số nộp cả năm) về việc thực hiện nghĩa vụ nộp thuế; - Báo cáo kiểm toán (nếu có); - Các hồ sơ khác. Các hồ sơ trên đây phải phù hợp với số liệu nhà thầu đã kê khai trên Hệ thống Thuế điện tử tại thời điểm đóng thầu. Mẫu 09B NGUỒN LỰC TÀI CHÍNH (1) Nêu rõ các nguồn tài chính dự kiến, chẳng hạn như các tài sản có khả năng thanh khoản cao(2), hạn mức tín dụng khả dụng (hạn mức tín dụng còn được sử dụng) hoặc các nguồn tài chính khác (không bao gồm các khoản tạm ứng thanh toán theo hợp đồng) có sẵn để đáp ứng yêu cầu về nguồn lực tài chính được nêu trong Mẫu 09C Chương này. [BẢNG: Không tiêu đề] Ghi chú: (1) Từng nhà thầu hoặc thành viên liên danh phải cung cấp thông tin về nguồn lực tài chính của mình, kèm theo hồ sơ chứng minh. Nguồn lực tài chính mà nhà thầu dự kiến huy động để thực hiện gói thầu được tính theo công thức sau: NLTC = TNL - ĐTH Trong đó: - NLTC là nguồn lực tài chính mà nhà thầu dự kiến huy động để thực hiện gói thầu; - TNL là tổng nguồn lực tài chính của nhà thầu (nêu tại Mẫu này); - ĐTH là tổng yêu cầu về nguồn lực tài chính hàng tháng cho các hợp đồng đang thực hiện (nêu tại Mẫu 09C). Nhà thầu được đánh giá là đáp ứng yêu cầu về nguồn lực tài chính cho gói thầu nếu có nguồn lực tài chính dự kiến huy động để thực hiện gói thầu (NLTC) tối thiểu bằng giá trị yêu cầu tại tiêu chí đánh giá 3. 3 Bảng số 01: Tiêu chuẩn đánh giá về năng lực tài chính và kinh nghiệm Mục 2. 1 Chương II. Trường hợp HSYC có yêu cầu về cam kết cung cấp tín dụng và trong HSĐX của nhà thầu có nộp kèm theo bản cam kết cung cấp tín dụng của tổ chức tín dụng hoạt động hợp pháp tại Việt Nam, trong đó cam kết sẽ cung cấp tín dụng cho nhà thầu để thực hiện gói đang xét đáp ứng quy định tại tiêu chí đánh giá 3. 3 Bảng số 01: Tiêu chuẩn đánh giá về năng lực tài chính và kinh nghiệm Mục 2. 1 Chương II thì nhà thầu được đánh giá là đáp ứng yêu cầu về nguồn lực tài chính cho gói thầu. Bản cam kết cung cấp tín dụng bao gồm các điều kiện để được ngân hàng cấp tín dụng theo quy định của pháp luật về tín dụng vẫn được chấp nhận; bên cạnh việc sử dụng cam kết cung cấp tín dụng, nhà thầu vẫn phải kê khai thông tin theo Mẫu này và Mẫu 09C. (2) Tài sản có khả năng thanh khoản cao là tiền mặt và tương đương tiền mặt, các công cụ tài chính ngắn hạn, các chứng khoán sẵn sàng để bán, chứng khoán dễ bán, các khoản phải thu thương mại, các khoản phải thu tài chính ngắn hạn và các tài sản khác mà có thể chuyển đổi thành tiền mặt trong vòng một năm. Mẫu 09C NGUỒN LỰC TÀI CHÍNH HÀNG THÁNG CHO CÁC HỢP ĐỒNG ĐANG THỰC HIỆN (1) [BẢNG: Không tiêu đề] Ghi chú: (1) Từng nhà thầu hoặc thành viên liên danh phải cung cấp thông tin được nêu dưới đây để tính toán tổng các yêu cầu về nguồn lực tài chính, bằng tổng của: (i) các cam kết hiện tại của nhà thầu (hoặc từng thành viên trong liên danh) trong tất cả các hợp đồng mà nhà thầu (hoặc từng thành trong viên liên danh) đang thực hiện hoặc sẽ được thực hiện; (ii) yêu cầu về nguồn lực tài chính đối với hợp đồng đang xét. Ngoài ra, nhà thầu cũng phải cung cấp thông tin về bất kỳ nghĩa vụ tài chính nào khác có thể ảnh hưởng đáng kể đến việc thực hiện hợp đồng đang xét nếu nhà thầu được trao hợp đồng. (2) Thời hạn còn lại của hợp đồng tính tại thời điểm 28 ngày trước ngày có thời điểm đóng thầu. (3) Giá trị hợp đồng còn lại chưa được thanh toán tính tại thời điểm 28 ngày trước ngày có thời điểm đóng thầu. Mẫu 10A PHẠM VI CÔNG VIỆC SỬ DỤNG thầu phụ(1) [BẢNG: Không tiêu đề] Ghi chú: (1) Trường hợp HSYC có quy định về việc sử dụng thầu phụ thì nhà thầu kê khai theo Mẫu này. (2) Nhà thầu ghi cụ thể tên thầu phụ. Trường hợp khi dự thầu chưa xác định được cụ thể danh tính của thầu phụ thì không phải kê khai vào cột này mà chỉ kê khai vào cột “Phạm vi công việc”. Nếu nhà thầu trúng thầu thì khi huy động thầu phụ thực hiện công việc đã kê khai phải được sự chấp thuận của Chủ đầu tư. (3) Nhà thầu ghi cụ thể tên hạng mục công việc dành cho thầu phụ. (4) Nhà thầu ghi cụ thể khối lượng công việc dành cho thầu phụ. (5) Nhà thầu ghi cụ thể giá trị % công việc mà thầu phụ đảm nhận so với giá thầu nhưng không được vượt quá tỷ lệ phần trăm (%) quy định tại Mục 12. 2 Chương I. Trường hợp nhà thầu liên danh, thành viên liên danh được sử dụng thầu phụ đối với phần công việc đảm nhận theo tỷ lệ % quy định tại Mục 12. 2 Chương I. (6) Nhà thầu ghi cụ thể số hợp đồng hoặc văn bản thỏa thuận và đính kèm bản chụp được chứng thực các hồ sơ này trong HSĐX. Trường hợp khi dự thầu chưa xác định được thầu phụ thì để trống cột này. Mẫu 10B BẢNG KÊ KHAI thầu phụ ĐẶC BIỆT(1) Nhà thầu phải cung cấp hồ sơ chứng minh đáp ứng yêu cầu quy định tại Mục 2. 3 Chương II. [BẢNG: Không tiêu đề] Ghi chú: (1) Trường hợp sử dụng thầu phụ đặc biệt thì kê khai theo Mẫu này. (2) Nhà thầu ghi cụ thể tên thầu phụ đặc biệt. (3) Chủ đầu tư ghi cụ thể tên hạng mục công việc sẽ được sử dụng thầu phụ đặc biệt. (4) Nhà thầu ghi cụ thể khối lượng công việc dành cho thầu phụ đặc biệt. (5) Nhà thầu ghi cụ thể giá trị % công việc mà thầu phụ đặc biệt đảm nhận so với giá trị gói thầu. (6) Nhà thầu ghi cụ thể số hợp đồng hoặc văn bản thỏa thuận và đính kèm các hồ sơ này trong HSĐX. Mẫu 10C DANH SÁCH CÁC CÔNG TY CON, CÔNG TY THÀNH VIÊN ĐẢM NHẬN PHẦN CÔNG VIỆC CỦA GÓI THẦU(1) [BẢNG: Không tiêu đề] Ghi chú: (1) Trường hợp nhà thầu dự thầu là công ty mẹ (ví dụ như Tổng công ty) huy động công ty con, công ty thành viên thực hiện một phần công việc gói thầu thì phải kê khai cụ thể tại bảng này. Việc đánh giá kinh nghiệm thực hiện hợp đồng tương tự căn cứ vào giá trị, khối lượng công việc do công ty mẹ, công ty con đảm nhiệm trong gói thầu. Trường hợp nhà thầu dự thầu không phải là công ty mẹ thì không áp dụng Mẫu này. (2) Ghi cụ thể tên công ty con, công ty thành viên. (3) Ghi cụ thể phần công việc đảm nhận của công ty con, công ty thành viên. (4) Ghi cụ thể giá trị % công việc của công ty con, công ty thành viên đảm nhận so với giá thầu. Mẫu 11 BẢNG TIẾN ĐỘ THỰC HIỆN Nhà thầu đề xuất tiến độ thực hiện phù hợp với yêu cầu của Chủ đầu tư và phù hợp với đề xuất kỹ thuật của nhà thầu [BẢNG: Không tiêu đề] Ghi chú: (2), (3), (4), (5): Chủ đầu tư điền theo yêu cầu tại Chương IV. (6): Nhà thầu đề xuất. Phần 2. YÊU VẦU VỀ XÂY LẮP Chương IV. YÊU CẦU VỀ XÂY LẮP I. Giới thiệu về gói thầu 1. Phạm vi công việc của gói thầu. 2. Thời hạn hoàn thành. II. Yêu cầu về tiến độ thực hiện Nêu yêu cầu về thời gian từ khi khởi công đến khi hoàn thành hợp đồng theo ngày/tuần/tháng. Trường hợp ngoài yêu cầu thời hạn hoàn thành cho toàn bộ dự án còn có yêu cầu tiến độ hoàn thành cho từng hạng mục dự án thì lập bảng yêu cầu tiến độ hoàn thành. [BẢNG: Không tiêu đề] III. Yêu cầu về kỹ thuật/chỉ dẫn kỹ thuật 1. Quy định kỹ thuật chính xác và rõ ràng là một điều kiện tiên quyết để nhà thầu đáp ứng một cách thực tế và cạnh tranh các yêu cầu của Chủ đầu tư mà không đặt điều kiện cho HSĐX của nhà thầu. Quy định kỹ thuật phải được soạn thảo để không làm hạn chế cạnh tranh, đồng thời nêu rõ các yêu cầu về trình độ tay nghề, vật tư và hiệu suất sử dụng của các hàng hóa và dịch vụ được cung cấp. Quy định kỹ thuật cần yêu cầu rằng tất cả hàng hóa và vật tư được sử dụng trong dự án đều mới, chưa từng qua sử dụng, thuộc thế hệ mới nhất, đã đưa vào tất cả các cải tiến về thiết kế và vật liệu trừ khi được quy định khác đi trong hợp đồng. 2. Trong yêu cầu về mặt kỹ thuật không được đưa ra các điều kiện nhằm hạn chế sự tham gia của nhà thầu hoặc nhằm tạo lợi thế cho một hoặc một số nhà thầu gây ra sự cạnh tranh không bình đẳng, đồng thời cũng không đưa ra các yêu cầu quá cao dẫn đến làm tăng giá thầu. 3. Chủ đầu tư được đưa ra yêu cầu về ký mã hiệu, nhãn hiệu, xuất xứ cho nguyên nhiên vật liệu, vật tư, máy móc, thiết bị và các yếu tố đầu vào khác. Nhà thầu được chào theo ký mã hiệu, nhãn hiệu, xuất xứ các nguyên nhiên vật liệu, vật tư, máy móc, thiết bị và các yếu tố đầu vào khác theo quy định trong hồ sơ yêu cầu hoặc ký mã hiệu, nhãn hiệu, xuất xứ khác có chất lượng hàng hóa (đặc tính kỹ thuật, tính năng sử dụng) tương đương hoặc tốt hơn. 4. Yêu cầu về bảo hành, bảo trì, duy tu bảo dưỡng (nếu có); 5. Đấu thầu bền vững: Trường hợp có yêu cầu về đấu thầu bền vững thì Chủ đầu tư cần đưa ra quy định bảo đảm sự thân thiện với môi trường, xã hội (sử dụng vật tư, vật liệu xây dựng, thiết bị được chứng nhận nhãn năng lượng, nhãn sinh thái, vật liệu không nung, vật liệu bền vững, thân thiện môi trường, vật liệu có khả năng tái chế, tái sử dụng; biện pháp thi công nhằm hạn chế mức độ xả thải, rác thải, ô nhiễm môi trường, giảm thiểu tác động tiêu cực tới mặt bằng, khu vực thi công. ..) nhưng phải bảo đảm các quy định này là rõ ràng, không làm hạn chế sự tham gia của nhà thầu. 6. Đối với phạm vi công việc gói thầu áp dụng loại hợp đồng theo kết quả đầu ra, các yêu cầu về kỹ thuật do Chủ đầu tư đưa ra cần chú trọng vào sản phẩm đầu ra như tiêu chuẩn, quy cách, thông số kỹ thuật, chất lượng. .. của các công việc này. Chủ đầu tư cũng cần nêu các tiêu chuẩn thi công nhà thầu phải đáp ứng, nhà thầu có thể áp dụng các tiêu chuẩn khác nhưng phải chứng minh các tiêu chuẩn này tương đương hoặc cao hơn tiêu chuẩn do Chủ đầu tư yêu cầu. Về cơ bản, HSYC không cần nêu quy trình, phương pháp thực hiện dịch vụ cụ thể mà nhà thầu phải tuân theo. Nhà thầu được quyền đề xuất quy trình, phương pháp thực hiện mà nhà thầu thấy là thích hợp để thực hiện gói thầu. Yêu cầu về kỹ thuật cần thể hiện các mức độ đáp ứng yêu cầu về kết quả đầu ra tương ứng với số tiền bị giảm trừ giá trị thanh toán trong quá trình khai thác dự án; yêu cầu về chất lượng, độ bền dự án và các yêu cầu khác. IV. Các bản vẽ HSYC này gồm có các bản vẽ trong danh mục sau đây: [BẢNG: Không tiêu đề] Phần 3. ĐIỀU KIỆN HỢP ĐỒNG VÀ BIỂU MẪU HỢP ĐỒNG Căn cứ quy mô, tính chất, loại hợp đồng của gói thầu, Chủ đầu tư, tổ chuyên gia sử dụng các Chương VI, VII, VIII của Mẫu E-HSMT xây lắp một giai đoạn một túi hồ sơ ban hành kèm theo Thông tư số 79/2025/TT-BTC để xây dựng các Chương V. ĐIỀU KIỆN CHUNG, Chương VI. ĐIỀU KIỆN CỤ THỂ, Chương VII. BIỂU MẪU HỢP ĐỒNG cho phù hợp với quy định của Luật Đấu thầu, Nghị định số 214/2025/NĐ-CP. Trong quá trình thực hiện, trường hợp Thông tư số 79/2025/TT-BTC được sửa đổi, bổ sung hoặc thay thế thì áp dụng theo văn bản quy phạm pháp luật sửa đổi, bổ sung hoặc thay thế Thông tư số 79/2025/TT-BTC. Lưu ý: khi sử dụng cần thay đổi các thuật ngữ cho phù hợp như sau: - E-ĐKC thành ĐKC; - E-ĐKCT thành ĐKCT; - E-HSMT thành HSYC; - E-HSDT thành HSĐX.", "type": "bill_of_quantities", "rows": []}], "parsing_metadata": {"bidding_type": null, "detected_sections": {"general_info": [], "technical_requirements": [], "evaluation_criteria": [], "contract_conditions": [], "bidding_process": [], "forms": [], "drawings": [], "bill_of_quantities": []}, "document_info": {"project_name": "/dự toán mua sắm]. 2. nguồn vốn để thực hiện gói thầu: ______ [ghi rõ nguồn vốn đã được xác định hoặ", "package_name": "xây lắp (ban hành kèm theo thông tư số 80/2025/tt-btc ngày 08 tháng 8 năm 2025 của bộ trưởng bộ tài", "owner": "___ [ghi tên, địa chỉ chủ đầu tư] mời nhà thầu nhận hsyc gói thầu ___ [ghi tên gói thầu theo kế hoạc"}, "statistics": {}}, "extraction_metadata": {"source_file": "01A. Mẫu HSYC Xây lắp.docx", "file_type": "bidding_document", "document_category": "construction", "extracted_at": "2025-10-30T19:54:40.828563", "file_size_bytes": 215777, "project_name": "/dự toán mua sắm].", "package_name": "XÂY LẮP", "bidding_method": "CHỈ ĐỊNH THẦU", "owner": "___ [Ghi tên, địa chỉ Chủ đầu tư] mời nhà thầu nhận HSYC gói thầu ___ [Ghi tên gói thầu theo kế hoạch lựa chọn nhà thầu được duyệt] thuộc ___ [Ghi tên dự án/dự toán mua sắm]."}}
