{"content": "Mẫu 1C HỒ SƠ YÊU CẦU GÓI THẦU DỊCH VỤ PHI TƯ VẤN (Ban hành kèm theo Thông tư số 80/2025/TT-BTC ngày 08 tháng 8 năm 2025 của Bộ trưởng Bộ Tài chính) HỒ SƠ YÊU CẦU DỊCH VỤ PHI TƯ VẤN [BẢNG: Không tiêu đề] TỪ NGỮ VIẾT TẮT [BẢNG: Không tiêu đề] Phần 1. THỦ TỤC CHỈ ĐỊNH THẦU Chương I. CHỈ DẪN NHÀ THẦU Mục 1. Phạm vi gói thầu 1. Chủ đầu tư ___ [Ghi tên, địa chỉ Chủ đầu tư] mời nhà thầu nhận HSYC gói thầu___ [Ghi tên gói thầu theo kế hoạch lựa chọn nhà thầu được duyệt] thuộc ___ [Ghi tên dự án/dự toán mua sắm]. 2. Nguồn vốn để thực hiện gói thầu__[Ghi rõ nguồn vốn đã được xác định hoặc phê duyệt; trường hợp sử dụng vốn ODA, vốn vay ưu đãi nước ngoài thì phải ghi rõ tên nhà tài trợ và cơ cấu nguồn vốn, bao gồm vốn tài trợ, vốn đối ứng trong nước]. 3. Thời gian thực hiện gói thầu là: ___ngày [Ghi thời gian cụ thể theo kế hoạch lựa chọn nhà thầu được duyệt], được tính từ ngày hợp đồng có hiệu lực đến ngày nghiệm thu dịch vụ. Mục 2. Hành vi bị cấm trong đấu thầu Hành vi bị cấm trong đấu thầu là hành vi quy định tại Điều 16 của Luật Đấu thầu. Mục 3. Tư cách hợp lệ của nhà thầu 1. Nhà thầu là tổ chức có tư cách hợp lệ khi đáp ứng quy định tại các điểm a, b, c, d, e và g Khoản 1 Điều 5 của Luật Đấu thầu. 2. Nhà thầu là hộ kinh doanh có tư cách hợp lệ khi đáp ứng quy định tại các điểm a, b Khoản 2 và các điểm d, e Khoản 1 Điều 5 của Luật Đấu thầu. Trường hợp pháp luật có liên quan quy định nhà thầu dự thầu, thực hiện hợp đồng phải độc lập với các tổ chức, cá nhân khác thì phải tuân thủ quy định đó. Mục 4. Làm rõ, sửa đổi HSYC 1. Trường hợp nhà thầu cần làm rõ HSYC, nhà thầu gửi văn bản đến Chủ đầu tư trong thời hạn tối thiểu 03 ngày làm việc trước ngày có thời điểm đóng thầu để đánh giá, xử lý. 2. Trường hợp Chủ đầu tư sửa đổi HSYC, Chủ đầu tư có trách nhiệm gửi quyết định sửa đổi và các nội dung sửa đổi tới nhà thầu. Thời gian gửi văn bản sửa đổi HSYC đến nhà thầu là ___ [Ghi số ngày cụ thể, tối thiểu 03 ngày làm việc trước ngày có thời điểm đóng thầu và bảo đảm đủ thời gian để nhà thầu hoàn chỉnh HSĐX]; trường hợp không bảo đảm đủ thời gian như nêu trên thì phải gia hạn thời điểm đóng thầu. Mục 5. Chi phí, đồng tiền, ngôn ngữ khi dự thầu 1. Nhà thầu phải chịu mọi chi phí liên quan đến quá trình dự thầu. 2. Đồng tiền dự thầu và đồng tiền thanh toán là VND. 3. HSĐX cũng như tất cả văn bản và hồ sơ liên quan đến HSĐX được viết bằng tiếng Việt. Các hồ sơ bổ trợ trong HSĐX có thể được viết bằng ngôn ngữ khác, đồng thời kèm theo bản dịch sang tiếng Việt. Trường hợp thiếu bản dịch, Chủ đầu tư có thể yêu cầu nhà thầu gửi bổ sung (nếu cần thiết). Mục 6. Thành phần của HSĐX HSĐX do nhà thầu chuẩn bị phải bao gồm: 1. Đơn dự thầu theo Mẫu 01 Chương III; 2. Thỏa thuận liên danh nếu là nhà thầu liên danh theo Mẫu 03 Chương III; 3. hồ sơ chứng minh tư cách hợp lệ, năng lực và kinh nghiệm của nhà thầu, của người ký đơn dự thầu; 4. Đề xuất kỹ thuật theo quy định tại Mục 8 Chương này; 5. Đề xuất về giá theo Mẫu 04 (04A hoặc 04B hoặc 04C hoặc 04D hoặc 04E hoặc 04G) Chương III; 6. Các nội dung khác ___ [Nêu các nội dung khác tùy theo tính chất, yêu cầu của gói thầu]. Mục 7. giá thầu 1. giá thầu là giá do nhà thầu chào trong đơn dự thầu bao gồm toàn bộ các chi phí (chưa tính giảm giá) để thực hiện gói thầu theo yêu cầu của HSYC, kể cả các loại thuế, phí, lệ phí (nếu có) áp theo thuế suất, mức phí, lệ phí tại thời điểm 28 ngày trước ngày có thời điểm đóng thầu. 2. Nhà thầu phải nộp HSĐX cho toàn bộ công việc được mô tả tại Chương IV và chào giá cho tất cả các công việc nêu trong bảng giá tương ứng quy định tại Chương III. Mục 8. Thành phần đề xuất kỹ thuật Nhà thầu phải nộp đề xuất kỹ thuật, trong đó mô tả cụ thể phương pháp thực hiện công việc, thiết bị, nhân sự, lịch biểu thực hiện và các thông tin cần thiết khác theo quy định tại Chương IV để chứng minh tính phù hợp của đề xuất đối với các yêu cầu công việc và thời hạn cần hoàn thành công việc. Mục 9. Hiệu lực của HSĐX Thời gian có hiệu lực của HSĐX phải bảo đảm theo yêu cầu là ___ [Ghi rõ số ngày tuỳ thuộc quy mô, tính chất của gói thầu, bảo đảm thời gian có hiệu lực đến ngày ký kết hợp đồng] kể từ ngày có thời điểm đóng thầu. 2. Trong trường hợp cần thiết, trước khi hết thời hạn hiệu lực của HSĐX, Chủ đầu tư có thể đề nghị nhà thầu gia hạn hiệu lực của HSĐX. Việc đề nghị gia hạn và chấp thuận gia hạn phải được thể hiện bằng văn bản. Mục 10. Quy cách của HSĐX và chữ ký trong HSĐX 1. Nhà thầu phải chuẩn bị một bản gốc và ______bản chụp HSĐX [Ghi số lượng yêu cầu nhưng không quá 03 bản], ghi rõ \"bản gốc\" và \"bản chụp\" tương ứng. Nhà thầu cần ghi rõ tên gói thầu, tên nhà thầu, tên Chủ đầu tư bên ngoài túi đựng HSĐX. Nhà thầu phải chịu trách nhiệm về tính chính xác và phù hợp giữa bản chụp và bản gốc. Trường hợp có sự sai khác giữa bản gốc và bản chụp thì căn cứ vào bản gốc để đánh giá. 2. Tất cả các thành phần của HSĐX nêu tại Mục 6 Chương I phải được ký bởi người đại diện hợp pháp của nhà thầu. Trường hợp là nhà thầu liên danh thì HSĐX phải có chữ ký của đại diện hợp pháp của tất cả thành viên liên danh hoặc thành viên đại diện nhà thầu liên danh theo phân công trong thỏa thuận liên danh. 3. Những chữ được ghi thêm, ghi chèn vào giữa các dòng, những chữ bị tẩy xóa hoặc viết đè lên sẽ chỉ được coi là hợp lệ nếu có chữ ký ở bên cạnh hoặc tại trang đó của người ký đơn dự thầu. Mục 11. Thời điểm đóng thầu và mở thầu 1. HSĐX do nhà thầu nộp trực tiếp hoặc gửi đến địa chỉ của Chủ đầu tư: __[Ghi địa chỉ] nhưng phải bảo đảm Chủ đầu tư nhận được trước thời điểm đóng thầu: ___ giờ, ngày ___ tháng ___ năm ____ [Ghi thời điểm đóng thầu]. 2. Mở thầu: Chủ đầu tư tiến hành mở thầu bao gồm các nội dung sau: a) Kiểm tra niêm phong; b) Mở hồ sơ và đọc rõ các thông tin về tên nhà thầu: - Tham dự độc lập hay liên danh; - Số lượng bản gốc, bản chụp; - giá thầu chào trong đơn dự thầu; - Giá trị giảm giá (nếu có); - Thời gian có hiệu lực của HSĐX; - Thời gian thực hiện gói thầu; - Các thông tin khác liên quan. Biên bản mở thầu bao gồm các thông tin quy định tại điểm a và điểm b khoản này. Biên bản mở thầu phải được ký xác nhận bởi đại diện của Chủ đầu tư và các nhà thầu tham dự lễ mở thầu. Biên bản này phải được gửi cho các nhà thầu nộp HSĐX. Đại diện của Chủ đầu tư phải ký xác nhận vào bản gốc đơn dự thầu, thư giảm giá (nếu có), giấy ủy quyền của người đại diện theo pháp luật của nhà thầu (nếu có), thỏa thuận liên danh (nếu có), các nội dung đề xuất về tài chính và các nội dung quan trọng khác của từng HSĐX. Mục 12. thầu phụ 1. thầu phụ là tổ chức, cá nhân ký kết hợp đồng với nhà thầu để thực hiện một phần công việc trong bảng giá thầu; không bao gồm tổ chức, cá nhân cung cấp, nguyên liệu, nhiên liệu, vật liệu, vật tư, cấu kiện bán thành phẩm, thiết bị, cho thuê thiết bị thi công. Việc nhà thầu thuê nhân công để thực hiện gói thầu không phải là sử dụng thầu phụ. Trường hợp nhà thầu cần sử dụng thầu phụ thì phải kê khai danh sách thầu phụ theo Mẫu 10A Chương III. Việc sử dụng thầu phụ sẽ không làm thay đổi các trách nhiệm của nhà thầu. Nhà thầu phải chịu trách nhiệm về khối lượng, chất lượng, tiến độ và các trách nhiệm khác đối với phần công việc do thầu phụ thực hiện. Năng lực và kinh nghiệm của thầu phụ sẽ không được đánh giá khi đánh giá HSĐX của nhà thầu. Bản thân nhà thầu phải đáp ứng các tiêu chí năng lực và kinh nghiệm (không xét đến năng lực và kinh nghiệm của thầu phụ). 2. Nhà thầu chỉ được sử dụng thầu phụ thực hiện các công việc với tổng giá trị dành cho thầu phụ không vượt quá ___ [tùy theo quy mô, tính chất gói thầu, Chủ đầu tư ghi tỷ lệ % tối đa dành cho thầu phụ] giá thầu của nhà thầu. Đối với trường hợp liên danh, từng thành viên liên danh chỉ được sử dụng thầu phụ không vượt quá tỷ lệ phần trăm quy định tại Mục này trên giá trị phần công việc mà thành viên liên danh đó đảm nhận trong thỏa thuận liên danh. Mục 13. Đánh giá HSĐX và thương thảo về các đề xuất của nhà thầu 1. Việc đánh giá HSĐX được thực hiện theo quy định tại Chương II. 2. Trong quá trình đánh giá, Chủ đầu tư mời nhà thầu thương thảo về giá bảo đảm đáp ứng tỷ lệ tiết kiệm theo quy định của HSYC, thương thảo, làm rõ hoặc sửa đổi, bổ sung nội dung HSĐX để chứng minh việc đáp ứng yêu cầu về năng lực, kinh nghiệm, tiến độ, khối lượng, chất lượng, giải pháp kỹ thuật, biện pháp tổ chức thực hiện gói thầu và tỷ lệ tiết kiệm. Mục 14. Điều kiện đối với nhà thầu được đề nghị chỉ định thầu Nhà thầu được đề nghị trúng thầu khi đáp ứng đầy đủ các điều kiện sau đây: 1. Có HSĐX hợp lệ; 2. Có năng lực, kinh nghiệm và đề xuất kỹ thuật đáp ứng yêu cầu của HSYC; 3. Có giá đề nghị trúng thầu không vượt giá gói thầu được duyệt và đáp ứng tỷ lệ tiết kiệm tối thiểu__ % giá gói thầu. [Căn cứ quy mô, tính chất, điều kiện cụ thể của gói thầu, Chủ đầu tư quy định trong HSYC mức tỷ lệ tiết kiệm của giá đề nghị trúng thầu để làm cơ sở cho nhà thầu chuẩn bị HSĐX]. Mục 15. Thông báo kết quả lựa chọn nhà thầu Trong thời hạn 05 ngày làm việc kể từ ngày kết quả lựa chọn nhà thầu được phê duyệt, Chủ đầu tư đăng tải thông tin về kết quả lựa chọn nhà thầu lên Hệ thống mạng đấu thầu quốc gia; gửi văn bản thông báo kết quả lựa chọn nhà thầu cho nhà thầu dự thầu. Nội dung thông báo kết quả lựa chọn nhà thầu như sau: a) Thông tin về gói thầu: - Tên gói thầu; - Giá gói thầu hoặc dự toán được duyệt (nếu có); ; - Tên Chủ đầu tư; - Hình thức lựa chọn nhà thầu; - Loại hợp đồng; - Thời gian thực hiện gói thầu. b) Thông tin về nhà thầu trúng thầu: - Tên nhà thầu; - Mã số thuế (nếu có); - giá thầu; - Giá trúng thầu; - Thời gian thực hiện gói thầu; - Thời gian thực hiện hợp đồng. c) Kế hoạch hoàn thiện, ký kết hợp đồng với nhà thầu trúng thầu. Mục 16. Điều kiện ký kết hợp đồng 1. Tại thời điểm ký kết, HSĐX của nhà thầu trúng thầu còn hiệu lực. 2. Tại thời điểm ký kết hợp đồng, nhà thầu trúng thầu phải bảo đảm đáp ứng yêu cầu về năng lực kỹ thuật, tài chính để thực hiện gói thầu theo yêu cầu của HSYC. Trường hợp thực tế nhà thầu không còn đáp ứng cơ bản yêu cầu về năng lực kỹ thuật, tài chính theo quy định nêu trong HSYC thì Chủ đầu tư sẽ từ chối ký kết hợp đồng với nhà thầu và hủy quyết định phê duyệt kết quả lựa chọn nhà thầu. 3. Chủ đầu tư phải bảo đảm các điều kiện về vốn tạm ứng, vốn thanh toán, mặt bằng thực hiện và điều kiện cần thiết khác để triển khai thực hiện gói thầu theo đúng tiến độ. Mục 17. Bảo đảm thực hiện hợp đồng 1. Trước hoặc cùng thời điểm hợp đồng có hiệu lực, nhà thầu được chỉ định thầu phải cung cấp bảo đảm thực hiện hợp đồng theo quy định của HSYC. Trường hợp nhà thầu sử dụng thư bảo lãnh thực hiện hợp đồng thì phải sử dụng Mẫu thư bảo lãnh trong HSYC này hoặc Mẫu thư bảo lãnh khác được Chủ đầu tư chấp thuận. 2. Nhà thầu không được hoàn trả bảo đảm thực hiện hợp đồng trong trường hợp sau đây: a) Từ chối thực hiện hợp đồng khi hợp đồng đã có hiệu lực; b) Vi phạm thỏa thuận trong hợp đồng; c) Thực hiện hợp đồng chậm tiến độ do lỗi của nhà thầu nhưng từ chối gia hạn hiệu lực của bảo đảm thực hiện hợp đồng. Mục 18. Giải quyết kiến nghị 1. Đối với gói thầu thuộc phạm vi điều chỉnh của Luật Đấu thầu a) Khi thấy quyền và lợi ích hợp pháp bị ảnh hưởng, nhà thầu được kiến nghị người có thẩm quyền, Chủ đầu tư, Hội đồng giải quyết kiến nghị đánh giá lại các vấn đề trong quá trình lựa chọn nhà thầu, kết quả lựa chọn nhà thầu theo quy định tại Điều 89 Luật Đấu thầu và các Điều 137, 138 và 139 của Nghị định số 214/2025/NĐ-CP. b) Địa chỉ nhận đơn kiến nghị - Địa chỉ nhận đơn kiến nghị của Chủ đầu tư: ______ [ghi đầy đủ tên, địa chỉ, số điện thoại, email]. - Địa chỉ nhận đơn kiến nghị của người có thẩm quyền: ______ [ghi đầy đủ tên, địa chỉ, số điện thoại, email]. - Địa chỉ bộ phận thường trực giúp việc của Hội đồng giải quyết kiến nghị: ___ [ghi đầy đủ tên, địa chỉ, số điện thoại, email]. 2. Đối với hoạt động lựa chọn nhà thầu quy định tại điểm d Khoản 7 Điều 3 của Luật Đấu thầu hoặc hoạt động lựa chọn nhà thầu không thuộc phạm vi điều chỉnh của Luật Đấu thầu: Khi thấy quyền và lợi ích hợp pháp bị ảnh hưởng, nhà thầu, cơ quan, tổ chức được kiến nghị theo quy trình sau: ______ [ghi cụ thể quy trình, thủ tục của việc giải quyết kiến nghị của đơn vị, tổ chức đồng thời ghi rõ email, địa chỉ của cá nhân/tổ chức/đơn vị giải quyết kiến nghị]. Mục 19. Ưu đãi trong lựa chọn nhà thầu Ưu đãi: _____ [Chủ đầu tư ghi rõ đối tượng, điều kiện ưu đãi theo quy định tại Nghị quyết của Quốc hội hoặc văn bản quy phạm pháp luật (nếu có)]. Chương II. TIÊU CHUẨN ĐÁNH GIÁ HSĐX Mục 1. Đánh giá tính hợp lệ của HSĐX 1. 1. Kiểm tra HSĐX a) Kiểm tra số lượng bản gốc, bản chụp HSĐX; b) Kiểm tra các thành phần của HSĐX theo quy định tại Mục 6 Chương I; c) Kiểm tra sự thống nhất nội dung giữa bản gốc và bản chụp để phục vụ quá trình đánh giá chi tiết HSĐX. 1. 2. Đánh giá tính hợp lệ của HSĐX HSĐX của nhà thầu được đánh giá là hợp lệ khi đáp ứng đầy đủ các nội dung sau đây: a) Có bản gốc HSĐX; b) Có đơn dự thầu được đại diện hợp pháp của nhà thầu ký tên, đóng dấu (nếu có) theo yêu cầu của HSYC; thời gian ký đơn dự thầu phải sau thời điểm phát hành HSYC; không đề xuất các giá thầu khác nhau hoặc có kèm theo điều kiện gây bất lợi cho Chủ đầu tư. Đối với nhà thầu liên danh, đơn dự thầu phải do đại diện hợp pháp của từng thành viên liên danh ký tên, đóng dấu (nếu có) hoặc thành viên được phân công thay mặt liên danh ký đơn dự thầu theo phân công trách nhiệm trong thỏa thuận liên danh; c) Hiệu lực của HSĐX đáp ứng yêu cầu theo quy định tại Mục 9 Chương I; d) Có thỏa thuận liên danh (trong trường hợp liên danh) được đại diện hợp pháp của từng thành viên liên danh ký tên, đóng dấu (nếu có); thỏa thuận liên danh phải nêu rõ nội dung công việc cụ thể và ước tính giá trị tương ứng mà từng thành viên trong liên danh sẽ thực hiện. Việc phân chia công việc trong liên danh phải căn cứ các hạng mục nêu trong bảng giá thầu quy định tại Mẫu 04 (04A hoặc 04B hoặc 04C hoặc 04D hoặc 04E hoặc 04G) Chương III hoặc theo các công việc thuộc quá trình sản xuất hạng mục trong bảng giá thầu; không được phân chia các công việc không thuộc các hạng mục này hoặc không thuộc quá trình sản xuất các hạng mục này; đ) Nhà thầu bảo đảm tư cách hợp lệ theo quy định tại Mục 3 Chương I. e) Trong thời hạn 03 năm trước thời điểm đóng thầu, nhà thầu không có nhân sự (ký kết hợp đồng lao động với nhà thầu tại thời điểm nhân sự thực hiện hành vi vi phạm) bị Tòa án kết án có hành vi vi phạm quy định về đấu thầu gây hậu quả nghiêm trọng theo quy định của pháp luật về hình sự nhằm mục đích cho nhà thầu đó trúng thầu. Nhà thầu có HSĐX hợp lệ được đánh giá, đánh giá trong bước tiếp theo. Mục 2. Tiêu chuẩn đánh giá về năng lực, kinh nghiệm Nhà thầu được đánh giá là đạt về năng lực và kinh nghiệm khi đáp ứng tất cả các tiêu chuẩn đánh giá quy định tại Mục 2. 1, 2. 2. Năng lực và kinh nghiệm của thầu phụ sẽ không được đánh giá khi đánh giá HSĐX của nhà thầu. Bản thân nhà thầu phải đáp ứng các tiêu chí đánh giá về năng lực và kinh nghiệm. 2. 1. Tiêu chuẩn đánh giá về năng lực và kinh nghiệm Tiêu chuẩn đánh giá năng lực và kinh nghiệm thực hiện theo quy định tại Bảng số 01 Chương này, nhà thầu được đánh giá đạt tất cả nội dung quy định tại Bảng số 01 thì đáp ứng yêu cầu về năng lực và kinh nghiệm. Không đưa ra yêu cầu nhà thầu đã từng thực hiện một hoặc nhiều hợp đồng trên một địa bàn cụ thể hoặc nhà thầu phải có kinh nghiệm cung cấp dịch vụ trên một địa bàn cụ thể như là tiêu chí để loại bỏ nhà thầu. Trường hợp đồng tiền nêu trong các hợp đồng tương tự hoặc xác nhận thanh toán của Chủ đầu tư đối với những hợp đồng cung cấp dịch vụ phi tư vấn đã thực hiện hoặc tờ khai nộp thuế hoặc các hồ sơ liên quan chứng minh năng lực, kinh nghiệm của nhà thầu không phải VND thì khi lập HSĐX, nhà thầu phải quy đổi về VND nêu tại HSYC để làm cơ sở đánh giá HSĐX. Việc quy đổi được áp dụng tỷ giá quy đổi của ___ [ghi căn cứ xác định tỷ giá quy đổi, thường áp dụng tỷ giá bán ra của một ngân hàng thương mại hoạt động tại Việt Nam] tại ngày ký hợp đồng tương tự đó. Trường hợp nhà thầu dự thầu là công ty mẹ (ví dụ như Tổng công ty) có huy động công ty con, công ty thành viên thực hiện một phần công việc của gói thầu thì nhà thầu phải kê khai cụ thể phần công việc dành cho các công ty con, công ty thành viên theo Mẫu 10B Chương III. Việc đánh giá kinh nghiệm thực hiện hợp đồng tương tự căn cứ vào giá trị, khối lượng công việc do công ty mẹ, công ty con, công ty thành viên đảm nhiệm trong gói thầu. [BẢNG: Bảng số 01 BẢNG TIÊU CHUẨN ĐÁNH GIÁ VỀ NĂNG LỰC VÀ KINH NGHIỆM] Ghi chú: (1) Ghi thời gian yêu cầu, thông thường là 03 năm trước năm có thời điểm đóng thầu. Ví dụ: từ ngày 01 tháng 01 năm 2022 đến thời điểm đóng thầu. (2) Hợp đồng cung cấp dịch vụ phi tư vấn không hoàn thành do lỗi của nhà thầu bao gồm: - Hợp đồng cung cấp dịch vụ phi tư vấn bị Chủ đầu tư kết luận nhà thầu không hoàn thành và nhà thầu không phản đối; - Hợp đồng cung cấp dịch vụ phi tư vấn bị Chủ đầu tư kết luận nhà thầu không hoàn thành, không được nhà thầu chấp thuận nhưng đã được trọng tài hoặc Tòa án kết luận theo hướng bất lợi cho nhà thầu. Các hợp đồng cung cấp dịch vụ phi tư vấn không hoàn thành không bao gồm các hợp đồng mà quyết định của Chủ đầu tư đã bị bác bỏ bằng cơ chế giải quyết tranh chấp. Việc xác định hợp đồng không hoàn thành phải dựa trên tất cả những thông tin về tranh chấp hoặc kiện tụng được giải quyết theo quy định của cơ chế giải quyết tranh chấp của hợp đồng tương ứng và khi mà nhà thầu đã hết tất cả các cơ hội có thể khiếu nại. Đối với các hợp đồng chậm tiến độ do lỗi của nhà thầu nhưng vẫn hoàn thành hợp đồng thì không được coi là hợp đồng không hoàn thành. Đối với nhà thầu liên danh mà chỉ có một hoặc một số thành viên trong liên danh vi phạm và bị cấm tham gia hoạt động đấu thầu theo quy định tại Khoản 1 Điều 133 của Nghị định số 214/2025/NĐ-CP thì thành viên liên danh còn lại không bị coi là không hoàn thành hợp đồng do lỗi của nhà thầu. Trường hợp một hoặc một số thành viên liên danh vi phạm hợp đồng, không còn năng lực để tiếp tục thực hiện hợp đồng, làm ảnh hưởng nghiêm trọng đến tiến độ, chất lượng, hiệu quả của gói thầu thì chỉ một hoặc một số thành viên liên danh vi phạm hợp đồng bị coi là không hoàn thành hợp đồng, thành viên còn lại không bị coi là không hoàn thành hợp đồng do lỗi của nhà thầu. (3) Nhà thầu cung cấp hồ sơ chứng minh đã thực hiện nghĩa vụ kê khai thuế và nộp thuế thu nhập doanh nghiệp (thuế thu nhập cá nhân đối với nhà thầu là hộ kinh doanh) của năm tài chính gần nhất so với thời điểm đóng thầu. Nghĩa vụ kê khai thuế và nộp thuế phải được thực hiện trước thời điểm đóng thầu. Nghĩa vụ nộp thuế là nộp thuế với giá trị thuế tương ứng với thuế suất, thu nhập chịu thuế, doanh thu tính thuế nhà thầu kê khai trên Hệ thống thuế điện tử (số thuế đã nộp tương ứng với số thuế phải nộp); trường hợp được chậm nộp thuế, miễn thuế, giảm thuế theo chính sách của Nhà nước thì thực hiện theo quy định này. Nhà thầu nộp các hồ sơ như sau: - Tờ khai thuế (hoặc thông báo nộp tiền của cơ quan thuế đối với hộ kinh doanh) và Giấy nộp tiền có xác nhận của cơ quan thuế được in từ Hệ thống thuế điện tử hoặc - Tờ khai thuế (hoặc thông báo nộp tiền của cơ quan thuế đối với hộ kinh doanh) và xác nhận của cơ quan thuế về việc thực hiện nghĩa vụ thuế. Trường hợp thời điểm đóng thầu sau ngày kết thúc năm tài chính của nhà thầu (năm Y) và trước hoặc trong ngày cuối cùng của tháng thứ 3 tính từ ngày kết thúc năm Y, yêu cầu đã thực hiện nghĩa vụ kê khai thuế và nộp thuế áp dụng đối với năm tài chính trước năm Y (năm Y-1). Ví dụ: Thời điểm đóng thầu là ngày 20/3/2024, năm tài chính của nhà thầu kết thúc vào ngày 31/12 thì nhà thầu phải chứng minh đã thực hiện nghĩa vụ kê khai thuế và nộp thuế của năm 2022. (4) Đối với doanh nghiệp khởi nghiệp sáng tạo trong nước khi chào thầu sản phẩm đổi mới sáng tạo là dịch vụ phi tư vấn của doanh nghiệp đó theo quy định tại Khoản 4 Điều 6 của Nghị định số 214/2025/NĐ-CP không phải đáp ứng tiêu chí này trong thời hạn 06 năm kể từ khi sản phẩm lần đầu được sản xuất và đủ điều kiện để đưa ra thị trường. Nhà thầu trong nước thuộc trường hợp quy định tại điểm g Khoản 1 Điều 10 của Luật Đấu thầu khi chào thầu sản phẩm do nhà thầu đó sản xuất không phải đáp ứng tiêu chí này trong thời hạn 05 năm kể từ khi được cơ quan có thẩm quyền công nhận. (5) Ghi thời gian yêu cầu, thông thường từ 03 đến 05 năm trước năm có thời điểm đóng thầu. Trường hợp nhà thầu có số năm thành lập ít hơn số năm theo yêu cầu của HSYC thì doanh thu bình quân hằng năm (không bao gồm thuế VAT) được tính trên số năm mà nhà thầu thành lập. Trong trường hợp này, nếu doanh thu bình quân hằng năm (không bao gồm thuế VAT) của nhà thầu đáp ứng yêu cầu về giá trị của HSYC thì nhà thầu vẫn được đánh giá tiếp mà không bị loại. Đối với nhà thầu là hộ kinh doanh, không bắt buộc phải nộp báo cáo tài chính nhưng nhà thầu phải cung cấp hồ sơ chứng minh doanh thu tương ứng với nghĩa vụ thuế. Trường hợp thời điểm đóng thầu sau ngày kết thúc năm tài chính của nhà thầu (năm Y) và trước hoặc trong ngày cuối cùng của tháng thứ 3 tính từ ngày kết thúc năm Y, yêu cầu về nộp báo cáo tài chính áp dụng đối với các năm trước của năm Y (năm Y-1; Y-2. ..). (Ví dụ: Thời điểm đóng thầu là vào ngày 20/3/2024, năm tài chính của nhà thầu kết thúc vào ngày 31/12 và HSYC yêu cầu nhà thầu nộp báo cáo tài chính của 03 năm gần nhất thì nhà thầu phải nộp báo cáo tài chính của các năm 2020, 2021, 2022). Ví dụ: Doanh thu bình quân hằng năm (không bao gồm thuế VAT) của 03 năm tài chính gần nhất so với thời điểm đóng thầu. Trong trường hợp này, thời điểm đóng thầu là ngày 15/11/2024 thì nhà thầu phải nộp báo cáo tài chính của các năm 2021, 2022, 2023. Nhà thầu được thành lập vào năm 2022 nhưng doanh thu trung bình của năm 2022 và năm 2023 đáp ứng yêu cầu thì nhà thầu được tiếp tục đánh giá. (6) Cách tính toán thông thường về mức yêu cầu doanh thu bình quân hằng năm (không bao gồm thuế VAT): a) Trường hợp thời gian thực hiện gói thầu từ 12 tháng trở lên thì cách tính doanh thu như sau: Yêu cầu tối thiểu về mức doanh thu bình quân hằng năm (không bao gồm thuế VAT) = [(Giá gói thầu - giá trị thuế VAT)/thời gian thực hiện gói thầu theo năm] x k. Thông thường yêu cầu hệ số “k” trong công thức này là từ 1 đến 1, 5. b) Trường hợp thời gian thực hiện gói thầu dưới 12 tháng thì cách tính doanh thu như sau: Yêu cầu tối thiểu về mức doanh thu bình quân hằng năm (không bao gồm thuế VAT) = (Giá gói thầu - giá trị thuế VAT) x k. Thông thường yêu cầu hệ số “k” trong công thức này là 1, 0. Đối với gói thầu bảo hiểm thì có thể đưa ra yêu cầu về doanh thu bình quân hằng năm cao hơn so với cách tính theo công thức nêu trên nhưng phải bảo đảm không được làm hạn chế sự tham gia của nhà thầu. (7) Đối với các hợp đồng mà nhà thầu đã tham gia với tư cách là thành viên liên danh hoặc thầu phụ thì chỉ tính giá trị phần việc do nhà thầu thực hiện. (8) Đối với các hợp đồng mà Chủ đầu tư, tổ chuyên gia có bằng chứng cho thấy nhà thầu đã thực hiện với tư cách thầu phụ do được chuyển nhượng thầu bất hợp pháp, vi phạm quy định tại Khoản 8 Điều 16 của Luật Đấu thầu thì hợp đồng này sẽ không được đánh giá, đánh giá. (9) Ghi thời gian yêu cầu thông thường là từ 03 đến 05 năm trước năm có thời điểm đóng thầu. Ví dụ: từ ngày 01 tháng 01 năm 2019 đến thời điểm đóng thầu. (10) Chủ đầu tư, tổ chuyên gia căn cứ vào nội dung, phạm vi công việc của gói thầu đang xét để đưa ra yêu cầu về tính chất của hợp đồng tương tự. Trường hợp gói thầu có nhiều hạng mục thì có thể chỉ quy định về tính chất tương tự cho các hạng mục chính của gói thầu. (11) Quy mô Hợp đồng tương tự: Trường hợp gói thầu có nhiều hạng mục công việc thì phải ghi giá trị tương ứng của từng hạng mục công việc để làm cơ sở đánh giá kinh nghiệm thực hiện hợp đồng tương tự của nhà thầu. Trường hợp gói thầu bao gồm nhiều hạng mục công việc khác nhau thì tùy theo tính chất, quy mô gói thầu, Chủ đầu tư, tổ chuyên gia đưa ra yêu cầu về quy mô tương tự trên cơ sở các hạng mục chính của gói thầu (phải nêu rõ các hạng mục chính) hoặc yêu cầu về quy mô tương tự trên cơ sở tất cả các hạng mục của gói thầu, trong đó ghi quy mô yêu cầu đối với mỗi hạng mục chính hoặc mỗi hạng mục công việc. Quy mô của hợp đồng tương tự thông thường khoảng 30% giá trị của gói thầu đang xét (hoặc 30% tổng giá trị của các hạng mục chính trong trường hợp gói thầu nhiều hạng mục công việc khác nhau và Chủ đầu tư yêu cầu quy mô trên cơ sở các hạng mục chính của gói thầu); đối với các công việc đặc thù hoặc ở các địa phương mà năng lực của nhà thầu trên địa bàn còn hạn chế hoặc gói thầu cung cấp dịch vụ phi tư vấn có khối lượng mời thầu lớn thì có thể điều chỉnh giảm yêu cầu về quy mô của hợp đồng tương tự xuống trong khoảng 20% giá trị của gói thầu đang xét (hoặc 20% tổng giá trị của các hạng mục chính trong trường hợp gói thầu nhiều hạng mục công việc khác nhau và Chủ đầu tư yêu cầu quy mô trên cơ sở các hạng mục chính của gói thầu). Việc đánh giá về quy mô của hợp đồng tương tự căn cứ vào giá trị hoàn thành, được nghiệm thu như sau: (i) Có ít nhất 01 hợp đồng hoàn thành cung cấp đầy đủ các hạng mục tương tự có giá trị đáp ứng tối thiểu là đáp ứng tối thiểu 30% (hoặc 20% trong trường hợp gói thầu có công việc đặc thù hoặc ở các địa phương mà năng lực của nhà thầu trên địa bàn còn hạn chế hoặc gói thầu có khối lượng mời thầu lớn) giá trị của gói thầu đang xét (hoặc tổng giá trị của các hạng mục chính trong trường hợp gói thầu nhiều hạng mục công việc khác nhau và Chủ đầu tư yêu cầu quy mô trên cơ sở các hạng mục chính của gói thầu), trong đó từng hạng mục tương tự trong hợp đồng không cần có giá trị đáp ứng 30% (hoặc 20% trong trường hợp gói thầu có công việc đặc thù hoặc ở các địa phương mà năng lực của nhà thầu trên địa bàn còn hạn chế hoặc gói thầu có khối lượng mời thầu lớn) giá trị tương ứng của hạng mục đó trong gói thầu (hoặc giá trị tương ứng của từng hạng mục chính trong trường hợp gói thầu nhiều hạng mục công việc khác nhau và Chủ đầu tư yêu cầu quy mô trên cơ sở các hạng mục chính của gói thầu); hoặc (ii) Có các hạng mục công việc tương tự đã thực hiện trong các hợp đồng khác nhau (hợp đồng có thể đã hoàn thành hoặc đang thực hiện, chưa nghiệm thu, thanh lý) hoặc trong một hợp đồng (hợp đồng chưa hoàn thành) và bảo đảm tổng giá trị của từng hạng mục công việc tương tự đã thực hiện đáp ứng tối thiểu 30% (hoặc 20% trong trường hợp gói thầu có công việc đặc thù hoặc ở các địa phương mà năng lực của nhà thầu trên địa bàn còn hạn chế hoặc gói thầu có khối lượng mời thầu lớn) giá trị của từng hạng mục công việc tương ứng trong gói thầu đang xét (hoặc giá trị của từng hạng mục chính tương ứng trong trường hợp gói thầu nhiều hạng mục công việc khác nhau và Chủ đầu tư yêu cầu quy mô trên cơ sở các hạng mục chính của gói thầu) và tổng giá trị các hạng mục đã thực hiện phải đáp ứng tối thiểu 30% (hoặc 20% trong trường hợp gói thầu có công việc đặc thù hoặc ở các địa phương mà năng lực của nhà thầu trên địa bàn còn hạn chế hoặc gói thầu có khối lượng mời thầu lớn) giá trị của gói thầu đang xét (hoặc tổng giá trị của các hạng mục chính trong trường hợp gói thầu nhiều hạng mục công việc khác nhau và Chủ đầu tư yêu cầu quy mô trên cơ sở các hạng mục chính của gói thầu). Được cộng gộp giá trị của hạng mục tương tự trong các hợp đồng khác nhau để xác định tổng giá trị hạng mục tương tự đáp ứng yêu cầu mà không yêu cầu giá trị của hạng mục tương tự trong mỗi hợp đồng phải đáp ứng tối thiểu 30% (hoặc 20% trong trường hợp gói thầu có công việc đặc thù hoặc ở các địa phương mà năng lực của nhà thầu trên địa bàn còn hạn chế hoặc gói thầu có khối lượng mời thầu lớn) giá trị hạng mục của gói thầu đang xét (hoặc giá trị của hạng mục chính trong trường hợp gói thầu nhiều hạng mục công việc khác nhau và Chủ đầu tư yêu cầu quy mô trên cơ sở các hạng mục chính của gói thầu). Trong đó: + Hạng mục công việc đã thực hiện là một phần hoặc toàn bộ khối lượng công việc trong hạng mục đã được nghiệm thu trong khoảng thời gian quy định mà không xét đến thời gian ký kết hợp đồng. Thời điểm xác nhận hạng mục công việc đã thực hiện để xác định hạng mục công việc tương tự là thời điểm nghiệm thu công việc, không căn cứ vào thời điểm ký kết hợp đồng. + Hợp đồng hoàn thành là hợp đồng có toàn bộ công việc đã được nghiệm thu hoặc hợp đồng đã được thanh lý. Thời điểm xác nhận hợp đồng hoàn thành để xác định hợp đồng tương tự là thời điểm nghiệm thu công việc, không căn cứ vào thời điểm ký kết hợp đồng. Đối với gói thầu phi tư vấn có tính chất công việc lặp lại theo chu kỳ qua các năm dẫn đến thời gian thực hiện hợp đồng kéo dài thì giá trị hợp đồng tương tự được xác định khoảng 30% (hoặc 20% trong trường hợp gói thầu có công việc đặc thù hoặc ở các địa phương mà năng lực của nhà thầu trên địa bàn còn hạn chế hoặc gói thầu có khối lượng mời thầu lớn) giá trị của phần công việc tính theo 01 chu kỳ (01 năm) mà không tính theo tổng giá trị gói thầu qua các năm. Trong trường hợp này, việc đánh giá về quy mô, tính chất của hợp đồng tương tự cũng được xét theo 01 chu kỳ (01 năm) tương ứng. Nhà thầu trong nước thuộc trường hợp quy định tại điểm g Khoản 1 Điều 10 của Luật Đấu thầu khi chào thầu sản phẩm do nhà thầu đó sản xuất không phải đáp ứng tiêu chí này trong thời hạn 05 năm kể từ khi được cơ quan có thẩm quyền công nhận. Ví dụ 1: Gói thầu đang xét là gói thầu thuê dịch vụ dọn vệ sinh tòa nhà trong 04 năm với giá trị 8. 800. 000. 000 VNĐ thì HSYC có thể yêu cầu về giá trị của hợp đồng tương tự trong 01 chu kỳ (01 năm) là 660. 000. 000 VNĐ. Trong cả 02 trường hợp sau đây, nhà thầu X đều được đánh giá là đáp ứng yêu cầu về giá trị hợp đồng tương tự của gói thầu này: - Nhà thầu X có hợp đồng dọn vệ sinh tòa nhà trong 48 tháng với Chủ đầu tư A (đang trong quá trình thực hiện, chưa hoàn thành, chưa được thanh lý), nhưng tính đến thời điểm dự thầu, nhà thầu X đã thực hiện được 16 tháng, trong đó giá trị công việc đã được nghiệm thu 12 tháng đầu là 660. 000. 000 VNĐ; - Nhà thầu X có hợp đồng hoàn thành N1 dọn vệ sinh tòa nhà, thời gian thực hiện hợp đồng trong 06 tháng với giá trị là 300. 000. 000 VNĐ; hợp đồng N2 dọn vệ sinh tòa nhà, thời gian thực hiện hợp đồng trong 24 tháng với giá trị là 800. 000. 000 VNĐ, trong đó giá trị công việc đã được nghiệm thu 12 tháng đầu là 400. 000. 000 VNĐ. Như vậy, tổng giá trị hạng mục dọn vệ sinh tòa nhà của nhà thầu X là 700. 000. 000 VNĐ. Ví dụ 2: Gói thầu đang xét là gói thầu cung cấp dịch vụ giặt là, giá gói thầu là 10 tỷ đồng, thời gian thực hiện là 06 tháng yêu cầu hợp đồng tương tự có giá trị 30% là 03 tỷ đồng. Nhà thầu X có hợp đồng A (chưa hoàn thành, chưa được thanh lý) có giá trị công việc cung cấp dịch vụ giặt là (đã được nghiệm thu) là 02 tỷ đồng; hợp đồng B (chưa hoàn thành, chưa được thanh lý) có giá trị công việc cung cấp dịch vụ giặt là (đã được nghiệm thu) là 01 tỷ đồng thì nhà thầu X được đánh giá là đáp ứng yêu cầu về giá trị hợp đồng tương tự của gói thầu này. Ví dụ 3: Gói thầu đang xét là gói thầu cung cấp dịch vụ gồm 02 hạng mục công việc khác nhau (N1, N2) với giá gói thầu là 07 tỷ đồng (trong đó, hạng mục N1 giá trị 04 tỷ đồng; hạng mục N2 giá trị 03 tỷ đồng), thời gian thực hiện 60 ngày, yêu cầu hợp đồng tương tự có giá trị 30% là 2, 1 tỷ đồng. Trong cả 02 trường hợp sau đây, nhà thầu X đều được đánh giá là đáp ứng yêu cầu về giá trị hợp đồng tương tự của gói thầu này: - Nhà thầu X có 1 hợp đồng đã hoàn thành có đầy đủ 02 hạng mục N1, N2 và tổng giá trị 02 hạng mục N1, N2 là 2, 5 tỷ đồng. - Nhà thầu X có các hợp đồng sau: + Hợp đồng A (chưa hoàn thành, chưa được thanh lý) có giá trị công việc N1 (đã được nghiệm thu) là 0, 5 tỷ đồng; hợp đồng B (chưa hoàn thành, chưa được thanh lý) có giá trị công việc N1 (đã được nghiệm thu) là 0, 8 tỷ đồng, tổng giá trị hạng mục công việc N1 đã được nghiệm thu là 1, 3 tỷ đồng, lớn hơn yêu cầu hạng mục N1 (30% x 04 tỷ đồng). + Hợp đồng C (chưa hoàn thành, chưa được thanh lý) có giá trị công việc N2 (đã được nghiệm thu) là 0, 6 tỷ đồng; hợp đồng D (chưa hoàn thành, chưa được thanh lý) có giá trị công việc N2 (đã được nghiệm thu) là 0, 5 tỷ đồng. Như vậy, tổng giá trị hạng mục công việc N2 là 1, 1 tỷ đồng, lớn hơn yêu cầu hạng mục N2 (30% x 03 tỷ đồng). Bảng số Y BẢNG YÊU CẦU VỀ HỢP ĐỒNG TƯƠNG TỰ (Áp dụng đối với gói thầu có nhiều hạng mục dịch vụ (*)) [BẢNG: Không tiêu đề] Ghi chú: (1) Giá trị tại cột này được Chủ đầu tư xác định theo nguyên tắc nêu tại ghi chú số (10), (11) Bảng số 01 Chương này. 2. 2. Tiêu chuẩn đánh giá về nhân sự chủ chốt và thiết bị chủ yếu a) Nhân sự chủ chốt Không yêu cầu về nhân sự chủ chốt đối với gói thầu dịch vụ phi tư vấn không đòi hỏi nhân sự có chuyên môn cao, trừ trường hợp cần lao động có trình độ cao, lao động lành nghề thực hiện công việc đặc thù. Trường hợp dịch vụ phi tư vấn có yếu tố đặc thù, phức tạp cần thiết phải có nhân sự có trình độ cao, lao động lành nghề, nhiều kinh nghiệm đảm nhận thì có thể đưa ra yêu cầu về huy động nhân sự chủ chốt để thực hiện các công việc đặc thù, phức tạp này. Ngoài ra, không yêu cầu nhân sự chủ chốt là lao động phổ thông. Trường hợp HSYC có yêu cầu về nhân sự chủ chốt thì nhà thầu phải chứng minh khả năng huy động các nhân sự chủ chốt đã đề xuất. Nhân sự chủ chốt có thể thuộc biên chế của nhà thầu hoặc do nhà thầu huy động. Trường hợp nhân sự chủ chốt mà nhà thầu kê khai trong HSĐX không đáp ứng yêu cầu hoặc không chứng minh được khả năng huy động nhân sự (bao gồm cả trường hợp nhân sự đã huy động cho hợp đồng khác có thời gian làm việc trùng với thời gian thực hiện gói thầu này) thì Chủ đầu tư cho phép nhà thầu bổ sung, thay thế. Trường hợp nhà thầu không có nhân sự chủ chốt thay thế đáp ứng yêu cầu của HSYC thì nhà thầu bị loại. Trường hợp nhà thầu cố ý kê khai nhân sự chủ chốt không trung thực trong HSĐX nhằm làm sai lệch kết quả lựa chọn nhà thầu thì nhà thầu không được thay thế nhân sự khác, HSĐX của nhà thầu bị loại và nhà thầu sẽ bị coi là gian lận theo quy định tại điểm b Khoản 4 Điều 16 của Luật Đấu thầu và bị xử lý theo quy định tại Khoản 1 Điều 133 của Nghị định số 214/2025/NĐ-CP. Kinh nghiệm trong các công việc tương tự được thể hiện ở số năm tối thiểu nhân sự thực hiện các công việc tương tự hoặc số hợp đồng tối thiểu trong các công việc tương tự. Số năm kinh nghiệm của nhân sự chủ chốt được tính từ thời điểm nhân sự bắt đầu thực hiện công việc tương tự đó đến thời điểm đóng thầu. Nhà thầu phải cung cấp thông tin chi tiết về các nhân sự chủ chốt được đề xuất theo các Mẫu 07A, 07B và 07C Chương III để chứng minh rằng mình có đầy đủ nhân sự cho các vị trí chủ chốt đáp ứng những yêu cầu sau đây: Bảng số 02: Yêu cầu về nhân sự chủ chốt (1) [BẢNG: Không tiêu đề] Ghi chú: (1) Trường hợp gói thầu không có yêu cầu về nhân sự chủ chốt thì Chủ đầu tư không nhập Bảng này. (2) Chỉ quy định trong trường hợp pháp luật chuyên ngành có yêu cầu về bằng cấp/chứng chỉ chuyên môn. b) Thiết bị chủ yếu dự kiến huy động để thực hiện gói thầu Căn cứ vào quy mô, tính chất của gói thầu, Chủ đầu tư đưa ra yêu cầu về thiết bị chủ yếu dự kiến huy động và số lượng để thực hiện gói thầu cho phù hợp. Chỉ quy định về thiết bị chủ yếu đối với các thiết bị đặc chủng, đặc thù bắt buộc phải có để triển khai thực hiện gói thầu. Thiết bị chủ yếu có thể thuộc sở hữu của nhà thầu hoặc do nhà thầu huy động. Trường hợp thiết bị chủ yếu mà nhà thầu đề xuất trong HSĐX không đáp ứng yêu cầu thì Chủ đầu tư cho phép nhà thầu bổ sung, thay thế. Trường hợp nhà thầu không có thiết bị thay thế đáp ứng yêu cầu của HSYC thì nhà thầu bị loại. Trường hợp nhà thầu cố ý kê khai thiết bị chủ yếu không trung thực trong HSĐX nhằm làm sai lệch kết quả lựa chọn nhà thầu thì nhà thầu không được thay thế thiết bị khác, HSĐX của nhà thầu bị loại và nhà thầu sẽ bị coi là gian lận theo quy định tại điểm b Khoản 4 Điều 16 của Luật Đấu thầu và bị xử lý theo quy định tại Khoản 1 Điều 133 của Nghị định số 214/2025/NĐ-CP. Nhà thầu phải cung cấp thông tin chi tiết về các thiết bị chủ yếu được đề xuất theo Mẫu 07D Chương III để chứng minh rằng mình có đầy đủ thiết bị đáp ứng những yêu cầu sau đây: Bảng số 03: Yêu cầu về thiết bị chủ yếu [BẢNG: Không tiêu đề] c) Trường hợp nhà thầu trúng thầu và ký kết hợp đồng, nhà thầu có nghĩa vụ huy động nhân sự chủ chốt, thiết bị chủ yếu như đã đề xuất ban đầu hoặc đề xuất thay đổi theo quy định tại Mục này. Trường hợp không huy động được nhân sự chủ chốt, thiết bị chủ yếu, nhà thầu bị phạt hợp đồng. Mục 3. Tiêu chuẩn đánh giá về kỹ thuật Sử dụng tiêu chí đạt/không đạt để xây dựng tiêu chuẩn đánh giá về kỹ thuật. Đối với các tiêu chí đánh giá tổng quát, chỉ sử dụng tiêu chí đạt, không đạt. Đối với các tiêu chí chi tiết cơ bản trong tiêu chí tổng quát, chỉ sử dụng tiêu chí đạt, không đạt; đối với các tiêu chí chi tiết không cơ bản trong tiêu chí tổng quát, ngoài tiêu chí đạt, không đạt, được áp dụng thêm tiêu chí chấp nhận được nhưng không được vượt quá 30% tổng số các tiêu chí chi tiết trong tiêu chí tổng quát đó. Tiêu chí tổng quát được đánh giá là đạt khi tất cả các tiêu chí chi tiết cơ bản được đánh giá là đạt và các tiêu chí chi tiết không cơ bản được đánh giá là đạt hoặc chấp nhận được. Việc xây dựng tiêu chuẩn đánh giá về kỹ thuật dựa trên yêu cầu về các sản phẩm đầu ra được nêu tại Chương IV, thông tin về kết quả thực hiện hợp đồng của nhà thầu theo quy định tại Điều 19 và Điều 20 của Nghị định số 214/2025/NĐ-CP và các yêu cầu khác nêu trong HSYC. Căn cứ vào từng gói thầu cụ thể, khi lập HSYC, Chủ đầu tư phải cụ thể hóa các tiêu chí làm cơ sở đánh giá về kỹ thuật bao gồm: - Tính hiệu quả của việc cung cấp dịch vụ; - Mức độ hiểu biết về tính chất và mục đích công việc; - Tính hợp lý và khả thi của kế hoạch, các giải pháp kỹ thuật, biện pháp tổ chức cung cấp dịch vụ; - Mức độ đáp ứng hệ thống đảm bảo chất lượng và phương pháp thực hiện; - Mức độ đáp ứng các yêu cầu về tiêu chuẩn thực hiện dịch vụ; - Tiến độ thực hiện gói thầu đáp ứng yêu cầu của HSYC; - Bảo đảm điều kiện vệ sinh môi trường và các điều kiện khác như phòng cháy, chữa cháy, an toàn lao động (nếu có); - Mức độ đáp ứng các yêu cầu về bảo hành, bảo trì (nếu có); - Tiêu chí đấu thầu bền vững (nếu có): các yếu tố thân thiện môi trường (nếu có) như: việc sử dụng các vật tư, vật liệu; biện pháp tổ chức thi công; dây chuyền, kỹ thuật thi công và các yếu tố khác (nếu có); - Thông tin về kết quả thực hiện hợp đồng của nhà thầu theo quy định tại Điều 19 và Điều 20 của Nghị định số 214/2025/NĐ-CP; - Các yếu tố cần thiết khác. HSĐX được đánh giá là đáp ứng yêu cầu về kỹ thuật khi có tất cả các tiêu chí tổng quát đều được đánh giá là đạt. Mục 4. Tiêu chuẩn đánh giá về tài chính Bước 1. Xác định giá thầu; Bước 2. Sửa lỗi, hiệu chỉnh sai lệch theo quy định tại Điều 31 của Nghị định số 214/2025/NĐ-CP (nếu có); Bước 3. Xác định giá thầu sau sửa lỗi, hiệu chỉnh sai lệch (nếu có), trừ đi giá trị giảm giá (nếu có) và đáp ứng tỷ lệ tiết kiệm theo quy định tại Mục 14 Chương I. Chương III. BIỂU MẪU Mẫu 01 ĐƠN DỰ THẦU ________, ngày ____ tháng ____ năm ____ Kính gửi: __________________ [Ghi tên Chủ đầu tư] (sau đây gọi là Chủ đầu tư) Sau khi nghiên cứu hồ sơ yêu cầu và văn bản sửa đổi hồ sơ yêu cầu số ____ [Ghi số của văn bản sửa đổi, nếu có] mà chúng tôi đã nhận được, chúng tôi, ____ [Ghi tên nhà thầu], có địa chỉ tại _____ [Ghi địa chỉ của nhà thầu] cam kết thực hiện gói thầu____ [Ghi tên gói thầu] theo đúng yêu cầu của hồ sơ yêu cầu với tổng số tiền là____ [Ghi giá trị bằng số, bằng chữ và đồng tiền dự thầu] cùng với biểu giá kèm theo. Thời gian thực hiện gói thầu là ____ [Ghi thời gian thực hiện tất cả các công việc theo yêu cầu của gói thầu]. Hồ sơ đề xuất này có hiệu lực trong thời gian ____ ngày, kể từ ngày ____ tháng ____ năm ____ [Ghi ngày có thời điểm đóng thầu]. Chúng tôi cam kết: 1. Không đang trong quá trình thực hiện thủ tục giải thể hoặc bị thu hồi giấy chứng nhận đăng ký doanh nghiệp, giấy chứng nhận đăng ký hợp tác xã, liên hiệp hợp tác xã, tổ hợp tác, không thuộc trường hợp mất khả năng thanh toán theo quy định của pháp luật về phá sản (không đang trong quá trình chấm dứt hoạt động hoặc bị thu hồi giấy chứng nhận đăng ký hộ kinh doanh đối với nhà thầu là hộ kinh doanh). 2. Đã thực hiện nghĩa vụ kê khai thuế và nộp thuế của năm tài chính gần nhất so với thời điểm đóng thầu; 3. Không đang trong thời gian bị cấm dự thầu theo quy định của pháp luật đấu thầu; 4. Không đang bị truy cứu trách nhiệm hình sự (chủ hộ không đang bị truy cứu trách nhiệm hình sự trong trường hợp nhà thầu là hộ kinh doanh); 5. Trong thời hạn 03 năm trước thời điểm đóng thầu, nhà thầu không có nhân sự (ký kết hợp đồng lao động với nhà thầu tại thời điểm nhân sự thực hiện hành vi vi phạm) bị tòa án kết án có hành vi vi phạm quy định về đấu thầu gây hậu quả nghiêm trọng theo quy định của pháp luật về hình sự nhằm mục đích cho nhà thầu trúng thầu(2). 6. Không thực hiện các hành vi tham nhũng, hối lộ, thông thầu, cản trở và các hành vi vi phạm quy định khác của pháp luật đấu thầu khi tham dự gói thầu này. 7. Những thông tin kê khai trong HSĐX là trung thực. 8. Trường hợp trúng thầu, HSĐX và các văn bản bổ sung, làm rõ HSĐX tạo thành thỏa thuận ràng buộc trách nhiệm giữa hai bên cho tới khi hợp đồng được ký kết. 9. Nếu HSĐX của chúng tôi được chấp nhận, chúng tôi sẽ thực hiện biện pháp bảo đảm thực hiện hợp đồng theo quy định của HSYC. Đại diện hợp pháp của nhà thầu(1) [Ghi tên, chức danh, ký tên và đóng dấu] Ghi chú: (1) Trường hợp đại diện theo pháp luật của nhà thầu ủy quyền cho cấp dưới ký đơn dự thầu thì phải gửi kèm theo Giấy ủy quyền theo Mẫu 02 Chương này. Trường hợp tại điều lệ công ty hoặc tại các hồ sơ khác liên quan có phân công trách nhiệm cho cấp dưới ký đơn dự thầu thì phải gửi kèm theo bản chụp các văn bản, hồ sơ này (không cần lập Giấy ủy quyền theo Mẫu 02 Chương này). (2) HSYC không được yêu cầu nhà thầu phải nộp lý lịch tư pháp của nhân sự để chứng minh cho nội dung đánh giá này. Nội dung này chỉ yêu cầu nhà thầu cam kết trong Đơn này. Mẫu 02 GIẤY ỦY QUYỀN(1) Hôm nay, ngày ____ tháng ____ năm ____, tại ____ Tôi là__ [Ghi tên, số CCCD hoặc số hộ chiếu, chức danh của người đại diện theo pháp luật của nhà thầu], là người đại diện theo pháp luật của __ [Ghi tên nhà thầu] có địa chỉ tại___ [Ghi địa chỉ của nhà thầu] bằng văn bản này ủy quyền cho____ [Ghi tên, số CCCD hoặc số hộ chiếu, chức danh của người được ủy quyền] thực hiện các công việc sau đây trong quá trình dự thầu gói thầu__ [Ghi tên gói thầu] thuộc ____ [Ghi tên dự án/dự toán mua sắm] do____ [Ghi tên Chủ đầu tư] tổ chức: [- Ký đơn dự thầu; - Ký thỏa thuận liên danh (nếu có); - Ký các văn bản, hồ sơ để giao dịch với Chủ đầu tư trong quá trình dự thầu, kể cả văn bản giải trình, làm rõ HSĐX; - Tham gia quá trình thương thảo (nếu có), hoàn thiện hợp đồng; - Ký kết hợp đồng với Chủ đầu tư nếu được chỉ định thầu.] (2) Người được ủy quyền nêu trên chỉ thực hiện các công việc trong phạm vi ủy quyền với tư cách là đại diện hợp pháp của____ [Ghi tên nhà thầu]. ____ [Ghi tên nhà thầu] chịu trách nhiệm hoàn toàn về những công việc do ____ [Ghi tên người được ủy quyền] thực hiện trong phạm vi ủy quyền. Giấy ủy quyền có hiệu lực kể từ ngày ____ đến ngày ____(3). Giấy ủy quyền này được lập thành ____ bản có giá trị pháp lý như nhau, người ủy quyền giữ ____ bản, người được ủy quyền giữ ____ bản. [BẢNG: Không tiêu đề] Ghi chú: (1) Trường hợp ủy quyền thì bản gốc giấy ủy quyền phải được gửi cho Chủ đầu tư cùng với đơn dự thầu. Việc ủy quyền của người đại diện theo pháp luật của nhà thầu cho cấp phó, cấp dưới, giám đốc chi nhánh, người đứng đầu văn phòng đại diện của nhà thầu để thay mặt cho người đại diện theo pháp luật của nhà thầu thực hiện một hoặc các nội dung công việc nêu trên đây. Việc sử dụng con dấu trong trường hợp được ủy quyền có thể là dấu của nhà thầu hoặc dấu của đơn vị mà cá nhân liên quan được ủy quyền. Người được ủy quyền không được tiếp tục ủy quyền cho người khác. (2) Phạm vi ủy quyền bao gồm một hoặc nhiều công việc nêu trên. (3) Ghi ngày có hiệu lực và ngày hết hiệu lực của giấy ủy quyền phù hợp với quá trình dự thầu và phải bảo đảm có hiệu lực trước ngày thực hiện các công việc được ủy quyền. Mẫu 03 THỎA THUẬN LIÊN DANH(1), ngày tháng năm Gói thầu: ___ [Ghi tên gói thầu] Thuộc: ___ [Ghi tên dự án/dự toán mua sắm] - Căn cứ ___ [Luật Đấu thầu](2); - Căn cứ ___ (2); - Căn cứ hồ sơ yêu cầu gói thầu ____[Ghi tên gói thầu] ngày ___ tháng ____ năm ____ [Ngày được ghi trên HSYC]; Chúng tôi, đại diện cho các bên ký thỏa thuận liên danh, gồm có: Tên thành viên liên danh [Ghi tên từng thành viên liên danh] Đại diện là ông/bà: Chức vụ: Địa chỉ: Điện thoại: E-mail: Tài khoản: Mã số thuế: Giấy ủy quyền số __ ngày __tháng __ năm __ (trường hợp được ủy quyền). Các bên (sau đây gọi là thành viên) thống nhất ký kết thỏa thuận liên danh với các nội dung sau: Điều 1. Nguyên tắc chung 1. Các thành viên tự nguyện hình thành liên danh để dự thầu gói thầu [Ghi tên gói thầu] thuộc ___ [Ghi tên dự án/dự toán mua sắm]. 2. Các thành viên thống nhất tên gọi của liên danh cho mọi giao dịch liên quan đến gói thầu này là: [Ghi tên của liên danh]. 3. Các thành viên cam kết không thành viên nào có quyền từ chối thực hiện các trách nhiệm và nghĩa vụ quy định trong hợp đồng. Trường hợp thành viên của liên danh từ chối hoàn thành trách nhiệm riêng của mình như đã thỏa thuận thì thành viên đó bị xử lý như sau: - Bồi thường thiệt hại cho các bên trong liên danh - Bồi thường thiệt hại cho Chủ đầu tư theo quy định nêu trong hợp đồng - Hình thức xử lý khác [Ghi rõ hình thức xử lý khác]. Điều 2. Phân công trách nhiệm Các thành viên thống nhất chịu trách nhiệm chung, trách nhiệm riêng để thực hiện gói thầu [Ghi tên gói thầu] thuộc ___ [Ghi tên dự án/dự toán mua sắm] đối với từng thành viên như sau: 1. Thành viên đứng đầu liên danh Các bên nhất trí ủy quyền cho [Ghi tên một bên] làm thành viên đứng đầu liên danh, đại diện cho liên danh trong những phần việc sau(3): [- Ký đơn dự thầu; - Ký các văn bản, hồ sơ để giao dịch với Chủ đầu tư trong quá trình dự thầu, kể cả văn bản đề nghị làm rõ HSYC và văn bản giải trình, làm rõ HSĐX; - Tham gia quá trình thương thảo (nếu có), hoàn thiện hợp đồng; - Các công việc khác trừ việc ký kết hợp đồng [Ghi rõ nội dung các công việc khác (nếu có)]. 2. Các thành viên trong liên danh thỏa thuận phân công trách nhiệm thực hiện công việc theo bảng dưới đây(4): [BẢNG: Không tiêu đề] Điều 3. Hiệu lực của thỏa thuận liên danh 1. Thỏa thuận liên danh có hiệu lực kể từ ngày ký. 2. Thỏa thuận liên danh chấm dứt hiệu lực trong các trường hợp sau: - Các bên hoàn thành trách nhiệm và nghĩa vụ của mình và tiến hành thanh lý hợp đồng; - Các bên cùng thỏa thuận chấm dứt; - Nhà thầu liên danh không được chỉ định thầu; - Hủy thầu gói thầu [Ghi tên gói thầu] thuộc ___ [Ghi tên dự án/dự toán mua sắm] theo thông báo của Chủ đầu tư. Thỏa thuận liên danh được lập thành bản, mỗi bên giữ bản, các bản thỏa thuận có giá trị pháp lý như nhau. ĐẠI DIỆN HỢP PHÁP CỦA THÀNH VIÊN ĐỨNG ĐẦU LIÊN DANH(5) [Ghi tên, chức danh, ký tên và đóng dấu] ĐẠI DIỆN HỢP PHÁP CỦA THÀNH VIÊN LIÊN DANH [Ghi tên từng thành viên, chức danh, ký tên và đóng dấu] Ghi chú: (1) Căn cứ quy mô, tính chất của gói thầu, nội dung thỏa thuận liên danh theo mẫu này có thể được sửa đổi bổ sung cho phù hợp. (2) Cập nhật các văn bản quy phạm pháp luật theo quy định hiện hành. (3) Phạm vi ủy quyền bao gồm một hoặc nhiều công việc nêu trên. (4) Nhà thầu phải ghi rõ nội dung công việc cụ thể và ước tính giá trị tương ứng mà từng thành viên trong liên danh sẽ thực hiện, trách nhiệm chung, trách nhiệm của từng thành viên, kể cả thành viên đứng đầu liên danh. Việc phân chia công việc trong liên danh phải căn cứ các hạng mục nêu trong bảng giá thầu quy định tại Mẫu 04 (04A hoặc 04B hoặc 04C hoặc 04D hoặc 04E hoặc 04G) Chương III; không được phân chia các công việc không thuộc các hạng mục này hoặc không thuộc quá trình sản xuất các hạng mục này. (5) Đại diện hợp pháp của thành viên liên danh có thể là người đại diện theo pháp luật hoặc người được người đại diện theo pháp luật ủy quyền. Mẫu 04A BẢNG giá thầu VÀ TIẾN ĐỘ THỰC HIỆN (áp dụng đối với loại hợp đồng trọn gói, hợp đồng theo kết quả đầu ra) Chủ đầu tư liệt kê chi tiết danh mục các dịch vụ yêu cầu, mô tả ngắn gọn dịch vụ theo Bảng sau: [BẢNG: Không tiêu đề] Đại diện hợp pháp của nhà thầu [ghi tên, chức danh, ký tên và đóng dấu] Ghi chú: (2), (4), (5), (6), (7): Chủ đầu tư ghi tên các hạng mục công việc cụ thể, đơn vị tính, khối lượng, địa điểm thực hiện dịch vụ, ngày hoàn thành các nội dung công việc để nhà thầu làm cơ sở chào giá thầu. (3) Chủ đầu tư ghi dẫn chiếu cụ thể đến nội dung yêu cầu về kỹ thuật/chỉ dẫn kỹ thuật để thực hiện hạng mục công việc tương ứng trong Chương IV hoặc trong hồ sơ chỉ dẫn kỹ thuật (tên Mục, số trang, số quyển. ..) để nhà thầu thuận tiện trong việc đánh giá, nghiên cứu các yêu cầu về kỹ thuật/chỉ dẫn kỹ thuật làm cơ sở chào giá thầu. (8): Nhà thầu điền. (9), (10): Nhà thầu điền đơn giá, thành tiền cho tất cả các hạng mục công việc. Đơn giá nhà thầu chào bao gồm các chi phí cần thiết để thực hiện gói thầu, trong đó bao gồm các chi phí thuế, phí, lệ phí, chi phí dự phòng (nếu có). Khi dự thầu, nhà thầu phải chịu trách nhiệm tìm hiểu, tính toán và chào đầy đủ các loại thuế, phí, lệ phí (nếu có) theo thuế suất, mức phí, lệ phí tại thời điểm 28 ngày trước ngày có thời điểm đóng thầu theo quy định. Mẫu 04B [BẢNG: BẢNG giá thầu VÀ TIẾN ĐỘ THỰC HIỆN (áp dụng đối với loại hợp đồng theo đơn giá cố định) Chủ đầu t] Mẫu 04C [BẢNG: BẢNG giá thầu VÀ TIẾN ĐỘ THỰC HIỆN (áp dụng đối với loại hợp đồng theo đơn giá điều chỉnh) Chủ đầ] Mẫu 04D BẢNG giá thầu VÀ TIẾN ĐỘ THỰC HIỆN (áp dụng đối với loại hợp đồng theo tỷ lệ phần trăm) Chủ đầu tư liệt kê chi tiết danh mục các dịch vụ, mô tả ngắn gọn dịch vụ cung cấp theo Bảng sau: [BẢNG: Không tiêu đề] Mẫu 04E [BẢNG: BẢNG giá thầu VÀ TIẾN ĐỘ THỰC HIỆN (áp dụng đối với loại hợp đồng theo thời gian) Chủ đầu tư liệ] Mẫu 04G BẢNG giá thầu VÀ TIẾN ĐỘ THỰC HIỆN (áp dụng đối với loại hợp đồng hỗn hợp) Chủ đầu tư liệt kê chi tiết danh mục các dịch vụ yêu cầu, mô tả ngắn gọn dịch vụ yêu cầu cung cấp theo Bảng sau: I. Các hạng mục áp dụng loại hợp đồng trọn gói, hợp đồng theo kết quả đầu ra [BẢNG: Không tiêu đề] Ghi chú: (2), (4), (5), (6), (7): Chủ đầu tư ghi tên các hạng mục công việc cụ thể, đơn vị tính, khối lượng, địa điểm thực hiện dịch vụ, ngày hoàn thành các nội dung công việc để nhà thầu làm cơ sở chào giá thầu. (3) Chủ đầu tư ghi dẫn chiếu cụ thể đến nội dung yêu cầu về kỹ thuật/chỉ dẫn kỹ thuật để thực hiện hạng mục công việc tương ứng trong Chương IV hoặc trong hồ sơ chỉ dẫn kỹ thuật (tên Mục, số trang, số quyển. ..) để nhà thầu thuận tiện trong việc đánh giá, nghiên cứu các yêu cầu về kỹ thuật/chỉ dẫn kỹ thuật làm cơ sở chào giá thầu. (8): Nhà thầu điền. (9), (10): Nhà thầu điền đơn giá, thành tiền cho tất cả các hạng mục công việc. Đơn giá nhà thầu chào bao gồm các chi phí cần thiết để thực hiện gói thầu, trong đó bao gồm các chi phí thuế, phí, lệ phí, chi phí dự phòng (nếu có). Khi dự thầu, nhà thầu phải chịu trách nhiệm tìm hiểu, tính toán và chào đầy đủ các loại thuế, phí, lệ phí (nếu có) theo thuế suất, mức phí, lệ phí tại thời điểm 28 ngày trước ngày có thời điểm đóng thầu theo quy định. II. Các hạng mục áp dụng loại hợp đồng theo đơn giá cố định [BẢNG: Không tiêu đề] III. Các hạng mục áp dụng loại hợp đồng theo đơn giá điều chỉnh [BẢNG: Không tiêu đề] Ghi chú: (2), (4), (5), (6), (7) Chủ đầu tư ghi tên các hạng mục công việc cụ thể, đơn vị tính, khối lượng, địa điểm thực hiện dịch vụ, ngày hoàn thành để nhà thầu làm cơ sở chào thầu. (3) Chủ đầu tư ghi dẫn chiếu cụ thể đến nội dung yêu cầu về kỹ thuật/chỉ dẫn kỹ thuật để thực hiện hạng mục công việc tương ứng trong Chương IV hoặc trong hồ sơ chỉ dẫn kỹ thuật (tên Mục, số trang, số quyển. ..) để nhà thầu thuận tiện trong việc đánh giá, nghiên cứu các yêu cầu về kỹ thuật/chỉ dẫn kỹ thuật làm cơ sở chào giá thầu. (*) Trong HSYC phải ghi rõ tỷ lệ dự phòng cho khối lượng phát sinh và chi phí dự phòng trượt giá (b2%) làm cơ sở để nhà thầu chào thầu. Khi dự thầu, nhà thầu phải chào chi phí dự phòng cho khối lượng phát sinh và chi phí dự phòng trượt giá với giá trị bằng tỷ lệ phần trăm (%) quy định trong HSYC (b2%) nhân với chi phí của các hạng mục do nhà thầu chào (A). Chi phí dự phòng chỉ được sử dụng khi có phát sinh khối lượng công việc trong thực tế và có trượt giá. (8): Nhà thầu điền. (9), (10): Nhà thầu điền đơn giá, thành tiền cho tất cả các hạng mục công việc. Đơn giá nhà thầu chào bao gồm các chi phí cần thiết để thực hiện gói thầu, trong đó bao gồm các chi phí thuế, phí, lệ phí (nếu có). Khi dự thầu, nhà thầu phải chịu trách nhiệm tìm hiểu, tính toán và chào đầy đủ các loại thuế, phí, lệ phí (nếu có) theo thuế suất, mức phí, lệ phí tại thời điểm 28 ngày trước ngày có thời điểm đóng thầu theo quy định. IV. Các hạng mục áp dụng loại hợp đồng theo thời gian [BẢNG: Không tiêu đề] Ghi chú: (2), (4), (5), (6), (7) Chủ đầu tư ghi tên các hạng mục công việc cụ thể, khối lượng từng ngày (tháng), số ngày/tháng thực hiện, đơn vị tính, địa điểm thực hiện dịch vụ làm cơ sở để nhà thầu chào thầu (3) Chủ đầu tư ghi dẫn chiếu cụ thể đến nội dung yêu cầu về kỹ thuật/chỉ dẫn kỹ thuật để thực hiện hạng mục công việc tương ứng trong Chương IV hoặc trong hồ sơ chỉ dẫn kỹ thuật (tên Mục, số trang, số quyển. ..) để nhà thầu thuận tiện trong việc đánh giá, nghiên cứu các yêu cầu về kỹ thuật/chỉ dẫn kỹ thuật làm cơ sở chào giá thầu. (8), (9) Chủ đầu tư ghi số ngày kể từ ngày hợp đồng có hiệu lực hoặc kể từ ngày Chủ đầu tư yêu cầu thực hiện dịch vụ đối với trường hợp thực hiện dịch vụ lặp lại nhiều lần. (*)Trong HSYC phải ghi rõ tỷ lệ dự phòng cho khối lượng phát sinh theo thời gian (b3%) làm cơ sở để nhà thầu chào thầu. Khi dự thầu, nhà thầu phải chào chi phí dự phòng cho khối lượng phát sinh theo thời gian với giá trị bằng tỷ lệ phần trăm (%) quy định trong HSYC (b3%) nhân với Chi phí của các hạng mục do nhà thầu chào (A). Chi phí dự phòng chỉ được sử dụng khi có phát sinh khối lượng công việc trong thực tế. (10) Ngày bắt đầu thực hiện dịch vụ do nhà thầu đề xuất phải nằm trong khoảng thời gian yêu cầu. Nhà thầu đề xuất thời gian bắt đầu thực hiện dịch vụ sớm hơn ngày bắt đầu thực hiện dịch vụ thì không được tính ưu tiên và không bị loại, trừ trường hợp yêu cầu kỹ thuật có quy định khác. Nhà thầu đề xuất thời gian bắt đầu thực hiện dịch vụ muộn hơn khoảng thời gian này thì HSĐX của nhà thầu sẽ bị loại. (11), (12): Nhà thầu điền đơn giá theo ngày (tháng), thành tiền cho hạng mục công việc. Đơn giá nhà thầu chào bao gồm các chi phí cần thiết để thực hiện gói thầu, trong đó bao gồm các chi phí thuế, phí, lệ phí (nếu có). Khi dự thầu, nhà thầu phải chịu trách nhiệm tìm hiểu, tính toán và chào đầy đủ các loại thuế, phí, lệ phí (nếu có) theo thuế suất, mức phí, lệ phí tại thời điểm 28 ngày trước ngày có thời điểm đóng thầu theo quy định. V. Tổng hợp các hạng mục [BẢNG: Không tiêu đề] Đại diện hợp pháp của nhà thầu [ghi tên, chức danh, ký tên và đóng dấu] Mẫu 05 BẢN KÊ KHAI THÔNG TIN VỀ NHÀ THẦU (1) Ngày: _________________ Tên gói thầu: _________________ [BẢNG: Không tiêu đề] Ghi chú: (1) Đối với nhà thầu liên danh thì từng thành viên phải kê khai theo Mẫu này. Mẫu 06 [BẢNG: Không tiêu đề] Thông tin về từng hợp đồng, mỗi hợp đồng cần bảo đảm các thông tin sau đây: [BẢNG: Không tiêu đề] Nhà thầu nghiên cứu kỹ HSYC và đề xuất các hợp đồng tương tự khác nhau để bảo đảm đáp ứng yêu cầu của HSYC. Nhà thầu phải gửi kèm theo bản chụp các văn bản, hồ sơ liên quan đến các hợp đồng đó (xác nhận của Chủ đầu tư về hợp đồng thực hiện theo các nội dung liên quan trong bảng trên. ..). Ghi chú: (1) Trong trường hợp liên danh, từng thành viên trong liên danh kê khai theo Mẫu này. Trường hợp nhà thầu có nhiều hợp đồng tương tự thì kê khai từng hợp đồng theo Mẫu này. Trường hợp HSYC không yêu cầu về Kinh nghiệm cụ thể trong thực hiện hợp đồng tương tự thì bỏ qua Bảng này. (2) Nhà thầu chỉ kê khai nội dung tương tự với yêu cầu của gói thầu. (3) Trường hợp giá trị hợp đồng không tính bằng VND thì quy đổi sang VND theo tỷ giá theo quy định tại Mục 2. 1 Chương II để làm cơ sở đánh giá. Mẫu 07A BẢNG ĐỀ XUẤT NHÂN SỰ CHỦ CHỐT Nhà thầu phải kê khai những nhân sự chủ chốt theo quy định tại điểm a Mục 2. 2 Chương II và phải chứng minh khả năng sẵn sàng huy động các nhân sự này để tham gia thực hiện gói thầu. Nhân sự chủ chốt có thể thuộc biên chế của nhà thầu hoặc do nhà thầu huy động. Trường hợp nhân sự chủ chốt mà nhà thầu kê khai trong HSĐX không đáp ứng yêu cầu của HSYC (bao gồm cả trường hợp nhân sự đã huy động cho hợp đồng khác có thời gian làm việc trùng với thời gian thực hiện gói thầu này) thì Chủ đầu tư cho phép nhà thầu bổ sung, thay thế nhân sự chủ chốt để đáp ứng yêu cầu của HSYC. Trường hợp nhà thầu không có nhân sự thay thế đáp ứng yêu cầu của HSYC thì HSĐX bị loại. Trường hợp nhà thầu cố ý kê khai nhân sự chủ chốt không trung thực trong HSĐX nhằm làm sai lệch kết quả lựa chọn nhà thầu thì nhà thầu không được thay thế nhân sự khác, HSĐX của nhà thầu bị loại và nhà thầu sẽ bị coi là gian lận theo quy định tại điểm b Khoản 4 Điều 16 của Luật Đấu thầu và bị xử lý theo quy định tại Khoản 1 Điều 133 của Nghị định số 214/2025/NĐ-CP. [BẢNG: Không tiêu đề] Mẫu 07B [BẢNG: Không tiêu đề] Nhà thầu phải cung cấp tất cả các thông tin trong HSĐX theo yêu cầu tại Bảng trên. Mẫu 07C [BẢNG: BẢNG KINH NGHIỆM CHUYÊN MÔN] Liệt kê theo trình tự thời gian quá trình công tác của chuyên gia, không cần liệt kê các công việc đã làm không phù hợp hoặc không liên quan với công việc đang yêu cầu. Nhà thầu phải cung cấp tất cả các thông tin được yêu cầu. Mẫu 07D BẢNG KÊ KHAI THIẾT BỊ CHỦ YẾU Nhà thầu phải kê khai những thiết bị chủ yếu theo quy định tại điểm b Mục 2. 2 Chương II và phải chứng minh khả năng sẵn sàng huy động các thiết bị này để tham gia thực hiện gói thầu. Thiết bị chủ yếu có thể thuộc sở hữu của nhà thầu hoặc do nhà thầu huy động. Trường hợp thiết bị mà nhà thầu kê khai trong HSĐX không đáp ứng yêu cầu của HSYC thì Chủ đầu tư cho phép nhà thầu bổ sung, thay thế thiết bị để đáp ứng yêu cầu của HSYC. Trường hợp nhà thầu không có thiết bị thay thế đáp ứng yêu cầu của HSĐX thì nhà thầu bị loại. Trường hợp nhà thầu cố ý kê khai thiết bị chủ yếu không trung thực trong HSĐX nhằm làm sai lệch kết quả lựa chọn nhà thầu thì nhà thầu không được thay thế thiết bị khác, HSĐX của nhà thầu bị loại và nhà thầu sẽ bị coi là gian lận theo quy định tại điểm b Khoản 4 Điều 16 của Luật Đấu thầu và bị xử lý theo quy định tại Khoản 1 Điều 133 của Nghị định số 214/2025/NĐ-CP. [BẢNG: Không tiêu đề] Đối với các thiết bị không thuộc sở hữu của mình thì nhà thầu phải kê khai thêm các thông tin dưới đây: [BẢNG: Không tiêu đề] Mẫu 08 HỢP ĐỒNG CUNG CẤP DỊCH VỤ PHI TƯ VẤN KHÔNG HOÀN THÀNH DO LỖI CỦA NHÀ THẦU Tên nhà thầu: ________________ Ngày: ______________________ Tên thành viên của nhà thầu liên danh (nếu có): _________________ [BẢNG: Không tiêu đề] Ghi chú: (1) Nhà thầu phải kê khai chính xác, trung thực các hợp đồng cung cấp dịch vụ phi tư vấn không hoàn thành do lỗi của nhà thầu trong quá khứ. Trường hợp Chủ đầu tư phát hiện nhà thầu có hợp đồng cung cấp dịch vụ phi tư vấn không hoàn thành do lỗi của nhà thầu trong quá khứ mà không kê khai thì được coi là có hành vi gian lận và HSĐX của nhà thầu sẽ bị loại. Trường hợp nhà thầu liên danh thì từng thành viên của nhà thầu liên danh phải kê khai theo Mẫu này. Mẫu 09 TÌNH HÌNH TÀI CHÍNH CỦA NHÀ THẦU(1) Tên nhà thầu: ________________ Ngày: ______________________ [BẢNG: Không tiêu đề] Ghi chú: (1) Trường hợp nhà thầu liên danh thì từng thành viên liên danh phải kê khai theo Mẫu này. (2) Để xác định doanh thu bình quân hằng năm (không bao gồm thuế VAT), nhà thầu chia tổng doanh thu của các năm (không bao gồm thuế VAT) cho số năm dựa trên thông tin đã được cung cấp. Doanh thu hằng năm được tính bằng tổng doanh thu trong báo cáo tài chính của năm đó (chưa bao gồm thuế VAT). Doanh thu bình quân hằng năm (không bao gồm thuế VAT) = tổng doanh thu từng năm (không bao gồm thuế VAT) theo yêu cầu của HSYC/số năm. Trường hợp nhà thầu mới thành lập không đủ số năm theo yêu cầu của HSYC thì Doanh thu bình quân hằng năm (không bao gồm thuế VAT) được tính trên cơ sở số năm mà nhà thầu có số liệu tài chính. Nhà thầu phải nộp các hồ sơ như sau: Bản sao các báo cáo tài chính (các bảng cân đối kế toán bao gồm tất cả thuyết minh có liên quan, và các báo cáo kết quả kinh doanh) cho các năm như đã nêu trên, tuân thủ các điều kiện sau: 1. Phản ánh tình hình tài chính của nhà thầu hoặc thành viên liên danh (nếu là nhà thầu liên danh) mà không phải tình hình tài chính của một chủ thể liên kết như công ty mẹ liên kết với công ty con hoặc công ty liên kết với nhà thầu hoặc thành viên liên danh. 2. Các báo cáo tài chính phải hoàn chỉnh, đầy đủ nội dung theo quy định. 3. Các báo cáo tài chính phải tương ứng với các kỳ kế toán đã hoàn thành kèm theo bản chụp được chứng thực một trong các hồ sơ sau đây: - Biên bản kiểm tra quyết toán thuế; - Tờ khai tự quyết toán thuế (thuế giá trị gia tăng và thuế thu nhập doanh nghiệp) có xác nhận của cơ quan thuế về thời điểm đã nộp tờ khai; - hồ sơ chứng minh việc nhà thầu đã kê khai quyết toán thuế điện tử; - Văn bản xác nhận của cơ quan quản lý thuế (xác nhận số nộp cả năm) về việc thực hiện nghĩa vụ nộp thuế; - Báo cáo kiểm toán (nếu có); - Các hồ sơ khác. Các hồ sơ trên đây phải phù hợp với số liệu nhà thầu đã kê khai trên Hệ thống Thuế điện tử tại thời điểm đóng thầu. Mẫu 10A PHẠM VI CÔNG VIỆC SỬ DỤNG thầu phụ(1) [BẢNG: Không tiêu đề] Ghi chú: (1) Trường hợp HSYC có quy định về việc sử dụng thầu phụ thì nhà thầu kê khai theo Mẫu này. Đối với gói thầu của dự án thuộc lĩnh vực khoa học, kỹ thuật, đổi mới sáng tạo và chuyển đổi số tổ chức đấu thầu trong nước, nhà thầu trong nước được sử dụng thầu phụ là nhà thầu nước ngoài đối với phần công việc đặc thù mà nhà thầu trong nước chưa thực hiện được hoặc cần chuyển giao kỹ thuật theo quy định tại Khoản 4 Điều 11 Luật Đấu thầu. (2) Nhà thầu ghi cụ thể tên thầu phụ. Trường hợp khi dự thầu chưa xác định được cụ thể danh tính của thầu phụ thì không phải kê khai vào cột này mà chỉ kê khai vào cột “Phạm vi công việc”. Nếu nhà thầu trúng thầu thì khi huy động thầu phụ thực hiện công việc đã kê khai phải được sự chấp thuận của Chủ đầu tư. (3) Nhà thầu ghi cụ thể tên hạng mục công việc dành cho thầu phụ. (4) Nhà thầu ghi cụ thể khối lượng công việc dành cho thầu phụ. (5) Nhà thầu ghi cụ thể giá trị % công việc mà thầu phụ đảm nhận so với giá thầu nhưng không được vượt quá tỷ lệ phần trăm (%) quy định tại Mục 12. 2 Chương I. Trường hợp nhà thầu liên danh, thành viên liên danh được sử dụng thầu phụ đối với phần công việc đảm nhận theo tỷ lệ % quy định tại Mục 12. 2 Chương I. (6) Nhà thầu ghi cụ thể số hợp đồng hoặc văn bản thỏa thuận và đính kèm bản chụp được chứng thực các hồ sơ này trong HSĐX. Trường hợp khi dự thầu chưa xác định được thầu phụ thì để trống cột này. Mẫu 10B DANH SÁCH CÁC CÔNG TY CON, CÔNG TY THÀNH VIÊN ĐẢM NHẬN PHẦN CÔNG VIỆC CỦA GÓI THẦU(1) [BẢNG: Không tiêu đề] Ghi chú: (1) Trường hợp nhà thầu dự thầu là công ty mẹ (ví dụ như Tổng công ty) huy động công ty con, công ty thành viên thực hiện một phần công việc gói thầu thì phải kê khai cụ thể tại bảng này. Việc đánh giá kinh nghiệm thực hiện hợp đồng tương tự căn cứ vào giá trị, khối lượng công việc do công ty mẹ, công ty con đảm nhiệm trong gói thầu. Trường hợp nhà thầu dự thầu không phải là công ty mẹ thì không áp dụng Mẫu này. (2) Ghi cụ thể tên công ty con, công ty thành viên. (3) Ghi cụ thể phần công việc đảm nhận của công ty con, công ty thành viên. (4) Ghi cụ thể giá trị % công việc của công ty con, công ty thành viên đảm nhận so với giá thầu. Phần 2. YÊU CẦU VỀ KỸ THUẬT Chương IV. YÊU CẦU VỀ KỸ THUẬT Yêu cầu về kỹ thuật mang tính kỹ thuật thuần túy và các yêu cầu khác liên quan đến việc cung cấp dịch vụ (trừ giá). Yêu cầu về kỹ thuật phải được nêu đầy đủ, rõ ràng và cụ thể để làm cơ sở cho nhà thầu lập HSĐX. Trong yêu cầu về kỹ thuật không được đưa ra các điều kiện nhằm hạn chế sự tham gia của nhà thầu hoặc nhằm tạo lợi thế cho một hoặc một số nhà thầu gây ra sự cạnh tranh không bình đẳng. Yêu cầu về kỹ thuật bao gồm các nội dung cơ bản như sau: 1. Giới thiệu chung về dự án/dự toán mua sắm, gói thầu Mục này nêu thông tin tóm tắt về dự án/ dự toán mua sắm, gói thầu như: địa điểm thực hiện dự án/ dự toán mua sắm, quy mô của dự án/ dự toán mua sắm, yêu cầu về cung cấp dịch vụ, thời gian thực hiện và những thông tin khác tùy theo tính chất và yêu cầu của gói thầu. 2. Mục tiêu công việc Trong mục này Chủ đầu tư cần cung cấp đầy đủ, chi tiết thông tin về các dịch vụ sẽ được thực hiện để bảo đảm nhà thầu có thể lập HSĐX một cách hiệu quả, chính xác và cạnh tranh nhất có thể. 3. Yêu cầu kỹ thuật của gói thầu Mục này đưa ra các yêu cầu về kỹ thuật đối với việc cung cấp dịch vụ nhằm đảm bảo chất lượng dịch vụ đáp ứng mục tiêu ban đầu của Chủ đầu tư. Trong đó, các yêu cầu do Chủ đầu tư đưa ra cần chú trọng vào sản phẩm đầu ra như tiêu chuẩn, quy cách, thông số kỹ thuật, chất lượng. .. của dịch vụ. Chủ đầu tư cũng cần nêu các tiêu chuẩn về dịch vụ mà nhà thầu phải đáp ứng. Nhà thầu có thể áp dụng các tiêu chuẩn dịch vụ khác nhưng phải chứng minh các tiêu chuẩn này tương đương hoặc cao hơn tiêu chuẩn do Chủ đầu tư yêu cầu. Về cơ bản, Chủ đầu tư không cần nêu quy trình, phương pháp thực hiện dịch vụ cụ thể mà nhà thầu phải tuân theo. Nhà thầu được quyền đề xuất quy trình, phương pháp thực hiện mà nhà thầu thấy là thích hợp để thực hiện gói thầu. Chủ đầu tư có thể đưa ra các yêu cầu về đấu thầu bền vững để bảo đảm dịch vụ cung cấp cho gói thầu thân thiện với môi trường, xã hội (việc sử dụng các vật tư, vật liệu được chứng nhận nhãn sinh thái và tương đương; sử dụng vật liệu không nung, vật liệu bền vững, thân thiện môi trường có khả năng tái chế, tái sử dụng; hạn chế mức độ xả thải, rác thải, ô nhiễm môi trường, hạn chế lượng bê tông sử dụng trong dự án; biện pháp tổ chức thi công; dây chuyền, kỹ thuật thi công và các yếu tố khác) nhưng phải bảo đảm các quy định này là rõ ràng, không làm hạn chế nhà thầu. 4. Giải pháp và phương pháp luận Nhà thầu chuẩn bị đề xuất giải pháp, phương pháp luận tổng quát thực hiện dịch vụ theo các nội dung quy định tại Chương này, gồm các phần như sau: 1. Giải pháp và phương pháp luận; 2. Kế hoạch công tác. 5. Quy định về kiểm tra, nghiệm thu sản phẩm Mục này quy định về quy trình kiểm tra, nghiệm thu sản phẩm, trình tự giao nộp sản phẩm (nếu có). .. để phục vụ công tác thanh, quyết toán hợp đồng. Phần 3. ĐIỀU KIỆN HỢP ĐỒNG VÀ BIỂU MẪU HỢP ĐỒNG Căn cứ quy mô, tính chất, loại hợp đồng của gói thầu, Chủ đầu tư, tổ chuyên gia sử dụng các Chương VI, VII, VIII của Mẫu E-HSMT dịch vụ phi tư vấn một giai đoạn một túi hồ sơ ban hành kèm theo Thông tư số 79/2025/TT-BTC để xây dựng các Chương V. ĐIỀU KIỆN CHUNG, Chương VI. ĐIỀU KIỆN CỤ THỂ, Chương VII. BIỂU MẪU HỢP ĐỒNG cho phù hợp với quy định của Luật Đấu thầu, Nghị định số 214/2025/NĐ-CP. Trong quá trình thực hiện, trường hợp Thông tư số 79/2025/TT-BTC được sửa đổi, bổ sung hoặc thay thế thì áp dụng theo văn bản quy phạm pháp luật sửa đổi, bổ sung hoặc thay thế Thông tư số 79/2025/TT-BTC. Lưu ý: khi sử dụng cần thay đổi các thuật ngữ cho phù hợp như sau: - E-ĐKC thành ĐKC; - E-ĐKCT thành ĐKCT; - E-HSMT thành HSYC; - E-HSDT thành HSĐX. Phụ lục MỘT SỐ VÍ DỤ VỀ TIÊU CHUẨN ĐÁNH GIÁ VỀ KỸ THUẬT VÀ YÊU CẦU VỀ KỸ THUẬT DỰA TRÊN KẾT QUẢ ĐẦU RA Ví dụ 1: Yêu cầu kỹ thuật dựa trên chất lượng đầu ra gói thầu cung cấp dịch vụ vệ sinh tòa nhà [BẢNG: Không tiêu đề] Ví dụ 2: Phụ lục hợp đồng về giảm trừ thanh toán đối với gói thầu cung cấp dịch vụ hỗ trợ khách hàng [BẢNG: Không tiêu đề] Ví dụ 3: Phụ lục hợp đồng về giảm trừ thanh toán đối với gói thầu cung cấp dịch vụ quản lý hệ thống máy tính nội bộ [BẢNG: Không tiêu đề]", "metadata": {"source_file": "01C. Mẫu HSYC Phi tư vấn.docx", "file_type": "bidding_document", "document_category": "goods", "extracted_at": "2025-10-30T19:54:41.203965", "file_size_bytes": 198843, "project_name": "/dự toán mua sắm]. 2. Nguồn vốn để thực hiện gói thầu__[Ghi rõ nguồn vốn đã được xác định hoặc phê duyệt; trường hợp sử dụng vốn ODA, vốn vay ưu đãi n", "package_name": "DỊCH VỤ PHI TƯ VẤN (Ban hành kèm theo Thông tư số 80/2025/TT-BTC ngày 08 tháng 8 năm 2025 của Bộ trưởng Bộ Tài chính) HỒ SƠ YÊU CẦU DỊCH VỤ PHI TƯ VẤN", "bidding_method": "CHỈ ĐỊNH THẦU", "owner": "___ [Ghi tên, địa chỉ Chủ đầu tư] mời nhà thầu nhận HSYC gói thầu___ [Ghi tên gói thầu theo kế hoạch lựa chọn nhà thầu được duyệt] thuộc ___ [Ghi tên", "chunk_index": 0, "char_count": 67298, "word_count": 14964, "paragraph_count": 1, "doc_type": "bidding", "processed_at": "2025-10-30T19:54:41.262856", "total_chunks": 1, "document_type": "bidding_document", "file_path": "/home/sakana/Code/RAG-bidding/data/raw/Ho so moi thau/1. Mẫu HSYC/01C. Mẫu HSYC Phi tư vấn.docx", "bidding_type": "construction", "extraction_metadata": {"source_file": "01C. Mẫu HSYC Phi tư vấn.docx", "file_type": "bidding_document", "document_category": "goods", "extracted_at": "2025-10-30T19:54:41.203965", "file_size_bytes": 198843, "project_name": "/dự toán mua sắm].", "package_name": "DỊCH VỤ PHI TƯ VẤN", "bidding_method": "CHỈ ĐỊNH THẦU", "owner": "___ [Ghi tên, địa chỉ Chủ đầu tư] mời nhà thầu nhận HSYC gói thầu___ [Ghi tên gói thầu theo kế hoạch lựa chọn nhà thầu được duyệt] thuộc ___ [Ghi tên dự án/dự toán mua sắm]."}, "parsing_metadata": {"bidding_type": null, "detected_sections": {"general_info": [], "technical_requirements": [], "evaluation_criteria": [], "contract_conditions": [], "bidding_process": [], "forms": [], "drawings": [], "bill_of_quantities": []}, "document_info": {"project_name": "/dự toán mua sắm]. 2. nguồn vốn để thực hiện gói thầu__[ghi rõ nguồn vốn đã được xác định hoặc phê d", "package_name": "dịch vụ phi tư vấn (ban hành kèm theo thông tư số 80/2025/tt-btc ngày 08 tháng 8 năm 2025 của bộ trư", "owner": "___ [ghi tên, địa chỉ chủ đầu tư] mời nhà thầu nhận hsyc gói thầu___ [ghi tên gói thầu theo kế hoạch"}, "statistics": {}}, "contract_value": "tương tự được xác định khoảng 30% (hoặc 20% trong", "duration": "gói thầu là: ___ngày [Ghi thời gian cụ thể theo kế", "hierarchy": "HỒ SƠ MỜI THẦU > Phần 1 > Chương I > Mục 1 > Điều 16", "section_type": "scope_of_work", "has_tables": true, "table_count": 1, "table_types": ["bill_of_quantities"], "contains_forms": true, "contains_technical_specs": true, "contains_evaluation": true, "contains_monetary_values": true, "monetary_value_count": 24, "contains_time_references": true, "time_reference_count": 38, "entities": {"locations": ["các điểm a, b, c, d, e và g Khoản 1 Điều 5 của Luật", "các điểm a, b Khoản 2 và các điểm d, e Khoản 1 Điều", "Mục 8 Chương này; 5. Đề xuất về giá theo Mẫu 04 (04", "thời điểm 28 ngày trước ngày có thời điểm đóng thầu", "Chương IV và chào giá cho tất cả các công việc nêu", "Chương III. Mục 8. Thành phần đề xuất kỹ thuật Nhà", "Chương IV để chứng minh tính phù hợp của đề xuất đố", "Mục 6 Chương I phải được ký bởi người đại diện hợp", "bên cạnh hoặc tại trang đó của người ký đơn dự thầu", "thầu 1. HSĐX do nhà thầu nộp trực tiếp hoặc gửi đến", "thầu: Chủ đầu tư tiến hành mở thầu bao gồm các nội", "hồ sơ và đọc rõ các thông tin về tên nhà thầu: - Th", "thầu bao gồm các thông tin quy định tại điểm a và đ", "thầu phải được ký xác nhận bởi đại diện của Chủ đầu", "thầu. Biên bản này phải được gửi cho các nhà thầu n", "Mục này trên giá trị phần công việc mà thành viên l", "Chương II. 2. Trong quá trình đánh giá, Chủ đầu tư", "cho nhà thầu chuẩn bị HSĐX]. Mục 15. Thông báo kết", "thời điểm ký kết, HSĐX của nhà thầu trúng thầu còn", "thời điểm ký kết hợp đồng, nhà thầu trúng thầu phải", "Nghị quyết của Quốc hội hoặc văn bản quy phạm pháp", "Mục 6 Chương I; c) Kiểm tra sự thống nhất nội dung", "Mục 9 Chương I; d) Có thỏa thuận liên danh (trong t", "Mẫu 04 (04A hoặc 04B hoặc 04C hoặc 04D hoặc 04E hoặ", "Mục 3 Chương I. e) Trong thời hạn 03 năm trước thời", "thời điểm nhân sự thực hiện hành vi vi phạm) bị Tòa", "Mục 2. 1, 2. 2. Năng lực và kinh nghiệm của thầu ph", "Bảng số 01 Chương này, nhà thầu được đánh giá đạt t", "Bảng số 01 thì đáp ứng yêu cầu về năng lực và kinh", "HSYC để làm cơ sở đánh giá HSĐX. Việc quy đổi được", "Việt Nam] tại ngày ký hợp đồng tương tự đó. Trường", "Khoản 1 Điều 133 của Nghị định số 214/2025/NĐ-CP th", "Khoản 4 Điều 6 của Nghị định số 214/2025/NĐ-CP khôn", "lên thì cách tính doanh thu như sau: Yêu cầu tối th", "Khoản 8 Điều 16 của Luật Đấu thầu thì hợp đồng này", "các hạng mục chính của gói thầu (phải nêu rõ các hạ", "tất cả các hạng mục của gói thầu, trong đó ghi quy", "các hạng mục chính của gói thầu); đối với các công", "các địa phương mà năng lực của nhà thầu trên địa bà", "các hạng mục chính của gói thầu). Việc đánh giá về", "các địa phương mà năng lực của nhà thầu trên địa bà", "các hạng mục chính của gói thầu), trong đó từng hạn", "các địa phương mà năng lực của nhà thầu trên địa bà", "các hạng mục chính của gói thầu); hoặc (ii) Có các", "các địa phương mà năng lực của nhà thầu trên địa bà", "các hạng mục chính của gói thầu) và tổng giá trị cá", "các địa phương mà năng lực của nhà thầu trên địa bà", "các hạng mục chính của gói thầu). Được cộng gộp giá", "các địa phương mà năng lực của nhà thầu trên địa bà", "các hạng mục chính của gói thầu). Trong đó: + Hạng", "các địa phương mà năng lực của nhà thầu trên địa bà", "cột này được Chủ đầu tư xác định theo nguyên tắc nê", "ghi chú số (10), (11) Bảng số 01 Chương này. 2. 2.", "Khoản 1 Điều 133 của Nghị định số 214/2025/NĐ-CP. K", "số năm tối thiểu nhân sự thực hiện các công việc tư", "hữu của nhà thầu hoặc do nhà thầu huy động. Trường", "Khoản 1 Điều 133 của Nghị định số 214/2025/NĐ-CP. N", "Mục này. Trường hợp không huy động được nhân sự chủ", "Chương IV, thông tin về kết quả thực hiện hợp đồng", "Mục 14 Chương I. Chương III. BIỂU MẪU Mẫu 01 ĐƠN DỰ", "thời điểm nhân sự thực hiện hành vi vi phạm) bị tòa", "và các hành vi vi phạm quy định khác của pháp luật", "các hồ sơ khác liên quan có phân công trách nhiệm c", "Mẫu 04 (04A hoặc 04B hoặc 04C hoặc 04D hoặc 04E hoặ", "chào giá thầu. (3) Chủ đầu tư ghi dẫn chiếu cụ thể", "chào giá thầu. (8): Nhà thầu điền. (9), (10): Nhà t", "thời điểm 28 ngày trước ngày có thời điểm đóng thầu", "chào giá thầu. (3) Chủ đầu tư ghi dẫn chiếu cụ thể", "chào giá thầu. (8): Nhà thầu điền. (9), (10): Nhà t", "thời điểm 28 ngày trước ngày có thời điểm đóng thầu", "chào thầu. (3) Chủ đầu tư ghi dẫn chiếu cụ thể đến", "chào giá thầu. (*) Trong HSYC phải ghi rõ tỷ lệ dự", "thời điểm 28 ngày trước ngày có thời điểm đóng thầu", "chào giá thầu. (8), (9) Chủ đầu tư ghi số ngày kể t", "thời điểm 28 ngày trước ngày có thời điểm đóng thầu", "Mục 2. 1 Chương II để làm cơ sở đánh giá. Mẫu 07A B", "Khoản 1 Điều 133 của Nghị định số 214/2025/NĐ-CP. [", "Bảng trên. Mẫu 07C [BẢNG: BẢNG KINH NGHIỆM CHUYÊN M", "hữu của nhà thầu hoặc do nhà thầu huy động. Trường", "Khoản 1 Điều 133 của Nghị định số 214/2025/NĐ-CP. [", "hữu của mình thì nhà thầu phải kê khai thêm các thô", "số năm mà nhà thầu có số liệu tài chính. Nhà thầu p", "thời điểm đóng thầu. Mẫu 10A PHẠM VI CÔNG VIỆC SỬ D", "Khoản 4 Điều 11 Luật Đấu thầu. (2) Nhà thầu ghi cụ", "Mục 12. 2 Chương I. Trường hợp nhà thầu liên danh,", "Mục 12. 2 Chương I. (6) Nhà thầu ghi cụ thể số hợp", "bảng này. Việc đánh giá kinh nghiệm thực hiện hợp đ", "cho nhà thầu lập HSĐX. Trong yêu cầu về kỹ thuật kh", "Chương này, gồm các phần như sau: 1. Giải pháp và p"]}, "content_stats": {"char_count": 67298, "word_count": 14964, "line_count": 1, "paragraph_count": 1, "sentence_count": 467}}, "chunk_id": "chunk_000", "char_count": 67298, "level": "paragraph", "hierarchy": [], "parent_id": null, "parsed_sections": [], "tables": [{"start_line": 0, "end_line": 1, "content": "Mẫu 1C HỒ SƠ YÊU CẦU GÓI THẦU DỊCH VỤ PHI TƯ VẤN (Ban hành kèm theo Thông tư số 80/2025/TT-BTC ngày 08 tháng 8 năm 2025 của Bộ trưởng Bộ Tài chính) HỒ SƠ YÊU CẦU DỊCH VỤ PHI TƯ VẤN [BẢNG: Không tiêu đề] TỪ NGỮ VIẾT TẮT [BẢNG: Không tiêu đề] Phần 1. THỦ TỤC CHỈ ĐỊNH THẦU Chương I. CHỈ DẪN NHÀ THẦU Mục 1. Phạm vi gói thầu 1. Chủ đầu tư ___ [Ghi tên, địa chỉ Chủ đầu tư] mời nhà thầu nhận HSYC gói thầu___ [Ghi tên gói thầu theo kế hoạch lựa chọn nhà thầu được duyệt] thuộc ___ [Ghi tên dự án/dự toán mua sắm]. 2. Nguồn vốn để thực hiện gói thầu__[Ghi rõ nguồn vốn đã được xác định hoặc phê duyệt; trường hợp sử dụng vốn ODA, vốn vay ưu đãi nước ngoài thì phải ghi rõ tên nhà tài trợ và cơ cấu nguồn vốn, bao gồm vốn tài trợ, vốn đối ứng trong nước]. 3. Thời gian thực hiện gói thầu là: ___ngày [Ghi thời gian cụ thể theo kế hoạch lựa chọn nhà thầu được duyệt], được tính từ ngày hợp đồng có hiệu lực đến ngày nghiệm thu dịch vụ. Mục 2. Hành vi bị cấm trong đấu thầu Hành vi bị cấm trong đấu thầu là hành vi quy định tại Điều 16 của Luật Đấu thầu. Mục 3. Tư cách hợp lệ của nhà thầu 1. Nhà thầu là tổ chức có tư cách hợp lệ khi đáp ứng quy định tại các điểm a, b, c, d, e và g Khoản 1 Điều 5 của Luật Đấu thầu. 2. Nhà thầu là hộ kinh doanh có tư cách hợp lệ khi đáp ứng quy định tại các điểm a, b Khoản 2 và các điểm d, e Khoản 1 Điều 5 của Luật Đấu thầu. Trường hợp pháp luật có liên quan quy định nhà thầu dự thầu, thực hiện hợp đồng phải độc lập với các tổ chức, cá nhân khác thì phải tuân thủ quy định đó. Mục 4. Làm rõ, sửa đổi HSYC 1. Trường hợp nhà thầu cần làm rõ HSYC, nhà thầu gửi văn bản đến Chủ đầu tư trong thời hạn tối thiểu 03 ngày làm việc trước ngày có thời điểm đóng thầu để đánh giá, xử lý. 2. Trường hợp Chủ đầu tư sửa đổi HSYC, Chủ đầu tư có trách nhiệm gửi quyết định sửa đổi và các nội dung sửa đổi tới nhà thầu. Thời gian gửi văn bản sửa đổi HSYC đến nhà thầu là ___ [Ghi số ngày cụ thể, tối thiểu 03 ngày làm việc trước ngày có thời điểm đóng thầu và bảo đảm đủ thời gian để nhà thầu hoàn chỉnh HSĐX]; trường hợp không bảo đảm đủ thời gian như nêu trên thì phải gia hạn thời điểm đóng thầu. Mục 5. Chi phí, đồng tiền, ngôn ngữ khi dự thầu 1. Nhà thầu phải chịu mọi chi phí liên quan đến quá trình dự thầu. 2. Đồng tiền dự thầu và đồng tiền thanh toán là VND. 3. HSĐX cũng như tất cả văn bản và hồ sơ liên quan đến HSĐX được viết bằng tiếng Việt. Các hồ sơ bổ trợ trong HSĐX có thể được viết bằng ngôn ngữ khác, đồng thời kèm theo bản dịch sang tiếng Việt. Trường hợp thiếu bản dịch, Chủ đầu tư có thể yêu cầu nhà thầu gửi bổ sung (nếu cần thiết). Mục 6. Thành phần của HSĐX HSĐX do nhà thầu chuẩn bị phải bao gồm: 1. Đơn dự thầu theo Mẫu 01 Chương III; 2. Thỏa thuận liên danh nếu là nhà thầu liên danh theo Mẫu 03 Chương III; 3. hồ sơ chứng minh tư cách hợp lệ, năng lực và kinh nghiệm của nhà thầu, của người ký đơn dự thầu; 4. Đề xuất kỹ thuật theo quy định tại Mục 8 Chương này; 5. Đề xuất về giá theo Mẫu 04 (04A hoặc 04B hoặc 04C hoặc 04D hoặc 04E hoặc 04G) Chương III; 6. Các nội dung khác ___ [Nêu các nội dung khác tùy theo tính chất, yêu cầu của gói thầu]. Mục 7. giá thầu 1. giá thầu là giá do nhà thầu chào trong đơn dự thầu bao gồm toàn bộ các chi phí (chưa tính giảm giá) để thực hiện gói thầu theo yêu cầu của HSYC, kể cả các loại thuế, phí, lệ phí (nếu có) áp theo thuế suất, mức phí, lệ phí tại thời điểm 28 ngày trước ngày có thời điểm đóng thầu. 2. Nhà thầu phải nộp HSĐX cho toàn bộ công việc được mô tả tại Chương IV và chào giá cho tất cả các công việc nêu trong bảng giá tương ứng quy định tại Chương III. Mục 8. Thành phần đề xuất kỹ thuật Nhà thầu phải nộp đề xuất kỹ thuật, trong đó mô tả cụ thể phương pháp thực hiện công việc, thiết bị, nhân sự, lịch biểu thực hiện và các thông tin cần thiết khác theo quy định tại Chương IV để chứng minh tính phù hợp của đề xuất đối với các yêu cầu công việc và thời hạn cần hoàn thành công việc. Mục 9. Hiệu lực của HSĐX Thời gian có hiệu lực của HSĐX phải bảo đảm theo yêu cầu là ___ [Ghi rõ số ngày tuỳ thuộc quy mô, tính chất của gói thầu, bảo đảm thời gian có hiệu lực đến ngày ký kết hợp đồng] kể từ ngày có thời điểm đóng thầu. 2. Trong trường hợp cần thiết, trước khi hết thời hạn hiệu lực của HSĐX, Chủ đầu tư có thể đề nghị nhà thầu gia hạn hiệu lực của HSĐX. Việc đề nghị gia hạn và chấp thuận gia hạn phải được thể hiện bằng văn bản. Mục 10. Quy cách của HSĐX và chữ ký trong HSĐX 1. Nhà thầu phải chuẩn bị một bản gốc và ______bản chụp HSĐX [Ghi số lượng yêu cầu nhưng không quá 03 bản], ghi rõ \"bản gốc\" và \"bản chụp\" tương ứng. Nhà thầu cần ghi rõ tên gói thầu, tên nhà thầu, tên Chủ đầu tư bên ngoài túi đựng HSĐX. Nhà thầu phải chịu trách nhiệm về tính chính xác và phù hợp giữa bản chụp và bản gốc. Trường hợp có sự sai khác giữa bản gốc và bản chụp thì căn cứ vào bản gốc để đánh giá. 2. Tất cả các thành phần của HSĐX nêu tại Mục 6 Chương I phải được ký bởi người đại diện hợp pháp của nhà thầu. Trường hợp là nhà thầu liên danh thì HSĐX phải có chữ ký của đại diện hợp pháp của tất cả thành viên liên danh hoặc thành viên đại diện nhà thầu liên danh theo phân công trong thỏa thuận liên danh. 3. Những chữ được ghi thêm, ghi chèn vào giữa các dòng, những chữ bị tẩy xóa hoặc viết đè lên sẽ chỉ được coi là hợp lệ nếu có chữ ký ở bên cạnh hoặc tại trang đó của người ký đơn dự thầu. Mục 11. Thời điểm đóng thầu và mở thầu 1. HSĐX do nhà thầu nộp trực tiếp hoặc gửi đến địa chỉ của Chủ đầu tư: __[Ghi địa chỉ] nhưng phải bảo đảm Chủ đầu tư nhận được trước thời điểm đóng thầu: ___ giờ, ngày ___ tháng ___ năm ____ [Ghi thời điểm đóng thầu]. 2. Mở thầu: Chủ đầu tư tiến hành mở thầu bao gồm các nội dung sau: a) Kiểm tra niêm phong; b) Mở hồ sơ và đọc rõ các thông tin về tên nhà thầu: - Tham dự độc lập hay liên danh; - Số lượng bản gốc, bản chụp; - giá thầu chào trong đơn dự thầu; - Giá trị giảm giá (nếu có); - Thời gian có hiệu lực của HSĐX; - Thời gian thực hiện gói thầu; - Các thông tin khác liên quan. Biên bản mở thầu bao gồm các thông tin quy định tại điểm a và điểm b khoản này. Biên bản mở thầu phải được ký xác nhận bởi đại diện của Chủ đầu tư và các nhà thầu tham dự lễ mở thầu. Biên bản này phải được gửi cho các nhà thầu nộp HSĐX. Đại diện của Chủ đầu tư phải ký xác nhận vào bản gốc đơn dự thầu, thư giảm giá (nếu có), giấy ủy quyền của người đại diện theo pháp luật của nhà thầu (nếu có), thỏa thuận liên danh (nếu có), các nội dung đề xuất về tài chính và các nội dung quan trọng khác của từng HSĐX. Mục 12. thầu phụ 1. thầu phụ là tổ chức, cá nhân ký kết hợp đồng với nhà thầu để thực hiện một phần công việc trong bảng giá thầu; không bao gồm tổ chức, cá nhân cung cấp, nguyên liệu, nhiên liệu, vật liệu, vật tư, cấu kiện bán thành phẩm, thiết bị, cho thuê thiết bị thi công. Việc nhà thầu thuê nhân công để thực hiện gói thầu không phải là sử dụng thầu phụ. Trường hợp nhà thầu cần sử dụng thầu phụ thì phải kê khai danh sách thầu phụ theo Mẫu 10A Chương III. Việc sử dụng thầu phụ sẽ không làm thay đổi các trách nhiệm của nhà thầu. Nhà thầu phải chịu trách nhiệm về khối lượng, chất lượng, tiến độ và các trách nhiệm khác đối với phần công việc do thầu phụ thực hiện. Năng lực và kinh nghiệm của thầu phụ sẽ không được đánh giá khi đánh giá HSĐX của nhà thầu. Bản thân nhà thầu phải đáp ứng các tiêu chí năng lực và kinh nghiệm (không xét đến năng lực và kinh nghiệm của thầu phụ). 2. Nhà thầu chỉ được sử dụng thầu phụ thực hiện các công việc với tổng giá trị dành cho thầu phụ không vượt quá ___ [tùy theo quy mô, tính chất gói thầu, Chủ đầu tư ghi tỷ lệ % tối đa dành cho thầu phụ] giá thầu của nhà thầu. Đối với trường hợp liên danh, từng thành viên liên danh chỉ được sử dụng thầu phụ không vượt quá tỷ lệ phần trăm quy định tại Mục này trên giá trị phần công việc mà thành viên liên danh đó đảm nhận trong thỏa thuận liên danh. Mục 13. Đánh giá HSĐX và thương thảo về các đề xuất của nhà thầu 1. Việc đánh giá HSĐX được thực hiện theo quy định tại Chương II. 2. Trong quá trình đánh giá, Chủ đầu tư mời nhà thầu thương thảo về giá bảo đảm đáp ứng tỷ lệ tiết kiệm theo quy định của HSYC, thương thảo, làm rõ hoặc sửa đổi, bổ sung nội dung HSĐX để chứng minh việc đáp ứng yêu cầu về năng lực, kinh nghiệm, tiến độ, khối lượng, chất lượng, giải pháp kỹ thuật, biện pháp tổ chức thực hiện gói thầu và tỷ lệ tiết kiệm. Mục 14. Điều kiện đối với nhà thầu được đề nghị chỉ định thầu Nhà thầu được đề nghị trúng thầu khi đáp ứng đầy đủ các điều kiện sau đây: 1. Có HSĐX hợp lệ; 2. Có năng lực, kinh nghiệm và đề xuất kỹ thuật đáp ứng yêu cầu của HSYC; 3. Có giá đề nghị trúng thầu không vượt giá gói thầu được duyệt và đáp ứng tỷ lệ tiết kiệm tối thiểu__ % giá gói thầu. [Căn cứ quy mô, tính chất, điều kiện cụ thể của gói thầu, Chủ đầu tư quy định trong HSYC mức tỷ lệ tiết kiệm của giá đề nghị trúng thầu để làm cơ sở cho nhà thầu chuẩn bị HSĐX]. Mục 15. Thông báo kết quả lựa chọn nhà thầu Trong thời hạn 05 ngày làm việc kể từ ngày kết quả lựa chọn nhà thầu được phê duyệt, Chủ đầu tư đăng tải thông tin về kết quả lựa chọn nhà thầu lên Hệ thống mạng đấu thầu quốc gia; gửi văn bản thông báo kết quả lựa chọn nhà thầu cho nhà thầu dự thầu. Nội dung thông báo kết quả lựa chọn nhà thầu như sau: a) Thông tin về gói thầu: - Tên gói thầu; - Giá gói thầu hoặc dự toán được duyệt (nếu có); ; - Tên Chủ đầu tư; - Hình thức lựa chọn nhà thầu; - Loại hợp đồng; - Thời gian thực hiện gói thầu. b) Thông tin về nhà thầu trúng thầu: - Tên nhà thầu; - Mã số thuế (nếu có); - giá thầu; - Giá trúng thầu; - Thời gian thực hiện gói thầu; - Thời gian thực hiện hợp đồng. c) Kế hoạch hoàn thiện, ký kết hợp đồng với nhà thầu trúng thầu. Mục 16. Điều kiện ký kết hợp đồng 1. Tại thời điểm ký kết, HSĐX của nhà thầu trúng thầu còn hiệu lực. 2. Tại thời điểm ký kết hợp đồng, nhà thầu trúng thầu phải bảo đảm đáp ứng yêu cầu về năng lực kỹ thuật, tài chính để thực hiện gói thầu theo yêu cầu của HSYC. Trường hợp thực tế nhà thầu không còn đáp ứng cơ bản yêu cầu về năng lực kỹ thuật, tài chính theo quy định nêu trong HSYC thì Chủ đầu tư sẽ từ chối ký kết hợp đồng với nhà thầu và hủy quyết định phê duyệt kết quả lựa chọn nhà thầu. 3. Chủ đầu tư phải bảo đảm các điều kiện về vốn tạm ứng, vốn thanh toán, mặt bằng thực hiện và điều kiện cần thiết khác để triển khai thực hiện gói thầu theo đúng tiến độ. Mục 17. Bảo đảm thực hiện hợp đồng 1. Trước hoặc cùng thời điểm hợp đồng có hiệu lực, nhà thầu được chỉ định thầu phải cung cấp bảo đảm thực hiện hợp đồng theo quy định của HSYC. Trường hợp nhà thầu sử dụng thư bảo lãnh thực hiện hợp đồng thì phải sử dụng Mẫu thư bảo lãnh trong HSYC này hoặc Mẫu thư bảo lãnh khác được Chủ đầu tư chấp thuận. 2. Nhà thầu không được hoàn trả bảo đảm thực hiện hợp đồng trong trường hợp sau đây: a) Từ chối thực hiện hợp đồng khi hợp đồng đã có hiệu lực; b) Vi phạm thỏa thuận trong hợp đồng; c) Thực hiện hợp đồng chậm tiến độ do lỗi của nhà thầu nhưng từ chối gia hạn hiệu lực của bảo đảm thực hiện hợp đồng. Mục 18. Giải quyết kiến nghị 1. Đối với gói thầu thuộc phạm vi điều chỉnh của Luật Đấu thầu a) Khi thấy quyền và lợi ích hợp pháp bị ảnh hưởng, nhà thầu được kiến nghị người có thẩm quyền, Chủ đầu tư, Hội đồng giải quyết kiến nghị đánh giá lại các vấn đề trong quá trình lựa chọn nhà thầu, kết quả lựa chọn nhà thầu theo quy định tại Điều 89 Luật Đấu thầu và các Điều 137, 138 và 139 của Nghị định số 214/2025/NĐ-CP. b) Địa chỉ nhận đơn kiến nghị - Địa chỉ nhận đơn kiến nghị của Chủ đầu tư: ______ [ghi đầy đủ tên, địa chỉ, số điện thoại, email]. - Địa chỉ nhận đơn kiến nghị của người có thẩm quyền: ______ [ghi đầy đủ tên, địa chỉ, số điện thoại, email]. - Địa chỉ bộ phận thường trực giúp việc của Hội đồng giải quyết kiến nghị: ___ [ghi đầy đủ tên, địa chỉ, số điện thoại, email]. 2. Đối với hoạt động lựa chọn nhà thầu quy định tại điểm d Khoản 7 Điều 3 của Luật Đấu thầu hoặc hoạt động lựa chọn nhà thầu không thuộc phạm vi điều chỉnh của Luật Đấu thầu: Khi thấy quyền và lợi ích hợp pháp bị ảnh hưởng, nhà thầu, cơ quan, tổ chức được kiến nghị theo quy trình sau: ______ [ghi cụ thể quy trình, thủ tục của việc giải quyết kiến nghị của đơn vị, tổ chức đồng thời ghi rõ email, địa chỉ của cá nhân/tổ chức/đơn vị giải quyết kiến nghị]. Mục 19. Ưu đãi trong lựa chọn nhà thầu Ưu đãi: _____ [Chủ đầu tư ghi rõ đối tượng, điều kiện ưu đãi theo quy định tại Nghị quyết của Quốc hội hoặc văn bản quy phạm pháp luật (nếu có)]. Chương II. TIÊU CHUẨN ĐÁNH GIÁ HSĐX Mục 1. Đánh giá tính hợp lệ của HSĐX 1. 1. Kiểm tra HSĐX a) Kiểm tra số lượng bản gốc, bản chụp HSĐX; b) Kiểm tra các thành phần của HSĐX theo quy định tại Mục 6 Chương I; c) Kiểm tra sự thống nhất nội dung giữa bản gốc và bản chụp để phục vụ quá trình đánh giá chi tiết HSĐX. 1. 2. Đánh giá tính hợp lệ của HSĐX HSĐX của nhà thầu được đánh giá là hợp lệ khi đáp ứng đầy đủ các nội dung sau đây: a) Có bản gốc HSĐX; b) Có đơn dự thầu được đại diện hợp pháp của nhà thầu ký tên, đóng dấu (nếu có) theo yêu cầu của HSYC; thời gian ký đơn dự thầu phải sau thời điểm phát hành HSYC; không đề xuất các giá thầu khác nhau hoặc có kèm theo điều kiện gây bất lợi cho Chủ đầu tư. Đối với nhà thầu liên danh, đơn dự thầu phải do đại diện hợp pháp của từng thành viên liên danh ký tên, đóng dấu (nếu có) hoặc thành viên được phân công thay mặt liên danh ký đơn dự thầu theo phân công trách nhiệm trong thỏa thuận liên danh; c) Hiệu lực của HSĐX đáp ứng yêu cầu theo quy định tại Mục 9 Chương I; d) Có thỏa thuận liên danh (trong trường hợp liên danh) được đại diện hợp pháp của từng thành viên liên danh ký tên, đóng dấu (nếu có); thỏa thuận liên danh phải nêu rõ nội dung công việc cụ thể và ước tính giá trị tương ứng mà từng thành viên trong liên danh sẽ thực hiện. Việc phân chia công việc trong liên danh phải căn cứ các hạng mục nêu trong bảng giá thầu quy định tại Mẫu 04 (04A hoặc 04B hoặc 04C hoặc 04D hoặc 04E hoặc 04G) Chương III hoặc theo các công việc thuộc quá trình sản xuất hạng mục trong bảng giá thầu; không được phân chia các công việc không thuộc các hạng mục này hoặc không thuộc quá trình sản xuất các hạng mục này; đ) Nhà thầu bảo đảm tư cách hợp lệ theo quy định tại Mục 3 Chương I. e) Trong thời hạn 03 năm trước thời điểm đóng thầu, nhà thầu không có nhân sự (ký kết hợp đồng lao động với nhà thầu tại thời điểm nhân sự thực hiện hành vi vi phạm) bị Tòa án kết án có hành vi vi phạm quy định về đấu thầu gây hậu quả nghiêm trọng theo quy định của pháp luật về hình sự nhằm mục đích cho nhà thầu đó trúng thầu. Nhà thầu có HSĐX hợp lệ được đánh giá, đánh giá trong bước tiếp theo. Mục 2. Tiêu chuẩn đánh giá về năng lực, kinh nghiệm Nhà thầu được đánh giá là đạt về năng lực và kinh nghiệm khi đáp ứng tất cả các tiêu chuẩn đánh giá quy định tại Mục 2. 1, 2. 2. Năng lực và kinh nghiệm của thầu phụ sẽ không được đánh giá khi đánh giá HSĐX của nhà thầu. Bản thân nhà thầu phải đáp ứng các tiêu chí đánh giá về năng lực và kinh nghiệm. 2. 1. Tiêu chuẩn đánh giá về năng lực và kinh nghiệm Tiêu chuẩn đánh giá năng lực và kinh nghiệm thực hiện theo quy định tại Bảng số 01 Chương này, nhà thầu được đánh giá đạt tất cả nội dung quy định tại Bảng số 01 thì đáp ứng yêu cầu về năng lực và kinh nghiệm. Không đưa ra yêu cầu nhà thầu đã từng thực hiện một hoặc nhiều hợp đồng trên một địa bàn cụ thể hoặc nhà thầu phải có kinh nghiệm cung cấp dịch vụ trên một địa bàn cụ thể như là tiêu chí để loại bỏ nhà thầu. Trường hợp đồng tiền nêu trong các hợp đồng tương tự hoặc xác nhận thanh toán của Chủ đầu tư đối với những hợp đồng cung cấp dịch vụ phi tư vấn đã thực hiện hoặc tờ khai nộp thuế hoặc các hồ sơ liên quan chứng minh năng lực, kinh nghiệm của nhà thầu không phải VND thì khi lập HSĐX, nhà thầu phải quy đổi về VND nêu tại HSYC để làm cơ sở đánh giá HSĐX. Việc quy đổi được áp dụng tỷ giá quy đổi của ___ [ghi căn cứ xác định tỷ giá quy đổi, thường áp dụng tỷ giá bán ra của một ngân hàng thương mại hoạt động tại Việt Nam] tại ngày ký hợp đồng tương tự đó. Trường hợp nhà thầu dự thầu là công ty mẹ (ví dụ như Tổng công ty) có huy động công ty con, công ty thành viên thực hiện một phần công việc của gói thầu thì nhà thầu phải kê khai cụ thể phần công việc dành cho các công ty con, công ty thành viên theo Mẫu 10B Chương III. Việc đánh giá kinh nghiệm thực hiện hợp đồng tương tự căn cứ vào giá trị, khối lượng công việc do công ty mẹ, công ty con, công ty thành viên đảm nhiệm trong gói thầu. [BẢNG: Bảng số 01 BẢNG TIÊU CHUẨN ĐÁNH GIÁ VỀ NĂNG LỰC VÀ KINH NGHIỆM] Ghi chú: (1) Ghi thời gian yêu cầu, thông thường là 03 năm trước năm có thời điểm đóng thầu. Ví dụ: từ ngày 01 tháng 01 năm 2022 đến thời điểm đóng thầu. (2) Hợp đồng cung cấp dịch vụ phi tư vấn không hoàn thành do lỗi của nhà thầu bao gồm: - Hợp đồng cung cấp dịch vụ phi tư vấn bị Chủ đầu tư kết luận nhà thầu không hoàn thành và nhà thầu không phản đối; - Hợp đồng cung cấp dịch vụ phi tư vấn bị Chủ đầu tư kết luận nhà thầu không hoàn thành, không được nhà thầu chấp thuận nhưng đã được trọng tài hoặc Tòa án kết luận theo hướng bất lợi cho nhà thầu. Các hợp đồng cung cấp dịch vụ phi tư vấn không hoàn thành không bao gồm các hợp đồng mà quyết định của Chủ đầu tư đã bị bác bỏ bằng cơ chế giải quyết tranh chấp. Việc xác định hợp đồng không hoàn thành phải dựa trên tất cả những thông tin về tranh chấp hoặc kiện tụng được giải quyết theo quy định của cơ chế giải quyết tranh chấp của hợp đồng tương ứng và khi mà nhà thầu đã hết tất cả các cơ hội có thể khiếu nại. Đối với các hợp đồng chậm tiến độ do lỗi của nhà thầu nhưng vẫn hoàn thành hợp đồng thì không được coi là hợp đồng không hoàn thành. Đối với nhà thầu liên danh mà chỉ có một hoặc một số thành viên trong liên danh vi phạm và bị cấm tham gia hoạt động đấu thầu theo quy định tại Khoản 1 Điều 133 của Nghị định số 214/2025/NĐ-CP thì thành viên liên danh còn lại không bị coi là không hoàn thành hợp đồng do lỗi của nhà thầu. Trường hợp một hoặc một số thành viên liên danh vi phạm hợp đồng, không còn năng lực để tiếp tục thực hiện hợp đồng, làm ảnh hưởng nghiêm trọng đến tiến độ, chất lượng, hiệu quả của gói thầu thì chỉ một hoặc một số thành viên liên danh vi phạm hợp đồng bị coi là không hoàn thành hợp đồng, thành viên còn lại không bị coi là không hoàn thành hợp đồng do lỗi của nhà thầu. (3) Nhà thầu cung cấp hồ sơ chứng minh đã thực hiện nghĩa vụ kê khai thuế và nộp thuế thu nhập doanh nghiệp (thuế thu nhập cá nhân đối với nhà thầu là hộ kinh doanh) của năm tài chính gần nhất so với thời điểm đóng thầu. Nghĩa vụ kê khai thuế và nộp thuế phải được thực hiện trước thời điểm đóng thầu. Nghĩa vụ nộp thuế là nộp thuế với giá trị thuế tương ứng với thuế suất, thu nhập chịu thuế, doanh thu tính thuế nhà thầu kê khai trên Hệ thống thuế điện tử (số thuế đã nộp tương ứng với số thuế phải nộp); trường hợp được chậm nộp thuế, miễn thuế, giảm thuế theo chính sách của Nhà nước thì thực hiện theo quy định này. Nhà thầu nộp các hồ sơ như sau: - Tờ khai thuế (hoặc thông báo nộp tiền của cơ quan thuế đối với hộ kinh doanh) và Giấy nộp tiền có xác nhận của cơ quan thuế được in từ Hệ thống thuế điện tử hoặc - Tờ khai thuế (hoặc thông báo nộp tiền của cơ quan thuế đối với hộ kinh doanh) và xác nhận của cơ quan thuế về việc thực hiện nghĩa vụ thuế. Trường hợp thời điểm đóng thầu sau ngày kết thúc năm tài chính của nhà thầu (năm Y) và trước hoặc trong ngày cuối cùng của tháng thứ 3 tính từ ngày kết thúc năm Y, yêu cầu đã thực hiện nghĩa vụ kê khai thuế và nộp thuế áp dụng đối với năm tài chính trước năm Y (năm Y-1). Ví dụ: Thời điểm đóng thầu là ngày 20/3/2024, năm tài chính của nhà thầu kết thúc vào ngày 31/12 thì nhà thầu phải chứng minh đã thực hiện nghĩa vụ kê khai thuế và nộp thuế của năm 2022. (4) Đối với doanh nghiệp khởi nghiệp sáng tạo trong nước khi chào thầu sản phẩm đổi mới sáng tạo là dịch vụ phi tư vấn của doanh nghiệp đó theo quy định tại Khoản 4 Điều 6 của Nghị định số 214/2025/NĐ-CP không phải đáp ứng tiêu chí này trong thời hạn 06 năm kể từ khi sản phẩm lần đầu được sản xuất và đủ điều kiện để đưa ra thị trường. Nhà thầu trong nước thuộc trường hợp quy định tại điểm g Khoản 1 Điều 10 của Luật Đấu thầu khi chào thầu sản phẩm do nhà thầu đó sản xuất không phải đáp ứng tiêu chí này trong thời hạn 05 năm kể từ khi được cơ quan có thẩm quyền công nhận. (5) Ghi thời gian yêu cầu, thông thường từ 03 đến 05 năm trước năm có thời điểm đóng thầu. Trường hợp nhà thầu có số năm thành lập ít hơn số năm theo yêu cầu của HSYC thì doanh thu bình quân hằng năm (không bao gồm thuế VAT) được tính trên số năm mà nhà thầu thành lập. Trong trường hợp này, nếu doanh thu bình quân hằng năm (không bao gồm thuế VAT) của nhà thầu đáp ứng yêu cầu về giá trị của HSYC thì nhà thầu vẫn được đánh giá tiếp mà không bị loại. Đối với nhà thầu là hộ kinh doanh, không bắt buộc phải nộp báo cáo tài chính nhưng nhà thầu phải cung cấp hồ sơ chứng minh doanh thu tương ứng với nghĩa vụ thuế. Trường hợp thời điểm đóng thầu sau ngày kết thúc năm tài chính của nhà thầu (năm Y) và trước hoặc trong ngày cuối cùng của tháng thứ 3 tính từ ngày kết thúc năm Y, yêu cầu về nộp báo cáo tài chính áp dụng đối với các năm trước của năm Y (năm Y-1; Y-2. ..). (Ví dụ: Thời điểm đóng thầu là vào ngày 20/3/2024, năm tài chính của nhà thầu kết thúc vào ngày 31/12 và HSYC yêu cầu nhà thầu nộp báo cáo tài chính của 03 năm gần nhất thì nhà thầu phải nộp báo cáo tài chính của các năm 2020, 2021, 2022). Ví dụ: Doanh thu bình quân hằng năm (không bao gồm thuế VAT) của 03 năm tài chính gần nhất so với thời điểm đóng thầu. Trong trường hợp này, thời điểm đóng thầu là ngày 15/11/2024 thì nhà thầu phải nộp báo cáo tài chính của các năm 2021, 2022, 2023. Nhà thầu được thành lập vào năm 2022 nhưng doanh thu trung bình của năm 2022 và năm 2023 đáp ứng yêu cầu thì nhà thầu được tiếp tục đánh giá. (6) Cách tính toán thông thường về mức yêu cầu doanh thu bình quân hằng năm (không bao gồm thuế VAT): a) Trường hợp thời gian thực hiện gói thầu từ 12 tháng trở lên thì cách tính doanh thu như sau: Yêu cầu tối thiểu về mức doanh thu bình quân hằng năm (không bao gồm thuế VAT) = [(Giá gói thầu - giá trị thuế VAT)/thời gian thực hiện gói thầu theo năm] x k. Thông thường yêu cầu hệ số “k” trong công thức này là từ 1 đến 1, 5. b) Trường hợp thời gian thực hiện gói thầu dưới 12 tháng thì cách tính doanh thu như sau: Yêu cầu tối thiểu về mức doanh thu bình quân hằng năm (không bao gồm thuế VAT) = (Giá gói thầu - giá trị thuế VAT) x k. Thông thường yêu cầu hệ số “k” trong công thức này là 1, 0. Đối với gói thầu bảo hiểm thì có thể đưa ra yêu cầu về doanh thu bình quân hằng năm cao hơn so với cách tính theo công thức nêu trên nhưng phải bảo đảm không được làm hạn chế sự tham gia của nhà thầu. (7) Đối với các hợp đồng mà nhà thầu đã tham gia với tư cách là thành viên liên danh hoặc thầu phụ thì chỉ tính giá trị phần việc do nhà thầu thực hiện. (8) Đối với các hợp đồng mà Chủ đầu tư, tổ chuyên gia có bằng chứng cho thấy nhà thầu đã thực hiện với tư cách thầu phụ do được chuyển nhượng thầu bất hợp pháp, vi phạm quy định tại Khoản 8 Điều 16 của Luật Đấu thầu thì hợp đồng này sẽ không được đánh giá, đánh giá. (9) Ghi thời gian yêu cầu thông thường là từ 03 đến 05 năm trước năm có thời điểm đóng thầu. Ví dụ: từ ngày 01 tháng 01 năm 2019 đến thời điểm đóng thầu. (10) Chủ đầu tư, tổ chuyên gia căn cứ vào nội dung, phạm vi công việc của gói thầu đang xét để đưa ra yêu cầu về tính chất của hợp đồng tương tự. Trường hợp gói thầu có nhiều hạng mục thì có thể chỉ quy định về tính chất tương tự cho các hạng mục chính của gói thầu. (11) Quy mô Hợp đồng tương tự: Trường hợp gói thầu có nhiều hạng mục công việc thì phải ghi giá trị tương ứng của từng hạng mục công việc để làm cơ sở đánh giá kinh nghiệm thực hiện hợp đồng tương tự của nhà thầu. Trường hợp gói thầu bao gồm nhiều hạng mục công việc khác nhau thì tùy theo tính chất, quy mô gói thầu, Chủ đầu tư, tổ chuyên gia đưa ra yêu cầu về quy mô tương tự trên cơ sở các hạng mục chính của gói thầu (phải nêu rõ các hạng mục chính) hoặc yêu cầu về quy mô tương tự trên cơ sở tất cả các hạng mục của gói thầu, trong đó ghi quy mô yêu cầu đối với mỗi hạng mục chính hoặc mỗi hạng mục công việc. Quy mô của hợp đồng tương tự thông thường khoảng 30% giá trị của gói thầu đang xét (hoặc 30% tổng giá trị của các hạng mục chính trong trường hợp gói thầu nhiều hạng mục công việc khác nhau và Chủ đầu tư yêu cầu quy mô trên cơ sở các hạng mục chính của gói thầu); đối với các công việc đặc thù hoặc ở các địa phương mà năng lực của nhà thầu trên địa bàn còn hạn chế hoặc gói thầu cung cấp dịch vụ phi tư vấn có khối lượng mời thầu lớn thì có thể điều chỉnh giảm yêu cầu về quy mô của hợp đồng tương tự xuống trong khoảng 20% giá trị của gói thầu đang xét (hoặc 20% tổng giá trị của các hạng mục chính trong trường hợp gói thầu nhiều hạng mục công việc khác nhau và Chủ đầu tư yêu cầu quy mô trên cơ sở các hạng mục chính của gói thầu). Việc đánh giá về quy mô của hợp đồng tương tự căn cứ vào giá trị hoàn thành, được nghiệm thu như sau: (i) Có ít nhất 01 hợp đồng hoàn thành cung cấp đầy đủ các hạng mục tương tự có giá trị đáp ứng tối thiểu là đáp ứng tối thiểu 30% (hoặc 20% trong trường hợp gói thầu có công việc đặc thù hoặc ở các địa phương mà năng lực của nhà thầu trên địa bàn còn hạn chế hoặc gói thầu có khối lượng mời thầu lớn) giá trị của gói thầu đang xét (hoặc tổng giá trị của các hạng mục chính trong trường hợp gói thầu nhiều hạng mục công việc khác nhau và Chủ đầu tư yêu cầu quy mô trên cơ sở các hạng mục chính của gói thầu), trong đó từng hạng mục tương tự trong hợp đồng không cần có giá trị đáp ứng 30% (hoặc 20% trong trường hợp gói thầu có công việc đặc thù hoặc ở các địa phương mà năng lực của nhà thầu trên địa bàn còn hạn chế hoặc gói thầu có khối lượng mời thầu lớn) giá trị tương ứng của hạng mục đó trong gói thầu (hoặc giá trị tương ứng của từng hạng mục chính trong trường hợp gói thầu nhiều hạng mục công việc khác nhau và Chủ đầu tư yêu cầu quy mô trên cơ sở các hạng mục chính của gói thầu); hoặc (ii) Có các hạng mục công việc tương tự đã thực hiện trong các hợp đồng khác nhau (hợp đồng có thể đã hoàn thành hoặc đang thực hiện, chưa nghiệm thu, thanh lý) hoặc trong một hợp đồng (hợp đồng chưa hoàn thành) và bảo đảm tổng giá trị của từng hạng mục công việc tương tự đã thực hiện đáp ứng tối thiểu 30% (hoặc 20% trong trường hợp gói thầu có công việc đặc thù hoặc ở các địa phương mà năng lực của nhà thầu trên địa bàn còn hạn chế hoặc gói thầu có khối lượng mời thầu lớn) giá trị của từng hạng mục công việc tương ứng trong gói thầu đang xét (hoặc giá trị của từng hạng mục chính tương ứng trong trường hợp gói thầu nhiều hạng mục công việc khác nhau và Chủ đầu tư yêu cầu quy mô trên cơ sở các hạng mục chính của gói thầu) và tổng giá trị các hạng mục đã thực hiện phải đáp ứng tối thiểu 30% (hoặc 20% trong trường hợp gói thầu có công việc đặc thù hoặc ở các địa phương mà năng lực của nhà thầu trên địa bàn còn hạn chế hoặc gói thầu có khối lượng mời thầu lớn) giá trị của gói thầu đang xét (hoặc tổng giá trị của các hạng mục chính trong trường hợp gói thầu nhiều hạng mục công việc khác nhau và Chủ đầu tư yêu cầu quy mô trên cơ sở các hạng mục chính của gói thầu). Được cộng gộp giá trị của hạng mục tương tự trong các hợp đồng khác nhau để xác định tổng giá trị hạng mục tương tự đáp ứng yêu cầu mà không yêu cầu giá trị của hạng mục tương tự trong mỗi hợp đồng phải đáp ứng tối thiểu 30% (hoặc 20% trong trường hợp gói thầu có công việc đặc thù hoặc ở các địa phương mà năng lực của nhà thầu trên địa bàn còn hạn chế hoặc gói thầu có khối lượng mời thầu lớn) giá trị hạng mục của gói thầu đang xét (hoặc giá trị của hạng mục chính trong trường hợp gói thầu nhiều hạng mục công việc khác nhau và Chủ đầu tư yêu cầu quy mô trên cơ sở các hạng mục chính của gói thầu). Trong đó: + Hạng mục công việc đã thực hiện là một phần hoặc toàn bộ khối lượng công việc trong hạng mục đã được nghiệm thu trong khoảng thời gian quy định mà không xét đến thời gian ký kết hợp đồng. Thời điểm xác nhận hạng mục công việc đã thực hiện để xác định hạng mục công việc tương tự là thời điểm nghiệm thu công việc, không căn cứ vào thời điểm ký kết hợp đồng. + Hợp đồng hoàn thành là hợp đồng có toàn bộ công việc đã được nghiệm thu hoặc hợp đồng đã được thanh lý. Thời điểm xác nhận hợp đồng hoàn thành để xác định hợp đồng tương tự là thời điểm nghiệm thu công việc, không căn cứ vào thời điểm ký kết hợp đồng. Đối với gói thầu phi tư vấn có tính chất công việc lặp lại theo chu kỳ qua các năm dẫn đến thời gian thực hiện hợp đồng kéo dài thì giá trị hợp đồng tương tự được xác định khoảng 30% (hoặc 20% trong trường hợp gói thầu có công việc đặc thù hoặc ở các địa phương mà năng lực của nhà thầu trên địa bàn còn hạn chế hoặc gói thầu có khối lượng mời thầu lớn) giá trị của phần công việc tính theo 01 chu kỳ (01 năm) mà không tính theo tổng giá trị gói thầu qua các năm. Trong trường hợp này, việc đánh giá về quy mô, tính chất của hợp đồng tương tự cũng được xét theo 01 chu kỳ (01 năm) tương ứng. Nhà thầu trong nước thuộc trường hợp quy định tại điểm g Khoản 1 Điều 10 của Luật Đấu thầu khi chào thầu sản phẩm do nhà thầu đó sản xuất không phải đáp ứng tiêu chí này trong thời hạn 05 năm kể từ khi được cơ quan có thẩm quyền công nhận. Ví dụ 1: Gói thầu đang xét là gói thầu thuê dịch vụ dọn vệ sinh tòa nhà trong 04 năm với giá trị 8. 800. 000. 000 VNĐ thì HSYC có thể yêu cầu về giá trị của hợp đồng tương tự trong 01 chu kỳ (01 năm) là 660. 000. 000 VNĐ. Trong cả 02 trường hợp sau đây, nhà thầu X đều được đánh giá là đáp ứng yêu cầu về giá trị hợp đồng tương tự của gói thầu này: - Nhà thầu X có hợp đồng dọn vệ sinh tòa nhà trong 48 tháng với Chủ đầu tư A (đang trong quá trình thực hiện, chưa hoàn thành, chưa được thanh lý), nhưng tính đến thời điểm dự thầu, nhà thầu X đã thực hiện được 16 tháng, trong đó giá trị công việc đã được nghiệm thu 12 tháng đầu là 660. 000. 000 VNĐ; - Nhà thầu X có hợp đồng hoàn thành N1 dọn vệ sinh tòa nhà, thời gian thực hiện hợp đồng trong 06 tháng với giá trị là 300. 000. 000 VNĐ; hợp đồng N2 dọn vệ sinh tòa nhà, thời gian thực hiện hợp đồng trong 24 tháng với giá trị là 800. 000. 000 VNĐ, trong đó giá trị công việc đã được nghiệm thu 12 tháng đầu là 400. 000. 000 VNĐ. Như vậy, tổng giá trị hạng mục dọn vệ sinh tòa nhà của nhà thầu X là 700. 000. 000 VNĐ. Ví dụ 2: Gói thầu đang xét là gói thầu cung cấp dịch vụ giặt là, giá gói thầu là 10 tỷ đồng, thời gian thực hiện là 06 tháng yêu cầu hợp đồng tương tự có giá trị 30% là 03 tỷ đồng. Nhà thầu X có hợp đồng A (chưa hoàn thành, chưa được thanh lý) có giá trị công việc cung cấp dịch vụ giặt là (đã được nghiệm thu) là 02 tỷ đồng; hợp đồng B (chưa hoàn thành, chưa được thanh lý) có giá trị công việc cung cấp dịch vụ giặt là (đã được nghiệm thu) là 01 tỷ đồng thì nhà thầu X được đánh giá là đáp ứng yêu cầu về giá trị hợp đồng tương tự của gói thầu này. Ví dụ 3: Gói thầu đang xét là gói thầu cung cấp dịch vụ gồm 02 hạng mục công việc khác nhau (N1, N2) với giá gói thầu là 07 tỷ đồng (trong đó, hạng mục N1 giá trị 04 tỷ đồng; hạng mục N2 giá trị 03 tỷ đồng), thời gian thực hiện 60 ngày, yêu cầu hợp đồng tương tự có giá trị 30% là 2, 1 tỷ đồng. Trong cả 02 trường hợp sau đây, nhà thầu X đều được đánh giá là đáp ứng yêu cầu về giá trị hợp đồng tương tự của gói thầu này: - Nhà thầu X có 1 hợp đồng đã hoàn thành có đầy đủ 02 hạng mục N1, N2 và tổng giá trị 02 hạng mục N1, N2 là 2, 5 tỷ đồng. - Nhà thầu X có các hợp đồng sau: + Hợp đồng A (chưa hoàn thành, chưa được thanh lý) có giá trị công việc N1 (đã được nghiệm thu) là 0, 5 tỷ đồng; hợp đồng B (chưa hoàn thành, chưa được thanh lý) có giá trị công việc N1 (đã được nghiệm thu) là 0, 8 tỷ đồng, tổng giá trị hạng mục công việc N1 đã được nghiệm thu là 1, 3 tỷ đồng, lớn hơn yêu cầu hạng mục N1 (30% x 04 tỷ đồng). + Hợp đồng C (chưa hoàn thành, chưa được thanh lý) có giá trị công việc N2 (đã được nghiệm thu) là 0, 6 tỷ đồng; hợp đồng D (chưa hoàn thành, chưa được thanh lý) có giá trị công việc N2 (đã được nghiệm thu) là 0, 5 tỷ đồng. Như vậy, tổng giá trị hạng mục công việc N2 là 1, 1 tỷ đồng, lớn hơn yêu cầu hạng mục N2 (30% x 03 tỷ đồng). Bảng số Y BẢNG YÊU CẦU VỀ HỢP ĐỒNG TƯƠNG TỰ (Áp dụng đối với gói thầu có nhiều hạng mục dịch vụ (*)) [BẢNG: Không tiêu đề] Ghi chú: (1) Giá trị tại cột này được Chủ đầu tư xác định theo nguyên tắc nêu tại ghi chú số (10), (11) Bảng số 01 Chương này. 2. 2. Tiêu chuẩn đánh giá về nhân sự chủ chốt và thiết bị chủ yếu a) Nhân sự chủ chốt Không yêu cầu về nhân sự chủ chốt đối với gói thầu dịch vụ phi tư vấn không đòi hỏi nhân sự có chuyên môn cao, trừ trường hợp cần lao động có trình độ cao, lao động lành nghề thực hiện công việc đặc thù. Trường hợp dịch vụ phi tư vấn có yếu tố đặc thù, phức tạp cần thiết phải có nhân sự có trình độ cao, lao động lành nghề, nhiều kinh nghiệm đảm nhận thì có thể đưa ra yêu cầu về huy động nhân sự chủ chốt để thực hiện các công việc đặc thù, phức tạp này. Ngoài ra, không yêu cầu nhân sự chủ chốt là lao động phổ thông. Trường hợp HSYC có yêu cầu về nhân sự chủ chốt thì nhà thầu phải chứng minh khả năng huy động các nhân sự chủ chốt đã đề xuất. Nhân sự chủ chốt có thể thuộc biên chế của nhà thầu hoặc do nhà thầu huy động. Trường hợp nhân sự chủ chốt mà nhà thầu kê khai trong HSĐX không đáp ứng yêu cầu hoặc không chứng minh được khả năng huy động nhân sự (bao gồm cả trường hợp nhân sự đã huy động cho hợp đồng khác có thời gian làm việc trùng với thời gian thực hiện gói thầu này) thì Chủ đầu tư cho phép nhà thầu bổ sung, thay thế. Trường hợp nhà thầu không có nhân sự chủ chốt thay thế đáp ứng yêu cầu của HSYC thì nhà thầu bị loại. Trường hợp nhà thầu cố ý kê khai nhân sự chủ chốt không trung thực trong HSĐX nhằm làm sai lệch kết quả lựa chọn nhà thầu thì nhà thầu không được thay thế nhân sự khác, HSĐX của nhà thầu bị loại và nhà thầu sẽ bị coi là gian lận theo quy định tại điểm b Khoản 4 Điều 16 của Luật Đấu thầu và bị xử lý theo quy định tại Khoản 1 Điều 133 của Nghị định số 214/2025/NĐ-CP. Kinh nghiệm trong các công việc tương tự được thể hiện ở số năm tối thiểu nhân sự thực hiện các công việc tương tự hoặc số hợp đồng tối thiểu trong các công việc tương tự. Số năm kinh nghiệm của nhân sự chủ chốt được tính từ thời điểm nhân sự bắt đầu thực hiện công việc tương tự đó đến thời điểm đóng thầu. Nhà thầu phải cung cấp thông tin chi tiết về các nhân sự chủ chốt được đề xuất theo các Mẫu 07A, 07B và 07C Chương III để chứng minh rằng mình có đầy đủ nhân sự cho các vị trí chủ chốt đáp ứng những yêu cầu sau đây: Bảng số 02: Yêu cầu về nhân sự chủ chốt (1) [BẢNG: Không tiêu đề] Ghi chú: (1) Trường hợp gói thầu không có yêu cầu về nhân sự chủ chốt thì Chủ đầu tư không nhập Bảng này. (2) Chỉ quy định trong trường hợp pháp luật chuyên ngành có yêu cầu về bằng cấp/chứng chỉ chuyên môn. b) Thiết bị chủ yếu dự kiến huy động để thực hiện gói thầu Căn cứ vào quy mô, tính chất của gói thầu, Chủ đầu tư đưa ra yêu cầu về thiết bị chủ yếu dự kiến huy động và số lượng để thực hiện gói thầu cho phù hợp. Chỉ quy định về thiết bị chủ yếu đối với các thiết bị đặc chủng, đặc thù bắt buộc phải có để triển khai thực hiện gói thầu. Thiết bị chủ yếu có thể thuộc sở hữu của nhà thầu hoặc do nhà thầu huy động. Trường hợp thiết bị chủ yếu mà nhà thầu đề xuất trong HSĐX không đáp ứng yêu cầu thì Chủ đầu tư cho phép nhà thầu bổ sung, thay thế. Trường hợp nhà thầu không có thiết bị thay thế đáp ứng yêu cầu của HSYC thì nhà thầu bị loại. Trường hợp nhà thầu cố ý kê khai thiết bị chủ yếu không trung thực trong HSĐX nhằm làm sai lệch kết quả lựa chọn nhà thầu thì nhà thầu không được thay thế thiết bị khác, HSĐX của nhà thầu bị loại và nhà thầu sẽ bị coi là gian lận theo quy định tại điểm b Khoản 4 Điều 16 của Luật Đấu thầu và bị xử lý theo quy định tại Khoản 1 Điều 133 của Nghị định số 214/2025/NĐ-CP. Nhà thầu phải cung cấp thông tin chi tiết về các thiết bị chủ yếu được đề xuất theo Mẫu 07D Chương III để chứng minh rằng mình có đầy đủ thiết bị đáp ứng những yêu cầu sau đây: Bảng số 03: Yêu cầu về thiết bị chủ yếu [BẢNG: Không tiêu đề] c) Trường hợp nhà thầu trúng thầu và ký kết hợp đồng, nhà thầu có nghĩa vụ huy động nhân sự chủ chốt, thiết bị chủ yếu như đã đề xuất ban đầu hoặc đề xuất thay đổi theo quy định tại Mục này. Trường hợp không huy động được nhân sự chủ chốt, thiết bị chủ yếu, nhà thầu bị phạt hợp đồng. Mục 3. Tiêu chuẩn đánh giá về kỹ thuật Sử dụng tiêu chí đạt/không đạt để xây dựng tiêu chuẩn đánh giá về kỹ thuật. Đối với các tiêu chí đánh giá tổng quát, chỉ sử dụng tiêu chí đạt, không đạt. Đối với các tiêu chí chi tiết cơ bản trong tiêu chí tổng quát, chỉ sử dụng tiêu chí đạt, không đạt; đối với các tiêu chí chi tiết không cơ bản trong tiêu chí tổng quát, ngoài tiêu chí đạt, không đạt, được áp dụng thêm tiêu chí chấp nhận được nhưng không được vượt quá 30% tổng số các tiêu chí chi tiết trong tiêu chí tổng quát đó. Tiêu chí tổng quát được đánh giá là đạt khi tất cả các tiêu chí chi tiết cơ bản được đánh giá là đạt và các tiêu chí chi tiết không cơ bản được đánh giá là đạt hoặc chấp nhận được. Việc xây dựng tiêu chuẩn đánh giá về kỹ thuật dựa trên yêu cầu về các sản phẩm đầu ra được nêu tại Chương IV, thông tin về kết quả thực hiện hợp đồng của nhà thầu theo quy định tại Điều 19 và Điều 20 của Nghị định số 214/2025/NĐ-CP và các yêu cầu khác nêu trong HSYC. Căn cứ vào từng gói thầu cụ thể, khi lập HSYC, Chủ đầu tư phải cụ thể hóa các tiêu chí làm cơ sở đánh giá về kỹ thuật bao gồm: - Tính hiệu quả của việc cung cấp dịch vụ; - Mức độ hiểu biết về tính chất và mục đích công việc; - Tính hợp lý và khả thi của kế hoạch, các giải pháp kỹ thuật, biện pháp tổ chức cung cấp dịch vụ; - Mức độ đáp ứng hệ thống đảm bảo chất lượng và phương pháp thực hiện; - Mức độ đáp ứng các yêu cầu về tiêu chuẩn thực hiện dịch vụ; - Tiến độ thực hiện gói thầu đáp ứng yêu cầu của HSYC; - Bảo đảm điều kiện vệ sinh môi trường và các điều kiện khác như phòng cháy, chữa cháy, an toàn lao động (nếu có); - Mức độ đáp ứng các yêu cầu về bảo hành, bảo trì (nếu có); - Tiêu chí đấu thầu bền vững (nếu có): các yếu tố thân thiện môi trường (nếu có) như: việc sử dụng các vật tư, vật liệu; biện pháp tổ chức thi công; dây chuyền, kỹ thuật thi công và các yếu tố khác (nếu có); - Thông tin về kết quả thực hiện hợp đồng của nhà thầu theo quy định tại Điều 19 và Điều 20 của Nghị định số 214/2025/NĐ-CP; - Các yếu tố cần thiết khác. HSĐX được đánh giá là đáp ứng yêu cầu về kỹ thuật khi có tất cả các tiêu chí tổng quát đều được đánh giá là đạt. Mục 4. Tiêu chuẩn đánh giá về tài chính Bước 1. Xác định giá thầu; Bước 2. Sửa lỗi, hiệu chỉnh sai lệch theo quy định tại Điều 31 của Nghị định số 214/2025/NĐ-CP (nếu có); Bước 3. Xác định giá thầu sau sửa lỗi, hiệu chỉnh sai lệch (nếu có), trừ đi giá trị giảm giá (nếu có) và đáp ứng tỷ lệ tiết kiệm theo quy định tại Mục 14 Chương I. Chương III. BIỂU MẪU Mẫu 01 ĐƠN DỰ THẦU ________, ngày ____ tháng ____ năm ____ Kính gửi: __________________ [Ghi tên Chủ đầu tư] (sau đây gọi là Chủ đầu tư) Sau khi nghiên cứu hồ sơ yêu cầu và văn bản sửa đổi hồ sơ yêu cầu số ____ [Ghi số của văn bản sửa đổi, nếu có] mà chúng tôi đã nhận được, chúng tôi, ____ [Ghi tên nhà thầu], có địa chỉ tại _____ [Ghi địa chỉ của nhà thầu] cam kết thực hiện gói thầu____ [Ghi tên gói thầu] theo đúng yêu cầu của hồ sơ yêu cầu với tổng số tiền là____ [Ghi giá trị bằng số, bằng chữ và đồng tiền dự thầu] cùng với biểu giá kèm theo. Thời gian thực hiện gói thầu là ____ [Ghi thời gian thực hiện tất cả các công việc theo yêu cầu của gói thầu]. Hồ sơ đề xuất này có hiệu lực trong thời gian ____ ngày, kể từ ngày ____ tháng ____ năm ____ [Ghi ngày có thời điểm đóng thầu]. Chúng tôi cam kết: 1. Không đang trong quá trình thực hiện thủ tục giải thể hoặc bị thu hồi giấy chứng nhận đăng ký doanh nghiệp, giấy chứng nhận đăng ký hợp tác xã, liên hiệp hợp tác xã, tổ hợp tác, không thuộc trường hợp mất khả năng thanh toán theo quy định của pháp luật về phá sản (không đang trong quá trình chấm dứt hoạt động hoặc bị thu hồi giấy chứng nhận đăng ký hộ kinh doanh đối với nhà thầu là hộ kinh doanh). 2. Đã thực hiện nghĩa vụ kê khai thuế và nộp thuế của năm tài chính gần nhất so với thời điểm đóng thầu; 3. Không đang trong thời gian bị cấm dự thầu theo quy định của pháp luật đấu thầu; 4. Không đang bị truy cứu trách nhiệm hình sự (chủ hộ không đang bị truy cứu trách nhiệm hình sự trong trường hợp nhà thầu là hộ kinh doanh); 5. Trong thời hạn 03 năm trước thời điểm đóng thầu, nhà thầu không có nhân sự (ký kết hợp đồng lao động với nhà thầu tại thời điểm nhân sự thực hiện hành vi vi phạm) bị tòa án kết án có hành vi vi phạm quy định về đấu thầu gây hậu quả nghiêm trọng theo quy định của pháp luật về hình sự nhằm mục đích cho nhà thầu trúng thầu(2). 6. Không thực hiện các hành vi tham nhũng, hối lộ, thông thầu, cản trở và các hành vi vi phạm quy định khác của pháp luật đấu thầu khi tham dự gói thầu này. 7. Những thông tin kê khai trong HSĐX là trung thực. 8. Trường hợp trúng thầu, HSĐX và các văn bản bổ sung, làm rõ HSĐX tạo thành thỏa thuận ràng buộc trách nhiệm giữa hai bên cho tới khi hợp đồng được ký kết. 9. Nếu HSĐX của chúng tôi được chấp nhận, chúng tôi sẽ thực hiện biện pháp bảo đảm thực hiện hợp đồng theo quy định của HSYC. Đại diện hợp pháp của nhà thầu(1) [Ghi tên, chức danh, ký tên và đóng dấu] Ghi chú: (1) Trường hợp đại diện theo pháp luật của nhà thầu ủy quyền cho cấp dưới ký đơn dự thầu thì phải gửi kèm theo Giấy ủy quyền theo Mẫu 02 Chương này. Trường hợp tại điều lệ công ty hoặc tại các hồ sơ khác liên quan có phân công trách nhiệm cho cấp dưới ký đơn dự thầu thì phải gửi kèm theo bản chụp các văn bản, hồ sơ này (không cần lập Giấy ủy quyền theo Mẫu 02 Chương này). (2) HSYC không được yêu cầu nhà thầu phải nộp lý lịch tư pháp của nhân sự để chứng minh cho nội dung đánh giá này. Nội dung này chỉ yêu cầu nhà thầu cam kết trong Đơn này. Mẫu 02 GIẤY ỦY QUYỀN(1) Hôm nay, ngày ____ tháng ____ năm ____, tại ____ Tôi là__ [Ghi tên, số CCCD hoặc số hộ chiếu, chức danh của người đại diện theo pháp luật của nhà thầu], là người đại diện theo pháp luật của __ [Ghi tên nhà thầu] có địa chỉ tại___ [Ghi địa chỉ của nhà thầu] bằng văn bản này ủy quyền cho____ [Ghi tên, số CCCD hoặc số hộ chiếu, chức danh của người được ủy quyền] thực hiện các công việc sau đây trong quá trình dự thầu gói thầu__ [Ghi tên gói thầu] thuộc ____ [Ghi tên dự án/dự toán mua sắm] do____ [Ghi tên Chủ đầu tư] tổ chức: [- Ký đơn dự thầu; - Ký thỏa thuận liên danh (nếu có); - Ký các văn bản, hồ sơ để giao dịch với Chủ đầu tư trong quá trình dự thầu, kể cả văn bản giải trình, làm rõ HSĐX; - Tham gia quá trình thương thảo (nếu có), hoàn thiện hợp đồng; - Ký kết hợp đồng với Chủ đầu tư nếu được chỉ định thầu.] (2) Người được ủy quyền nêu trên chỉ thực hiện các công việc trong phạm vi ủy quyền với tư cách là đại diện hợp pháp của____ [Ghi tên nhà thầu]. ____ [Ghi tên nhà thầu] chịu trách nhiệm hoàn toàn về những công việc do ____ [Ghi tên người được ủy quyền] thực hiện trong phạm vi ủy quyền. Giấy ủy quyền có hiệu lực kể từ ngày ____ đến ngày ____(3). Giấy ủy quyền này được lập thành ____ bản có giá trị pháp lý như nhau, người ủy quyền giữ ____ bản, người được ủy quyền giữ ____ bản. [BẢNG: Không tiêu đề] Ghi chú: (1) Trường hợp ủy quyền thì bản gốc giấy ủy quyền phải được gửi cho Chủ đầu tư cùng với đơn dự thầu. Việc ủy quyền của người đại diện theo pháp luật của nhà thầu cho cấp phó, cấp dưới, giám đốc chi nhánh, người đứng đầu văn phòng đại diện của nhà thầu để thay mặt cho người đại diện theo pháp luật của nhà thầu thực hiện một hoặc các nội dung công việc nêu trên đây. Việc sử dụng con dấu trong trường hợp được ủy quyền có thể là dấu của nhà thầu hoặc dấu của đơn vị mà cá nhân liên quan được ủy quyền. Người được ủy quyền không được tiếp tục ủy quyền cho người khác. (2) Phạm vi ủy quyền bao gồm một hoặc nhiều công việc nêu trên. (3) Ghi ngày có hiệu lực và ngày hết hiệu lực của giấy ủy quyền phù hợp với quá trình dự thầu và phải bảo đảm có hiệu lực trước ngày thực hiện các công việc được ủy quyền. Mẫu 03 THỎA THUẬN LIÊN DANH(1), ngày tháng năm Gói thầu: ___ [Ghi tên gói thầu] Thuộc: ___ [Ghi tên dự án/dự toán mua sắm] - Căn cứ ___ [Luật Đấu thầu](2); - Căn cứ ___ (2); - Căn cứ hồ sơ yêu cầu gói thầu ____[Ghi tên gói thầu] ngày ___ tháng ____ năm ____ [Ngày được ghi trên HSYC]; Chúng tôi, đại diện cho các bên ký thỏa thuận liên danh, gồm có: Tên thành viên liên danh [Ghi tên từng thành viên liên danh] Đại diện là ông/bà: Chức vụ: Địa chỉ: Điện thoại: E-mail: Tài khoản: Mã số thuế: Giấy ủy quyền số __ ngày __tháng __ năm __ (trường hợp được ủy quyền). Các bên (sau đây gọi là thành viên) thống nhất ký kết thỏa thuận liên danh với các nội dung sau: Điều 1. Nguyên tắc chung 1. Các thành viên tự nguyện hình thành liên danh để dự thầu gói thầu [Ghi tên gói thầu] thuộc ___ [Ghi tên dự án/dự toán mua sắm]. 2. Các thành viên thống nhất tên gọi của liên danh cho mọi giao dịch liên quan đến gói thầu này là: [Ghi tên của liên danh]. 3. Các thành viên cam kết không thành viên nào có quyền từ chối thực hiện các trách nhiệm và nghĩa vụ quy định trong hợp đồng. Trường hợp thành viên của liên danh từ chối hoàn thành trách nhiệm riêng của mình như đã thỏa thuận thì thành viên đó bị xử lý như sau: - Bồi thường thiệt hại cho các bên trong liên danh - Bồi thường thiệt hại cho Chủ đầu tư theo quy định nêu trong hợp đồng - Hình thức xử lý khác [Ghi rõ hình thức xử lý khác]. Điều 2. Phân công trách nhiệm Các thành viên thống nhất chịu trách nhiệm chung, trách nhiệm riêng để thực hiện gói thầu [Ghi tên gói thầu] thuộc ___ [Ghi tên dự án/dự toán mua sắm] đối với từng thành viên như sau: 1. Thành viên đứng đầu liên danh Các bên nhất trí ủy quyền cho [Ghi tên một bên] làm thành viên đứng đầu liên danh, đại diện cho liên danh trong những phần việc sau(3): [- Ký đơn dự thầu; - Ký các văn bản, hồ sơ để giao dịch với Chủ đầu tư trong quá trình dự thầu, kể cả văn bản đề nghị làm rõ HSYC và văn bản giải trình, làm rõ HSĐX; - Tham gia quá trình thương thảo (nếu có), hoàn thiện hợp đồng; - Các công việc khác trừ việc ký kết hợp đồng [Ghi rõ nội dung các công việc khác (nếu có)]. 2. Các thành viên trong liên danh thỏa thuận phân công trách nhiệm thực hiện công việc theo bảng dưới đây(4): [BẢNG: Không tiêu đề] Điều 3. Hiệu lực của thỏa thuận liên danh 1. Thỏa thuận liên danh có hiệu lực kể từ ngày ký. 2. Thỏa thuận liên danh chấm dứt hiệu lực trong các trường hợp sau: - Các bên hoàn thành trách nhiệm và nghĩa vụ của mình và tiến hành thanh lý hợp đồng; - Các bên cùng thỏa thuận chấm dứt; - Nhà thầu liên danh không được chỉ định thầu; - Hủy thầu gói thầu [Ghi tên gói thầu] thuộc ___ [Ghi tên dự án/dự toán mua sắm] theo thông báo của Chủ đầu tư. Thỏa thuận liên danh được lập thành bản, mỗi bên giữ bản, các bản thỏa thuận có giá trị pháp lý như nhau. ĐẠI DIỆN HỢP PHÁP CỦA THÀNH VIÊN ĐỨNG ĐẦU LIÊN DANH(5) [Ghi tên, chức danh, ký tên và đóng dấu] ĐẠI DIỆN HỢP PHÁP CỦA THÀNH VIÊN LIÊN DANH [Ghi tên từng thành viên, chức danh, ký tên và đóng dấu] Ghi chú: (1) Căn cứ quy mô, tính chất của gói thầu, nội dung thỏa thuận liên danh theo mẫu này có thể được sửa đổi bổ sung cho phù hợp. (2) Cập nhật các văn bản quy phạm pháp luật theo quy định hiện hành. (3) Phạm vi ủy quyền bao gồm một hoặc nhiều công việc nêu trên. (4) Nhà thầu phải ghi rõ nội dung công việc cụ thể và ước tính giá trị tương ứng mà từng thành viên trong liên danh sẽ thực hiện, trách nhiệm chung, trách nhiệm của từng thành viên, kể cả thành viên đứng đầu liên danh. Việc phân chia công việc trong liên danh phải căn cứ các hạng mục nêu trong bảng giá thầu quy định tại Mẫu 04 (04A hoặc 04B hoặc 04C hoặc 04D hoặc 04E hoặc 04G) Chương III; không được phân chia các công việc không thuộc các hạng mục này hoặc không thuộc quá trình sản xuất các hạng mục này. (5) Đại diện hợp pháp của thành viên liên danh có thể là người đại diện theo pháp luật hoặc người được người đại diện theo pháp luật ủy quyền. Mẫu 04A BẢNG giá thầu VÀ TIẾN ĐỘ THỰC HIỆN (áp dụng đối với loại hợp đồng trọn gói, hợp đồng theo kết quả đầu ra) Chủ đầu tư liệt kê chi tiết danh mục các dịch vụ yêu cầu, mô tả ngắn gọn dịch vụ theo Bảng sau: [BẢNG: Không tiêu đề] Đại diện hợp pháp của nhà thầu [ghi tên, chức danh, ký tên và đóng dấu] Ghi chú: (2), (4), (5), (6), (7): Chủ đầu tư ghi tên các hạng mục công việc cụ thể, đơn vị tính, khối lượng, địa điểm thực hiện dịch vụ, ngày hoàn thành các nội dung công việc để nhà thầu làm cơ sở chào giá thầu. (3) Chủ đầu tư ghi dẫn chiếu cụ thể đến nội dung yêu cầu về kỹ thuật/chỉ dẫn kỹ thuật để thực hiện hạng mục công việc tương ứng trong Chương IV hoặc trong hồ sơ chỉ dẫn kỹ thuật (tên Mục, số trang, số quyển. ..) để nhà thầu thuận tiện trong việc đánh giá, nghiên cứu các yêu cầu về kỹ thuật/chỉ dẫn kỹ thuật làm cơ sở chào giá thầu. (8): Nhà thầu điền. (9), (10): Nhà thầu điền đơn giá, thành tiền cho tất cả các hạng mục công việc. Đơn giá nhà thầu chào bao gồm các chi phí cần thiết để thực hiện gói thầu, trong đó bao gồm các chi phí thuế, phí, lệ phí, chi phí dự phòng (nếu có). Khi dự thầu, nhà thầu phải chịu trách nhiệm tìm hiểu, tính toán và chào đầy đủ các loại thuế, phí, lệ phí (nếu có) theo thuế suất, mức phí, lệ phí tại thời điểm 28 ngày trước ngày có thời điểm đóng thầu theo quy định. Mẫu 04B [BẢNG: BẢNG giá thầu VÀ TIẾN ĐỘ THỰC HIỆN (áp dụng đối với loại hợp đồng theo đơn giá cố định) Chủ đầu t] Mẫu 04C [BẢNG: BẢNG giá thầu VÀ TIẾN ĐỘ THỰC HIỆN (áp dụng đối với loại hợp đồng theo đơn giá điều chỉnh) Chủ đầ] Mẫu 04D BẢNG giá thầu VÀ TIẾN ĐỘ THỰC HIỆN (áp dụng đối với loại hợp đồng theo tỷ lệ phần trăm) Chủ đầu tư liệt kê chi tiết danh mục các dịch vụ, mô tả ngắn gọn dịch vụ cung cấp theo Bảng sau: [BẢNG: Không tiêu đề] Mẫu 04E [BẢNG: BẢNG giá thầu VÀ TIẾN ĐỘ THỰC HIỆN (áp dụng đối với loại hợp đồng theo thời gian) Chủ đầu tư liệ] Mẫu 04G BẢNG giá thầu VÀ TIẾN ĐỘ THỰC HIỆN (áp dụng đối với loại hợp đồng hỗn hợp) Chủ đầu tư liệt kê chi tiết danh mục các dịch vụ yêu cầu, mô tả ngắn gọn dịch vụ yêu cầu cung cấp theo Bảng sau: I. Các hạng mục áp dụng loại hợp đồng trọn gói, hợp đồng theo kết quả đầu ra [BẢNG: Không tiêu đề] Ghi chú: (2), (4), (5), (6), (7): Chủ đầu tư ghi tên các hạng mục công việc cụ thể, đơn vị tính, khối lượng, địa điểm thực hiện dịch vụ, ngày hoàn thành các nội dung công việc để nhà thầu làm cơ sở chào giá thầu. (3) Chủ đầu tư ghi dẫn chiếu cụ thể đến nội dung yêu cầu về kỹ thuật/chỉ dẫn kỹ thuật để thực hiện hạng mục công việc tương ứng trong Chương IV hoặc trong hồ sơ chỉ dẫn kỹ thuật (tên Mục, số trang, số quyển. ..) để nhà thầu thuận tiện trong việc đánh giá, nghiên cứu các yêu cầu về kỹ thuật/chỉ dẫn kỹ thuật làm cơ sở chào giá thầu. (8): Nhà thầu điền. (9), (10): Nhà thầu điền đơn giá, thành tiền cho tất cả các hạng mục công việc. Đơn giá nhà thầu chào bao gồm các chi phí cần thiết để thực hiện gói thầu, trong đó bao gồm các chi phí thuế, phí, lệ phí, chi phí dự phòng (nếu có). Khi dự thầu, nhà thầu phải chịu trách nhiệm tìm hiểu, tính toán và chào đầy đủ các loại thuế, phí, lệ phí (nếu có) theo thuế suất, mức phí, lệ phí tại thời điểm 28 ngày trước ngày có thời điểm đóng thầu theo quy định. II. Các hạng mục áp dụng loại hợp đồng theo đơn giá cố định [BẢNG: Không tiêu đề] III. Các hạng mục áp dụng loại hợp đồng theo đơn giá điều chỉnh [BẢNG: Không tiêu đề] Ghi chú: (2), (4), (5), (6), (7) Chủ đầu tư ghi tên các hạng mục công việc cụ thể, đơn vị tính, khối lượng, địa điểm thực hiện dịch vụ, ngày hoàn thành để nhà thầu làm cơ sở chào thầu. (3) Chủ đầu tư ghi dẫn chiếu cụ thể đến nội dung yêu cầu về kỹ thuật/chỉ dẫn kỹ thuật để thực hiện hạng mục công việc tương ứng trong Chương IV hoặc trong hồ sơ chỉ dẫn kỹ thuật (tên Mục, số trang, số quyển. ..) để nhà thầu thuận tiện trong việc đánh giá, nghiên cứu các yêu cầu về kỹ thuật/chỉ dẫn kỹ thuật làm cơ sở chào giá thầu. (*) Trong HSYC phải ghi rõ tỷ lệ dự phòng cho khối lượng phát sinh và chi phí dự phòng trượt giá (b2%) làm cơ sở để nhà thầu chào thầu. Khi dự thầu, nhà thầu phải chào chi phí dự phòng cho khối lượng phát sinh và chi phí dự phòng trượt giá với giá trị bằng tỷ lệ phần trăm (%) quy định trong HSYC (b2%) nhân với chi phí của các hạng mục do nhà thầu chào (A). Chi phí dự phòng chỉ được sử dụng khi có phát sinh khối lượng công việc trong thực tế và có trượt giá. (8): Nhà thầu điền. (9), (10): Nhà thầu điền đơn giá, thành tiền cho tất cả các hạng mục công việc. Đơn giá nhà thầu chào bao gồm các chi phí cần thiết để thực hiện gói thầu, trong đó bao gồm các chi phí thuế, phí, lệ phí (nếu có). Khi dự thầu, nhà thầu phải chịu trách nhiệm tìm hiểu, tính toán và chào đầy đủ các loại thuế, phí, lệ phí (nếu có) theo thuế suất, mức phí, lệ phí tại thời điểm 28 ngày trước ngày có thời điểm đóng thầu theo quy định. IV. Các hạng mục áp dụng loại hợp đồng theo thời gian [BẢNG: Không tiêu đề] Ghi chú: (2), (4), (5), (6), (7) Chủ đầu tư ghi tên các hạng mục công việc cụ thể, khối lượng từng ngày (tháng), số ngày/tháng thực hiện, đơn vị tính, địa điểm thực hiện dịch vụ làm cơ sở để nhà thầu chào thầu (3) Chủ đầu tư ghi dẫn chiếu cụ thể đến nội dung yêu cầu về kỹ thuật/chỉ dẫn kỹ thuật để thực hiện hạng mục công việc tương ứng trong Chương IV hoặc trong hồ sơ chỉ dẫn kỹ thuật (tên Mục, số trang, số quyển. ..) để nhà thầu thuận tiện trong việc đánh giá, nghiên cứu các yêu cầu về kỹ thuật/chỉ dẫn kỹ thuật làm cơ sở chào giá thầu. (8), (9) Chủ đầu tư ghi số ngày kể từ ngày hợp đồng có hiệu lực hoặc kể từ ngày Chủ đầu tư yêu cầu thực hiện dịch vụ đối với trường hợp thực hiện dịch vụ lặp lại nhiều lần. (*)Trong HSYC phải ghi rõ tỷ lệ dự phòng cho khối lượng phát sinh theo thời gian (b3%) làm cơ sở để nhà thầu chào thầu. Khi dự thầu, nhà thầu phải chào chi phí dự phòng cho khối lượng phát sinh theo thời gian với giá trị bằng tỷ lệ phần trăm (%) quy định trong HSYC (b3%) nhân với Chi phí của các hạng mục do nhà thầu chào (A). Chi phí dự phòng chỉ được sử dụng khi có phát sinh khối lượng công việc trong thực tế. (10) Ngày bắt đầu thực hiện dịch vụ do nhà thầu đề xuất phải nằm trong khoảng thời gian yêu cầu. Nhà thầu đề xuất thời gian bắt đầu thực hiện dịch vụ sớm hơn ngày bắt đầu thực hiện dịch vụ thì không được tính ưu tiên và không bị loại, trừ trường hợp yêu cầu kỹ thuật có quy định khác. Nhà thầu đề xuất thời gian bắt đầu thực hiện dịch vụ muộn hơn khoảng thời gian này thì HSĐX của nhà thầu sẽ bị loại. (11), (12): Nhà thầu điền đơn giá theo ngày (tháng), thành tiền cho hạng mục công việc. Đơn giá nhà thầu chào bao gồm các chi phí cần thiết để thực hiện gói thầu, trong đó bao gồm các chi phí thuế, phí, lệ phí (nếu có). Khi dự thầu, nhà thầu phải chịu trách nhiệm tìm hiểu, tính toán và chào đầy đủ các loại thuế, phí, lệ phí (nếu có) theo thuế suất, mức phí, lệ phí tại thời điểm 28 ngày trước ngày có thời điểm đóng thầu theo quy định. V. Tổng hợp các hạng mục [BẢNG: Không tiêu đề] Đại diện hợp pháp của nhà thầu [ghi tên, chức danh, ký tên và đóng dấu] Mẫu 05 BẢN KÊ KHAI THÔNG TIN VỀ NHÀ THẦU (1) Ngày: _________________ Tên gói thầu: _________________ [BẢNG: Không tiêu đề] Ghi chú: (1) Đối với nhà thầu liên danh thì từng thành viên phải kê khai theo Mẫu này. Mẫu 06 [BẢNG: Không tiêu đề] Thông tin về từng hợp đồng, mỗi hợp đồng cần bảo đảm các thông tin sau đây: [BẢNG: Không tiêu đề] Nhà thầu nghiên cứu kỹ HSYC và đề xuất các hợp đồng tương tự khác nhau để bảo đảm đáp ứng yêu cầu của HSYC. Nhà thầu phải gửi kèm theo bản chụp các văn bản, hồ sơ liên quan đến các hợp đồng đó (xác nhận của Chủ đầu tư về hợp đồng thực hiện theo các nội dung liên quan trong bảng trên. ..). Ghi chú: (1) Trong trường hợp liên danh, từng thành viên trong liên danh kê khai theo Mẫu này. Trường hợp nhà thầu có nhiều hợp đồng tương tự thì kê khai từng hợp đồng theo Mẫu này. Trường hợp HSYC không yêu cầu về Kinh nghiệm cụ thể trong thực hiện hợp đồng tương tự thì bỏ qua Bảng này. (2) Nhà thầu chỉ kê khai nội dung tương tự với yêu cầu của gói thầu. (3) Trường hợp giá trị hợp đồng không tính bằng VND thì quy đổi sang VND theo tỷ giá theo quy định tại Mục 2. 1 Chương II để làm cơ sở đánh giá. Mẫu 07A BẢNG ĐỀ XUẤT NHÂN SỰ CHỦ CHỐT Nhà thầu phải kê khai những nhân sự chủ chốt theo quy định tại điểm a Mục 2. 2 Chương II và phải chứng minh khả năng sẵn sàng huy động các nhân sự này để tham gia thực hiện gói thầu. Nhân sự chủ chốt có thể thuộc biên chế của nhà thầu hoặc do nhà thầu huy động. Trường hợp nhân sự chủ chốt mà nhà thầu kê khai trong HSĐX không đáp ứng yêu cầu của HSYC (bao gồm cả trường hợp nhân sự đã huy động cho hợp đồng khác có thời gian làm việc trùng với thời gian thực hiện gói thầu này) thì Chủ đầu tư cho phép nhà thầu bổ sung, thay thế nhân sự chủ chốt để đáp ứng yêu cầu của HSYC. Trường hợp nhà thầu không có nhân sự thay thế đáp ứng yêu cầu của HSYC thì HSĐX bị loại. Trường hợp nhà thầu cố ý kê khai nhân sự chủ chốt không trung thực trong HSĐX nhằm làm sai lệch kết quả lựa chọn nhà thầu thì nhà thầu không được thay thế nhân sự khác, HSĐX của nhà thầu bị loại và nhà thầu sẽ bị coi là gian lận theo quy định tại điểm b Khoản 4 Điều 16 của Luật Đấu thầu và bị xử lý theo quy định tại Khoản 1 Điều 133 của Nghị định số 214/2025/NĐ-CP. [BẢNG: Không tiêu đề] Mẫu 07B [BẢNG: Không tiêu đề] Nhà thầu phải cung cấp tất cả các thông tin trong HSĐX theo yêu cầu tại Bảng trên. Mẫu 07C [BẢNG: BẢNG KINH NGHIỆM CHUYÊN MÔN] Liệt kê theo trình tự thời gian quá trình công tác của chuyên gia, không cần liệt kê các công việc đã làm không phù hợp hoặc không liên quan với công việc đang yêu cầu. Nhà thầu phải cung cấp tất cả các thông tin được yêu cầu. Mẫu 07D BẢNG KÊ KHAI THIẾT BỊ CHỦ YẾU Nhà thầu phải kê khai những thiết bị chủ yếu theo quy định tại điểm b Mục 2. 2 Chương II và phải chứng minh khả năng sẵn sàng huy động các thiết bị này để tham gia thực hiện gói thầu. Thiết bị chủ yếu có thể thuộc sở hữu của nhà thầu hoặc do nhà thầu huy động. Trường hợp thiết bị mà nhà thầu kê khai trong HSĐX không đáp ứng yêu cầu của HSYC thì Chủ đầu tư cho phép nhà thầu bổ sung, thay thế thiết bị để đáp ứng yêu cầu của HSYC. Trường hợp nhà thầu không có thiết bị thay thế đáp ứng yêu cầu của HSĐX thì nhà thầu bị loại. Trường hợp nhà thầu cố ý kê khai thiết bị chủ yếu không trung thực trong HSĐX nhằm làm sai lệch kết quả lựa chọn nhà thầu thì nhà thầu không được thay thế thiết bị khác, HSĐX của nhà thầu bị loại và nhà thầu sẽ bị coi là gian lận theo quy định tại điểm b Khoản 4 Điều 16 của Luật Đấu thầu và bị xử lý theo quy định tại Khoản 1 Điều 133 của Nghị định số 214/2025/NĐ-CP. [BẢNG: Không tiêu đề] Đối với các thiết bị không thuộc sở hữu của mình thì nhà thầu phải kê khai thêm các thông tin dưới đây: [BẢNG: Không tiêu đề] Mẫu 08 HỢP ĐỒNG CUNG CẤP DỊCH VỤ PHI TƯ VẤN KHÔNG HOÀN THÀNH DO LỖI CỦA NHÀ THẦU Tên nhà thầu: ________________ Ngày: ______________________ Tên thành viên của nhà thầu liên danh (nếu có): _________________ [BẢNG: Không tiêu đề] Ghi chú: (1) Nhà thầu phải kê khai chính xác, trung thực các hợp đồng cung cấp dịch vụ phi tư vấn không hoàn thành do lỗi của nhà thầu trong quá khứ. Trường hợp Chủ đầu tư phát hiện nhà thầu có hợp đồng cung cấp dịch vụ phi tư vấn không hoàn thành do lỗi của nhà thầu trong quá khứ mà không kê khai thì được coi là có hành vi gian lận và HSĐX của nhà thầu sẽ bị loại. Trường hợp nhà thầu liên danh thì từng thành viên của nhà thầu liên danh phải kê khai theo Mẫu này. Mẫu 09 TÌNH HÌNH TÀI CHÍNH CỦA NHÀ THẦU(1) Tên nhà thầu: ________________ Ngày: ______________________ [BẢNG: Không tiêu đề] Ghi chú: (1) Trường hợp nhà thầu liên danh thì từng thành viên liên danh phải kê khai theo Mẫu này. (2) Để xác định doanh thu bình quân hằng năm (không bao gồm thuế VAT), nhà thầu chia tổng doanh thu của các năm (không bao gồm thuế VAT) cho số năm dựa trên thông tin đã được cung cấp. Doanh thu hằng năm được tính bằng tổng doanh thu trong báo cáo tài chính của năm đó (chưa bao gồm thuế VAT). Doanh thu bình quân hằng năm (không bao gồm thuế VAT) = tổng doanh thu từng năm (không bao gồm thuế VAT) theo yêu cầu của HSYC/số năm. Trường hợp nhà thầu mới thành lập không đủ số năm theo yêu cầu của HSYC thì Doanh thu bình quân hằng năm (không bao gồm thuế VAT) được tính trên cơ sở số năm mà nhà thầu có số liệu tài chính. Nhà thầu phải nộp các hồ sơ như sau: Bản sao các báo cáo tài chính (các bảng cân đối kế toán bao gồm tất cả thuyết minh có liên quan, và các báo cáo kết quả kinh doanh) cho các năm như đã nêu trên, tuân thủ các điều kiện sau: 1. Phản ánh tình hình tài chính của nhà thầu hoặc thành viên liên danh (nếu là nhà thầu liên danh) mà không phải tình hình tài chính của một chủ thể liên kết như công ty mẹ liên kết với công ty con hoặc công ty liên kết với nhà thầu hoặc thành viên liên danh. 2. Các báo cáo tài chính phải hoàn chỉnh, đầy đủ nội dung theo quy định. 3. Các báo cáo tài chính phải tương ứng với các kỳ kế toán đã hoàn thành kèm theo bản chụp được chứng thực một trong các hồ sơ sau đây: - Biên bản kiểm tra quyết toán thuế; - Tờ khai tự quyết toán thuế (thuế giá trị gia tăng và thuế thu nhập doanh nghiệp) có xác nhận của cơ quan thuế về thời điểm đã nộp tờ khai; - hồ sơ chứng minh việc nhà thầu đã kê khai quyết toán thuế điện tử; - Văn bản xác nhận của cơ quan quản lý thuế (xác nhận số nộp cả năm) về việc thực hiện nghĩa vụ nộp thuế; - Báo cáo kiểm toán (nếu có); - Các hồ sơ khác. Các hồ sơ trên đây phải phù hợp với số liệu nhà thầu đã kê khai trên Hệ thống Thuế điện tử tại thời điểm đóng thầu. Mẫu 10A PHẠM VI CÔNG VIỆC SỬ DỤNG thầu phụ(1) [BẢNG: Không tiêu đề] Ghi chú: (1) Trường hợp HSYC có quy định về việc sử dụng thầu phụ thì nhà thầu kê khai theo Mẫu này. Đối với gói thầu của dự án thuộc lĩnh vực khoa học, kỹ thuật, đổi mới sáng tạo và chuyển đổi số tổ chức đấu thầu trong nước, nhà thầu trong nước được sử dụng thầu phụ là nhà thầu nước ngoài đối với phần công việc đặc thù mà nhà thầu trong nước chưa thực hiện được hoặc cần chuyển giao kỹ thuật theo quy định tại Khoản 4 Điều 11 Luật Đấu thầu. (2) Nhà thầu ghi cụ thể tên thầu phụ. Trường hợp khi dự thầu chưa xác định được cụ thể danh tính của thầu phụ thì không phải kê khai vào cột này mà chỉ kê khai vào cột “Phạm vi công việc”. Nếu nhà thầu trúng thầu thì khi huy động thầu phụ thực hiện công việc đã kê khai phải được sự chấp thuận của Chủ đầu tư. (3) Nhà thầu ghi cụ thể tên hạng mục công việc dành cho thầu phụ. (4) Nhà thầu ghi cụ thể khối lượng công việc dành cho thầu phụ. (5) Nhà thầu ghi cụ thể giá trị % công việc mà thầu phụ đảm nhận so với giá thầu nhưng không được vượt quá tỷ lệ phần trăm (%) quy định tại Mục 12. 2 Chương I. Trường hợp nhà thầu liên danh, thành viên liên danh được sử dụng thầu phụ đối với phần công việc đảm nhận theo tỷ lệ % quy định tại Mục 12. 2 Chương I. (6) Nhà thầu ghi cụ thể số hợp đồng hoặc văn bản thỏa thuận và đính kèm bản chụp được chứng thực các hồ sơ này trong HSĐX. Trường hợp khi dự thầu chưa xác định được thầu phụ thì để trống cột này. Mẫu 10B DANH SÁCH CÁC CÔNG TY CON, CÔNG TY THÀNH VIÊN ĐẢM NHẬN PHẦN CÔNG VIỆC CỦA GÓI THẦU(1) [BẢNG: Không tiêu đề] Ghi chú: (1) Trường hợp nhà thầu dự thầu là công ty mẹ (ví dụ như Tổng công ty) huy động công ty con, công ty thành viên thực hiện một phần công việc gói thầu thì phải kê khai cụ thể tại bảng này. Việc đánh giá kinh nghiệm thực hiện hợp đồng tương tự căn cứ vào giá trị, khối lượng công việc do công ty mẹ, công ty con đảm nhiệm trong gói thầu. Trường hợp nhà thầu dự thầu không phải là công ty mẹ thì không áp dụng Mẫu này. (2) Ghi cụ thể tên công ty con, công ty thành viên. (3) Ghi cụ thể phần công việc đảm nhận của công ty con, công ty thành viên. (4) Ghi cụ thể giá trị % công việc của công ty con, công ty thành viên đảm nhận so với giá thầu. Phần 2. YÊU CẦU VỀ KỸ THUẬT Chương IV. YÊU CẦU VỀ KỸ THUẬT Yêu cầu về kỹ thuật mang tính kỹ thuật thuần túy và các yêu cầu khác liên quan đến việc cung cấp dịch vụ (trừ giá). Yêu cầu về kỹ thuật phải được nêu đầy đủ, rõ ràng và cụ thể để làm cơ sở cho nhà thầu lập HSĐX. Trong yêu cầu về kỹ thuật không được đưa ra các điều kiện nhằm hạn chế sự tham gia của nhà thầu hoặc nhằm tạo lợi thế cho một hoặc một số nhà thầu gây ra sự cạnh tranh không bình đẳng. Yêu cầu về kỹ thuật bao gồm các nội dung cơ bản như sau: 1. Giới thiệu chung về dự án/dự toán mua sắm, gói thầu Mục này nêu thông tin tóm tắt về dự án/ dự toán mua sắm, gói thầu như: địa điểm thực hiện dự án/ dự toán mua sắm, quy mô của dự án/ dự toán mua sắm, yêu cầu về cung cấp dịch vụ, thời gian thực hiện và những thông tin khác tùy theo tính chất và yêu cầu của gói thầu. 2. Mục tiêu công việc Trong mục này Chủ đầu tư cần cung cấp đầy đủ, chi tiết thông tin về các dịch vụ sẽ được thực hiện để bảo đảm nhà thầu có thể lập HSĐX một cách hiệu quả, chính xác và cạnh tranh nhất có thể. 3. Yêu cầu kỹ thuật của gói thầu Mục này đưa ra các yêu cầu về kỹ thuật đối với việc cung cấp dịch vụ nhằm đảm bảo chất lượng dịch vụ đáp ứng mục tiêu ban đầu của Chủ đầu tư. Trong đó, các yêu cầu do Chủ đầu tư đưa ra cần chú trọng vào sản phẩm đầu ra như tiêu chuẩn, quy cách, thông số kỹ thuật, chất lượng. .. của dịch vụ. Chủ đầu tư cũng cần nêu các tiêu chuẩn về dịch vụ mà nhà thầu phải đáp ứng. Nhà thầu có thể áp dụng các tiêu chuẩn dịch vụ khác nhưng phải chứng minh các tiêu chuẩn này tương đương hoặc cao hơn tiêu chuẩn do Chủ đầu tư yêu cầu. Về cơ bản, Chủ đầu tư không cần nêu quy trình, phương pháp thực hiện dịch vụ cụ thể mà nhà thầu phải tuân theo. Nhà thầu được quyền đề xuất quy trình, phương pháp thực hiện mà nhà thầu thấy là thích hợp để thực hiện gói thầu. Chủ đầu tư có thể đưa ra các yêu cầu về đấu thầu bền vững để bảo đảm dịch vụ cung cấp cho gói thầu thân thiện với môi trường, xã hội (việc sử dụng các vật tư, vật liệu được chứng nhận nhãn sinh thái và tương đương; sử dụng vật liệu không nung, vật liệu bền vững, thân thiện môi trường có khả năng tái chế, tái sử dụng; hạn chế mức độ xả thải, rác thải, ô nhiễm môi trường, hạn chế lượng bê tông sử dụng trong dự án; biện pháp tổ chức thi công; dây chuyền, kỹ thuật thi công và các yếu tố khác) nhưng phải bảo đảm các quy định này là rõ ràng, không làm hạn chế nhà thầu. 4. Giải pháp và phương pháp luận Nhà thầu chuẩn bị đề xuất giải pháp, phương pháp luận tổng quát thực hiện dịch vụ theo các nội dung quy định tại Chương này, gồm các phần như sau: 1. Giải pháp và phương pháp luận; 2. Kế hoạch công tác. 5. Quy định về kiểm tra, nghiệm thu sản phẩm Mục này quy định về quy trình kiểm tra, nghiệm thu sản phẩm, trình tự giao nộp sản phẩm (nếu có). .. để phục vụ công tác thanh, quyết toán hợp đồng. Phần 3. ĐIỀU KIỆN HỢP ĐỒNG VÀ BIỂU MẪU HỢP ĐỒNG Căn cứ quy mô, tính chất, loại hợp đồng của gói thầu, Chủ đầu tư, tổ chuyên gia sử dụng các Chương VI, VII, VIII của Mẫu E-HSMT dịch vụ phi tư vấn một giai đoạn một túi hồ sơ ban hành kèm theo Thông tư số 79/2025/TT-BTC để xây dựng các Chương V. ĐIỀU KIỆN CHUNG, Chương VI. ĐIỀU KIỆN CỤ THỂ, Chương VII. BIỂU MẪU HỢP ĐỒNG cho phù hợp với quy định của Luật Đấu thầu, Nghị định số 214/2025/NĐ-CP. Trong quá trình thực hiện, trường hợp Thông tư số 79/2025/TT-BTC được sửa đổi, bổ sung hoặc thay thế thì áp dụng theo văn bản quy phạm pháp luật sửa đổi, bổ sung hoặc thay thế Thông tư số 79/2025/TT-BTC. Lưu ý: khi sử dụng cần thay đổi các thuật ngữ cho phù hợp như sau: - E-ĐKC thành ĐKC; - E-ĐKCT thành ĐKCT; - E-HSMT thành HSYC; - E-HSDT thành HSĐX. Phụ lục MỘT SỐ VÍ DỤ VỀ TIÊU CHUẨN ĐÁNH GIÁ VỀ KỸ THUẬT VÀ YÊU CẦU VỀ KỸ THUẬT DỰA TRÊN KẾT QUẢ ĐẦU RA Ví dụ 1: Yêu cầu kỹ thuật dựa trên chất lượng đầu ra gói thầu cung cấp dịch vụ vệ sinh tòa nhà [BẢNG: Không tiêu đề] Ví dụ 2: Phụ lục hợp đồng về giảm trừ thanh toán đối với gói thầu cung cấp dịch vụ hỗ trợ khách hàng [BẢNG: Không tiêu đề] Ví dụ 3: Phụ lục hợp đồng về giảm trừ thanh toán đối với gói thầu cung cấp dịch vụ quản lý hệ thống máy tính nội bộ [BẢNG: Không tiêu đề]", "type": "bill_of_quantities", "rows": []}], "parsing_metadata": {"bidding_type": null, "detected_sections": {"general_info": [], "technical_requirements": [], "evaluation_criteria": [], "contract_conditions": [], "bidding_process": [], "forms": [], "drawings": [], "bill_of_quantities": []}, "document_info": {"project_name": "/dự toán mua sắm]. 2. nguồn vốn để thực hiện gói thầu__[ghi rõ nguồn vốn đã được xác định hoặc phê d", "package_name": "dịch vụ phi tư vấn (ban hành kèm theo thông tư số 80/2025/tt-btc ngày 08 tháng 8 năm 2025 của bộ trư", "owner": "___ [ghi tên, địa chỉ chủ đầu tư] mời nhà thầu nhận hsyc gói thầu___ [ghi tên gói thầu theo kế hoạch"}, "statistics": {}}, "extraction_metadata": {"source_file": "01C. Mẫu HSYC Phi tư vấn.docx", "file_type": "bidding_document", "document_category": "goods", "extracted_at": "2025-10-30T19:54:41.203965", "file_size_bytes": 198843, "project_name": "/dự toán mua sắm].", "package_name": "DỊCH VỤ PHI TƯ VẤN", "bidding_method": "CHỈ ĐỊNH THẦU", "owner": "___ [Ghi tên, địa chỉ Chủ đầu tư] mời nhà thầu nhận HSYC gói thầu___ [Ghi tên gói thầu theo kế hoạch lựa chọn nhà thầu được duyệt] thuộc ___ [Ghi tên dự án/dự toán mua sắm]."}}
